Workbook
Name Analysis: Analysis!$B$8
Name BS: Statements!$B$57
Name CF: Statements!$B$101
Name days: Dashboard!$G$18
Name Debt: Schedule!$B$78
Name EF: Scenario!$B$51
Name IS: Statements!$B$17
Name PPE: Schedule!$B$13
Name RE: Schedule!$B$107
Name RF: Scenario!$B$13
Name tax_rate: FCFF!$E$14
Name Terminal_rate: FCFF!$E$13
Name WACC: FCFF!$E$12
Name WC: Schedule!$B$42

Sheet Dashboard
B2: Apple, Inc.
B3: Dashboard
B4: (In millions, except number of shares, which are reflected in thousands, and per-share amounts)
B7: Model Assumption | F7: Units:
B9: Company Name | G9: =B2 -> Apple, Inc.
B10: Ticker | G10: AAPL
B11: Last Historical | F11: Date | G11: =Statements!J7 -> 45961
B13: Selected Scenario | G13: Street
B15: Model Start Date | F15: Date | G15: =Statements!J7 -> 45961
B16: Model End Date | F16: Date | G16: =Statements!O7 -> 47787
B17: No. of Years Projected | F17: Years | G17: =YEARFRAC(G15,G16,1) -> 5.0004564
B18: Days in an Year | F18: Days | G18: 365
B21: Table of Contents
B22: Sl.No | C22: Particulars
B23: 1 | C23: Dashboard
B24: 2 | C24: Equity Report
B25: 3 | C25: Financials
B26: 4 | C26: Statements
B27: 5 | C27: Scenario
B28: 6 | C28: Assumptions
B29: 7 | C29: Schedule
B30: 8 | C30: Valuation | G30: Cell Reference
B31: 9 | C31: Beta
B32: 10 | C32: WACC | G32: Hardcode | H32: Caution
B33: 11 | C33: FCFF | G33: Calculation | H33: Assumptions
B34: 12 | C34: Ratio Analysis | G34: Reference | H34: Notes
B35: 13 | C35: Analysis | G35: (Except for dashboard)

Sheet Report
B2: =Dashboard!B2&" - Equity Research Report" -> Apple, Inc. - Equity Research Report
B4: Apple, Inc | C4: USA | Technology | Technology Equipment
B5: Company Overview | Q5: 24 | R5: 25 | S5: 26 | T5: 27
B6: Apple Inc. (Apple) designs, manufactures, and markets smartphones, personal computers, tablets, wearables, and and accessories and sells a | P6: Market Cap | Q6: =Statements!I47*Statements!I51 -> 93681.218 | R6: =Statements!J47*Statements!J51 -> 111935.04 | S6: =Statements!K47*Statements!K51 -> 101530.46 | T6: =Statements!L47*Statements!L51 -> 114881.8
B7: range of related services. The company’s products include iPhone (50% of FY25 revenue), Mac (8%), iPad (7%), wearables, home, and | P7: Cash | Q7: =Statements!I61 -> 29943 | R7: =Statements!J61 -> 35934 | S7: =Statements!K61 -> 50346.589 | T7: =Statements!L61 -> 39765.201
B8: accessories (9%) like AirPods, Apple TV, Apple Watch, HomePod, and an online services business (26%). | P8: Debt | Q8: =Statements!I82+Statements!I86 -> 96662 | R8: =Statements!J82+Statements!J86 -> 90678 | S8: =Statements!K82+Statements!K86 -> 78285 | T8: =Statements!L82+Statements!L86 -> 68207
P9: EV | Q9: =Q6+Q8-Q7 -> 160400.22 | R9: =R6+R8-R7 -> 166679.04 | S9: =S6+S8-S7 -> 129468.87 | T9: =T6+T8-T7 -> 143323.6
B10: Financial Summary | D10: =Statements!I7 -> 45596 | E10: =Statements!J7 -> 45961 | F10: =Statements!K7 -> 46326 | G10: =Statements!L7 -> 46691 | I10: Key Financial Data
B11: (USD 'Millions)
B12: Sales | D12: =Statements!I22 -> 391035 | E12: =Statements!J22 -> 416161 | F12: =Statements!K22 -> 443442.18 | G12: =Statements!L22 -> 473669.4 | I12: Ticker: | L12: AAPL
B13: Sales Growth (YoY %) | D13: =Scenario!I48 -> 0.020219941 | E13: =Scenario!J48 -> 0.064255118 | F13: =Scenario!K48 -> 0.065554398 | G13: =Scenario!L48 -> 0.068164943 | I13: Sector: | L13: Technology
B14: Gross Profit Margins (%) | D14: ='Ratio Analysis'!F19 -> 0.4620635 | E14: ='Ratio Analysis'!G19 -> 0.46905164 | F14: ='Ratio Analysis'!H19 -> 0.47561943 | G14: ='Ratio Analysis'!I19 -> 0.49017946 | L14: Technology Equipment
B15: EBITDA Margins (%) | D15: =Statements!I54 -> 0.34437071 | E15: =Statements!J54 -> 0.34781731 | F15: =Statements!K54 -> 0.37274545 | G15: =Statements!L54 -> 0.35715955 | I15: Rating: | L15: Overvalued
B16: EBIT Margins (%) | D16: ='Ratio Analysis'!F20 -> 0.31510223 | E16: ='Ratio Analysis'!G20 -> 0.319708 | F16: ='Ratio Analysis'!H20 -> 0.32398431 | G16: ='Ratio Analysis'!I20 -> 0.33751847
B17: Net Profit Margins (%) | D17: ='Ratio Analysis'!F22 -> 0.23971256 | E17: ='Ratio Analysis'!G22 -> 0.26915064 | F17: ='Ratio Analysis'!H22 -> 0.26561469 | G17: ='Ratio Analysis'!I22 -> 0.27829699 | I17: Market Cap (USDb): | L17: =L18*L20 -> 4009935
B18: EPS (in $) | D18: ='Ratio Analysis'!F36 -> 6.11 | E18: ='Ratio Analysis'!G36 -> 7.49 | F18: ='Ratio Analysis'!H36 -> 6.7920167 | G18: ='Ratio Analysis'!I36 -> 7.6851724 | I18: Share Price (USD): | L18: =FCFF!I11 -> 271.86
B19: EPS Growth (YoY %) | D19: ='Ratio Analysis'!F36/'Ratio Analysis'!E36-1 -> -0.0081168831 | E19: ='Ratio Analysis'!G36/'Ratio Analysis'!F36-1 -> 0.22585925 | F19: ='Ratio Analysis'!H36/'Ratio Analysis'!G36-1 -> -0.093188691 | G19: ='Ratio Analysis'!I36/'Ratio Analysis'!H36-1 -> 0.13150081 | I19: Implied Price (USD): | L19: =FCFF!I10 -> 173.91744
B20: Dividend Per Share (YoY %) | D20: ='Ratio Analysis'!F37 -> 0.99180235 | E20: ='Ratio Analysis'!G37 -> 1.0310734 | F20: ='Ratio Analysis'!H37 -> 1.087353 | G20: ='Ratio Analysis'!I37 -> 1.1331551 | I20: Volume (m.Share): | L20: =FCFF!E36 -> 14750
B21: DPS Growth (YoY %) | D21: ='Ratio Analysis'!F37/'Ratio Analysis'!E37-1 -> 0.041288695 | E21: ='Ratio Analysis'!G37/'Ratio Analysis'!F37-1 -> 0.039595595 | F21: ='Ratio Analysis'!H37/'Ratio Analysis'!G37-1 -> 0.054583576 | G21: ='Ratio Analysis'!I37/'Ratio Analysis'!H37-1 -> 0.042122526 | I21: Debt / Equity (x): | L21: =(Statements!J82+Statements!J86)/Statements!J95 -> 1.2298157
B23: Key Financial Ratios | D23: =D10 -> 45596 | E23: =E10 -> 45961 | F23: =F10 -> 46326 | G23: =G10 -> 46691 | I23: Share Price - (5M)
B24: EV/EBITDA (x) | D24: =Q9/'Ratio Analysis'!F13 -> 1.1911408 | E24: =R9/'Ratio Analysis'!G13 -> 1.1515119 | F24: =S9/'Ratio Analysis'!H13 -> 0.78327815 | G24: =T9/'Ratio Analysis'!I13 -> 0.84718862
B25: EV/Sales (x) | D25: =Q9/D12 -> 0.41019402 | E25: =R9/E12 -> 0.40051576 | F25: =S9/F12 -> 0.29196337 | G25: =T9/G12 -> 0.30258151
B26: ROE (%) | D26: ='Ratio Analysis'!F23 -> 0.60303627 | E26: ='Ratio Analysis'!G23 -> 0.73952828 | F26: ='Ratio Analysis'!H23 -> 0.78793697 | G26: ='Ratio Analysis'!I23 -> 0.88183275
B27: ROCE (%) | D27: ='Ratio Analysis'!F24 -> 0.65336077 | E27: ='Ratio Analysis'!G24 -> 0.68720624 | F27: ='Ratio Analysis'!H24 -> 0.70502544 | G27: ='Ratio Analysis'!I24 -> 0.77231532
B29: Investment Overview
B31: iPhone specification upgrades to drive premium model mix higher. We expect the launches
B32: of the ultra-thin iPhone 17 Air in 2025 and Apple's first foldable iPhone in 2026 to set new
B33: benchmarks in the smartphone market. Android manufacturers will likely follow suit,
B34: accelerating their own specification upgrades. We expect the users of iPhone to increase
B35: from 1.56B FY25 to 1.62B FY26, that’s an increase of 4% YoY.
I36: DCF - (Forecast upto year FY29)
B37: Sales growth in China fell by 4% Yoy FY25, whereas iPhone sales in Rest of Aisa Pacific increa-
B38: by 10% YoY FY25. The decline in sales growth in China was offset by higher Net sales of Mac. | I38: Terminal Value: | K38: =FCFF!I29 -> 2788331.9
I39: Enterprise Value: | K39: =FCFF!E31 -> 2523540.2
B40: Risks | I40: Add: Cash: | K40: =FCFF!E32 -> 35934
B41: Apple Inc. faces significant risks from proposed and existing tariffs, primarily due to its heavy | I41: Add: Invest. & Sec.: | K41: =FCFF!E33 -> 96486
B42: reliance on Chinese manufacturing (approx. 80–90% of iPhones), threatening annual cost | I42: Less: Debt: | K42: =FCFF!E34 -> -90678
B43: increases of $8–18 billion. Potential impacts include severe pressure on profit margins, | I43: PV of Equity: | K43: =FCFF!E35 -> 2565282.2
B44: significantly higher U.S. consumer prices for devices, and stock volatility. | I44: Shares Outstanding: | K44: =FCFF!E36 -> 14750
I45: Price per Share (USD): | L45: =FCFF!E37 -> 173.91744
B46: As of early 2026, Apple is diversifying its manufacturing, with China still producing the majority
B47: of products while India and Vietnam grow rapidly. Approximately 25% of iPhones are now
B48: manufactured in India, while China remains the primary base for iPhones, Macs, and iPads.
B49: Vietnam serves as a key hub for wearables like AirPods.

Sheet Financials->

Sheet Statements
B2: =Dashboard!B2 -> Apple, Inc.
B3: Financial statements
B4: =Dashboard!B4 -> (In millions, except number of shares, which are reflected in thousands, and per-share amounts)
B5: Active Scenario | D5: =Dashboard!G13 -> Street
B6: Historical / Projections | G6: Historicals | K6: Projections | P6: CAGR | R6: Notes
B7: Year | G7: 44865 | H7: =EDATE(G7,12) -> 45230 | I7: =EDATE(H7,12) -> 45596 | J7: =EDATE(I7,12) -> 45961 | K7: =EDATE(J7,12) -> 46326 | L7: =EDATE(K7,12) -> 46691 | M7: =EDATE(L7,12) -> 47057 | N7: =EDATE(M7,12) -> 47422 | O7: =EDATE(N7,12) -> 47787 | P7: FY 22 - FY 25 | Q7: FY 26 - FY 30
B9: <-Back to dashboard
B11: Go to -> | C11: Income statement | E11: Balance statement | G11: Cash flow statement
B13: Templete: | C13: Standard | E13: Currency: | F13: USD
B14: Period type: | C14: Annual | E14: Units: | F14: Millions
B15: Source: | C15: Company Website | E15: Decimals: | F15: Default
A17: # | B17: Income statement | G17: 44865 | H17: 45230 | I17: 45596 | J17: 45961 | K17: 46326 | L17: 46691 | M17: 47057 | N17: 47422 | O17: 47787
B19: Net sales:
B20: Products | G20: 316199 | H20: 298085 | I20: 294866 | J20: 307003 | K20: =Scenario!K21+Scenario!K27+Scenario!K32+Scenario!K37 -> 319547.85 | L20: =Scenario!L21+Scenario!L27+Scenario!L32+Scenario!L37 -> 331655.52 | M20: =Scenario!M21+Scenario!M27+Scenario!M32+Scenario!M37 -> 343035.13 | N20: =Scenario!N21+Scenario!N27+Scenario!N32+Scenario!N37 -> 353409.88 | O20: =Scenario!O21+Scenario!O27+Scenario!O32+Scenario!O37 -> 362529.28
B21: Services | G21: 78129 | H21: 85200 | I21: 96169 | J21: 109158 | K21: =Scenario!K42 -> 123894.33 | L21: =Scenario!L42 -> 142013.88 | M21: =Scenario!M42 -> 164381.06 | N21: =Scenario!N42 -> 192120.37 | O21: =Scenario!O42 -> 226702.03
B22: Total net sales | G22: =SUM(G20:G21) -> 394328 | H22: =SUM(H20:H21) -> 383285 | I22: =SUM(I20:I21) -> 391035 | J22: =SUM(J20:J21) -> 416161 | K22: =SUM(K20:K21) -> 443442.18 | L22: =SUM(L20:L21) -> 473669.4 | M22: =SUM(M20:M21) -> 507416.2 | N22: =SUM(N20:N21) -> 545530.24 | O22: =SUM(O20:O21) -> 589231.31 | P22: =_xlfn.RRI(3,G22,J22) -> 0.018125357 | Q22: =_xlfn.RRI(4,K22,O22) -> 0.073648701
B24: Cost of sales:
B25: Products | G25: 201471 | H25: 189282 | I25: 185233 | J25: 194116 | K25: =Scenario!K55 -> 203433.57 | L25: =Scenario!L55 -> 210146.88 | M25: =Scenario!M55 -> 213929.52 | N25: =Scenario!N55 -> 214571.31 | O25: =Scenario!O55 -> 211996.45
B26: Services | G26: 22075 | H26: 24855 | I26: 25119 | J26: 26844 | K26: =Scenario!K60 -> 29098.896 | L26: =Scenario!L60 -> 31339.511 | M26: =Scenario!M60 -> 34105.223 | N26: =Scenario!N60 -> 37498.693 | O26: =Scenario!O60 -> 39598.619
B27: Total cost of sales | G27: =SUM(G25:G26) -> 223546 | H27: =SUM(H25:H26) -> 214137 | I27: =SUM(I25:I26) -> 210352 | J27: =SUM(J25:J26) -> 220960 | K27: =SUM(K25:K26) -> 232532.46 | L27: =SUM(L25:L26) -> 241486.39 | M27: =SUM(M25:M26) -> 248034.74 | N27: =SUM(N25:N26) -> 252070 | O27: =SUM(O25:O26) -> 251595.07 | P27: =_xlfn.RRI(3,G27,J27) -> -0.0038709949 | Q27: =_xlfn.RRI(4,K27,O27) -> 0.019893054
B29: Gross margin | G29: =G22-G27 -> 170782 | H29: =H22-H27 -> 169148 | I29: =I22-I27 -> 180683 | J29: =J22-J27 -> 195201 | K29: =K22-K27 -> 210909.72 | L29: =L22-L27 -> 232183.01 | M29: =M22-M27 -> 259381.45 | N29: =N22-N27 -> 293460.24 | O29: =O22-O27 -> 337636.24 | P29: =_xlfn.RRI(3,G29,J29) -> 0.045554433 | Q29: =_xlfn.RRI(4,K29,O29) -> 0.12483317
B31: Operating expenses:
B32: Research and development | G32: 26251 | H32: 29915 | I32: 31370 | J32: 34550 | K32: =Scenario!K70 -> 38039.55 | L32: =Scenario!L70 -> 41634.287 | M32: =Scenario!M70 -> 45298.105 | N32: =Scenario!N70 -> 48989.9 | O32: =Scenario!O70 -> 52664.143
B33: Selling, general and administrative | G33: 25094 | H33: 24932 | I33: 26097 | J33: 27601 | K33: =Scenario!K75 -> 29201.858 | L33: =Scenario!L75 -> 30676.552 | M33: =Scenario!M75 -> 31995.644 | N33: =Scenario!N75 -> 33131.489 | O33: =Scenario!O75 -> 34059.171
B34: Total operating expenses | G34: =SUM(G32:G33) -> 51345 | H34: =SUM(H32:H33) -> 54847 | I34: =SUM(I32:I33) -> 57467 | J34: =SUM(J32:J33) -> 62151 | K34: =SUM(K32:K33) -> 67241.408 | L34: =SUM(L32:L33) -> 72310.839 | M34: =SUM(M32:M33) -> 77293.748 | N34: =SUM(N32:N33) -> 82121.389 | O34: =SUM(O32:O33) -> 86723.313 | P34: =_xlfn.RRI(3,G34,J34) -> 0.065736862 | Q34: =_xlfn.RRI(4,K34,O34) -> 0.065674971
B36: Operating income (EBIT) | G36: =G29-G34 -> 119437 | H36: =H29-H34 -> 114301 | I36: =I29-I34 -> 123216 | J36: =J29-J34 -> 133050 | K36: =K29-K34 -> 143668.31 | L36: =L29-L34 -> 159872.17 | M36: =M29-M34 -> 182087.71 | N36: =N29-N34 -> 211338.85 | O36: =O29-O34 -> 250912.93 | P36: =_xlfn.RRI(3,G36,J36) -> 0.036633718 | Q36: =_xlfn.RRI(4,K36,O36) -> 0.14958347
B38: Finance costs | G38: 0 | H38: 0 | I38: 0 | J38: 0 | K38: =-Schedule!K88+Schedule!K105 -> -3162.138 | L38: =-Schedule!L88+Schedule!L105 -> -2656.32 | M38: =-Schedule!M88+Schedule!M105 -> -2220.315 | N38: =-Schedule!N88+Schedule!N105 -> -1893.2775 | O38: =-Schedule!O88+Schedule!O105 -> -1663.62
B39: Other income/(expense), net | G39: -334 | H39: -565 | I39: 269 | J39: -321 | K39: =Assumptions!K16 -> -286.22359 | L39: =Assumptions!L16 -> -286.36345 | M39: =Assumptions!M16 -> -182.67604 | N39: =Assumptions!N16 -> -380.37365 | O39: =Assumptions!O16 -> -413.16042
B40: Income before provision for income taxes | G40: =G36+G39 -> 119103 | H40: =H36+H39 -> 113736 | I40: =I36+I39 -> 123485 | J40: =J36+J39 -> 132729 | K40: =K36+K39+K38 -> 140219.95 | L40: =L36+L39+L38 -> 156929.49 | M40: =M36+M39+M38 -> 179684.71 | N40: =N36+N39+N38 -> 209065.2 | O40: =O36+O39+O38 -> 248836.15 | P40: =_xlfn.RRI(3,G40,J40) -> 0.036766702 | Q40: =_xlfn.RRI(4,K40,O40) -> 0.1541863
B42: Provision for income taxes | G42: 19300 | H42: 16741 | I42: 29749 | J42: 20719 | K42: =Assumptions!K13 -> 22435.192 | L42: =Assumptions!L13 -> 25108.718 | M42: =Assumptions!M13 -> 28749.554 | N42: =Assumptions!N13 -> 33450.432 | O42: =Assumptions!O13 -> 39813.783
B43: Net income | G43: =G40-G42 -> 99803 | H43: =H40-H42 -> 96995 | I43: =I40-I42 -> 93736 | J43: =J40-J42 -> 112010 | K43: =K40-K42 -> 117784.76 | L43: =L40-L42 -> 131820.77 | M43: =M40-M42 -> 150935.16 | N43: =N40-N42 -> 175614.77 | O43: =O40-O42 -> 209022.36 | P43: =_xlfn.RRI(3,G43,J43) -> 0.039212592 | Q43: =_xlfn.RRI(4,K43,O43) -> 0.1541863
B45: Earnings per share:
B46: Basic | G46: 6.15 | H46: 6.16 | I46: 6.11 | J46: 7.49 | K46: =(K$43-Assumptions!K$22)/K50 -> 6.7920167 | L46: =(L$43-Assumptions!L$22)/L50 -> 7.6851724 | M46: =(M$43-Assumptions!M$22)/M50 -> 8.8954662 | N46: =(N$43-Assumptions!N$22)/N50 -> 10.461582 | O46: =(O$43-Assumptions!O$22)/O50 -> 12.584549 | P46: =_xlfn.RRI(3,G46,J46) -> 0.067912248 | Q46: =_xlfn.RRI(4,K46,O46) -> 0.16670142
B47: Diluted | G47: 6.11 | H47: 6.13 | I47: 6.08 | J47: 7.46 | K47: =(K$43-Assumptions!K$22)/K51 -> 6.7665786 | L47: =(L$43-Assumptions!L$22)/L51 -> 7.6563891 | M47: =(M$43-Assumptions!M$22)/M51 -> 8.86215 | N47: =(N$43-Assumptions!N$22)/N51 -> 10.4224 | O47: =(O$43-Assumptions!O$22)/O51 -> 12.537416 | P47: =_xlfn.RRI(3,G47,J47) -> 0.068806794 | Q47: =_xlfn.RRI(4,K47,O47) -> 0.16670142
B49: Shares used in computing earnings per share:
B50: Basic | G50: 16215.963 | H50: 15744.231 | I50: 15343.783 | J50: 14948.5 | K50: =J50 -> 14948.5 | L50: =K50 -> 14948.5 | M50: =L50 -> 14948.5 | N50: =M50 -> 14948.5 | O50: =N50 -> 14948.5
B51: Diluted | G51: 16325.819 | H51: 15812.547 | I51: 15408.095 | J51: 15004.697 | K51: =J51 -> 15004.697 | L51: =K51 -> 15004.697 | M51: =L51 -> 15004.697 | N51: =M51 -> 15004.697 | O51: =N51 -> 15004.697
B53: EBITDA | H53: =H36+Schedule!H18 -> 125820 | I53: =I36+Schedule!I18 -> 134661 | J53: =J36+Schedule!J18 -> 144748 | K53: =K22-K29-K34 -> 165291.06 | L53: =L22-L29-L34 -> 169175.55 | M53: =M22-M29-M34 -> 170740.99 | N53: =N22-N29-N34 -> 169948.61 | O53: =O22-O29-O34 -> 164871.76
B54: EBITDA Margin | H54: =H53/H22 -> 0.32826748 | I54: =I53/I22 -> 0.34437071 | J54: =J53/J22 -> 0.34781731 | K54: =K53/K22 -> 0.37274545 | L54: =L53/L22 -> 0.35715955 | M54: =M53/M22 -> 0.33649102 | N54: =N53/N22 -> 0.31152922 | O54: =O53/O22 -> 0.27980821
A57: # | B57: Balance sheet | G57: 44865 | H57: 45230 | I57: 45596 | J57: 45961 | K57: 46326 | L57: 46691 | M57: 47057 | N57: 47422 | O57: 47787
B59: ASSETS:
B60: Current assets:
B61: Cash and cash equivalents | G61: 23646 | H61: 29965 | I61: 29943 | J61: 35934 | K61: =K134 -> 50346.589 | L61: =L134 -> 39765.201 | M61: =M134 -> 35704.455 | N61: =N134 -> 36234.144 | O61: =O134 -> 39450.342
B62: Marketable securities | G62: 24658 | H62: 31590 | I62: 35228 | J62: 18763 | K62: =J62 -> 18763 | L62: =K62 -> 18763 | M62: =L62 -> 18763 | N62: =M62 -> 18763 | O62: =N62 -> 18763
B63: Accounts receivable, net | G63: 28184 | H63: 29508 | I63: 33410 | J63: 39777 | K63: =Schedule!K45 -> 42384.557 | L63: =Schedule!L45 -> 45273.698 | M63: =Schedule!M45 -> 48499.244 | N63: =Schedule!N45 -> 52142.215 | O63: =Schedule!O45 -> 56319.198
B64: Vendor non-trade receivables | G64: 32748 | H64: 31477 | I64: 32833 | J64: 33180 | K64: =Schedule!K46 -> 35355.095 | L64: =Schedule!L46 -> 37765.073 | M64: =Schedule!M46 -> 40455.664 | N64: =Schedule!N46 -> 43494.449 | O64: =Schedule!O46 -> 46978.681
B65: Inventories | G65: 4946 | H65: 6331 | I65: 7286 | J65: 5718 | K65: =Schedule!K47 -> 6092.8401 | L65: =Schedule!L47 -> 6508.1581 | M65: =Schedule!M47 -> 6971.835 | N65: =Schedule!N47 -> 7495.5172 | O65: =Schedule!O47 -> 8095.9644
B66: Other current assets | G66: 21223 | H66: 14695 | I66: 14287 | J66: 14585 | K66: =Schedule!K48 -> 15541.111 | L66: =Schedule!L48 -> 16600.47 | M66: =Schedule!M48 -> 17783.178 | N66: =Schedule!N48 -> 19118.943 | O66: =Schedule!O48 -> 20650.514
B67: Total current assets | G67: =SUM(G61:G66) -> 135405 | H67: =SUM(H61:H66) -> 143566 | I67: =SUM(I61:I66) -> 152987 | J67: =SUM(J61:J66) -> 147957 | K67: =SUM(K61:K66) -> 168483.19 | L67: =SUM(L61:L66) -> 164675.6 | M67: =SUM(M61:M66) -> 168177.38 | N67: =SUM(N61:N66) -> 177248.27 | O67: =SUM(O61:O66) -> 190257.7
B69: Non-current assets:
B70: Marketable securities | G70: 120805 | H70: 100544 | I70: 91479 | J70: 77723 | K70: =J70 -> 77723 | L70: =K70 -> 77723 | M70: =L70 -> 77723 | N70: =M70 -> 77723 | O70: =N70 -> 77723
B71: Property, plant and equipment, net | G71: 42117 | H71: 43715 | I71: 45680 | J71: 49834 | K71: =Schedule!K32 -> 53058.726 | L71: =Schedule!L32 -> 56706.28 | M71: =Schedule!M32 -> 61369.802 | N71: =Schedule!N32 -> 66038.563 | O71: =Schedule!O32 -> 71347.251
B72: Other non-current assets | G72: 54428 | H72: 64758 | I72: 74834 | J72: 83727 | K72: =Schedule!K39 -> 77552.005 | L72: =Schedule!L39 -> 87203.098 | M72: =Schedule!M39 -> 95337.252 | N72: =Schedule!N39 -> 102022.91 | O72: =Schedule!O39 -> 108107.94
B73: Total non-current assets | G73: =SUM(G70:G72) -> 217350 | H73: =SUM(H70:H72) -> 209017 | I73: =SUM(I70:I72) -> 211993 | J73: =SUM(J70:J72) -> 211284 | K73: =SUM(K70:K72) -> 208333.73 | L73: =SUM(L70:L72) -> 221632.38 | M73: =SUM(M70:M72) -> 234430.05 | N73: =SUM(N70:N72) -> 245784.48 | O73: =SUM(O70:O72) -> 257178.19
B74: Total assets | G74: =G73+G67 -> 352755 | H74: =H73+H67 -> 352583 | I74: =I73+I67 -> 364980 | J74: =J73+J67 -> 359241 | K74: =SUM(K67,K73) -> 376816.92 | L74: =SUM(L67,L73) -> 386307.98 | M74: =SUM(M67,M73) -> 402607.43 | N74: =SUM(N67,N73) -> 423032.75 | O74: =SUM(O67,O73) -> 447435.89
B76: LIABILITIES AND SHAREHOLDERS' EQUITY:
B77: Current liabilities:
B78: Accounts payable | G78: 64115 | H78: 62611 | I78: 68960 | J78: 69860 | K78: =Schedule!K51 -> 73518.818 | L78: =Schedule!L51 -> 76349.742 | M78: =Schedule!M51 -> 78420.108 | N78: =Schedule!N51 -> 79695.919 | O78: =Schedule!O51 -> 79545.763
B79: Other current liabilities | G79: 60845 | H79: 58829 | I79: 78304 | J79: 66387 | K79: =Schedule!K52 -> 69863.924 | L79: =Schedule!L52 -> 72554.113 | M79: =Schedule!M52 -> 74521.553 | N79: =Schedule!N52 -> 75733.939 | O79: =Schedule!O52 -> 75591.247
B80: Deferred revenue | G80: 7912 | H80: 8061 | I80: 8249 | J80: 9055 | K80: =Schedule!K53 -> 9306.6948 | L80: =Schedule!L53 -> 10050.37 | M80: =Schedule!M53 -> 10790.105 | N80: =Schedule!N53 -> 11623.71 | O80: =Schedule!O53 -> 12488.387
B81: Commercial paper | G81: 9982 | H81: 5985 | I81: 9967 | J81: 7979 | K81: =Schedule!K102 -> 8000 | L81: =Schedule!L102 -> 8000 | M81: =Schedule!M102 -> 8000 | N81: =Schedule!N102 -> 8000 | O81: =Schedule!O102 -> 8000
B82: Term debt | G82: 11128 | H82: 9822 | I82: 10912 | J82: 12350 | K82: =J82 -> 12350 | L82: =K82 -> 12350 | M82: =L82 -> 12350 | N82: =M82 -> 12350 | O82: =N82 -> 12350
B83: Total current liabilities | G83: =SUM(G78:G82) -> 153982 | H83: =SUM(H78:H82) -> 145308 | I83: =SUM(I78:I82) -> 176392 | J83: =SUM(J78:J82) -> 165631 | K83: =SUM(K78:K82) -> 173039.44 | L83: =SUM(L78:L82) -> 179304.22 | M83: =SUM(M78:M82) -> 184081.77 | N83: =SUM(N78:N82) -> 187403.57 | O83: =SUM(O78:O82) -> 187975.4
B85: Non-current liabilities:
B86: Term debt | G86: 98959 | H86: 95281 | I86: 85750 | J86: 78328 | K86: =Schedule!K85 -> 65935 | L86: =Schedule!L85 -> 55857 | M86: =Schedule!M85 -> 46557 | N86: =Schedule!N85 -> 41322 | O86: =Schedule!O85 -> 36350
B87: Other non-current liabilities | G87: 49142 | H87: 49848 | I87: 45888 | J87: 41549 | K87: =Schedule!K72 -> 52311.286 | L87: =Schedule!L72 -> 55088.929 | M87: =Schedule!M72 -> 57269.247 | N87: =Schedule!N72 -> 60959.202 | O87: =Schedule!O72 -> 67596.083
B88: Total non-current liabilities | G88: =SUM(G86:G87) -> 148101 | H88: =SUM(H86:H87) -> 145129 | I88: =SUM(I86:I87) -> 131638 | J88: =SUM(J86:J87) -> 119877 | K88: =SUM(K86:K87) -> 118246.29 | L88: =SUM(L86:L87) -> 110945.93 | M88: =SUM(M86:M87) -> 103826.25 | N88: =SUM(N86:N87) -> 102281.2 | O88: =SUM(O86:O87) -> 103946.08
B89: Total liabilities | G89: =G83+G88 -> 302083 | H89: =H83+H88 -> 290437 | I89: =I83+I88 -> 308030 | J89: =J83+J88 -> 285508 | K89: =SUM(K83,K88) -> 291285.72 | L89: =SUM(L83,L88) -> 290250.15 | M89: =SUM(M83,M88) -> 287908.01 | N89: =SUM(N83,N88) -> 289684.77 | O89: =SUM(O83,O88) -> 291921.48
B91: Shareholders' equity:
B92: Common stock & APIC | G92: 64849 | H92: 73812 | I92: 83276 | J92: 93568 | K92: =Schedule!K117 -> 106732.64 | L92: =Schedule!L117 -> 121019.46 | M92: =Schedule!M117 -> 136370.17 | N92: =Schedule!N117 -> 152754.65 | O92: =Schedule!O117 -> 170519.72
B93: Accumulated deficit | G93: -3068 | H93: -214 | I93: -19154 | J93: -14264 | K93: =Schedule!K113 -> -15630.443 | L93: =Schedule!L113 -> -19390.637 | M93: =Schedule!M113 -> -16099.756 | N93: =Schedule!N113 -> -13835.67 | O93: =Schedule!O113 -> -9434.3153
B94: Accumulated other comprehensive loss | G94: -11109 | H94: -11452 | I94: -7172 | J94: -5571 | K94: =J94 -> -5571 | L94: =K94 -> -5571 | M94: =L94 -> -5571 | N94: =M94 -> -5571 | O94: =N94 -> -5571
B95: Total shareholders' equity | G95: =SUM(G92:G94) -> 50672 | H95: =SUM(H92:H94) -> 62146 | I95: =SUM(I92:I94) -> 56950 | J95: =SUM(J92:J94) -> 73733 | K95: =SUM(K92:K94) -> 85531.2 | L95: =SUM(L92:L94) -> 96057.824 | M95: =SUM(M92:M94) -> 114699.42 | N95: =SUM(N92:N94) -> 133347.98 | O95: =SUM(O92:O94) -> 155514.41
B96: Total liabilities and shareholders' equity | G96: =G95+G89 -> 352755 | H96: =H95+H89 -> 352583 | I96: =I95+I89 -> 364980 | J96: =J95+J89 -> 359241 | K96: =SUM(K89,K95) -> 376816.92 | L96: =SUM(L89,L95) -> 386307.98 | M96: =SUM(M89,M95) -> 402607.43 | N96: =SUM(N89,N95) -> 423032.75 | O96: =SUM(O89,O95) -> 447435.89
B98: B.S Check | G98: =IF(G96=G74,"TRUE",G74-G96) -> TRUE | H98: =IF(H96=H74,"TRUE",H74-H96) -> TRUE | I98: =IF(I96=I74,"TRUE",I74-I96) -> TRUE | J98: =IF(J96=J74,"TRUE",J74-J96) -> TRUE | K98: =IF(K96=K74,"TRUE",K74-K96) -> TRUE | L98: =IF(L96=L74,"TRUE",L74-L96) -> 1.1641532e-10 | M98: =IF(M96=M74,"TRUE",M74-M96) -> TRUE | N98: =IF(N96=N74,"TRUE",N74-N96) -> TRUE | O98: =IF(O96=O74,"TRUE",O74-O96) -> TRUE
A101: # | B101: Cash flow statement | K101: 46326 | L101: 46691 | M101: 47057 | N101: 47422 | O101: 47787
B103: Operating activities
B104: Net Income | K104: =K43 -> 117784.76 | L104: =L43 -> 131820.77 | M104: =M43 -> 150935.16 | N104: =N43 -> 175614.77 | O104: =O43 -> 209022.36
B105: Add/Less: Non-cash items
B106: Depreciation and Ammortisation | K106: =Schedule!K18 -> 13546.4 | L106: =Schedule!L18 -> 14880.301 | M106: =Schedule!M18 -> 15799.337 | N106: =Schedule!N18 -> 17860.862 | O106: =Schedule!O18 -> 19509.955
B107: Share based compensation | K107: =Assumptions!K19 -> 13164.643 | L107: =Assumptions!L19 -> 14286.818 | M107: =Assumptions!M19 -> 15350.711 | N107: =Assumptions!N19 -> 16384.474 | O107: =Assumptions!O19 -> 17765.077
B108: Other Income/(Expenses) | K108: =-K39 -> 286.22359 | L108: =-L39 -> 286.36345 | M108: =-M39 -> 182.67604 | N108: =-N39 -> 380.37365 | O108: =-O39 -> 413.16042
B109: Finance costs | K109: =-K38 -> 3162.138 | L109: =-L38 -> 2656.32 | M109: =-M38 -> 2220.315 | N109: =-N38 -> 1893.2775 | O109: =-O38 -> 1663.62
B110: Changes in working capital
B111: Change in working capital assets | K111: =SUM(J62:J66)-SUM(K62:K66) -> -6113.6032 | L111: =SUM(K62:K66)-SUM(L62:L66) -> -6773.796 | M111: =SUM(L62:L66)-SUM(M62:M66) -> -7562.5218 | N111: =SUM(M62:M66)-SUM(N62:N66) -> -8541.2041 | O111: =SUM(N62:N66)-SUM(O62:O66) -> -9793.2329
B112: Change in working capital liabilities | K112: =SUM(K78:K80)-SUM(J78:J80) -> 7387.4366 | L112: =SUM(L78:L80)-SUM(K78:K80) -> 6264.7879 | M112: =SUM(M78:M80)-SUM(L78:L80) -> 4777.5419 | N112: =SUM(N78:N80)-SUM(M78:M80) -> 3321.8011 | O112: =SUM(O78:O80)-SUM(N78:N80) -> 571.82918
B113: Change in non-working capital liablities | K113: =K87-J87 -> 10762.286 | L113: =L87-K87 -> 2777.6427 | M113: =M87-L87 -> 2180.3183 | N113: =N87-M87 -> 3689.9544 | O113: =O87-N87 -> 6636.8811
B114: Cash flow from opearating activities | K114: =SUM(K104:K113) -> 159980.28 | L114: =SUM(L104:L113) -> 166199.2 | M114: =SUM(M104:M113) -> 183883.54 | N114: =SUM(N104:N113) -> 210604.31 | O114: =SUM(O104:O113) -> 245789.65
B116: Investing Activities
B117: Proceeds from purchase of PPE | K117: =-Schedule!K15 -> -13303.266 | L117: =-Schedule!L15 -> -14683.751 | M117: =-Schedule!M15 -> -16237.318 | N117: =-Schedule!N15 -> -18002.498 | O117: =-Schedule!O15 -> -20033.865
B118: Addition/(Disposal) of non-current assets | K118: =-Schedule!K37 -> 2707.1353 | L118: =-Schedule!L37 -> -13495.197 | M118: =-Schedule!M37 -> -12359.695 | N118: =-Schedule!N37 -> -11212.787 | O118: =-Schedule!O37 -> -10869.8
B119: Other income/(Expenses) | K119: =K39 -> -286.22359 | L119: =L39 -> -286.36345 | M119: =M39 -> -182.67604 | N119: =N39 -> -380.37365 | O119: =O39 -> -413.16042
B120: Cash flow from investing activities | K120: =SUM(K117:K119) -> -10882.354 | L120: =SUM(L117:L119) -> -28465.311 | M120: =SUM(M117:M119) -> -28779.689 | N120: =SUM(N117:N119) -> -29595.659 | O120: =SUM(O117:O119) -> -31316.825
B122: Financing Activities
B123: Issuance of Long-term debt | K123: =Schedule!K83 -> 0 | L123: =Schedule!L83 -> 0 | M123: =Schedule!M83 -> 0 | N123: =Schedule!N83 -> 0 | O123: =Schedule!O83 -> 0
B124: Repayment of Long-term debt | K124: =-Schedule!K84 -> -12393 | L124: =-Schedule!L84 -> -10078 | M124: =-Schedule!M84 -> -9300 | N124: =-Schedule!N84 -> -5235 | O124: =-Schedule!O84 -> -4972
B125: Commercial paper drawn/(Paid) | K125: =K81-J81 -> 21 | L125: =L81-K81 -> 0 | M125: =M81-L81 -> 0 | N125: =N81-M81 -> 0 | O125: =O81-N81 -> 0
B126: Payments for dividends issued | K126: =-Assumptions!K22 -> -16254.297 | L126: =-Assumptions!L22 -> -16938.969 | M126: =-Assumptions!M22 -> -17961.284 | N126: =-Assumptions!N22 -> -19229.817 | O126: =-Assumptions!O22 -> -20902.236
B127: Proceeds from share buy-back issued | K127: =-Assumptions!K25 -> -102896.9 | L127: =-Assumptions!L25 -> -118641.99 | M127: =-Assumptions!M25 -> -129682.99 | N127: =-Assumptions!N25 -> -154120.87 | O127: =-Assumptions!O25 -> -183718.77
B128: Finance costs (Fixed + Variable) | K128: =K38 -> -3162.138 | L128: =L38 -> -2656.32 | M128: =M38 -> -2220.315 | N128: =N38 -> -1893.2775 | O128: =O38 -> -1663.62
...

Sheet Scenario
B2: =Dashboard!B2 -> Apple, Inc.
B3: Scenario
B4: =Dashboard!B4 -> (In millions, except number of shares, which are reflected in thousands, and per-share amounts)
B5: Active Scenario | D5: =Dashboard!G13 -> Street
B6: Historical / Projections | G6: =Statements!G6 -> Historicals | K6: =Statements!K6 -> Projections | P6: CAGR | R6: Notes
B7: Year | G7: 44865 | H7: =EDATE(G7,12) -> 45230 | I7: =EDATE(H7,12) -> 45596 | J7: =EDATE(I7,12) -> 45961 | K7: =EDATE(J7,12) -> 46326 | L7: =EDATE(K7,12) -> 46691 | M7: =EDATE(L7,12) -> 47057 | N7: =EDATE(M7,12) -> 47422 | O7: =EDATE(N7,12) -> 47787 | P7: 22A - 25A | Q7: 26E - 30E
B9: <-Back to dashboard
B11: Go to -> | C11: Revenue forecast | E11: Expense forecast
A13: # | B13: Revenue Forecast
B15: Number of iPhone users worldwide projected
B16: (In Billions) | G16: 1.33 | H16: 1.38 | I16: 1.46 | J16: 1.56 | K16: =J16*(1+K17) -> 1.6224 | L16: =K16*(1+L17) -> 1.6808064 | M16: =L16*(1+M17) -> 1.7345922 | N16: =M16*(1+N17) -> 1.7831608 | O16: =N16*(1+O17) -> 1.8259566 | P16: =_xlfn.RRI(3,G16,J16) -> 0.054607816 | Q16: =_xlfn.RRI(4,K16,O16) -> 0.029990291
B17: yoy iPhone users growth (%) | H17: =H16/G16-1 -> 0.037593985 | I17: =I16/H16-1 -> 0.057971014 | J17: =J16/I16-1 -> 0.068493151 | K17: =K25 -> 0.04 | L17: =L25 -> 0.036 | M17: =M25 -> 0.032 | N17: =N25 -> 0.028 | O17: =O25 -> 0.024
B19: Revenue Products and Service Wise:
B21: iPhone | G21: 205489 | H21: 200583 | I21: 201183 | J21: 209586 | K21: =(K$22/$J$22)*$J$21 -> 217969.44 | L21: =(L$22/$J$22)*$J$21 -> 225816.34 | M21: =(M$22/$J$22)*$J$21 -> 233042.46 | N21: =(N$22/$J$22)*$J$21 -> 239567.65 | O21: =(O$22/$J$22)*$J$21 -> 245317.28 | S21: =J21/J$47 -> 0.50361759
B22: iPhone revenue per user | G22: =G21/(G16*100) -> 1545.0301 | H22: =H21/(H16*100) -> 1453.5 | I22: =I21/(I16*100) -> 1377.9658 | J22: =J21/(J16*100) -> 1343.5 | K22: =J22*(1+K23) -> 1397.24 | L22: =K22*(1+L23) -> 1447.5406 | M22: =L22*(1+M23) -> 1493.8619 | N22: =M22*(1+N23) -> 1535.6901 | O22: =N22*(1+O23) -> 1572.5466 | P22: =_xlfn.RRI(3,G22,J22) -> -0.045519828 | Q22: =_xlfn.RRI(4,K22,O22) -> 0.029990291
B23: yoy iPhone revenue growth per user (%) | H23: =H22/G22-1 -> -0.059241614 | I23: =I22/H22-1 -> -0.051967146 | J23: =J22/I22-1 -> -0.025012054 | K23: =OFFSET(K23,MATCH($D$5,$B24:$B26,0),0) -> 0.04 | L23: =OFFSET(L23,MATCH($D$5,$B24:$B26,0),0) -> 0.036 | M23: =OFFSET(M23,MATCH($D$5,$B24:$B26,0),0) -> 0.032 | N23: =OFFSET(N23,MATCH($D$5,$B24:$B26,0),0) -> 0.028 | O23: =OFFSET(O23,MATCH($D$5,$B24:$B26,0),0) -> 0.024
B24: Optimistic | K24: =K25+$R$24 -> 0.0595 | L24: =L25+$R$24 -> 0.0555 | M24: =M25+$R$24 -> 0.0515 | N24: =N25+$R$24 -> 0.0475 | O24: =O25+$R$24 -> 0.0435 | R24: 0.0195
B25: Street | K25: 0.04 | L25: =K25+($O$25-$K$25)/4 -> 0.036 | M25: =L25+($O$25-$K$25)/4 -> 0.032 | N25: =M25+($O$25-$K$25)/4 -> 0.028 | O25: 0.024
B26: Pessimestic | K26: =K25+$R$26 -> 0.0075 | L26: =L25+$R$26 -> 0.0035 | M26: =M25+$R$26 -> -0.0005 | N26: =N25+$R$26 -> -0.0045 | O26: =O25+$R$26 -> -0.0085 | R26: -0.0325
B27: Mac | G27: 40177 | H27: 29357 | I27: 29984 | J27: 33708 | K27: =J27*(1+K28) -> 37752.96 | L27: =K27*(1+L28) -> 41603.762 | M27: =L27*(1+M28) -> 45098.478 | N27: =M27*(1+N28) -> 48074.977 | O27: =N27*(1+O28) -> 50382.576 | P27: =_xlfn.RRI(3,G27,J27) -> -0.056840464 | Q27: =_xlfn.RRI(4,K27,O27) -> 0.07481159 | S27: =J27/J$47 -> 0.080997499
B28: yoy Mac revenue growth (%) | H28: =H27/G27-1 -> -0.26930831 | I28: =I27/H27-1 -> 0.021357768 | J28: =J27/I27-1 -> 0.12419957 | K28: =OFFSET(K28,MATCH($D$5,$B29:$B31,0),0) -> 0.12 | L28: =OFFSET(L28,MATCH($D$5,$B29:$B31,0),0) -> 0.102 | M28: =OFFSET(M28,MATCH($D$5,$B29:$B31,0),0) -> 0.084 | N28: =OFFSET(N28,MATCH($D$5,$B29:$B31,0),0) -> 0.066 | O28: =OFFSET(O28,MATCH($D$5,$B29:$B31,0),0) -> 0.048
B29: Optimistic | K29: =K30+$R$24 -> 0.1395 | L29: =L30+$R$24 -> 0.1215 | M29: =M30+$R$24 -> 0.1035 | N29: =N30+$R$24 -> 0.0855 | O29: =O30+$R$24 -> 0.0675
B30: Street | K30: 0.12 | L30: =K30+($O$30-$K$30)/4 -> 0.102 | M30: =L30+($O$30-$K$30)/4 -> 0.084 | N30: =M30+($O$30-$K$30)/4 -> 0.066 | O30: 0.048
B31: Pessimestic | K31: =K30+$R$26 -> 0.0875 | L31: =L30+$R$26 -> 0.0695 | M31: =M30+$R$26 -> 0.0515 | N31: =N30+$R$26 -> 0.0335 | O31: =O30+$R$26 -> 0.0155
B32: iPad | G32: 29292 | H32: 28300 | I32: 26694 | J32: 28023 | K32: =J32*(1+K33) -> 29424.15 | L32: =K32*(1+L33) -> 30762.949 | M32: =L32*(1+M33) -> 32024.23 | N32: =M32*(1+N33) -> 33193.114 | O32: =N32*(1+O33) -> 34255.294 | P32: =_xlfn.RRI(3,G32,J32) -> -0.014654509 | Q32: =_xlfn.RRI(4,K32,O32) -> 0.038737816 | S32: =J32/J$47 -> 0.06733692
B33: yoy iPad revenue growth (%) | H33: =H32/G32-1 -> -0.033865902 | I33: =I32/H32-1 -> -0.056749117 | J33: =J32/I32-1 -> 0.049786469 | K33: =OFFSET(K33,MATCH($D$5,$B34:$B36,0),0) -> 0.05 | L33: =OFFSET(L33,MATCH($D$5,$B34:$B36,0),0) -> 0.0455 | M33: =OFFSET(M33,MATCH($D$5,$B34:$B36,0),0) -> 0.041 | N33: =OFFSET(N33,MATCH($D$5,$B34:$B36,0),0) -> 0.0365 | O33: =OFFSET(O33,MATCH($D$5,$B34:$B36,0),0) -> 0.032
B34: Optimistic | K34: =K35+$R$24 -> 0.0695 | L34: =L35+$R$24 -> 0.065 | M34: =M35+$R$24 -> 0.0605 | N34: =N35+$R$24 -> 0.056 | O34: =O35+$R$24 -> 0.0515
B35: Street | K35: 0.05 | L35: =K35+($O$35-$K$35)/4 -> 0.0455 | M35: =L35+($O$35-$K$35)/4 -> 0.041 | N35: =M35+($O$35-$K$35)/4 -> 0.0365 | O35: 0.032
B36: Pessimestic | K36: =K35+$R$26 -> 0.0175 | L36: =L35+$R$26 -> 0.013 | M36: =M35+$R$26 -> 0.0085 | N36: =N35+$R$26 -> 0.004 | O36: =O35+$R$26 -> -0.0005
B37: Wearables, Home and Accessories | G37: 41241 | H37: 39845 | I37: 37005 | J37: 35686 | K37: =J37*(1+K38) -> 34401.304 | L37: =K37*(1+L38) -> 33472.469 | M37: =L37*(1+M38) -> 32869.964 | N37: =M37*(1+N38) -> 32574.135 | O37: =N37*(1+O38) -> 32574.135 | P37: =_xlfn.RRI(3,G37,J37) -> -0.04708047 | Q37: =_xlfn.RRI(4,K37,O37) -> -0.013551321 | S37: =J37/J$47 -> 0.085750467
B38: yoy WHA revenue growth (%) | H38: =H37/G37-1 -> -0.03384981 | I38: =I37/H37-1 -> -0.071276195 | J38: =J37/I37-1 -> -0.035643832 | K38: =OFFSET(K38,MATCH($D$5,$B39:$B41,0),0) -> -0.036 | L38: =OFFSET(L38,MATCH($D$5,$B39:$B41,0),0) -> -0.027 | M38: =OFFSET(M38,MATCH($D$5,$B39:$B41,0),0) -> -0.018 | N38: =OFFSET(N38,MATCH($D$5,$B39:$B41,0),0) -> -0.009 | O38: =OFFSET(O38,MATCH($D$5,$B39:$B41,0),0) -> 0
B39: Optimistic | K39: =K40+$R$24 -> -0.0165 | L39: =L40+$R$24 -> -0.0075 | M39: =M40+$R$24 -> 0.0015 | N39: =N40+$R$24 -> 0.0105 | O39: =O40+$R$24 -> 0.0195
B40: Street | K40: -0.036 | L40: =K40+($O$40-$K$40)/4 -> -0.027 | M40: =L40+($O$40-$K$40)/4 -> -0.018 | N40: =M40+($O$40-$K$40)/4 -> -0.009 | O40: 0
B41: Pessimestic | K41: =K40+$R$26 -> -0.0685 | L41: =L40+$R$26 -> -0.0595 | M41: =M40+$R$26 -> -0.0505 | N41: =N40+$R$26 -> -0.0415 | O41: =O40+$R$26 -> -0.0325
B42: Services | G42: 78129 | H42: 85200 | I42: 96169 | J42: 109158 | K42: =J42*(1+K43) -> 123894.33 | L42: =K42*(1+L43) -> 142013.88 | M42: =L42*(1+M43) -> 164381.06 | N42: =M42*(1+N43) -> 192120.37 | O42: =N42*(1+O43) -> 226702.03 | P42: =_xlfn.RRI(3,G42,J42) -> 0.11792955 | Q42: =_xlfn.RRI(4,K42,O42) -> 0.16305699 | S42: =J42/J$47 -> 0.26229752
B43: yoy Services revenue growth (%) | H43: =H42/G42-1 -> 0.090504166 | I43: =I42/H42-1 -> 0.12874413 | J43: =J42/I42-1 -> 0.13506431 | K43: =OFFSET(K43,MATCH($D$5,$B44:$B46,0),0) -> 0.135 | L43: =OFFSET(L43,MATCH($D$5,$B44:$B46,0),0) -> 0.14625 | M43: =OFFSET(M43,MATCH($D$5,$B44:$B46,0),0) -> 0.1575 | N43: =OFFSET(N43,MATCH($D$5,$B44:$B46,0),0) -> 0.16875 | O43: =OFFSET(O43,MATCH($D$5,$B44:$B46,0),0) -> 0.18
B44: Optimistic | K44: =K45+$R$24 -> 0.1545 | L44: =L45+$R$24 -> 0.16575 | M44: =M45+$R$24 -> 0.177 | N44: =N45+$R$24 -> 0.18825 | O44: =O45+$R$24 -> 0.1995
B45: Street | K45: 0.135 | L45: =K45+($O$45-$K$45)/4 -> 0.14625 | M45: =L45+($O$45-$K$45)/4 -> 0.1575 | N45: =M45+($O$45-$K$45)/4 -> 0.16875 | O45: 0.18
B46: Pessimestic | K46: =K45+$R$26 -> 0.1025 | L46: =L45+$R$26 -> 0.11375 | M46: =M45+$R$26 -> 0.125 | N46: =N45+$R$26 -> 0.13625 | O46: =O45+$R$26 -> 0.1475
B47: Total Revenue | G47: 394328 | H47: 383285 | I47: 391035 | J47: 416161 | K47: =K21+K27+K32+K37+K42 -> 443442.18 | L47: =L21+L27+L32+L37+L42 -> 473669.4 | M47: =M21+M27+M32+M37+M42 -> 507416.2 | N47: =N21+N27+N32+N37+N42 -> 545530.24 | O47: =O21+O27+O32+O37+O42 -> 589231.31 | P47: =_xlfn.RRI(3,G47,J47) -> 0.018125357 | Q47: =_xlfn.RRI(4,K47,O47) -> 0.073648701
B48: yoy total revenue growth (%) | H48: =H47/G47-1 -> -0.028004605 | I48: =I47/H47-1 -> 0.020219941 | J48: =J47/I47-1 -> 0.064255118 | K48: =K47/J47-1 -> 0.065554398 | L48: =L47/K47-1 -> 0.068164943 | M48: =M47/L47-1 -> 0.071245474 | N48: =N47/M47-1 -> 0.075113975 | O48: =O47/N47-1 -> 0.080107507
A51: # | B51: Expenses forecast
B53: Cost of Sales:
B55: Products | G55: =Statements!G25 -> 201471 | H55: =Statements!H25 -> 189282 | I55: =Statements!I25 -> 185233 | J55: =Statements!J25 -> 194116 | K55: =J55*(1+K56) -> 203433.57 | L55: =K55*(1+L56) -> 210146.88 | M55: =L55*(1+M56) -> 213929.52 | N55: =M55*(1+N56) -> 214571.31 | O55: =N55*(1+O56) -> 211996.45 | P55: =_xlfn.RRI(3,G55,J55) -> -0.01231999 | Q55: =_xlfn.RRI(4,K55,O55) -> 0.010360814
B56: yoy products cost growth (%) | H56: =H55/G55-1 -> -0.060500022 | I56: =I55/H55-1 -> -0.021391363 | J56: =J55/I55-1 -> 0.047955818 | K56: =OFFSET(K56,MATCH($D$5,$B57:$B59,0),0) -> 0.048 | L56: =OFFSET(L56,MATCH($D$5,$B57:$B59,0),0) -> 0.033 | M56: =OFFSET(M56,MATCH($D$5,$B57:$B59,0),0) -> 0.018 | N56: =OFFSET(N56,MATCH($D$5,$B57:$B59,0),0) -> 0.003 | O56: =OFFSET(O56,MATCH($D$5,$B57:$B59,0),0) -> -0.012
B57: Optimistic | K57: =K58+$R$24 -> 0.0675 | L57: =L58+$R$24 -> 0.0525 | M57: =M58+$R$24 -> 0.0375 | N57: =N58+$R$24 -> 0.0225 | O57: =O58+$R$24 -> 0.0075
B58: Street | K58: 0.048 | L58: =K58+($O$58-$K$58)/4 -> 0.033 | M58: =L58+($O$58-$K$58)/4 -> 0.018 | N58: =M58+($O$58-$K$58)/4 -> 0.003 | O58: -0.012
B59: Pessimestic | K59: =K58+$R$26 -> 0.0155 | L59: =L58+$R$26 -> 0.0005 | M59: =M58+$R$26 -> -0.0145 | N59: =N58+$R$26 -> -0.0295 | O59: =O58+$R$26 -> -0.0445
B60: Services | G60: =Statements!G26 -> 22075 | H60: =Statements!H26 -> 24855 | I60: =Statements!I26 -> 25119 | J60: =Statements!J26 -> 26844 | K60: =J60*(1+K61) -> 29098.896 | L60: =K60*(1+L61) -> 31339.511 | M60: =L60*(1+M61) -> 34105.223 | N60: =M60*(1+N61) -> 37498.693 | O60: =N60*(1+O61) -> 39598.619 | P60: =_xlfn.RRI(3,G60,J60) -> 0.067371263 | Q60: =_xlfn.RRI(4,K60,O60) -> 0.080067462
B61: yoy services cost growth (%) | H61: =H60/G60-1 -> 0.12593431 | I61: =I60/H60-1 -> 0.010621605 | J61: =J60/I60-1 -> 0.068673116 | K61: =OFFSET(K61,MATCH($D$5,$B62:$B64,0),0) -> 0.084 | L61: =OFFSET(L61,MATCH($D$5,$B62:$B64,0),0) -> 0.077 | M61: =OFFSET(M61,MATCH($D$5,$B62:$B64,0),0) -> 0.08825 | N61: =OFFSET(N61,MATCH($D$5,$B62:$B64,0),0) -> 0.0995 | O61: =OFFSET(O61,MATCH($D$5,$B62:$B64,0),0) -> 0.056
B62: Optimistic | K62: =K63+$R$24 -> 0.1035 | L62: =L63+$R$24 -> 0.0965 | M62: =M63+$R$24 -> 0.10775 | N62: =N63+$R$24 -> 0.119 | O62: =O63+$R$24 -> 0.0755
B63: Street | K63: 0.084 | L63: =K63+($O$63-$K$63)/4 -> 0.077 | M63: =L63+($O$45-$K$45)/4 -> 0.08825 | N63: =M63+($O$45-$K$45)/4 -> 0.0995 | O63: 0.056
B64: Pessimestic | K64: =K63+$R$26 -> 0.0515 | L64: =L63+$R$26 -> 0.0445 | M64: =M63+$R$26 -> 0.05575 | N64: =N63+$R$26 -> 0.067 | O64: =O63+$R$26 -> 0.0235
B65: Total Cost of Sales | G65: =G55+G60 -> 223546 | H65: =H55+H60 -> 214137 | I65: =I55+I60 -> 210352 | J65: =J55+J60 -> 220960 | K65: =K55+K60 -> 232532.46 | L65: =L55+L60 -> 241486.39 | M65: =M55+M60 -> 248034.74 | N65: =N55+N60 -> 252070 | O65: =O55+O60 -> 251595.07 | P65: =_xlfn.RRI(3,G65,J65) -> -0.0038709949 | Q65: =_xlfn.RRI(4,K65,O65) -> 0.019893054
B66: yoy total cost of sales growth (%) | H66: =H65/G65-1 -> -0.042089771 | I66: =I65/H65-1 -> -0.0176756 | J66: =J65/I65-1 -> 0.050429756 | K66: =K65/J65-1 -> 0.05237357 | L66: =L65/K65-1 -> 0.038506119 | M66: =M65/L65-1 -> 0.027116873 | N66: =N65/M65-1 -> 0.016268923 | O66: =O65/N65-1 -> -0.0018841152
B68: Operating expenses:
B70: Research and development | G70: =Statements!G32 -> 26251 | H70: =Statements!H32 -> 29915 | I70: =Statements!I32 -> 31370 | J70: =Statements!J32 -> 34550 | K70: =J70*(1+K71) -> 38039.55 | L70: =K70*(1+L71) -> 41634.287 | M70: =L70*(1+M71) -> 45298.105 | N70: =M70*(1+N71) -> 48989.9 | O70: =N70*(1+O71) -> 52664.143 | P70: =_xlfn.RRI(3,G70,J70) -> 0.0958911 | Q70: =_xlfn.RRI(4,K70,O70) -> 0.084725656
B71: yoy R&D expenses growth (%) | H71: =H70/G70-1 -> 0.13957564 | I71: =I70/H70-1 -> 0.048637807 | J71: =J70/I70-1 -> 0.10137074 | K71: =OFFSET(K71,MATCH($D$5,$B72:$B74,0),0) -> 0.101 | L71: =OFFSET(L71,MATCH($D$5,$B72:$B74,0),0) -> 0.0945 | M71: =OFFSET(M71,MATCH($D$5,$B72:$B74,0),0) -> 0.088 | N71: =OFFSET(N71,MATCH($D$5,$B72:$B74,0),0) -> 0.0815 | O71: =OFFSET(O71,MATCH($D$5,$B72:$B74,0),0) -> 0.075
B72: Optimistic | K72: =K73-$R$24 -> 0.0815 | L72: =L73-$R$24 -> 0.075 | M72: =M73-$R$24 -> 0.0685 | N72: =N73-$R$24 -> 0.062 | O72: =O73-$R$24 -> 0.0555
B73: Street | K73: 0.101 | L73: =K73+($O$73-$K$73)/4 -> 0.0945 | M73: =L73+($O$73-$K$73)/4 -> 0.088 | N73: =M73+($O$73-$K$73)/4 -> 0.0815 | O73: 0.075
B74: Pessimestic | K74: =K73-$R$26 -> 0.1335 | L74: =L73-$R$26 -> 0.127 | M74: =M73-$R$26 -> 0.1205 | N74: =N73-$R$26 -> 0.114 | O74: =O73-$R$26 -> 0.1075
B75: Selling, general and administrative | G75: =Statements!G33 -> 25094 | H75: =Statements!H33 -> 24932 | I75: =Statements!I33 -> 26097 | J75: =Statements!J33 -> 27601 | K75: =J75*(1+K76) -> 29201.858 | L75: =K75*(1+L76) -> 30676.552 | M75: =L75*(1+M76) -> 31995.644 | N75: =M75*(1+N76) -> 33131.489 | O75: =N75*(1+O76) -> 34059.171 | P75: =_xlfn.RRI(3,G75,J75) -> 0.032250197 | Q75: =_xlfn.RRI(4,K75,O75) -> 0.03921617
B76: yoy SG&A expenses growth (%) | H76: =H75/G75-1 -> -0.0064557265 | I76: =I75/H75-1 -> 0.046727098 | J76: =J75/I75-1 -> 0.057631145 | K76: =OFFSET(K76,MATCH($D$5,$B77:$B79,0),0) -> 0.058 | L76: =OFFSET(L76,MATCH($D$5,$B77:$B79,0),0) -> 0.0505 | M76: =OFFSET(M76,MATCH($D$5,$B77:$B79,0),0) -> 0.043 | N76: =OFFSET(N76,MATCH($D$5,$B77:$B79,0),0) -> 0.0355 | O76: =OFFSET(O76,MATCH($D$5,$B77:$B79,0),0) -> 0.028
B77: Optimistic | K77: =K78-$R$24 -> 0.0385 | L77: =L78-$R$24 -> 0.031 | M77: =M78-$R$24 -> 0.0235 | N77: =N78-$R$24 -> 0.016 | O77: =O78-$R$24 -> 0.0085
B78: Street | K78: 0.058 | L78: =K78+($O$78-$K$78)/4 -> 0.0505 | M78: =L78+($O$78-$K$78)/4 -> 0.043 | N78: =M78+($O$78-$K$78)/4 -> 0.0355 | O78: 0.028
B79: Pessimestic | K79: =K78-$R$26 -> 0.0905 | L79: =L78-$R$26 -> 0.083 | M79: =M78-$R$26 -> 0.0755 | N79: =N78-$R$26 -> 0.068 | O79: =O78-$R$26 -> 0.0605
B80: Total operating expenses | G80: =G70+G75 -> 51345 | H80: =H70+H75 -> 54847 | I80: =I70+I75 -> 57467 | J80: =J70+J75 -> 62151 | K80: =K70+K75 -> 67241.408 | L80: =L70+L75 -> 72310.839 | M80: =M70+M75 -> 77293.748 | N80: =N70+N75 -> 82121.389 | O80: =O70+O75 -> 86723.313 | P80: =_xlfn.RRI(3,G80,J80) -> 0.065736862 | Q80: =_xlfn.RRI(4,K80,O80) -> 0.065674971
B81: yoy total operating expense growth (%) | H81: =H80/G80-1 -> 0.068205278 | I81: =I80/H80-1 -> 0.047769249 | J81: =J80/I80-1 -> 0.081507648 | K81: =K80/J80-1 -> 0.081903879 | L81: =L80/K80-1 -> 0.07539151 | M81: =M80/L80-1 -> 0.068909573 | N81: =N80/M80-1 -> 0.062458362 | O81: =O80/N80-1 -> 0.056038071
B84: <- Go back to the top

Sheet Assumptions
B2: =Dashboard!B2 -> Apple, Inc.
B3: Assumptions
B4: =Dashboard!B4 -> (In millions, except number of shares, which are reflected in thousands, and per-share amounts)
B5: Active Scenario | D5: =Dashboard!G13 -> Street
B6: Historical / Projections | G6: =Statements!G6 -> Historicals | K6: =Statements!K6 -> Projections | P6: CAGR | R6: Notes
B7: Year | G7: 44865 | H7: =EDATE(G7,12) -> 45230 | I7: =EDATE(H7,12) -> 45596 | J7: =EDATE(I7,12) -> 45961 | K7: =EDATE(J7,12) -> 46326 | L7: =EDATE(K7,12) -> 46691 | M7: =EDATE(L7,12) -> 47057 | N7: =EDATE(M7,12) -> 47422 | O7: =EDATE(N7,12) -> 47787 | P7: 22A - 25A | Q7: 26E - 30E
B9: <-Back to dashboard
A11: # | B11: Assumptions
B13: Income taxes | G13: =Statements!G42 -> 19300 | H13: =Statements!H42 -> 16741 | I13: =Statements!I42 -> 29749 | J13: =Statements!J42 -> 20719 | K13: =K14*Statements!K40 -> 22435.192 | L13: =L14*Statements!L40 -> 25108.718 | M13: =M14*Statements!M40 -> 28749.554 | N13: =N14*Statements!N40 -> 33450.432 | O13: =O14*Statements!O40 -> 39813.783 | P13: =_xlfn.RRI(3,G13,J13) -> 0.023930533 | Q13: =_xlfn.RRI(4,K13,O13) -> 0.1541863
B14: Income taxes as a % of PBT | G14: =G13/Statements!G40 -> 0.16204462 | H14: =H13/Statements!H40 -> 0.14719174 | I14: =I13/Statements!I40 -> 0.24091185 | J14: =J13/Statements!J40 -> 0.15610002 | K14: 0.16 | L14: 0.16 | M14: 0.16 | N14: 0.16 | O14: 0.16
B16: Other Income / (Expenses) | G16: =Statements!G39 -> -334 | H16: =Statements!H39 -> -565 | I16: =Statements!I39 -> 269 | J16: =Statements!J39 -> -321 | K16: =Statements!K36*Assumptions!K17 -> -286.22359 | L16: =Statements!L36*Assumptions!L17 -> -286.36345 | M16: =Statements!M36*Assumptions!M17 -> -182.67604 | N16: =Statements!N36*Assumptions!N17 -> -380.37365 | O16: =Statements!O36*Assumptions!O17 -> -413.16042 | P16: =_xlfn.RRI(3,G16,J16) -> -0.013146115 | Q16: =_xlfn.RRI(4,K16,O16) -> 0.096107933
B17: Others as a % of EBIT | G17: =G16/Statements!G36 -> -0.0027964534 | H17: =H16/Statements!H36 -> -0.0049430889 | I17: =I16/Statements!I36 -> 0.002183158 | J17: =J16/Statements!J36 -> -0.0024126268 | K17: =AVERAGE(G17:J17) -> -0.0019922528 | L17: =AVERAGE(H17:K17) -> -0.0017912026 | M17: =AVERAGE(I17:L17) -> -0.001003231 | N17: =AVERAGE(J17:M17) -> -0.0017998283 | O17: =AVERAGE(K17:N17) -> -0.0016466287
B19: Share based compensation | H19: 10833 | I19: 11688 | J19: 12863 | K19: =K20*Statements!K22 -> 13164.643 | L19: =L20*Statements!L22 -> 14286.818 | M19: =M20*Statements!M22 -> 15350.711 | N19: =N20*Statements!N22 -> 16384.474 | O19: =O20*Statements!O22 -> 17765.077 | Q19: =_xlfn.RRI(4,K19,O19) -> 0.077803282
B20: Share based compensation as a % of revenue | H20: =H19/Statements!H22 -> 0.028263564 | I20: =I19/Statements!I22 -> 0.029889908 | J20: =J19/Statements!J22 -> 0.030908711 | K20: =AVERAGE(H20:J20) -> 0.029687394 | L20: =AVERAGE(I20:K20) -> 0.030162004 | M20: =AVERAGE(J20:L20) -> 0.030252703 | N20: =AVERAGE(K20:M20) -> 0.030034034 | O20: =AVERAGE(L20:N20) -> 0.03014958
B22: Dividends Paid | H22: 14996 | I22: 15218 | J22: 15413 | K22: =K23*Statements!K$43 -> 16254.297 | L22: =L23*Statements!L$43 -> 16938.969 | M22: =M23*Statements!M$43 -> 17961.284 | N22: =N23*Statements!N$43 -> 19229.817 | O22: =O23*Statements!O$43 -> 20902.236 | Q22: =_xlfn.RRI(4,K22,O22) -> 0.064893418
B23: Dividends paid as a % of Net income | H23: =H22/Statements!H$43 -> 0.15460591 | I23: =I22/Statements!I$43 -> 0.16234958 | J23: =J22/Statements!J$43 -> 0.13760379 | K23: 0.138 | L23: =K23+($O$23-$K$23)/4 -> 0.1285 | M23: =L23+($O$23-$K$23)/4 -> 0.119 | N23: =M23+($O$23-$K$23)/4 -> 0.1095 | O23: 0.1
B25: Share Buy-back | H25: 77046 | I25: 95846 | J25: 90052 | K25: =K26*Statements!K$43 -> 102896.9 | L25: =L26*Statements!L$43 -> 118641.99 | M25: =M26*Statements!M$43 -> 129682.99 | N25: =N26*Statements!N$43 -> 154120.87 | O25: =O26*Statements!O$43 -> 183718.77 | Q25: =_xlfn.RRI(4,K25,O25) -> 0.15594669
B26: Share Buy-back as a % of Net income | H26: =H25/Statements!H$43 -> 0.7943296 | I26: =I25/Statements!I$43 -> 1.02251 | J26: =J25/Statements!J$43 -> 0.80396393 | K26: =AVERAGE(H26:J26) -> 0.87360119 | L26: =AVERAGE(I26:K26) -> 0.90002505 | M26: =AVERAGE(J26:L26) -> 0.85919672 | N26: =AVERAGE(K26:M26) -> 0.87760765 | O26: =AVERAGE(L26:N26) -> 0.87894314

Sheet Schedule
B2: =Dashboard!B2 -> Apple, Inc.
B3: Schedule
B4: =Dashboard!B4 -> (In millions, except number of shares, which are reflected in thousands, and per-share amounts)
B5: Active Scenario | D5: =Dashboard!G13 -> Street
B6: Historical / Projections | G6: =Statements!G6 -> Historicals | K6: =Statements!G6 -> Historicals
B7: Year | G7: 44865 | H7: =EDATE(G7,12) -> 45230 | I7: =EDATE(H7,12) -> 45596 | J7: =EDATE(I7,12) -> 45961 | K7: =EDATE(J7,12) -> 46326 | L7: =EDATE(K7,12) -> 46691 | M7: =EDATE(L7,12) -> 47057 | N7: =EDATE(M7,12) -> 47422 | O7: =EDATE(N7,12) -> 47787
B9: <-Back to dashboard
B11: Go to -> | C11: PPE and intangibles | E11: Working capital | G11: Debt schedule | H11: Equity schedule
A13: # | B13: Property, plant, and equipment and Intangible schedule
B15: CapEx on PPE and intangibles | H15: 10959 | I15: 9447 | J15: 12715 | K15: =K16*Statements!K22 -> 13303.266 | L15: =L16*Statements!L22 -> 14683.751 | M15: =M16*Statements!M22 -> 16237.318 | N15: =N16*Statements!N22 -> 18002.498 | O15: =O16*Statements!O22 -> 20033.865
B16: CapEx as a % of revenue | H16: =H15/Statements!H22 -> 0.028592301 | I16: =I15/Statements!I22 -> 0.024158963 | J16: =J15/Statements!J22 -> 0.030553079 | K16: 0.03 | L16: =K16+($O$16-$K$16)/4 -> 0.031 | M16: =L16+($O$16-$K$16)/4 -> 0.032 | N16: =M16+($O$16-$K$16)/4 -> 0.033 | O16: 0.034
B18: Depreciation and Amortisation | H18: 11519 | I18: 11445 | J18: 11698 | K18: =K20+K24 -> 13546.4 | L18: =L20+L24 -> 14880.301 | M18: =M20+M24 -> 15799.337 | N18: =N20+N24 -> 17860.862 | O18: =O20+O24 -> 19509.955
B20: Depreciation and Ammortisation related to NCA | H20: =H18-H24 -> 3019 | I20: =I18-I24 -> 3245 | J20: =J18-J24 -> 3698 | K20: =K21*K22 -> 3467.8599 | L20: =L21*L22 -> 3844.1035 | M20: =M21*M22 -> 4225.5414 | N20: =N21*N22 -> 4527.124 | O20: =O21*O22 -> 4784.779
B21: Other non-current assets | H21: =Statements!H72 -> 64758 | I21: =Statements!I72 -> 74834 | J21: =Statements!J72 -> 83727 | K21: =K71 -> 77552.005 | L21: =L71 -> 87203.098 | M21: =M71 -> 95337.252 | N21: =N71 -> 102022.91 | O21: =O71 -> 108107.94
B22: Dep and Ammort related to NCA as a % of NCA | H22: =H20/H21 -> 0.046619723 | I22: =I20/I21 -> 0.043362643 | J22: =J20/J21 -> 0.044167353 | K22: =AVERAGE(H22:J22) -> 0.044716573 | L22: =AVERAGE(I22:K22) -> 0.04408219 | M22: =AVERAGE(J22:L22) -> 0.044322039 | N22: =AVERAGE(K22:M22) -> 0.0443736 | O22: =AVERAGE(L22:N22) -> 0.044259276
B24: Depreciation on PPE | H24: 8500 | I24: 8200 | J24: 8000 | K24: =K25*K15 -> 10078.54 | L24: =L25*L15 -> 11036.197 | M24: =M25*M15 -> 11573.796 | N24: =N25*N15 -> 13333.738 | O24: =O25*O15 -> 14725.176
B25: Depreciation as a % of CapEx | H25: =H24/H15 -> 0.77561821 | I25: =I24/I15 -> 0.86800042 | J25: =J24/J15 -> 0.62917814 | K25: =AVERAGE(H25:J25) -> 0.75759892 | L25: =AVERAGE(I25:K25) -> 0.75159249 | M25: =AVERAGE(J25:L25) -> 0.71278985 | N25: =AVERAGE(K25:M25) -> 0.74066042 | O25: =AVERAGE(L25:N25) -> 0.73501426
B27: Property, plant and equipment
B29: Opening balance of Net PPE | I29: =H32 -> 43715 | J29: =I32 -> 45680 | K29: =J32 -> 49834 | L29: =K32 -> 53058.726 | M29: =L32 -> 56706.28 | N29: =M32 -> 61369.802 | O29: =N32 -> 66038.563
B30: Additions to PPE | K30: =K15 -> 13303.266 | L30: =L15 -> 14683.751 | M30: =M15 -> 16237.318 | N30: =N15 -> 18002.498 | O30: =O15 -> 20033.865
B31: Less: Depreciation on PPE | K31: =-K24 -> -10078.54 | L31: =-L24 -> -11036.197 | M31: =-M24 -> -11573.796 | N31: =-N24 -> -13333.738 | O31: =-O24 -> -14725.176
B32: Closing balance of Net PPE block | H32: =Statements!H71 -> 43715 | I32: =Statements!I71 -> 45680 | J32: =Statements!J71 -> 49834 | K32: =SUM(K29:K31) -> 53058.726 | L32: =SUM(L29:L31) -> 56706.28 | M32: =SUM(M29:M31) -> 61369.802 | N32: =SUM(N29:N31) -> 66038.563 | O32: =SUM(O29:O31) -> 71347.251
B34: Other non-current assets
B36: Opening balance of NCA | K36: =J21 -> 83727 | L36: =K39 -> 77552.005 | M36: =L39 -> 87203.098 | N36: =M39 -> 95337.252 | O36: =N39 -> 102022.91
B37: Additions/ (Disposal) to NCA | K37: =K39-K36-K38 -> -2707.1353 | L37: =L39-L36-L38 -> 13495.197 | M37: =M39-M36-M38 -> 12359.695 | N37: =N39-N36-N38 -> 11212.787 | O37: =O39-O36-O38 -> 10869.8
B38: Less: Depreciation related to NCA | K38: =-K20 -> -3467.8599 | L38: =-L20 -> -3844.1035 | M38: =-M20 -> -4225.5414 | N38: =-N20 -> -4527.124 | O38: =-O20 -> -4784.779
B39: Closing balance of NCA (net) | K39: =K21 -> 77552.005 | L39: =L21 -> 87203.098 | M39: =M21 -> 95337.252 | N39: =N21 -> 102022.91 | O39: =O21 -> 108107.94
A42: # | B42: Working capital schedule
B44: Current assets
B45: Accounts receivable, net | G45: =Statements!G63 -> 28184 | H45: =Statements!H63 -> 29508 | I45: =Statements!I63 -> 33410 | J45: =Statements!J63 -> 39777 | K45: =K61*Statements!K$22/days -> 42384.557 | L45: =L61*Statements!L$22/days -> 45273.698 | M45: =M61*Statements!M$22/days -> 48499.244 | N45: =N61*Statements!N$22/days -> 52142.215 | O45: =O61*Statements!O$22/days -> 56319.198
B46: Vendor non-trade receivables | G46: =Statements!G64 -> 32748 | H46: =Statements!H64 -> 31477 | I46: =Statements!I64 -> 32833 | J46: =Statements!J64 -> 33180 | K46: =K62*Statements!K$22/days -> 35355.095 | L46: =L62*Statements!L$22/days -> 37765.073 | M46: =M62*Statements!M$22/days -> 40455.664 | N46: =N62*Statements!N$22/days -> 43494.449 | O46: =O62*Statements!O$22/days -> 46978.681
B47: Inventories | G47: =Statements!G65 -> 4946 | H47: =Statements!H65 -> 6331 | I47: =Statements!I65 -> 7286 | J47: =Statements!J65 -> 5718 | K47: =K63*Statements!K$22/days -> 6092.8401 | L47: =L63*Statements!L$22/days -> 6508.1581 | M47: =M63*Statements!M$22/days -> 6971.835 | N47: =N63*Statements!N$22/days -> 7495.5172 | O47: =O63*Statements!O$22/days -> 8095.9644
B48: Other current assets | G48: =Statements!G66 -> 21223 | H48: =Statements!H66 -> 14695 | I48: =Statements!I66 -> 14287 | J48: =Statements!J66 -> 14585 | K48: =K64*Statements!K$22/days -> 15541.111 | L48: =L64*Statements!L$22/days -> 16600.47 | M48: =M64*Statements!M$22/days -> 17783.178 | N48: =N64*Statements!N$22/days -> 19118.943 | O48: =O64*Statements!O$22/days -> 20650.514
B50: Current liabilities
B51: Accounts payable | G51: =Statements!G78 -> 64115 | H51: =Statements!H78 -> 62611 | I51: =Statements!I78 -> 68960 | J51: =Statements!J78 -> 69860 | K51: =K66*Statements!K$27/days -> 73518.818 | L51: =L66*Statements!L$27/days -> 76349.742 | M51: =M66*Statements!M$27/days -> 78420.108 | N51: =N66*Statements!N$27/days -> 79695.919 | O51: =O66*Statements!O$27/days -> 79545.763
B52: Other current liabilities | G52: =Statements!G79 -> 60845 | H52: =Statements!H79 -> 58829 | I52: =Statements!I79 -> 78304 | J52: =Statements!J79 -> 66387 | K52: =K67*Statements!K$27/days -> 69863.924 | L52: =L67*Statements!L$27/days -> 72554.113 | M52: =M67*Statements!M$27/days -> 74521.553 | N52: =N67*Statements!N$27/days -> 75733.939 | O52: =O67*Statements!O$27/days -> 75591.247
B53: Deferred revenue | G53: =Statements!G80 -> 7912 | H53: =Statements!H80 -> 8061 | I53: =Statements!I80 -> 8249 | J53: =Statements!J80 -> 9055 | K53: =K69*Statements!K22 -> 9306.6948 | L53: =L69*Statements!L22 -> 10050.37 | M53: =M69*Statements!M22 -> 10790.105 | N53: =N69*Statements!N22 -> 11623.71 | O53: =O69*Statements!O22 -> 12488.387
B55: Current assets | G55: =SUM(G45:G48) -> 87101 | H55: =SUM(H45:H48) -> 82011 | I55: =SUM(I45:I48) -> 87816 | J55: =SUM(J45:J48) -> 93260 | K55: =SUM(K45:K48) -> 99373.603 | L55: =SUM(L45:L48) -> 106147.4 | M55: =SUM(M45:M48) -> 113709.92 | N55: =SUM(N45:N48) -> 122251.13 | O55: =SUM(O45:O48) -> 132044.36
B56: Current liabilities | G56: =SUM(G51:G53) -> 132872 | H56: =SUM(H51:H53) -> 129501 | I56: =SUM(I51:I53) -> 155513 | J56: =SUM(J51:J53) -> 145302 | K56: =SUM(K51:K53) -> 152689.44 | L56: =SUM(L51:L53) -> 158954.22 | M56: =SUM(M51:M53) -> 163731.77 | N56: =SUM(N51:N53) -> 167053.57 | O56: =SUM(O51:O53) -> 167625.4
B57: Total working capital | J57: =J55-J56 -> -52042 | K57: =K55-K56 -> -53315.833 | L57: =L55-L56 -> -52806.825 | M57: =M55-M56 -> -50021.845 | N57: =N55-N56 -> -44802.442 | O57: =O55-O56 -> -35581.039
B58: Change in working capital | K58: =J57-K57 -> 1273.8334 | L58: =K57-L57 -> -509.00812 | M58: =L57-M57 -> -2784.9799 | N58: =M57-N57 -> -5219.403 | O58: =N57-O57 -> -9221.4037
B60: Turnover Ratio
B61: Accounts receivable, net | G61: =G45*days/Statements!G$22 -> 26.087825 | H61: =H45*days/Statements!H$22 -> 28.100291 | I61: =I45*days/Statements!I$22 -> 31.185572 | J61: =J45*days/Statements!J$22 -> 34.886991 | K61: =J61 -> 34.886991 | L61: =K61 -> 34.886991 | M61: =L61 -> 34.886991 | N61: =M61 -> 34.886991 | O61: =N61 -> 34.886991
B62: Vendor non-trade receivables | G62: =G46*days/Statements!G$22 -> 30.31238 | H62: =H46*days/Statements!H$22 -> 29.975358 | I62: =I46*days/Statements!I$22 -> 30.646988 | J62: =J46*days/Statements!J$22 -> 29.100997 | K62: =J62 -> 29.100997 | L62: =K62 -> 29.100997 | M62: =L62 -> 29.100997 | N62: =M62 -> 29.100997 | O62: =N62 -> 29.100997
B63: Inventories | G63: =G47*days/Statements!G$22 -> 4.5781431 | H63: =H47*days/Statements!H$22 -> 6.0289732 | I63: =I47*days/Statements!I$22 -> 6.8009002 | J63: =J47*days/Statements!J$22 -> 5.0150543 | K63: =J63 -> 5.0150543 | L63: =K63 -> 5.0150543 | M63: =L63 -> 5.0150543 | N63: =M63 -> 5.0150543 | O63: =N63 -> 5.0150543
B64: Other current assets | G64: =G48*days/Statements!G$22 -> 19.644547 | H64: =H48*days/Statements!H$22 -> 13.99396 | I64: =I48*days/Statements!I$22 -> 13.335776 | J64: =J48*days/Statements!J$22 -> 12.791984 | K64: =J64 -> 12.791984 | L64: =K64 -> 12.791984 | M64: =L64 -> 12.791984 | N64: =M64 -> 12.791984 | O64: =N64 -> 12.791984
B66: Accounts payable | G66: =G51*days/Statements!G$27 -> 104.68528 | H66: =H51*days/Statements!H$27 -> 106.72147 | I66: =I51*days/Statements!I$27 -> 119.65848 | J66: =J51*days/Statements!J$27 -> 115.40052 | K66: =J66 -> 115.40052 | L66: =K66 -> 115.40052 | M66: =L66 -> 115.40052 | N66: =M66 -> 115.40052 | O66: =N66 -> 115.40052
B67: Other current liabilities | G67: =G52*days/Statements!G$27 -> 99.346108 | H67: =H52*days/Statements!H$27 -> 100.27499 | I67: =I52*days/Statements!I$27 -> 135.87206 | J67: =J52*days/Statements!J$27 -> 109.66354 | K67: =J67 -> 109.66354 | L67: =K67 -> 109.66354 | M67: =L67 -> 109.66354 | N67: =M67 -> 109.66354 | O67: =N67 -> 109.66354
B69: Deferred revenue as a % of revenue | G69: =G53/Statements!G22 -> 0.020064515 | H69: =H53/Statements!H22 -> 0.021031347 | I69: =I53/Statements!I22 -> 0.021095298 | J69: =J53/Statements!J22 -> 0.021758406 | K69: =AVERAGE(G69:J69) -> 0.020987392 | L69: =AVERAGE(H69:K69) -> 0.021218111 | M69: =AVERAGE(I69:L69) -> 0.021264802 | N69: =AVERAGE(J69:M69) -> 0.021307178 | O69: =AVERAGE(K69:N69) -> 0.02119437
B71: Other non-current assets | G71: =Statements!G72 -> 54428 | H71: =Statements!H72 -> 64758 | I71: =Statements!I72 -> 74834 | J71: =Statements!J72 -> 83727 | K71: =K74*Statements!K$22 -> 77552.005 | L71: =L74*Statements!L$22 -> 87203.098 | M71: =M74*Statements!M$22 -> 95337.252 | N71: =N74*Statements!N$22 -> 102022.91 | O71: =O74*Statements!O$22 -> 108107.94
B72: Other non-current liabilities | G72: =Statements!G87 -> 49142 | H72: =Statements!H87 -> 49848 | I72: =Statements!I87 -> 45888 | J72: =Statements!J87 -> 41549 | K72: =K75*Statements!K22 -> 52311.286 | L72: =L75*Statements!L22 -> 55088.929 | M72: =M75*Statements!M22 -> 57269.247 | N72: =N75*Statements!N22 -> 60959.202 | O72: =O75*Statements!O22 -> 67596.083
B74: Other NCA as a % of Revenue | G74: =G71/Statements!G$22 -> 0.13802723 | H74: =H71/Statements!H$22 -> 0.16895522 | I74: =I71/Statements!I$22 -> 0.19137417 | J74: =J71/Statements!J$22 -> 0.20118896 | K74: =AVERAGE(G74:J74) -> 0.17488639 | L74: =AVERAGE(H74:K74) -> 0.18410119 | M74: =AVERAGE(I74:L74) -> 0.18788768 | N74: =AVERAGE(J74:M74) -> 0.18701606 | O74: =AVERAGE(K74:N74) -> 0.18347283
B75: Other NCL as a % of Revenue | G75: =G72/Statements!G22 -> 0.12462214 | H75: =H72/Statements!H22 -> 0.13005466 | I75: =I72/Statements!I22 -> 0.11735011 | J75: =J72/Statements!J22 -> 0.099838764 | K75: =AVERAGE(G75:J75) -> 0.11796642 | L75: =AVERAGE(H75:K75) -> 0.11630249 | M75: =AVERAGE(I75:L75) -> 0.11286445 | N75: =AVERAGE(J75:M75) -> 0.11174303 | O75: =AVERAGE(K75:N75) -> 0.1147191
A78: # | B78: Debt schedule
B80: Long-Term Debt
B82: Opening balance of Long-term debt | K82: 78328 | L82: =K85 -> 65935 | M82: =L85 -> 55857 | N82: =M85 -> 46557 | O82: =N85 -> 41322
B83: Issuance of new debt | K83: 0 | L83: 0 | M83: 0 | N83: 0 | O83: 0
B84: Repayment of debt | K84: 12393 | L84: 10078 | M84: 9300 | N84: 5235 | O84: 4972
B85: Closing balance of Long-term debt | K85: =K82+K83-K84 -> 65935 | L85: =L82+L83-L84 -> 55857 | M85: =M82+M83-M84 -> 46557 | N85: =N82+N83-N84 -> 41322 | O85: =O82+O83-O84 -> 36350
B87: Avg Interest Rate | E87: 0.045
B88: Finance costs | K88: =AVERAGE(K82,K85)*$E$87 -> 3245.9175 | L88: =AVERAGE(L82,L85)*$E$87 -> 2740.32 | M88: =AVERAGE(M82,M85)*$E$87 -> 2304.315 | N88: =AVERAGE(N82,N85)*$E$87 -> 1977.2775 | O88: =AVERAGE(O82,O85)*$E$87 -> 1747.62
A90: # | B90: Revolver
B92: Cash flow generated during the year | K92: =Statements!K114+Statements!K120+Statements!K124+Statements!K126+Statements!K127+Statements!K123 -> 17553.727 | L92: =Statements!L114+Statements!L120+Statements!L124+Statements!L126+Statements!L127+Statements!L123 -> -7925.0681 | M92: =Statements!M114+Statements!M120+Statements!M124+Statements!M126+Statements!M127+Statements!M123 -> -1840.4304 | N92: =Statements!N114+Statements!N120+Statements!N124+Statements!N126+Statements!N127+Statements!N123 -> 2422.966 | O92: =Statements!O114+Statements!O120+Statements!O124+Statements!O126+Statements!O127+Statements!O123 -> 4879.8185
B93: Add: Cash from beginning of the year | K93: =Statements!J61 -> 35934 | L93: =Statements!K61 -> 50346.589 | M93: =Statements!L61 -> 39765.201 | N93: =Statements!M61 -> 35704.455 | O93: =Statements!N61 -> 36234.144
B94: Minimum cash balance | K94: -15000 | L94: -15000 | M94: -15000 | N94: -15000 | O94: -15000
B95: Cash available for repayment of debt | K95: =SUM(K92:K94) -> 38487.727 | L95: =SUM(L92:L94) -> 27421.521 | M95: =SUM(M92:M94) -> 22924.77 | N95: =SUM(N92:N94) -> 23127.421 | O95: =SUM(O92:O94) -> 26113.962
B97: Commercial paper
B99: Opening balance of Commercial paper | K99: 7979 | L99: =K102 -> 8000 | M99: =L102 -> 8000 | N99: =M102 -> 8000 | O99: =N102 -> 8000
B100: Commercial paper to be paid/(drawn) | K100: =-MIN(K99,K95) -> -7979 | L100: =-MIN(L99,L95) -> -8000 | M100: =-MIN(M99,M95) -> -8000 | N100: =-MIN(N99,N95) -> -8000 | O100: =-MIN(O99,O95) -> -8000
B101: Issuance of commercial paper | K101: 8000 | L101: 8000 | M101: 8000 | N101: 8000 | O101: 8000
B102: Closing balance of commercial paper | K102: =SUM(K99:K101) -> 8000 | L102: =SUM(L99:L101) -> 8000 | M102: =SUM(M99:M101) -> 8000 | N102: =SUM(N99:N101) -> 8000 | O102: =SUM(O99:O101) -> 8000
B104: Avg Interest Rate | E104: 0.0105
B105: Finance costs | K105: =K99*$E$104 -> 83.7795 | L105: =L99*$E$104 -> 84 | M105: =M99*$E$104 -> 84 | N105: =N99*$E$104 -> 84 | O105: =O99*$E$104 -> 84
A107: # | B107: Equity schedule
B109: Opening balance of accumulated deficit | K109: -14264 | L109: =K113 -> -15630.443 | M109: =L113 -> -19390.637 | N109: =M113 -> -16099.756 | O109: =N113 -> -13835.67
B110: Net income for the year | K110: =Statements!K43 -> 117784.76 | L110: =Statements!L43 -> 131820.77 | M110: =Statements!M43 -> 150935.16 | N110: =Statements!N43 -> 175614.77 | O110: =Statements!O43 -> 209022.36
B111: Issuance of dividends for the year | K111: =-Assumptions!K22 -> -16254.297 | L111: =-Assumptions!L22 -> -16938.969 | M111: =-Assumptions!M22 -> -17961.284 | N111: =-Assumptions!N22 -> -19229.817 | O111: =-Assumptions!O22 -> -20902.236
B112: Share buy-back | K112: =-Assumptions!K25 -> -102896.9 | L112: =-Assumptions!L25 -> -118641.99 | M112: =-Assumptions!M25 -> -129682.99 | N112: =-Assumptions!N25 -> -154120.87 | O112: =-Assumptions!O25 -> -183718.77
B113: Closing balance of accumulated deficit | K113: =SUM(K109:K112) -> -15630.443 | L113: =SUM(L109:L112) -> -19390.637 | M113: =SUM(M109:M112) -> -16099.756 | N113: =SUM(N109:N112) -> -13835.67 | O113: =SUM(O109:O112) -> -9434.3153
B115: Opening balance of CS and APIC | K115: =Statements!J92 -> 93568 | L115: =K117 -> 106732.64 | M115: =L117 -> 121019.46 | N115: =M117 -> 136370.17 | O115: =N117 -> 152754.65
B116: Share based compensation | K116: =Assumptions!K19 -> 13164.643 | L116: =Assumptions!L19 -> 14286.818 | M116: =Assumptions!M19 -> 15350.711 | N116: =Assumptions!N19 -> 16384.474 | O116: =Assumptions!O19 -> 17765.077
B117: Closing balance of CS and APIC | K117: =SUM(K115:K116) -> 106732.64 | L117: =SUM(L115:L116) -> 121019.46 | M117: =SUM(M115:M116) -> 136370.17 | N117: =SUM(N115:N116) -> 152754.65 | O117: =SUM(O115:O116) -> 170519.72
B120: <- Go back to the top

Sheet Valuation->
A1: \

Sheet Beta
B2: =Dashboard!B2 -> Apple, Inc.
B3: Beta
B4: =Dashboard!B4 -> (In millions, except number of shares, which are reflected in thousands, and per-share amounts)
B5: Active Scenario | D5: =Dashboard!G13 -> Street
B8: <-Back to dashboard
B10: (Data is the daily closing price from 3/26 to 3/25)
B11: APPLE Inc. | F11: NYSE | J11: Beta Drifting
B13: Date | C13: Price | D13: Returns | F13: Date | G13: Price | H13: Returns | J13: Calculated beta | L13: =SLOPE(D15:D263,H15:H263) -> 1.3948533
B14: 46085 | C14: 262.52 | F14: 46085 | G14: 23086.3
B15: 46084 | C15: 263.75 | D15: =C15/C14-1 -> 0.0046853573 | F15: 46084 | G15: 22998.2 | H15: =G15/G14-1 -> -0.0038161161 | J15: Levered beta | L15: =L13 -> 1.3948533
B16: 46083 | C16: 264.72 | D16: =C16/C15-1 -> 0.0036777251 | F16: 46083 | G16: 23413.1 | H16: =G16/G15-1 -> 0.018040542 | J16: Raw beta weight | L16: 0.75
B17: 46080 | C17: 264.18 | D17: =C17/C16-1 -> -0.0020398912 | F17: 46080 | G17: 23494.4 | H17: =G17/G16-1 -> 0.003472415
B18: 46079 | C18: 272.95 | D18: =C18/C17-1 -> 0.033197063 | F18: 46079 | G18: 23524.8 | H18: =G18/G17-1 -> 0.0012939254 | J18: Market beta | L18: =SLOPE(H15:H263,H15:H263) -> 1
B19: 46078 | C19: 274.23 | D19: =C19/C18-1 -> 0.0046895036 | F19: 46078 | G19: 23452.7 | H19: =G19/G18-1 -> -0.0030648507 | J19: Raw beta weight | L19: 0.25
B20: 46077 | C20: 272.14 | D20: =C20/C19-1 -> -0.0076213398 | F20: 46077 | G20: 23383.8 | H20: =G20/G19-1 -> -0.0029378281
B21: 46076 | C21: 266.18 | D21: =C21/C20-1 -> -0.021900492 | F21: 46076 | G21: 23214.9 | H21: =G21/G20-1 -> -0.0072229492 | J21: Adjusted beta | L21: =L15*L16+L18*L19 -> 1.29614
B22: 46073 | C22: 264.58 | D22: =C22/C21-1 -> -0.00601097 | F22: 46073 | G22: 23452.6 | H22: =G22/G21-1 -> 0.010239114
B23: 46072 | C23: 260.58 | D23: =C23/C22-1 -> -0.015118301 | F23: 46072 | G23: 23358.3 | H23: =G23/G22-1 -> -0.0040208762 | J23: Total years | L23: =YEARFRAC(F263,F14,1) -> 0.99452055
B24: 46071 | C24: 264.35 | D24: =C24/C23-1 -> 0.014467726 | F24: 46071 | G24: 23387.5 | H24: =G24/G23-1 -> 0.001250091 | J24: Market returns (%) | L24: =AVERAGE(H15:H263) -> -0.00062817509
B25: 46070 | C25: 263.88 | D25: =C25/C24-1 -> -0.0017779459 | F25: 46070 | G25: 23300.8 | H25: =G25/G24-1 -> -0.0037071085
B26: 46066 | C26: 255.78 | D26: =C26/C25-1 -> -0.030695771 | F26: 46066 | G26: 23326.1 | H26: =G26/G25-1 -> 0.0010857996
B27: 46065 | C27: 261.73 | D27: =C27/C26-1 -> 0.023262178 | F27: 46065 | G27: 23188.8 | H27: =G27/G26-1 -> -0.0058861104
B28: 46064 | C28: 275.5 | D28: =C28/C27-1 -> 0.05261147 | F28: 46064 | G28: 23479.7 | H28: =G28/G27-1 -> 0.012544849
B29: 46063 | C29: 273.68 | D29: =C29/C28-1 -> -0.0066061706 | F29: 46063 | G29: 23398.1 | H29: =G29/G28-1 -> -0.0034753425
B30: 46062 | C30: 274.62 | D30: =C30/C29-1 -> 0.0034346682 | F30: 46062 | G30: 23340.7 | H30: =G30/G29-1 -> -0.0024531906
B31: 46059 | C31: 278.12 | D31: =C31/C30-1 -> 0.012744884 | F31: 46059 | G31: 23252.8 | H31: =G31/G30-1 -> -0.0037659539
B32: 46058 | C32: 275.91 | D32: =C32/C31-1 -> -0.0079462103 | F32: 46058 | G32: 22733.3 | H32: =G32/G31-1 -> -0.022341395
B33: 46057 | C33: 276.49 | D33: =C33/C32-1 -> 0.0021021348 | F33: 46057 | G33: 22975.6 | H33: =G33/G32-1 -> 0.010658373
B34: 46056 | C34: 269.48 | D34: =C34/C33-1 -> -0.025353539 | F34: 46056 | G34: 22881.2 | H34: =G34/G33-1 -> -0.0041087066
B35: 46055 | C35: 270.01 | D35: =C35/C34-1 -> 0.0019667508 | F35: 46055 | G35: 22885.7 | H35: =G35/G34-1 -> 0.00019666801
B36: 46052 | C36: 259.48 | D36: =C36/C35-1 -> -0.038998556 | F36: 46052 | G36: 22719.3 | H36: =G36/G35-1 -> -0.0072709159
... B263: 45722 | C263: 235.33 | D263: =C263/C262-1 -> -0.015643954 | F263: 45722 | G263: 19506.3 | H263: =G263/G262-1 -> -0.0034128472

Sheet WACC
B2: =Dashboard!B2 -> Apple, Inc.
B3: WACC
B4: =Dashboard!B4 -> (In millions, except number of shares, which are reflected in thousands, and per-share amounts)
B5: Active Scenario | D5: =Dashboard!G13 -> Street
B8: <-Back to dashboard
B10: Cost of Equity | G10: Capital Structure
B11: Risk free rate | D11: 0.04148 | G11: Market Cap | H11: 4000000
B12: Adj. Default Spread | D12: 0.0023 | G12: Debt | H12: =Statements!J82+Statements!J81+Statements!J86 -> 98657
B13: Equity risk premium | D13: 0.0446 | G13: Total Capital | H13: =H11+H12 -> 4098657
B14: Country risk premium | D14: 0.0023
B15: Levered beta | D15: =Beta!L21 -> 1.29614 | G15: Debt / Total Cap | H15: =H11/H13 -> 0.97592943
B16: Cost of equity | D16: =(D11-D12)+(D13*D15)+D14 -> 0.099287844 | G16: Equity / Total Cap | H16: =H12/H13 -> 0.024070568
B18: Cost of Debt | G18: WACC
B19: (Using yield of Apple bond) | G19: Cost of Equity | H19: =D16*H15 -> 0.096897929
B20: CMP | D20: 96 | G20: Cost of Debt | H20: =D28*H16 -> 0.00097494453
B21: Face value | D21: 100 | G21: WACC | H21: =H19+H20 -> 0.097872873
B22: Maturity year | D22: 55953
B23: Total years | D23: =YEARFRAC(TODAY(),D22,1) -> 26.962355
B24: Coupon rate | D24: 0.0485
B25: YTM | D25: =RATE(D23,(D21*D24),-D20,D21) -> 0.051270374
B27: Tax rate | D27: 0.21
B28: Post-tax cost of debt | D28: =D25*(1-D27) -> 0.040503595

Sheet FCFF
B2: =Dashboard!B2 -> Apple, Inc.
B3: FCFF
B4: =Dashboard!B4 -> (In millions, except number of shares, which are reflected in thousands, and per-share amounts)
B5: Active Scenario | D5: =Dashboard!G13 -> Street
B7: <-Back to dashboard
B9: Valuation parameters
B10: Valuation as on specified date | E10: 45961 | G10: Implied Share Price | I10: =E37 -> 173.91744
B11: Date of year ending | E11: 46022 | G11: Current Share Price | I11: 271.86
B12: WACC | E12: =WACC!H21 -> 0.097872873 | G12: Premium / (Discount) | I12: =I11/I10-1 -> 0.56315553
B13: Terminal growth rate | E13: 0.02
B14: Tax Rate | E14: 0.21
B16: Free Cash Flow to Firm | E16: =Statements!K101 -> 46326 | F16: =Statements!L101 -> 46691 | G16: =Statements!M101 -> 47057 | H16: =Statements!N101 -> 47422 | I16: =Statements!O101 -> 47787
B18: EBIT | E18: =Statements!K36 -> 143668.31 | F18: =Statements!L36 -> 159872.17 | G18: =Statements!M36 -> 182087.71 | H18: =Statements!N36 -> 211338.85 | I18: =Statements!O36 -> 250912.93
B19: Tax Rate | E19: =tax_rate -> 0.21 | F19: =tax_rate -> 0.21 | G19: =tax_rate -> 0.21 | H19: =tax_rate -> 0.21 | I19: =tax_rate -> 0.21
B20: NOPAT | E20: =E18*(1-E19) -> 113497.97 | F20: =F18*(1-F19) -> 126299.01 | G20: =G18*(1-G19) -> 143849.29 | H20: =H18*(1-H19) -> 166957.69 | I20: =I18*(1-I19) -> 198221.21
B22: Add: Depreciaton & Amortization | E22: =Statements!K106 -> 13546.4 | F22: =Statements!L106 -> 14880.301 | G22: =Statements!M106 -> 15799.337 | H22: =Statements!N106 -> 17860.862 | I22: =Statements!O106 -> 19509.955
B23: Add: Share-based Compensation | E23: =Statements!K107 -> 13164.643 | F23: =Statements!L107 -> 14286.818 | G23: =Statements!M107 -> 15350.711 | H23: =Statements!N107 -> 16384.474 | I23: =Statements!O107 -> 17765.077
B24: Less: CapEx | E24: =Statements!K117 -> -13303.266 | F24: =Statements!L117 -> -14683.751 | G24: =Statements!M117 -> -16237.318 | H24: =Statements!N117 -> -18002.498 | I24: =Statements!O117 -> -20033.865
B25: Add|Less: Change in NWC | E25: =SUM(Statements!K111:K113) -> 12036.12 | F25: =SUM(Statements!L111:L113) -> 2268.6346 | G25: =SUM(Statements!M111:M113) -> -604.6616 | H25: =SUM(Statements!N111:N113) -> -1529.4486 | I25: =SUM(Statements!O111:O113) -> -2584.5227
B26: FCFF | E26: =SUM(E20:E25) -> 138941.86 | F26: =SUM(F20:F25) -> 143051.02 | G26: =SUM(G20:G25) -> 158157.36 | H26: =SUM(H20:H25) -> 181671.08 | I26: =SUM(I20:I25) -> 212877.86
B28: Discount Factor | E28: =(E11-E10)/(365/2) -> 0.33424658 | F28: =E28+1 -> 1.3342466 | G28: =F28+1 -> 2.3342466 | H28: =G28+1 -> 3.3342466 | I28: =H28+1 -> 4.3342466
B29: Terminal Value | I29: =I26*(1+Terminal_rate)/(WACC-Terminal_rate) -> 2788331.9
B30: PV of Firm | E30: =E26/(1+WACC)^E28 -> 134672.44 | F30: =F26/(1+WACC)^F28 -> 126294.52 | G30: =G26/(1+WACC)^G28 -> 127183.54 | H30: =H26/(1+WACC)^H28 -> 133068.5 | I30: =(I26+I29)/(1+WACC)^I28 -> 2002321.2
B31: Enterprise Value | E31: =SUM(E30:I30) -> 2523540.2
B32: Add: Cash | E32: =Statements!J61 -> 35934
B33: Add: Investments & Securities | E33: =Statements!J62+Statements!J70 -> 96486
B34: Less: Debt | E34: =-(Statements!J82+Statements!J86) -> -90678
B35: PV of Equity | E35: =SUM(E31:E34) -> 2565282.2
B36: Shares Outstanding | E36: 14750
B37: Price per Share | E37: =E35/E36 -> 173.91744
A40: # | B40: Sensitivity Analysis
D42: Terminal Growth %
C43: =E37 -> 173.91744 | D43: 0 | E43: =D43+1% -> 0.01 | F43: =E43+1% -> 0.02 | G43: =F43+1% -> 0.03 | H43: =G43+1% -> 0.04
B44: WACC | C44: =C45+1% -> 0.12 | D44: 119.33181 | E44: 126.82488 | F44: 135.81656 | G44: 146.80638 | H44: 160.54367
C45: =C47+2% -> 0.11 | D45: 130.11227 | E45: 139.3769 | F45: 150.70033 | G45: 164.85461 | H45: 183.05298
C46: 0.097872863 | D46: 146.17726 | E46: 158.46893 | F46: 173.91746 | G46: 193.91818 | H46: 220.83085
C47: =C48+1% -> 0.09 | D47: 158.94803 | E47: 173.98696 | F47: 193.32272 | G47: 219.10373 | H47: 255.19715
C48: =C49+1% -> 0.08 | D48: 178.8252 | E48: 198.76439 | F48: 225.34997 | G48: 262.56978 | H48: 318.3995
C49: 0.07 | D49: 204.42421 | E49: 231.8473 | F49: 270.23963 | G49: 327.82813 | H49: 423.80895

Sheet Ratio Analysis
B2: =Dashboard!B2 -> Apple, Inc.
B3: Ratio Analysis
B4: =Dashboard!B4 -> (In millions, except number of shares, which are reflected in thousands, and per-share amounts)
B5: Active Scenario | D5: =Dashboard!G13 -> Street
B6: Historical / Projections | E6: =Statements!G6 -> Historicals | H6: =Statements!K6 -> Projections
B7: Year | E7: =Statements!H7 -> 45230 | F7: =Statements!I7 -> 45596 | G7: =Statements!J7 -> 45961 | H7: =Statements!K7 -> 46326 | I7: =Statements!L7 -> 46691 | J7: =Statements!M7 -> 47057 | K7: =Statements!N7 -> 47422 | L7: =Statements!O7 -> 47787
B9: <-Back to dashboard
A11: # | B11: Ratio Analysis
B13: EBITDA | E13: =Statements!H53 -> 125820 | F13: =Statements!I53 -> 134661 | G13: =Statements!J53 -> 144748 | H13: =Statements!K53 -> 165291.06 | I13: =Statements!L53 -> 169175.55 | J13: =Statements!M53 -> 170740.99 | K13: =Statements!N53 -> 169948.61 | L13: =Statements!O53 -> 164871.76
B14: EBIT | E14: =Statements!H36 -> 114301 | F14: =Statements!I36 -> 123216 | G14: =Statements!J36 -> 133050 | H14: =Statements!K36 -> 143668.31 | I14: =Statements!L36 -> 159872.17 | J14: =Statements!M36 -> 182087.71 | K14: =Statements!N36 -> 211338.85 | L14: =Statements!O36 -> 250912.93
B15: NOPAT | E15: =E14*(1-Assumptions!H14) -> 97476.837 | F15: =F14*(1-Assumptions!I14) -> 93531.805 | G15: =G14*(1-Assumptions!J14) -> 112280.89 | H15: =H14*(1-Assumptions!K14) -> 120681.38 | I15: =I14*(1-Assumptions!L14) -> 134292.62 | J15: =J14*(1-Assumptions!M14) -> 152953.67 | K15: =K14*(1-Assumptions!N14) -> 177524.64 | L15: =L14*(1-Assumptions!O14) -> 210766.86
B16: PAT | E16: =Statements!H43 -> 96995 | F16: =Statements!I43 -> 93736 | G16: =Statements!J43 -> 112010 | H16: =Statements!K43 -> 117784.76 | I16: =Statements!L43 -> 131820.77 | J16: =Statements!M43 -> 150935.16 | K16: =Statements!N43 -> 175614.77 | L16: =Statements!O43 -> 209022.36
B18: Profitability ratio
B19: Gross Margin (GM) | E19: =Statements!H29/Statements!H22 -> 0.4413113 | F19: =Statements!I29/Statements!I22 -> 0.4620635 | G19: =Statements!J29/Statements!J22 -> 0.46905164 | H19: =Statements!K29/Statements!K22 -> 0.47561943 | I19: =Statements!L29/Statements!L22 -> 0.49017946 | J19: =Statements!M29/Statements!M22 -> 0.51118087 | K19: =Statements!N29/Statements!N22 -> 0.53793579 | L19: =Statements!O29/Statements!O22 -> 0.57301137
B20: Operating Margin (OPM) | E20: =Statements!H36/Statements!H22 -> 0.29821412 | F20: =Statements!I36/Statements!I22 -> 0.31510223 | G20: =Statements!J36/Statements!J22 -> 0.319708 | H20: =Statements!K36/Statements!K22 -> 0.32398431 | I20: =Statements!L36/Statements!L22 -> 0.33751847 | J20: =Statements!M36/Statements!M22 -> 0.35885277 | K20: =Statements!N36/Statements!N22 -> 0.3874008 | L20: =Statements!O36/Statements!O22 -> 0.42583095
B21: PBT Margin | E21: =Statements!H40/Statements!H22 -> 0.29674002 | F21: =Statements!I40/Statements!I22 -> 0.31579015 | G21: =Statements!J40/Statements!J22 -> 0.31893666 | H21: =Statements!K40/Statements!K22 -> 0.31620796 | I21: =Statements!L40/Statements!L22 -> 0.33130594 | J21: =Statements!M40/Statements!M22 -> 0.35411703 | K21: =Statements!N40/Statements!N22 -> 0.38323302 | L21: =Statements!O40/Statements!O22 -> 0.42230639
B22: PAT Margin | E22: =Statements!H43/Statements!H22 -> 0.25306234 | F22: =Statements!I43/Statements!I22 -> 0.23971256 | G22: =Statements!J43/Statements!J22 -> 0.26915064 | H22: =Statements!K43/Statements!K22 -> 0.26561469 | I22: =Statements!L43/Statements!L22 -> 0.27829699 | J22: =Statements!M43/Statements!M22 -> 0.2974583 | K22: =Statements!N43/Statements!N22 -> 0.32191574 | L22: =Statements!O43/Statements!O22 -> 0.35473736
B23: ROE | E23: =Statements!H43/(AVERAGE(Statements!G50:H50)*10) -> 0.60697379 | F23: =Statements!I43/(AVERAGE(Statements!H50:I50)*10) -> 0.60303627 | G23: =Statements!J43/(AVERAGE(Statements!I50:J50)*10) -> 0.73952828 | H23: =Statements!K43/(AVERAGE(Statements!J50:K50)*10) -> 0.78793697 | I23: =Statements!L43/(AVERAGE(Statements!K50:L50)*10) -> 0.88183275 | J23: =Statements!M43/(AVERAGE(Statements!L50:M50)*10) -> 1.009701 | K23: =Statements!N43/(AVERAGE(Statements!M50:N50)*10) -> 1.1747986 | L23: =Statements!O43/(AVERAGE(Statements!N50:O50)*10) -> 1.3982832
B24: ROCE | E24: =Statements!H36/(Statements!H74-Statements!H83) -> 0.55144615 | F24: =Statements!I36/(Statements!I74-Statements!I83) -> 0.65336077 | G24: =Statements!J36/(Statements!J74-Statements!J83) -> 0.68720624 | H24: =Statements!K36/(Statements!K74-Statements!K83) -> 0.70502544 | I24: =Statements!L36/(Statements!L74-Statements!L83) -> 0.77231532 | J24: =Statements!M36/(Statements!M74-Statements!M83) -> 0.83325547 | K24: =Statements!N36/(Statements!N74-Statements!N83) -> 0.89691292 | L24: =Statements!O36/(Statements!O74-Statements!O83) -> 0.96705639
B25: ROIC | H25: =H15/(Statements!K95+Statements!K86+Statements!K82+Statements!K81) -> 0.70238652 | I25: =I15/(Statements!L95+Statements!L86+Statements!L82+Statements!L81) -> 0.77957077 | J25: =J15/(Statements!M95+Statements!M86+Statements!M82+Statements!M81) -> 0.84222615 | K25: =K15/(Statements!N95+Statements!N86+Statements!N82+Statements!N81) -> 0.9102895 | L25: =L15/(Statements!O95+Statements!O86+Statements!O82+Statements!O81) -> 0.99317883
B26: ROA | H26: =H16/AVERAGE(Statements!J74:K74) -> 0.32004209 | I26: =I16/AVERAGE(Statements!K74:L74) -> 0.34547626 | J26: =J16/AVERAGE(Statements!L74:M74) -> 0.38263966 | K26: =K16/AVERAGE(Statements!M74:N74) -> 0.42540268 | L26: =L16/AVERAGE(Statements!N74:O74) -> 0.48025249
B28: Leverage Ratio
B29: Debt to Equity | H29: =Statements!K89/Statements!K95 -> 3.4056078 | I29: =Statements!L89/Statements!L95 -> 3.0216191 | J29: =Statements!M89/Statements!M95 -> 2.5101088 | K29: =Statements!N89/Statements!N95 -> 2.1723972 | L29: =Statements!O89/Statements!O95 -> 1.8771346
B30: Debt to Asset | H30: =Statements!K74/Statements!K95 -> 4.4056078 | I30: =Statements!L74/Statements!L95 -> 4.0216191 | J30: =Statements!M74/Statements!M95 -> 3.5101088 | K30: =Statements!N74/Statements!N95 -> 3.1723972 | L30: =Statements!O74/Statements!O95 -> 2.8771346
B31: Current Ratio | H31: =Statements!K67/Statements!K83 -> 0.97366933 | I31: =Statements!L67/Statements!L83 -> 0.9184145 | J31: =Statements!M67/Statements!M83 -> 0.91360149 | K31: =Statements!N67/Statements!N83 -> 0.94581054 | L31: =Statements!O67/Statements!O83 -> 1.0121415
B32: Quick Ratio | H32: =(Statements!K61+Statements!K62+Statements!K63+Statements!K64)/Statements!K83 -> 0.84864609 | I32: =(Statements!L61+Statements!L62+Statements!L63+Statements!L64)/Statements!L83 -> 0.78953506 | J32: =(Statements!M61+Statements!M62+Statements!M63+Statements!M64)/Statements!M83 -> 0.77912314 | K32: =(Statements!N61+Statements!N62+Statements!N63+Statements!N64)/Statements!N83 -> 0.80379371 | L32: =(Statements!O61+Statements!O62+Statements!O63+Statements!O64)/Statements!O83 -> 0.85921469
B33: Cash Ratio | H33: =Statements!K61/Statements!K83 -> 0.29095442 | I33: =Statements!L61/Statements!L83 -> 0.22177503 | J33: =Statements!M61/Statements!M83 -> 0.19395976 | K33: =Statements!N61/Statements!N83 -> 0.19334821 | L33: =Statements!O61/Statements!O83 -> 0.20986971
B35: Valuation Ratio
B36: EPS (₹) | E36: =Statements!H46 -> 6.16 | F36: =Statements!I46 -> 6.11 | G36: =Statements!J46 -> 7.49 | H36: =Statements!K46 -> 6.7920167 | I36: =Statements!L46 -> 7.6851724 | J36: =Statements!M46 -> 8.8954662 | K36: =Statements!N46 -> 10.461582 | L36: =Statements!O46 -> 12.584549
B37: DPS (₹) | E37: =Assumptions!H22/Statements!H50 -> 0.95247586 | F37: =Assumptions!I22/Statements!I50 -> 0.99180235 | G37: =Assumptions!J22/Statements!J50 -> 1.0310734 | H37: =Assumptions!K22/Statements!K50 -> 1.087353 | I37: =Assumptions!L22/Statements!L50 -> 1.1331551 | J37: =Assumptions!M22/Statements!M50 -> 1.2015442 | K37: =Assumptions!N22/Statements!N50 -> 1.2864045 | L37: =Assumptions!O22/Statements!O50 -> 1.3982832
B38: Dividend Yield | E38: =Assumptions!H23 -> 0.15460591 | F38: =Assumptions!I23 -> 0.16234958 | G38: =Assumptions!J23 -> 0.13760379 | H38: =Assumptions!K23 -> 0.138 | I38: =Assumptions!L23 -> 0.1285 | J38: =Assumptions!M23 -> 0.119 | K38: =Assumptions!N23 -> 0.1095 | L38: =Assumptions!O23 -> 0.1
B40: Operating Ratio
B41: Fixed Asset Turnover | H41: =Statements!K22/AVERAGE(Statements!J71:K71) -> 8.619505 | I41: =Statements!L22/AVERAGE(Statements!K71:L71) -> 8.6306085 | J41: =Statements!M22/AVERAGE(Statements!L71:M71) -> 8.5947329 | K41: =Statements!N22/AVERAGE(Statements!M71:N71) -> 8.5634918 | L41: =Statements!O22/AVERAGE(Statements!N71:O71) -> 8.5777606
B42: Total Asset Turnover | H42: =Statements!K22/AVERAGE(Statements!J74:K74) -> 1.2049111 | I42: =Statements!L22/AVERAGE(Statements!K74:L74) -> 1.2413942 | J42: =Statements!M22/AVERAGE(Statements!L74:M74) -> 1.286364 | K42: =Statements!N22/AVERAGE(Statements!M74:N74) -> 1.3214721 | L42: =Statements!O22/AVERAGE(Statements!N74:O74) -> 1.3538255
B43: Working Capital Turnover | H43: =Statements!K22/(Schedule!J55-Schedule!J56) -> -8.5208521 | I43: =Statements!L22/(Schedule!K55-Schedule!K56) -> -8.8842163 | J43: =Statements!M22/(Schedule!L55-Schedule!L56) -> -9.6089131 | K43: =Statements!N22/(Schedule!M55-Schedule!M56) -> -10.90584 | L43: =Statements!O22/(Schedule!N55-Schedule!N56) -> -13.151768
B45: Dupoint Analysis
B46: Profit Margin | H46: =H22 -> 0.26561469 | I46: =I22 -> 0.27829699 | J46: =J22 -> 0.2974583 | K46: =K22 -> 0.32191574 | L46: =L22 -> 0.35473736
B47: Asset Turnover | H47: =H42 -> 1.2049111 | I47: =I42 -> 1.2413942 | J47: =J42 -> 1.286364 | K47: =K42 -> 1.3214721 | L47: =L42 -> 1.3538255
B48: Asset Leverage | H48: =(Statements!K81+Statements!K82+Statements!K86)/Statements!K74 -> 0.22898388 | I48: =(Statements!L81+Statements!L82+Statements!L86)/Statements!L74 -> 0.19727007 | J48: =(Statements!M81+Statements!M82+Statements!M86)/Statements!M74 -> 0.16618422 | K48: =(Statements!N81+Statements!N82+Statements!N86)/Statements!N74 -> 0.1457854 | L48: =(Statements!O81+Statements!O82+Statements!O86)/Statements!O74 -> 0.12672207
B49: Dupont ROE | H49: =H46*H47*H48 -> 0.073284479 | I49: =I46*I47*I48 -> 0.068152124 | J49: =J46*J47*J48 -> 0.063588671 | K49: =K46*K47*K48 -> 0.062017501 | L49: =L46*L47*L48 -> 0.060858587

Sheet Analysis
B2: =Dashboard!B2 -> Apple, Inc.
B3: Analysis
B4: =Dashboard!B4 -> (In millions, except number of shares, which are reflected in thousands, and per-share amounts)
B5: Active Scenario | D5: =Dashboard!G13 -> Street
B6: Historical / Projections | E6: =Statements!G6 -> Historicals | I6: =Statements!K6 -> Projections
B7: Year | E7: 45230 | F7: =EDATE(E7,12) -> 45596 | G7: =EDATE(F7,12) -> 45961 | H7: =EDATE(G7,12) -> 46326 | I7: =EDATE(H7,12) -> 46691 | J7: =EDATE(I7,12) -> 47057 | K7: =EDATE(J7,12) -> 47422 | L7: =EDATE(K7,12) -> 47787
A9: # | B9: Income Statement (Trend Analysis)
B11: Net sales:
B12: Products | E12: - | F12: =Statements!H20/Statements!G20-1 -> -0.057286709 | G12: =Statements!I20/Statements!H20-1 -> -0.010798933 | H12: =Statements!J20/Statements!I20-1 -> 0.04116107 | I12: =Statements!K20/Statements!J20-1 -> 0.040862317 | J12: =Statements!L20/Statements!K20-1 -> 0.037889991 | K12: =Statements!M20/Statements!L20-1 -> 0.034311551 | L12: =Statements!N20/Statements!M20-1 -> 0.030243967
B13: Services | E13: - | F13: =Statements!H21/Statements!G21-1 -> 0.090504166 | G13: =Statements!I21/Statements!H21-1 -> 0.12874413 | H13: =Statements!J21/Statements!I21-1 -> 0.13506431 | I13: =Statements!K21/Statements!J21-1 -> 0.135 | J13: =Statements!L21/Statements!K21-1 -> 0.14625 | K13: =Statements!M21/Statements!L21-1 -> 0.1575 | L13: =Statements!N21/Statements!M21-1 -> 0.16875
B14: Total net sales | E14: - | F14: =Statements!H22/Statements!G22-1 -> -0.028004605 | G14: =Statements!I22/Statements!H22-1 -> 0.020219941 | H14: =Statements!J22/Statements!I22-1 -> 0.064255118 | I14: =Statements!K22/Statements!J22-1 -> 0.065554398 | J14: =Statements!L22/Statements!K22-1 -> 0.068164943 | K14: =Statements!M22/Statements!L22-1 -> 0.071245474 | L14: =Statements!N22/Statements!M22-1 -> 0.075113975
B16: Cost of sales:
B17: Products | E17: - | F17: =Statements!H25/Statements!G25-1 -> -0.060500022 | G17: =Statements!I25/Statements!H25-1 -> -0.021391363 | H17: =Statements!J25/Statements!I25-1 -> 0.047955818 | I17: =Statements!K25/Statements!J25-1 -> 0.048 | J17: =Statements!L25/Statements!K25-1 -> 0.033 | K17: =Statements!M25/Statements!L25-1 -> 0.018 | L17: =Statements!N25/Statements!M25-1 -> 0.003
B18: Services | E18: - | F18: =Statements!H26/Statements!G26-1 -> 0.12593431 | G18: =Statements!I26/Statements!H26-1 -> 0.010621605 | H18: =Statements!J26/Statements!I26-1 -> 0.068673116 | I18: =Statements!K26/Statements!J26-1 -> 0.084 | J18: =Statements!L26/Statements!K26-1 -> 0.077 | K18: =Statements!M26/Statements!L26-1 -> 0.08825 | L18: =Statements!N26/Statements!M26-1 -> 0.0995
B19: Total cost of sales | E19: - | F19: =Statements!H27/Statements!G27-1 -> -0.042089771 | G19: =Statements!I27/Statements!H27-1 -> -0.0176756 | H19: =Statements!J27/Statements!I27-1 -> 0.050429756 | I19: =Statements!K27/Statements!J27-1 -> 0.05237357 | J19: =Statements!L27/Statements!K27-1 -> 0.038506119 | K19: =Statements!M27/Statements!L27-1 -> 0.027116873 | L19: =Statements!N27/Statements!M27-1 -> 0.016268923
B21: Gross margin | E21: - | F21: =Statements!H29/Statements!G29-1 -> -0.009567753 | G21: =Statements!I29/Statements!H29-1 -> 0.068194717 | H21: =Statements!J29/Statements!I29-1 -> 0.080350669 | I21: =Statements!K29/Statements!J29-1 -> 0.080474588 | J21: =Statements!L29/Statements!K29-1 -> 0.10086443 | K21: =Statements!M29/Statements!L29-1 -> 0.11714227 | L21: =Statements!N29/Statements!M29-1 -> 0.13138483
B23: Operating expenses:
B24: Research and development | E24: - | F24: =Statements!H32/Statements!G32-1 -> 0.13957564 | G24: =Statements!I32/Statements!H32-1 -> 0.048637807 | H24: =Statements!J32/Statements!I32-1 -> 0.10137074 | I24: =Statements!K32/Statements!J32-1 -> 0.101 | J24: =Statements!L32/Statements!K32-1 -> 0.0945 | K24: =Statements!M32/Statements!L32-1 -> 0.088 | L24: =Statements!N32/Statements!M32-1 -> 0.0815
B25: Selling, general and administrative | E25: - | F25: =Statements!H33/Statements!G33-1 -> -0.0064557265 | G25: =Statements!I33/Statements!H33-1 -> 0.046727098 | H25: =Statements!J33/Statements!I33-1 -> 0.057631145 | I25: =Statements!K33/Statements!J33-1 -> 0.058 | J25: =Statements!L33/Statements!K33-1 -> 0.0505 | K25: =Statements!M33/Statements!L33-1 -> 0.043 | L25: =Statements!N33/Statements!M33-1 -> 0.0355
B26: Total operating expenses | E26: - | F26: =Statements!H34/Statements!G34-1 -> 0.068205278 | G26: =Statements!I34/Statements!H34-1 -> 0.047769249 | H26: =Statements!J34/Statements!I34-1 -> 0.081507648 | I26: =Statements!K34/Statements!J34-1 -> 0.081903879 | J26: =Statements!L34/Statements!K34-1 -> 0.07539151 | K26: =Statements!M34/Statements!L34-1 -> 0.068909573 | L26: =Statements!N34/Statements!M34-1 -> 0.062458362
B28: Operating income (EBIT) | E28: - | F28: =Statements!H36/Statements!G36-1 -> -0.04300175 | G28: =Statements!I36/Statements!H36-1 -> 0.077995818 | H28: =Statements!J36/Statements!I36-1 -> 0.079811063 | I28: =Statements!K36/Statements!J36-1 -> 0.07980693 | J28: =Statements!L36/Statements!K36-1 -> 0.11278658 | K28: =Statements!M36/Statements!L36-1 -> 0.13895812 | L28: =Statements!N36/Statements!M36-1 -> 0.16064318
B30: Finance costs | J30: =Statements!L38/Statements!K38-1 -> -0.15996076 | K30: =Statements!M38/Statements!L38-1 -> -0.16413873 | L30: =Statements!N38/Statements!M38-1 -> -0.14729329
B31: Other income/(expense), net | E31: - | F31: =Statements!H39/Statements!G39-1 -> 0.69161677 | G31: =Statements!I39/Statements!H39-1 -> -1.4761062 | H31: =Statements!J39/Statements!I39-1 -> -2.1933086 | I31: =Statements!K39/Statements!J39-1 -> -0.10833772 | J31: =Statements!L39/Statements!K39-1 -> 0.00048862218 | K31: =Statements!M39/Statements!L39-1 -> -0.36208325 | L31: =Statements!N39/Statements!M39-1 -> 1.0822307
B32: Income before provision for income taxes | E32: - | F32: =Statements!H40/Statements!G40-1 -> -0.045061837 | G32: =Statements!I40/Statements!H40-1 -> 0.085716044 | H32: =Statements!J40/Statements!I40-1 -> 0.074859295 | I32: =Statements!K40/Statements!J40-1 -> 0.056437933 | J32: =Statements!L40/Statements!K40-1 -> 0.1191666 | K32: =Statements!M40/Statements!L40-1 -> 0.14500289 | L32: =Statements!N40/Statements!M40-1 -> 0.16351134
B34: Provision for income taxes | E34: - | F34: =Statements!H42/Statements!G42-1 -> -0.13259067 | G34: =Statements!I42/Statements!H42-1 -> 0.77701452 | H34: =Statements!J42/Statements!I42-1 -> -0.30353961 | I34: =Statements!K42/Statements!J42-1 -> 0.0828318 | J34: =Statements!L42/Statements!K42-1 -> 0.1191666 | K34: =Statements!M42/Statements!L42-1 -> 0.14500289 | L34: =Statements!N42/Statements!M42-1 -> 0.16351134
B35: Net income | E35: - | F35: =Statements!H43/Statements!G43-1 -> -0.028135427 | G35: =Statements!I43/Statements!H43-1 -> -0.03359967 | H35: =Statements!J43/Statements!I43-1 -> 0.19495178 | I35: =Statements!K43/Statements!J43-1 -> 0.051555739 | J35: =Statements!L43/Statements!K43-1 -> 0.1191666 | K35: =Statements!M43/Statements!L43-1 -> 0.14500289 | L35: =Statements!N43/Statements!M43-1 -> 0.16351134
A37: # | B37: Income Statement (Common-size Analysis)
B39: Net sales:
B40: Products | E40: =Statements!G20/Statements!G$22 -> 0.80186799 | F40: =Statements!H20/Statements!H$22 -> 0.7777111 | G40: =Statements!I20/Statements!I$22 -> 0.75406549 | H40: =Statements!J20/Statements!J$22 -> 0.73770248 | I40: =Statements!K20/Statements!K$22 -> 0.7206077 | J40: =Statements!L20/Statements!L$22 -> 0.70018355 | K40: =Statements!M20/Statements!M$22 -> 0.67604294 | L40: =Statements!N20/Statements!N$22 -> 0.6478282
B41: Services | E41: =Statements!G21/Statements!G$22 -> 0.19813201 | F41: =Statements!H21/Statements!H$22 -> 0.2222889 | G41: =Statements!I21/Statements!I$22 -> 0.24593451 | H41: =Statements!J21/Statements!J$22 -> 0.26229752 | I41: =Statements!K21/Statements!K$22 -> 0.2793923 | J41: =Statements!L21/Statements!L$22 -> 0.29981645 | K41: =Statements!M21/Statements!M$22 -> 0.32395706 | L41: =Statements!N21/Statements!N$22 -> 0.3521718
B42: Total net sales | E42: =Statements!G22/Statements!G$22 -> 1 | F42: =Statements!H22/Statements!H$22 -> 1 | G42: =Statements!I22/Statements!I$22 -> 1 | H42: =Statements!J22/Statements!J$22 -> 1 | I42: =Statements!K22/Statements!K$22 -> 1 | J42: =Statements!L22/Statements!L$22 -> 1 | K42: =Statements!M22/Statements!M$22 -> 1 | L42: =Statements!N22/Statements!N$22 -> 1
B44: Cost of sales:
B45: Products | E45: =Statements!G25/Statements!G$22 -> 0.51092238 | F45: =Statements!H25/Statements!H$22 -> 0.4938414 | G45: =Statements!I25/Statements!I$22 -> 0.47369929 | H45: =Statements!J25/Statements!J$22 -> 0.46644448 | I45: =Statements!K25/Statements!K$22 -> 0.45876007 | J45: =Statements!L25/Statements!L$22 -> 0.44365728 | K45: =Statements!M25/Statements!M$22 -> 0.42160562 | L45: =Statements!N25/Statements!N$22 -> 0.39332615
B46: Services | E46: =Statements!G26/Statements!G$22 -> 0.055981315 | F46: =Statements!H26/Statements!H$22 -> 0.064847307 | G46: =Statements!I26/Statements!I$22 -> 0.064237217 | H46: =Statements!J26/Statements!J$22 -> 0.064503882 | I46: =Statements!K26/Statements!K$22 -> 0.065620496 | J46: =Statements!L26/Statements!L$22 -> 0.066163259 | K46: =Statements!M26/Statements!M$22 -> 0.067213509 | L46: =Statements!N26/Statements!N$22 -> 0.068738064
B47: Total cost of sales | E47: =Statements!G27/Statements!G$22 -> 0.56690369 | F47: =Statements!H27/Statements!H$22 -> 0.5586887 | G47: =Statements!I27/Statements!I$22 -> 0.5379365 | H47: =Statements!J27/Statements!J$22 -> 0.53094836 | I47: =Statements!K27/Statements!K$22 -> 0.52438057 | J47: =Statements!L27/Statements!L$22 -> 0.50982054 | K47: =Statements!M27/Statements!M$22 -> 0.48881913 | L47: =Statements!N27/Statements!N$22 -> 0.46206421
B49: Gross margin | E49: =Statements!G29/Statements!G$22 -> 0.43309631 | F49: =Statements!H29/Statements!H$22 -> 0.4413113 | G49: =Statements!I29/Statements!I$22 -> 0.4620635 | H49: =Statements!J29/Statements!J$22 -> 0.46905164 | I49: =Statements!K29/Statements!K$22 -> 0.47561943 | J49: =Statements!L29/Statements!L$22 -> 0.49017946 | K49: =Statements!M29/Statements!M$22 -> 0.51118087 | L49: =Statements!N29/Statements!N$22 -> 0.53793579
B51: Operating expenses:
B52: Research and development | E52: =Statements!G32/Statements!G$22 -> 0.066571484 | F52: =Statements!H32/Statements!H$22 -> 0.078048971 | G52: =Statements!I32/Statements!I$22 -> 0.080222998 | H52: =Statements!J32/Statements!J$22 -> 0.083020754 | I52: =Statements!K32/Statements!K$22 -> 0.085782434 | J52: =Statements!L32/Statements!L$22 -> 0.087897356 | K52: =Statements!M32/Statements!M$22 -> 0.089272091 | L52: =Statements!N32/Statements!N$22 -> 0.089802355
B53: Selling, general and administrative | E53: =Statements!G33/Statements!G$22 -> 0.063637378 | F53: =Statements!H33/Statements!H$22 -> 0.065048202 | G53: =Statements!I33/Statements!I$22 -> 0.066738272 | H53: =Statements!J33/Statements!J$22 -> 0.066322889 | I53: =Statements!K33/Statements!K$22 -> 0.065852684 | J53: =Statements!L33/Statements!L$22 -> 0.064763635 | K53: =Statements!M33/Statements!M$22 -> 0.063056016 | L53: =Statements!N33/Statements!N$22 -> 0.060732635
B54: Total operating expenses | E54: =Statements!G34/Statements!G$22 -> 0.13020886 | F54: =Statements!H34/Statements!H$22 -> 0.14309717 | G54: =Statements!I34/Statements!I$22 -> 0.14696127 | H54: =Statements!J34/Statements!J$22 -> 0.14934364 | I54: =Statements!K34/Statements!K$22 -> 0.15163512 | J54: =Statements!L34/Statements!L$22 -> 0.15266099 | K54: =Statements!M34/Statements!M$22 -> 0.15232811 | L54: =Statements!N34/Statements!N$22 -> 0.15053499
B56: Operating income (EBIT) | E56: =Statements!G36/Statements!G$22 -> 0.30288744 | F56: =Statements!H36/Statements!H$22 -> 0.29821412 | G56: =Statements!I36/Statements!I$22 -> 0.31510223 | H56: =Statements!J36/Statements!J$22 -> 0.319708 | I56: =Statements!K36/Statements!K$22 -> 0.32398431 | J56: =Statements!L36/Statements!L$22 -> 0.33751847 | K56: =Statements!M36/Statements!M$22 -> 0.35885277 | L56: =Statements!N36/Statements!N$22 -> 0.3874008
B58: Finance costs | E58: - | F58: - | G58: - | H58: - | I58: =Statements!K38/Statements!K$22 -> -0.0071308913 | J58: =Statements!L38/Statements!L$22 -> -0.0056079621 | K58: =Statements!M38/Statements!M$22 -> -0.0043757275 | L58: =Statements!N38/Statements!N$22 -> -0.0034705271
B59: Other income/(expense), net | E59: =Statements!G39/Statements!G$22 -> -0.00084701061 | F59: =Statements!H39/Statements!H$22 -> -0.0014740989 | G59: =Statements!I39/Statements!I$22 -> 0.00068791796 | H59: =Statements!J39/Statements!J$22 -> -0.00077133609 | I59: =Statements!K39/Statements!K$22 -> -0.00064545864 | J59: =Statements!L39/Statements!L$22 -> -0.00060456396 | K59: =Statements!M39/Statements!M$22 -> -0.00036001223 | L59: =Statements!N39/Statements!N$22 -> -0.00069725493
B60: Income before provision for income taxes | E60: =Statements!G40/Statements!G$22 -> 0.30204043 | F60: =Statements!H40/Statements!H$22 -> 0.29674002 | G60: =Statements!I40/Statements!I$22 -> 0.31579015 | H60: =Statements!J40/Statements!J$22 -> 0.31893666 | I60: =Statements!K40/Statements!K$22 -> 0.31620796 | J60: =Statements!L40/Statements!L$22 -> 0.33130594 | K60: =Statements!M40/Statements!M$22 -> 0.35411703 | L60: =Statements!N40/Statements!N$22 -> 0.38323302
B62: Provision for income taxes | E62: =Statements!G42/Statements!G$22 -> 0.048944026 | F62: =Statements!H42/Statements!H$22 -> 0.043677681 | G62: =Statements!I42/Statements!I$22 -> 0.076077589 | H62: =Statements!J42/Statements!J$22 -> 0.04978602 | I62: =Statements!K42/Statements!K$22 -> 0.050593274 | J62: =Statements!L42/Statements!L$22 -> 0.053008951 | K62: =Statements!M42/Statements!M$22 -> 0.056658724 | L62: =Statements!N42/Statements!N$22 -> 0.061317283
B63: Net income | E63: =Statements!G43/Statements!G$22 -> 0.25309641 | F63: =Statements!H43/Statements!H$22 -> 0.25306234 | G63: =Statements!I43/Statements!I$22 -> 0.23971256 | H63: =Statements!J43/Statements!J$22 -> 0.26915064 | I63: =Statements!K43/Statements!K$22 -> 0.26561469 | J63: =Statements!L43/Statements!L$22 -> 0.27829699 | K63: =Statements!M43/Statements!M$22 -> 0.2974583 | L63: =Statements!N43/Statements!N$22 -> 0.32191574
