Workbook

Sheet Overview
D2: Valuation & Analysis of Choice Hotels International Inc. (NYSE: CHH)
D4: Overview
D16: Comparable Company Analysis
D18: Universe of Comparable Companies
D20: Sector: | E20: Consumer Discretionary
D21: Industry: | E21: Hotels, Resorts & Cruise Lines (Hospitality / Lodging – Asset-light franchising model)
D22: Geography: | E22: Primarily United States (core revenue concentration), with operations in 50+ countries and territories through direct and master franchising
D23: Products: | E23: Hotel franchising services under multiple brands (economy to upscale), reservation systems, loyalty programs, and ancillary services via travel and vendor partnerships
D24: Customers: | E24: Franchisees (hotel owners, developers, operators), End consumers (business and leisure travelers across price segments)
D25: Competitors: | E25: Marriott International, Airbnb Inc, Hilton Worldwide Holdings, Wyndham Hotels & Resorts Inc, Hyatt Hotels Corporation
D26: Distribution Channel: | E26: Primarily B2B (franchise agreements with hotel owners) supported by B2C channels including direct bookings via brand websites, mobile apps, central reservation systems,
E27: and third-party travel platforms (OTAs)
D28: End Markets: | E28: Business travel, Leisure travel, Budget to midscale lodging segments, Extended stay and select upscale segments
D30: ($ in millions)
D31: List of Comparable Companies
G32: Equity | H32: Enterprise | I32: LTM | J32: LTM
D33: Company | E33: Ticker | F33: Sector | G33: Value | H33: Value | I33: Sales | J33: EBITDA
D34: Marriot International Inc | E34: MAR | F34: Consumer Discretionary | G34: =MAR!H25 -> 96703.864 | H34: =MAR!H31 -> 112549.86 | I34: =MAR!R11 -> 26186 | J34: =MAR!R41 -> 4695
D35: Airbnb Inc CI A | E35: ABNB | F35: Consumer Discretionary | G35: =ABNB!H25 -> 83701.62 | H35: =ABNB!H31 -> 79140.62 | I35: =ABNB!R11 -> 12241 | J35: =ABNB!R42 -> 4297
D36: Hilton Worldwide Holdings Inc. | E36: HLT | F36: Consumer Discretionary | G36: =HLT!H25 -> 78279.057 | H36: =HLT!H31 -> 89714.057 | I36: =HLT!R11 -> 12039 | J36: =HLT!R41 -> 3538
D37: Hyatt Hotels Corporation | E37: H | F37: Consumer Discretionary | G37: =H!H25 -> 16017.976 | H37: =H!H31 -> 19832.976 | I37: =H!R11 -> 7101 | J37: =H!R41 -> 1159
D38: Wyndham Hotels & Resorts Inc | E38: WH | F38: Consumer Discretionary | G38: =WH!H25 -> 6773.941 | H38: =WH!H31 -> 9269.941 | I38: =WH!R11 -> 1429 | J38: =WH!R42 -> 718

Sheet Comps_Sum
D2: Public Market Comparable Valuation — Choice Hotels International Inc. (NYSE: CHH)
D3: Peer Trading Multiples & Implied Equity Value Assessment
E5: Valuation Date | G5: Prepared By | I5: Fiscal Year End | K5: Currency | M5: Projection Period
E6: 04/17/2026 | G6: Eldric Sequeira | I6: 12/31/2025 | K6: USD (millions) | M6: 5 Years ('FY26 - 'FY30)
D8: 1 · Valuation Snapshot
D10: Implied Share Price | F10: Implied EV Range | H10: EV/EBITDA | J10: EV/Revenue | L10: P/E | N10: Current Price
D11: =L64 -> 190.96784 | F11: $ 8,076.9 - $ 15,863.5 | H11: 18.4x | J11: 6.5x | L11: 28.0x | N11: =116.7 -> 116.7
D13: 2 · Peer Universe & Selection Criteria
D14: Screening criteria applied | J14: Target company profile
D15: Sector / Industry | H15: Consumer Discretionary | J15: LTM Revenue | M15: =CHH!R11 -> 1596.793
D16: Market Cap Range | F16: =CompsVal!M10 -> 6170.8628 | G16: - | H16: =CompsVal!O10 -> 13957.392 | J16: LTM EBITDA | M16: =DCF!H18 -> 508.114
D17: Revenue Range | F17: =WH!R11 -> 1429 | G17: - | H17: =ABNB!R11 -> 12241 | J17: EBITDA Margin (LTM) | M17: =DCF!H19 -> 0.31820906
D18: Geography | H18: North America | J18: Revenue Growth (YoY) | M18: =DCF!H9 -> 0.007542722
J19: Net Debt | M19: =CHH!H27 -> 1906.122
J20: Shares Outstanding | M20: =CHH!H24 -> 46.203843
J21: Current Market Cap | M21: =CHH!H25 -> 5390.1403
D23: 3 · Comparable Companies — Trading Multiples
D24: Company | G24: Mkt Cap | H24: EV | I24: EV / Rev | J24: EV / EBITDA | K24: EV / EBIT | L24: P/E | M24: Rev Growth | N24: EBITDA Mg.
D25: =Comps2!D11 -> Marriott International Inc. | G25: =Comps2!H11 -> 96703.864 | H25: =Comps2!I11 -> 112549.86 | I25: =Comps1!J12 -> 4.298093 | J25: =Comps1!M12 -> 23.972282 | K25: =Comps1!P12 -> 27.120449 | L25: =Comps1!U12 -> 9.5065789 | M25: =MAR!E64 -> 0.043266932 | N25: =MAR!R42 -> 0.17929428
D26: =Comps2!D12 -> Airbnb Inc. Cl A | G26: =Comps2!H12 -> 83701.62 | H26: =Comps2!I12 -> 79140.62 | I26: =Comps1!J13 -> 6.4652087 | J26: =Comps1!M13 -> 18.417645 | K26: =Comps1!P13 -> 31.108734 | L26: =Comps1!U13 -> 22.269394 | M26: =ABNB!E64 -> 0.10259413 | N26: =ABNB!R43 -> 0.35103341
D27: =Comps2!D13 -> Hilton Worldwide Holdings Inc. | G27: =Comps2!H13 -> 78279.057 | H27: =Comps2!I13 -> 89714.057 | I27: =Comps1!J14 -> 7.4519526 | J27: =Comps1!M14 -> 25.35728 | K27: =Comps1!P14 -> 33.313798 | L27: =Comps1!U14 -> 53.579094 | M27: =HLT!E64 -> 0.077411849 | N27: =HLT!R42 -> 0.29387823
D28: =Comps2!D14 -> Hyatt Hotels Corporation | G28: =Comps2!H14 -> 16017.976 | H28: =Comps2!I14 -> 19832.976 | I28: =Comps1!J15 -> 2.7929835 | J28: =Comps1!M15 -> 17.112145 | K28: =Comps1!P15 -> 56.991311 | L28: =Comps1!U15 -> -308.038 | M28: =H!E64 -> 0.068140794 | N28: =H!R42 -> 0.16321645
D29: =Comps2!D15 -> Wyndham Hotels & Resorts Inc. | G29: =Comps2!H15 -> 6773.941 | H29: =Comps2!I15 -> 9269.941 | I29: =Comps1!J16 -> 6.4870126 | J29: =Comps1!M16 -> 12.910781 | K29: =Comps1!P16 -> 14.131008 | L29: =Comps1!U16 -> 28.845322 | M29: =WH!E64 -> 0.014914773 | N29: =WH!R43 -> 0.50244927
D31: Min | I31: =MIN(I$25:I$29) -> 2.7929835 | J31: =MIN(J$25:J$29) -> 12.910781 | K31: =MIN(K$25:K$29) -> 14.131008 | L31: =MIN(L$25:L$29) -> -308.038 | M31: =MIN(M$25:M$29) -> 0.014914773 | N31: =MIN(N$25:N$29) -> 0.16321645
D32: 25th Percentile | I32: =PERCENTILE(I$25:I$29,25%) -> 4.298093 | J32: =PERCENTILE(J$25:J$29,25%) -> 17.112145 | K32: =PERCENTILE(K$25:K$29,25%) -> 27.120449 | L32: =PERCENTILE(L$25:L$29,25%) -> 9.5065789 | M32: =PERCENTILE(M$25:M$29,25%) -> 0.043266932 | N32: =PERCENTILE(N$25:N$29,25%) -> 0.17929428
D33: Median | I33: =MEDIAN(I$25:I$29) -> 6.4652087 | J33: =MEDIAN(J$25:J$29) -> 18.417645 | K33: =MEDIAN(K$25:K$29) -> 31.108734 | L33: =MEDIAN(L$25:L$29) -> 22.269394 | M33: =MEDIAN(M$25:M$29) -> 0.068140794 | N33: =MEDIAN(N$25:N$29) -> 0.29387823
D34: Mean | I34: =AVERAGE(I$25:I$29) -> 5.4990501 | J34: =AVERAGE(J$25:J$29) -> 19.554027 | K34: =AVERAGE(K$25:K$29) -> 32.53306 | L34: =AVERAGE(L$25:L$29) -> -38.767523 | M34: =AVERAGE(M$25:M$29) -> 0.061265695 | N34: =AVERAGE(N$25:N$29) -> 0.29797433
D35: 75th Percentile | I35: =PERCENTILE(I$25:I$29,75%) -> 6.4870126 | J35: =PERCENTILE(J$25:J$29,75%) -> 23.972282 | K35: =PERCENTILE(K$25:K$29,75%) -> 33.313798 | L35: =PERCENTILE(L$25:L$29,75%) -> 28.845322 | M35: =PERCENTILE(M$25:M$29,75%) -> 0.077411849 | N35: =PERCENTILE(N$25:N$29,75%) -> 0.35103341
D36: Max | I36: =MAX(I$25:I$29) -> 7.4519526 | J36: =MAX(J$25:J$29) -> 25.35728 | K36: =MAX(K$25:K$29) -> 56.991311 | L36: =MAX(L$25:L$29) -> 53.579094 | M36: =MAX(M$25:M$29) -> 0.10259413 | N36: =MAX(N$25:N$29) -> 0.50244927
D38: 4 · Forward Multiple Benchmarking
D39: Company | G39: Revenue | H39: EBITDA | I39: EV / Rev | J39: EV / EBITDA | K39: EV / EBIT | L39: P/E | M39: PEG Ratio
D40: =D25 -> Marriott International Inc. | G40: =MAR!F37 -> 27901 | H40: =MAR!F39 -> 5900 | I40: =Comps1!K12 -> 4.0339007 | J40: =Comps1!N12 -> 19.076248 | K40: =Comps1!Q12 -> 22.769546 | L40: =Comps1!V12 -> 11.310405 | M40: =Comps2!O11/Comps2!Q11/100 -> 5.3634977
D41: =D26 -> Airbnb Inc. Cl A | G41: =ABNB!F37 -> 13697 | H41: =ABNB!F39 -> 4812 | I41: =Comps1!K13 -> 5.7779528 | J41: =Comps1!N13 -> 16.446513 | K41: =Comps1!Q13 -> 26.424247 | L41: =Comps1!V13 -> 27.956453 | M41: =Comps2!O12/Comps2!Q12/100 -> 2.3297044
D42: =D27 -> Hilton Worldwide Holdings Inc. | G42: =HLT!F37 -> 13095 | H42: =HLT!F39 -> 4032 | I42: =Comps1!K14 -> 6.8510162 | J42: =Comps1!N14 -> 22.25051 | K42: =Comps1!Q14 -> 25.936414 | L42: =Comps1!V14 -> 37.580682 | M42: =Comps2!O13/Comps2!Q13/100 -> 2.5917712
D43: =D28 -> Hyatt Hotels Corporation | G43: =H!F37 -> 7195 | H43: =H!F39 -> 1179 | I43: =Comps1!K15 -> 2.7564943 | J43: =Comps1!N15 -> 16.821863 | K43: =Comps1!Q15 -> 30.758338 | L43: =Comps1!V15 -> 57.216495 | M43: =Comps2!O14/Comps2!Q14/100 -> 8.173785
D44: =D29 -> Wyndham Hotels & Resorts Inc. | G44: =WH!F37 -> 1481 | H44: =WH!F39 -> 741.1 | I44: =Comps1!K16 -> 6.2592444 | J44: =Comps1!N16 -> 12.508354 | K44: =Comps1!Q16 -> 15.296932 | L44: =Comps1!V16 -> 19.169565 | M44: =Comps2!O15/Comps2!Q15/100 -> 2.3961957
D46: Median | I46: =MEDIAN(I40:I44) -> 5.7779528 | J46: =MEDIAN(J40:J44) -> 16.821863 | K46: =MEDIAN(K40:K44) -> 25.936414 | L46: =MEDIAN(L40:L44) -> 27.956453 | M46: =MEDIAN(M40:M44) -> 2.5917712
D48: 5 · Implied Enterprise & Equity Value (USD Millions)
D49: Metric Used | E49: Subject Metric | G49: Peer Low | H49: Peer Median | I49: Peer High | J49: Implied EV (Low) | L49: Implied EV (Mid) | N49: Implied EV (High)
D50: LTM Sales | E50: =DCF!H8 -> 1596.793 | G50: =Comps1!J22 -> 2.7929835 | H50: =Comps1!J19 -> 6.4652087 | I50: =Comps1!J21 -> 7.4519526 | J50: =G50*E50 -> 4459.8166 | L50: =H50*E50 -> 10323.6 | N50: =I50*E50 -> 11899.226
D51: LTM EBITDA | E51: =DCF!H18 -> 508.114 | G51: =Comps1!M22 -> 12.910781 | H51: =Comps1!M19 -> 18.417645 | I51: =Comps1!M21 -> 25.35728 | J51: =G51*E51 -> 6560.1487 | L51: =H51*E51 -> 9358.2632 | N51: =I51*E51 -> 12884.389
D52: LTM EBIT | E52: =DCF!H22 -> 448.399 | G52: =Comps1!P22 -> 14.131008 | H52: =Comps1!P19 -> 31.108734 | I52: =Comps1!P21 -> 56.991311 | J52: =G52*E52 -> 6336.3297 | L52: =H52*E52 -> 13949.125 | N52: =I52*E52 -> 25554.847
D53: NTM Sales | E53: =CHH!F37 -> 1613 | G53: =Comps1!K22 -> 2.7564943 | H53: =Comps1!K19 -> 5.7779528 | I53: =Comps1!K21 -> 6.8510162 | J53: =G53*E53 -> 4446.2252 | L53: =H53*E53 -> 9319.8379 | N53: =I53*E53 -> 11050.689
D54: NTM EBITDA | E54: =CHH!F39 -> 635.9 | G54: =Comps1!N22 -> 12.508354 | H54: =Comps1!N19 -> 16.821863 | I54: =Comps1!N21 -> 22.25051 | J54: =G54*E54 -> 7954.0622 | L54: =H54*E54 -> 10697.023 | N54: =I54*E54 -> 14149.099
D55: Blended | J55: =AVERAGE(J50:K54) -> 5951.3165 | L55: =AVERAGE(L50:M54) -> 10729.57 | N55: =AVERAGE(N50:O54) -> 15107.65
D56: Implied EV
D58: Equity Value per Share | J58: Low | L58: Mid (Base) | N58: High
D59: Implied Enterprise Value | J59: =J55 -> 5951.3165 | L59: =L55 -> 10729.57 | N59: =N55 -> 15107.65
D60: Less: Net Debt | J60: =DCF!$K$40 -> -1906.122 | L60: =DCF!$K$40 -> -1906.122 | N60: =DCF!$K$40 -> -1906.122
D61: Less: Minority Interest | J61: =DCF!$K$42 -> 0 | L61: =DCF!$K$42 -> 0 | N61: =DCF!$K$42 -> 0
D62: Implied Equity Value | J62: =SUM(J59:K61) -> 4045.1945 | L62: =SUM(L59:M61) -> 8823.4478 | N62: =SUM(N59:O61) -> 13201.528
D63: Diluted Shares Outstanding | J63: =DCF!$K$47 -> 46.203843 | L63: =DCF!$K$47 -> 46.203843 | N63: =DCF!$K$47 -> 46.203843
D64: Implied Price per Share | J64: =J62/J63 -> 87.55104 | L64: =L62/L63 -> 190.96784 | N64: =N62/N63 -> 285.7236
D66: 7 · Football Field — Implied Share Price Range (USD)
D82: 8 · Valuation Conclusion
D83: Comps-Implied Equity Value Range — Choice Hotels International Inc.
D85: Low Case | E85: → | F85: Base Case | G85: → | H85: High Case
D86: =J64 -> 87.55104 | F86: =L64 -> 190.96784 | H86: =N64 -> 285.7236

Sheet DCF_Sum
D2: DCF Valuation Summary — Choice Hotels International Inc. (NYSE: CHH)
D3: Intrinsic Value Assessment & Equity Valuation Report
E5: Valuation Date | G5: Prepared By | I5: Fiscal Year End | K5: Currency | M5: Projection Period
E6: 04/17/2026 | G6: Eldric Sequeira | I6: 12/31/2025 | K6: USD (millions) | M6: 5 Years ('FY26 - 'FY30)
D8: 1 · Valuation Snapshot
D10: Intrinsic Value per Share | F10: Enterprise Value (EV) | H10: Equity Value | J10: Shares Outstanding | L10: WACC | N10: Terminal Growth Rate
D11: =DCF!K49 -> 148.27396 | F11: =DCF!F49 -> 8711.9516 | H11: =DCF!K45 -> 6850.8266 | J11: =DCF!K47 -> 46.203843 | L11: =DCF!E32 -> 0.078407245 | N11: =DCF!P43 -> 0.03
D13: 2 · Key Assumptions
D14: Operating Assumptions | I14: WACC Components
D15: Revenue CAGR ('FY26 - 'FY30) | G15: =DCF!O8 -> 0.034747978 | I15: Risk-Free Rate | L15: =WACC!F20 -> 0.04261
D16: EBITDA Margin | G16: =DCF!J19 -> 0.31820906 | I16: Equity Risk Premium | L16: =WACC!F21 -> 0.0423
D17: Dep. & Amort. % of Revenue | G17: =Historical!I16 -> 0.037396832 | I17: Beta (Levered) | L17: =WACC!F22 -> 0.94879003
D18: Capex % of Revenue | G18: =Historical!I33 -> 0.024376359 | I18: Cost of Equity (Ke) | L18: =WACC!F24 -> 0.085043818
D19: Change in NWC % of Revenue | G19: =DCF!J29/DCF!J8 -> 0.002405394 | I19: Pre-Tax Cost of Debt (Kd) | L19: =WACC!F14 -> 0.051
D20: Effective Tax Rate | G20: =Historical!I19 -> 0.2 | I20: Debt / Total Capital | L20: =Historical!I96/(Historical!I96+Historical!I111) -> 0.75116644
D22: 3 · Revenue & EBITDA Projections (USD Millions)
D23: Metric | F23: 2026E | G23: 2027E | H23: 2028E | I23: 2029E | J23: 2030E
D24: Revenue | F24: =DCF!J8 -> 1620.7449 | G24: =DCF!K8 -> 1674.2295 | H24: =DCF!L8 -> 1729.479 | I24: =DCF!M8 -> 1795.1993 | J24: =DCF!N8 -> 1858.0312
D25: YoY Growth (%) | F25: =DCF!J9 -> 0.015 | G25: =DCF!K9 -> 0.033 | H25: =DCF!L9 -> 0.033 | I25: =DCF!M9 -> 0.038 | J25: =DCF!N9 -> 0.035
D26: Gross Profit | F26: =DCF!J12 -> 849.62808 | G26: =DCF!K12 -> 877.66581 | H26: =DCF!L12 -> 906.62878 | I26: =DCF!M12 -> 941.08067 | J26: =DCF!N12 -> 974.0185
D27: Gross Margin (%) | F27: =DCF!J13 -> 0.52422073 | G27: =DCF!K13 -> 0.52422073 | H27: =DCF!L13 -> 0.52422073 | I27: =DCF!M13 -> 0.52422073 | J27: =DCF!N13 -> 0.52422073
D28: EBITDA | F28: =DCF!J18 -> 515.73571 | G28: =DCF!K18 -> 532.75499 | H28: =DCF!L18 -> 550.3359 | I28: =DCF!M18 -> 571.24867 | J28: =DCF!N18 -> 591.24237
D29: EBITDA Margin (%) | F29: =DCF!J19 -> 0.31820906 | G29: =DCF!K19 -> 0.31820906 | H29: =DCF!L19 -> 0.31820906 | I29: =DCF!M19 -> 0.31820906 | J29: =DCF!N19 -> 0.31820906
D30: EBIT (NOPAT adj.) | F30: =DCF!J22 -> 455.12498 | G30: =DCF!K22 -> 470.14411 | H30: =DCF!L22 -> 485.65887 | I30: =DCF!M22 -> 504.1139 | J30: =DCF!N22 -> 521.75789
D32: 4 · Unlevered Free Cash Flow Forecast (USD Millions)
D33: Metric | F33: 2026E | G33: 2027E | H33: 2028E | I33: 2029E | J33: 2030E
D34: EBIT | F34: =DCF!J22 -> 455.12498 | G34: =DCF!K22 -> 470.14411 | H34: =DCF!L22 -> 485.65887 | I34: =DCF!M22 -> 504.1139 | J34: =DCF!N22 -> 521.75789
D35: Less: Taxes on EBIT | F35: =-DCF!J24 -> -108.46587 | G35: =-DCF!K24 -> -109.35816 | H35: =-DCF!L24 -> -111.08533 | I35: =-DCF!M24 -> -112.90755 | J35: =-DCF!N24 -> 0
D36: NOPAT | F36: =DCF!J25 -> 346.65911 | G36: =DCF!K25 -> 360.78595 | H36: =DCF!L25 -> 374.57353 | I36: =DCF!M25 -> 391.20636 | J36: =DCF!N25 -> 521.75789
D37: Add: Dep. & Amort. | F37: =DCF!J27 -> 60.610725 | G37: =DCF!K27 -> 62.610879 | H37: =DCF!L27 -> 64.677038 | I37: =DCF!M27 -> 67.134765 | J37: =DCF!N27 -> 69.484482
D38: Less: Capex | F38: =DCF!J28 -> -39.50786 | G38: =DCF!K28 -> -40.811619 | H38: =DCF!L28 -> -42.158403 | I38: =DCF!M28 -> -43.760422 | J38: =DCF!N28 -> -45.292037
D39: Inc/Dec in NWC | F39: =DCF!J29 -> 3.89853 | G39: =DCF!K29 -> 8.7054175 | H39: =DCF!L29 -> 8.9926963 | I39: =DCF!M29 -> 10.696948 | J39: =DCF!N29 -> 10.226846
D40: Unlevered FCF | F40: =DCF!J31 -> 371.66051 | G40: =DCF!K31 -> 391.29062 | H40: =DCF!L31 -> 406.08486 | I40: =DCF!M31 -> 425.27765 | J40: =DCF!N31 -> 556.17718
D41: Discount Factor | F41: =DCF!J34 -> 0.96296078 | G41: =DCF!K34 -> 0.89294725 | H41: =DCF!L34 -> 0.82802416 | I41: =DCF!M34 -> 0.7678214 | J41: =DCF!N34 -> 0.71199577
D42: Present Value of FCF | F42: =DCF!J35 -> 357.89449 | G42: =DCF!K35 -> 349.40189 | H42: =DCF!L35 -> 336.24808 | I42: =DCF!M35 -> 326.53728 | J42: =DCF!N35 -> 395.9958
D44: 5 · NPV & Terminal Value Build (USD Millions)
D58: Bridge to Equity Value | G58: Amount (USD M)
D59: Enterprise Value | G59: =DCF!K39 -> 8711.9516
D60: Less: Total Debt | G60: =DCF!K40 -> -1906.122
D61: Less: Preferred Stock | G61: =DCF!K40 -> -1906.122
D62: Less: Minority Interest | G62: =DCF!K41 -> 0
D63: Add: Cash & Cash Equivalents | G63: =DCF!K43 -> 44.997
D64: Equity Value | G64: =DCF!K45 -> 6850.8266
D65: Diluted Shares Outstanding | G65: =DCF!K47 -> 46.203843
D66: Intrinsic Value per Share | G66: =DCF!K49 -> 148.27396
D68: 6 · Sensitivity Analysis — Equity Value per Share (USD)
D69: Choice Hotels International Inc. Sensitivity Analysis - Terminal Growth Rate
F70: Discount Rate
E71: =DCF!K49 -> 148.27396 | F71: 0.05 | G71: 0.06 | H71: 0.07 | I71: 0.08 | J71: 0.09 | K71: 0.1 | L71: 0.11
D72: Implied Perpetuity Growth Rate | E72: 0.015 | F72: 257.36133 | G72: 189.54952 | H72: 146.47725 | I72: 116.72263 | J72: 94.955617 | K72: 78.354595 | L72: 65.286127
E73: 0.02 | F73: 302.69377 | G73: 215.13054 | H73: 162.67986 | I73: 127.78156 | J73: 102.91004 | K73: 84.302686 | L73: 69.86928
E74: 0.025 | F74: 366.15919 | G74: 248.02042 | H74: 182.48306 | I74: 140.85121 | J74: 112.08823 | K74: 91.043856 | L74: 74.991628
E75: 0.03 | F75: 461.35731 | G75: 291.87361 | H75: 207.23704 | I75: 156.53478 | J75: 122.79611 | K75: 98.74805 | L75: 80.754269
E76: 0.035 | F76: 620.02085 | G76: 353.26806 | H76: 239.0636 | I76: 175.7036 | J76: 135.45088 | K76: 107.63751 | L76: 87.285263
E77: 0.04 | F77: 937.34792 | G77: 445.35974 | H77: 281.49901 | I77: 199.66462 | J77: 150.6366 | K77: 118.00854 | L77: 94.749256
E78: 0.045 | F78: 1889.3291 | G78: 598.84588 | H78: 340.90859 | I78: 230.47164 | J78: 169.19693 | K78: 130.26521 | L78: 103.36155
D80: Choice Hotels International Inc. Sensitivity Analysis - Terminal Growth Rate
F81: Discount Rate
E82: =DCF!K60 -> 140.19604 | F82: 0.05 | G82: 0.06 | H82: 0.07 | I82: 0.08 | J82: 0.09 | K82: 0.1 | L82: 0.11
D83: Implied Perpetuity Growth Rate | E83: 0.015 | F83: 130.4305 | G83: 123.90765 | H83: 117.70626 | I83: 111.80755 | J83: 106.19398 | K83: 100.84919 | L83: 95.757903
E84: 0.02 | F84: 134.96375 | G84: 128.25159 | H84: 121.87048 | I84: 115.80105 | J84: 110.02524 | K84: 104.5262 | L84: 99.28817
E85: 0.025 | F85: 139.49699 | G85: 132.59554 | H85: 126.0347 | I85: 119.79455 | J85: 113.8565 | K85: 108.2032 | L85: 102.81844
E86: 0.03 | F86: 144.03024 | G86: 136.93949 | H86: 130.19893 | I86: 123.78806 | J86: 117.68776 | K86: 111.8802 | L86: 106.3487
E87: 0.035 | F87: 148.56348 | G87: 141.28344 | H87: 134.36315 | I87: 127.78156 | J87: 121.51902 | K87: 115.5572 | L87: 109.87897
E88: 0.04 | F88: 153.09672 | G88: 145.62738 | H88: 138.52737 | I88: 131.77506 | J88: 125.35028 | K88: 119.2342 | L88: 113.40924
E89: 0.045 | F89: 157.62997 | G89: 149.97133 | H89: 142.69159 | I89: 135.76857 | J89: 129.18154 | K89: 122.91121 | L89: 116.9395
D91: 7 · Scenario Analysis
D92: Scenario | E92: Rev. CAGR | F92: EBITDA Margin | H92: WACC | I92: TGR | J92: EV ($M) | L92: Share Value
D93: Bull Case | E93: 0.040998318 | F93: 0.28081223 | H93: 0.078407245 | I93: 0.03 | J93: 8952.661 | L93: 153.48368
D94: Base Case | E94: 0.034747978 | F94: 0.28081223 | H94: 0.078407245 | I94: 0.03 | J94: 8711.9516 | L94: 148.27396
D95: Bear Case | E95: 0.024747714 | F95: 0.28081223 | H95: 0.078407245 | I95: 0.03 | J95: 8367.0336 | L95: 140.80882
D97: 8 · Valuation Conclusion
D98: Intrinsic Value Range — Base Case DCF
D100: Bear Case | E100: → | F100: Base Case | G100: → | H100: Bull Case
D101: =L95 -> 140.80882 | F101: =L94 -> 148.27396 | H101: =L93 -> 153.48368

Sheet Comps Analysis->

Sheet CHH
D2: Choice Hotels International Inc. (NYSE: CHH)
D3: Input Page
D4: ($ in millions, except per share data)
D7: General Information | J7: Reported Income Statement | T7: Balance Sheet Data
D8: Company Name | H8: Choice Hotels International Inc. | P8: Prior Stub 12/31/2025 | Q8: Current Stub 12/31/2025 | R8: LTM 12/31/2025 | W8: 2025A | X8: -
D9: Ticker | H9: CHH | M9: Fiscal Year Ending December 31, | T9: Cash & Cash Equivalents | W9: 44.997
D10: Stock Exchange | H10: NYSE | M10: 2023A | N10: 2024A | O10: 2025A | T10: Accounts Receivables | W10: =207.491+94.686 -> 302.177
D11: Fisical Year Ending | H11: 12/31/2025 | J11: Sales | M11: 1544.165 | N11: 1584.839 | O11: 1596.793 | R11: =O11 -> 1596.793 | T11: Income Tax receivables | W11: 13.456
D12: Moody's Corporate Rating | H12: Baa2 | J12: COGS (incl. D&A) | M12: =1165.401-312.701 -> 852.7 | N12: =1121.066-312.388 -> 808.678 | O12: =1148.394-328.958 -> 819.436 | R12: =O12 -> 819.436 | T12: Prepaids & Other Current Assets | W12: 45.368
D13: S&P Corporate Rating | H13: BBB- | J13: Gross Profit | M13: =M11-M12 -> 691.465 | N13: =N11-N12 -> 776.161 | O13: =O11-O12 -> 777.357 | R13: =O13 -> 777.357 | T13: Total Current Assets | W13: =SUM(W9:W12) -> 405.998
D14: Predicted Beta | H14: 0.84 | J14: SG&A | M14: 312.701 | N14: 312.388 | O14: 328.958 | R14: =O14 -> 328.958
D15: Marginal Tax | H15: 0.2 | J15: EBIT | M15: =M13-M14 -> 378.764 | N15: =N13-N14 -> 463.773 | O15: =O13-O14 -> 448.399 | R15: =O15 -> 448.399 | T15: Property, Plant & Equivalent, net | W15: 649.291
J16: Interest Expense | M16: =63.78-7.764 -> 56.016 | N16: =87.131-8.646 -> 78.485 | O16: =91.148-6.237 -> 84.911 | R16: =O16 -> 84.911 | T16: Goodwill & Intangible Assets | W16: =77.67+305.758+1082.486 -> 1465.914
D17: Selected Market Data | J17: Other income/(expenses), net | M17: =-4.416-10.649-2.879 -> -17.944 | N17: =0.331+1.641-12.329 -> -10.357 | O17: =-100.025-0.713-6.989+14.324 -> -93.403 | R17: =O17 -> -93.403 | T17: Other Assets | W17: =12.49+50.227+134.975+75.371+123.937 -> 397
D18: Current Price | H18: 116.66 | J18: Pre-tax Income | M18: =M15-M16-M17 -> 340.692 | N18: =N15-N16-N17 -> 395.645 | O18: =O15-O16-O17 -> 456.891 | R18: =O18 -> 456.891 | T18: Total Assets | W18: =SUM(W15:W17)+W13 -> 2918.203
D19: % of 52-week High | H19: =H18/H20 -> 0.85496519 | J19: Income Taxes | M19: -78.449 | N19: -95.98 | O19: -86.945 | R19: =O19 -> -86.945
D20: 52-week High Price | H20: 136.45 | J20: Non-controlling Interest | M20: 0 | N20: 0 | O20: 0 | R20: =O20 -> 0 | T20: Liability for guest loyalty program | W20: 85.035
D21: 52-week Low Price | H21: 84.04 | J21: Preferred Dividends | M21: 0 | N21: 0 | O21: 0 | R21: =O21 -> 0 | T21: Accounts Payable | W21: 156.276
D22: Dividend Per Share | H22: 1.15 | J22: Net Income | M22: =SUM(M18:M21) -> 262.243 | N22: =SUM(N18:N21) -> 299.665 | O22: =SUM(O18:O21) -> 369.946 | R22: =O22 -> 369.946 | T22: Accrued Liabilities | W22: 125.282
J23: Effective Tax Rate | M23: =ABS(M19/M18) -> 0.2302637 | N23: =ABS(N19/N18) -> 0.24259121 | O23: =ABS(O19/O18) -> 0.19029703 | R23: =O23 -> 0.19029703 | T23: Deferred revenue | W23: 100.698
D24: Fully Diluted Shares Outstanding | H24: =X44 -> 46.203843 | T24: Total Current Liabilities | W24: =SUM(W20:W23) -> 467.291
D25: Equity Value | H25: =H24*H18 -> 5390.1403 | J25: Weighted Avg. Diluted Shares | M25: 50.7 | N25: 48.078 | O25: =H24 -> 46.203843 | R25: =O25 -> 46.203843
J26: Diluted EPS | M26: =M22/M25 -> 5.1724458 | N26: =N22/N25 -> 6.2328924 | O26: =O22/O25 -> 8.0068232 | R26: =O26 -> 8.0068232 | T26: Total Debt | W26: 1906.122
D27: Plus: Total Debt | H27: =W26 -> 1906.122 | T27: Other Long-term Liabilities | W27: =130.505+56.532+25.303+107.963+39.771+3.487 -> 363.561
D28: Plus: Preferred Stock | H28: =+W31 -> 0 | J28: Adjusted Income Statement | T28: Total Liabilities | W28: =SUM(W26:W27)+W24 -> 2736.974
D29: Plus: Non-controlling Intererst | H29: =+W30 -> 0 | J29: Reported Gross Profit | M29: =M13 -> 691.465 | N29: =N13 -> 776.161 | O29: =O13 -> 777.357 | R29: =O29 -> 777.357
D30: Less: Cash & Cash Equivalents | H30: =-W9 -> -44.997 | J30: Non-recurring items in COGS | M30: 0 | N30: 0 | O30: 0 | R30: =O30 -> 0 | T30: Non-Controlling Interest | W30: 0
D31: Enterprise Value | H31: =SUM(H25:H30) -> 7251.2653 | J31: Adj. Gross Profit | M31: =SUM(M29:M30) -> 691.465 | N31: =SUM(N29:N30) -> 776.161 | O31: =SUM(O29:O30) -> 777.357 | R31: =O31 -> 777.357 | T31: Preferred Stock | W31: 0
J32: % Margin | M32: =M31/M$11 -> 0.44779217 | N32: =N31/N$11 -> 0.48974123 | O32: =O31/O$11 -> 0.4868239 | R32: =O32 -> 0.4868239 | T32: Shareholder's Equity | W32: 181.229
D33: Trading Multiples | T33: Total Liabilities & Equity | W33: =SUM(W30:W32)+W28 -> 2918.203
E34: LTM 12/31/2025 | F34: NFY 12/31/2026 | G34: NFY+1 12/31/2027 | H34: NFY+2 12/31/2028 | J34: Reported EBIT | M34: =M15 -> 378.764 | N34: =N15 -> 463.773 | O34: =O15 -> 448.399 | R34: =O34 -> 448.399
J35: Non-recurring items in COGS | M35: 0 | N35: 0 | O35: 0 | R35: =O35 -> 0 | T35: Balance Check | W35: =IF(W33=W18,W18-W33,W18-W33) -> 4.5474735e-13
D36: EV/Sales | E36: =$H$31/E37 -> 4.5411429 | F36: =$H$31/F37 -> 4.4955147 | G36: =$H$31/G37 -> 4.3525002 | H36: =$H$31/H37 -> 4.2109554 | J36: Other Non-recurring items | M36: 23 | N36: 23 | O36: 23 | R36: =O36 -> 23
D37: Metric | E37: =R11 -> 1596.793 | F37: 1613 | G37: 1666 | H37: 1722 | J37: Adjusted EBIT | M37: =M41-M40 -> 500.841 | N37: =N41-N40 -> 559.062 | O37: =O41-O40 -> 573.647 | R37: =O37 -> 573.647
D38: EV/EBITDA | E38: =$H$31/E39 -> 11.590897 | F38: =$H$31/F39 -> 11.403153 | G38: =$H$31/G39 -> 11.142079 | H38: =$H$31/H39 -> 10.848691 | J38: % Margin | M38: =M37/M$11 -> 0.32434422 | N38: =N37/N$11 -> 0.35275634 | O38: =O37/O$11 -> 0.35924945 | R38: =O38 -> 0.35924945 | T38: Calculation of Fully Diluted Shares Outstanding
D39: Metric | E39: =R41 -> 625.6 | F39: 635.9 | G39: 650.8 | H39: 668.4 | T39: Basic Shares Outstanding | X39: 46.17
D40: EV/EBIT | E40: =$H$31/E41 -> 16.171457 | F40: =$H$31/F41 -> 16.031982 | G40: =$H$31/G41 -> 13.966227 | H40: =$H$31/H41 -> 13.086564 | J40: Depreciation & Amortization | M40: 39.659 | N40: 45.038 | O40: 51.953 | R40: =O40 -> 51.953 | T40: Plus: Shares from In-the-Money Options | X40: =W54 -> 0.695083
D41: Metric | E41: =R34 -> 448.399 | F41: 452.3 | G41: 519.2 | H41: 554.1 | J41: Adjusted EBITDA | M41: 540.5 | N41: 604.1 | O41: 625.6 | R41: =O41 -> 625.6 | T41: Less: Shares Repurchased | X41: =-X54/H18 -> -0.66124045
D42: P/E | E42: =$H$18/E43 -> 14.570073 | F42: =$H$18/F43 -> 19.67285 | G42: =$H$18/G43 -> 16.093254 | H42: =$H$18/H43 -> 14.520787 | J42: % Margin | M42: =M41/M$11 -> 0.35002736 | N42: =N41/N$11 -> 0.38117437 | O42: =O41/O$11 -> 0.39178528 | R42: =O42 -> 0.39178528 | T42: Net New Shares from Options | X42: =SUM(X40:X41) -> 0.033842546
D43: Metric | E43: =R26 -> 8.0068232 | F43: 5.93 | G43: 7.249 | H43: 8.034 | T43: Plus: Shares from Convertible Securities | X43: 0
D44: FCF Yield | E44: =E45/$H$25 -> 0.023125001 | F44: =F45/$H$25 -> 0.029591067 | G44: =G45/$H$25 -> 0.062948269 | H44: 0.06 | J44: Reported Net Income | M44: =M22 -> 262.243 | N44: =N22 -> 299.665 | O44: =O22 -> 369.946 | R44: =O44 -> 369.946 | T44: Fully Diluted Shares Outstanding | X44: =X39+X42 -> 46.203843
D45: Metric | E45: =R58 -> 124.647 | F45: 159.5 | G45: 339.3 | H45: =H44*H25 -> 323.40842 | J45: Non-recurring items in COGS | M45: =M30 -> 0 | N45: 0 | O45: 0 | R45: =O45 -> 0
J46: Other Non-recurring items | M46: =M35 -> 0 | N46: 0 | O46: 0 | R46: =O46 -> 0 | T46: Options/Warrants
D47: LTM Return on Investment Ratio | J47: Non-operating Non-rec. Items | M47: =M36 -> 23 | N47: =N36 -> 23 | O47: =O36 -> 23 | R47: =O47 -> 23 | U47: Number of Shares | V47: Exercise Price | W47: In-the-Money Shares | X47: Proceeds
D48: Return on Invested Capital | H48: =R49/(W26-W9+W32) -> 0.19465088 | J48: Tax Adjustment | M48: =-M47*$H$15 -> -4.6 | N48: =N47*$H$15 -> 4.6 | O48: =O47*$H$15 -> 4.6 | R48: =O48 -> 4.6 | T48: Tranche
D49: Return on Equity | H49: =ABS(R49/W32) -> 2.1936114 | J49: Adjusted Net Income | M49: =SUM(M44:M48) -> 280.643 | N49: =SUM(N44:N48) -> 327.265 | O49: =SUM(O44:O48) -> 397.546 | R49: =O49 -> 397.546 | T49: Tranche 1 | U49: 0.695083 | V49: 110.98 | W49: =IF(V49<$H$18,U49,0) -> 0.695083 | X49: =IF(W49>0,V49*U49) -> 77.140311
D50: Return on Assets | H50: =ABS(R49/W18) -> 0.13622973 | J50: % Margin | M50: =M49/M$11 -> 0.18174418 | N50: =N49/N$11 -> 0.20649732 | O50: =O49/O$11 -> 0.24896527 | R50: =O50 -> 0.24896527 | T50: Tranche 2 | U50: 0.343165 | V50: 138.02 | W50: =IF(V50<$H$18,U50,0) -> 0 | X50: =IF(W50>0,V50*U50) -> FALSE
D51: Implied Annual Dividend per Share | H51: =H22/H18 -> 0.0098577062 | T51: Tranche 3 | U51: 0.444811 | V51: 138.89 | W51: =IF(V51<$H$18,U51,0) -> 0 | X51: =IF(W51>0,V51*U51) -> FALSE
J52: Adjusted Diluted EPS | M52: =M49/M25 -> 5.5353649 | N52: =N49/N25 -> 6.8069595 | O52: =O49/O25 -> 8.6041761 | R52: =O52 -> 8.6041761 | T52: Tranche 4 | U52: 0 | V52: 0 | W52: 0 | X52: 0
D53: LTM Credit Statistics | T53: Tranche 5 | U53: 0 | V53: 0 | W53: 0 | X53: 0
D54: Debt/Total Capitalization | H54: =W26/(W26+W32) -> 0.91317752 | J54: Cash Flow Statement Data | T54: Total | U54: =SUM(U49:U53) -> 1.483059 | V54: =SUM(V49:V53) -> 387.89 | W54: =SUM(W49:W53) -> 0.695083 | X54: =SUM(X49:X53) -> 77.140311
D55: Total Debt/EBITDA | H55: =W26/R41 -> 3.0468702 | J55: Cash From Operations | M55: 296.554 | N55: 319.403 | O55: 270.447 | R55: =O56 -> 145.8
D56: Net Debt/EBITDA | H56: =(W26-W9)/R41 -> 2.9749441 | J56: Capital Expenditure | M56: 116.3 | N56: 145.9 | O56: 145.8 | R56: =O56 -> 145.8 | T56: Convertible Securities
D57: EBITDA/Interest Expense | H57: =ABS(R41/R17) -> 6.6978577 | J57: % Sales | M57: =M56/M$11 -> 0.075315786 | N57: =N56/N$11 -> 0.092059824 | O57: =O56/O$11 -> 0.091308016 | R57: =O57 -> 0.091308016 | U57: Amount | V57: Conversion Price | W57: Conversion Ratio | X57: New Shares
D58: (EBITDA - Capex)/Interest Expense | H58: =ABS((R41-R56)/R17) -> 5.13688 | J58: Free Cash Flow | M58: =M55-M56 -> 180.254 | N58: =N55-N56 -> 173.503 | O58: =O55-O56 -> 124.647 | R58: =O58 -> 124.647
D59: EBIT/Interest Expense | H59: =ABS(R37/R17) -> 6.1416336 | J59: % Margin | M59: =M58/M$11 -> 0.11673234 | N59: =N58/N$11 -> 0.10947674 | O59: =O58/O$11 -> 0.078060838 | R59: =O59 -> 0.078060838 | T59: Issue 1 | U59: 0 | V59: 0 | W59: 0 | X59: 0
J60: FCF/Share | M60: =M58/M25 -> 3.5553057 | N60: =N58/N25 -> 3.6087816 | O60: =O58/O25 -> 2.6977626 | R60: =O60 -> 2.6977626 | T60: Issue 2 | U60: 0 | V60: 0 | W60: 0 | X60: 0
D61: Growth Rates | T61: Issue 3 | U61: 0 | V61: 0 | W61: 0 | X61: 0
E62: Sales | F62: EBITDA | G62: FCF | H62: EPS | J62: Depreciation & Amortization | M62: =M40 -> 39.659 | N62: =N40 -> 45.038 | O62: =O40 -> 51.953 | R62: =O62 -> 51.953 | T62: Issue 4 | U62: 0 | V62: 0 | W62: 0 | X62: 0
D63: Historical | J63: % Sales | M63: =M62/M$11 -> 0.025683136 | N63: =N62/N$11 -> 0.028418029 | O63: =O62/O$11 -> 0.032535839 | R63: =O63 -> 0.032535839 | T63: Issue 5 | U63: 0 | V63: 0 | W63: 0 | X63: 0
D64: 1-year | E64: =O11/N11-1 -> 0.007542722 | F64: =O41/N41-1 -> 0.035590134 | G64: =O58/N58-1 -> -0.28158591 | H64: =O26/N26-1 -> 0.28460797 | T64: Total | U64: =SUM(U59:U63) -> 0 | V64: =SUM(V59:V63) -> 0 | W64: =SUM(W59:W63) -> 0 | X64: =SUM(X59:X63) -> 0
D65: 2-year CAGR | E65: =_xlfn.RRI(2,M11,O11) -> 0.016898151 | F65: =_xlfn.RRI(2,M41,O41) -> 0.075847019 | G65: =_xlfn.RRI(2,M58,O58) -> -0.16843068 | H65: =_xlfn.RRI(2,M26,O26) -> 0.24417694
D66: Estimated | J66: Notes
D67: 1-year | E67: =F37/E37-1 -> 0.010149719 | F67: =F39/E39-1 -> 0.016464194 | G67: =F45/E45-1 -> 0.27961363 | H67: =F43/E43-1 -> -0.25938168
D68: 2-year CAGR | E68: =_xlfn.RRI(2,E37,G37) -> 0.02144077 | F68: =_xlfn.RRI(2,E39,G39) -> 0.019941827 | G68: =_xlfn.RRI(2,E45,G45) -> 0.6498749 | H68: =_xlfn.RRI(2,E43,G43) -> -0.0484997
D69: Long-term | H69: 0.11

Sheet MAR
D2: Marriott International (NYSE: MAR)
D3: Input Page
D4: ($ in millions, except per share data)
D7: General Information | J7: Reported Income Statement | T7: Balance Sheet Data
D8: Company Name | H8: Marriott International Inc. | P8: Prior Stub 12/31/2025 | Q8: Current Stub 12/31/2025 | R8: LTM 12/31/2025 | W8: 2025A | X8: -
D9: Ticker | H9: MAR | M9: Fiscal Year Ending December 31, | T9: Cash & Cash Equivalents | W9: 358
D10: Stock Exchange | H10: NYSE | M10: 2023A | N10: 2024A | O10: 2025A | T10: Accounts Receivables | W10: 2909
D11: Fisical Year Ending | H11: 12/31/2025 | J11: Sales | M11: 23713 | N11: 25100 | O11: 26186 | R11: =O11 -> 26186 | T11: Inventories | W11: 0
D12: Moody's Corporate Rating | H12: Baa2 | J12: COGS (incl. D&A) | M12: =19849-867 -> 18982 | N12: =21333-945 -> 20388 | O12: =22045-870 -> 21175 | R12: =O12 -> 21175 | T12: Prepaids & Other Current Assets | W12: 317
D13: S&P Corporate Rating | H13: BBB | J13: Gross Profit | M13: =M11-M12 -> 4731 | N13: =N11-N12 -> 4712 | O13: =O11-O12 -> 5011 | R13: =O13 -> 5011 | T13: Total Current Assets | W13: =SUM(W9:W12) -> 3584
D14: Predicted Beta | H14: 1.1 | J14: SG&A | M14: 867 | N14: 945 | O14: 870 | R14: =O14 -> 870
D15: Marginal Tax | H15: 0.2 | J15: Other Income/(Expense) | M15: 40 | N15: 31 | O15: 9 | R15: =O15 -> 9 | T15: Property, Plant & Equivalent, net | W15: 1954
J16: EBIT | M16: =M13-M14+M15 -> 3904 | N16: =N13-N14+N15 -> 3798 | O16: =O13-O14+O15 -> 4150 | R16: =O16 -> 4150 | T16: Goodwill & Intangible Assets | W16: =6207+4129+8907 -> 19243
D17: Selected Market Data | J17: Interest Expense | M17: =30+9-565 -> -526 | N17: =40+8-695 -> -647 | O17: =42+11-809 -> -756 | R17: =O17 -> -756 | T17: Other Assets | W17: =298+151+570+941+799 -> 2759
D18: Current Price | H18: 363.98 | J18: Pre-tax Income | M18: =SUM(M16:M17) -> 3378 | N18: =SUM(N16:N17) -> 3151 | O18: =SUM(O16:O17) -> 3394 | R18: =O18 -> 3394 | T18: Total Assets | W18: =SUM(W15:W17)+W13 -> 27540
D19: % of 52-week High | H19: =H18/H20 -> 0.98372973 | J19: Income Taxes | M19: -295 | N19: -776 | O19: -793 | R19: =O19 -> -793
D20: 52-week High Price | H20: 370 | J20: Non-controlling Interest | M20: 0 | N20: 0 | O20: 0 | R20: =O20 -> 0 | T20: Current Portion of Long-term Debt | W20: 1209
D21: 52-week Low Price | H21: 212.53 | J21: Preferred Dividends | M21: 0 | N21: 0 | O21: 0 | R21: =O21 -> 0 | T21: Accounts Payable | W21: 814
D22: Dividend Per Share | H22: 2.68 | J22: Net Income | M22: =SUM(M18:M21) -> 3083 | N22: =SUM(N18:N21) -> 2375 | O22: =SUM(O18:O21) -> 2601 | R22: =O22 -> 2601 | T22: Accrued Liabilities | W22: =1438+1440 -> 2878
J23: Effective Tax Rate | M23: =ABS(M19/M18) -> 0.087329781 | N23: =ABS(N19/N18) -> 0.24627103 | O23: =ABS(O19/O18) -> 0.23364761 | R23: =O23 -> 0.23364761 | T23: Other Current Liabilties | W23: 3497
D24: Fully Diluted Shares Outstanding | H24: =X44 -> 265.68455 | T24: Total Current Liabilities | W24: =SUM(W20:W23) -> 8398
D25: Equity Value | H25: =H24*H18 -> 96703.864 | J25: Weighted Avg. Diluted Shares | M25: 302.9 | N25: 285.2 | O25: 273.6 | R25: =O25 -> 273.6
J26: Diluted EPS | M26: =M22/M25 -> 10.178277 | N26: =N22/N25 -> 8.3274895 | O26: =O22/O25 -> 9.5065789 | R26: =O26 -> 9.5065789 | T26: Total Debt | W26: 14995
D27: Plus: Total Debt | H27: =+W26+W20 -> 16204 | T27: Other Long-term Liabilities | W27: =4495+79+1200+879+1265 -> 7918
D28: Plus: Preferred Stock | H28: =+W31 -> 0 | J28: Adjusted Income Statement | T28: Total Liabilities | W28: =SUM(W26:W27)+W24 -> 31311
D29: Plus: Non-controlling Intererst | H29: =+W30 -> 0 | J29: Reported Gross Profit | M29: =M13 -> 4731 | N29: =N13 -> 4712 | O29: =O13 -> 5011 | R29: =O29 -> 5011
D30: Less: Cash & Cash Equivalents | H30: =-W9 -> -358 | J30: Non-recurring items in COGS | M30: 0 | N30: 0 | O30: 0 | R30: =O30 -> 0 | T30: Non-Controlling Interest | W30: 0
D31: Enterprise Value | H31: =SUM(H25:H30) -> 112549.86 | J31: Adj. Gross Profit | M31: =SUM(M29:M30) -> 4731 | N31: =SUM(N29:N30) -> 4712 | O31: =SUM(O29:O30) -> 5011 | R31: =O31 -> 5011 | T31: Preferred Stock | W31: 0
J32: % Margin | M32: =M31/M$11 -> 0.19951082 | N32: =N31/N$11 -> 0.18772908 | O32: =O31/O$11 -> 0.1913618 | R32: =O32 -> 0.1913618 | T32: Shareholder's Equity | W32: -3771
D33: Trading Multiples | T33: Total Liabilities & Equity | W33: =SUM(W30:W32)+W28 -> 27540
E34: LTM 12/31/2025 | F34: NFY 12/31/2026 | G34: NFY+1 12/31/2027 | H34: NFY+2 12/31/2028 | J34: Reported EBIT | M34: =M16 -> 3904 | N34: =N16 -> 3798 | O34: =O16 -> 4150 | R34: =O34 -> 4150
J35: Non-recurring items in COGS | M35: 0 | N35: 0 | O35: 0 | R35: =O35 -> 0 | T35: Balance Check | W35: =IF(W33=W18,W18-W33,W18-W33) -> 0
D36: EV/Sales | E36: =$H$31/E37 -> 4.298093 | F36: =$H$31/F37 -> 4.0339007 | G36: =$H$31/G37 -> 3.8293989 | H36: =$H$31/H37 -> 3.7047355 | J36: Other Non-recurring items | M36: 23 | N36: -55 | O36: -54 | R36: =O36 -> -54
D37: Metric | E37: =R11 -> 26186 | F37: 27901 | G37: 29391 | H37: 30380 | J37: Adjusted EBIT | M37: =SUM(M34:M36) -> 3927 | N37: =SUM(N34:N36) -> 3743 | O37: =SUM(O34:O36) -> 4096 | R37: =O37 -> 4096
D38: EV/EBITDA | E38: =$H$31/E39 -> 23.972282 | F38: =$H$31/F39 -> 19.076248 | G38: =$H$31/G39 -> 17.794445 | H38: =$H$31/H39 -> 16.750984 | J38: % Margin | M38: =M37/M$11 -> 0.16560536 | N38: =N37/N$11 -> 0.14912351 | O38: =O37/O$11 -> 0.15641946 | R38: =O38 -> 0.15641946 | T38: Calculation of Fully Diluted Shares Outstanding
D39: Metric | E39: =R41 -> 4695 | F39: 5900 | G39: 6325 | H39: 6719 | T39: Basic Shares Outstanding | X39: 264.98455
D40: EV/EBIT | E40: =$H$31/E41 -> 27.120449 | F40: =$H$31/F41 -> 22.769546 | G40: =$H$31/G41 -> 20.935615 | H40: =$H$31/H41 -> 19.67999 | J40: Depreciation & Amortization | M40: 436 | N40: 492 | O40: 599 | R40: =O40 -> 599 | T40: Plus: Shares from In-the-Money Options | X40: 0
D41: Metric | E41: =R34 -> 4150 | F41: 4943 | G41: 5376 | H41: 5719 | J41: Adjusted EBITDA | M41: =M37+M40 -> 4363 | N41: =N37+N40 -> 4235 | O41: =O37+O40 -> 4695 | R41: =O41 -> 4695 | T41: Less: Shares Repurchased | X41: 0
D42: P/E | E42: =$H$18/E43 -> 38.28717 | F42: =$H$18/F43 -> 32.180986 | G42: =$H$18/G43 -> 29.663762 | H42: =$H$18/H43 -> 27.164007 | J42: % Margin | M42: =M41/M$11 -> 0.1839919 | N42: =N41/N$11 -> 0.1687251 | O42: =O41/O$11 -> 0.17929428 | R42: =O42 -> 0.17929428 | T42: Net New Shares from Options | X42: 0.7
D43: Metric | E43: =R26 -> 9.5065789 | F43: =3005/H24 -> 11.310405 | G43: =3260/H24 -> 12.27019 | H43: =3560/H24 -> 13.399349 | T43: Plus: Shares from Convertible Securities | X43: 0
D44: FCF Yield | E44: =E45/$H$25 -> 0.027496316 | F44: =F45/$H$25 -> 0.029140511 | G44: =G45/$H$25 -> 0.03388696 | H44: =H45/$H$25 -> 0.034714228 | J44: Reported Net Income | M44: =M22 -> 3083 | N44: =N22 -> 2375 | O44: =O22 -> 2601 | R44: =O44 -> 2601 | T44: Fully Diluted Shares Outstanding | X44: =X39+X42 -> 265.68455
D45: Metric | E45: =R58 -> 2659 | F45: 2818 | G45: 3277 | H45: 3357 | J45: Non-recurring items in COGS | M45: =M30 -> 0 | N45: 0 | O45: 0 | R45: =O45 -> 0
J46: Other Non-recurring items | M46: =M35 -> 0 | N46: 0 | O46: 0 | R46: =O46 -> 0 | T46: Options/Warrants
D47: LTM Return on Investment Ratio | J47: Non-operating Non-rec. Items | M47: =M36 -> 23 | N47: =N36 -> -55 | O47: =O36 -> -54 | R47: =O47 -> -54 | U47: Number of Shares | V47: Exercise Price | W47: In-the-Money Shares | X47: Proceeds
D48: Return on Invested Capital | H48: =R49/(W26-W9+W32) -> 0.23340696 | J48: Tax Adjustment | M48: =-M47*$H$15 -> -4.6 | N48: =N47*$H$15 -> -11 | O48: =O47*$H$15 -> -10.8 | R48: =O48 -> -10.8 | T48: Tranche
D49: Return on Equity | H49: =ABS(R49/W32) -> 0.6725537 | J49: Adjusted Net Income | M49: =SUM(M44:M48) -> 3101.4 | N49: =SUM(N44:N48) -> 2309 | O49: =SUM(O44:O48) -> 2536.2 | R49: =O49 -> 2536.2 | T49: Tranche 1 | U49: 0 | V49: 0 | W49: 0 | X49: 0
D50: Return on Assets | H50: =ABS(R49/W18) -> 0.092091503 | J50: % Margin | M50: =M49/M$11 -> 0.13078902 | N50: =N49/N$11 -> 0.091992032 | O50: =O49/O$11 -> 0.09685328 | R50: =O50 -> 0.09685328 | T50: Tranche 2 | U50: 0 | V50: 0 | W50: 0 | X50: 0
D51: Implied Annual Dividend per Share | H51: =H22/H18 -> 0.0073630419 | T51: Tranche 3 | U51: 0 | V51: 0 | W51: 0 | X51: 0
J52: Adjusted Diluted EPS | M52: =M49/M25 -> 10.239023 | N52: =N49/N25 -> 8.0960729 | O52: =O49/O25 -> 9.2697368 | R52: =O52 -> 9.2697368 | T52: Tranche 4 | U52: 0 | V52: 0 | W52: 0 | X52: 0
D53: LTM Credit Statistics | T53: Tranche 5 | U53: 0 | V53: 0 | W53: 0 | X53: 0
D54: Debt/Total Capitalization | H54: =W26/(W26+W32) -> 1.3359765 | J54: Cash Flow Statement Data | T54: Total | U54: =SUM(U49:U53) -> 0 | V54: =SUM(V49:V53) -> 0 | W54: =SUM(W49:W53) -> 0 | X54: =SUM(X49:X53) -> 0
D55: Total Debt/EBITDA | H55: =W26/R41 -> 3.1938232 | J55: Cash From Operations | M55: 3170 | N55: 2749 | O55: 3212 | R55: =O55 -> 3212
D56: Net Debt/EBITDA | H56: =(W26-W9)/R41 -> 3.1175719 | J56: Capital Expenditure | M56: =350+604 -> 954 | N56: =750+26 -> 776 | O56: =101+452 -> 553 | R56: =O56 -> 553 | T56: Convertible Securities
D57: EBITDA/Interest Expense | H57: =ABS(R41/R17) -> 6.2103175 | J57: % Sales | M57: =M56/M$11 -> 0.040231097 | N57: =N56/N$11 -> 0.030916335 | O57: =O56/O$11 -> 0.021118155 | R57: =O57 -> 0.021118155 | U57: Amount | V57: Conversion Price | W57: Conversion Ratio | X57: New Shares
D58: (EBITDA - Capex)/Interest Expense | H58: =ABS((R41-R56)/R17) -> 5.478836 | J58: Free Cash Flow | M58: =M55-M56 -> 2216 | N58: =N55-N56 -> 1973 | O58: =O55-O56 -> 2659 | R58: =O58 -> 2659
D59: EBIT/Interest Expense | H59: =ABS(R37/R17) -> 5.4179894 | J59: % Margin | M59: =M58/M$11 -> 0.09345085 | N59: =N58/N$11 -> 0.078605578 | O59: =O58/O$11 -> 0.10154281 | R59: =O59 -> 0.10154281 | T59: Issue 1 | U59: 0 | V59: 0 | W59: 0 | X59: 0
J60: FCF/Share | M60: =M58/M25 -> 7.3159459 | N60: =N58/N25 -> 6.9179523 | O60: =O58/O25 -> 9.7185673 | R60: =O60 -> 9.7185673 | T60: Issue 2 | U60: 0 | V60: 0 | W60: 0 | X60: 0
D61: Growth Rates | T61: Issue 3 | U61: 0 | V61: 0 | W61: 0 | X61: 0
E62: Sales | F62: EBITDA | G62: FCF | H62: EPS | J62: Depreciation & Amortization | M62: =M40 -> 436 | N62: =N40 -> 492 | O62: =O40 -> 599 | R62: =O62 -> 599 | T62: Issue 4 | U62: 0 | V62: 0 | W62: 0 | X62: 0
D63: Historical | J63: % Sales | M63: =M62/M$11 -> 0.018386539 | N63: =N62/N$11 -> 0.019601594 | O63: =O62/O$11 -> 0.022874819 | R63: =O63 -> 0.022874819 | T63: Issue 5 | U63: 0 | V63: 0 | W63: 0 | X63: 0
D64: 1-year | E64: =O11/N11-1 -> 0.043266932 | F64: =O41/N41-1 -> 0.10861865 | G64: =O58/N58-1 -> 0.34769387 | H64: =O26/N26-1 -> 0.14159003 | T64: Total | U64: =SUM(U59:U63) -> 0 | V64: =SUM(V59:V63) -> 0 | W64: =SUM(W59:W63) -> 0 | X64: =SUM(X59:X63) -> 0
D65: 2-year CAGR | E65: =_xlfn.RRI(2,M11,O11) -> 0.050851458 | F65: =_xlfn.RRI(2,M41,O41) -> 0.037349715 | G65: =_xlfn.RRI(2,M58,O58) -> 0.09540392 | H65: =_xlfn.RRI(2,M26,O26) -> -0.033559761
D66: Estimated | J66: Notes
D67: 1-year | E67: =F37/E37-1 -> 0.065493012 | F67: =F39/E39-1 -> 0.25665602 | G67: =F45/E45-1 -> 0.059796916 | H67: =F43/E43-1 -> 0.18974506
D68: 2-year CAGR | E68: =_xlfn.RRI(2,E37,G37) -> 0.059430812 | F68: =_xlfn.RRI(2,E39,G39) -> 0.16067991 | G68: =_xlfn.RRI(2,E45,G45) -> 0.11014333 | H68: =_xlfn.RRI(2,E43,G43) -> 0.13609204
D69: Long-term | H69: 0.06

Sheet ABNB
D2: Airbnb Inc. Cl A (NYSE: ABNB)
D3: Input Page
D4: ($ in millions, except per share data)
D7: General Information | J7: Reported Income Statement | T7: Balance Sheet Data
D8: Company Name | H8: Airbnb Inc. Cl A | P8: Prior Stub 12/31/2025 | Q8: Current Stub 12/31/2025 | R8: LTM 12/31/2025 | W8: 2025A | X8: -
D9: Ticker | H9: ABNB | M9: Fiscal Year Ending December 31, | T9: Cash & Cash Equivalents | W9: 6560
D10: Stock Exchange | H10: NYSE | M10: 2023A | N10: 2024A | O10: 2025A | T10: Accounts Receivables | W10: 6959
D11: Fisical Year Ending | H11: 12/31/2025 | J11: Sales | M11: 9917 | N11: 11102 | O11: 12241 | R11: =O11 -> 12241 | T11: Short-term investments | W11: 4454
D12: Moody's Corporate Rating | H12: Baa1 | J12: COGS (incl. D&A) | M12: =1703+1186 -> 2889 | N12: =1878+1282 -> 3160 | O12: =2086+1327 -> 3413 | R12: =O12 -> 3413 | T12: Prepaids & Other Current Assets | W12: 824
D13: S&P Corporate Rating | H13: A- | J13: Gross Profit | M13: =M11-M12 -> 7028 | N13: =N11-N12 -> 7942 | O13: =O11-O12 -> 8828 | R13: =O13 -> 8828 | T13: Total Current Assets | W13: =SUM(W9:W12) -> 18797
D14: Predicted Beta | H14: 1.56 | J14: Product & Development | M14: 1722 | N14: 2056 | O14: 2354 | R14: =O14 -> 2354
D15: Marginal Tax | H15: 0.2 | J15: SG&A | M15: =1763+2025 -> 3788 | N15: =2148+1185 -> 3333 | O15: =2588+1342 -> 3930 | T15: Deferred income tax assets | W15: 2102
J16: EBIT | M16: =M13-M14-M15 -> 1518 | N16: =N13-N14-N15 -> 2553 | O16: =O13-O14-O15 -> 2544 | R16: =O16 -> 2544 | T16: Goodwill & Intangible Assets | W16: 770
D17: Selected Market Data | J17: Interest Income | M17: 721 | N17: 818 | O17: 705 | T17: Other Assets | W17: 539
D18: Current Price | H18: 134.51 | J18: Other expense, net | M18: -137 | N18: -40 | O18: -112 | R18: =O18 -> -112 | T18: Total Assets | W18: =SUM(W15:W17)+W13 -> 22208
D19: % of 52-week High | H19: =H18/H20 -> 0.93487629 | J19: Pre-tax Income | M19: =SUM(M16:M18) -> 2102 | N19: =SUM(N16:N18) -> 3331 | O19: =SUM(O16:O18) -> 3137 | R19: =O19 -> 3137
D20: 52-week High Price | H20: 143.88 | J20: Income Taxes | M20: 2690 | N20: 683 | O20: 626 | R20: =O20 -> 626 | T20: Accrued exp, Acc payable and current | W20: 2948
D21: 52-week Low Price | H21: 109.79 | J21: Non-controlling Interest | M21: 0 | N21: 0 | O21: 0 | R21: =O21 -> 0 | T21: Funds payable and amount payable | W21: 6959
D22: Dividend Per Share | H22: 0 | J22: Preferred Dividends | M22: 0 | N22: 0 | O22: 0 | R22: =O22 -> 0 | T22: Current portion of long-term debt | W22: 1999
J23: Net Income | M23: =SUM(M19:M22) -> 4792 | N23: =SUM(N19:N22) -> 4014 | O23: =SUM(O19:O22) -> 3763 | R23: =O23 -> 3763 | T23: Other Current Liabilties | W23: 1743
D24: Fully Diluted Shares Outstanding | H24: =X44 -> 622.27061 | J24: Effective Tax Rate | M24: =ABS(M20/M19) -> 1.2797336 | N24: =ABS(N20/N19) -> 0.20504353 | O24: =ABS(O20/O19) -> 0.19955371 | R24: =O24 -> 0.19955371 | T24: Total Current Liabilities | W24: =SUM(W20:W23) -> 13649
D25: Equity Value | H25: =H24*H18 -> 83701.62
J26: Weighted Avg. Diluted Shares | M26: 662 | N26: 645 | O26: 623 | R26: =O26 -> 623 | T26: Total Debt | W26: 0
D27: Plus: Total Debt | H27: =W26+W22 -> 1999 | J27: Diluted EPS | M27: =M23/M26 -> 7.2386707 | N27: =N23/N26 -> 6.2232558 | O27: =O23/O26 -> 6.0401284 | R27: =O27 -> 6.0401284 | T27: Other Long-term Liabilities | W27: 360
D28: Plus: Preferred Stock | H28: =+W31 -> 0 | T28: Total Liabilities | W28: =SUM(W26:W27)+W24 -> 14009
D29: Plus: Non-controlling Intererst | H29: =+W30 -> 0 | J29: Adjusted Income Statement
D30: Less: Cash & Cash Equivalents | H30: =-W9 -> -6560 | J30: Reported Gross Profit | M30: =M13 -> 7028 | N30: =N13 -> 7942 | O30: =O13 -> 8828 | R30: =O30 -> 8828 | T30: Non-Controlling Interest | W30: 0
D31: Enterprise Value | H31: =SUM(H25:H30) -> 79140.62 | J31: Non-recurring items in COGS | M31: 0 | N31: 0 | O31: 0 | R31: =O31 -> 0 | T31: Preferred Stock | W31: 0
J32: Adj. Gross Profit | M32: =SUM(M30:M31) -> 7028 | N32: =SUM(N30:N31) -> 7942 | O32: =SUM(O30:O31) -> 8828 | R32: =O32 -> 8828 | T32: Shareholder's Equity | W32: 8199
D33: Trading Multiples | J33: % Margin | M33: =M32/M$11 -> 0.70868206 | N33: =N32/N$11 -> 0.7153666 | O33: =O32/O$11 -> 0.72118291 | R33: =O33 -> 0.72118291 | T33: Total Liabilities & Equity | W33: =SUM(W30:W32)+W28 -> 22208
E34: LTM 12/31/2025 | F34: NFY 12/31/2026 | G34: NFY+1 12/31/2027 | H34: NFY+2 12/31/2028
J35: Reported EBIT | M35: =M16 -> 1518 | N35: =N16 -> 2553 | O35: =O16 -> 2544 | R35: =O35 -> 2544 | T35: Balance Check | W35: =IF(W33=W18,W18-W33,W18-W33) -> 0
D36: EV/Sales | E36: =$H$31/E37 -> 6.4652087 | F36: =$H$31/F37 -> 5.7779528 | G36: =$H$31/G37 -> 5.2487478 | H36: =$H$31/H37 -> 4.7859591 | J36: Non-recurring items in COGS | M36: =1120+974-3 -> 2091 | N36: =1407+23-7 -> 1423 | O36: =1592+74+1-5 -> 1662 | R36: =O36 -> 1662
D37: Metric | E37: =R11 -> 12241 | F37: 13697 | G37: 15078 | H37: 16536 | J37: Other Non-recurring items | M37: 0 | N37: 0 | O37: 0 | R37: =O37 -> 0
D38: EV/EBITDA | E38: =$H$31/E39 -> 18.417645 | F38: =$H$31/F39 -> 16.446513 | G38: =$H$31/G39 -> 14.652957 | H38: =$H$31/H39 -> 13.0552 | J38: Adjusted EBIT | M38: =SUM(M35:M37) -> 3609 | N38: =SUM(N35:N37) -> 3976 | O38: =SUM(O35:O37) -> 4206 | R38: =O38 -> 4206 | T38: Calculation of Fully Diluted Shares Outstanding
D39: Metric | E39: =R42 -> 4297 | F39: 4812 | G39: 5401 | H39: 6062 | J39: % Margin | M39: =M38/M$11 -> 0.36392054 | N39: =N38/N$11 -> 0.35813367 | O39: =O38/O$11 -> 0.34359938 | R39: =O39 -> 0.34359938 | T39: Basic Shares Outstanding | X39: 613
D40: EV/EBIT | E40: =$H$31/E41 -> 31.108734 | F40: =$H$31/F41 -> 26.424247 | G40: =$H$31/G41 -> 22.57935 | H40: =$H$31/H41 -> 19.608677 | T40: Plus: Shares from In-the-Money Options | X40: =W54 -> 37
D41: Metric | E41: =R35 -> 2544 | F41: 2995 | G41: 3505 | H41: 4036 | J41: Depreciation & Amortization | M41: 44 | N41: 65 | O41: 91 | R41: =O41 -> 91 | T41: Less: Shares Repurchased | X41: =-(X54/H18) -> -27.729388
D42: P/E | E42: =$H$18/E43 -> 22.269394 | F42: =$H$18/F43 -> 27.956453 | G42: =$H$18/G43 -> 24.481316 | H42: =$H$18/H43 -> 21.622738 | J42: Adjusted EBITDA | M42: =M38+M41 -> 3653 | N42: =N38+N41 -> 4041 | O42: =O38+O41 -> 4297 | R42: =O42 -> 4297 | T42: Net New Shares from Options | X42: =SUM(X40:X41) -> 9.2706119
D43: Metric | E43: =R27 -> 6.0401284 | F43: =2994/H24 -> 4.8114115 | G43: =3419/H24 -> 5.4943941 | H43: =3871/H24 -> 6.2207662 | J43: % Margin | M43: =M42/M$11 -> 0.36835737 | N43: =N42/N$11 -> 0.36398847 | O43: =O42/O$11 -> 0.35103341 | R43: =O43 -> 0.35103341 | T43: Plus: Shares from Convertible Securities | X43: 0
D44: FCF Yield | E44: =E45/$H$25 -> 0.055506692 | F44: =F45/$H$25 -> 0.061109928 | G44: =G45/$H$25 -> 0.066175541 | H44: =H45/$H$25 -> 0.077262543 | T44: Fully Diluted Shares Outstanding | X44: =X39+X42 -> 622.27061
D45: Metric | E45: =R59 -> 4646 | F45: 5115 | G45: 5539 | H45: 6467 | J45: Reported Net Income | M45: =M23 -> 4792 | N45: =N23 -> 4014 | O45: =O23 -> 3763 | R45: =O45 -> 3763
J46: Non-recurring items in COGS | M46: =M31 -> 0 | N46: =N31 -> 0 | O46: =O31 -> 0 | R46: =O46 -> 0 | T46: Options/Warrants
D47: LTM Return on Investment Ratio | J47: Other Non-recurring items | M47: =M36 -> 2091 | N47: =N36 -> 1423 | O47: =O36 -> 1662 | R47: =O47 -> 1662 | U47: Number of Shares | V47: Exercise Price | W47: In-the-Money Shares | X47: Proceeds
D48: Return on Invested Capital | H48: =R50/(W26-W9+W32) -> 3.1071385 | J48: Non-operating Non-rec. Items | M48: =-M20 -> -2690 | N48: =N37 -> 0 | O48: =O37 -> 0 | R48: =O48 -> 0 | T48: Tranche
D49: Return on Equity | H49: =ABS(R50/W32) -> 0.62112453 | J49: Tax Adjustment | M49: 0 | N49: =-N47*0.2 -> -284.6 | O49: =-O47*0.2 -> -332.4 | R49: =O49 -> -332.4 | T49: Tranche 1 | U49: 5 | V49: 108.28 | W49: =IF(V49<H18,U49,0) -> 5 | X49: =V49*U49 -> 541.4
D50: Return on Assets | H50: =ABS(R50/W18) -> 0.22931376 | J50: Adjusted Net Income | M50: =SUM(M45:M49) -> 4193 | N50: =SUM(N45:N49) -> 5152.4 | O50: =SUM(O45:O49) -> 5092.6 | R50: =O50 -> 5092.6 | T50: Tranche 2 | U50: 32 | V50: 99.64 | W50: =IF(V50<H18,U50,0) -> 32 | X50: =V50*U50 -> 3188.48
D51: Implied Annual Dividend per Share | H51: =H22/H18 -> 0 | J51: % Margin | M51: =M50/M$11 -> 0.42280932 | N51: =N50/N$11 -> 0.46409656 | O51: =O50/O$11 -> 0.4160281 | R51: =O51 -> 0.4160281 | T51: Tranche 3 | U51: 0 | V51: 0 | W51: 0 | X51: 0
T52: Tranche 4 | U52: 0 | V52: 0 | W52: 0 | X52: 0
D53: LTM Credit Statistics | J53: Adjusted Diluted EPS | M53: =M50/M26 -> 6.3338369 | N53: =N50/N26 -> 7.9882171 | O53: =O50/O26 -> 8.1743178 | R53: =O53 -> 8.1743178 | T53: Tranche 5 | U53: 0 | V53: 0 | W53: 0 | X53: 0
D54: Debt/Total Capitalization | H54: =W26/(W26+W32) -> 0 | T54: Total | U54: =SUM(U49:U53) -> 37 | V54: =SUM(V49:V53) -> 207.92 | W54: =SUM(W49:W53) -> 37 | X54: =SUM(X49:X53) -> 3729.88
D55: Total Debt/EBITDA | H55: =W26/R42 -> 0 | J55: Cash Flow Statement Data
D56: Net Debt/EBITDA | H56: =(W26-W9)/R42 -> -1.5266465 | J56: Cash From Operations | M56: 3884 | N56: 4518 | O56: 4646 | R56: =O56 -> 4646 | T56: Convertible Securities
D57: EBITDA/Interest Expense | H57: =ABS(R42/R18) -> 38.366071 | J57: Capital Expenditure | M57: 0 | N57: 0 | O57: 0 | R57: =O57 -> 0 | U57: Amount | V57: Conversion Price | W57: Conversion Ratio | X57: New Shares
D58: (EBITDA - Capex)/Interest Expense | H58: =ABS((R42-R57)/R18) -> 38.366071 | J58: % Sales | M58: =M57/M$11 -> 0 | N58: =N57/N$11 -> 0 | O58: =O57/O$11 -> 0 | R58: =O58 -> 0
D59: EBIT/Interest Expense | H59: =ABS(R38/R18) -> 37.553571 | J59: Free Cash Flow | M59: =M56-M57 -> 3884 | N59: =N56-N57 -> 4518 | O59: =O56-O57 -> 4646 | R59: =O59 -> 4646 | T59: Issue 1 | U59: 0 | V59: 0 | W59: 0 | X59: 0
J60: % Margin | M60: =M59/M$11 -> 0.3916507 | N60: =N59/N$11 -> 0.4069537 | O60: =O59/O$11 -> 0.37954415 | R60: =O60 -> 0.37954415 | T60: Issue 2 | U60: 0 | V60: 0 | W60: 0 | X60: 0
D61: Growth Rates | J61: FCF/Share | M61: =M59/M26 -> 5.8670695 | N61: =N59/N26 -> 7.0046512 | O61: =O59/O26 -> 7.4574639 | R61: =O61 -> 7.4574639 | T61: Issue 3 | U61: 0 | V61: 0 | W61: 0 | X61: 0
E62: Sales | F62: EBITDA | G62: FCF | H62: EPS | T62: Issue 4 | U62: 0 | V62: 0 | W62: 0 | X62: 0
D63: Historical | J63: Depreciation & Amortization | M63: =M41 -> 44 | N63: =N41 -> 65 | O63: =O41 -> 91 | R63: =O63 -> 91 | T63: Issue 5 | U63: 0 | V63: 0 | W63: 0 | X63: 0
D64: 1-year | E64: =O11/N11-1 -> 0.10259413 | F64: =O42/N42-1 -> 0.063350656 | G64: =O59/N59-1 -> 0.02833112 | H64: =O27/N27-1 -> -0.029426302 | J64: % Sales | M64: =M63/M$11 -> 0.0044368257 | N64: =N63/N$11 -> 0.0058548009 | O64: =O63/O$11 -> 0.0074340332 | R64: =O64 -> 0.0074340332 | T64: Total | U64: =SUM(U59:U63) -> 0 | V64: =SUM(V59:V63) -> 0 | W64: =SUM(W59:W63) -> 0 | X64: =SUM(X59:X63) -> 0
D65: 2-year CAGR | E65: =_xlfn.RRI(2,M11,O11) -> 0.11101083 | F65: =_xlfn.RRI(2,M42,O42) -> 0.084570633 | G65: =_xlfn.RRI(2,M59,O59) -> 0.093704483 | H65: =_xlfn.RRI(2,M27,O27) -> -0.086531289
D66: Estimated
D67: 1-year | E67: =F37/E37-1 -> 0.11894453 | F67: =F39/E39-1 -> 0.11985106 | G67: =F45/E45-1 -> 0.10094705 | H67: =F43/E43-1 -> -0.20342562 | J67: Notes
D68: 2-year CAGR | E68: =_xlfn.RRI(2,E37,G37) -> 0.10984779 | F68: =_xlfn.RRI(2,E39,G39) -> 0.12112597 | G68: =_xlfn.RRI(2,E45,G45) -> 0.091882938 | H68: =_xlfn.RRI(2,E43,G43) -> -0.046245019
D69: Long-term | H69: 0.12

Sheet HLT
D2: Hilton Worldwide Holding Inc. (NYSE: HLT)
D3: Input Page
D4: ($ in millions, except per share data)
D7: General Information | J7: Reported Income Statement | T7: Balance Sheet Data
D8: Company Name | H8: Hilton Worldwide Holdings Inc. | P8: Prior Stub 12/31/2025 | Q8: Current Stub 12/31/2025 | R8: LTM 12/31/2025 | W8: 2025A | X8: -
D9: Ticker | H9: HLT | M9: Fiscal Year Ending December 31, | T9: Cash & Cash Equivalents | W9: =918+52 -> 970
D10: Stock Exchange | H10: NYSE | M10: 2023A | N10: 2024A | O10: 2025A | T10: Accounts Receivables | W10: 1690
D11: Fisical Year Ending | H11: 12/31/2025 | J11: Sales | M11: 10235 | N11: 11174 | O11: 12039 | R11: =O11 -> 12039 | T11: Prepaid expenses | W11: 219
D12: Moody's Corporate Rating | H12: Ba2 | J12: COGS (incl. D&A) | M12: =8010-393 -> 7617 | N12: =8809-415 -> 8394 | O12: =9346-408 -> 8938 | R12: =O12 -> 8938 | T12: Other Current Assets | W12: 117
D13: S&P Corporate Rating | H13: BB+ | J13: Gross Profit | M13: =M11-M12 -> 2618 | N13: =N11-N12 -> 2780 | O13: =O11-O12 -> 3101 | R13: =O13 -> 3101 | T13: Total Current Assets | W13: =SUM(W9:W12) -> 2996
D14: Predicted Beta | H14: 1.04 | J14: SG&A | M14: 393 | N14: 415 | O14: 408 | R14: =O14 -> 408
D15: Marginal Tax | H15: 0.2 | J15: Other Income/(Expense) | M15: 0 | N15: 5 | O15: 0 | R15: =O15 -> 0 | T15: Property, Plant & Equivalent, net | W15: 684
J16: EBIT | M16: =M13-M14+M15 -> 2225 | N16: =N13-N14+N15 -> 2370 | O16: =O13-O14+O15 -> 2693 | R16: =O16 -> 2693 | T16: Goodwill & Intangible Assets | W16: =5081+5023+1471+206 -> 11781
D17: Selected Market Data | J17: Interest Expense | M17: =39-92-16-464 -> -533 | N17: =-6-12-569 -> -587 | O17: =10-11-620 -> -621 | R17: =O17 -> -621 | T17: Other Assets | W17: =577+252+484 -> 1313
D18: Current Price | H18: 330.71 | J18: Pre-tax Income | M18: =SUM(M16:M17) -> 1692 | N18: =SUM(N16:N17) -> 1783 | O18: =SUM(O16:O17) -> 2072 | R18: =O18 -> 2072 | T18: Total Assets | W18: =SUM(W15:W17)+W13 -> 16774
D19: % of 52-week High | H19: =H18/H20 -> 0.99056491 | J19: Income Taxes | M19: -541 | N19: -244 | O19: -611 | R19: =O19 -> -611
D20: 52-week High Price | H20: 333.86 | J20: Non-controlling Interest | M20: 0 | N20: 0 | O20: 0 | R20: =O20 -> 0 | T20: Current Portion of Long-term Debt | W20: 25
D21: 52-week Low Price | H21: 201.15 | J21: Preferred Dividends | M21: 0 | N21: 0 | O21: 0 | R21: =O21 -> 0 | T21: Accounts Payable | W21: 2336
D22: Dividend Per Share | H22: 0.6 | J22: Net Income | M22: =SUM(M18:M21) -> 1151 | N22: =SUM(N18:N21) -> 1539 | O22: =SUM(O18:O21) -> 1461 | R22: =O22 -> 1461 | T22: Accrued Liabilities | W22: 858
J23: Effective Tax Rate | M23: =ABS(M19/M18) -> 0.31973995 | N23: =ABS(N19/N18) -> 0.13684801 | O23: =ABS(O19/O18) -> 0.29488417 | R23: =O23 -> 0.29488417 | T23: Other Current Liabilties | W23: 1289
D24: Fully Diluted Shares Outstanding | H24: =X44 -> 236.7 | T24: Total Current Liabilities | W24: =SUM(W20:W23) -> 4508
D25: Equity Value | H25: =H24*H18 -> 78279.057 | J25: Weighted Avg. Diluted Shares | M25: 264 | N25: 250 | O25: =H24 -> 236.7 | R25: =O25 -> 236.7
J26: Diluted EPS | M26: =M22/M25 -> 4.3598485 | N26: =N22/N25 -> 6.156 | O26: =O22/O25 -> 6.1723701 | R26: =O26 -> 6.1723701 | T26: Total Debt | W26: 12338
D27: Plus: Total Debt | H27: =+W20+W26 -> 12363 | T27: Other Long-term Liabilities | W27: =730+1648+322+1624+950 -> 5274
D28: Plus: Preferred Stock | H28: =+W31 -> 0 | J28: Adjusted Income Statement | T28: Total Liabilities | W28: =SUM(W26:W27)+W24 -> 22120
D29: Plus: Non-controlling Intererst | H29: =+W30 -> 42 | J29: Reported Gross Profit | M29: =M13 -> 2618 | N29: =N13 -> 2780 | O29: =O13 -> 3101 | R29: =O29 -> 3101
D30: Less: Cash & Cash Equivalents | H30: =-W9 -> -970 | J30: Non-recurring items in COGS | M30: 0 | N30: 0 | O30: 0 | R30: =O30 -> 0 | T30: Non-Controlling Interest | W30: =29+13 -> 42
D31: Enterprise Value | H31: =SUM(H25:H30) -> 89714.057 | J31: Adj. Gross Profit | M31: =SUM(M29:M30) -> 2618 | N31: =SUM(N29:N30) -> 2780 | O31: =SUM(O29:O30) -> 3101 | R31: =O31 -> 3101 | T31: Preferred Stock | W31: 0
J32: % Margin | M32: =M31/M$11 -> 0.25578896 | N32: =N31/N$11 -> 0.24879184 | O32: =O31/O$11 -> 0.25757953 | R32: =O32 -> 0.25757953 | T32: Shareholder's Equity | W32: -5388
D33: Trading Multiples | T33: Total Liabilities & Equity | W33: =SUM(W30:W32)+W28 -> 16774
E34: LTM 12/31/2025 | F34: NFY 12/31/2026 | G34: NFY+1 12/31/2027 | H34: NFY+2 12/31/2028 | J34: Reported EBIT | M34: =M16 -> 2225 | N34: =N16 -> 2370 | O34: =O16 -> 2693 | R34: =O34 -> 2693
J35: Non-recurring items in COGS | M35: 0 | N35: 0 | O35: 0 | R35: =O35 -> 0 | T35: Balance Check | W35: =IF(W33=W18,W18-W33,W18-W33) -> 0
D36: EV/Sales | E36: =$H$31/E37 -> 7.4519526 | F36: =$H$31/F37 -> 6.8510162 | G36: =$H$31/G37 -> 6.3227893 | H36: =$H$31/H37 -> 5.8579208 | J36: Other Non-recurring items | M36: =16+92+63+169+38+43+337+28-147 -> 639 | N36: =-5+12+50+57+176+50-6428+6985+34-146 -> 785 | O36: =73+170+57-7085+7550+80-177 -> 668 | R36: =N36 -> 785
D37: Metric | E37: =R11 -> 12039 | F37: 13095 | G37: 14189 | H37: 15315 | J37: Adjusted EBIT | M37: =SUM(M34:M36) -> 2864 | N37: =SUM(N34:N36) -> 3155 | O37: =SUM(O34:O36) -> 3361 | R37: =O37 -> 3361
D38: EV/EBITDA | E38: =$H$31/E39 -> 25.35728 | F38: =$H$31/F39 -> 22.25051 | G38: =$H$31/G39 -> 20.412755 | H38: =$H$31/H39 -> 18.733359 | J38: % Margin | M38: =M37/M$11 -> 0.27982413 | N38: =N37/N$11 -> 0.28235189 | O38: =O37/O$11 -> 0.27917601 | R38: =O38 -> 0.27917601 | T38: Calculation of Fully Diluted Shares Outstanding
D39: Metric | E39: =R41 -> 3538 | F39: 4032 | G39: 4395 | H39: 4789 | T39: Basic Shares Outstanding | X39: 236
D40: EV/EBIT | E40: =$H$31/E41 -> 33.313798 | F40: =$H$31/F41 -> 25.936414 | G40: =$H$31/G41 -> 23.509973 | H40: =$H$31/H41 -> 21.370666 | J40: Depreciation & Amortization | M40: 147 | N40: 146 | O40: 177 | R40: =O40 -> 177 | T40: Plus: Shares from In-the-Money Options | X40: =W54 -> 4.025
D41: Metric | E41: =R34 -> 2693 | F41: 3459 | G41: 3816 | H41: 4198 | J41: Adjusted EBITDA | M41: =M37+M40 -> 3011 | N41: =N37+N40 -> 3301 | O41: =O37+O40 -> 3538 | R41: =O41 -> 3538 | T41: Less: Shares Repurchased | X41: =-X54/H18 -> -1.8649819
D42: P/E | E42: =$H$18/E43 -> 53.579094 | F42: =$H$18/F43 -> 37.580682 | G42: =$H$18/G43 -> 33.203815 | H42: =$H$18/H43 -> 28.558722 | J42: % Margin | M42: =M41/M$11 -> 0.29418661 | N42: =N41/N$11 -> 0.29541793 | O42: =O41/O$11 -> 0.29387823 | R42: =O42 -> 0.29387823 | T42: Net New Shares from Options | X42: 0.7
D43: Metric | E43: =R26 -> 6.1723701 | F43: 8.8 | G43: 9.96 | H43: 11.58 | T43: Plus: Shares from Convertible Securities | X43: 0
D44: FCF Yield | E44: =E45/$H$25 -> 0.025907313 | F44: =F45/$H$25 -> 0.029101015 | G44: =G45/$H$25 -> 0.029586458 | H44: =H45/$H$25 -> 0.031681526 | J44: Reported Net Income | M44: =M22 -> 1151 | N44: =N22 -> 1539 | O44: =O22 -> 1461 | R44: =O44 -> 1461 | T44: Fully Diluted Shares Outstanding | X44: =X39+X42 -> 236.7
D45: Metric | E45: =R58 -> 2028 | F45: 2278 | G45: 2316 | H45: 2480 | J45: Non-recurring items in COGS | M45: =M30 -> 0 | N45: 0 | O45: 0 | R45: =O45 -> 0
J46: Other Non-recurring items | M46: =M35 -> 0 | N46: 0 | O46: 0 | R46: =O46 -> 0 | T46: Options/Warrants
D47: LTM Return on Investment Ratio | J47: Non-operating Non-rec. Items | M47: =M36 -> 639 | N47: =N36 -> 785 | O47: =O36 -> 668 | R47: =O47 -> 668 | U47: Number of Shares | V47: Exercise Price | W47: In-the-Money Shares | X47: Proceeds
D48: Return on Invested Capital | H48: =R49/(W26-W9+W32) -> 0.33367893 | J48: Tax Adjustment | M48: =-M47*$H$15 -> -127.8 | N48: =-N47*$H$15 -> -157 | O48: =-O47*$H$15 -> -133.6 | R48: =O48 -> -133.6 | T48: Tranche
D49: Return on Equity | H49: =ABS(R49/W32) -> 0.3703415 | J49: Adjusted Net Income | M49: =SUM(M44:M48) -> 1662.2 | N49: =SUM(N44:N48) -> 2167 | O49: =SUM(O44:O48) -> 1995.4 | R49: =O49 -> 1995.4 | T49: Tranche 1 | U49: 2.673 | V49: 124.32 | W49: =IF(V49<$H$18,U49,0) -> 2.673 | X49: =IF(W49>0,U49*V49,0) -> 332.30736
D50: Return on Assets | H50: =ABS(R49/W18) -> 0.11895791 | J50: % Margin | M50: =M49/M$11 -> 0.16240352 | N50: =N49/N$11 -> 0.19393234 | O50: =O49/O$11 -> 0.16574466 | R50: =O50 -> 0.16574466 | T50: Tranche 2 | U50: 0.798 | V50: 220.64 | W50: =IF(V50<$H$18,U50,0) -> 0.798 | X50: =IF(W50>0,U50*V50,0) -> 176.07072
D51: Implied Annual Dividend per Share | H51: =H22/H18 -> 0.0018142784 | T51: Tranche 3 | U51: 0.554 | V51: 195.65 | W51: =IF(V51<$H$18,U51,0) -> 0.554 | X51: =IF(W51>0,U51*V51,0) -> 108.3901
J52: Adjusted Diluted EPS | M52: =M49/M25 -> 6.2962121 | N52: =N49/N25 -> 8.668 | O52: =O49/O25 -> 8.4300803 | R52: =O52 -> 8.4300803 | T52: Tranche 4 | U52: 0 | V52: 0 | W52: 0 | X52: 0
D53: LTM Credit Statistics | T53: Tranche 5 | U53: 0 | V53: 0 | W53: 0 | X53: 0
D54: Debt/Total Capitalization | H54: =W26/(W26+W32) -> 1.7752518 | J54: Cash Flow Statement Data | T54: Total | U54: =SUM(U49:U53) -> 4.025 | V54: =SUM(V49:V53) -> 540.61 | W54: =SUM(W49:W53) -> 4.025 | X54: =SUM(X49:X53) -> 616.76818
D55: Total Debt/EBITDA | H55: =W26/R41 -> 3.4872809 | J55: Cash From Operations | M55: 1946 | N55: 2013 | O55: 2129 | R55: =O55 -> 2129
D56: Net Debt/EBITDA | H56: =(W26-W9)/R41 -> 3.2131148 | J56: Capital Expenditure | M56: 151 | N56: 96 | O56: 101 | R56: =O56 -> 101 | T56: Convertible Securities
D57: EBITDA/Interest Expense | H57: =ABS(R41/R17) -> 5.6972625 | J57: % Sales | M57: =M56/M$11 -> 0.014753298 | N57: =N56/N$11 -> 0.0085913728 | O57: =O56/O$11 -> 0.0083894011 | R57: =O57 -> 0.0083894011 | U57: Amount | V57: Conversion Price | W57: Conversion Ratio | X57: New Shares
D58: (EBITDA - Capex)/Interest Expense | H58: =ABS((R41-R56)/R17) -> 5.5346216 | J58: Free Cash Flow | M58: =M55-M56 -> 1795 | N58: =N55-N56 -> 1917 | O58: =O55-O56 -> 2028 | R58: =O58 -> 2028
D59: EBIT/Interest Expense | H59: =ABS(R37/R17) -> 5.4122383 | J59: % Margin | M59: =M58/M$11 -> 0.1753786 | N59: =N58/N$11 -> 0.17155898 | O59: =O58/O$11 -> 0.16845253 | R59: =O59 -> 0.16845253 | T59: Issue 1 | U59: 0 | V59: 0 | W59: 0 | X59: 0
J60: FCF/Share | M60: =M58/M25 -> 6.7992424 | N60: =N58/N25 -> 7.668 | O60: =O58/O25 -> 8.5678074 | R60: =O60 -> 8.5678074 | T60: Issue 2 | U60: 0 | V60: 0 | W60: 0 | X60: 0
D61: Growth Rates | T61: Issue 3 | U61: 0 | V61: 0 | W61: 0 | X61: 0
E62: Sales | F62: EBITDA | G62: FCF | H62: EPS | J62: Depreciation & Amortization | M62: =M40 -> 147 | N62: =N40 -> 146 | O62: =O40 -> 177 | R62: =O62 -> 177 | T62: Issue 4 | U62: 0 | V62: 0 | W62: 0 | X62: 0
D63: Historical | J63: % Sales | M63: =M62/M$11 -> 0.014362482 | N63: =N62/N$11 -> 0.013066046 | O63: =O62/O$11 -> 0.014702218 | R63: =O63 -> 0.014702218 | T63: Issue 5 | U63: 0 | V63: 0 | W63: 0 | X63: 0
D64: 1-year | E64: =O11/N11-1 -> 0.077411849 | F64: =O41/N41-1 -> 0.071796425 | G64: =O58/N58-1 -> 0.057902973 | H64: =O26/N26-1 -> 0.0026592087 | T64: Total | U64: =SUM(U59:U63) -> 0 | V64: =SUM(V59:V63) -> 0 | W64: =SUM(W59:W63) -> 0 | X64: =SUM(X59:X63) -> 0
D65: 2-year CAGR | E65: =_xlfn.RRI(2,M11,O11) -> 0.084554258 | F65: =_xlfn.RRI(2,M41,O41) -> 0.083985659 | G65: =_xlfn.RRI(2,M58,O58) -> 0.062922864 | H65: =_xlfn.RRI(2,M26,O26) -> 0.1898447
D66: Estimated | J66: Notes
D67: 1-year | E67: =F37/E37-1 -> 0.087714926 | F67: =F39/E39-1 -> 0.13962691 | G67: =F45/E45-1 -> 0.12327416 | H67: =F43/E43-1 -> 0.42570842
D68: 2-year CAGR | E68: =_xlfn.RRI(2,E37,G37) -> 0.085627128 | F68: =_xlfn.RRI(2,E39,G39) -> 0.11455249 | G68: =_xlfn.RRI(2,E45,G45) -> 0.068649538 | H68: =_xlfn.RRI(2,E43,G43) -> 0.27029237
D69: Long-term | H69: 0.145

Sheet H
D2: Hyatt Hotels Corporation (NYSE: H)
D3: Input Page
D4: ($ in millions, except per share data)
D7: General Information | J7: Reported Income Statement | T7: Balance Sheet Data
D8: Company Name | H8: Hyatt Hotels Corporation | P8: Prior Stub 12/31/2025 | Q8: Current Stub 12/31/2025 | R8: LTM 12/31/2025 | W8: 2025A | X8: -
D9: Ticker | H9: H | M9: Fiscal Year Ending December 31, | T9: Cash & Cash Equivalents | W9: 788
D10: Stock Exchange | H10: NYSE | M10: 2023A | N10: 2024A | O10: 2025A | T10: Accounts Receivables | W10: 1123
D11: Fisical Year Ending | H11: 12/31/2025 | J11: Sales | M11: 6667 | N11: 6648 | O11: 7101 | R11: =O11 -> 7101 | T11: Inventories | W11: 8
D12: Moody's Corporate Rating | H12: Baa3 | J12: COGS (incl. D&A) | M12: =6378-578 -> 5800 | N12: =6274-548 -> 5726 | O12: =6753-555 -> 6198 | R12: =O12 -> 6198 | T12: Prepaids & Other Current Assets | W12: =26+169+63 -> 258
D13: S&P Corporate Rating | H13: BBB- | J13: Gross Profit | M13: =M11-M12 -> 867 | N13: =N11-N12 -> 922 | O13: =O11-O12 -> 903 | R13: =O13 -> 903 | T13: Total Current Assets | W13: =SUM(W9:W12) -> 2177
D14: Predicted Beta | H14: 1.22 | J14: SG&A | M14: 578 | N14: 548 | O14: 555 | R14: =O14 -> 555
D15: Marginal Tax | H15: 0.2 | J15: EBIT | M15: =M13-M14 -> 289 | N15: =N13-N14 -> 374 | O15: =O13-O14 -> 348 | R15: =O15 -> 348 | T15: Property, Plant & Equivalent, net | W15: 1577
J16: Interest Expense | M16: -145 | N16: -180 | O16: -317 | R16: =O16 -> -317 | T16: Goodwill & Intangible Assets | W16: =3454+2229 -> 5683
D17: Selected Market Data | J17: Other Income/(Expense) | M17: =55-1+18-30+124 -> 166 | N17: =49+31+1245-213+257 -> 1369 | O17: =50-46-15-40+101 -> 50 | T17: Other Assets | W17: =186+442+328+518+3125 -> 4599
D18: Current Price | H18: 166.5 | J18: Pre-tax Income | M18: =SUM(M15:M17) -> 310 | N18: =SUM(N15:N17) -> 1563 | O18: =SUM(O15:O17) -> 81 | R18: =O18 -> 81 | T18: Total Assets | W18: =SUM(W15:W17)+W13 -> 14036
D19: % of 52-week High | H19: =H18/H20 -> 0.92228438 | J19: Income Taxes | M19: -90 | N19: -267 | O19: -130 | R19: =O19 -> -130
D20: 52-week High Price | H20: 180.53 | J20: Non-controlling Interest | M20: 0 | N20: 0 | O20: -3 | R20: =O20 -> -3 | T20: Current Portion of Long-term Debt | W20: 6
D21: 52-week Low Price | H21: 102.93 | J21: Preferred Dividends | M21: 0 | N21: 0 | O21: 0 | R21: =O21 -> 0 | T21: Accounts Payable | W21: 451
D22: Dividend Per Share | H22: 0.6 | J22: Net Income | M22: =SUM(M18:M21) -> 220 | N22: =SUM(N18:N21) -> 1296 | O22: =SUM(O18:O21) -> -52 | R22: =O22 -> -52 | T22: Accrued Liabilities | W22: 1584
J23: Effective Tax Rate | M23: =ABS(M19/M18) -> 0.29032258 | N23: =ABS(N19/N18) -> 0.17082534 | O23: =ABS(O19/O18) -> 1.6049383 | R23: =O23 -> 1.6049383 | T23: Other Current Liabilties | W23: =592+226+35 -> 853
D24: Fully Diluted Shares Outstanding | H24: =X44 -> 96.204061 | T24: Total Current Liabilities | W24: =SUM(W20:W23) -> 2894
D25: Equity Value | H25: =H24*H18 -> 16017.976 | J25: Weighted Avg. Diluted Shares | M25: 107.72696 | N25: 102.4241 | O25: =H24 -> 96.204061 | R25: =O25 -> 96.204061
J26: Diluted EPS | M26: =M22/M25 -> 2.0422 | N26: =N22/N25 -> 12.653272 | O26: =O22/O25 -> -0.54051772 | R26: =O26 -> -0.54051772 | T26: Total Debt | W26: 4272
D27: Plus: Total Debt | H27: =+W20+W26 -> 4278 | T27: Other Long-term Liabilities | W27: =1012+243+1956 -> 3211
D28: Plus: Preferred Stock | H28: =+W31 -> 0 | J28: Adjusted Income Statement | T28: Total Liabilities | W28: =SUM(W26:W27)+W24 -> 10377
D29: Plus: Non-controlling Intererst | H29: =+W30 -> 325 | J29: Reported Gross Profit | M29: =M13 -> 867 | N29: =N13 -> 922 | O29: =O13 -> 903 | R29: =O29 -> 903
D30: Less: Cash & Cash Equivalents | H30: =-W9 -> -788 | J30: Non-recurring items in COGS | M30: 0 | N30: 0 | O30: 0 | R30: =O30 -> 0 | T30: Non-Controlling Interest | W30: 325
D31: Enterprise Value | H31: =SUM(H25:H30) -> 19832.976 | J31: Adj. Gross Profit | M31: =SUM(M29:M30) -> 867 | N31: =SUM(N29:N30) -> 922 | O31: =SUM(O29:O30) -> 903 | R31: =O31 -> 903 | T31: Preferred Stock | W31: 0
J32: % Margin | M32: =M31/M$11 -> 0.1300435 | N32: =N31/N$11 -> 0.13868833 | O32: =O31/O$11 -> 0.12716519 | R32: =O32 -> 0.12716519 | T32: Shareholder's Equity | W32: 3334
D33: Trading Multiples | T33: Total Liabilities & Equity | W33: =SUM(W30:W32)+W28 -> 14036
E34: LTM 12/31/2025 | F34: NFY 12/31/2026 | G34: NFY+1 12/31/2027 | H34: NFY+2 12/31/2028 | J34: Reported EBIT | M34: =M15 -> 289 | N34: =N15 -> 374 | O34: =O15 -> 348 | R34: =O34 -> 348
J35: Non-recurring items in COGS | M35: 0 | N35: 0 | O35: 0 | R35: =O35 -> 0 | T35: Balance Check | W35: =IF(W33=W18,W18-W33,W18-W33) -> 0
D36: EV/Sales | E36: =$H$31/E37 -> 2.7929835 | F36: =$H$31/F37 -> 2.7564943 | G36: =$H$31/G37 -> 2.5647195 | H36: =$H$31/H37 -> 2.3999245 | J36: Other Non-recurring items | M36: =M37-M34 -> 343 | N36: =N37-N34 -> 389 | O36: =O37-O34 -> 486 | R36: =O36 -> 486
D37: Metric | E37: =R11 -> 7101 | F37: 7195 | G37: 7733 | H37: 8264 | J37: Adjusted EBIT | M37: =M41-M40 -> 632 | N37: =N41-N40 -> 763 | O37: =O41-O40 -> 834 | R37: =O37 -> 834
D38: EV/EBITDA | E38: =$H$31/E39 -> 17.112145 | F38: =$H$31/F39 -> 16.821863 | G38: =$H$31/G39 -> 15.128128 | H38: =$H$31/H39 -> 13.328613 | J38: % Margin | M38: =M37/M$11 -> 0.09479526 | N38: =N37/N$11 -> 0.11477136 | O38: =O37/O$11 -> 0.11744825 | R38: =O38 -> 0.11744825 | T38: Calculation of Fully Diluted Shares Outstanding
D39: Metric | E39: =R41 -> 1159 | F39: 1179 | G39: 1311 | H39: 1488 | T39: Basic Shares Outstanding | X39: 95.504061
D40: EV/EBIT | E40: =$H$31/E41 -> 56.991311 | F40: =$H$31/F41 -> 30.758338 | G40: =$H$31/G41 -> 24.812932 | H40: =$H$31/H41 -> 21.597491 | J40: Depreciation & Amortization | M40: 397 | N40: 333 | O40: 325 | R40: =O40 -> 325 | T40: Plus: Shares from In-the-Money Options | X40: =W54 -> 4.880074
D41: Metric | E41: =R34 -> 348 | F41: 644.8 | G41: 799.3 | H41: 918.3 | J41: Adjusted EBITDA | M41: 1029 | N41: 1096 | O41: 1159 | R41: =O41 -> 1159 | T41: Less: Shares Repurchased | X41: =-X54/H18 -> -2.7774793
D42: P/E | E42: =$H$18/E43 -> -308.038 | F42: =$H$18/F43 -> 57.216495 | G42: =$H$18/G43 -> 39.642857 | H42: =$H$18/H43 -> 32.267442 | J42: % Margin | M42: =M41/M$11 -> 0.15434228 | N42: =N41/N$11 -> 0.16486161 | O42: =O41/O$11 -> 0.16321645 | R42: =O42 -> 0.16321645 | T42: Net New Shares from Options | X42: 0.7
D43: Metric | E43: =R26 -> -0.54051772 | F43: 2.91 | G43: 4.2 | H43: 5.16 | T43: Plus: Shares from Convertible Securities | X43: 0
D44: FCF Yield | E44: =E45/$H$25 -> 0.166001 | F44: =F45/$H$25 -> 0.026332915 | G44: =G45/$H$25 -> 0.037376757 | H44: =H45/$H$25 -> 0.03966169 | J44: Reported Net Income | M44: =M22 -> 220 | N44: =N22 -> 1296 | O44: =O22 -> -52 | R44: =O44 -> -52 | T44: Fully Diluted Shares Outstanding | X44: =X39+X42 -> 96.204061
D45: Metric | E45: =R58 -> 2659 | F45: 421.8 | G45: 598.7 | H45: 635.3 | J45: Non-recurring items in COGS | M45: =M30 -> 0 | N45: 0 | O45: 0 | R45: =O45 -> 0
J46: Other Non-recurring items | M46: =M35 -> 0 | N46: 0 | O46: 0 | R46: =O46 -> 0 | T46: Options/Warrants
D47: LTM Return on Investment Ratio | J47: Non-operating Non-rec. Items | M47: =M36 -> 343 | N47: =N36 -> 389 | O47: =O36 -> 486 | R47: =O47 -> 486 | U47: Number of Shares | V47: Exercise Price | W47: In-the-Money Shares | X47: Proceeds
D48: Return on Invested Capital | H48: =R49/(W26-W9+W32) -> 0.049398651 | J48: Tax Adjustment | M48: =-M47*$H$15 -> -68.6 | N48: =-N47*$H$15 -> -77.8 | O48: =-O47*$H$15 -> -97.2 | R48: =O48 -> -97.2 | T48: Tranche
D49: Return on Equity | H49: =ABS(R49/W32) -> 0.1010198 | J49: Adjusted Net Income | M49: =SUM(M44:M48) -> 494.4 | N49: =SUM(N44:N48) -> 1607.2 | O49: =SUM(O44:O48) -> 336.8 | R49: =O49 -> 336.8 | T49: Tranche 1 | U49: 3.484151 | V49: 80.75 | W49: =IF(V49<$H$18,U49,0) -> 3.484151 | X49: =IF(W49>0,U49*V49,0) -> 281.34519
D50: Return on Assets | H50: =ABS(R49/W18) -> 0.02399544 | J50: % Margin | M50: =M49/M$11 -> 0.074156292 | N50: =N49/N$11 -> 0.24175692 | O50: =O49/O$11 -> 0.047429939 | R50: =O50 -> 0.047429939 | T50: Tranche 2 | U50: 0.955167 | V50: 127.32 | W50: =IF(V50<$H$18,U50,0) -> 0.955167 | X50: =IF(W50>0,U50*V50,0) -> 121.61186
D51: Implied Annual Dividend per Share | H51: =H22/H18 -> 0.0036036036 | T51: Tranche 3 | U51: 0.440756 | V51: 134.98 | W51: =IF(V51<$H$18,U51,0) -> 0.440756 | X51: =IF(W51>0,U51*V51,0) -> 59.493245
J52: Adjusted Diluted EPS | M52: =M49/M25 -> 4.5893804 | N52: =N49/N25 -> 15.691619 | O52: =O49/O25 -> 3.5008917 | R52: =O52 -> 3.5008917 | T52: Tranche 4 | U52: 0 | V52: 0 | W52: 0 | X52: 0
D53: LTM Credit Statistics | T53: Tranche 5 | U53: 0 | V53: 0 | W53: 0 | X53: 0
D54: Debt/Total Capitalization | H54: =W26/(W26+W32) -> 0.56166185 | J54: Cash Flow Statement Data | T54: Total | U54: =SUM(U49:U53) -> 4.880074 | V54: =SUM(V49:V53) -> 343.05 | W54: =SUM(W49:W53) -> 4.880074 | X54: =SUM(X49:X53) -> 462.4503
D55: Total Debt/EBITDA | H55: =W26/R41 -> 3.6859362 | J55: Cash From Operations | M55: 3170 | N55: 2749 | O55: 3212 | R55: =O55 -> 3212
D56: Net Debt/EBITDA | H56: =(W26-W9)/R41 -> 3.0060397 | J56: Capital Expenditure | M56: =350+604 -> 954 | N56: =750+26 -> 776 | O56: =101+452 -> 553 | R56: =O56 -> 553 | T56: Convertible Securities
D57: EBITDA/Interest Expense | H57: =ABS(R41/R16) -> 3.6561514 | J57: % Sales | M57: =M56/M$11 -> 0.14309285 | N57: =N56/N$11 -> 0.11672684 | O57: =O56/O$11 -> 0.077876355 | R57: =O57 -> 0.077876355 | U57: Amount | V57: Conversion Price | W57: Conversion Ratio | X57: New Shares
D58: (EBITDA - Capex)/Interest Expense | H58: =ABS((R41-R56)/R16) -> 1.9116719 | J58: Free Cash Flow | M58: =M55-M56 -> 2216 | N58: =N55-N56 -> 1973 | O58: =O55-O56 -> 2659 | R58: =O58 -> 2659
D59: EBIT/Interest Expense | H59: =ABS(R37/R16) -> 2.6309148 | J59: % Margin | M59: =M58/M$11 -> 0.33238338 | N59: =N58/N$11 -> 0.29678099 | O59: =O58/O$11 -> 0.3744543 | R59: =O59 -> 0.3744543 | T59: Issue 1 | U59: 0 | V59: 0 | W59: 0 | X59: 0
J60: FCF/Share | M60: =M58/M25 -> 20.570524 | N60: =N58/N25 -> 19.263045 | O60: =O58/O25 -> 27.639166 | R60: =O60 -> 27.639166 | T60: Issue 2 | U60: 0 | V60: 0 | W60: 0 | X60: 0
D61: Growth Rates | T61: Issue 3 | U61: 0 | V61: 0 | W61: 0 | X61: 0
E62: Sales | F62: EBITDA | G62: FCF | H62: EPS | J62: Depreciation & Amortization | M62: =M40 -> 397 | N62: =N40 -> 333 | O62: =O40 -> 325 | R62: =O62 -> 325 | T62: Issue 4 | U62: 0 | V62: 0 | W62: 0 | X62: 0
D63: Historical | J63: % Sales | M63: =M62/M$11 -> 0.059547023 | N63: =N62/N$11 -> 0.050090253 | O63: =O62/O$11 -> 0.045768202 | R63: =O63 -> 0.045768202 | T63: Issue 5 | U63: 0 | V63: 0 | W63: 0 | X63: 0
D64: 1-year | E64: =O11/N11-1 -> 0.068140794 | F64: =O41/N41-1 -> 0.057481752 | G64: =O58/N58-1 -> 0.34769387 | H64: =O26/N26-1 -> -1.0427176 | T64: Total | U64: =SUM(U59:U63) -> 0 | V64: =SUM(V59:V63) -> 0 | W64: =SUM(W59:W63) -> 0 | X64: =SUM(X59:X63) -> 0
D65: 2-year CAGR | E65: =_xlfn.RRI(2,M11,O11) -> 0.032035244 | F65: =_xlfn.RRI(2,M41,O41) -> 0.061289899 | G65: =_xlfn.RRI(2,M58,O58) -> 0.09540392 | H65: =_xlfn.RRI(2,M26,O26) -> #NUM!
D66: Estimated | J66: Notes
D67: 1-year | E67: =F37/E37-1 -> 0.013237572 | F67: =F39/E39-1 -> 0.017256255 | G67: =F45/E45-1 -> -0.84136894 | H67: =F43/E43-1 -> -6.3837273
D68: 2-year CAGR | E68: =_xlfn.RRI(2,E37,G37) -> 0.04355237 | F68: =_xlfn.RRI(2,E39,G39) -> 0.063554202 | G68: =_xlfn.RRI(2,E45,G45) -> -0.5254899 | H68: =_xlfn.RRI(2,E43,G43) -> #NUM!
D69: Long-term | H69: 0.07

Sheet WH
D2: Wyndham Hotels & Resorts Inc. (NYSE: WH)
D3: Input Page
D4: ($ in millions, except per share data)
D7: General Information | J7: Reported Income Statement | T7: Balance Sheet Data
D8: Company Name | H8: Wyndham Hotels & Resorts Inc. | P8: Prior Stub 12/31/2025 | Q8: Current Stub 12/31/2025 | R8: LTM 12/31/2025 | W8: 2025A | X8: -
D9: Ticker | H9: WH | M9: Fiscal Year Ending December 31, | T9: Cash & Cash Equivalents | W9: 64
D10: Stock Exchange | H10: NYSE | M10: 2023A | N10: 2024A | O10: 2025A | T10: Accounts Receivables | W10: 291
D11: Fisical Year Ending | H11: 12/31/2025 | J11: Sales | M11: 1397 | N11: 1408 | O11: 1429 | R11: =O11 -> 1429 | T11: Prepaid Expenses | W11: 33
D12: Moody's Corporate Rating | H12: Ba2 | J12: COGS (incl. D&A) | M12: =894-569-94 -> 231 | N12: =913-564-81 -> 268 | O12: =1027-565-168 -> 294 | R12: =O12 -> 294 | T12: Other Current Assets | W12: 47
D13: S&P Corporate Rating | H13: BB+ | J13: Gross Profit | M13: =M11-M12 -> 1166 | N13: =N11-N12 -> 1140 | O13: =O11-O12 -> 1135 | R13: =O13 -> 1135 | T13: Total Current Assets | W13: =SUM(W9:W12) -> 435
D14: Predicted Beta | H14: 1.01 | J14: SG&A | M14: 130 | N14: 130 | O14: 125 | R14: =O14 -> 125
D15: Marginal Tax | H15: 0.2 | J15: Other Income/(Expense) | M15: 569 | N15: 564 | O15: 565 | R15: =O15 -> 565 | T15: Property, Plant & Equivalent, net | W15: 104
J16: EBIT | M16: =M13-M14-M15 -> 467 | N16: =N13-N14-N15 -> 446 | O16: =O13-O14-O15 -> 445 | R16: =O16 -> 445 | T16: Goodwill & Intangible Assets | W16: =1525+1208+282 -> 3015
D17: Selected Market Data | J17: Interest Expense | M17: -102 | N17: -124 | O17: -139 | R17: =O17 -> -139 | T17: Other Assets | W17: 628
D18: Current Price | H18: 88.18 | J18: Early extingushment of debt | M18: -3 | N18: -3 | O18: 0 | R18: =O18 -> 0 | T18: Total Assets | W18: =SUM(W15:W17)+W13 -> 4182
D19: % of 52-week High | H19: =H18/H20 -> 0.95134319 | J19: Pre-tax Income | M19: =SUM(M16:M18) -> 362 | N19: =SUM(N16:N18) -> 319 | O19: =SUM(O16:O18) -> 306 | R19: =O19 -> 306
D20: 52-week High Price | H20: 92.69 | J20: Income Taxes | M20: -109 | N20: -79 | O20: -70 | R20: =O20 -> -70 | T20: Current Portion of Long-term Debt | W20: 45
D21: 52-week Low Price | H21: 69.21 | J21: Non-controlling Interest | M21: 0 | N21: 0 | O21: 0 | R21: =O21 -> 0 | T21: Accounts Payable | W21: 38
D22: Dividend Per Share | H22: 1.72 | J22: Preferred Dividends | M22: 0 | N22: 0 | O22: 0 | R22: =O22 -> 0 | T22: Deferred Revenue | W22: 134
J23: Net Income | M23: =SUM(M19:M22) -> 253 | N23: =SUM(N19:N22) -> 240 | O23: =SUM(O19:O22) -> 236 | R23: =O23 -> 236 | T23: Other Current Liabilties | W23: 290
D24: Fully Diluted Shares Outstanding | H24: =X44 -> 76.819472 | J24: Effective Tax Rate | M24: =ABS(M20/M19) -> 0.30110497 | N24: =ABS(N20/N19) -> 0.2476489 | O24: =ABS(O20/O19) -> 0.22875817 | R24: =O24 -> 0.22875817 | T24: Total Current Liabilities | W24: =SUM(W20:W23) -> 507
D25: Equity Value | H25: =H24*H18 -> 6773.941
J26: Weighted Avg. Diluted Shares | M26: 84.9 | N26: 80.1 | O26: 77.2 | R26: =O26 -> 77.2 | T26: Total Debt | W26: 2515
D27: Plus: Total Debt | H27: =+W20+W26 -> 2560 | J27: Diluted EPS | M27: =M23/M26 -> 2.9799764 | N27: =N23/N26 -> 2.9962547 | O27: =O23/O26 -> 3.0569948 | R27: =O27 -> 3.0569948 | T27: Other Long-term Liabilities | W27: =271+220+201 -> 692
D28: Plus: Preferred Stock | H28: =+W31 -> 0 | T28: Total Liabilities | W28: =SUM(W26:W27)+W24 -> 3714
D29: Plus: Non-controlling Intererst | H29: =+W30 -> 0 | J29: Adjusted Income Statement
D30: Less: Cash & Cash Equivalents | H30: =-W9 -> -64 | J30: Reported Gross Profit | M30: =M13 -> 1166 | N30: =N13 -> 1140 | O30: =O13 -> 1135 | R30: =O30 -> 1135 | T30: Non-Controlling Interest | W30: 0
D31: Enterprise Value | H31: =SUM(H25:H30) -> 9269.941 | J31: Non-recurring items in COGS | M31: 0 | N31: 0 | O31: 0 | R31: =O31 -> 0 | T31: Preferred Stock | W31: 0
J32: Adj. Gross Profit | M32: =SUM(M30:M31) -> 1166 | N32: =SUM(N30:N31) -> 1140 | O32: =SUM(O30:O31) -> 1135 | R32: =O32 -> 1135 | T32: Shareholder's Equity | W32: 468
D33: Trading Multiples | J33: % Margin | M33: =M32/M$11 -> 0.83464567 | N33: =N32/N$11 -> 0.80965909 | O33: =O32/O$11 -> 0.79426172 | R33: =O33 -> 0.79426172 | T33: Total Liabilities & Equity | W33: =SUM(W30:W32)+W28 -> 4182
E34: LTM 12/31/2025 | F34: NFY 12/31/2026 | G34: NFY+1 12/31/2027 | H34: NFY+2 12/31/2028
J35: Reported EBIT | M35: =M16 -> 467 | N35: =N16 -> 446 | O35: =O16 -> 445 | R35: =O35 -> 445 | T35: Balance Check | W35: =IF(W33=W18,W18-W33,W18-W33) -> 0
D36: EV/Sales | E36: =$H$31/E37 -> 6.4870126 | F36: =$H$31/F37 -> 6.2592444 | G36: =$H$31/G37 -> 5.9195026 | H36: =$H$31/H37 -> 5.5508629 | J36: Non-recurring items in COGS | M36: 0 | N36: 0 | O36: 0 | R36: =O36 -> 0
D37: Metric | E37: =R11 -> 1429 | F37: 1481 | G37: 1566 | H37: 1670 | J37: Other Non-recurring items | M37: =M38-M35 -> 116 | N37: =N38-N35 -> 177 | O37: =O38-O35 -> 211 | R37: =O37 -> 211
D38: EV/EBITDA | E38: =$H$31/E39 -> 12.910781 | F38: =$H$31/F39 -> 12.508354 | G38: =$H$31/G39 -> 11.722232 | H38: =$H$31/H39 -> 10.786527 | J38: Adjusted EBIT | M38: =M42-M41 -> 583 | N38: =N42-N41 -> 623 | O38: =O42-O41 -> 656 | R38: =O38 -> 656 | T38: Calculation of Fully Diluted Shares Outstanding
D39: Metric | E39: =R42 -> 718 | F39: 741.1 | G39: 790.8 | H39: 859.4 | J39: % Margin | M39: =M38/M$11 -> 0.41732283 | N39: =N38/N$11 -> 0.44247159 | O39: =O38/O$11 -> 0.45906228 | R39: =O39 -> 0.45906228 | T39: Basic Shares Outstanding | X39: 76.8
D40: EV/EBIT | E40: =$H$31/E41 -> 14.131008 | F40: =$H$31/F41 -> 15.296932 | G40: =$H$31/G41 -> 14.250486 | H40: =$H$31/H41 -> 12.777314 | T40: Plus: Shares from In-the-Money Options | X40: =W54 -> 1.3
D41: Metric | E41: =R38 -> 656 | F41: 606 | G41: 650.5 | H41: 725.5 | J41: Depreciation & Amortization | M41: 76 | N41: 71 | O41: 62 | R41: =O41 -> 62 | T41: Less: Shares Repurchased | X41: =-X54/H18 -> -1.2805285
D42: P/E | E42: =$H$18/E43 -> 28.845322 | F42: =$H$18/F43 -> 19.169565 | G42: =$H$18/G43 -> 17.148969 | H42: =$H$18/H43 -> 14.94323 | J42: Adjusted EBITDA | M42: 659 | N42: 694 | O42: 718 | R42: =O42 -> 718 | T42: Net New Shares from Options | X42: =SUM(X40:X41) -> 0.019471535
D43: Metric | E43: =R27 -> 3.0569948 | F43: 4.6 | G43: 5.142 | H43: 5.901 | J43: % Margin | M43: =M42/M$11 -> 0.47172513 | N43: =N42/N$11 -> 0.49289773 | O43: =O42/O$11 -> 0.50244927 | R43: =O43 -> 0.50244927 | T43: Plus: Shares from Convertible Securities | X43: 0
D44: FCF Yield | E44: =E45/$H$25 -> 0.047387481 | F44: =F45/$H$25 -> 0.06415763 | G44: =G45/$H$25 -> 0.068881616 | H44: 0.065 | T44: Fully Diluted Shares Outstanding | X44: =X39+X42 -> 76.819472
D45: Metric | E45: =R59 -> 321 | F45: 434.6 | G45: 466.6 | H45: =H44*H25 -> 440.30617 | J45: Reported Net Income | M45: =M23 -> 253 | N45: =N23 -> 240 | O45: =O23 -> 236 | R45: =O45 -> 236
J46: Non-recurring items in COGS | M46: =M31 -> 0 | N46: 0 | O46: 0 | R46: =O46 -> 0 | T46: Options/Warrants
D47: LTM Return on Investment Ratio | J47: Other Non-recurring items | M47: =M36 -> 0 | N47: 0 | O47: 0 | R47: =O47 -> 0 | U47: Number of Shares | V47: Exercise Price | W47: In-the-Money Shares | X47: Proceeds
D48: Return on Invested Capital | H48: =R50/(W26-W9+W32) -> 0.13867763 | J48: Non-operating Non-rec. Items | M48: =M37 -> 116 | N48: =N37 -> 177 | O48: =O37 -> 211 | R48: =O48 -> 211 | T48: Tranche
D49: Return on Equity | H49: =ABS(R50/W32) -> 0.86495726 | J49: Tax Adjustment | M49: =-M48*$H$15 -> -23.2 | N49: =-N48*$H$15 -> -35.4 | O49: =-O48*$H$15 -> -42.2 | R49: =O49 -> -42.2 | T49: Tranche 1 | U49: 0.8 | V49: 87.29 | W49: =IF(V49<$H$18,U49,0) -> 0.8 | X49: =IF(W49>0,U49*V49) -> 69.832
D50: Return on Assets | H50: =ABS(R50/W18) -> 0.096795791 | J50: Adjusted Net Income | M50: =SUM(M45:M49) -> 345.8 | N50: =SUM(N45:N49) -> 381.6 | O50: =SUM(O45:O49) -> 404.8 | R50: =O50 -> 404.8 | T50: Tranche 2 | U50: 0.5 | V50: 86.17 | W50: =IF(V50<$H$18,U50,0) -> 0.5 | X50: =IF(W50>0,U50*V50) -> 43.085
D51: Implied Annual Dividend per Share | H51: =H22/H18 -> 0.019505557 | J51: % Margin | M51: =M50/M$11 -> 0.24753042 | N51: =N50/N$11 -> 0.27102273 | O51: =O50/O$11 -> 0.28327502 | R51: =O51 -> 0.28327502 | T51: Tranche 3 | U51: 0 | V51: 0 | W51: 0 | X51: 0
T52: Tranche 4 | U52: 0 | V52: 0 | W52: 0 | X52: 0
D53: LTM Credit Statistics | J53: Adjusted Diluted EPS | M53: =M50/M26 -> 4.0730271 | N53: =N50/N26 -> 4.7640449 | O53: =O50/O26 -> 5.2435233 | R53: =O53 -> 5.2435233 | T53: Tranche 5 | U53: 0 | V53: 0 | W53: 0 | X53: 0
D54: Debt/Total Capitalization | H54: =W26/(W26+W32) -> 0.84311096 | T54: Total | U54: =SUM(U49:U53) -> 1.3 | V54: =SUM(V49:V53) -> 173.46 | W54: =SUM(W49:W53) -> 1.3 | X54: =SUM(X49:X53) -> 112.917
D55: Total Debt/EBITDA | H55: =W26/R42 -> 3.5027855 | J55: Cash Flow Statement Data
D56: Net Debt/EBITDA | H56: =(W26-W9)/R42 -> 3.413649 | J56: Cash From Operations | M56: 376 | N56: 2290 | O56: 367 | R56: =O56 -> 367 | T56: Convertible Securities
D57: EBITDA/Interest Expense | H57: =ABS(R42/R17) -> 5.1654676 | J57: Capital Expenditure | M57: 37 | N57: 49 | O57: 46 | R57: =O57 -> 46 | U57: Amount | V57: Conversion Price | W57: Conversion Ratio | X57: New Shares
D58: (EBITDA - Capex)/Interest Expense | H58: =ABS((R42-R57)/R17) -> 4.8345324 | J58: % Sales | M58: =M57/M$11 -> 0.026485326 | N58: =N57/N$11 -> 0.034801136 | O58: =O57/O$11 -> 0.032190343 | R58: =O58 -> 0.032190343
D59: EBIT/Interest Expense | H59: =ABS(R38/R17) -> 4.7194245 | J59: Free Cash Flow | M59: =M56-M57 -> 339 | N59: =N56-N57 -> 2241 | O59: =O56-O57 -> 321 | R59: =O59 -> 321 | T59: Issue 1 | U59: 0 | V59: 0 | W59: 0 | X59: 0
J60: % Margin | M60: =M59/M$11 -> 0.24266285 | N60: =N59/N$11 -> 1.5916193 | O60: =O59/O$11 -> 0.22463261 | R60: =O60 -> 0.22463261 | T60: Issue 2 | U60: 0 | V60: 0 | W60: 0 | X60: 0
D61: Growth Rates | J61: FCF/Share | M61: =M59/M26 -> 3.9929329 | N61: =N59/N26 -> 27.977528 | O61: =O59/O26 -> 4.1580311 | R61: =O61 -> 4.1580311 | T61: Issue 3 | U61: 0 | V61: 0 | W61: 0 | X61: 0
E62: Sales | F62: EBITDA | G62: FCF | H62: EPS | T62: Issue 4 | U62: 0 | V62: 0 | W62: 0 | X62: 0
D63: Historical | J63: Depreciation & Amortization | M63: =M41 -> 76 | N63: =N41 -> 71 | O63: =O41 -> 62 | R63: =O63 -> 62 | T63: Issue 5 | U63: 0 | V63: 0 | W63: 0 | X63: 0
D64: 1-year | E64: =O11/N11-1 -> 0.014914773 | F64: =O42/N42-1 -> 0.034582133 | G64: =O59/N59-1 -> -0.85676037 | H64: =O27/N27-1 -> 0.020272021 | J64: % Sales | M64: =M63/M$11 -> 0.054402291 | N64: =N63/N$11 -> 0.050426136 | O64: =O63/O$11 -> 0.043386984 | R64: =O64 -> 0.043386984 | T64: Total | U64: =SUM(U59:U63) -> 0 | V64: =SUM(V59:V63) -> 0 | W64: =SUM(W59:W63) -> 0 | X64: =SUM(X59:X63) -> 0
D65: 2-year CAGR | E65: =_xlfn.RRI(2,M11,O11) -> 0.011388267 | F65: =_xlfn.RRI(2,M42,O42) -> 0.043805341 | G65: =_xlfn.RRI(2,M59,O59) -> -0.026910767 | H65: =_xlfn.RRI(2,M27,O27) -> 0.012840213
D66: Estimated
D67: 1-year | E67: =F37/E37-1 -> 0.036389083 | F67: =F39/E39-1 -> 0.032172702 | G67: =F45/E45-1 -> 0.35389408 | H67: =F43/E43-1 -> 0.50474576 | J67: Notes
D68: 2-year CAGR | E68: =_xlfn.RRI(2,E37,G37) -> 0.046838688 | F68: =_xlfn.RRI(2,E39,G39) -> 0.049472609 | G68: =_xlfn.RRI(2,E45,G45) -> 0.20564611 | H68: =_xlfn.RRI(2,E43,G43) -> 0.29693642
D69: Long-term | H69: 0.08

Sheet Comps1
D2: Choice Hotels International Inc. (NYSE: CHH)
D3: Company Comparable Analysis (Trading Multiples Output Page)
D4: ($ in millions, except per share data)
F7: Current Share Price | G7: % of 52-week High | J7: Enterprise Value / | S7: LTM | T7: Total | U7: Price/ | X7: LT
H8: Equity | I8: Enterprise | J8: LTM | K8: 2026E | L8: 2027E | M8: LTM | N8: 2026E | O8: 2027E | P8: LTM | Q8: 2026E | R8: 2027E | S8: EBITDA | T8: Debt/ | U8: LTM | V8: 2026E | W8: 2027E | X8: EPS
D9: Company | E9: Ticker | H9: Value | I9: Value | J9: Sales | K9: Sales | L9: Sales | M9: EBITDA | N9: EBITDA | O9: EBITDA | P9: EBIT | Q9: EBIT | R9: EBIT | S9: Margin | T9: EBITDA | U9: EPS | V9: EPS | W9: EPS | X9: Growth
D11: Consumer Discretionary
D12: =MAR!H8 -> Marriott International Inc. | E12: MAR | F12: =MAR!H18 -> 363.98 | G12: =MAR!H19 -> 0.98372973 | H12: =MAR!H25 -> 96703.864 | I12: =MAR!H31 -> 112549.86 | J12: =MAR!E36 -> 4.298093 | K12: =MAR!F36 -> 4.0339007 | L12: =MAR!G36 -> 3.8293989 | M12: =MAR!E38 -> 23.972282 | N12: =MAR!F38 -> 19.076248 | O12: =MAR!G38 -> 17.794445 | P12: =MAR!E40 -> 27.120449 | Q12: =MAR!F40 -> 22.769546 | R12: =MAR!G40 -> 20.935615 | S12: =HLT!R42 -> 0.29387823 | T12: =MAR!H55 -> 3.1938232 | U12: =MAR!E43 -> 9.5065789 | V12: =MAR!F43 -> 11.310405 | W12: =MAR!G43 -> 12.27019 | X12: =MAR!H69 -> 0.06
D13: =ABNB!H8 -> Airbnb Inc. Cl A | E13: ABNB | F13: =ABNB!H18 -> 134.51 | G13: =ABNB!H19 -> 0.93487629 | H13: =ABNB!H25 -> 83701.62 | I13: =ABNB!H31 -> 79140.62 | J13: =ABNB!E36 -> 6.4652087 | K13: =ABNB!F36 -> 5.7779528 | L13: =ABNB!G36 -> 5.2487478 | M13: =ABNB!E38 -> 18.417645 | N13: =ABNB!F38 -> 16.446513 | O13: =ABNB!G38 -> 14.652957 | P13: =ABNB!E40 -> 31.108734 | Q13: =ABNB!F40 -> 26.424247 | R13: =ABNB!G40 -> 22.57935 | S13: =ABNB!R43 -> 0.35103341 | T13: =ABNB!H55 -> 0 | U13: =ABNB!E42 -> 22.269394 | V13: =ABNB!F42 -> 27.956453 | W13: =ABNB!G42 -> 24.481316 | X13: =ABNB!H69 -> 0.12
D14: =HLT!H8 -> Hilton Worldwide Holdings Inc. | E14: HLT | F14: =HLT!H18 -> 330.71 | G14: =HLT!H19 -> 0.99056491 | H14: =HLT!H25 -> 78279.057 | I14: =HLT!H31 -> 89714.057 | J14: =HLT!E36 -> 7.4519526 | K14: =HLT!F36 -> 6.8510162 | L14: =HLT!G36 -> 6.3227893 | M14: =HLT!E38 -> 25.35728 | N14: =HLT!F38 -> 22.25051 | O14: =HLT!G38 -> 20.412755 | P14: =HLT!E40 -> 33.313798 | Q14: =HLT!F40 -> 25.936414 | R14: =HLT!G40 -> 23.509973 | S14: =HLT!R38 -> 0.27917601 | T14: =HLT!H55 -> 3.4872809 | U14: =HLT!E42 -> 53.579094 | V14: =HLT!F42 -> 37.580682 | W14: =HLT!G42 -> 33.203815 | X14: =HLT!H69 -> 0.145
D15: =H!H8 -> Hyatt Hotels Corporation | E15: H | F15: =H!H18 -> 166.5 | G15: =H!H19 -> 0.92228438 | H15: =H!H25 -> 16017.976 | I15: =H!H31 -> 19832.976 | J15: =H!E36 -> 2.7929835 | K15: =H!F36 -> 2.7564943 | L15: =H!G36 -> 2.5647195 | M15: =H!E38 -> 17.112145 | N15: =H!F38 -> 16.821863 | O15: =H!G38 -> 15.128128 | P15: =H!E40 -> 56.991311 | Q15: =H!F40 -> 30.758338 | R15: =H!G40 -> 24.812932 | S15: =H!R42 -> 0.16321645 | T15: =H!H55 -> 3.6859362 | U15: =H!E42 -> -308.038 | V15: =H!F42 -> 57.216495 | W15: =H!G42 -> 39.642857 | X15: =H!H69 -> 0.07
D16: =WH!H8 -> Wyndham Hotels & Resorts Inc. | E16: WH | F16: =WH!H18 -> 88.18 | G16: =WH!H19 -> 0.95134319 | H16: =WH!H25 -> 6773.941 | I16: =WH!H31 -> 9269.941 | J16: =WH!E36 -> 6.4870126 | K16: =WH!F36 -> 6.2592444 | L16: =WH!G36 -> 5.9195026 | M16: =WH!E38 -> 12.910781 | N16: =WH!F38 -> 12.508354 | O16: =WH!G38 -> 11.722232 | P16: =WH!E40 -> 14.131008 | Q16: =WH!F40 -> 15.296932 | R16: =WH!G40 -> 14.250486 | S16: =WH!R43 -> 0.50244927 | T16: =WH!H55 -> 3.5027855 | U16: =WH!E42 -> 28.845322 | V16: =WH!F42 -> 19.169565 | W16: =WH!G42 -> 17.148969 | X16: =WH!H69 -> 0.08
D18: Mean | J18: =AVERAGE(J12:J16) -> 5.4990501 | K18: =AVERAGE(K12:K16) -> 5.1357217 | L18: =AVERAGE(L12:L16) -> 4.7770316 | M18: =AVERAGE(M12:M16) -> 19.554027 | N18: =AVERAGE(N12:N16) -> 17.420698 | O18: =AVERAGE(O12:O16) -> 15.942103 | P18: =AVERAGE(P12:P16) -> 32.53306 | Q18: =AVERAGE(Q12:Q16) -> 24.237095 | ... X18: =AVERAGE(X12:X16) -> 0.095
D19: Median | J19: =MEDIAN(J12:J16) -> 6.4652087 | K19: =MEDIAN(K12:K16) -> 5.7779528 | L19: =MEDIAN(L12:L16) -> 5.2487478 | M19: =MEDIAN(M12:M16) -> 18.417645 | N19: =MEDIAN(N12:N16) -> 16.821863 | O19: =MEDIAN(O12:O16) -> 15.128128 | P19: =MEDIAN(P12:P16) -> 31.108734 | Q19: =MEDIAN(Q12:Q16) -> 25.936414 | ... X19: =MEDIAN(X12:X16) -> 0.08
D21: Maximum | J21: =MAX(J12:J16) -> 7.4519526 | K21: =MAX(K12:K16) -> 6.8510162 | L21: =MAX(L12:L16) -> 6.3227893 | M21: =MAX(M12:M16) -> 25.35728 | N21: =MAX(N12:N16) -> 22.25051 | O21: =MAX(O12:O16) -> 20.412755 | P21: =MAX(P12:P16) -> 56.991311 | Q21: =MAX(Q12:Q16) -> 30.758338 | ... X21: =MAX(X12:X16) -> 0.145
D22: Minimum | J22: =MIN(J12:J16) -> 2.7929835 | K22: =MIN(K12:K16) -> 2.7564943 | L22: =MIN(L12:L16) -> 2.5647195 | M22: =MIN(M12:M16) -> 12.910781 | N22: =MIN(N12:N16) -> 12.508354 | O22: =MIN(O12:O16) -> 11.722232 | P22: =MIN(P12:P16) -> 14.131008 | Q22: =MIN(Q12:Q16) -> 15.296932 | ... X22: =MIN(X12:X16) -> 0.06

Sheet Comps2
D2: Choice Hotels International Inc. (NYSE: CHH)
D3: Company Comparable Analysis (For Equity Research Analysts and Equity Investors)
D4: ($ in millions, except per share data)
F6: Current Share Price | G6: % of 52-week High | L6: 2026E | M6: LTM | N6: LTM | Q6: LT
H7: Equity | I7: Enterprise | J7: EV/EBITDA | L7: EBITDA | M7: Debt/ | N7: Int Exp/ | O7: P/E | Q7: EPS | R7: Div | S7: FCF Yield
D8: Company | E8: Ticker | H8: Value | I8: Value | J8: 2026E | K8: 2027E | L8: Margin | M8: EBITDA | N8: EBITDA | O8: 2026E | P8: 2027E | Q8: Growth | R8: Yield | S8: 2026E | T8: 2027E
D10: Consumer Discretionary
D11: =Comps1!D12 -> Marriott International Inc. | E11: =Comps1!E12 -> MAR | F11: =Comps1!F12 -> 363.98 | G11: =Comps1!G12 -> 0.98372973 | H11: =Comps1!H12 -> 96703.864 | I11: =Comps1!I12 -> 112549.86 | J11: =MAR!F38 -> 19.076248 | K11: =MAR!G38 -> 17.794445 | L11: =MAR!F64 -> 0.10861865 | M11: =MAR!H55 -> 3.1938232 | N11: =MAR!H57 -> 6.2103175 | O11: =MAR!F42 -> 32.180986 | P11: =MAR!G42 -> 29.663762 | Q11: =MAR!H69 -> 0.06 | R11: =MAR!H51 -> 0.0073630419 | S11: =MAR!F44 -> 0.029140511 | T11: =MAR!G44 -> 0.03388696
D12: =Comps1!D13 -> Airbnb Inc. Cl A | E12: =Comps1!E13 -> ABNB | F12: =Comps1!F13 -> 134.51 | G12: =Comps1!G13 -> 0.93487629 | H12: =Comps1!H13 -> 83701.62 | I12: =Comps1!I13 -> 79140.62 | J12: =ABNB!F38 -> 16.446513 | K12: =ABNB!G38 -> 14.652957 | L12: =ABNB!F64 -> 0.063350656 | M12: =ABNB!H55 -> 0 | N12: =ABNB!H57 -> 38.366071 | O12: =ABNB!F42 -> 27.956453 | P12: =ABNB!G42 -> 24.481316 | Q12: =ABNB!H69 -> 0.12 | R12: =ABNB!H51 -> 0 | S12: =ABNB!F44 -> 0.061109928 | T12: =ABNB!G44 -> 0.066175541
D13: =Comps1!D14 -> Hilton Worldwide Holdings Inc. | E13: =Comps1!E14 -> HLT | F13: =Comps1!F14 -> 330.71 | G13: =Comps1!G14 -> 0.99056491 | H13: =Comps1!H14 -> 78279.057 | I13: =Comps1!I14 -> 89714.057 | J13: =HLT!F38 -> 22.25051 | K13: =HLT!G38 -> 20.412755 | L13: =HLT!F64 -> 0.071796425 | M13: =HLT!H55 -> 3.4872809 | N13: =HLT!H57 -> 5.6972625 | O13: =HLT!F42 -> 37.580682 | P13: =HLT!G42 -> 33.203815 | Q13: =HLT!H69 -> 0.145 | R13: =HLT!H51 -> 0.0018142784 | S13: =HLT!F44 -> 0.029101015 | T13: =HLT!G44 -> 0.029586458
D14: =Comps1!D15 -> Hyatt Hotels Corporation | E14: =Comps1!E15 -> H | F14: =Comps1!F15 -> 166.5 | G14: =Comps1!G15 -> 0.92228438 | H14: =Comps1!H15 -> 16017.976 | I14: =Comps1!I15 -> 19832.976 | J14: =H!F38 -> 16.821863 | K14: =H!G38 -> 15.128128 | L14: =H!F64 -> 0.057481752 | M14: =H!H55 -> 3.6859362 | N14: =H!H57 -> 3.6561514 | O14: =H!F42 -> 57.216495 | P14: =H!G42 -> 39.642857 | Q14: =H!H69 -> 0.07 | R14: =H!H51 -> 0.0036036036 | S14: =H!F44 -> 0.026332915 | T14: =H!G44 -> 0.037376757
D15: =Comps1!D16 -> Wyndham Hotels & Resorts Inc. | E15: =Comps1!E16 -> WH | F15: =Comps1!F16 -> 88.18 | G15: =Comps1!G16 -> 0.95134319 | H15: =Comps1!H16 -> 6773.941 | I15: =Comps1!I16 -> 9269.941 | J15: =WH!F38 -> 12.508354 | K15: =WH!G38 -> 11.722232 | L15: =WH!F64 -> 0.034582133 | M15: =WH!H55 -> 3.5027855 | N15: =WH!H57 -> 5.1654676 | O15: =WH!F42 -> 19.169565 | P15: =WH!G42 -> 17.148969 | Q15: =WH!H69 -> 0.08 | R15: =WH!H51 -> 0.019505557 | S15: =WH!F44 -> 0.06415763 | T15: =WH!G44 -> 0.068881616
D17: Mean | J17: =AVERAGE(J11:J15) -> 17.420698 | K17: =AVERAGE(K11:K15) -> 15.942103 | L17: =AVERAGE(L11:L15) -> 0.067165924 | M17: =AVERAGE(M11:M15) -> 2.7739652 | N17: =AVERAGE(N11:N15) -> 11.819054 | O17: =AVERAGE(O11:O15) -> 34.820836 | P17: =AVERAGE(P11:P15) -> 28.828144 | Q17: =AVERAGE(Q11:Q15) -> 0.095 | ... T17: =AVERAGE(T11:T15) -> 0.047181466
D18: Median | J18: =MEDIAN(J11:J15) -> 16.821863 | K18: =MEDIAN(K11:K15) -> 15.128128 | L18: =MEDIAN(L11:L15) -> 0.063350656 | M18: =MEDIAN(M11:M15) -> 3.4872809 | N18: =MEDIAN(N11:N15) -> 5.6972625 | O18: =MEDIAN(O11:O15) -> 32.180986 | P18: =MEDIAN(P11:P15) -> 29.663762 | Q18: =MEDIAN(Q11:Q15) -> 0.08 | ... T18: =MEDIAN(T11:T15) -> 0.037376757
D20: Maximum | J20: =MAX(J11:J15) -> 22.25051 | K20: =MAX(K11:K15) -> 20.412755 | L20: =MAX(L11:L15) -> 0.10861865 | M20: =MAX(M11:M15) -> 3.6859362 | N20: =MAX(N11:N15) -> 38.366071 | O20: =MAX(O11:O15) -> 57.216495 | P20: =MAX(P11:P15) -> 39.642857 | Q20: =MAX(Q11:Q15) -> 0.145 | ... T20: =MAX(T11:T15) -> 0.068881616
D21: Minimum | J21: =MIN(J11:J15) -> 12.508354 | K21: =MIN(K11:K15) -> 11.722232 | L21: =MIN(L11:L15) -> 0.034582133 | M21: =MIN(M11:M15) -> 0 | N21: =MIN(N11:N15) -> 3.6561514 | O21: =MIN(O11:O15) -> 19.169565 | P21: =MIN(P11:P15) -> 17.148969 | Q21: =MIN(Q11:Q15) -> 0.06 | ... T21: =MIN(T11:T15) -> 0.029586458

Sheet CompsVal
D2: Choice Hotels International Inc. (NYSE: CHH)
D3: Comparable Companies Valuation
D4: ($ in millions, except per share data)
D6: Valuation Implied by EV/EBITDA
L7: Less: | P7: Fully
E8: Financial | I8: Implied | L8: Net | M8: Implied | P8: Diluted | Q8: Implied
D9: EBITDA | E9: Metric | F9: Multiple Range | I9: Enterprise Value | L9: Debt | M9: Equity Value | P9: Shares | Q9: Share Value
D10: LTM | E10: =CHH!E39 -> 625.6 | F10: =Comps1!M22 -> 12.910781 | G10: - | H10: =Comps1!M21 -> 25.35728 | I10: =E10*F10 -> 8076.9848 | J10: - | K10: =E10*H10 -> 15863.514 | L10: =-CHH!$H$27 -> -1906.122 | M10: =I10+L10 -> 6170.8628 | N10: - | O10: =K10+L10 -> 13957.392 | P10: =CHH!$H$24 -> 46.203843 | Q10: =M10/P10 -> 133.55735 | R10: - | S10: =O10/P10 -> 302.08294
D11: 2026E | E11: =CHH!F39 -> 635.9 | F11: =Comps1!N22 -> 12.508354 | G11: - | H11: =Comps1!N21 -> 22.25051 | I11: =E11*F11 -> 7954.0622 | J11: - | K11: =E11*H11 -> 14149.099 | L11: =-CHH!$H$27 -> -1906.122 | M11: =I11+L11 -> 6047.9402 | N11: - | O11: =K11+L11 -> 12242.977 | P11: =CHH!$H$24 -> 46.203843 | Q11: =M11/P11 -> 130.89691 | R11: - | S11: =O11/P11 -> 264.97747
D12: 2027E | E12: =CHH!G39 -> 650.8 | F12: =Comps1!O22 -> 11.722232 | G12: - | H12: =Comps1!O21 -> 20.412755 | I12: =E12*F12 -> 7628.8285 | J12: - | K12: =E12*H12 -> 13284.621 | L12: =-CHH!$H$27 -> -1906.122 | M12: =I12+L12 -> 5722.7065 | N12: - | O12: =K12+L12 -> 11378.499 | P12: =CHH!$H$24 -> 46.203843 | Q12: =M12/P12 -> 123.85781 | R12: - | S12: =O12/P12 -> 246.26737
D14: Valuation Implied by P/E - Share Price
L15: Fully
D16: Net | E16: Financial | I16: Implied | L16: Diluted | M16: Implied
D17: Income | E17: Metric | F17: Multiple Range | I17: Equity Value | L17: Shares | M17: Share Value
D18: LTM | E18: =CHH!R49 -> 397.546 | F18: =Comps1!U22 -> -308.038 | G18: - | H18: =Comps1!U21 -> 53.579094 | I18: =E18*F18 -> -122459.28 | J18: - | K18: =E18*H18 -> 21300.155 | L18: =CHH!$H$24 -> 46.203843 | M18: =I18/L18 -> -2650.4132 | N18: - | O18: =K18/L18 -> 461.00397
D19: 2026E | E19: =CHH!F37*CHH!R50 -> 401.58098 | F19: =Comps1!V22 -> 11.310405 | G19: - | H19: =Comps1!V21 -> 57.216495 | I19: =E19*F19 -> 4542.0437 | J19: - | K19: =E19*H19 -> 22977.056 | L19: =CHH!$H$24 -> 46.203843 | M19: =I19/L19 -> 98.304457 | N19: - | O19: =K19/L19 -> 497.29751
D20: 2027E | E20: =CHH!G37*CHH!R50 -> 414.77614 | F20: =Comps1!W22 -> 12.27019 | G20: - | H20: =Comps1!W21 -> 39.642857 | I20: =E20*F20 -> 5089.3821 | J20: - | K20: =E20*H20 -> 16442.911 | L20: =CHH!$H$24 -> 46.203843 | M20: =I20/L20 -> 110.15062 | N20: - | O20: =K20/L20 -> 355.87757
D22: Valuation Implied by P/E - Enterprise Value
L23: Plus:
D24: Net | E24: Financial | I24: Implied | L24: Net | M24: Implied
D25: Income | E25: Metric | F25: Multiple Range | I25: Equity Value | L25: Debt | M25: Enterprise Value
D26: LTM | E26: =E18 -> 397.546 | F26: =F18 -> -308.038 | G26: - | H26: =H18 -> 53.579094 | I26: =E26*F26 -> -122459.28 | J26: - | K26: =E26*H26 -> 21300.155 | L26: =CHH!$H$27 -> 1906.122 | M26: =I26+L26 -> -120553.15 | N26: - | O26: =K26+L26 -> 23206.277
D27: 2026E | E27: =E19 -> 401.58098 | F27: =F19 -> 11.310405 | G27: - | H27: =H19 -> 57.216495 | I27: =E27*F27 -> 4542.0437 | J27: - | K27: =E27*H27 -> 22977.056 | L27: =CHH!$H$27 -> 1906.122 | M27: =I27+L27 -> 6448.1657 | N27: - | O27: =K27+L27 -> 24883.178
D28: 2027E | E28: =E20 -> 414.77614 | F28: =F20 -> 12.27019 | G28: - | H28: =H20 -> 39.642857 | I28: =E28*F28 -> 5089.3821 | J28: - | K28: =E28*H28 -> 16442.911 | L28: =CHH!$H$27 -> 1906.122 | M28: =I28+L28 -> 6995.5041 | N28: - | O28: =K28+L28 -> 18349.033

Sheet DCF->

Sheet Historical
D2: Choice Hotels International Inc. (NYSE: CHH)
D3: Financial Statements
D4: ($ in millions, except per share data)
D6: ($ in millions, except per share amounts, Fiscal year ending December 31)
D7: Choice Hotels International Inc. Summary Historical and Projection Data
D9: Operating Assumptions
F10: Historical Period | I10: Projection Period
F11: 2023A | G11: 2024A | H11: 2025A | I11: 2026E | J11: 2027E | K11: 2028E | L11: 2029E | M11: 2030E
D12: Revenue Growth % | F12: =F44/1401.949-1 -> 0.10144164 | G12: =G44/F44-1 -> 0.026340449 | H12: =H44/G44-1 -> 0.007542722 | I12: {=_xlfn.IFS(DCF!$E$5=1,1.5%,DCF!$E$5=2,2%,DCF!$E$5=3,1%)} -> 0.015 | J12: {=_xlfn.IFS(DCF!$E$5=1,3.3%,DCF!$E$5=2,4.1%,DCF!$E$5=3,2.5%)} -> 0.033 | K12: {=_xlfn.IFS(DCF!$E$5=1,3.3%,DCF!$E$5=2,3.8%,DCF!$E$5=3,2.4%)} -> 0.033 | L12: {=_xlfn.IFS(DCF!$E$5=1,3.8%,DCF!$E$5=2,4.3%,DCF!$E$5=3,2.8%)} -> 0.038 | M12: {=_xlfn.IFS(DCF!$E$5=1,3.5%,DCF!$E$5=2,4.2%,DCF!$E$5=3,2.2%)} -> 0.035
D13: COGS % Revenue | F13: =F45/F$44 -> 0.52304126 | G13: =G45/G$44 -> 0.47747752 | H13: =H45/H$44 -> 0.47577927 | I13: =H13 -> 0.47577927 | J13: =I13 -> 0.47577927 | K13: =J13 -> 0.47577927 | L13: =K13 -> 0.47577927 | M13: =L13 -> 0.47577927
D14: SG&A % Revenue | F14: =F47/F$44 -> 0.20250491 | G14: =G47/G$44 -> 0.19711024 | H14: =H47/H$44 -> 0.20601167 | I14: =H14 -> 0.20601167 | J14: =I14 -> 0.20601167 | K14: =J14 -> 0.20601167 | L14: =K14 -> 0.20601167 | M14: =L14 -> 0.20601167
D16: Depreciation & Amortization % Revenue | F16: =F48/F$44 -> 0.029166572 | G16: =G48/G$44 -> 0.032781248 | H16: =H48/H$44 -> 0.037396832 | I16: =H16 -> 0.037396832 | J16: =I16 -> 0.037396832 | K16: =J16 -> 0.037396832 | L16: =K16 -> 0.037396832 | M16: =L16 -> 0.037396832
D17: Debt Interest Rate | F17: 0 | G17: 0 | H17: 0 | I17: 0.051 | J17: =I17 -> 0.051 | K17: =J17 -> 0.051 | L17: =K17 -> 0.051 | M17: =L17 -> 0.051
D18: Interest Income % Revenue | F18: =-F52/F44 -> 0.0050279601 | G18: =-G52/G44 -> 0.0054554437 | H18: =-H52/H44 -> 0.003905954 | I18: =H18 -> 0.003905954 | J18: =I18 -> 0.003905954 | K18: =J18 -> 0.003905954 | L18: =K18 -> 0.003905954 | M18: =L18 -> 0.003905954
D19: Effective Tax Rate | F19: =F60/F59 -> 0.1865293 | G19: =G60/G59 -> 0.18044711 | H19: =H60/H59 -> 0.19764405 | I19: =CHH!H15 -> 0.2 | J19: =I19 -> 0.2 | K19: =J19 -> 0.2 | L19: =K19 -> 0.2 | M19: =L19 -> 0.2
D21: Accounts Receivable % Revenue | F21: =F70/F44 -> 0.12686209 | G21: =G70/G44 -> 0.11147631 | H21: =H70/H44 -> 0.12994233 | I21: =I22/365 -> 0.12994233 | J21: =J22/365 -> 0.12994233 | K21: =K22/365 -> 0.12994233 | L21: =L22/365 -> 0.12994233 | M21: =M22/365 -> 0.12994233
D22: Accounts Receivable Days | F22: =F21*365 -> 46.304663 | G22: =G21*365 -> 40.688852 | H22: =H21*365 -> 47.42895 | I22: =H22 -> 47.42895 | J22: =I22 -> 47.42895 | K22: =J22 -> 47.42895 | L22: =K22 -> 47.42895 | M22: =L22 -> 47.42895
D23: Prepaid Expenses and Other % Revenue | F23: =F73/F44 -> 0.025146924 | G23: =G73/G44 -> 0.026070156 | H23: =H73/H44 -> 0.028411948 | I23: =H23 -> 0.028411948 | J23: =I23 -> 0.028411948 | K23: =J23 -> 0.028411948 | L23: =K23 -> 0.028411948 | M23: =L23 -> 0.028411948
D24: Other Non-current Assets % Revenue | F24: =F85/F44 -> 0.060413881 | G24: =G85/G44 -> 0.059208538 | H24: =H85/H44 -> 0.077616197 | I24: =H24 -> 0.077616197 | J24: =I24 -> 0.077616197 | K24: =J24 -> 0.077616197 | L24: =K24 -> 0.077616197 | M24: =L24 -> 0.077616197
D25: Amortization of Intangibles | I25: 80 | J25: =I25*0.8 -> 64 | K25: =J25*0.8 -> 51.2 | L25: =K25*0.8 -> 40.96 | M25: =L25*0.8 -> 32.768
D27: Accounts Payable % COGS | F27: =F89/F45 -> 0.16254819 | G27: =G89/G45 -> 0.17822194 | H27: =H89/H45 -> 0.20570183 | I27: =I28/365 -> 0.20570183 | J27: =J28/365 -> 0.20570183 | K27: =K28/365 -> 0.20570183 | L27: =L28/365 -> 0.20570183 | M27: =M28/365 -> 0.20570183
D28: Accounts Payable Days | F28: =F27*365 -> 59.330091 | G28: =G27*365 -> 65.051009 | H28: =H27*365 -> 75.081168 | I28: =H28 -> 75.081168 | J28: =I28 -> 75.081168 | K28: =J28 -> 75.081168 | L28: =K28 -> 75.081168 | M28: =L28 -> 75.081168
D29: Accrued Expenses % Operating Expenses | F29: =F90/F45 -> 0.1352645 | G29: =G90/G45 -> 0.18068519 | H29: =H90/H45 -> 0.16490527 | I29: =H29 -> 0.16490527 | J29: =I29 -> 0.16490527 | K29: =J29 -> 0.16490527 | L29: =K29 -> 0.16490527 | M29: =L29 -> 0.16490527
D30: Short-Term Deferred Revenue % Revenue | F30: =F91/F44 -> 0.070145354 | G30: =G91/G44 -> 0.064431781 | H30: =H91/H44 -> 0.063062651 | I30: =H30 -> 0.063062651 | J30: =I30 -> 0.063062651 | K30: =J30 -> 0.063062651 | L30: =K30 -> 0.063062651 | M30: =L30 -> 0.063062651
D31: Long-Term Deferred Revenue % Revenue | F31: =F97/F44 -> 0.086455139 | G31: =G97/G44 -> 0.083452641 | H31: =H97/H44 -> 0.081729441 | I31: =H31 -> 0.081729441 | J31: =I31 -> 0.081729441 | K31: =J31 -> 0.081729441 | L31: =K31 -> 0.081729441 | M31: =L31 -> 0.081729441
D33: CapEx % Revenue | F33: =(47.717/F44) -> 0.03090149 | G33: =(39.102/G44) -> 0.024672538 | H33: =(38.924/H44) -> 0.024376359 | I33: =H33 -> 0.024376359 | J33: =I33 -> 0.024376359 | K33: =J33 -> 0.024376359 | L33: =K33 -> 0.024376359 | M33: =L33 -> 0.024376359
D34: Dividends Paid % Revenue | F34: =F37/F44 -> 0.036561507 | G34: =G37/G44 -> 0.035017437 | H34: =H37/H44 -> 0.033487121 | I34: =H34 -> 0.033487121 | J34: =I34 -> 0.033487121 | K34: =J34 -> 0.033487121 | L34: =K34 -> 0.033487121 | M34: =L34 -> 0.033487121
D35: Common Share Repurchases % Revenue | F35: =F38/F44 -> 0.0091959085 | G35: =G38/G44 -> 0.0078241386 | H35: =H38/H44 -> 0.006199927 | I35: =H35 -> 0.006199927 | J35: =I35 -> 0.006199927 | K35: =J35 -> 0.006199927 | L35: =K35 -> 0.006199927 | M35: =L35 -> 0.006199927
D37: Dividends Issued | F37: 56.457 | G37: 55.497 | H37: 53.472 | I37: =I44*I34 -> 54.27408 | J37: =J44*J34 -> 56.065125 | K37: =K44*K34 -> 57.915274 | L37: =L44*L34 -> 60.116054 | M37: =M44*M34 -> 62.220116
D38: Common Share Repurchases | F38: 14.2 | G38: 12.4 | H38: 9.9 | I38: =I35*I44 -> 10.0485 | J38: =J35*J44 -> 10.3801 | K38: =K35*K44 -> 10.722644 | L38: =L35*L44 -> 11.130104 | M38: =M35*M44 -> 11.519658
D39: Long-term Debt Repayment | F39: 0 | G39: 0 | H39: 0 | I39: 250 | J39: 225 | K39: 200 | L39: 175 | M39: 150
D41: Income Statement
F42: Historical Period | I42: Projection Period
F43: 2023A | G43: 2024A | H43: 2025A | I43: 2026E | J43: 2027E | K43: 2028E | L43: 2029E | M43: 2030E
D44: Revenue | F44: 1544.165 | G44: 1584.839 | H44: 1596.793 | I44: =H44*(1+I12) -> 1620.7449 | J44: =I44*(1+J12) -> 1674.2295 | K44: =J44*(1+K12) -> 1729.479 | L44: =K44*(1+L12) -> 1795.1993 | M44: =L44*(1+M12) -> 1858.0312
D45: Operating Expenses | F45: 807.662 | G45: 756.725 | H45: 759.721 | I45: =I$44*I13 -> 771.11681 | J45: =J$44*J13 -> 796.56367 | K45: =K$44*K13 -> 822.85027 | L45: =L$44*L13 -> 854.11858 | M45: =M$44*M13 -> 884.01273
D46: Gross Profit | F46: =F44-F45 -> 736.503 | G46: =G44-G45 -> 828.114 | H46: =H44-H45 -> 837.072 | I46: =I44-I45 -> 849.62808 | J46: =J44-J45 -> 877.66581 | K46: =K44-K45 -> 906.62878 | L46: =L44-L45 -> 941.08067 | M46: =M44-M45 -> 974.0185
D47: Selling, general and administrative | F47: 312.701 | G47: 312.388 | H47: 328.958 | I47: =I$44*I14 -> 333.89237 | J47: =J$44*J14 -> 344.91082 | K47: =K$44*K14 -> 356.29288 | L47: =L$44*L14 -> 369.832 | M47: =M$44*M14 -> 382.77612
D48: Depreciation and amortization | F48: 45.038 | G48: 51.953 | H48: 59.715 | I48: =I$44*I16 -> 60.610725 | J48: =J$44*J16 -> 62.610879 | K48: =K$44*K16 -> 64.677038 | L48: =L$44*L16 -> 67.134765 | M48: =M$44*M16 -> 69.484482
D49: Impairment of long-lived assets | F49: -3.736 | G49: 0 | H49: 0 | I49: 0 | J49: 0 | K49: 0 | L49: 0 | M49: 0
D50: Operating income | F50: =F46-SUM(F47:F49) -> 382.5 | G50: =G46-SUM(G47:G49) -> 463.773 | H50: =H46-SUM(H47:H49) -> 448.399 | I50: =I46-SUM(I47:I49) -> 455.12498 | J50: =J46-SUM(J47:J49) -> 470.14411 | K50: =K46-SUM(K47:K49) -> 485.65887 | L50: =L46-SUM(L47:L49) -> 504.1139 | M50: =M46-SUM(M47:M49) -> 521.75789
D51: Interest expense | F51: 63.78 | G51: 87.131 | H51: 91.148 | I51: =AVERAGE(H96,I96)*I17 -> 90.837222 | J51: =AVERAGE(I96,J96)*J17 -> 78.724722 | K51: =AVERAGE(J96,K96)*K17 -> 67.887222 | L51: =AVERAGE(K96,L96)*L17 -> 58.324722 | M51: =AVERAGE(L96,M96)*M17 -> 50.037222
D52: Interest income | F52: -7.764 | G52: -8.646 | H52: -6.237 | I52: =-I$44*I18 -> -6.330555 | J52: =-J$44*J18 -> -6.5394633 | K52: =-K$44*K18 -> -6.7552656 | L52: =-L$44*L18 -> -7.0119657 | M52: =-M$44*M18 -> -7.2573845
D53: Gain from an acquisition of a joint venture | F53: 0 | G53: 0 | H53: -100.025 | I53: 0 | J53: 0 | K53: 0 | L53: 0 | M53: 0
D54: Gain on sale of assets | F54: 0 | G54: 0 | H54: -0.713 | I54: 0 | J54: 0 | K54: 0 | L54: 0 | M54: 0
D55: Loss (gain) on extinguishment of debt | F55: -4.416 | G55: 0.331 | H55: 0 | I55: 0 | J55: 0 | K55: 0 | L55: 0 | M55: 0
D56: Other (gains) losses, net | F56: -10.649 | G56: 1.641 | H56: -6.989 | I56: 0 | J56: 0 | K56: 0 | L56: 0 | M56: 0
D57: Equity in net loss (gain) of affiliates | F57: -2.879 | G57: -12.329 | H57: 14.324 | I57: 0 | J57: 0 | K57: 0 | L57: 0 | M57: 0
D58: Total other expenses and (income), net | F58: =SUM(F51:F57) -> 38.072 | G58: =SUM(G51:G57) -> 68.128 | H58: =SUM(H51:H57) -> -8.492 | I58: =SUM(I51:I57) -> 84.506667 | J58: =SUM(J51:J57) -> 72.185259 | K58: =SUM(K51:K57) -> 61.131956 | L58: =SUM(L51:L57) -> 51.312756 | M58: =SUM(M51:M57) -> 42.779838
D59: Income before income taxes | F59: =F50+F58 -> 420.572 | G59: =G50+G58 -> 531.901 | H59: =H50+H58 -> 439.907 | I59: =I50+I58 -> 539.63165 | J59: =J50+J58 -> 542.32937 | K59: =K50+K58 -> 546.79082 | L59: =L50+L58 -> 555.42666 | M59: =M50+M58 -> 564.53773
D60: Income tax expense | F60: 78.449 | G60: 95.98 | H60: 86.945 | I60: =I$59*I19 -> 107.92633 | J60: =J$59*J19 -> 108.46587 | K60: =K$59*K19 -> 109.35816 | L60: =L$59*L19 -> 111.08533 | M60: =M$59*M19 -> 112.90755
D61: Net income | F61: =F59-F60 -> 342.123 | G61: =G59-G60 -> 435.921 | H61: =H59-H60 -> 352.962 | I61: =I59-I60 -> 431.70532 | J61: =J59-J60 -> 433.86349 | K61: =K59-K60 -> 437.43266 | L61: =L59-L60 -> 444.34133 | M61: =M59-M60 -> 451.63018
D63: Basic earnings per share | F63: 5.11 | G63: 6.26 | H63: 7.97 | I63: =I61/CHH!$X$39 -> 9.3503427 | J63: =J61/CHH!$X$39 -> 9.3970867 | K63: =K61/CHH!$X$39 -> 9.4743915 | L63: =L61/CHH!$X$39 -> 9.624027 | M63: =M61/CHH!$X$39 -> 9.7818969
D64: Diluted earnings per share | F64: 5.07 | G64: 6.2 | H64: 7.9 | I64: =I61/CHH!$X$44 -> 9.3434939 | J64: =J61/CHH!$X$44 -> 9.3902037 | K64: =K61/CHH!$X$44 -> 9.4674519 | L64: =L61/CHH!$X$44 -> 9.6169778 | M64: =M61/CHH!$X$44 -> 9.7747321
D66: Balance Sheet
F67: Historical Period | I67: Projection Period
F68: 2023A | G68: 2024A | H68: 2025A | I68: 2026E | J68: 2027E | K68: 2028E | L68: 2029E | M68: 2030E
D69: Cash and cash equivalents | F69: 26.754 | G69: 40.177 | H69: 44.997 | I69: =I150 -> 265.52208 | J69: =J150 -> 498.29376 | K69: =K150 -> 745.51157 | L69: =L150 -> 1013.5371 | M69: =M150 -> 1303.738
D70: Accounts receivables | F70: 195.896 | G70: 176.672 | H70: 207.491 | I70: =I$44*I21 -> 210.60336 | J70: =J$44*J21 -> 217.55328 | K70: =K$44*K21 -> 224.73253 | L70: =L$44*L21 -> 233.27237 | M70: =M$44*M21 -> 241.4369
D71: Income taxes receivable | F71: 14.283 | G71: 5.419 | H71: 13.456 | I71: =H71 -> 13.456 | J71: =I71 -> 13.456 | K71: =J71 -> 13.456 | L71: =K71 -> 13.456 | M71: =L71 -> 13.456
D72: Notes receivable | F72: 20.766 | G72: 75.501 | H72: 94.686 | I72: =H72 -> 94.686 | J72: =I72 -> 94.686 | K72: =J72 -> 94.686 | L72: =K72 -> 94.686 | M72: =L72 -> 94.686
D73: Prepaid expenses and other current assets | F73: 38.831 | G73: 41.317 | H73: 45.368 | I73: =I$44*I23 -> 46.04852 | J73: =J$44*J23 -> 47.568121 | K73: =K$44*K23 -> 49.137869 | L73: =L$44*L23 -> 51.005108 | M73: =M$44*M23 -> 52.790287
D74: Total current assets | F74: 296.53 | G74: 339.086 | H74: 405.998 | I74: =SUM(I69:I73) -> 630.31597 | J74: =SUM(J69:J73) -> 871.55716 | K74: =SUM(K69:K73) -> 1127.524 | L74: =SUM(L69:L73) -> 1405.9566 | M74: =SUM(M69:M73) -> 1706.1072
D76: Property and equipment, net | F76: 493.478 | G76: 604.345 | H76: 649.291 | I76: =H76-I121-I136 -> 628.18814 | J76: =I76-J121-J136 -> 606.38888 | K76: =J76-K121-K136 -> 583.87024 | L76: =K76-L121-L136 -> 560.4959 | M76: =L76-M121-M136 -> 536.30345
D77: Operating lease right-of-use assets | F77: 85.101 | G77: 83.451 | H77: 77.67 | I77: =H77 -> 77.67 | J77: =I77 -> 77.67 | K77: =J77 -> 77.67 | L77: =K77 -> 77.67 | M77: =L77 -> 77.67
D78: Goodwill | F78: 220.187 | G78: 220.187 | H78: 305.758 | I78: =H78 -> 305.758 | J78: =I78 -> 305.758 | K78: =J78 -> 305.758 | L78: =K78 -> 305.758 | M78: =L78 -> 305.758
D79: Intangible assets, net | F79: 811.075 | G79: 884.013 | H79: 1082.486 | I79: =H79-I122-I137 -> 1002.486 | J79: =I79-J122-J137 -> 938.486 | K79: =J79-K122-K137 -> 887.286 | L79: =K79-L122-L137 -> 846.326 | M79: =L79-M122-M137 -> 813.558
D80: Notes receivable | F80: 78.9 | G80: 32.682 | H80: 12.49 | I80: =H80 -> 12.49 | J80: =I80 -> 12.49 | K80: =J80 -> 12.49 | L80: =K80 -> 12.49 | M80: =L80 -> 12.49
D81: Investments in equity securities, at fair value | F81: 116.374 | G81: 0 | H81: 0 | I81: 0 | J81: 0 | K81: 0 | L81: 0 | M81: 0
D82: Investments for employee benefit plans | F82: 39.751 | G82: 47.603 | H82: 50.227 | I82: =H82 -> 50.227 | J82: =I82 -> 50.227 | K82: =J82 -> 50.227 | L82: =K82 -> 50.227 | M82: =L82 -> 50.227
D83: Investments in affiliates | F83: 70.579 | G83: 117.016 | H83: 134.975 | I83: =H83 -> 134.975 | J83: =I83 -> 134.975 | K83: =J83 -> 134.975 | L83: =K83 -> 134.975 | M83: =L83 -> 134.975
D84: Deferred income taxes | F84: 89.535 | G84: 108.308 | H84: 75.371 | I84: =H84 -> 75.371 | J84: =I84 -> 75.371 | K84: =J84 -> 75.371 | L84: =K84 -> 75.371 | M84: =L84 -> 75.371
D85: Other assets | F85: 93.289 | G85: 93.836 | H85: 123.937 | I85: =I$44*I24 -> 125.79605 | J85: =J$44*J24 -> 129.94732 | K85: =K$44*K24 -> 134.23559 | L85: =L$44*L24 -> 139.33654 | M85: =M$44*M24 -> 144.21332
D86: Total assets | F86: 2394.799 | G86: 2530.527 | H86: 2918.203 | I86: =SUM(I76:I85)+I74 -> 3043.2772 | J86: =SUM(J76:J85)+J74 -> 3202.8704 | K86: =SUM(K76:K85)+K74 -> 3389.4068 | L86: =SUM(L76:L85)+L74 -> 3608.606 | M86: =SUM(M76:M85)+M74 -> 3856.673
D88: Liabilities & Shareholder's Equity
D89: Accounts payable | F89: 131.284 | G89: 134.865 | H89: 156.276 | I89: =I$45*I27 -> 158.62014 | J89: =J$45*J27 -> 163.8546 | K89: =K$45*K27 -> 169.26181 | L89: =L$45*L27 -> 175.69376 | M89: =M$45*M27 -> 181.84304
D90: Accrued expenses and other current liabilities | F90: 109.248 | G90: 136.729 | H90: 125.282 | I90: =I$45*I29 -> 127.16123 | J90: =J$45*J29 -> 131.35755 | K90: =K$45*K29 -> 135.69235 | L90: =L$45*L29 -> 140.84866 | M90: =M$45*M29 -> 145.77836
D91: Deferred revenue | F91: 108.316 | G91: 102.114 | H91: 100.698 | I91: =I$44*I30 -> 102.20847 | J91: =J$44*J30 -> 105.58135 | K91: =K$44*K30 -> 109.06553 | L91: =L$44*L30 -> 113.21002 | M91: =M$44*M30 -> 117.17238
D92: Liability for guest loyalty program | F92: 94.574 | G92: 89.013 | H92: 85.035 | I92: =H92 -> 85.035 | J92: =I92 -> 85.035 | K92: =J92 -> 85.035 | L92: =K92 -> 85.035 | M92: =L92 -> 85.035
D93: Current portion of long-term debt | F93: 499.268 | G93: 0 | H93: 0 | I93: =H93 -> 0 | J93: =I93 -> 0 | K93: =J93 -> 0 | L93: =K93 -> 0 | M93: =L93 -> 0
D94: Total current liabilities | F94: 942.69 | G94: 462.721 | H94: 467.291 | I94: =SUM(I89:I93) -> 473.02484 | J94: =SUM(J89:J93) -> 485.8285 | K94: =SUM(K89:K93) -> 499.05469 | L94: =SUM(L89:L93) -> 514.78744 | M94: =SUM(M89:M93) -> 529.82877
D96: Long-term debt | F96: 1068.751 | G96: 1768.526 | H96: 1906.122 | I96: =H96+I145 -> 1656.122 | J96: =I96+J145 -> 1431.122 | K96: =J96+K145 -> 1231.122 | L96: =K96+L145 -> 1056.122 | M96: =L96+M145 -> 906.122
D97: Long-term deferred revenue | F97: 133.501 | G97: 132.259 | H97: 130.505 | I97: =I$44*I31 -> 132.46257 | J97: =J$44*J31 -> 136.83384 | K97: =K$44*K31 -> 141.34936 | L97: =L$44*L31 -> 146.72063 | M97: =M$44*M31 -> 151.85585
D98: Deferred compensation and retirement plan | F98: 45.657 | G98: 53.316 | H98: 56.532 | I98: =H98 -> 56.532 | J98: =I98 -> 56.532 | K98: =J98 -> 56.532 | L98: =K98 -> 56.532 | M98: =L98 -> 56.532
D99: Deferred income taxes | F99: 8.601 | G99: 0 | H99: 25.303 | I99: =H99 -> 25.303 | J99: =I99 -> 25.303 | K99: =J99 -> 25.303 | L99: =K99 -> 25.303 | M99: =L99 -> 25.303
D100: Operating lease liabilities | F100: 109.483 | G100: 113.255 | H100: 107.963 | I100: =H100 -> 107.963 | J100: =I100 -> 107.963 | K100: =J100 -> 107.963 | L100: =K100 -> 107.963 | M100: =L100 -> 107.963
D101: Liability for guest loyalty program | F101: 43.266 | G101: 40.607 | H101: 39.771 | I101: =H101 -> 39.771 | J101: =I101 -> 39.771 | K101: =J101 -> 39.771 | L101: =K101 -> 39.771 | M101: =L101 -> 39.771
D102: Other liabilities | F102: 7.252 | G102: 5.114 | H102: 3.487 | I102: =H102 -> 3.487 | J102: =I102 -> 3.487 | K102: =J102 -> 3.487 | L102: =K102 -> 3.487 | M102: =L102 -> 3.487
D103: Total liabilities | F103: 2359.201 | G103: 2575.798 | H103: 2736.974 | I103: =SUM(I96:I102)+I94 -> 2494.6654 | J103: =SUM(J96:J102)+J94 -> 2286.8403 | K103: =SUM(K96:K102)+K94 -> 2104.582 | L103: =SUM(L96:L102)+L94 -> 1950.6861 | M103: =SUM(M96:M102)+M94 -> 1820.8626
D105: Shareholder's Equity
D106: Common stock | F106: 0.951 | G106: 0.951 | H106: 0.951 | I106: =H106 -> 0.951 | J106: =I106 -> 0.951 | K106: =J106 -> 0.951 | L106: =K106 -> 0.951 | M106: =L106 -> 0.951
D107: Additional paid-in-capital | F107: 330.75 | G107: 370.201 | H107: 403.927 | I107: =H107 -> 403.927 | J107: =I107 -> 403.927 | K107: =J107 -> 403.927 | L107: =K107 -> 403.927 | M107: =L107 -> 403.927
D108: Accumulated other comprehensive loss | F108: -5.671 | G108: -6.193 | H108: -5.307 | I108: =H108 -> -5.307 | J108: =I108 -> -5.307 | K108: =J108 -> -5.307 | L108: =K108 -> -5.307 | M108: =L108 -> -5.307
D109: Treasury stock | F109: -2046.791 | G109: -2411.527 | H109: -2536.373 | I109: =H109 -> -2536.373 | J109: =I109 -> -2536.373 | K109: =J109 -> -2536.373 | L109: =K109 -> -2536.373 | M109: =L109 -> -2536.373
D110: Retained earnings | F110: 1756.359 | G110: 2001.297 | H110: 2318.031 | I110: =H110+I61+I142+I143 -> 2685.4137 | J110: =I110+J61+J142+J143 -> 3052.832 | K110: =J110+K61+K142+K143 -> 3421.6268 | L110: =K110+L61+L142+L143 -> 3794.7219 | M110: =L110+M61+M142+M143 -> 4172.6123
D111: Total shareholders' equity (deficit) | F111: 35.598 | G111: -45.271 | H111: 181.229 | I111: =SUM(I106:I110) -> 548.61174 | J111: =SUM(J106:J110) -> 916.03001 | K111: =SUM(K106:K110) -> 1284.8248 | L111: =SUM(L106:L110) -> 1657.9199 | M111: =SUM(M106:M110) -> 2035.8103
D112: Total liabilities and shareholders' equity (deficit) | F112: 2394.799 | G112: 2530.527 | H112: 2918.203 | I112: =I103+I111 -> 3043.2772 | J112: =J103+J111 -> 3202.8704 | K112: =K103+K111 -> 3389.4068 | L112: =L103+L111 -> 3608.606 | M112: =M103+M111 -> 3856.673
D114: Balance Check | F114: =IF(F112=F86,F86-F112,F86-F112) -> 0 | G114: =IF(G112=G86,G86-G112,G86-G112) -> 0 | H114: =IF(H112=H86,H86-H112,H86-H112) -> 0 | I114: =IF(I112=I86,I86-I112,I86-I112) -> 4.5474735e-13 | J114: =IF(J112=J86,J86-J112,J86-J112) -> 0 | K114: =IF(K112=K86,K86-K112,K86-K112) -> -9.094947e-13 | L114: =IF(L112=L86,L86-L112,L86-L112) -> 0 | M114: =IF(M112=M86,M86-M112,M86-M112) -> -4.5474735e-13
D116: Cash Flow Statement
F117: Historical Period | I117: Projection Period
...

Sheet WACC
D2: Choice Hotels International Inc. (NYSE: CHH)
D3: Weighted Average Cost of Capital Analysis
D4: ($ in millions, except per share amounts, Fiscal year ending December 31)
D7: WACC Calculation | H7: Comparable Companies Unlevered Beta
D8: Target Capital Structure | I8: Predicted | J8: Market | K8: Market | L8: Debt/ | M8: Marginal | N8: Unlevered
D9: Debt-to-Total Capitalization | F9: 0.15 | H9: Company | I9: Levered Beta (4) | J9: Value of Debt | K9: Value of Equity | L9: Equity | M9: Tax Rate | N9: Beta
D10: Equity-to-Total Capitalization | F10: =(1-F9) -> 0.85 | H10: =MAR!H8 -> Marriott International Inc. | I10: =MAR!H14 -> 1.1 | J10: =CHH!H27 -> 1906.122 | K10: =MAR!H25 -> 96703.864 | L10: =J10/K10 -> 0.019710919 | M10: =$F$15 -> 0.2 | N10: =I10/(1+L10)*(1-M10) -> 0.86298968
H11: =ABNB!H8 -> Airbnb Inc. Cl A | I11: =ABNB!H14 -> 1.56 | J11: =ABNB!H27 -> 1999 | K11: =ABNB!H25 -> 83701.62 | L11: =J11/K11 -> 0.023882453 | M11: =$F$15 -> 0.2 | N11: =I11/(1+L11)*(1-M11) -> 1.2188899
H12: =HLT!H8 -> Hilton Worldwide Holdings Inc. | I12: =HLT!H14 -> 1.04 | J12: =HLT!H27 -> 12363 | K12: =HLT!H25 -> 78279.057 | L12: =J12/K12 -> 0.15793496 | M12: =$F$15 -> 0.2 | N12: =I12/(1+L12)*(1-M12) -> 0.71852049
D13: Cost of Debt | H13: =H!H8 -> Hyatt Hotels Corporation | I13: =H!H14 -> 1.22 | J13: =H!H27 -> 4278 | K13: =H!H25 -> 16017.976 | L13: =J13/K13 -> 0.26707494 | M13: =$F$15 -> 0.2 | N13: =I13/(1+L13)*(1-M13) -> 0.77027804
D14: Cost-of-Debt (5) | F14: =Historical!I17 -> 0.051 | H14: =WH!H8 -> Wyndham Hotels & Resorts Inc. | I14: =WH!H14 -> 1.01 | J14: =WH!H27 -> 2560 | K14: =WH!H25 -> 6773.941 | L14: =J14/K14 -> 0.37791885 | M14: =$F$15 -> 0.2 | N14: =I14/(1+L14)*(1-M14) -> 0.58639157
D15: Tax Rate | F15: =Historical!I19 -> 0.2
D16: After-tax Cost of Debt | F16: =F14*(1-F15) -> 0.0408 | H16: Mean | I16: =AVERAGE(I10:I14) -> 1.186 | L16: =AVERAGE(L10:L14) -> 0.16930442 | N16: =AVERAGE(N10:N14) -> 0.83141394
H17: Median | I17: =MEDIAN(I10:I14) -> 1.1 | L17: =MEDIAN(L10:L14) -> 0.15793496 | N17: =MEDIAN(N10:N14) -> 0.77027804
D19: Cost of Equity | H19: Alphabet Inc Relevered Beta
D20: Risk-free Rate (1) | F20: 0.04261 | K20: Mean | L20: Target | M20: Target
D21: Market Risk Premium (2) | F21: =4.46%-0.23% -> 0.0423 | K21: UnLevered | L21: Debt/ | M21: Marginal | N21: Relevered
D22: Levered Beta | F22: =N23 -> 0.94879003 | K22: Beta | L22: Equity | M22: Tax Rate | N22: Beta
D23: Country Risk Premium (3) | F23: 0.0023 | H23: Relevered Beta | K23: =N16 -> 0.83141394 | L23: =F9/F10 -> 0.17647059 | M23: =F15 -> 0.2 | N23: =K23*(1+L23*(1-M23)) -> 0.94879003
D24: Cost of Equity | F24: =F20+(F21*F22)+F23 -> 0.085043818
H25: WACC Sensitivity Analysis
D26: WACC | F26: =(F16*F9)+(F24*F10) -> 0.078407245 | J26: Pre-Tax Cost of Debt
H27: Debt-to-Total Capitalization | I27: =F26 -> 0.078407245 | J27: 0.04 | K27: 0.045 | L27: 0.05 | M27: 0.055 | N27: 0.06
I28: 0.05 | J28: 0.079081622 | K28: 0.079281622 | L28: 0.079481622 | M28: 0.079681622 | N28: 0.079881622
I29: 0.1 | J29: 0.078084433 | K29: 0.078484433 | L29: 0.078884433 | M29: 0.079284433 | N29: 0.079684433
I30: 0.15 | J30: 0.077087245 | K30: 0.077687245 | L30: 0.078287245 | M30: 0.078887245 | N30: 0.079487245
I31: 0.2 | J31: 0.076090057 | K31: 0.076890057 | L31: 0.077690057 | M31: 0.078490057 | N31: 0.079290057
I32: 0.25 | J32: 0.075092869 | K32: 0.076092869 | L32: 0.077092869 | M32: 0.078092869 | N32: 0.079092869
D33: (1) Interpolated yield on 10-year U.S. Treasury bond, sourced from investing.com
D34: (2), (3) Obtained from Aswath Damodaran's Country Default Spreads and Risk Premiums
D35: (4) Sourced from market watch.com
D36: (5) Average cost of debt across Choice Hotels International Inc.'s capital structure

Sheet DCF
D2: Choice Hotels International Inc. (NYSE: CHH)
D3: Discounted Cash Flow Analysis
D4: ($ in millions, except per share amounts, Fiscal year ending December 31) | M4: Operating Scenario | O4: =VLOOKUP($E$5,[1]Data!$K$4:$L$6,2,TRUE) -> Base
D5: Opearting Scenario | E5: 1
D6: Mid-Year Convention | E6: Y | F6: Historical Period | I6: CAGR | J6: Projection Period | O6: CAGR
D7: Use Multiple Method? | E7: Y | F7: 2023A | G7: 2024A | H7: 2025A | I7: ('23-'25) | J7: 2026 | K7: 2027 | L7: 2028 | M7: 2029 | N7: 2030 | O7: ('26-'30)
D8: Sales | F8: =Historical!F44 -> 1544.165 | G8: =Historical!G44 -> 1584.839 | H8: =Historical!H44 -> 1596.793 | I8: =_xlfn.RRI(2,F8,H8) -> 0.016898151 | J8: =Historical!I44 -> 1620.7449 | K8: =Historical!J44 -> 1674.2295 | L8: =Historical!K44 -> 1729.479 | M8: =Historical!L44 -> 1795.1993 | N8: =Historical!M44 -> 1858.0312 | O8: =_xlfn.RRI(4,J8,N8) -> 0.034747978
D9: % growth | F9: =[1]Input!F32 -> NA | G9: =G8/F8-1 -> 0.026340449 | H9: =H8/G8-1 -> 0.007542722 | J9: =J8/H8-1 -> 0.015 | K9: =K8/J8-1 -> 0.033 | L9: =L8/K8-1 -> 0.033 | M9: =M8/L8-1 -> 0.038 | N9: =N8/M8-1 -> 0.035
D10: Costs and expenses | F10: =Historical!F45 -> 807.662 | G10: =Historical!G45 -> 756.725 | H10: =Historical!H45 -> 759.721 | J10: =Historical!I45 -> 771.11681 | K10: =Historical!J45 -> 796.56367 | L10: =Historical!K45 -> 822.85027 | M10: =Historical!L45 -> 854.11858 | N10: =Historical!M45 -> 884.01273
D11: % sales | F11: =F10/F$8 -> 0.52304126 | G11: =G10/G$8 -> 0.47747752 | H11: =H10/H$8 -> 0.47577927 | J11: =J10/J$8 -> 0.47577927 | K11: =K10/K$8 -> 0.47577927 | L11: =L10/L$8 -> 0.47577927 | M11: =M10/M$8 -> 0.47577927 | N11: =N10/N$8 -> 0.47577927
D12: Gross Profit | F12: =F8-F10 -> 736.503 | G12: =G8-G10 -> 828.114 | H12: =H8-H10 -> 837.072 | I12: =_xlfn.RRI(2,F12,H12) -> 0.066090682 | J12: =J8-J10 -> 849.62808 | K12: =K8-K10 -> 877.66581 | L12: =L8-L10 -> 906.62878 | M12: =M8-M10 -> 941.08067 | N12: =N8-N10 -> 974.0185 | O12: =_xlfn.RRI(4,J12,N12) -> 0.034747978
D13: % margin | F13: =F12/F$8 -> 0.47695874 | G13: =G12/G$8 -> 0.52252248 | H13: =H12/H$8 -> 0.52422073 | J13: =J12/J$8 -> 0.52422073 | K13: =K12/K$8 -> 0.52422073 | L13: =L12/L$8 -> 0.52422073 | M13: =M12/M$8 -> 0.52422073 | N13: =N12/N$8 -> 0.52422073
D14: S,G&A | F14: =Historical!F47 -> 312.701 | G14: =Historical!G47 -> 312.388 | H14: =Historical!H47 -> 328.958 | J14: =Historical!I47 -> 333.89237 | K14: =Historical!J47 -> 344.91082 | L14: =Historical!K47 -> 356.29288 | M14: =Historical!L47 -> 369.832 | N14: =Historical!M47 -> 382.77612
D15: % sales | F15: =F14/F$8 -> 0.20250491 | G15: =G14/G$8 -> 0.19711024 | H15: =H14/H$8 -> 0.20601167 | J15: =J14/J$8 -> 0.20601167 | K15: =K14/K$8 -> 0.20601167 | L15: =L14/L$8 -> 0.20601167 | M15: =M14/M$8 -> 0.20601167 | N15: =N14/N$8 -> 0.20601167
D16: Impairment of long-lived assets | F16: =Historical!F49 -> -3.736 | G16: =Historical!G49 -> 0 | H16: =Historical!H49 -> 0 | J16: =Historical!I49 -> 0 | K16: =Historical!J49 -> 0 | L16: =Historical!K49 -> 0 | M16: =Historical!L49 -> 0 | N16: =Historical!M49 -> 0
D17: % sales | F17: =F16/F$8 -> -0.0024194306 | G17: =G16/G$8 -> 0 | H17: =H16/H$8 -> 0 | J17: =J16/J$8 -> 0 | K17: =K16/K$8 -> 0 | L17: =L16/L$8 -> 0 | M17: =M16/M$8 -> 0 | N17: =N16/N$8 -> 0
D18: EBITDA | F18: =F12-F14-F16 -> 427.538 | G18: =G12-G14-G16 -> 515.726 | H18: =H12-H14-H16 -> 508.114 | I18: =_xlfn.RRI(2,F18,H18) -> 0.090167473 | J18: =J12-J14-J16 -> 515.73571 | K18: =K12-K14-K16 -> 532.75499 | L18: =L12-L14-L16 -> 550.3359 | M18: =M12-M14-M16 -> 571.24867 | N18: =N12-N14-N16 -> 591.24237 | O18: =_xlfn.RRI(4,J18,N18) -> 0.034747978
D19: % margin | F19: =F18/F$8 -> 0.27687326 | G19: =G18/G$8 -> 0.32541223 | H19: =H18/H$8 -> 0.31820906 | J19: =J18/J$8 -> 0.31820906 | K19: =K18/K$8 -> 0.31820906 | L19: =L18/L$8 -> 0.31820906 | M19: =M18/M$8 -> 0.31820906 | N19: =N18/N$8 -> 0.31820906
D20: Depreciation | F20: =Historical!F48 -> 45.038 | G20: =Historical!G48 -> 51.953 | H20: =Historical!H48 -> 59.715 | J20: =Historical!I48 -> 60.610725 | K20: =Historical!J48 -> 62.610879 | L20: =Historical!K48 -> 64.677038 | M20: =Historical!L48 -> 67.134765 | N20: =Historical!M48 -> 69.484482
D21: % sales | F21: =[1]Input!F46 -> 0.038862177 | G21: =[1]Input!G46 -> 0.043743465 | H21: =[1]Input!H46 -> 0.052468002 | J21: =[1]Input!H46 -> 0.052468002 | K21: =J21 -> 0.052468002 | L21: =K21 -> 0.052468002 | M21: =L21 -> 0.052468002 | N21: =M21 -> 0.052468002
D22: EBIT | F22: =F18-F20 -> 382.5 | G22: =G18-G20 -> 463.773 | H22: =H18-H20 -> 448.399 | I22: =_xlfn.RRI(2,F22,H22) -> 0.082721094 | J22: =J18-J20 -> 455.12498 | K22: =K18-K20 -> 470.14411 | L22: =L18-L20 -> 485.65887 | M22: =M18-M20 -> 504.1139 | N22: =N18-N20 -> 521.75789 | O22: =_xlfn.RRI(4,J22,N22) -> 0.034747978
D23: % margin | F23: =F22/F$8 -> 0.24770669 | G23: =G22/G$8 -> 0.29263099 | H23: =H22/H$8 -> 0.28081223 | J23: =J22/J$8 -> 0.28081223 | K23: =K22/K$8 -> 0.28081223 | L23: =L22/L$8 -> 0.28081223 | M23: =M22/M$8 -> 0.28081223 | N23: =N22/N$8 -> 0.28081223
D24: Taxes | F24: =Historical!F60 -> 78.449 | G24: =Historical!G60 -> 95.98 | H24: =Historical!H60 -> 86.945 | J24: =Historical!J60 -> 108.46587 | K24: =Historical!K60 -> 109.35816 | L24: =Historical!L60 -> 111.08533 | M24: =Historical!M60 -> 112.90755 | N24: =Historical!N60 -> 0
D25: NOPAT | J25: =J22-J24 -> 346.65911 | K25: =K22-K24 -> 360.78595 | L25: =L22-L24 -> 374.57353 | M25: =M22-M24 -> 391.20636 | N25: =N22-N24 -> 521.75789
D27: Plus: D&A | F27: =F20 -> 45.038 | G27: =G20 -> 51.953 | H27: =H20 -> 59.715 | J27: =J20 -> 60.610725 | K27: =K20 -> 62.610879 | L27: =L20 -> 64.677038 | M27: =M20 -> 67.134765 | N27: =N20 -> 69.484482
D28: Less: Capex | F28: =Historical!F44*Historical!F33 -> 47.717 | G28: =Historical!G44*Historical!G33 -> 39.102 | H28: =Historical!H44*Historical!H33 -> 38.924 | J28: =Historical!I136 -> -39.50786 | K28: =Historical!J136 -> -40.811619 | L28: =Historical!K136 -> -42.158403 | M28: =Historical!L136 -> -43.760422 | N28: =Historical!M136 -> -45.292037
D29: Inc/Dec in NWC | J29: =SUM(Historical!I125:I129) -> 3.89853 | K29: =SUM(Historical!J125:J129) -> 8.7054175 | L29: =SUM(Historical!K125:K129) -> 8.9926963 | M29: =SUM(Historical!L125:L129) -> 10.696948 | N29: =SUM(Historical!M125:M129) -> 10.226846
D31: Unlevered Free Cash Flow | J31: =SUM(J25:J29) -> 371.66051 | K31: =SUM(K25:K29) -> 391.29062 | L31: =SUM(L25:L29) -> 406.08486 | M31: =SUM(M25:M29) -> 425.27765 | N31: =SUM(N25:N29) -> 556.17718
D32: WACC | E32: =WACC!F26 -> 0.078407245
D33: Discount Period | J33: =IF($E$6="Y",0.5,1) -> 0.5 | K33: =J33+1 -> 1.5 | L33: =K33+1 -> 2.5 | M33: =L33+1 -> 3.5 | N33: =M33+1 -> 4.5
D34: Discount Factor | J34: =1/(1+$E$32)^J33 -> 0.96296078 | K34: =1/(1+$E$32)^K33 -> 0.89294725 | L34: =1/(1+$E$32)^L33 -> 0.82802416 | M34: =1/(1+$E$32)^M33 -> 0.7678214 | N34: =1/(1+$E$32)^N33 -> 0.71199577
D35: Present Value of Free Cash Flow | J35: =J31*J34 -> 357.89449 | K35: =K31*K34 -> 349.40189 | L35: =L31*L34 -> 336.24808 | M35: =M31*M34 -> 326.53728 | N35: =N31*N34 -> 395.9958
D38: Enterprise Value | H38: Implied Equity Value and Share Price | M38: Implied Perpetuity Growth Rate
D39: Cumulative Present Value of FCF | F39: =SUM(J35:N35) -> 1766.0775 | H39: Enterprise Value | K39: =F49 -> 8711.9516 | M39: Treminal Year Free Cash Flow (2030E) | P39: =N31 -> 556.17718
H40: Less: Total Debt | K40: =-CHH!H27 -> -1906.122 | M40: WACC | P40: =E32 -> 0.078407245
D41: Terminal Value | H41: Less: Preferred Stock | K41: =-CHH!H28 -> 0 | M41: Terminal Value | P41: =F44 -> 9755.4991
D42: Terminal Year EBITDA (2030E) | F42: =N18 -> 591.24237 | H42: Less: Noncontrolling Interest | K42: =-CHH!H29 -> 0
D43: Exit Multiple | F43: 16.5 | H43: Plus: Cash & Cash Equivalents | K43: =-CHH!H30 -> 44.997 | M43: Implied Perpetuity Growth Rate | P43: 0.03
D44: Terminal Value | F44: =IF(E7="Y",F43*F42,F42*(1+P43)/(E32-P43)) -> 9755.4991
D45: Discount Factor | F45: =N34 -> 0.71199577 | H45: Implied Equity Value | K45: =SUM(K39:K43) -> 6850.8266 | M45: Implied EV/EBITDA
D46: Present Value of Terminal Value | F46: =F44*F45 -> 6945.8741 | M46: Enterprise Value | P46: =F49 -> 8711.9516
D47: % of Enterprise Value | F47: =F46/F49 -> 0.79728107 | H47: Fully Diluted Shares Outstanding | K47: =CHH!H24 -> 46.203843 | M47: 12/31/2025 EBITDA | P47: =H18 -> 508.114
D49: Enterprise Value | F49: =F39+F46 -> 8711.9516 | H49: Implied Share Price | K49: =K45/K47 -> 148.27396 | M49: Implied EV/EBITDA | P49: =P46/P47 -> 17.145663
D52: Implied Share Price
D54: Choice Hotels International Inc. Sensitivity Analysis - Terminal Growth Rate
E55: Discount Rate
E56: =K49 -> 148.27396 | F56: 0.065 | G56: 0.07 | H56: 0.075 | I56: 0.08 | J56: 0.085 | K56: 0.09 | L56: 0.095
D57: Implied Perpetuity Growth Rate | E57: 0.015 | F57: 158.21559 | G57: 154.42984 | H57: 150.73772 | I57: 147.13648 | J57: 143.62344 | K57: 140.19604 | L57: 136.85178
E58: 0.02 | F58: 158.21559 | G58: 154.42984 | H58: 150.73772 | I58: 147.13648 | J58: 143.62344 | K58: 140.19604 | L58: 136.85178
E59: 0.025 | F59: 158.21559 | G59: 154.42984 | H59: 150.73772 | I59: 147.13648 | J59: 143.62344 | K59: 140.19604 | L59: 136.85178
E60: 0.03 | F60: 158.21559 | G60: 154.42984 | H60: 150.73772 | I60: 147.13648 | J60: 143.62344 | K60: 140.19604 | L60: 136.85178
E61: 0.035 | F61: 158.21559 | G61: 154.42984 | H61: 150.73772 | I61: 147.13648 | J61: 143.62344 | K61: 140.19604 | L61: 136.85178
E62: 0.04 | F62: 158.21559 | G62: 154.42984 | H62: 150.73772 | I62: 147.13648 | J62: 143.62344 | K62: 140.19604 | L62: 136.85178
E63: 0.045 | F63: 158.21559 | G63: 154.42984 | H63: 150.73772 | I63: 147.13648 | J63: 143.62344 | K63: 140.19604 | L63: 136.85178
D65: Choice Hotels International Inc. Sensitivity Analysis - Exit Multiple
E66: Discount Rate
E67: =K49 -> 148.27396 | F67: 0.065 | G67: 0.07 | H67: 0.075 | I67: 0.08 | J67: 0.085 | K67: 0.09 | L67: 0.095
D68: Exit Multiple | E68: 15 | F68: 148.27396 | G68: 148.27396 | H68: 148.27396 | I68: 148.27396 | J68: 148.27396 | K68: 148.27396 | L68: 148.27396
E69: 15.5 | F69: 148.27396 | G69: 148.27396 | H69: 148.27396 | I69: 148.27396 | J69: 148.27396 | K69: 148.27396 | L69: 148.27396
E70: 16 | F70: 148.27396 | G70: 148.27396 | H70: 148.27396 | I70: 148.27396 | J70: 148.27396 | K70: 148.27396 | L70: 148.27396
E71: 16.5 | F71: 148.27396 | G71: 148.27396 | H71: 148.27396 | I71: 148.27396 | J71: 148.27396 | K71: 148.27396 | L71: 148.27396
E72: 17 | F72: 148.27396 | G72: 148.27396 | H72: 148.27396 | I72: 148.27396 | J72: 148.27396 | K72: 148.27396 | L72: 148.27396
E73: 17.5 | F73: 148.27396 | G73: 148.27396 | H73: 148.27396 | I73: 148.27396 | J73: 148.27396 | K73: 148.27396 | L73: 148.27396
E74: 18 | F74: 148.27396 | G74: 148.27396 | H74: 148.27396 | I74: 148.27396 | J74: 148.27396 | K74: 148.27396 | L74: 148.27396
D76: Implied Enterprise Value
D78: Choice Hotels International Inc. Sensitivity Analysis - Terminal Growth Rate
E79: Discount Rate
E80: =F49 -> 8711.9516 | F80: 0.065 | G80: 0.07 | H80: 0.075 | I80: 0.08 | J80: 0.085 | K80: 0.09 | L80: 0.095
D81: Implied Perpetuity Growth Rate | E81: 0.015 | F81: 8711.9516 | G81: 8711.9516 | H81: 8711.9516 | I81: 8711.9516 | J81: 8711.9516 | K81: 8711.9516 | L81: 8711.9516
E82: 0.02 | F82: 8711.9516 | G82: 8711.9516 | H82: 8711.9516 | I82: 8711.9516 | J82: 8711.9516 | K82: 8711.9516 | L82: 8711.9516
E83: 0.025 | F83: 8711.9516 | G83: 8711.9516 | H83: 8711.9516 | I83: 8711.9516 | J83: 8711.9516 | K83: 8711.9516 | L83: 8711.9516
E84: 0.03 | F84: 8711.9516 | G84: 8711.9516 | H84: 8711.9516 | I84: 8711.9516 | J84: 8711.9516 | K84: 8711.9516 | L84: 8711.9516
E85: 0.035 | F85: 8711.9516 | G85: 8711.9516 | H85: 8711.9516 | I85: 8711.9516 | J85: 8711.9516 | K85: 8711.9516 | L85: 8711.9516
E86: 0.04 | F86: 8711.9516 | G86: 8711.9516 | H86: 8711.9516 | I86: 8711.9516 | J86: 8711.9516 | K86: 8711.9516 | L86: 8711.9516
E87: 0.045 | F87: 8711.9516 | G87: 8711.9516 | H87: 8711.9516 | I87: 8711.9516 | J87: 8711.9516 | K87: 8711.9516 | L87: 8711.9516
D89: Choice Hotels International Inc. Sensitivity Analysis - Exit Multiple
E90: Discount Rate
E91: =F49 -> 8711.9516 | F91: 0.065 | G91: 0.07 | H91: 0.075 | I91: 0.08 | J91: 0.085 | K91: 0.09 | L91: 0.095
D92: Exit Multiple | E92: 15 | F92: 8711.9516 | G92: 8711.9516 | H92: 8711.9516 | I92: 8711.9516 | J92: 8711.9516 | K92: 8711.9516 | L92: 8711.9516
E93: 15.5 | F93: 8711.9516 | G93: 8711.9516 | H93: 8711.9516 | I93: 8711.9516 | J93: 8711.9516 | K93: 8711.9516 | L93: 8711.9516
E94: 16 | F94: 8711.9516 | G94: 8711.9516 | H94: 8711.9516 | I94: 8711.9516 | J94: 8711.9516 | K94: 8711.9516 | L94: 8711.9516
E95: 16.5 | F95: 8711.9516 | G95: 8711.9516 | H95: 8711.9516 | I95: 8711.9516 | J95: 8711.9516 | K95: 8711.9516 | L95: 8711.9516
E96: 17 | F96: 8711.9516 | G96: 8711.9516 | H96: 8711.9516 | I96: 8711.9516 | J96: 8711.9516 | K96: 8711.9516 | L96: 8711.9516
E97: 17.5 | F97: 8711.9516 | G97: 8711.9516 | H97: 8711.9516 | I97: 8711.9516 | J97: 8711.9516 | K97: 8711.9516 | L97: 8711.9516
E98: 18 | F98: 8711.9516 | G98: 8711.9516 | H98: 8711.9516 | I98: 8711.9516 | J98: 8711.9516 | K98: 8711.9516 | L98: 8711.9516
D100: Implied Equity Value
D102: Choice Hotels International Inc. Sensitivity Analysis - Terminal Growth Rate
E103: Discount Rate
E104: =K45 -> 6850.8266 | F104: 0.065 | G104: 0.07 | H104: 0.075 | I104: 0.08 | J104: 0.085 | K104: 0.09 | L104: 0.095
D105: Implied Perpetuity Growth Rate | E105: 0.015 | F105: 6850.8266 | G105: 6850.8266 | H105: 6850.8266 | I105: 6850.8266 | J105: 6850.8266 | K105: 6850.8266 | L105: 6850.8266
E106: 0.02 | F106: 6850.8266 | G106: 6850.8266 | H106: 6850.8266 | I106: 6850.8266 | J106: 6850.8266 | K106: 6850.8266 | L106: 6850.8266
E107: 0.025 | F107: 6850.8266 | G107: 6850.8266 | H107: 6850.8266 | I107: 6850.8266 | J107: 6850.8266 | K107: 6850.8266 | L107: 6850.8266
E108: 0.03 | F108: 6850.8266 | G108: 6850.8266 | H108: 6850.8266 | I108: 6850.8266 | J108: 6850.8266 | K108: 6850.8266 | L108: 6850.8266
E109: 0.035 | F109: 6850.8266 | G109: 6850.8266 | H109: 6850.8266 | I109: 6850.8266 | J109: 6850.8266 | K109: 6850.8266 | L109: 6850.8266
E110: 0.04 | F110: 6850.8266 | G110: 6850.8266 | H110: 6850.8266 | I110: 6850.8266 | J110: 6850.8266 | K110: 6850.8266 | L110: 6850.8266
E111: 0.045 | F111: 6850.8266 | G111: 6850.8266 | H111: 6850.8266 | I111: 6850.8266 | J111: 6850.8266 | K111: 6850.8266 | L111: 6850.8266
D113: Choice Hotels International Inc. Sensitivity Analysis - Exit Multiple
E114: Discount Rate
E115: =K45 -> 6850.8266 | F115: 0.065 | G115: 0.07 | H115: 0.075 | I115: 0.08 | J115: 0.085 | K115: 0.09 | L115: 0.095
D116: Exit Multiple | E116: 15 | F116: 6850.8266 | G116: 6850.8266 | H116: 6850.8266 | I116: 6850.8266 | J116: 6850.8266 | K116: 6850.8266 | L116: 6850.8266
...

Sheet ValGraph
D2: Choice Hotels International Inc. (NYSE: CHH)
D3: Valuation Graph
D4: ($ in millions, except per share data)
D27: Valuation Statistics - Choice Hotels International Inc. (Implied Share Price)
J28: Range of Multiples | M28: Implied Share Price Range
J29: Min | K29: Median | L29: Max | M29: Min | N29: Median | O29: Max
D30: Discounted Cash Flow Analysis
D31: 6.5% - 9.5% Discount Rate, 1.5% - 4.5% Perpetuity Growth Rate | M31: 104.42276 | N31: 184.24421 | O31: 502.79575
D32: 6.5% - 9.5% Discount Rate, 13.0x - 19.0x EBITDA Multiple | M32: 124.09282 | N32: 147.13648 | O32: 172.6735
D34: Public Company Comparables
D35: LTM, EV/EBITDA | J35: =CompsVal!F10 -> 12.910781 | K35: =MEDIAN(J35,L35) -> 19.134031 | L35: =CompsVal!H10 -> 25.35728 | M35: =CompsVal!Q10 -> 133.55735 | N35: =MEDIAN(M35,O35) -> 217.82014 | O35: =CompsVal!S10 -> 302.08294
D36: 2026E, EV/EBITDA | J36: =CompsVal!F11 -> 12.508354 | K36: =MEDIAN(J36,L36) -> 17.379432 | L36: =CompsVal!H11 -> 22.25051 | M36: =CompsVal!Q11 -> 130.89691 | N36: =MEDIAN(M36,O36) -> 197.93719 | O36: =CompsVal!S11 -> 264.97747
D37: 2027E, EV/EBITDA | J37: =CompsVal!F12 -> 11.722232 | K37: =MEDIAN(J37,L37) -> 16.067493 | L37: =CompsVal!H12 -> 20.412755 | M37: =CompsVal!Q12 -> 123.85781 | N37: =MEDIAN(M37,O37) -> 185.06259 | O37: =CompsVal!S12 -> 246.26737
D39: LTM, P/E | J39: =CompsVal!F18 -> -308.038 | K39: =MEDIAN(J39,L39) -> -127.22945 | L39: =CompsVal!H18 -> 53.579094 | M39: =CompsVal!M18 -> -2650.4132 | N39: =MEDIAN(M39,O39) -> -1094.7046 | O39: =CompsVal!O18 -> 461.00397
D40: 2026E, P/E | J40: =CompsVal!F19 -> 11.310405 | K40: =MEDIAN(J40,L40) -> 34.26345 | L40: =CompsVal!H19 -> 57.216495 | M40: =CompsVal!M19 -> 98.304457 | N40: =MEDIAN(M40,O40) -> 297.80099 | O40: =CompsVal!O19 -> 497.29751
D41: 2027E, P/E | J41: =CompsVal!F20 -> 12.27019 | K41: =MEDIAN(J41,L41) -> 25.956524 | L41: =CompsVal!H20 -> 39.642857 | M41: =CompsVal!M20 -> 110.15062 | N41: =MEDIAN(M41,O41) -> 233.0141 | O41: =CompsVal!O20 -> 355.87757
D65: Valuation Statistics - Choice Hotels International Inc. (Implied Enterprise Value)
J66: Range of Multiples | M66: Implied Enterprise Value Range
J67: Min | K67: Median | L67: Max | M67: Min | N67: Median | O67: Max
D68: Discounted Cash Flow Analysis
D69: 6% - 8% Discount Rate, 1.5% - 4.5% Perpetuity Growth Rate | M69: 7040.0318 | N69: 9093.6335 | O69: 12906.782
D70: 6% - 8% Discount Rate, 13.0x - 19.0x EBITDA Multiple | M70: 7121.7329 | N70: 7580.6089 | O70: 8069.2188
D72: Public Company Comparables
D73: LTM, EV/EBITDA | J73: =CompsVal!F10 -> 12.910781 | K73: =MEDIAN(J73,L73) -> 19.134031 | L73: =CompsVal!H10 -> 25.35728 | M73: =CompsVal!I10 -> 8076.9848 | N73: =MEDIAN(M73,O73) -> 11970.25 | O73: =CompsVal!K10 -> 15863.514
D74: 2026E, EV/EBITDA | J74: =CompsVal!F11 -> 12.508354 | K74: =MEDIAN(J74,L74) -> 17.379432 | L74: =CompsVal!H11 -> 22.25051 | M74: =CompsVal!I11 -> 7954.0622 | N74: =MEDIAN(M74,O74) -> 11051.581 | O74: =CompsVal!K11 -> 14149.099
D75: 2027E, EV/EBITDA | J75: =CompsVal!F12 -> 11.722232 | K75: =MEDIAN(J75,L75) -> 16.067493 | L75: =CompsVal!H12 -> 20.412755 | M75: =CompsVal!I12 -> 7628.8285 | N75: =MEDIAN(M75,O75) -> 10456.725 | O75: =CompsVal!K12 -> 13284.621
D77: LTM, P/E | J77: =CompsVal!F26 -> -308.038 | K77: =MEDIAN(J77,L77) -> -127.22945 | L77: =CompsVal!H26 -> 53.579094 | M77: =CompsVal!M26 -> -120553.15 | N77: =MEDIAN(M77,O77) -> -48673.439 | O77: =CompsVal!O26 -> 23206.277
D78: 2026E, P/E | J78: =CompsVal!F27 -> 11.310405 | K78: =MEDIAN(J78,L78) -> 34.26345 | L78: =CompsVal!H27 -> 57.216495 | M78: =CompsVal!M27 -> 6448.1657 | N78: =MEDIAN(M78,O78) -> 15665.672 | O78: =CompsVal!O27 -> 24883.178
D79: 2027E, P/E | J79: =CompsVal!F28 -> 12.27019 | K79: =MEDIAN(J79,L79) -> 25.956524 | L79: =CompsVal!H28 -> 39.642857 | M79: =CompsVal!M28 -> 6995.5041 | N79: =MEDIAN(M79,O79) -> 12672.269 | O79: =CompsVal!O28 -> 18349.033
