Workbook
Name days: Schedule!$G$37
Name tax_rate: FCFF!$E$10
Name terminal_growth: FCFF!$E$12
Name wacc: FCFF!$E$11

Sheet Dashboard
B2: The Coca-Cola Company
B3: Dashboard
B4: (in Millions, except per share data)
B6: Company Name: | E6: =B2 -> The Coca-Cola Company | I6: Current Price: | L6: =FCFF!I9 -> 70.07
B7: Ticker: | E7: KO | I7: Implied Share Price: | L7: =FCFF!I8 -> 83.889061
I8: Premium (Discount): | L8: =L6/L7-1 -> -0.16473019
B9: Last Historical Date: | E9: =Historicals!K5 -> 45657
B10: Last Forecast Date: | E10: =Historicals!P5 -> 47483
B11: Forecast Period: | E11: =YEARFRAC(Historicals!K5,Historicals!P5,1) -> 4.9981752
B12: Days in an Year: | E12: 365
B15: Table of Contents
B16: Sl. No | C16: Particulars
B17: 1 | C17: Historicals
B18: 2 | C18: Assumptions
B19: 3 | C19: Schedule
B20: 4 | C20: Beta
B21: 5 | C21: WACC
B22: 6 | C22: FCFF
B23: 7 | C23: Ratio Analysis

Sheet Financials->

Sheet Historicals
B2: The Coca-Cola Company
B3: Financial Statements
B4: (in Millions, except per share data)
B5: Date | H5: 44561 | I5: =EDATE(H5,12) -> 44926 | J5: =EDATE(I5,12) -> 45291 | K5: =EDATE(J5,12) -> 45657 | L5: =EDATE(K5,12) -> 46022 | M5: =EDATE(L5,12) -> 46387 | N5: =EDATE(M5,12) -> 46752 | O5: =EDATE(N5,12) -> 47118 | P5: =EDATE(O5,12) -> 47483
B6: Actual / Forecast | H6: Actual | I6: Actual | J6: Actual | K6: Actual | L6: Forecast | M6: Forecast | N6: Forecast | O6: Forecast | P6: Forecast
A8: * | B8: Income Statement
B9: Net Revenue | H9: =Assumptions!G40 -> 38655 | I9: =Assumptions!H40 -> 43004 | J9: =Assumptions!I40 -> 45754 | K9: =Assumptions!J40 -> 47061
B10: Less: Extraordinary Item | H10: 3 | I10: 42 | J10: 30 | K10: -164
B11: Normalised Net Revenue | H11: =SUM(H9:H10) -> 38658 | I11: =SUM(I9:I10) -> 43046 | J11: =SUM(J9:J10) -> 45784 | K11: =SUM(K9:K10) -> 46897 | L11: =Assumptions!K40 -> 51644.976 | M11: =Assumptions!L40 -> 56165.181 | N11: =Assumptions!M40 -> 60498.75 | O11: =Assumptions!N40 -> 64515.925 | P11: =Assumptions!O40 -> 67471.203
B13: Cost of Goods Sold | H13: =Data!B5 -> 15357 | I13: =Data!C5 -> 18000 | J13: =Data!D5 -> 18520 | K13: =Data!E5 -> 18324
B14: Less: Extraordinary Item | H14: 53 | I14: -183 | J14: -55 | K14: -70
B15: Normalised COGS | H15: =SUM(H13:H14) -> 15410 | I15: =SUM(I13:I14) -> 17817 | J15: =SUM(J13:J14) -> 18465 | K15: =SUM(K13:K14) -> 18254 | L15: =Assumptions!K47 -> 20715.005 | M15: =Assumptions!L47 -> 22528.077 | N15: =Assumptions!M47 -> 24266.289 | O15: =Assumptions!N47 -> 25877.594 | P15: =Assumptions!O47 -> 27062.968
B17: Normalised Gross profit | H17: =H11-H15 -> 23248 | I17: =I11-I15 -> 25229 | J17: =J11-J15 -> 27319 | K17: =K11-K15 -> 28643 | L17: =L11-L15 -> 30929.971 | M17: =M11-M15 -> 33637.104 | N17: =N11-N15 -> 36232.461 | O17: =O11-O15 -> 38638.331 | P17: =P11-P15 -> 40408.236
B19: Selling, General and administrative expenses | H19: =Data!B7 -> 12144 | I19: =Data!C7 -> 12880 | J19: =Data!D7 -> 13972 | K19: =Data!E7 -> 14582
B20: Less: Extraordinary Item | H20: -5 | I20: 4 | J20: 11 | K20: -24
B21: Normalised SG&A | H21: =SUM(H19:H20) -> 12139 | I21: =SUM(I19:I20) -> 12884 | J21: =SUM(J19:J20) -> 13983 | K21: =SUM(K19:K20) -> 14558 | L21: =Assumptions!K50 -> 15862.629 | M21: =Assumptions!L50 -> 17250.999 | N21: =Assumptions!M50 -> 18582.044 | O21: =Assumptions!N50 -> 19815.909 | P21: =Assumptions!O50 -> 20723.616
B23: Other Operating Charges | H23: =Data!B8 -> 846 | I23: =Data!C8 -> 1215 | J23: =Data!D8 -> 1951 | K23: =Data!E8 -> 4163
B24: Less: Extraordinary Item | H24: =-78-369-261-138 -> -846 | I24: =-1000-117-41-57 -> -1215 | J24: =-1702-191-58 -> -1951 | K24: =-886-3118-133-26 -> -4163
B25: Normalised Other Operating Charges | H25: =SUM(H23:H24) -> 0 | I25: =SUM(I23:I24) -> 0 | J25: =SUM(J23:J24) -> 0 | K25: =SUM(K23:K24) -> 0 | L25: =K25 -> 0 | M25: =L25 -> 0 | N25: =M25 -> 0 | O25: =N25 -> 0 | P25: =O25 -> 0
B27: Normalised Operating Income | H27: =H17-H21-H25 -> 11109 | I27: =I17-I21-I25 -> 12345 | J27: =J17-J21-J25 -> 13336 | K27: =K17-K21-K25 -> 14085 | L27: =L17-L21-L25 -> 15067.342 | M27: =M17-M21-M25 -> 16386.105 | N27: =N17-N21-N25 -> 17650.417 | O27: =O17-O21-O25 -> 18822.422 | P27: =P17-P21-P25 -> 19684.62
B29: Interest Income | H29: =Data!B10 -> 276 | I29: =Data!C10 -> 449 | J29: =Data!D10 -> 907 | K29: =Data!E10 -> 988 | L29: 0 | M29: 0 | N29: 0 | O29: 0 | P29: 0
B30: Interest Expense | H30: =Data!B11 -> 1597 | I30: =Data!C11 -> 882 | J30: =Data!D11 -> 1527 | K30: =Data!E11 -> 1656
B31: Less: Extraordinary Item | H31: -821 | I31: 24 | J31: 25 | K31: 25
B32: Normalised Interest Expense | H32: =SUM(H30:H31) -> 776 | I32: =SUM(I30:I31) -> 906 | J32: =SUM(J30:J31) -> 1552 | K32: =SUM(K30:K31) -> 1681 | L32: =Schedule!L64+Schedule!L74 -> 1544.5661 | M32: =Schedule!M64+Schedule!M74 -> 1565.6026 | N32: =Schedule!N64+Schedule!N74 -> 1583.6435 | O32: =Schedule!O64+Schedule!O74 -> 1579.0232 | P32: =Schedule!P64+Schedule!P74 -> 1542.6994
B34: Equity Income (net) \ loss | H34: =Data!B12 -> 1438 | I34: =Data!C12 -> 1472 | J34: =Data!D12 -> 1691 | K34: =Data!E12 -> 1770
B35: Less: Extraordinary Item | H35: 13 | I35: 34 | J35: 159 | K35: 92
B36: Normalised Equity Income Net | H36: =SUM(H34:H35) -> 1451 | I36: =SUM(I34:I35) -> 1506 | J36: =SUM(J34:J35) -> 1850 | K36: =SUM(K34:K35) -> 1862 | L36: =Assumptions!K53 -> 1969.6939 | M36: =Assumptions!L53 -> 2142.0906 | N36: =Assumptions!M53 -> 2307.3691 | O36: =Assumptions!N53 -> 2460.5806 | P36: =Assumptions!O53 -> 2573.2923
B38: Other Income (net) \ loss | H38: =Data!B13 -> 2000 | I38: =Data!C13 -> -262 | J38: =Data!D13 -> 570 | K38: =Data!E13 -> 1992
B39: Less: Extraordinary Item | H39: =-1666-84+117 -> -1633 | I39: =96-294+443 -> 245 | J39: =-855+39+108 -> -708 | K39: =34-1741-206 -> -1913
B40: Normalised Other Income Net | H40: =SUM(H38:H39) -> 367 | I40: =SUM(I38:I39) -> -17 | J40: =SUM(J38:J39) -> -138 | K40: =SUM(K38:K39) -> 79 | L40: =Assumptions!K56 -> 100.21029 | M40: =Assumptions!L56 -> 108.98116 | N40: =Assumptions!M56 -> 117.38988 | O40: =Assumptions!N56 -> 125.18468 | P40: =Assumptions!O56 -> 130.91901
B41: Income Before Taxes | H41: =H27+H29-H32+H36+H40 -> 12427 | I41: =I27+I29-I32+I36+I40 -> 13377 | J41: =J27+J29-J32+J36+J40 -> 14403 | K41: =K27+K29-K32+K36+K40 -> 15333 | L41: =L27+L29-L32+L36+L40 -> 15592.68 | M41: =M27+M29-M32+M36+M40 -> 17071.574 | N41: =N27+N29-N32+N36+N40 -> 18491.533 | O41: =O27+O29-O32+O36+O40 -> 19829.164 | P41: =P27+P29-P32+P36+P40 -> 20846.132
B43: Income Taxes | H43: =Data!B15 -> 2621 | I43: =Data!C15 -> 2115 | J43: =Data!D15 -> 2249 | K43: =Data!E15 -> 2437
B44: Normalised Income Taxes | H44: 2308 | I44: 2545 | J44: 2737 | K44: =2852 -> 2852 | L44: =Assumptions!K59 -> 2931.4647 | M44: =Assumptions!L59 -> 3209.5006 | N44: =Assumptions!M59 -> 3476.4564 | O44: =Assumptions!N59 -> 3727.9346 | P44: =Assumptions!O59 -> 3919.1272
B45: Consolidated Net Income | H45: =H41-H44 -> 10119 | I45: =I41-I44 -> 10832 | J45: =J41-J44 -> 11666 | K45: =K41-K44 -> 12481 | L45: =L41-L44 -> 12661.216 | M45: =M41-M44 -> 13862.074 | N45: =N41-N44 -> 15015.076 | O45: =O41-O44 -> 16101.229 | P45: =P41-P44 -> 16927.004
B47: Net income (loss) attributable to NCI | H47: =Data!B17 -> 33 | I47: =Data!C17 -> 29 | J47: =Data!D17 -> -11 | K47: =Data!E17 -> 18 | L47: =Assumptions!K62 -> 17.25 | M47: =Assumptions!L62 -> 13.3125 | N47: =Assumptions!M62 -> 9.390625 | O47: =Assumptions!N62 -> 14.488281 | P47: =Assumptions!O62 -> 13.610352
B48: Net Income to Common | H48: =H45-H47 -> 10086 | I48: =I45-I47 -> 10803 | J48: =J45-J47 -> 11677 | K48: =K45-K47 -> 12463 | L48: =L45-L47 -> 12643.966 | M48: =M45-M47 -> 13848.761 | N48: =N45-N47 -> 15005.685 | O48: =O45-O47 -> 16086.741 | P48: =P45-P47 -> 16913.394
B50: Diluted Net Income Per Share | H50: =H48/H51 -> 2.3239631 | I50: =I48/I51 -> 2.4834483 | J50: =J48/J51 -> 2.6911731 | K50: =K48/K51 -> 2.8849537 | L50: =L48/L51 -> 2.9268439 | M50: =M48/M51 -> 3.2057317 | N50: =N48/N51 -> 3.4735383 | O50: =O48/O51 -> 3.7237826 | P50: =P48/P51 -> 3.9151375
B51: Average Shares Outstanding — Diluted | H51: =Data!B23 -> 4340 | I51: =Data!C23 -> 4350 | J51: =Data!D23 -> 4339 | K51: =Data!E23 -> 4320 | L51: =K51 -> 4320 | M51: =L51 -> 4320 | N51: =M51 -> 4320 | O51: =N51 -> 4320 | P51: =O51 -> 4320
B53: Dividend Per Share | H53: =Assumptions!G43/Historicals!H51 -> 1.6799539 | I53: =Assumptions!H43/Historicals!I51 -> 1.76 | J53: =Assumptions!I43/Historicals!J51 -> 1.8400553 | K53: =Assumptions!J43/Historicals!K51 -> 1.9349537 | L53: =Assumptions!K43/Historicals!L51 -> 1.9801979 | M53: =Assumptions!L43/Historicals!M51 -> 2.1876656 | N53: =Assumptions!M43/Historicals!N51 -> 2.3907743 | O53: =Assumptions!N43/Historicals!O51 -> 2.5848304 | P53: =Assumptions!O43/Historicals!P51 -> 2.7405963
B54: Dividend Payout Ratio | H54: =Assumptions!G44 -> 0.7228832 | I54: =Assumptions!H44 -> 0.70869203 | J54: =Assumptions!I44 -> 0.68373726 | K54: =Assumptions!J44 -> 0.67070529 | L54: =Assumptions!K44 -> 0.67656423 | M54: =Assumptions!L44 -> 0.68242317 | N54: =Assumptions!M44 -> 0.68828212 | O54: =Assumptions!N44 -> 0.69414106 | P54: =Assumptions!O44 -> 0.7
B56: Ratio's (In Percentages%)
B57: Gross Profit Margin | H57: =H17/H11 -> 0.60137617 | I57: =I17/I11 -> 0.58609395 | J57: =J17/J11 -> 0.59669317 | K57: =K17/K11 -> 0.61076401 | L57: =L17/L11 -> 0.59889603 | M57: =M17/M11 -> 0.59889603 | N57: =N17/N11 -> 0.59889603 | O57: =O17/O11 -> 0.59889603 | P57: =P17/P11 -> 0.59889603
B58: EBIT Margin | H58: =H27/H11 -> 0.28736613 | I58: =I27/I11 -> 0.28678623 | J58: =J27/J11 -> 0.2912808 | K58: =K27/K11 -> 0.30033904 | L58: =L27/L11 -> 0.29174846 | M58: =M27/M11 -> 0.29174846 | N58: =N27/N11 -> 0.29174846 | O58: =O27/O11 -> 0.29174846 | P58: =P27/P11 -> 0.29174846
B59: Effective Tax rate | H59: =H44/H41 -> 0.18572463 | I59: =I44/I41 -> 0.19025192 | J59: =J44/J41 -> 0.19002985 | K59: =K44/K41 -> 0.18600404 | L59: =L44/L41 -> 0.18800261 | M59: =M44/M41 -> 0.18800261 | N59: =N44/N41 -> 0.18800261 | O59: =O44/O41 -> 0.18800261 | P59: =P44/P41 -> 0.18800261
B60: Net Profit Margin | H60: =H48/H11 -> 0.26090331 | I60: =I48/I11 -> 0.25096408 | J60: =J48/J11 -> 0.25504543 | K60: =K48/K11 -> 0.26575261 | L60: =L48/L11 -> 0.2448247 | M60: =M48/M11 -> 0.246572 | N60: =N48/N11 -> 0.24803299 | O60: =O48/O11 -> 0.24934527 | P60: =P48/P11 -> 0.25067574
B62: EBITDA | H62: =H63+H27 -> 12561 | I62: =I63+I27 -> 13605 | J62: =J63+J27 -> 14464 | K62: =K63+K27 -> 15160 | L62: =L63+L27 -> 16254.621 | M62: =M63+M27 -> 17660.573 | N62: =N63+N27 -> 19019.98 | O62: =O63+O27 -> 20272.136 | P62: =P63+P27 -> 21191.183
B63: Depreciation and Ammortisation | H63: =Data!D75 -> 1452 | I63: =Data!C32 -> 1260 | J63: =Data!D32 -> 1128 | K63: =Data!E32 -> 1075 | L63: =Schedule!L17 -> 1187.2785 | M63: =Schedule!M17 -> 1274.4682 | N63: =Schedule!N17 -> 1369.5625 | O63: =Schedule!O17 -> 1449.7139 | P63: =Schedule!P17 -> 1506.5634
B64: EBITDA Margin % | H64: =H62/H11 -> 0.32492628 | I64: =I62/I11 -> 0.31605724 | J64: =J62/J11 -> 0.31591822 | K64: =K62/K11 -> 0.32326162 | L64: =K64 -> 0.32326162 | M64: =L64 -> 0.32326162 | N64: =M64 -> 0.32326162 | O64: =N64 -> 0.32326162 | P64: =O64 -> 0.32326162
B66: EPS Growth % | I66: =I50/H50-1 -> 0.068626365 | J66: =J50/I50-1 -> 0.083643701 | K66: =K50/J50-1 -> 0.072006005 | L66: =L50/K50-1 -> 0.014520232 | M66: =M50/L50-1 -> 0.095286202 | N66: =N50/M50-1 -> 0.083539916 | O66: =O50/N50-1 -> 0.072043059 | P66: =P50/O50-1 -> 0.051387232
A69: * | B69: Balance Sheet
B70: Assets
B71: Current Assets
B72: Cash and cash equivalents | H72: 9684 | I72: 9519 | J72: 9366 | K72: 10828 | L72: =L147 -> 8399.0759 | M72: =M147 -> 13489.719 | N72: =N147 -> 18409.62 | O72: =O147 -> 23046.582 | P72: =P147 -> 27104.991 | Q72: CFS
B73: Short-term investments | H73: 1242 | I73: 1043 | J73: 2997 | K73: 2020 | L73: =K73 -> 2020 | M73: =L73 -> 2020 | N73: =M73 -> 2020 | O73: =N73 -> 2020 | P73: =O73 -> 2020
B74: Total Cash, Cash Equivalents and Short-Term Investments | H74: 10926 | I74: 10562 | J74: 12363 | K74: 12848 | L74: =SUM(L72:L73) -> 10419.076 | M74: =SUM(M72:M73) -> 15509.719 | N74: =SUM(N72:N73) -> 20429.62 | O74: =SUM(O72:O73) -> 25066.582 | P74: =SUM(P72:P73) -> 29124.991
B76: Marketable securities | H76: 1699 | I76: 1069 | J76: 1300 | K76: 1723 | L76: =K76 -> 1723 | M76: =L76 -> 1723 | N76: =M76 -> 1723 | O76: =N76 -> 1723 | P76: =O76 -> 1723
B77: Trade accounts receivable | H77: 3512 | I77: 3487 | J77: 3410 | K77: 3569 | L77: =Schedule!L38 -> 3842.7862 | M77: =Schedule!M38 -> 4179.1244 | N77: =Schedule!N38 -> 4501.5755 | O77: =Schedule!O38 -> 4800.4845 | P77: =Schedule!P38 -> 5020.3801 | Q77: WC
B78: Inventories | H78: 3414 | I78: 4233 | J78: 4424 | K78: 4728 | L78: =Schedule!L39 -> 5192.9365 | M78: =Schedule!M39 -> 5647.4461 | N78: =Schedule!N39 -> 6083.1893 | O78: =Schedule!O39 -> 6487.119 | P78: =Schedule!P39 -> 6784.2742 | Q78: WC
B79: Prepaid expenses and other current assets | H79: 2994 | I79: 3240 | J79: 5235 | K79: 3129 | L79: =Schedule!L45 -> 3488.0963 | M79: =Schedule!M45 -> 3793.3905 | N79: =Schedule!N45 -> 4086.0793 | O79: =Schedule!O45 -> 4357.3988 | P79: =Schedule!P45 -> 4556.998 | Q79: WC
B80: Total Current Assets | H80: 22545 | I80: 22591 | J80: 26732 | K80: 25997 | L80: =SUM(L76:L79) -> 14246.819 | M80: =SUM(M76:M79) -> 15342.961 | N80: =SUM(N76:N79) -> 16393.844 | O80: =SUM(O76:O79) -> 17368.002 | P80: =SUM(P76:P79) -> 18084.652
B82: Equity method investments | H82: 17598 | I82: 18264 | J82: 19671 | K82: 18087 | L82: =K82 -> 18087 | M82: =L82 -> 18087 | N82: =M82 -> 18087 | O82: =N82 -> 18087 | P82: =O82 -> 18087
B83: Other investments | H83: 818 | I83: 501 | J83: 118 | K83: 44 | L83: =K83 -> 44 | M83: =L83 -> 44 | N83: =M83 -> 44 | O83: =N83 -> 44 | P83: =O83 -> 44
B84: Other noncurrent assets | H84: 6731 | I84: 6189 | J84: 7162 | K84: 12898 | L84: =K84 -> 12898 | M84: =L84 -> 12898 | N84: =M84 -> 12898 | O84: =N84 -> 12898 | P84: =O84 -> 12898
B85: Deferred income tax assets | H85: 2129 | I85: 1746 | J85: 1561 | K85: 1319 | L85: =K85 -> 1319 | M85: =L85 -> 1319 | N85: =M85 -> 1319 | O85: =N85 -> 1319 | P85: =O85 -> 1319 | Q85: *change after complettion
B86: Property, plant and equipment — net | H86: 9920 | I86: 9841 | J86: 9236 | K86: 10303 | L86: =Schedule!L14 -> 11886.133 | M86: =Schedule!M14 -> 12630.794 | N86: =Schedule!N14 -> 13198.726 | O86: =Schedule!O14 -> 13540.116 | P86: =Schedule!P14 -> 13352.186
B87: Trademarks with indefinite lives | H87: 14465 | I87: 14214 | J87: 14349 | K87: 13301 | L87: =K87 -> 13301 | M87: =L87 -> 13301 | N87: =M87 -> 13301 | O87: =N87 -> 13301 | P87: =O87 -> 13301
B88: Goodwill | H88: 19363 | I88: 18782 | J88: 18358 | K88: 18139 | L88: =K88 -> 18139 | M88: =L88 -> 18139 | N88: =M88 -> 18139 | O88: =N88 -> 18139 | P88: =O88 -> 18139
B89: Other intangible assets | H89: 785 | I89: 635 | J89: 516 | K89: 461 | L89: =Schedule!L24 -> 407 | M89: =Schedule!M24 -> 365 | N89: =Schedule!N24 -> 323 | O89: =Schedule!O24 -> 289 | P89: =Schedule!P24 -> 263
B90: Total Assets | H90: 94354 | I90: 92763 | J90: 97703 | K90: 100549 | L90: =SUM(L82:L89)+L74+L80 -> 100747.03 | M90: =SUM(M82:M89)+M74+M80 -> 107636.47 | N90: =SUM(N82:N89)+N74+N80 -> 114133.19 | O90: =SUM(O82:O89)+O74+O80 -> 120051.7 | P90: =SUM(P82:P89)+P74+P80 -> 124612.83
B91: Equity & Liabilities
B92: Current Liabilities
B93: Accounts payable and accrued expenses | H93: 14619 | I93: 15749 | J93: 15485 | K93: 21715 | L93: =Schedule!L49 -> 17371.885 | M93: =Schedule!M49 -> 18892.352 | N93: =Schedule!N49 -> 20350.04 | O93: =Schedule!O49 -> 21701.302 | P93: =Schedule!P49 -> 22695.373 | Q93: WC
B94: Loans and notes payable | H94: 3307 | I94: 2373 | J94: 4557 | K94: 1499 | L94: =Schedule!L71 -> 1512.324 | M94: =Schedule!M71 -> 1540.0133 | N94: =Schedule!N71 -> 1547.4968 | O94: =Schedule!O71 -> 1531.0054 | P94: =Schedule!P71 -> 1476.6791 | Q94: Debt schedule
B95: Current maturities of long-term debt | H95: 1338 | I95: 399 | J95: 1960 | K95: 648 | L95: =Schedule!M60 -> 1803 | M95: =Schedule!N60 -> 5064 | N95: =Schedule!O60 -> 2786 | O95: =Schedule!P60 -> 2684 | P95: =Schedule!Q60 -> 0 | Q95: Debt schedule
B96: Accrued income taxes | H96: 686 | I96: 1203 | J96: 1569 | K96: 1387 | L96: =Schedule!L52 -> 1425.6457 | M96: =Schedule!M52 -> 1560.8616 | N96: =Schedule!N52 -> 1690.689 | O96: =Schedule!O52 -> 1812.9892 | P96: =Schedule!P52 -> 1905.9711 | Q96: WC
B97: Total Current Liabilities | H97: 19950 | I97: 19724 | J97: 23571 | K97: 25249 | L97: =SUM(L93:L96) -> 22112.854 | M97: =SUM(M93:M96) -> 27057.227 | N97: =SUM(N93:N96) -> 26374.226 | O97: =SUM(O93:O96) -> 27729.297 | P97: =SUM(P93:P96) -> 26078.023
B99: Long-term debt | H99: 38116 | I99: 36377 | J99: 35547 | K99: 42375 | L99: =Schedule!L61-Schedule!M60 -> 41602.413 | M99: =Schedule!M61-Schedule!N60 -> 39136.128 | N99: =Schedule!N61-Schedule!O60 -> 41628.914 | O99: =Schedule!O61-Schedule!P60 -> 41257.592 | P99: =Schedule!P61-Schedule!Q60 -> 42382.366 | Q99: Debt schedule | R99: =_xlfn.FORMULATEXT(L99) -> =Schedule!L61-Schedule!M60
B100: Other noncurrent liabilities | H100: 8607 | I100: 7922 | J100: 8466 | K100: 4084 | L100: =K100 -> 4084 | M100: =L100 -> 4084 | N100: =M100 -> 4084 | O100: =N100 -> 4084 | P100: =O100 -> 4084
B101: Deferred income tax liabilities | H101: 2821 | I101: 2914 | J101: 2639 | K101: 2469 | L101: =K101 -> 2469 | M101: =L101 -> 2469 | N101: =M101 -> 2469 | O101: =N101 -> 2469 | P101: =O101 -> 2469
B103: Equity Attributable to Shareowners of The Coca-Cola Company | H103: 22999 | I103: 24105 | J103: 25941 | K103: 24856 | L103: =K103-Assumptions!K43+Historicals!L48 -> 28945.511 | M103: =L103-Assumptions!L43+Historicals!M48 -> 33343.556 | N103: =M103-Assumptions!M43+Historicals!N48 -> 38021.097 | O103: =N103-Assumptions!N43+Historicals!O48 -> 42941.37 | P103: =O103-Assumptions!O43+Historicals!P48 -> 48015.389
B104: Equity attributable to noncontrolling interests | H104: 1861 | I104: 1721 | J104: 1539 | K104: 1516 | L104: =K104+L47 -> 1533.25 | M104: =L104+M47 -> 1546.5625 | N104: =M104+N47 -> 1555.9531 | O104: =N104+O47 -> 1570.4414 | P104: =O104+P47 -> 1584.0518
B105: Total Equity | H105: 24860 | I105: 25826 | J105: 27480 | K105: 26372 | L105: =SUM(L103:L104) -> 30478.761 | M105: =SUM(M103:M104) -> 34890.119 | N105: =SUM(N103:N104) -> 39577.05 | O105: =SUM(O103:O104) -> 44511.812 | P105: =SUM(P103:P104) -> 49599.44
B106: Total Liabilities and Equity | H106: 94354 | I106: 92763 | J106: 97703 | K106: 100549 | L106: =SUM(L99:L101)+L105+L97 -> 100747.03 | M106: =SUM(M99:M101)+M105+M97 -> 107636.47 | N106: =SUM(N99:N101)+N105+N97 -> 114133.19 | O106: =SUM(O99:O101)+O105+O97 -> 120051.7 | P106: =SUM(P99:P101)+P105+P97 -> 124612.83
B108: B.S Check | H108: =IF(H106=H90,"TRUE",H90-H106) -> TRUE | I108: =IF(I106=I90,"TRUE",I90-I106) -> TRUE | J108: =IF(J106=J90,"TRUE",J90-J106) -> TRUE | K108: =IF(K106=K90,"TRUE",K90-K106) -> TRUE | L108: =IF(L106=L90,"TRUE",L90-L106) -> TRUE | M108: =IF(M106=M90,"TRUE",M90-M106) -> TRUE | N108: =IF(N106=N90,"TRUE",N90-N106) -> TRUE | O108: =IF(O106=O90,"TRUE",O90-O106) -> TRUE | P108: =IF(P106=P90,"TRUE",P90-P106) -> TRUE
A110: * | B110: Cash Flow Statement
B112: Operating Activities
B113: Consolidated Net Income | L113: =L45 -> 12661.216 | M113: =M45 -> 13862.074 | N113: =N45 -> 15015.076 | O113: =O45 -> 16101.229 | P113: =P45 -> 16927.004
B114: Add/Less: Non-Cash Items
B115: Depreciation and amortization | L115: =L63 -> 1187.2785 | M115: =M63 -> 1274.4682 | N115: =N63 -> 1369.5625 | O115: =O63 -> 1449.7139 | P115: =P63 -> 1506.5634
B116: Interest Expenses | L116: =L32 -> 1544.5661 | M116: =M32 -> 1565.6026 | N116: =N32 -> 1583.6435 | O116: =O32 -> 1579.0232 | P116: =P32 -> 1542.6994
B117: Interest Income | L117: =L29 -> 0 | M117: =M29 -> 0 | N117: =N29 -> 0 | O117: =O29 -> 0 | P117: =P29 -> 0
B118: Equity Income | L118: =-L36 -> -1969.6939 | M118: =-M36 -> -2142.0906 | N118: =-N36 -> -2307.3691 | O118: =-O36 -> -2460.5806 | P118: =-P36 -> -2573.2923
B119: Other Income | L119: =-L40 -> -100.21029 | M119: =-M40 -> -108.98116 | N119: =-N40 -> -117.38988 | O119: =-O40 -> -125.18468 | P119: =-P40 -> -130.91901
B120: Cash Flow from Operations before WC changes | L120: =SUM(L113:L119) -> 13323.156 | M120: =SUM(M113:M119) -> 14451.073 | N120: =SUM(N113:N119) -> 15543.523 | O120: =SUM(O113:O119) -> 16544.201 | P120: =SUM(P113:P119) -> 17272.056
B121: Changes in Working Capital
B122: Trade accounts receivable | L122: =-(L77-K77) -> -273.78618 | M122: =-(M77-L77) -> -336.33827 | N122: =-(N77-M77) -> -322.45107 | O122: =-(O77-N77) -> -298.90895 | P122: =-(P77-O77) -> -219.89561
B123: Inventories | L123: =-(L78-K78) -> -464.93652 | M123: =-(M78-L78) -> -454.50961 | N123: =-(N78-M78) -> -435.7432 | O123: =-(O78-N78) -> -403.92963 | P123: =-(P78-O78) -> -297.15521
B124: Prepaid expenses and other current assets | L124: =-(L79-K79) -> -359.0963 | M124: =-(M79-L79) -> -305.29418 | N124: =-(N79-M79) -> -292.68877 | O124: =-(O79-N79) -> -271.3196 | P124: =-(P79-O79) -> -199.5992
B125: Accounts payable and accrued expenses | L125: =L93-K93 -> -4343.1152 | M125: =M93-L93 -> 1520.467 | N125: =N93-M93 -> 1457.6879 | O125: =O93-N93 -> 1351.2622 | P125: =P93-O93 -> 994.0707
B126: Accrued income taxes | L126: =L96-K96 -> 38.645679 | M126: =M96-L96 -> 135.21592 | N126: =N96-M96 -> 129.82742 | O126: =O96-N96 -> 122.30023 | P126: =P96-O96 -> 92.981812
...

Sheet Assumptions
B2: The Coca-Cola Company
B3: Assumption Sheet
B4: (in Millions, except per share data)
B5: Date | G5: 44561 | H5: =EDATE(G5,12) -> 44926 | I5: =EDATE(H5,12) -> 45291 | J5: =EDATE(I5,12) -> 45657 | K5: =EDATE(J5,12) -> 46022 | L5: =EDATE(K5,12) -> 46387 | M5: =EDATE(L5,12) -> 46752 | N5: =EDATE(M5,12) -> 47118 | O5: =EDATE(N5,12) -> 47483
B6: Actual / Forecast | G6: Actual | H6: Actual | I6: Actual | J6: Actual | K6: Forecast | L6: Forecast | M6: Forecast | N6: Forecast | O6: Forecast
A8: * | B8: Revenue Assumptions
B9: Europe, Middle East & Africa | G9: 7193 | H9: 7523 | I9: 8078 | J9: 8122 | K9: =J9*(1+K12) -> 9056.03 | L9: =K9*(1+L12) -> 9961.633 | M9: =L9*(1+M12) -> 10808.372 | N9: =M9*(1+N12) -> 11564.958 | O9: =N9*(1+O12) -> 12027.556
B10: Growth Rate | H10: =H9/G9-1 -> 0.045877937 | I10: =I9/H9-1 -> 0.07377376 | J10: =J9/I9-1 -> 0.0054468928
B11: Fluctuations | H11: 0.13 | I11: 0.12 | J11: 0.16
B12: Total Growth | H12: =H10+H11 -> 0.17587794 | I12: =I10+I11 -> 0.19377376 | J12: =J10+J11 -> 0.16544689 | K12: 0.115 | L12: =K12+($O$12-$K$12)/5 -> 0.1 | M12: =L12+($O$12-$K$12)/5 -> 0.085 | N12: =M12+($O$12-$K$12)/5 -> 0.07 | O12: 0.04
B13: Latin America | G13: 4143 | H13: 4910 | I13: 5830 | J13: 6459 | K13: =J13*(1+K16) -> 7653.915 | L13: =K13*(1+L16) -> 8909.1571 | M13: =L13*(1+M16) -> 10183.167 | N13: =M13*(1+N16) -> 11425.513 | O13: =N13*(1+O16) -> 12339.554
B14: Growth Rate | H14: =H13/G13-1 -> 0.18513155 | I14: =I13/H13-1 -> 0.18737271 | J14: =J13/I13-1 -> 0.10789022
B15: Fluctuations | H15: 0.05 | I15: 0.03 | J15: 0.13
B16: Total Growth | H16: =H14+H15 -> 0.23513155 | I16: =I14+I15 -> 0.21737271 | J16: =J14+J15 -> 0.23789022 | K16: 0.185 | L16: =K16+($O$16-$K$16)/5 -> 0.164 | M16: =L16+($O$16-$K$16)/5 -> 0.143 | N16: =M16+($O$16-$K$16)/5 -> 0.122 | O16: 0.08
B17: North America | G17: 13190 | H17: 15674 | I17: 16774 | J17: 18649 | K17: =J17*(1+K20) -> 20327.41 | L17: =K17*(1+L20) -> 21994.258 | M17: =L17*(1+M20) -> 23621.833 | N17: =M17*(1+N20) -> 25180.874 | O17: =N17*(1+O20) -> 26439.917
B18: Growth Rate | H18: =H17/G17-1 -> 0.18832449 | I18: =I17/H17-1 -> 0.070179916 | J18: =J17/I17-1 -> 0.11178014
B19: Fluctuations | H19: 0 | I19: 0.01 | J19: 0
B20: Total Growth | H20: =SUM(H18:H19) -> 0.18832449 | I20: =SUM(I18:I19) -> 0.080179916 | J20: =SUM(J18:J19) -> 0.11178014 | K20: 0.09 | L20: =K20+($O$20-$K$20)/5 -> 0.082 | M20: =L20+($O$20-$K$20)/5 -> 0.074 | N20: =M20+($O$20-$K$20)/5 -> 0.066 | O20: 0.05
B21: Asia Pacific | G21: 5291 | H21: 5445 | I21: 5455 | J21: 5546 | K21: =J21*(1+K24) -> 5730.9344 | L21: =K21*(1+L24) -> 5902.915 | M21: =L21*(1+M24) -> 6060.3621 | N21: =M21*(1+N24) -> 6201.7891 | O21: =N21*(1+O24) -> 6325.8249
B22: Growth Rate | H22: =H21/G21-1 -> 0.029106029 | I22: =I21/H21-1 -> 0.0018365473 | J22: =J21/I21-1 -> 0.016681943
B23: Fluctuations | H23: 0.08 | I23: 0.05 | J23: 0.02
B24: Total Growth | H24: =SUM(H22:H23) -> 0.10910603 | I24: =SUM(I22:I23) -> 0.051836547 | J24: =SUM(J22:J23) -> 0.036681943 | K24: =J24+($O$24-$J$24)/5 -> 0.033345555 | L24: =K24+($O$24-$J$24)/5 -> 0.030009166 | M24: =L24+($O$24-$J$24)/5 -> 0.026672777 | N24: =M24+($O$24-$J$24)/5 -> 0.023336389 | O24: 0.02
B25: Global Ventures | G25: 2805 | H25: 2843 | I25: 3064 | J25: 3129 | K25: =J25*(1+K28) -> 3249.6895 | L25: =K25*(1+L28) -> 3366.4459 | M25: =L25*(1+M28) -> 3478.5002 | N25: =M25*(1+N28) -> 3585.0912 | O25: =N25*(1+O28) -> 3685.4738
B26: Growth Rate | H26: =H25/G25-1 -> 0.013547237 | I26: =I25/H25-1 -> 0.077734787 | J26: =J25/I25-1 -> 0.021214099
B27: Fluctuations | H27: 0.12 | I27: 0 | J27: 0.02
B28: Total Growth | H28: =SUM(H26:H27) -> 0.13354724 | I28: =SUM(I26:I27) -> 0.077734787 | J28: =SUM(J26:J27) -> 0.041214099 | K28: =J28+($O$28-$J$28)/5 -> 0.038571279 | L28: =K28+($O$28-$J$28)/5 -> 0.03592846 | M28: =L28+($O$28-$J$28)/5 -> 0.03328564 | N28: =M28+($O$28-$J$28)/5 -> 0.03064282 | O28: 0.028
B29: Bottling Investments | G29: 7203 | H29: 7891 | I29: 7860 | J29: 6223 | K29: =J29*(1+K32) -> 6692.116 | L29: =K29*(1+L32) -> 7087.2063 | M29: =L29*(1+M32) -> 7389.7741 | N29: =M29*(1+N32) -> 7584.4655 | O29: =N29*(1+O32) -> 7660.3102
B30: Growth Rate | H30: =H29/G29-1 -> 0.095515757 | I30: =I29/H29-1 -> -0.0039285262 | J30: =J29/I29-1 -> -0.20826972
B31: Fluctuations | H31: 0.09 | I31: 0.14 | J31: 0.3
B32: Total Growth | H32: =SUM(H30:H31) -> 0.18551576 | I32: =SUM(I30:I31) -> 0.13607147 | J32: =SUM(J30:J31) -> 0.09173028 | K32: =J32+($O$32-$J$32)/5 -> 0.075384224 | L32: =K32+($O$32-$J$32)/5 -> 0.059038168 | M32: =L32+($O$32-$J$32)/5 -> 0.042692112 | N32: =M32+($O$32-$J$32)/5 -> 0.026346056 | O32: 0.01
B33: Corporate | G33: 85 | H33: 94 | I33: 126 | J33: 97 | K33: =J33*(1+K36) -> 79.527683 | L33: =K33*(1+L36) -> 69.18151 | M33: =L33*(1+M36) -> 63.642596 | N33: =M33*(1+N36) -> 61.731298 | O33: =N33*(1+O36) -> 62.965924
B34: Growth Rate | H34: =H33/G33-1 -> 0.10588235 | I34: =I33/H33-1 -> 0.34042553 | J34: =J33/I33-1 -> -0.23015873
B35: Fluctuations | H35: 0 | I35: 0 | J35: 0
B36: Total Growth | H36: =SUM(H34:H35) -> 0.10588235 | I36: =SUM(I34:I35) -> 0.34042553 | J36: =SUM(J34:J35) -> -0.23015873 | K36: =J36+($O$36-$J$36)/5 -> -0.18012698 | L36: =K36+($O$36-$J$36)/5 -> -0.13009524 | M36: =L36+($O$36-$J$36)/5 -> -0.080063492 | N36: =M36+($O$36-$J$36)/5 -> -0.030031746 | O36: 0.02
B37: Eliminations | G37: -1255 | H37: -1376 | I37: -1433 | J37: -1164 | K37: =J37*(1+K38) -> -1144.6468 | L37: =K37*(1+L38) -> -1125.6154 | M37: =L37*(1+M38) -> -1106.9005 | N37: =M37*(1+N38) -> -1088.4966 | O37: =N37*(1+O38) -> -1070.3988
B38: Growth Rate | H38: =H37/G37-1 -> 0.096414343 | I38: =I37/H37-1 -> 0.041424419 | J38: =J37/I37-1 -> -0.18771807 | K38: =AVERAGE(H38:J38) -> -0.016626438 | L38: =K38 -> -0.016626438 | M38: =L38 -> -0.016626438 | N38: =M38 -> -0.016626438 | O38: =N38 -> -0.016626438
B40: Consolidated Revenue | G40: =G9+G13+G17+G21+G25+G29+G33+G37 -> 38655 | H40: =H9+H13+H17+H21+H25+H29+H33+H37 -> 43004 | I40: =I9+I13+I17+I21+I25+I29+I33+I37 -> 45754 | J40: =J9+J13+J17+J21+J25+J29+J33+J37 -> 47061 | K40: =K9+K13+K17+K21+K25+K29+K33+K37 -> 51644.976 | L40: =L9+L13+L17+L21+L25+L29+L33+L37 -> 56165.181 | M40: =M9+M13+M17+M21+M25+M29+M33+M37 -> 60498.75 | N40: =N9+N13+N17+N21+N25+N29+N33+N37 -> 64515.925 | O40: =O9+O13+O17+O21+O25+O29+O33+O37 -> 67471.203
B41: Revenue Growth % | H41: =H40/G40-1 -> 0.11250808 | I41: =I40/H40-1 -> 0.06394754 | J41: =J40/I40-1 -> 0.028565808 | K41: =K40/J40-1 -> 0.097404982 | L41: =L40/K40-1 -> 0.087524585 | M41: =M40/L40-1 -> 0.077157566 | N41: =N40/M40-1 -> 0.066400963 | O41: =O40/N40-1 -> 0.045806961
B43: Dividend Paid | G43: 7291 | H43: 7656 | I43: 7984 | J43: 8359 | K43: =Historicals!L48*Assumptions!K44 -> 8554.4549 | L43: =Historicals!M48*Assumptions!L44 -> 9450.7155 | M43: =Historicals!N48*Assumptions!M44 -> 10328.145 | N43: =Historicals!O48*Assumptions!N44 -> 11166.467 | O43: =Historicals!P48*Assumptions!O44 -> 11839.376
B44: Dividend Payout Ratio | G44: =G43/Historicals!H48 -> 0.7228832 | H44: =H43/Historicals!I48 -> 0.70869203 | I44: =I43/Historicals!J48 -> 0.68373726 | J44: =J43/Historicals!K48 -> 0.67070529 | K44: =J44+($O$44-$J$44)/5 -> 0.67656423 | L44: =K44+($O$44-$J$44)/5 -> 0.68242317 | M44: =L44+($O$44-$J$44)/5 -> 0.68828212 | N44: =M44+($O$44-$J$44)/5 -> 0.69414106 | O44: 0.7
A46: * | B46: Other Assumptions
B47: COGS | G47: =Historicals!H15 -> 15410 | H47: =Historicals!I15 -> 17817 | I47: =Historicals!J15 -> 18465 | J47: =Historicals!K15 -> 18254 | K47: =K40*K48 -> 20715.005 | L47: =L40*L48 -> 22528.077 | M47: =M40*M48 -> 24266.289 | N47: =N40*N48 -> 25877.594 | O47: =O40*O48 -> 27062.968
B48: COGS to Net Revenue % | G48: =G47/G40 -> 0.39865477 | H48: =H47/H40 -> 0.4143103 | I48: =I47/I40 -> 0.40357127 | J48: =J47/J40 -> 0.38787956 | K48: =AVERAGE($G$48:$J$48) -> 0.40110397 | L48: =AVERAGE($G$48:$J$48) -> 0.40110397 | M48: =AVERAGE($G$48:$J$48) -> 0.40110397 | N48: =AVERAGE($G$48:$J$48) -> 0.40110397 | O48: =AVERAGE($G$48:$J$48) -> 0.40110397
B50: Selling General & Adminstrative | G50: =Historicals!H21 -> 12139 | H50: =Historicals!I21 -> 12884 | I50: =Historicals!J21 -> 13983 | J50: =Historicals!K21 -> 14558 | K50: =K40*K51 -> 15862.629 | L50: =L40*L51 -> 17250.999 | M50: =M40*M51 -> 18582.044 | N50: =N40*N51 -> 19815.909 | O50: =O40*O51 -> 20723.616
B51: SG&A to Net Revenue % | G51: =G50/G40 -> 0.31403441 | H51: =H50/H40 -> 0.29960004 | I51: =I50/I40 -> 0.30561262 | J51: =J50/J40 -> 0.30934319 | K51: =AVERAGE($G$51:$J$51) -> 0.30714757 | L51: =AVERAGE($G$51:$J$51) -> 0.30714757 | M51: =AVERAGE($G$51:$J$51) -> 0.30714757 | N51: =AVERAGE($G$51:$J$51) -> 0.30714757 | O51: =AVERAGE($G$51:$J$51) -> 0.30714757
B53: Equity Income (net) \ loss | G53: =Historicals!H36 -> 1451 | H53: =Historicals!I36 -> 1506 | I53: =Historicals!J36 -> 1850 | J53: =Historicals!K36 -> 1862 | K53: =K40*K54 -> 1969.6939 | L53: =L40*L54 -> 2142.0906 | M53: =M40*M54 -> 2307.3691 | N53: =N40*N54 -> 2460.5806 | O53: =O40*O54 -> 2573.2923
B54: Equity Income to Net Revenue % | G54: =G53/G40 -> 0.037537188 | H54: =H53/H40 -> 0.035019998 | I54: =I53/I40 -> 0.040433623 | J54: =J53/J40 -> 0.03956567 | K54: =AVERAGE($G$54:$J$54) -> 0.03813912 | L54: =AVERAGE($G$54:$J$54) -> 0.03813912 | M54: =AVERAGE($G$54:$J$54) -> 0.03813912 | N54: =AVERAGE($G$54:$J$54) -> 0.03813912 | O54: =AVERAGE($G$54:$J$54) -> 0.03813912
B56: Other Income (net) \ loss | G56: =Historicals!H40 -> 367 | H56: =Historicals!I40 -> -17 | I56: =Historicals!J40 -> -138 | J56: =Historicals!K40 -> 79 | K56: =K40*K57 -> 100.21029 | L56: =L40*L57 -> 108.98116 | M56: =M40*M57 -> 117.38988 | N56: =N40*N57 -> 125.18468 | O56: =O40*O57 -> 130.91901
B57: Other Income to Net Revenue % | G57: =G56/G40 -> 0.009494244 | H57: =H56/H40 -> -0.00039531206 | I57: =I56/I40 -> -0.0030161297 | J57: =J56/J40 -> 0.0016786724 | K57: =AVERAGE($G$57:$J$57) -> 0.0019403686 | L57: =AVERAGE($G$57:$J$57) -> 0.0019403686 | M57: =AVERAGE($G$57:$J$57) -> 0.0019403686 | N57: =AVERAGE($G$57:$J$57) -> 0.0019403686 | O57: =AVERAGE($G$57:$J$57) -> 0.0019403686
B59: Income Taxes | G59: =Historicals!H44 -> 2308 | H59: =Historicals!I44 -> 2545 | I59: =Historicals!J44 -> 2737 | J59: =Historicals!K44 -> 2852 | K59: =Historicals!L41*Assumptions!K60 -> 2931.4647 | L59: =Historicals!M41*Assumptions!L60 -> 3209.5006 | M59: =Historicals!N41*Assumptions!M60 -> 3476.4564 | N59: =Historicals!O41*Assumptions!N60 -> 3727.9346 | O59: =Historicals!P41*Assumptions!O60 -> 3919.1272
B60: Effective tax rate to PBT % | G60: =G59/Historicals!H41 -> 0.18572463 | H60: =H59/Historicals!I41 -> 0.19025192 | I60: =I59/Historicals!J41 -> 0.19002985 | J60: =J59/Historicals!K41 -> 0.18600404 | K60: =AVERAGE($G$60:$J$60) -> 0.18800261 | L60: =AVERAGE($G$60:$J$60) -> 0.18800261 | M60: =AVERAGE($G$60:$J$60) -> 0.18800261 | N60: =AVERAGE($G$60:$J$60) -> 0.18800261 | O60: =AVERAGE($G$60:$J$60) -> 0.18800261
B62: Net income (loss) attributable to NCI | G62: =Historicals!H47 -> 33 | H62: =Historicals!I47 -> 29 | I62: =Historicals!J47 -> -11 | J62: =Historicals!K47 -> 18 | K62: =AVERAGE(G62:J62) -> 17.25 | L62: =AVERAGE(H62:K62) -> 13.3125 | M62: =AVERAGE(I62:L62) -> 9.390625 | N62: =AVERAGE(J62:M62) -> 14.488281 | O62: =AVERAGE(K62:N62) -> 13.610352
B64: Total LT Debt / EBITDA | G64: =(Historicals!H99+Historicals!H95)/Historicals!H62 -> 3.140992 | H64: =(Historicals!I99+Historicals!I95)/Historicals!I62 -> 2.7031239 | I64: =(Historicals!J99+Historicals!J95)/Historicals!J62 -> 2.5931278 | J64: =(Historicals!K99+Historicals!K95)/Historicals!K62 -> 2.8379288 | K64: =J64+($O$64-$J$64)/5 -> 2.670343 | L64: =K64+($O$64-$J$64)/5 -> 2.5027573 | M64: =L64+($O$64-$J$64)/5 -> 2.3351715 | N64: =M64+($O$64-$J$64)/5 -> 2.1675858 | O64: 2
B66: Notes and Loans Payable % to LT Debt | G66: =Historicals!H94/SUM(Historicals!H99,Historicals!H95) -> 0.083819131 | H66: =Historicals!I94/SUM(Historicals!I99,Historicals!I95) -> 0.064525778 | I66: =Historicals!J94/SUM(Historicals!J99,Historicals!J95) -> 0.12149732 | J66: =Historicals!K94/SUM(Historicals!K99,Historicals!K95) -> 0.034841829 | K66: =J66 -> 0.034841829 | L66: =K66 -> 0.034841829 | M66: =L66 -> 0.034841829 | N66: =M66 -> 0.034841829 | O66: =N66 -> 0.034841829

Sheet Schedule
B2: The Coca-Cola Company
B3: Schedule
B4: (in Millions, except per share data)
B5: Date | H5: 44561 | I5: =EDATE(H5,12) -> 44926 | J5: =EDATE(I5,12) -> 45291 | K5: =EDATE(J5,12) -> 45657 | L5: =EDATE(K5,12) -> 46022 | M5: =EDATE(L5,12) -> 46387 | N5: =EDATE(M5,12) -> 46752 | O5: =EDATE(N5,12) -> 47118 | P5: =EDATE(O5,12) -> 47483
B6: Actual / Forecast | H6: Actual | I6: Actual | J6: Actual | K6: Actual | L6: Forecast | M6: Forecast | N6: Forecast | O6: Forecast | P6: Forecast
A8: * | B8: Depreciation Schedule
B9: Property, plant and equipment
B10: Opening Gross Block | H10: 19700 | I10: =H12 -> 18862 | J10: =I12 -> 19075 | K10: =J12 -> 18469 | L10: =K12 -> 19873 | M10: =L12 -> 22589.411 | N10: =M12 -> 24566.54 | O10: =N12 -> 26462.035 | P10: =O12 -> 28219.139
B11: (+) Net Purchases | H11: =H12-H10 -> -838 | I11: =I12-I10 -> 213 | J11: =J12-J10 -> -606 | K11: =K12-K10 -> 1404 | L11: =L12-L10 -> 2716.4115 | M11: =M12-M10 -> 1977.1289 | N11: =N12-N10 -> 1895.4944 | O11: =O12-O10 -> 1757.1046 | P11: =P12-P10 -> 1292.633
B12: Closing Gross Block | H12: 18862 | I12: 19075 | J12: 18469 | K12: 19873 | L12: =Historicals!L11/Schedule!L19 -> 22589.411 | M12: =Historicals!M11/Schedule!M19 -> 24566.54 | N12: =Historicals!N11/Schedule!N19 -> 26462.035 | O12: =Historicals!O11/Schedule!O19 -> 28219.139 | P12: =Historicals!P11/Schedule!P19 -> 29511.772
B13: (-) Accumulated Depreciation | H13: 8942 | I13: 9234 | J13: 9233 | K13: 9570 | L13: =K13+L16 -> 10703.278 | M13: =L13+M16 -> 11935.747 | N13: =M13+N16 -> 13263.309 | O13: =N13+O16 -> 14679.023 | P13: =O13+P16 -> 16159.586
B14: Net PPE Block | H14: 9920 | I14: 9841 | J14: 9236 | K14: 10303 | L14: =L12-L13 -> 11886.133 | M14: =M12-M13 -> 12630.794 | N14: =N12-N13 -> 13198.726 | O14: =O12-O13 -> 13540.116 | P14: =P12-P13 -> 13352.186
B16: Depreciation | H16: 1262 | I16: 1125 | J16: 1018 | K16: 997 | L16: =L12*L18 -> 1133.2785 | M16: =M12*M18 -> 1232.4682 | N16: =N12*N18 -> 1327.5625 | O16: =O12*O18 -> 1415.7139 | P16: =P12*P18 -> 1480.5634
B17: Depreciation & Amortisation | H17: =Historicals!H63 -> 1452 | I17: =Historicals!I63 -> 1260 | J17: =Historicals!J63 -> 1128 | K17: =Historicals!K63 -> 1075 | L17: =L16+L33 -> 1187.2785 | M17: =M16+M33 -> 1274.4682 | N17: =N16+N33 -> 1369.5625 | O17: =O16+O33 -> 1449.7139 | P17: =P16+P33 -> 1506.5634
B18: Rate of Depreciation | H18: =H16/H12 -> 0.066907009 | I18: =I16/I12 -> 0.05897772 | J18: =J16/J12 -> 0.055119389 | K18: =K16/K12 -> 0.05016857 | L18: =K18 -> 0.05016857 | M18: =L18 -> 0.05016857 | N18: =M18 -> 0.05016857 | O18: =N18 -> 0.05016857 | P18: =O18 -> 0.05016857
B19: FATR | H19: =Historicals!H11/Schedule!H12 -> 2.0495175 | I19: =Historicals!I11/Schedule!I12 -> 2.256671 | J19: =Historicals!J11/Schedule!J12 -> 2.4789648 | K19: =Historicals!K11/Schedule!K12 -> 2.359835 | L19: =AVERAGE($H$19:$K$19) -> 2.2862471 | M19: =AVERAGE($H$19:$K$19) -> 2.2862471 | N19: =AVERAGE($H$19:$K$19) -> 2.2862471 | O19: =AVERAGE($H$19:$K$19) -> 2.2862471 | P19: =AVERAGE($H$19:$K$19) -> 2.2862471
B21: Other Intangible Assets
B22: Other Intangible Assets (with in-definite life) | H22: 211 | I22: 175 | J22: 161 | K22: =J22 -> 161 | L22: =K22 -> 161 | M22: =L22 -> 161 | N22: =M22 -> 161 | O22: =N22 -> 161 | P22: =O22 -> 161
B23: Other Intangible Assets (with definite life) | H23: =H31 -> 574 | I23: =I31 -> 460 | J23: =J31 -> 355 | K23: =K24-K22 -> 300 | L23: =L31 -> 246 | M23: =M31 -> 204 | N23: =N31 -> 162 | O23: =O31 -> 128 | P23: =P31 -> 102
B24: Total Other Intangible Assets | H24: =SUM(H22:H23) -> 785 | I24: =SUM(I22:I23) -> 635 | J24: =SUM(J22:J23) -> 516 | K24: 461 | L24: =SUM(L22:L23) -> 407 | M24: =SUM(M22:M23) -> 365 | N24: =SUM(N22:N23) -> 323 | O24: =SUM(O22:O23) -> 289 | P24: =SUM(P22:P23) -> 263
B26: Other Intangible Assets (with definite life)
B27: Opening Balance | H27: 772 | I27: =H29 -> 798 | J27: =I29 -> 707 | K27: =J29 -> 562 | L27: =K29 -> 562 | M27: =L29 -> 562 | N27: =M29 -> 562 | O27: =N29 -> 562 | P27: =O29 -> 562
B28: (+) Net Purchases | H28: =H29-H27 -> 26 | I28: =I29-I27 -> -91 | J28: =J29-J27 -> -145 | K28: 0 | L28: 0 | M28: 0 | N28: 0 | O28: 0 | P28: 0
B29: Closing Gross Block | H29: 798 | I29: 707 | J29: 562 | K29: =SUM(K27:K28) -> 562 | L29: =SUM(L27:L28) -> 562 | M29: =SUM(M27:M28) -> 562 | N29: =SUM(N27:N28) -> 562 | O29: =SUM(O27:O28) -> 562 | P29: =SUM(P27:P28) -> 562
B30: (-) Accumulated Amortization | H30: 224 | I30: 247 | J30: 207 | K30: =K29-K31 -> 262 | L30: =K30+L33 -> 316 | M30: =L30+M33 -> 358 | N30: =M30+N33 -> 400 | O30: =N30+O33 -> 434 | P30: =O30+P33 -> 460
B31: Net Other Intangible Assets Block | H31: =H29-H30 -> 574 | I31: =I29-I30 -> 460 | J31: =J29-J30 -> 355 | K31: =K23 -> 300 | L31: =L29-L30 -> 246 | M31: =M29-M30 -> 204 | N31: =N29-N30 -> 162 | O31: =O29-O30 -> 128 | P31: =P29-P30 -> 102
B33: Amortization Expense | L33: 54 | M33: 42 | N33: 42 | O33: 34 | P33: 26
A35: * | B35: Working Capital Schedule
B37: Current Assets | F37: Days | G37: 365
B38: Trade accounts receivable | H38: =Historicals!H77 -> 3512 | I38: =Historicals!I77 -> 3487 | J38: =Historicals!J77 -> 3410 | K38: =Historicals!K77 -> 3569 | L38: =Historicals!L11*Schedule!L42/days -> 3842.7862 | M38: =Historicals!M11*Schedule!M42/days -> 4179.1244 | N38: =Historicals!N11*Schedule!N42/days -> 4501.5755 | O38: =Historicals!O11*Schedule!O42/days -> 4800.4845 | P38: =Historicals!P11*Schedule!P42/days -> 5020.3801
B39: Inventories | H39: =Historicals!H78 -> 3414 | I39: =Historicals!I78 -> 4233 | J39: =Historicals!J78 -> 4424 | K39: =Historicals!K78 -> 4728 | L39: =Historicals!L15*Schedule!L43/days -> 5192.9365 | M39: =Historicals!M15*Schedule!M43/days -> 5647.4461 | N39: =Historicals!N15*Schedule!N43/days -> 6083.1893 | O39: =Historicals!O15*Schedule!O43/days -> 6487.119 | P39: =Historicals!P15*Schedule!P43/days -> 6784.2742
B41: Turnover Ratio (Days)
B42: Trade accounts receivable | I42: =AVERAGE(H38:I38)*days/Historicals!I11 -> 29.673315 | J42: =AVERAGE(I38:J38)*days/Historicals!J11 -> 27.492192 | K42: =AVERAGE(J38:K38)*days/Historicals!K11 -> 27.158827 | L42: =K42 -> 27.158827 | M42: =L42 -> 27.158827 | N42: =M42 -> 27.158827 | O42: =N42 -> 27.158827 | P42: =O42 -> 27.158827
B43: Inventories | I43: =AVERAGE(H39:I39)*days/Historicals!I15 -> 78.328422 | J43: =AVERAGE(I39:J39)*days/Historicals!J15 -> 85.562009 | K43: =AVERAGE(J39:K39)*days/Historicals!K15 -> 91.499945 | L43: =K43 -> 91.499945 | M43: =L43 -> 91.499945 | N43: =M43 -> 91.499945 | O43: =N43 -> 91.499945 | P43: =O43 -> 91.499945
B45: Prepaid expenses and other current assets | H45: =Historicals!H79 -> 2994 | I45: =Historicals!I79 -> 3240 | J45: =Historicals!J79 -> 5235 | K45: =Historicals!K79 -> 3129 | L45: =SUM(Historicals!L15,Historicals!L21)*Schedule!L46 -> 3488.0963 | M45: =SUM(Historicals!M15,Historicals!M21)*Schedule!M46 -> 3793.3905 | N45: =SUM(Historicals!N15,Historicals!N21)*Schedule!N46 -> 4086.0793 | O45: =SUM(Historicals!O15,Historicals!O21)*Schedule!O46 -> 4357.3988 | P45: =SUM(Historicals!P15,Historicals!P21)*Schedule!P46 -> 4556.998
B46: Prepaid expenses and other current assets % of (COGS & SG&A) | H46: =H45/SUM(Historicals!H15,Historicals!H21) -> 0.10867908 | I46: =I45/SUM(Historicals!I15,Historicals!I21) -> 0.10553402 | J46: =J45/SUM(Historicals!J15,Historicals!J21) -> 0.16133506 | K46: =K45/SUM(Historicals!K15,Historicals!K21) -> 0.095361453 | L46: =K46 -> 0.095361453 | M46: =L46 -> 0.095361453 | N46: =M46 -> 0.095361453 | O46: =N46 -> 0.095361453 | P46: =O46 -> 0.095361453
B48: Current Assets
B49: Accounts payable and accrued expenses | H49: =Historicals!H93 -> 14619 | I49: =Historicals!I93 -> 15749 | J49: =Historicals!J93 -> 15485 | K49: =Historicals!K93 -> 21715 | L49: =Historicals!L15*Schedule!L50 -> 17371.885 | M49: =Historicals!M15*Schedule!M50 -> 18892.352 | N49: =Historicals!N15*Schedule!N50 -> 20350.04 | O49: =Historicals!O15*Schedule!O50 -> 21701.302 | P49: =Historicals!P15*Schedule!P50 -> 22695.373
B50: Accounts payable and accrued expenses % of COGS | H50: =H49/Historicals!H15 -> 0.9486697 | I50: =I49/Historicals!I15 -> 0.88393108 | J50: =J49/Historicals!J15 -> 0.83861359 | K50: =K49/Historicals!K15 -> 1.1896023 | L50: =$J$50 -> 0.83861359 | M50: =$J$50 -> 0.83861359 | N50: =$J$50 -> 0.83861359 | O50: =$J$50 -> 0.83861359 | P50: =$J$50 -> 0.83861359
B52: Accrued income taxes | H52: =Historicals!H96 -> 686 | I52: =Historicals!I96 -> 1203 | J52: =Historicals!J96 -> 1569 | K52: =Historicals!K96 -> 1387 | L52: =Historicals!L44*Schedule!L53 -> 1425.6457 | M52: =Historicals!M44*Schedule!M53 -> 1560.8616 | N52: =Historicals!N44*Schedule!N53 -> 1690.689 | O52: =Historicals!O44*Schedule!O53 -> 1812.9892 | P52: =Historicals!P44*Schedule!P53 -> 1905.9711
B53: Accrued income taxes % of Taxes | H53: =H52/Historicals!H44 -> 0.29722704 | I53: =I52/Historicals!I44 -> 0.47269155 | J53: =J52/Historicals!J44 -> 0.57325539 | K53: =K52/Historicals!K44 -> 0.48632539 | L53: =K53 -> 0.48632539 | M53: =L53 -> 0.48632539 | N53: =M53 -> 0.48632539 | O53: =N53 -> 0.48632539 | P53: =O53 -> 0.48632539
A55: * | B55: Debt Schedule
B57: Long Term Debt
B58: Opening Balance | L58: 43023 | M58: =L61 -> 43405.413 | N58: =M61 -> 44200.128 | O58: =N61 -> 44414.914 | P58: =O61 -> 43941.592
B59: (+) Issuance of new Debt | L59: =L61+L60-L58 -> 1030.4127 | M59: =M61+M60-M58 -> 2597.7152 | N59: =N61+N60-N58 -> 5278.7862 | O59: =O61+O60-O58 -> 2312.6782 | P59: =P61+P60-P58 -> 1124.7739
B60: (-) Debt Repaid | L60: 648 | M60: 1803 | N60: 5064 | O60: 2786 | P60: 2684
B61: Closing Balance | L61: =L65*Historicals!L62 -> 43405.413 | M61: =M65*Historicals!M62 -> 44200.128 | N61: =N65*Historicals!N62 -> 44414.914 | O61: =O65*Historicals!O62 -> 43941.592 | P61: =P65*Historicals!P62 -> 42382.366
B63: Avg Int Rate | L63: 0.034 | M63: 0.034 | N63: 0.034 | O63: 0.034 | P63: 0.034
B64: Int Expenses | L64: =AVERAGE(L58,L61)*L63 -> 1469.283 | M64: =AVERAGE(M58,M61)*M63 -> 1489.2942 | N64: =AVERAGE(N58,N61)*N63 -> 1506.4557 | O64: =AVERAGE(O58,O61)*O63 -> 1502.0606 | P64: =AVERAGE(P58,P61)*P63 -> 1467.5073
B65: Total LT Debt / EBITDA | L65: =Assumptions!K64 -> 2.670343 | M65: =Assumptions!L64 -> 2.5027573 | N65: =Assumptions!M64 -> 2.3351715 | O65: =Assumptions!N64 -> 2.1675858 | P65: =Assumptions!O64 -> 2
B67: Loans and Note Payables
B68: Opening Balance | L68: =K71 -> 1499 | M68: =L71 -> 1512.324 | N68: =M71 -> 1540.0133 | O68: =N71 -> 1547.4968 | P68: =O71 -> 1531.0054
B69: (+) Issuance of new Debt | L69: =IF(L71>L68,L71-L68,0) -> 13.323958 | M69: =IF(M71>M68,M71-M68,0) -> 27.689332 | N69: =IF(N71>N68,N71-N68,0) -> 7.4835449 | O69: =IF(O71>O68,O71-O68,0) -> 0 | P69: =IF(P71>P68,P71-P68,0) -> 0
B70: (-) Debt Repaid | L70: 0 | M70: 0 | N70: 0 | O70: =MAX(0,O68+O69-O71) -> 16.491398 | P70: =MAX(0,P68+P69-P71) -> 54.326289
B71: Closing Balance | K71: =Historicals!K94 -> 1499 | L71: =L61*Assumptions!K66 -> 1512.324 | M71: =M61*Assumptions!L66 -> 1540.0133 | N71: =N61*Assumptions!M66 -> 1547.4968 | O71: =O61*Assumptions!N66 -> 1531.0054 | P71: =P61*Assumptions!O66 -> 1476.6791
B73: Avg Int Rate | L73: 0.05 | M73: 0.05 | N73: 0.05 | O73: 0.05 | P73: 0.05
B74: Int Expenses | L74: =AVERAGE(L68,L71)*L73 -> 75.283099 | M74: =AVERAGE(M68,M71)*M73 -> 76.308431 | N74: =AVERAGE(N68,N71)*N73 -> 77.187753 | O74: =AVERAGE(O68,O71)*O73 -> 76.962557 | P74: =AVERAGE(P68,P71)*P73 -> 75.192115

Sheet Valuation->

Sheet Beta
B2: Levered Beta
C4: NYSE | E4: The Coca-Cola Company | G4: Monster Beverage Corporation | I4: PepsiCo, Inc. | K4: Keurig Dr Pepper Inc.
B6: Beta | D6: =_xlfn.COVARIANCE.S($D$9:$D$269,D9:D269)/_xlfn.VAR.S($D$9:$D$269,D9:D269) -> 1.0019231 | F6: =_xlfn.COVARIANCE.S($D$9:$D$269,F9:F269)/_xlfn.VAR.S($D$9:$D$269,F9:F269) -> 0.4346445 | H6: =_xlfn.COVARIANCE.S($D$9:$D$269,H9:H269)/_xlfn.VAR.S($D$9:$D$269,H9:H269) -> 0.32854974 | J6: =_xlfn.COVARIANCE.S($D$9:$D$269,J9:J269)/_xlfn.VAR.S($D$9:$D$269,J9:J269) -> 0.3385208 | L6: =_xlfn.COVARIANCE.S($D$9:$D$269,L9:L269)/_xlfn.VAR.S($D$9:$D$269,L9:L269) -> 0.27251843
B7: Date | C7: Price | D7: Market Returns | E7: Price | F7: Market Returns | G7: Price | H7: Market Returns | I7: Price | J7: Market Returns | K7: Price | L7: Market Returns
B8: 46061 | C8: 23326.1 | E8: 78.68 | G8: 81.48 | I8: 165.94 | K8: 29.69
B9: 46054 | C9: 23252.8 | D9: =C9/C8-1 -> -0.0031424027 | E9: 79.03 | F9: =E9/E8-1 -> 0.0044483986 | G9: 82.54 | H9: =G9/G8-1 -> 0.013009327 | I9: 170.49 | J9: =I9/I8-1 -> 0.027419549 | K9: 28.41 | L9: =K9/K8-1 -> -0.043112159
B10: 46047 | C10: 22719.3 | D10: =C10/C9-1 -> -0.022943473 | E10: 74.81 | F10: =E10/E9-1 -> -0.053397444 | G10: 80.76 | H10: =G10/G9-1 -> -0.021565302 | I10: 153.63 | J10: =I10/I9-1 -> -0.098891431 | K10: 27.44 | L10: =K10/K9-1 -> -0.034142907
B11: 46040 | C11: 22757.2 | D11: =C11/C10-1 -> 0.0016681852 | E11: 72.88 | F11: =E11/E10-1 -> -0.02579869 | G11: 82 | H11: =G11/G10-1 -> 0.015354136 | I11: 144.58 | J11: =I11/I10-1 -> -0.058907765 | K11: 27.76 | L11: =K11/K10-1 -> 0.011661808
B12: 46033 | C12: 22807.1 | D12: =C12/C11-1 -> 0.0021927126 | E12: 70.44 | F12: =E12/E11-1 -> -0.033479693 | G12: 78.17 | H12: =G12/G11-1 -> -0.046707317 | I12: 146.32 | J12: =I12/I11-1 -> 0.01203486 | K12: 27.41 | L12: =K12/K11-1 -> -0.012608069
B13: 46026 | C13: 22591.7 | D13: =C13/C12-1 -> -0.0094444274 | E13: 70.51 | F13: =E13/E12-1 -> 0.00099375355 | G13: 77.34 | H13: =G13/G12-1 -> -0.010617884 | I13: 139.91 | J13: =I13/I12-1 -> -0.043808092 | K13: 27.79 | L13: =K13/K12-1 -> 0.013863553
B14: 46019 | C14: 22233.8 | D14: =C14/C13-1 -> -0.015842101 | E14: 69.12 | F14: =E14/E13-1 -> -0.019713516 | G14: 76.16 | H14: =G14/G13-1 -> -0.015257305 | I14: 142.23 | J14: =I14/I13-1 -> 0.016582088 | K14: 27.73 | L14: =K14/K13-1 -> -0.00215905
B15: 46012 | C15: 22246.6 | D15: =C15/C14-1 -> 0.00057570006 | E15: 69.87 | F15: =E15/E14-1 -> 0.010850694 | G15: 77.31 | H15: =G15/G14-1 -> 0.01509979 | I15: 143.78 | J15: =I15/I14-1 -> 0.010897842 | K15: 28.1 | L15: =K15/K14-1 -> 0.01334295
B16: 46005 | C16: 21923.9 | D16: =C16/C15-1 -> -0.014505587 | E16: 70.06 | F16: =E16/E15-1 -> 0.0027193359 | G16: 76.26 | H16: =G16/G15-1 -> -0.013581684 | I16: 148.16 | J16: =I16/I15-1 -> 0.030463208 | K16: 27.89 | L16: =K16/K15-1 -> -0.0074733096
B17: 45998 | C17: 22004.3 | D17: =C17/C16-1 -> 0.0036672307 | E17: 70.52 | F17: =E17/E16-1 -> 0.0065658007 | G17: 73.97 | H17: =G17/G16-1 -> -0.030028849 | I17: 150.65 | J17: =I17/I16-1 -> 0.016806156 | K17: 29.51 | L17: =K17/K16-1 -> 0.058085335
B18: 45991 | C18: 21810.1 | D18: =C18/C17-1 -> -0.0088255477 | E18: 70 | F18: =E18/E17-1 -> -0.0073737947 | G18: 73.74 | H18: =G18/G17-1 -> -0.0031093687 | I18: 145.02 | J18: =I18/I17-1 -> -0.037371391 | K18: 28.69 | L18: =K18/K17-1 -> -0.027787191
B19: 45984 | C19: 21824.7 | D19: =C19/C18-1 -> 0.00066941463 | E19: 73.12 | F19: =E19/E18-1 -> 0.044571429 | G19: 74.99 | H19: =G19/G18-1 -> 0.016951451 | I19: 148.74 | J19: =I19/I18-1 -> 0.025651634 | K19: 27.9 | L19: =K19/K18-1 -> -0.027535727
B20: 45977 | C20: 21177 | D20: =C20/C19-1 -> -0.029677384 | E20: 72.95 | F20: =E20/E19-1 -> -0.0023249453 | G20: 72.04 | H20: =G20/G19-1 -> -0.039338578 | I20: 146.33 | J20: =I20/I19-1 -> -0.01620277 | K20: 27.74 | L20: =K20/K19-1 -> -0.005734767
... B269: 44234 | C269: 15369.6 | D269: =C269/C268-1 -> 0.0004491398 | E269: 50.69 | F269: =E269/E268-1 -> 0.011574536 | G269: 45.87 | H269: =G269/G268-1 -> 0.023198751 | I269: 133.87 | J269: =I269/I268-1 -> 0.010263376 | K269: 31.77 | L269: =K269/K268-1 -> 0.016965429

Sheet WACC
B2: The Coca-Cola Company
B3: WACC
B4: (in Millions, except per share data)
A6: * | B6: Weighted Average Cost of Capital
B8: Calculation of Market Returns | F8: Cost of Debt
B9: Date | C9: Year | D9: Index Value | F9: (Yield of Coca-Cola Bond) | I9: (Using Credit Ratings)
B10: 25600 | C10: 1970 | D10: 529.7 | F10: CMP | G10: 123.597 | I10: Risk Free Rate | J10: =WACC!E28 -> 0.04054
B11: 46070 | C11: 2026 | D11: 23326.1 | F11: Face Value | G11: 100 | I11: Risk Premium 2 | J11: 0.007
F12: Maturity Year | G12: 70704 | I12: Cost of Debt | J12: =J10+J11 -> 0.04754
B13: Total Years | D13: =YEARFRAC(B10,B11,1) -> 56.044479 | F13: Total Years | G13: =YEARFRAC(FCFF!E8,WACC!G12,1) -> 67.576303
B14: CAGR | D14: =(D11/D10)^(1/D13)-1 -> 0.069868726 | F14: Coupon Rate | G14: 0.07375 | I14: Tax Rate (%) | J14: 0.25
F15: YTM | G15: =RATE(G13,(G11*G14),-G10,G11,0) -> 0.05943568 | I15: Post Tax Cost of Debt | J15: =G15*(1-J14) -> 0.04457676
B17: Un-Levered Beta
B18: Name | E18: Levered Beta | F18: Market Cap | G18: Debt | H18: Total Capital | I18: Un-Levered Beta
B19: The Coca-Cola Company | E19: =Beta!F6 -> 0.4346445 | F19: 338451 | G19: 28534 | H19: =SUM(F19:G19) -> 366985 | I19: =E19/(G19*(1-FCFF!$E$10)+F19)*F19 -> 0.40879603
B20: Monster Beverage Corporation | E20: =Beta!H6 -> 0.32854974 | F20: 79608 | G20: -3116 | H20: =SUM(F20:G20) -> 76492 | I20: =E20/(G20*(1-FCFF!$E$10)+F20)*F20 -> 0.33848647
B21: PepsiCo, Inc. | E21: =Beta!J6 -> 0.3385208 | F21: 226782 | G21: 38827 | H21: =SUM(F21:G21) -> 265609 | I21: =E21/(G21*(1-FCFF!$E$10)+F21)*F21 -> 0.29999902
B22: Keurig Dr Pepper Inc. | E22: =Beta!L6 -> 0.27251843 | F22: 40336 | G22: 12981 | H22: =SUM(F22:G22) -> 53317 | I22: =E22/(G22*(1-FCFF!$E$10)+F22)*F22 -> 0.21953104
E24: Un-Levered Beta | F24: Market Cap | G24: Debt | H24: Total Capital | I24: Levered Beta
B25: Levered Beta | E25: =AVERAGE(I19:I22) -> 0.31670314 | F25: =F19 -> 338451 | G25: =G19 -> 28534 | H25: =H19 -> 366985 | I25: =(E25/F25)*(G25*(1-J14)+WACC!F25) -> 0.33672851
B27: Cost of Equity
B28: Risk Free Rate1 | E28: 0.04054
B29: Equity Risk Premium | E29: 0.0446
B30: Market Premium | E30: =D14 -> 0.069868726
B31: Levered Beta | E31: =I25 -> 0.33672851
B32: Cost of Equity | E32: =E28+(E30+E29-E28)*E31 -> 0.06543391
B34: WACC | E34: =E32*(F25/H25)+J15*(G25/H25) -> 0.063812214
B37: Note:
B38: 1 - U-S 10 Year Bond Yield
B39: 2 - Aswath Damodaran Credit Rating (S&P bond ratings classes)

Sheet FCFF
B1: The Coca-Cola Company
B2: FCFF
B3: (in Millions, except per share data)
B4: Date | F4: =Schedule!L5 -> 46022 | G4: =Schedule!M5 -> 46387 | H4: =Schedule!N5 -> 46752 | I4: =Schedule!O5 -> 47118 | J4: =Schedule!P5 -> 47483
B5: Actual / Forecast | F5: Forecast | G5: Forecast | H5: Forecast | I5: Forecast | J5: Forecast
B7: Valuation Parameters
B8: Valuation as on Specified Date | E8: 46022 | G8: Implied Share Price | I8: =F33 -> 83.889061
B9: Date of Year Ending | E9: 46022 | G9: Current Share Price | I9: 70.07
B10: Marginal Tax Rate % | E10: 0.25 | G10: Premium (Discount) | I10: =I9/I8-1 -> -0.16473019
B11: WACC | E11: =WACC!E34 -> 0.063812214
B12: Terminal Growth Rate | E12: 0.02
A14: * | B14: FCFF
B15: EBIT | F15: =Historicals!L27 -> 15067.342 | G15: =Historicals!M27 -> 16386.105 | H15: =Historicals!N27 -> 17650.417 | I15: =Historicals!O27 -> 18822.422 | J15: =Historicals!P27 -> 19684.62
B16: Tax Rate % | F16: =tax_rate -> 0.25 | G16: =tax_rate -> 0.25 | H16: =tax_rate -> 0.25 | I16: =tax_rate -> 0.25 | J16: =tax_rate -> 0.25
B17: (-) Income Taxes | F17: =F15*F16 -> 3766.8356 | G17: =G15*G16 -> 4096.5263 | H17: =H15*H16 -> 4412.6043 | I17: =I15*I16 -> 4705.6054 | J17: =J15*J16 -> 4921.1549
B18: NOPAT | F18: =F15-F17 -> 11300.507 | G18: =G15-G17 -> 12289.579 | H18: =H15-H17 -> 13237.813 | I18: =I15-I17 -> 14116.816 | J18: =J15-J17 -> 14763.465
B19: (+) Depreciation & Amortisation | F19: =Schedule!L17 -> 1187.2785 | G19: =Schedule!M17 -> 1274.4682 | H19: =Schedule!N17 -> 1369.5625 | I19: =Schedule!O17 -> 1449.7139 | J19: =Schedule!P17 -> 1506.5634
B20: (+) / (-) Changes in WC | F20: =SUM(Historicals!L122:L126) -> -5402.2885 | G20: =SUM(Historicals!M122:M126) -> 559.54087 | H20: =SUM(Historicals!N122:N126) -> 536.63226 | I20: =SUM(Historicals!O122:O126) -> 499.40428 | J20: =SUM(Historicals!P122:P126) -> 370.4025
B21: (-) Capex | F21: =Schedule!L11 -> 2716.4115 | G21: =Schedule!M11 -> 1977.1289 | H21: =Schedule!N11 -> 1895.4944 | I21: =Schedule!O11 -> 1757.1046 | J21: =Schedule!P11 -> 1292.633
B22: FCFF | F22: =SUM(F18:F21) -> 9801.9081 | G22: =SUM(G18:G21) -> 16100.717 | H22: =SUM(H18:H21) -> 17039.502 | I22: =SUM(I18:I21) -> 17823.039 | J22: =SUM(J18:J21) -> 17933.064
B24: Discount Rate | F24: =10% -> 0.1 | G24: =F24+1 -> 1.1 | H24: =G24+1 -> 2.1 | I24: =H24+1 -> 3.1 | J24: =I24+1 -> 4.1
B25: Terminal value | J25: =J22*(1+terminal_growth)/(wacc-terminal_growth) -> 417502.87
B26: PV of FCFF | F26: =F22/(1+wacc)^F24 -> 9741.4618 | G26: =G22/(1+wacc)^G24 -> 15041.59 | H26: =H22/(1+wacc)^H24 -> 14963.75 | I26: =I22/(1+wacc)^I24 -> 14712.97 | J26: =(J22+J25)/(1+wacc)^J24 -> 337891.97
B27: PV of Enterprise value | F27: =+SUM(F26:J26) -> 392351.75
B28: Add: Cash | F28: =Historicals!K72 -> 10828
B29: Add: Investment & Securities | F29: =Historicals!K73+Historicals!K76 -> 3743
B30: Less: Debt | F30: =Historicals!K99+Historicals!K94+Historicals!K95 -> 44522
B31: PV of Equity Value | F31: =F27+F28+F29-F30 -> 362400.75
B32: No. of Shares outstanding | F32: =Historicals!K51 -> 4320
B33: Price Per Share | F33: =F31/F32 -> 83.889061
A35: * | B35: Sensitivity Table
B37: WACC | D37: Terminal Value %
C38: =F33 -> 83.889061 | D38: 0 | E38: =D38+1% -> 0.01 | F38: =E38+1% -> 0.02 | G38: =F38+1% -> 0.03 | H38: =G38+1% -> 0.04
C39: =C40+1% -> 0.08 | D39: 46.224537 | E39: 52.063949 | F39: 59.849831 | G39: 70.750065 | H39: 87.100417
C40: =C42+2% -> 0.07 | D40: 53.629311 | E40: 61.642986 | F40: 72.862131 | G40: 89.69085 | H40: 117.73871
C41: 0.0638 | D41: 59.387159 | E41: 69.371096 | F41: 83.913909 | G41: 107.06194 | H41: 149.66209
C42: =C43+1% -> 0.05 | D42: 77.333588 | E42: 95.176015 | F42: 124.91339 | G42: 184.38815 | H42: 362.81242
C43: 0.04 | D43: 98.080761 | E43: 128.71352 | F43: 189.97905 | G43: 373.77561 | H43: #DIV/0!

Sheet Ratio Analysis
B2: The Coca-Cola Company
B3: Ratio Analysis
B4: (in Millions, except per share data)
B5: Date | E5: 44561 | F5: =EDATE(E5,12) -> 44926 | G5: =EDATE(F5,12) -> 45291 | H5: =EDATE(G5,12) -> 45657 | I5: =EDATE(H5,12) -> 46022 | J5: =EDATE(I5,12) -> 46387 | K5: =EDATE(J5,12) -> 46752 | L5: =EDATE(K5,12) -> 47118 | M5: =EDATE(L5,12) -> 47483
B6: Actual / Forecast | E6: Actual | F6: Actual | G6: Actual | H6: Actual | I6: Forecast | J6: Forecast | K6: Forecast | L6: Forecast | M6: Forecast
A8: 1 | B8: Profitability Ratio | E8: 2021 | F8: =E8+1 -> 2022 | G8: =F8+1 -> 2023 | H8: =G8+1 -> 2024 | I8: =H8+1 -> 2025 | J8: =I8+1 -> 2026 | K8: =J8+1 -> 2027 | L8: =K8+1 -> 2028 | M8: =L8+1 -> 2029
B10: Gross Margin | E10: =Historicals!H17/Historicals!H$11 -> 0.60137617 | F10: =Historicals!I17/Historicals!I$11 -> 0.58609395 | G10: =Historicals!J17/Historicals!J$11 -> 0.59669317 | H10: =Historicals!K17/Historicals!K$11 -> 0.61076401 | I10: =Historicals!L17/Historicals!L$11 -> 0.59889603 | J10: =Historicals!M17/Historicals!M$11 -> 0.59889603 | K10: =Historicals!N17/Historicals!N$11 -> 0.59889603 | L10: =Historicals!O17/Historicals!O$11 -> 0.59889603 | M10: =Historicals!P17/Historicals!P$11 -> 0.59889603
B11: EBITDA Margin | E11: =Historicals!H62/Historicals!H$11 -> 0.32492628 | F11: =Historicals!I62/Historicals!I$11 -> 0.31605724 | G11: =Historicals!J62/Historicals!J$11 -> 0.31591822 | H11: =Historicals!K62/Historicals!K$11 -> 0.32326162 | I11: =Historicals!L62/Historicals!L$11 -> 0.3147377 | J11: =Historicals!M62/Historicals!M$11 -> 0.31443989 | K11: =Historicals!N62/Historicals!N$11 -> 0.31438632 | L11: =Historicals!O62/Historicals!O$11 -> 0.3142191 | M11: =Historicals!P62/Historicals!P$11 -> 0.31407744
B12: EBIT Margin | E12: =Historicals!H27/Historicals!H$11 -> 0.28736613 | F12: =Historicals!I27/Historicals!I$11 -> 0.28678623 | G12: =Historicals!J27/Historicals!J$11 -> 0.2912808 | H12: =Historicals!K27/Historicals!K$11 -> 0.30033904 | I12: =Historicals!L27/Historicals!L$11 -> 0.29174846 | J12: =Historicals!M27/Historicals!M$11 -> 0.29174846 | K12: =Historicals!N27/Historicals!N$11 -> 0.29174846 | L12: =Historicals!O27/Historicals!O$11 -> 0.29174846 | M12: =Historicals!P27/Historicals!P$11 -> 0.29174846
B13: PBT Margin | E13: =Historicals!H41/Historicals!H$11 -> 0.32145998 | F13: =Historicals!I41/Historicals!I$11 -> 0.31076058 | G13: =Historicals!J41/Historicals!J$11 -> 0.31458588 | H13: =Historicals!K41/Historicals!K$11 -> 0.32695055 | I13: =Historicals!L41/Historicals!L$11 -> 0.30192057 | J13: =Historicals!M41/Historicals!M$11 -> 0.30395298 | K13: =Historicals!N41/Historicals!N$11 -> 0.30565148 | L13: =Historicals!O41/Historicals!O$11 -> 0.30735301 | M13: =Historicals!P41/Historicals!P$11 -> 0.30896339
B14: PAT Margin | E14: =Historicals!H45/Historicals!H$11 -> 0.26175695 | F14: =Historicals!I45/Historicals!I$11 -> 0.25163778 | G14: =Historicals!J45/Historicals!J$11 -> 0.25480517 | H14: =Historicals!K45/Historicals!K$11 -> 0.26613643 | I14: =Historicals!L45/Historicals!L$11 -> 0.24515871 | J14: =Historicals!M45/Historicals!M$11 -> 0.24680903 | K14: =Historicals!N45/Historicals!N$11 -> 0.24818821 | L14: =Historicals!O45/Historicals!O$11 -> 0.24956984 | M14: =Historicals!P45/Historicals!P$11 -> 0.25087746
B16: ROE | E16: =Historicals!H48/Historicals!H105 -> 0.40571199 | F16: =Historicals!I48/Historicals!I105 -> 0.41829939 | G16: =Historicals!J48/Historicals!J105 -> 0.42492722 | H16: =Historicals!K48/Historicals!K105 -> 0.47258456 | I16: =Historicals!L48/Historicals!L105 -> 0.41484514 | J16: =Historicals!M48/Historicals!M105 -> 0.39692502 | K16: =Historicals!N48/Historicals!N105 -> 0.37915119 | L16: =Historicals!O48/Historicals!O105 -> 0.36140387 | M16: =Historicals!P48/Historicals!P105 -> 0.34099969
B17: ROA | E17: =Historicals!H48/Historicals!H86 -> 1.0167339 | F17: =Historicals!I48/Historicals!I86 -> 1.0977543 | G17: =Historicals!J48/Historicals!J86 -> 1.2642919 | H17: =Historicals!K48/Historicals!K86 -> 1.2096477 | I17: =Historicals!L48/Historicals!L86 -> 1.0637577 | J17: =Historicals!M48/Historicals!M86 -> 1.0964284 | K17: =Historicals!N48/Historicals!N86 -> 1.1369041 | L17: =Historicals!O48/Historicals!O86 -> 1.18808 | M17: =Historicals!P48/Historicals!P86 -> 1.2667135
B18: ROCE | E18: =Historicals!H48/(Historicals!H90-Historicals!H97) -> 0.13555723 | F18: =Historicals!I48/(Historicals!I90-Historicals!I97) -> 0.14790728 | G18: =Historicals!J48/(Historicals!J90-Historicals!J97) -> 0.15751632 | H18: =Historicals!K48/(Historicals!K90-Historicals!K97) -> 0.16551129 | I18: =Historicals!L48/(Historicals!L90-Historicals!L97) -> 0.16079479 | J18: =Historicals!M48/(Historicals!M90-Historicals!M97) -> 0.17186511 | K18: =Historicals!N48/(Historicals!N90-Historicals!N97) -> 0.1709875 | L18: =Historicals!O48/(Historicals!O90-Historicals!O97) -> 0.17424526 | M18: =Historicals!P48/(Historicals!P90-Historicals!P97) -> 0.17164893
B19: ROIC | I19: =Historicals!L48/(Historicals!L86+SUM(Historicals!L122:L126)) -> 1.9500723 | J19: =Historicals!M48/(Historicals!M86+SUM(Historicals!M122:M126)) -> 1.0499174 | K19: =Historicals!N48/(Historicals!N86+SUM(Historicals!N122:N126)) -> 1.0924859 | L19: =Historicals!O48/(Historicals!O86+SUM(Historicals!O122:O126)) -> 1.1458184 | M19: =Historicals!P48/(Historicals!P86+SUM(Historicals!P122:P126)) -> 1.2325221
A21: 2 | B21: Liquiditiy Ratio | E21: 2021 | F21: =E21+1 -> 2022 | G21: =F21+1 -> 2023 | H21: =G21+1 -> 2024 | I21: =H21+1 -> 2025 | J21: =I21+1 -> 2026 | K21: =J21+1 -> 2027 | L21: =K21+1 -> 2028 | M21: =L21+1 -> 2029
B23: Current Ratio | E23: =Historicals!H80/Historicals!H97 -> 1.1300752 | F23: =Historicals!I80/Historicals!I97 -> 1.1453559 | G23: =Historicals!J80/Historicals!J97 -> 1.1341055 | H23: =Historicals!K80/Historicals!K97 -> 1.0296249 | I23: =Historicals!L80/Historicals!L97 -> 0.6442777 | J23: =Historicals!M80/Historicals!M97 -> 0.56705594 | K23: =Historicals!N80/Historicals!N97 -> 0.6215858 | L23: =Historicals!O80/Historicals!O97 -> 0.62634125 | M23: =Historicals!P80/Historicals!P97 -> 0.69348249
B24: Quick Ratio | E24: =(Historicals!H80-Historicals!H78-Historicals!H79)/Historicals!H97 -> 0.80887218 | F24: =(Historicals!I80-Historicals!I78-Historicals!I79)/Historicals!I97 -> 0.76647739 | G24: =(Historicals!J80-Historicals!J78-Historicals!J79)/Historicals!J97 -> 0.72432226 | H24: =(Historicals!K80-Historicals!K78-Historicals!K79)/Historicals!K97 -> 0.71844429 | I24: =(Historicals!L80-Historicals!L78-Historicals!L79)/Historicals!L97 -> 0.25169913 | J24: =(Historicals!M80-Historicals!M78-Historicals!M79)/Historicals!M97 -> 0.21813486 | K24: =(Historicals!N80-Historicals!N78-Historicals!N79)/Historicals!N97 -> 0.23600979 | L24: =(Historicals!O80-Historicals!O78-Historicals!O79)/Historicals!O97 -> 0.23525604 | M24: =(Historicals!P80-Historicals!P78-Historicals!P79)/Historicals!P97 -> 0.25858479
B25: Cash Ratio | E25: =Historicals!H74/Historicals!H97 -> 0.54766917 | F25: =Historicals!I74/Historicals!I97 -> 0.53548976 | G25: =Historicals!J74/Historicals!J97 -> 0.52450045 | H25: =Historicals!K74/Historicals!K97 -> 0.50885184 | I25: =Historicals!L74/Historicals!L97 -> 0.47117734 | J25: =Historicals!M74/Historicals!M97 -> 0.57321909 | K25: =Historicals!N74/Historicals!N97 -> 0.77460549 | L25: =Historicals!O74/Historicals!O97 -> 0.90397469 | M25: =Historicals!P74/Historicals!P97 -> 1.1168405
B26: Operating Cash Flow | E26: - | F26: - | G26: - | H26: - | I26: =Historicals!L127/Historicals!L97 -> 0.35820195 | J26: =Historicals!M127/Historicals!M97 -> 0.55477281 | K26: =Historicals!N127/Historicals!N97 -> 0.60969204 | L26: =Historicals!O127/Historicals!O97 -> 0.61464254 | M26: =Historicals!P127/Historicals!P97 -> 0.67652592
B27: Net Working Capital | E27: =Historicals!H80-Historicals!H97 -> 2595 | F27: =Historicals!I80-Historicals!I97 -> 2867 | G27: =Historicals!J80-Historicals!J97 -> 3161 | H27: =Historicals!K80-Historicals!K97 -> 748 | I27: =Historicals!L80-Historicals!L97 -> -7866.0355 | J27: =Historicals!M80-Historicals!M97 -> -11714.266 | K27: =Historicals!N80-Historicals!N97 -> -9980.3815 | L27: =Historicals!O80-Historicals!O97 -> -10361.294 | M27: =Historicals!P80-Historicals!P97 -> -7993.3706
B28: Net Working Capital % Revenue | E28: =E27/Historicals!H11 -> 0.067127115 | F28: =F27/Historicals!I11 -> 0.066603169 | G28: =G27/Historicals!J11 -> 0.069041587 | H28: =H27/Historicals!K11 -> 0.015949848 | I28: =I27/Historicals!L11 -> -0.15230979 | J28: =J27/Historicals!M11 -> -0.20856811 | K28: =K27/Historicals!N11 -> -0.16496839 | L28: =L27/Historicals!O11 -> -0.16060057 | M28: =M27/Historicals!P11 -> -0.11847085
A30: 3 | B30: Efficiency Ratio | E30: 2021 | F30: =E30+1 -> 2022 | G30: =F30+1 -> 2023 | H30: =G30+1 -> 2024 | I30: =H30+1 -> 2025 | J30: =I30+1 -> 2026 | K30: =J30+1 -> 2027 | L30: =K30+1 -> 2028 | M30: =L30+1 -> 2029
B32: Asset Turnover | E32: =Historicals!H11/Historicals!H90 -> 0.40971236 | F32: =Historicals!I11/Historicals!I90 -> 0.46404278 | G32: =Historicals!J11/Historicals!J90 -> 0.46860383 | H32: =Historicals!K11/Historicals!K90 -> 0.46640941 | I32: =Historicals!L11/Historicals!L90 -> 0.51262034 | J32: =Historicals!M11/Historicals!M90 -> 0.52180436 | K32: =Historicals!N11/Historicals!N90 -> 0.53007149 | L32: =Historicals!O11/Historicals!O90 -> 0.53740117 | M32: =Historicals!P11/Historicals!P90 -> 0.54144668
B33: Fixed Asset Turnover Ratio | E33: =Historicals!H11/Historicals!H86 -> 3.8969758 | F33: =Historicals!I11/Historicals!I86 -> 4.374149 | G33: =Historicals!J11/Historicals!J86 -> 4.9571243 | H33: =Historicals!K11/Historicals!K86 -> 4.551781 | I33: =Historicals!L11/Historicals!L86 -> 4.3449771 | J33: =Historicals!M11/Historicals!M86 -> 4.4466866 | K33: =Historicals!N11/Historicals!N86 -> 4.5836811 | L33: =Historicals!O11/Historicals!O86 -> 4.7647984 | M33: =Historicals!P11/Historicals!P86 -> 5.0531953
B34: Receivables Turnover | E34: =Historicals!H11/Historicals!H77 -> 11.007403 | F34: =Historicals!I11/Historicals!I77 -> 12.344709 | G34: =Historicals!J11/Historicals!J77 -> 13.426393 | H34: =Historicals!K11/Historicals!K77 -> 13.140095 | I34: =Historicals!L11/Historicals!L77 -> 13.439461 | J34: =Historicals!M11/Historicals!M77 -> 13.439461 | K34: =Historicals!N11/Historicals!N77 -> 13.439461 | L34: =Historicals!O11/Historicals!O77 -> 13.439461 | M34: =Historicals!P11/Historicals!P77 -> 13.439461
B35: Days Sales Outstanding (DSO) | E35: =(Historicals!H77/Historicals!H11)*365 -> 33.159501 | F35: =(Historicals!I77/Historicals!I11)*365 -> 29.567323 | G35: =(Historicals!J77/Historicals!J11)*365 -> 27.185261 | H35: =(Historicals!K77/Historicals!K11)*365 -> 27.777576 | I35: =(Historicals!L77/Historicals!L11)*365 -> 27.158827 | J35: =(Historicals!M77/Historicals!M11)*365 -> 27.158827 | K35: =(Historicals!N77/Historicals!N11)*365 -> 27.158827 | L35: =(Historicals!O77/Historicals!O11)*365 -> 27.158827 | M35: =(Historicals!P77/Historicals!P11)*365 -> 27.158827
B36: Inventory Turnover | E36: =Historicals!H11/Historicals!H78 -> 11.323374 | F36: =Historicals!I11/Historicals!I78 -> 10.169147 | G36: =Historicals!J11/Historicals!J78 -> 10.349005 | H36: =Historicals!K11/Historicals!K78 -> 9.9189932 | I36: =Historicals!L11/Historicals!L78 -> 9.9452354 | J36: =Historicals!M11/Historicals!M78 -> 9.9452354 | K36: =Historicals!N11/Historicals!N78 -> 9.9452354 | L36: =Historicals!O11/Historicals!O78 -> 9.9452354 | M36: =Historicals!P11/Historicals!P78 -> 9.9452354
B37: Days Inventory Outstanding (DIO) | E37: =(Historicals!H78/Historicals!H11)*365 -> 32.234208 | F37: =(Historicals!I78/Historicals!I11)*365 -> 35.892882 | G37: =(Historicals!J78/Historicals!J11)*365 -> 35.26909 | H37: =(Historicals!K78/Historicals!K11)*365 -> 36.798089 | I37: =(Historicals!L78/Historicals!L11)*365 -> 36.700992 | J37: =(Historicals!M78/Historicals!M11)*365 -> 36.700992 | K37: =(Historicals!N78/Historicals!N11)*365 -> 36.700992 | L37: =(Historicals!O78/Historicals!O11)*365 -> 36.700992 | M37: =(Historicals!P78/Historicals!P11)*365 -> 36.700992
B38: Payables Turnover | E38: =Historicals!H11/Historicals!H93 -> 2.6443669 | F38: =Historicals!I11/Historicals!I93 -> 2.7332529 | G38: =Historicals!J11/Historicals!J93 -> 2.9566677 | H38: =Historicals!K11/Historicals!K93 -> 2.1596592 | I38: =Historicals!L11/Historicals!L93 -> 2.9729057 | J38: =Historicals!M11/Historicals!M93 -> 2.9729057 | K38: =Historicals!N11/Historicals!N93 -> 2.9729057 | L38: =Historicals!O11/Historicals!O93 -> 2.9729057 | M38: =Historicals!P11/Historicals!P93 -> 2.9729057
B39: Days Payable Outstanding (DPO) | E39: =(Historicals!H93/Historicals!H11)*365 -> 138.02926 | F39: =(Historicals!I93/Historicals!I11)*365 -> 133.54051 | G39: =(Historicals!J93/Historicals!J11)*365 -> 123.44979 | H39: =(Historicals!K93/Historicals!K11)*365 -> 169.00815 | I39: =(Historicals!L93/Historicals!L11)*365 -> 122.7755 | J39: =(Historicals!M93/Historicals!M11)*365 -> 122.7755 | K39: =(Historicals!N93/Historicals!N11)*365 -> 122.7755 | L39: =(Historicals!O93/Historicals!O11)*365 -> 122.7755 | M39: =(Historicals!P93/Historicals!P11)*365 -> 122.7755
B40: Cash Conversion Cycle (CCC) | E40: =E34+E37-E39 -> -94.787646 | F40: =F34+F37-F39 -> -85.302924 | G40: =G34+G37-G39 -> -74.754303 | H40: =H34+H37-H39 -> -119.06996 | I40: =I34+I37-I39 -> -72.635052 | J40: =J34+J37-J39 -> -72.635052 | K40: =K34+K37-K39 -> -72.635052 | L40: =L34+L37-L39 -> -72.635052 | M40: =M34+M37-M39 -> -72.635052
B41: Working Capital Turnover | E41: =Historicals!H11/'Ratio Analysis'!E27 -> 14.89711 | F41: =Historicals!I11/'Ratio Analysis'!F27 -> 15.014301 | G41: =Historicals!J11/'Ratio Analysis'!G27 -> 14.484024 | H41: =Historicals!K11/'Ratio Analysis'!H27 -> 62.696524 | I41: =Historicals!L11/'Ratio Analysis'!I27 -> -6.5655661 | J41: =Historicals!M11/'Ratio Analysis'!J27 -> -4.7945968 | K41: =Historicals!N11/'Ratio Analysis'!K27 -> -6.0617672 | L41: =Historicals!O11/'Ratio Analysis'!L27 -> -6.2266279 | M41: =Historicals!P11/'Ratio Analysis'!M27 -> -8.4408952
A43: 4 | B43: Solvency Ratio | E43: 2021 | F43: =E43+1 -> 2022 | G43: =F43+1 -> 2023 | H43: =G43+1 -> 2024 | I43: =H43+1 -> 2025 | J43: =I43+1 -> 2026 | K43: =J43+1 -> 2027 | L43: =K43+1 -> 2028 | M43: =L43+1 -> 2029
B45: Debt to Equity | E45: =(Historicals!H97+SUM(Historicals!H99:H101))/Historicals!H105 -> 2.7954143 | F45: =(Historicals!I97+SUM(Historicals!I99:I101))/Historicals!I105 -> 2.5918454 | G45: =(Historicals!J97+SUM(Historicals!J99:J101))/Historicals!J105 -> 2.5554221 | H45: =(Historicals!K97+SUM(Historicals!K99:K101))/Historicals!K105 -> 2.812718 | I45: =(Historicals!L97+SUM(Historicals!L99:L101))/Historicals!L105 -> 2.3054831 | J45: =(Historicals!M97+SUM(Historicals!M99:M101))/Historicals!M105 -> 2.0850131 | K45: =(Historicals!N97+SUM(Historicals!N99:N101))/Historicals!N105 -> 1.8838226 | L45: =(Historicals!O97+SUM(Historicals!O99:O101))/Historicals!O105 -> 1.6970751 | M45: =(Historicals!P97+SUM(Historicals!P99:P101))/Historicals!P105 -> 1.5123838
B46: Debt to Assets | E46: =(Historicals!H97+SUM(Historicals!H99:H101))/Historicals!H90 -> 0.73652415 | F46: =(Historicals!I97+SUM(Historicals!I99:I101))/Historicals!I90 -> 0.72159158 | G46: =(Historicals!J97+SUM(Historicals!J99:J101))/Historicals!J90 -> 0.71873945 | H46: =(Historicals!K97+SUM(Historicals!K99:K101))/Historicals!K90 -> 0.73771992 | I46: =(Historicals!L97+SUM(Historicals!L99:L101))/Historicals!L90 -> 0.69747236 | J46: =(Historicals!M97+SUM(Historicals!M99:M101))/Historicals!M90 -> 0.67585227 | K46: =(Historicals!N97+SUM(Historicals!N99:N101))/Historicals!N90 -> 0.65323803 | L46: =(Historicals!O97+SUM(Historicals!O99:O101))/Historicals!O90 -> 0.62922798 | M46: =(Historicals!P97+SUM(Historicals!P99:P101))/Historicals!P90 -> 0.60197164
B47: Debt to EBITDA | E47: =(Historicals!H98+SUM(Historicals!H100:H102))/Historicals!H62 -> 0.90980018 | F47: =(Historicals!I98+SUM(Historicals!I100:I102))/Historicals!I62 -> 0.79647189 | G47: =(Historicals!J98+SUM(Historicals!J100:J102))/Historicals!J62 -> 0.76776825 | H47: =(Historicals!K98+SUM(Historicals!K100:K102))/Historicals!K62 -> 0.43225594 | I47: =(Historicals!L98+SUM(Historicals!L100:L102))/Historicals!L62 -> 0.4031469 | J47: =(Historicals!M98+SUM(Historicals!M100:M102))/Historicals!M62 -> 0.37105251 | K47: =(Historicals!N98+SUM(Historicals!N100:N102))/Historicals!N62 -> 0.34453244 | L47: =(Historicals!O98+SUM(Historicals!O100:O102))/Historicals!O62 -> 0.32325159 | M47: =(Historicals!P98+SUM(Historicals!P100:P102))/Historicals!P62 -> 0.30923238
B48: Equity Multiplier | E48: =Historicals!H90/Historicals!H105 -> 3.7954143 | F48: =Historicals!I90/Historicals!I105 -> 3.5918454 | G48: =Historicals!J90/Historicals!J105 -> 3.5554221 | H48: =Historicals!K90/Historicals!K105 -> 3.812718 | I48: =Historicals!L90/Historicals!L105 -> 3.3054831 | J48: =Historicals!M90/Historicals!M105 -> 3.0850131 | K48: =Historicals!N90/Historicals!N105 -> 2.8838226 | L48: =Historicals!O90/Historicals!O105 -> 2.6970751 | M48: =Historicals!P90/Historicals!P105 -> 2.5123838
B49: Interest Coverage Ratio (ICR) | E49: =Historicals!H27/Historicals!H32 -> 14.315722 | F49: =Historicals!I27/Historicals!I32 -> 13.625828 | G49: =Historicals!J27/Historicals!J32 -> 8.5927835 | H49: =Historicals!K27/Historicals!K32 -> 8.3789411 | I49: =Historicals!L27/Historicals!L32 -> 9.7550646 | J49: =Historicals!M27/Historicals!M32 -> 10.466324 | K49: =Historicals!N27/Historicals!N32 -> 11.145449 | L49: =Historicals!O27/Historicals!O32 -> 11.920295 | M49: =Historicals!P27/Historicals!P32 -> 12.759854
B50: Debt Service Coverage Ratio (DSCR) | I50: =Historicals!L62/(Historicals!L32+Schedule!L60+Schedule!L70) -> 7.4135145 | J50: =Historicals!M62/(Historicals!M32+Schedule!M60+Schedule!M70) -> 5.2427001 | K50: =Historicals!N62/(Historicals!N32+Schedule!N60+Schedule!N70) -> 2.8611612 | L50: =Historicals!O62/(Historicals!O32+Schedule!O60+Schedule!O70) -> 4.6267416 | M50: =Historicals!P62/(Historicals!P32+Schedule!P60+Schedule!P70) -> 4.9500247
A52: 5 | B52: Financial Ratios | E52: 2021 | F52: =E52+1 -> 2022 | G52: =F52+1 -> 2023 | H52: =G52+1 -> 2024 | I52: =H52+1 -> 2025 | J52: =I52+1 -> 2026 | K52: =J52+1 -> 2027 | L52: =K52+1 -> 2028 | M52: =L52+1 -> 2029
B54: Earnings Per Share (Diluted) | E54: =Historicals!H50 -> 2.3239631 | F54: =Historicals!I50 -> 2.4834483 | G54: =Historicals!J50 -> 2.6911731 | H54: =Historicals!K50 -> 2.8849537 | I54: =Historicals!L50 -> 2.9268439 | J54: =Historicals!M50 -> 3.2057317 | K54: =Historicals!N50 -> 3.4735383 | L54: =Historicals!O50 -> 3.7237826 | M54: =Historicals!P50 -> 3.9151375
B55: EPS Growth (%) | F55: =F54/E54-1 -> 0.068626365 | G55: =G54/F54-1 -> 0.083643701 | H55: =H54/G54-1 -> 0.072006005 | I55: =I54/H54-1 -> 0.014520232 | J55: =J54/I54-1 -> 0.095286202 | K55: =K54/J54-1 -> 0.083539916 | L55: =L54/K54-1 -> 0.072043059 | M55: =M54/L54-1 -> 0.051387232
B56: Dividend Per Share (DPS) | E56: =Historicals!H53 -> 1.6799539 | F56: =Historicals!I53 -> 1.76 | G56: =Historicals!J53 -> 1.8400553 | H56: =Historicals!K53 -> 1.9349537 | I56: =Historicals!L53 -> 1.9801979 | J56: =Historicals!M53 -> 2.1876656 | K56: =Historicals!N53 -> 2.3907743 | L56: =Historicals!O53 -> 2.5848304 | M56: =Historicals!P53 -> 2.7405963
B57: DPS Growth (%) | F57: =F56/E56-1 -> 0.047647785 | G57: =G56/F56-1 -> 0.045485973 | H57: =H56/G56-1 -> 0.051573662 | I57: =I56/H56-1 -> 0.023382568 | J57: =J56/I56-1 -> 0.10477121 | K57: =K56/J56-1 -> 0.092842645 | L57: =L56/K56-1 -> 0.081168733 | M57: =M56/L56-1 -> 0.060261534
B58: Dividend Payout Ratio | E58: =Historicals!H54 -> 0.7228832 | F58: =Historicals!I54 -> 0.70869203 | G58: =Historicals!J54 -> 0.68373726 | H58: =Historicals!K54 -> 0.67070529 | I58: =Historicals!L54 -> 0.67656423 | J58: =Historicals!M54 -> 0.68242317 | K58: =Historicals!N54 -> 0.68828212 | L58: =Historicals!O54 -> 0.69414106 | M58: =Historicals!P54 -> 0.7
B59: Retention Ratio | E59: =1-E58 -> 0.2771168 | F59: =1-F58 -> 0.29130797 | G59: =1-G58 -> 0.31626274 | H59: =1-H58 -> 0.32929471 | I59: =1-I58 -> 0.32343577 | J59: =1-J58 -> 0.31757683 | K59: =1-K58 -> 0.31171788 | L59: =1-L58 -> 0.30585894 | M59: =1-M58 -> 0.3
B60: Bookvalue Per Share | E60: =Historicals!H105/Historicals!H51 -> 5.7281106 | F60: =Historicals!I105/Historicals!I51 -> 5.9370115 | G60: =Historicals!J105/Historicals!J51 -> 6.3332565 | H60: =Historicals!K105/Historicals!K51 -> 6.1046296 | I60: =Historicals!L105/Historicals!L51 -> 7.0552687 | J60: =Historicals!M105/Historicals!M51 -> 8.0764164 | K60: =Historicals!N105/Historicals!N51 -> 9.1613542 | L60: =Historicals!O105/Historicals!O51 -> 10.30366 | M60: =Historicals!P105/Historicals!P51 -> 11.481352
B61: Revenue Per Share | E61: =Historicals!H11/Historicals!H51 -> 8.9073733 | F61: =Historicals!I11/Historicals!I51 -> 9.8956322 | G61: =Historicals!J11/Historicals!J51 -> 10.55174 | H61: =Historicals!K11/Historicals!K51 -> 10.855787 | I61: =Historicals!L11/Historicals!L51 -> 11.954856 | J61: =Historicals!M11/Historicals!M51 -> 13.001199 | K61: =Historicals!N11/Historicals!N51 -> 14.00434 | L61: =Historicals!O11/Historicals!O51 -> 14.934242 | M61: =Historicals!P11/Historicals!P51 -> 15.618334
B62: EBITDA Per Share | E62: =Historicals!H62/Historicals!H51 -> 2.8942396 | F62: =Historicals!I62/Historicals!I51 -> 3.1275862 | G62: =Historicals!J62/Historicals!J51 -> 3.333487 | H62: =Historicals!K62/Historicals!K51 -> 3.5092593 | I62: =Historicals!L62/Historicals!L51 -> 3.7626437 | J62: =Historicals!M62/Historicals!M51 -> 4.0880957 | K62: =Historicals!N62/Historicals!N51 -> 4.402773 | L62: =Historicals!O62/Historicals!O51 -> 4.692624 | M62: =Historicals!P62/Historicals!P51 -> 4.9053665
A64: 6 | B64: Dupoint Analysis | E64: 2021 | F64: =E64+1 -> 2022 | G64: =F64+1 -> 2023 | H64: =G64+1 -> 2024 | I64: =H64+1 -> 2025 | J64: =I64+1 -> 2026 | K64: =J64+1 -> 2027 | L64: =K64+1 -> 2028 | M64: =L64+1 -> 2029
B66: Net Profit Margin | E66: =E14 -> 0.26175695 | F66: =F14 -> 0.25163778 | G66: =G14 -> 0.25480517 | H66: =H14 -> 0.26613643 | I66: =I14 -> 0.24515871 | J66: =J14 -> 0.24680903 | K66: =K14 -> 0.24818821 | L66: =L14 -> 0.24956984 | M66: =M14 -> 0.25087746
B67: Asset Turnover | E67: =E32 -> 0.40971236 | F67: =F32 -> 0.46404278 | G67: =G32 -> 0.46860383 | H67: =H32 -> 0.46640941 | I67: =I32 -> 0.51262034 | J67: =J32 -> 0.52180436 | K67: =K32 -> 0.53007149 | L67: =L32 -> 0.53740117 | M67: =M32 -> 0.54144668
B68: Equity Multiplier | E68: =E48 -> 3.7954143 | F68: =F48 -> 3.5918454 | G68: =G48 -> 3.5554221 | H68: =H48 -> 3.812718 | I68: =I48 -> 3.3054831 | J68: =J48 -> 3.0850131 | K68: =K48 -> 2.8838226 | L68: =L48 -> 2.6970751 | M68: =M48 -> 2.5123838
B69: Dupoint Ratio | E69: =E66*E67*E68 -> 0.40703942 | F69: =F66*F67*F68 -> 0.41942229 | G69: =G66*G67*G68 -> 0.42452693 | H69: =H66*H67*H68 -> 0.4732671 | I69: =I66*I67*I68 -> 0.4154111 | J69: =J66*J67*J68 -> 0.39730657 | K69: =K66*K67*K68 -> 0.37938846 | L69: =L66*L67*L68 -> 0.36172936 | M69: =M66*M67*M68 -> 0.3412741

Sheet Analysis
B2: The Coca-Cola Company
B3: Analysis
B4: (in Millions, except per share data)
B5: Date | E5: 44561 | F5: =EDATE(E5,12) -> 44926 | G5: =EDATE(F5,12) -> 45291 | H5: =EDATE(G5,12) -> 45657 | I5: =EDATE(H5,12) -> 46022 | J5: =EDATE(I5,12) -> 46387 | K5: =EDATE(J5,12) -> 46752 | L5: =EDATE(K5,12) -> 47118 | M5: =EDATE(L5,12) -> 47483
B6: Actual / Forecast | E6: Actual | F6: Actual | G6: Actual | H6: Actual | I6: Forecast | J6: Forecast | K6: Forecast | L6: Forecast | M6: Forecast
A8: * | B8: Horizontal Analysis
B10: Net Revenue | E10: =Historicals!H11/Historicals!H11 -> 1 | F10: =Historicals!I11/Historicals!I11 -> 1 | G10: =Historicals!J11/Historicals!J11 -> 1 | H10: =Historicals!K11/Historicals!K11 -> 1 | I10: =Historicals!L11/Historicals!L11 -> 1 | J10: =Historicals!M11/Historicals!M11 -> 1 | K10: =Historicals!N11/Historicals!N11 -> 1 | L10: =Historicals!O11/Historicals!O11 -> 1 | M10: =Historicals!P11/Historicals!P11 -> 1
B11: Cost of Goods Sold | E11: =Historicals!H15/Historicals!H11 -> 0.39862383 | F11: =Historicals!I15/Historicals!I11 -> 0.41390605 | G11: =Historicals!J15/Historicals!J11 -> 0.40330683 | H11: =Historicals!K15/Historicals!K11 -> 0.38923599 | I11: =Historicals!L15/Historicals!L11 -> 0.40110397 | J11: =Historicals!M15/Historicals!M11 -> 0.40110397 | K11: =Historicals!N15/Historicals!N11 -> 0.40110397 | L11: =Historicals!O15/Historicals!O11 -> 0.40110397 | M11: =Historicals!P15/Historicals!P11 -> 0.40110397
B12: Normalised Gross profit | E12: =Historicals!H17/Historicals!H11 -> 0.60137617 | F12: =Historicals!I17/Historicals!I11 -> 0.58609395 | G12: =Historicals!J17/Historicals!J11 -> 0.59669317 | H12: =Historicals!K17/Historicals!K11 -> 0.61076401 | I12: =Historicals!L17/Historicals!L11 -> 0.59889603 | J12: =Historicals!M17/Historicals!M11 -> 0.59889603 | K12: =Historicals!N17/Historicals!N11 -> 0.59889603 | L12: =Historicals!O17/Historicals!O11 -> 0.59889603 | M12: =Historicals!P17/Historicals!P11 -> 0.59889603
B14: Selling, General and administrative expenses | E14: =Historicals!H21/Historicals!H11 -> 0.31401004 | F14: =Historicals!I21/Historicals!I11 -> 0.29930772 | G14: =Historicals!J21/Historicals!J11 -> 0.30541237 | H14: =Historicals!K21/Historicals!K11 -> 0.31042497 | I14: =Historicals!L21/Historicals!L11 -> 0.30714757 | J14: =Historicals!M21/Historicals!M11 -> 0.30714757 | K14: =Historicals!N21/Historicals!N11 -> 0.30714757 | L14: =Historicals!O21/Historicals!O11 -> 0.30714757 | M14: =Historicals!P21/Historicals!P11 -> 0.30714757
B15: Normalised Operating Income | E15: =Historicals!H27/Historicals!H11 -> 0.28736613 | F15: =Historicals!I27/Historicals!I11 -> 0.28678623 | G15: =Historicals!J27/Historicals!J11 -> 0.2912808 | H15: =Historicals!K27/Historicals!K11 -> 0.30033904 | I15: =Historicals!L27/Historicals!L11 -> 0.29174846 | J15: =Historicals!M27/Historicals!M11 -> 0.29174846 | K15: =Historicals!N27/Historicals!N11 -> 0.29174846 | L15: =Historicals!O27/Historicals!O11 -> 0.29174846 | M15: =Historicals!P27/Historicals!P11 -> 0.29174846
B17: Normalised Interest Expense | E17: =Historicals!H32/Historicals!H11 -> 0.020073465 | F17: =Historicals!I32/Historicals!I11 -> 0.021047252 | G17: =Historicals!J32/Historicals!J11 -> 0.033898305 | H17: =Historicals!K32/Historicals!K11 -> 0.03584451 | I17: =Historicals!L32/Historicals!L11 -> 0.029907384 | J17: =Historicals!M32/Historicals!M11 -> 0.027874968 | K17: =Historicals!N32/Historicals!N11 -> 0.026176466 | L17: =Historicals!O32/Historicals!O11 -> 0.024474937 | M17: =Historicals!P32/Historicals!P11 -> 0.022864561
B18: Equity Income (net) \ loss | E18: =Historicals!H36/Historicals!H11 -> 0.037534275 | F18: =Historicals!I36/Historicals!I11 -> 0.034985829 | G18: =Historicals!J36/Historicals!J11 -> 0.040407129 | H18: =Historicals!K36/Historicals!K11 -> 0.039704032 | I18: =Historicals!L36/Historicals!L11 -> 0.03813912 | J18: =Historicals!M36/Historicals!M11 -> 0.03813912 | K18: =Historicals!N36/Historicals!N11 -> 0.03813912 | L18: =Historicals!O36/Historicals!O11 -> 0.03813912 | M18: =Historicals!P36/Historicals!P11 -> 0.03813912
B20: Normalised Other Income Net | E20: =Historicals!H40/Historicals!H11 -> 0.0094935072 | F20: =Historicals!I40/Historicals!I11 -> -0.00039492636 | G20: =Historicals!J40/Historicals!J11 -> -0.0030141534 | H20: =Historicals!K40/Historicals!K11 -> 0.0016845427 | I20: =Historicals!L40/Historicals!L11 -> 0.0019403686 | J20: =Historicals!M40/Historicals!M11 -> 0.0019403686 | K20: =Historicals!N40/Historicals!N11 -> 0.0019403686 | L20: =Historicals!O40/Historicals!O11 -> 0.0019403686 | M20: =Historicals!P40/Historicals!P11 -> 0.0019403686
B21: Income Before Taxes | E21: =Historicals!H41/Historicals!H11 -> 0.32145998 | F21: =Historicals!I41/Historicals!I11 -> 0.31076058 | G21: =Historicals!J41/Historicals!J11 -> 0.31458588 | H21: =Historicals!K41/Historicals!K11 -> 0.32695055 | I21: =Historicals!L41/Historicals!L11 -> 0.30192057 | J21: =Historicals!M41/Historicals!M11 -> 0.30395298 | K21: =Historicals!N41/Historicals!N11 -> 0.30565148 | L21: =Historicals!O41/Historicals!O11 -> 0.30735301 | M21: =Historicals!P41/Historicals!P11 -> 0.30896339
B23: Normalised Income Taxes | E23: =Historicals!H44/Historicals!H11 -> 0.059703037 | F23: =Historicals!I44/Historicals!I11 -> 0.059122799 | G23: =Historicals!J44/Historicals!J11 -> 0.059780709 | H23: =Historicals!K44/Historicals!K11 -> 0.060814125 | I23: =Historicals!L44/Historicals!L11 -> 0.056761855 | J23: =Historicals!M44/Historicals!M11 -> 0.057143955 | K23: =Historicals!N44/Historicals!N11 -> 0.057463278 | L23: =Historicals!O44/Historicals!O11 -> 0.05778317 | M23: =Historicals!P44/Historicals!P11 -> 0.058085925
B24: Consolidated Net Income | E24: =Historicals!H45/Historicals!H11 -> 0.26175695 | F24: =Historicals!I45/Historicals!I11 -> 0.25163778 | G24: =Historicals!J45/Historicals!J11 -> 0.25480517 | H24: =Historicals!K45/Historicals!K11 -> 0.26613643 | I24: =Historicals!L45/Historicals!L11 -> 0.24515871 | J24: =Historicals!M45/Historicals!M11 -> 0.24680903 | K24: =Historicals!N45/Historicals!N11 -> 0.24818821 | L24: =Historicals!O45/Historicals!O11 -> 0.24956984 | M24: =Historicals!P45/Historicals!P11 -> 0.25087746
B26: Net income (loss) attributable to NCI | E26: =Historicals!H47/Historicals!H11 -> 0.00085363961 | F26: =Historicals!I47/Historicals!I11 -> 0.0006736979 | G26: =Historicals!J47/Historicals!J11 -> -0.00024025861 | H26: =Historicals!K47/Historicals!K11 -> 0.00038381986 | I26: =Historicals!L47/Historicals!L11 -> 0.00033401119 | J26: =Historicals!M47/Historicals!M11 -> 0.00023702407 | K26: =Historicals!N47/Historicals!N11 -> 0.00015522015 | L26: =Historicals!O47/Historicals!O11 -> 0.00022456907 | M26: =Historicals!P47/Historicals!P11 -> 0.0002017209
B27: Net Income to Common | E27: =Historicals!H48/Historicals!H11 -> 0.26090331 | F27: =Historicals!I48/Historicals!I11 -> 0.25096408 | G27: =Historicals!J48/Historicals!J11 -> 0.25504543 | H27: =Historicals!K48/Historicals!K11 -> 0.26575261 | I27: =Historicals!L48/Historicals!L11 -> 0.2448247 | J27: =Historicals!M48/Historicals!M11 -> 0.246572 | K27: =Historicals!N48/Historicals!N11 -> 0.24803299 | L27: =Historicals!O48/Historicals!O11 -> 0.24934527 | M27: =Historicals!P48/Historicals!P11 -> 0.25067574
A30: * | B30: Trend Analysis
B32: Net Revenue | E32: - | F32: =Historicals!I11/Historicals!H11-1 -> 0.1135082 | G32: =Historicals!J11/Historicals!I11-1 -> 0.063606375 | H32: =Historicals!K11/Historicals!J11-1 -> 0.024309803 | I32: =Historicals!L11/Historicals!K11-1 -> 0.10124264 | J32: =Historicals!M11/Historicals!L11-1 -> 0.087524585 | K32: =Historicals!N11/Historicals!M11-1 -> 0.077157566 | L32: =Historicals!O11/Historicals!N11-1 -> 0.066400963 | M32: =Historicals!P11/Historicals!O11-1 -> 0.045806961
B33: Cost of Goods Sold | E33: - | F33: =Historicals!I15/Historicals!H15-1 -> 0.15619727 | G33: =Historicals!J15/Historicals!I15-1 -> 0.036369759 | H33: =Historicals!K15/Historicals!J15-1 -> -0.011427024 | I33: =Historicals!L15/Historicals!K15-1 -> 0.13482004 | J33: =Historicals!M15/Historicals!L15-1 -> 0.087524585 | K33: =Historicals!N15/Historicals!M15-1 -> 0.077157566 | L33: =Historicals!O15/Historicals!N15-1 -> 0.066400963 | M33: =Historicals!P15/Historicals!O15-1 -> 0.045806961
B34: Normalised Gross profit | E34: - | F34: =Historicals!I17/Historicals!H17-1 -> 0.085211631 | G34: =Historicals!J17/Historicals!I17-1 -> 0.082841175 | H34: =Historicals!K17/Historicals!J17-1 -> 0.048464439 | I34: =Historicals!L17/Historicals!K17-1 -> 0.079843969 | J34: =Historicals!M17/Historicals!L17-1 -> 0.087524585 | K34: =Historicals!N17/Historicals!M17-1 -> 0.077157566 | L34: =Historicals!O17/Historicals!N17-1 -> 0.066400963 | M34: =Historicals!P17/Historicals!O17-1 -> 0.045806961
B36: Selling, General and administrative expenses | E36: - | F36: =Historicals!I21/Historicals!H21-1 -> 0.061372436 | G36: =Historicals!J21/Historicals!I21-1 -> 0.085299596 | H36: =Historicals!K21/Historicals!J21-1 -> 0.041121362 | I36: =Historicals!L21/Historicals!K21-1 -> 0.089615922 | J36: =Historicals!M21/Historicals!L21-1 -> 0.087524585 | K36: =Historicals!N21/Historicals!M21-1 -> 0.077157566 | L36: =Historicals!O21/Historicals!N21-1 -> 0.066400963 | M36: =Historicals!P21/Historicals!O21-1 -> 0.045806961
B37: Normalised Operating Income | E37: - | F37: =Historicals!I27/Historicals!H27-1 -> 0.11126114 | G37: =Historicals!J27/Historicals!I27-1 -> 0.080275415 | H37: =Historicals!K27/Historicals!J27-1 -> 0.056163767 | I37: =Historicals!L27/Historicals!K27-1 -> 0.069743856 | J37: =Historicals!M27/Historicals!L27-1 -> 0.087524585 | K37: =Historicals!N27/Historicals!M27-1 -> 0.077157566 | L37: =Historicals!O27/Historicals!N27-1 -> 0.066400963 | M37: =Historicals!P27/Historicals!O27-1 -> 0.045806961
B39: Normalised Interest Expense | E39: - | F39: =Historicals!I32/Historicals!H32-1 -> 0.16752577 | G39: =Historicals!J32/Historicals!I32-1 -> 0.71302428 | H39: =Historicals!K32/Historicals!J32-1 -> 0.083118557 | I39: =Historicals!L32/Historicals!K32-1 -> -0.081162335 | J39: =Historicals!M32/Historicals!L32-1 -> 0.013619687 | K39: =Historicals!N32/Historicals!M32-1 -> 0.011523261 | L39: =Historicals!O32/Historicals!N32-1 -> -0.0029175136 | M39: =Historicals!P32/Historicals!O32-1 -> -0.023003942
B40: Equity Income (net) \ loss | E40: - | F40: =Historicals!I36/Historicals!H36-1 -> 0.037904893 | G40: =Historicals!J36/Historicals!I36-1 -> 0.22841965 | H40: =Historicals!K36/Historicals!J36-1 -> 0.0064864865 | I40: =Historicals!L36/Historicals!K36-1 -> 0.057837768 | J40: =Historicals!M36/Historicals!L36-1 -> 0.087524585 | K40: =Historicals!N36/Historicals!M36-1 -> 0.077157566 | L40: =Historicals!O36/Historicals!N36-1 -> 0.066400963 | M40: =Historicals!P36/Historicals!O36-1 -> 0.045806961
B42: Normalised Other Income Net | E42: - | F42: =Historicals!I40/Historicals!H40-1 -> -1.0463215 | G42: =Historicals!J40/Historicals!I40-1 -> 7.1176471 | H42: =Historicals!K40/Historicals!J40-1 -> -1.5724638 | I42: =Historicals!L40/Historicals!K40-1 -> 0.2684847 | J42: =Historicals!M40/Historicals!L40-1 -> 0.087524585 | K42: =Historicals!N40/Historicals!M40-1 -> 0.077157566 | L42: =Historicals!O40/Historicals!N40-1 -> 0.066400963 | M42: =Historicals!P40/Historicals!O40-1 -> 0.045806961
B43: Income Before Taxes | E43: - | F43: =Historicals!I41/Historicals!H41-1 -> 0.076446447 | G43: =Historicals!J41/Historicals!I41-1 -> 0.076698811 | H43: =Historicals!K41/Historicals!J41-1 -> 0.064569881 | I43: =Historicals!L41/Historicals!K41-1 -> 0.016936041 | J43: =Historicals!M41/Historicals!L41-1 -> 0.094845392 | K43: =Historicals!N41/Historicals!M41-1 -> 0.083176767 | L43: =Historicals!O41/Historicals!N41-1 -> 0.072337505 | M43: =Historicals!P41/Historicals!O41-1 -> 0.051286467
B45: Normalised Income Taxes | E45: - | F45: =Historicals!I44/Historicals!H44-1 -> 0.10268631 | G45: =Historicals!J44/Historicals!I44-1 -> 0.075442043 | H45: =Historicals!K44/Historicals!J44-1 -> 0.042016807 | I45: =Historicals!L44/Historicals!K44-1 -> 0.027862782 | J45: =Historicals!M44/Historicals!L44-1 -> 0.094845392 | K45: =Historicals!N44/Historicals!M44-1 -> 0.083176767 | L45: =Historicals!O44/Historicals!N44-1 -> 0.072337505 | M45: =Historicals!P44/Historicals!O44-1 -> 0.051286467
B46: Consolidated Net Income | E46: - | F46: =Historicals!I45/Historicals!H45-1 -> 0.070461508 | G46: =Historicals!J45/Historicals!I45-1 -> 0.076994092 | H46: =Historicals!K45/Historicals!J45-1 -> 0.069861135 | I46: =Historicals!L45/Historicals!K45-1 -> 0.0144392 | J46: =Historicals!M45/Historicals!L45-1 -> 0.094845392 | K46: =Historicals!N45/Historicals!M45-1 -> 0.083176767 | L46: =Historicals!O45/Historicals!N45-1 -> 0.072337505 | M46: =Historicals!P45/Historicals!O45-1 -> 0.051286467
B48: Net income (loss) attributable to NCI | E48: - | F48: =Historicals!I47/Historicals!H47-1 -> -0.12121212 | G48: =Historicals!J47/Historicals!I47-1 -> -1.3793103 | H48: =Historicals!K47/Historicals!J47-1 -> -2.6363636 | I48: =Historicals!L47/Historicals!K47-1 -> -0.041666667 | J48: =Historicals!M47/Historicals!L47-1 -> -0.22826087 | K48: =Historicals!N47/Historicals!M47-1 -> -0.29460094 | L48: =Historicals!O47/Historicals!N47-1 -> 0.54284526 | M48: =Historicals!P47/Historicals!O47-1 -> -0.060595848
B49: Net Income to Common | E49: - | F49: =Historicals!I48/Historicals!H48-1 -> 0.071088638 | G49: =Historicals!J48/Historicals!I48-1 -> 0.080903453 | H49: =Historicals!K48/Historicals!J48-1 -> 0.06731181 | I49: =Historicals!L48/Historicals!K48-1 -> 0.014520232 | J49: =Historicals!M48/Historicals!L48-1 -> 0.095286202 | K49: =Historicals!N48/Historicals!M48-1 -> 0.083539916 | L49: =Historicals!O48/Historicals!N48-1 -> 0.072043059 | M49: =Historicals!P48/Historicals!O48-1 -> 0.051387232
A51: * | B51: End

Sheet Data
B1: DO NOT MAKE CHANGES TO THIS SHEET
A2: Income Statement
A3: Year Ended December 31, | B3: 2021 | C3: 2022 | D3: 2023 | E3: 2024
A4: Net Operating Revenues | B4: 38655 | C4: 43004 | D4: 45754 | E4: 47061
A5: Cost of goods sold | B5: 15357 | C5: 18000 | D5: 18520 | E5: 18324
A6: Gross Profit | B6: 23298 | C6: 25004 | D6: 27234 | E6: 28737
A7: Selling, general and administrative expenses | B7: 12144 | C7: 12880 | D7: 13972 | E7: 14582
A8: Other operating charges | B8: 846 | C8: 1215 | D8: 1951 | E8: 4163
A9: Operating Income | B9: 10308 | C9: 10909 | D9: 11311 | E9: 9992
A10: Interest income | B10: 276 | C10: 449 | D10: 907 | E10: 988
A11: Interest expense | B11: 1597 | C11: 882 | D11: 1527 | E11: 1656
A12: Equity income (loss) — net | B12: 1438 | C12: 1472 | D12: 1691 | E12: 1770
A13: Other income (loss) — net | B13: 2000 | C13: -262 | D13: 570 | E13: 1992
A14: Income Before Income Taxes | B14: 12425 | C14: 11686 | D14: 12952 | E14: 13086
... A23: Average Shares Outstanding — Diluted | B23: 4340 | C23: 4350 | D23: 4339 | E23: 4320
A28: Year Ended December 31, | C28: 2022 | D28: 2023 | E28: 2024
A29: Operating Activities
A30: Consolidated net income | C30: 9,571 | D30: 10,703 | E30: 10,649
A31: Adjustments to reconcile consolidated net income to net cash provided by operating activities:
A32: Depreciation and amortization | C32: 1260 | D32: 1128 | E32: 1075
A33: Stock-based compensation expense | C33: 356 | D33: 254 | E33: 286
A34: Deferred income taxes | C34: -122 | D34: -2 | E34: -11
A35: Equity (income) loss — net of dividends | C35: -838 | D35: -1019 | E35: -802
A36: Foreign currency adjustments | C36: 203 | D36: 175 | E36: -110
A37: Significant (gains) losses — net | C37: -129 | D37: -492 | E37: -1737
A38: Other operating charges | C38: 1,086 | D38: 1,741 | E38: 4,000
A39: Other items | C39: 236 | D39: -43 | E39: -311
A40: Net change in operating assets and liabilities | C40: -605 | D40: -846 | E40: -6234
A41: Net Cash Provided by Operating Activities | C41: 11,018 | D41: 11,599 | E41: 6,805
A42: Investing Activities
A43: Purchases of investments | C43: -3751 | D43: -6698 | E43: -5640
A44: Proceeds from disposals of investments | C44: 4,771 | D44: 4,354 | E44: 6,589
A45: Acquisitions of businesses, equity method investments and nonmarketable securities | C45: -73 | D45: -62 | E45: -315
A46: Proceeds from disposals of businesses, equity method investments and nonmarketable securities | C46: 458 | D46: 430 | E46: 3,485
A47: Purchases of property, plant and equipment | C47: -1484 | D47: -1852 | E47: -2064
A48: Proceeds from disposals of property, plant and equipment | C48: 75 | D48: 74 | E48: 40
A49: Collateral (paid) received associated with hedging activities — net | C49: -1465 | D49: 366 | E49: 235
A50: Other investing activities | C50: 706 | D50: 39 | E50: 194
A51: Net Cash Provided by (Used in) Investing Activities | C51: -763 | D51: -3349 | E51: 2,524
A52: Financing Activities
A53: Issuances of loans, notes payable and long-term debt | C53: 3,972 | D53: 6,891 | E53: 12,061
A54: Payments of loans, notes payable and long-term debt | C54: -4930 | D54: -5034 | E54: -9533
A55: Issuances of stock | C55: 837 | D55: 539 | E55: 747
A56: Purchases of stock for treasury | C56: -1418 | D56: -2289 | E56: -1795
A57: Dividends | C57: -7616 | D57: -7952 | E57: -8359
A58: Other financing activities | C58: -1095 | D58: -465 | E58: -31
A59: Net Cash Provided by (Used in) Financing Activities | C59: -10250 | D59: -8310 | E59: -6910
A60: Effect of Exchange Rate Changes on Cash, Cash Equivalents, Restricted Cash and | C60: -205 | D60: -73 | E60: -623
A61: Restricted Cash Equivalents
A62: Cash, Cash Equivalents, Restricted Cash and Restricted Cash Equivalents
A63: Net increase (decrease) in cash, cash equivalents, restricted cash and restricted cash | C63: -200 | D63: -133 | E63: 1,796
A64: equivalents during the year
A65: Cash, cash equivalents, restricted cash and restricted cash equivalents at beginning of year | C65: 10,025 | D65: 9,825 | E65: 9,692
A66: Cash, Cash Equivalents, Restricted Cash and Restricted Cash Equivalents at End of Year | C66: 9,825 | D66: 9,692 | E66: 11,488
A67: Less: Restricted cash and restricted cash equivalents at end of year | C67: 306 | D67: 326 | E67: 660
A68: Cash and Cash Equivalents at End of Year | C68: 9,519 | D68: 9,366 | E68: 10,828
A72: Year Ended December 31, | D72: 2021
A73: Operating Activities
A74: Consolidated net income | D74: 9,804
A75: Depreciation and amortization | D75: 1452
A76: Stock-based compensation expense | D76: 337
A77: Deferred income taxes | D77: 894
A78: Equity (income) loss — net of dividends | D78: -615
A79: Foreign currency adjustments | D79: 86
A80: Significant (gains) losses — net | D80: -1365
A81: Other operating charges | D81: 506
A82: Other items | D82: 201
A83: Net change in operating assets and liabilities | D83: 1,325
A84: Net Cash Provided by Operating Activities | D84: 12,625
A85: Investing Activities
A86: Purchases of investments | D86: -6030
A87: Proceeds from disposals of investments | D87: 7,059
A88: Acquisitions of businesses, equity method investments and nonmarketable securities | D88: -4766
A89: Proceeds from disposals of businesses, equity method investments and nonmarketable securities | D89: 2,180
A90: Purchases of property, plant and equipment | D90: -1367
A91: Proceeds from disposals of property, plant and equipment | D91: 108
A92: Other investing activities | D92: 51
A93: Net Cash Provided by (Used in) Investing Activities | D93: -2765
A94: Financing Activities
A95: Issuances of debt | D95: 13,094
A96: Payments of debt | D96: -12866
A97: Issuances of stock | D97: 702
A98: Purchases of stock for treasury | D98: -111
A99: Dividends | D99: -7252
A100: Other financing activities | D100: -353
A101: Net Cash Provided by (Used in) Financing Activities | D101: -6786
A102: Effect of Exchange Rate Changes on Cash, Cash Equivalents, Restricted Cash and | D102: -159
A103: Restricted Cash Equivalents
A104: Cash, Cash Equivalents, Restricted Cash and Restricted Cash Equivalents
A105: Net increase (decrease) in cash, cash equivalents, restricted cash and restricted cash | D105: 2,915
A106: equivalents during the year
A107: Cash, cash equivalents, restricted cash and restricted cash equivalents at beginning of year | D107: 7,110
A108: Cash, Cash Equivalents, Restricted Cash and Restricted Cash Equivalents at End of Year | D108: 10,025
A109: Less: Restricted cash and restricted cash equivalents at end of year | D109: 341
A110: Cash and Cash Equivalents at End of Year | D110: 9,684
A112: Balance Sheet
B113: 2023 | C113: 2024
A114: ASSETS
A115: Current Assets
A116: Cash and cash equivalents | B116: 9,366 | C116: 10,828
...
