Workbook
Name coe: Valuation!$D$29
Name tgr: Valuation!$D$30

Sheet Summary
C2: Emirates NDB
C3: Valuation
C4: ( in AED Million, except earnings per share and shares outstanding)
C5: (Disclaimer - The valuation analysis is conducted only for educational purposes, not as a recommendation to buy/sell stock and securities.)
A7: # | C7: Overview
C8: The valuation analysis is conducted for Emirates NBD (Ticker: ENBD), which is a public joint stock company (PJSC) in the United Arab Emirates.
C9: The market cap for the stock is currently AED 174 Billion. Emirates NBD is recogonised as the 2nd largest bank of UAE.
C10: The stock price is currently trading between AED 26.20 to AED 27.55.
A12: # | C12: Valutation Thesis
B14: * | C14: Valuation Methadology
C15: The intrinsic value of Emirates NBD is determined through two complementary equity valuation frameworks: the Dividend Discount Model (DDM)
C16: and the Free Cash Flow to Equity (FCFE) Model, each applied over an explicit five-year forecast horizon.
B18: * | C18: Rationale for Methodology Selection
C19: Traditional free cash flow approaches — defined as operating cash flow less capital expenditures — are ill-suited for valuing financial institutions.
C21: Given that capital is effectively the raw material of a bank's operations, the distinction between operating, investing, and financing activities becomes
C22: fundamentally ambiguous. Accordingly, the DDM serves as the primary valuation framework, underpinned by the principle that, for regulated financial institutions,
C23: distributable cash flow is best approximated by dividends paid after satisfying prevailing regulatory capital requirements (Basel III).
C25: Furthermore, the relatively stable, predictable, and long-duration nature of bank dividend policies lends itself well to dividend-based valuation,
C26: reinforcing the suitability of the DDM for this analysis.
C28: The FCFE model is applied as a complementary cross-check, with free cash flow to equity defined as net income adjusted for changes in regulatory capital requirements,
C29: reflecting the binding constraint that capital adequacy ratios impose on a bank's capacity to return capital to shareholders.
B31: * | C31: Forecast Construction
C32: Rather than relying on conventional sustainable growth rate approximations, income statement projections are constructed bottom-up over the five-year explicit forecast period
C33: using real-time macroeconomic inputs. Nominal GDP growth serves as the primary driver for balance sheet asset expansion, anchoring the forecasts in observable economic
C34: conditions and enhancing the robustness of forward estimates.
C36: Terminal value in both models is calculated at the conclusion of the explicit forecast period using the Gordon Growth Model, capitalising normalised cash flows at the spread
C37: between the cost of equity and the terminal growth rate.
B39: * | C39: Scenario Analysis
C40: To capture the range of plausible outcomes and reflect the inherent uncertainty in long-term forecasting, the valuation is conducted across three distinct scenarios:
C41: 1.Base Case: Consensus / street assumptions; moderate growth and stable margins
C42: 2. Conservative Case: Downside scenario reflecting macro headwinds or margin compression
C43: 3. Optimistic Case: Upside scenario incorporating accelerated growth or margin expansion
C45: Scenarios are differentiated primarily through two key value drivers: the Cost of Equity (Ke) and the Terminal Growth Rate (g), with all other inputs held consistent across cases.
B47: * | C47: Valuation Mechanics
C48: Dividend Discount Model: Projected dividends are derived from forecasted net income, the prevailing dividend payout ratio, and return on equity.
C49: Dividends over the explicit forecast period and the terminal value are discounted to present value at the cost of equity.
C50: The resulting intrinsic value per share represents the sum of the present value of forecast-period dividends and the present value of the terminal value.
C52: Free Cash Flow to Equity Model: FCFE is computed as net income less the incremental investment required to maintain regulatory capital ratios
C53: (i.e., the change in risk-weighted assets multiplied by the target Tier 1 capital ratio).
C54: Key inputs include risk-weighted assets, Tier 1 capital, book value, return on equity, and net income. Terminal value is similarly derived via the Gordon Growth Model,
C55: with FCFE and terminal value discounted at the cost of equity to arrive at the present value of equity.
C57: The blended analysis across both models and three scenarios provides a valuation range within which Emirates NBD's fair value is assessed.
B59: * | C59: Football Field Valuation Analysis
C60: To provide a comprehensive view of Emirates NBD's intrinsic and relative value, the valuation summary is presented in the form of a football field analysis,
C61: a standard cross-methodological comparison used in equity research to illustrate the range of implied share price outcomes across independent valuation frameworks.
B63: # | C63: Football Field Valuation Analysis
C65: Metrics | D65: 25th Percentile | E65: Median | F65: 75th Percentile
C66: DDM | D66: =Valuation!M152 -> 17.762488 | E66: =Valuation!M150 -> 23.460442 | F66: =Valuation!M151 -> 32.402857
C67: FCFE | D67: =Valuation!M159 -> 28.48641 | E67: =Valuation!M157 -> 35.750801 | F67: =Valuation!M158 -> 46.283838
C68: 52-week | D68: ='52_week'!H8 -> 21.9375 | E68: ='52_week'!H6 -> 25.5 | F68: ='52_week'!H7 -> 27.8
C69: Comps | D69: =CoC!L7 -> 9.775 | E69: =CoC!L5 -> 11.88 | F69: =CoC!L6 -> 17.87
B71: * | C71: Football Field Summary Chart
C72: The chart below presents the implied share price ranges across all five methodologies.
C73: The current market price is overlaid as a reference line to contextualise
C74: where Emirates NBD trades relative to the full spectrum of valuation outcomes.
C76: Emirates NBD Current Share Price: (AED) | F76: 26.75

Sheet Valuation
C2: Emirates NDB
C3: Valuation
C4: ( in AED Million, except earnings per share and shares outstanding)
A7: # | C7: Dashboard
C9: Company Name: | F9: =C2 -> Emirates NDB | I9: Val. Using Dividend Discount Model | M9: Val. Using Free Cash Flow to Firm
C10: Ticker: | F10: ENBD | I10: Implied Price per share: | K10: =K124 -> 23.235493 | M10: Implied Price per share: | O10: =K143 -> 35.373564
I11: Current Share price: | K11: 26.75 | M11: Current Share price: | O11: 28.95
C12: Scenario Selected | G12: 1 | I12: Δ % Price: | K12: =K10/K11-1 -> -0.13138344 | M12: Δ % Price: | O12: =O10/O11-1 -> 0.22188477
C14: Start Date: | F14: Date | G14: 44561
C15: End Date: | F15: Date | G15: 47848
C16: No. of Years: | F16: Years | G16: =YEARFRAC(G14,G15,1) -> 9.0005476
C17: Days in an Year: | F17: Days | G17: 365
C19: Templete: | D19: Standard | F19: Currency: | G19: AED
C20: Period type: | D20: Annual | F20: Units: | G20: Millions
C21: Source: | D21: Company Website | F21: Decimals: | G21: Default
A23: # | C23: Assumptions
C25: Trigger | F25: Conservative | J25: Base / Street | N25: Optimistic
C27: Scenario: | D27: =$G$12 -> 1 | F27: Cost of Equity: | H27: =L27+1% -> 0.16141728 | J27: Cost of Equity: | L27: =CoC!E26 -> 0.15141728 | N27: Cost of Equity: | P27: =L27-1% -> 0.14141728
F28: TGR: | H28: 0.02 | J28: TGR: | L28: 0.03 | N28: TGR: | P28: 0.04
C29: Cost of Equity: | D29: =CHOOSE($D$27,L27,H27,P27) -> 0.15141728
C30: TGR: | D30: =CHOOSE($D$27,L28,H28,P28) -> 0.03
A32: # | C32: Income Statement (13/12 CYE) | G32: 44561 | H32: =EDATE(G32,12) -> 44926 | I32: =EDATE(H32,12) -> 45291 | J32: =EDATE(I32,12) -> 45657 | K32: =EDATE(J32,12) -> 46022 | L32: =EDATE(K32,12) -> 46387 | M32: =EDATE(L32,12) -> 46752 | N32: =EDATE(M32,12) -> 47118 | O32: =EDATE(N32,12) -> 47483 | P32: =EDATE(O32,12) -> 47848
C34: Interest & similar income | G34: =Data!D11 -> 23663.509 | H34: =Data!E11 -> 30779 | I34: =Data!F11 -> 50031 | J34: =Data!G11 -> 69129 | K34: =Data!H11 -> 70892 | L34: =K34*(1+L60) -> 72309.84 | M34: =L34*(1+M60) -> 74117.586 | N34: =M34*(1+N60) -> 75970.526 | O34: =N34*(1+O60) -> 78249.641 | P34: =O34*(1+P60) -> 80597.131
C35: Interest & similar expenses | G35: =Data!D17 -> -8929.717 | H35: =Data!E17 -> -10878 | I35: =Data!F17 -> -25239 | J35: =Data!G17 -> -42760 | K35: =Data!H17 -> -42485 | L35: =K35*(1+L60) -> -43334.7 | M35: =L35*(1+M60) -> -44418.067 | N35: =M35*(1+N60) -> -45528.519 | O35: =N35*(1+O60) -> -46894.375 | P35: =O35*(1+P60) -> -48301.206
C36: Net interest income | G36: =SUM(G34:G35) -> 14733.792 | H36: =SUM(H34:H35) -> 19901 | I36: =SUM(I34:I35) -> 24792 | J36: =SUM(J34:J35) -> 26369 | K36: =SUM(K34:K35) -> 28407 | L36: =SUM(L34:L35) -> 28975.14 | M36: =SUM(M34:M35) -> 29699.518 | N36: =SUM(N34:N35) -> 30442.006 | ... P36: =SUM(P34:P35) -> 32295.925
C38: Income from Islamic financing & Investment products | G38: =Data!D23 -> 2821.9299 | H38: =Data!E23 -> 4059 | I38: =Data!F23 -> 7288 | J38: =Data!G23 -> 9003 | K38: =Data!H23 -> 11083 | L38: =L84 -> 13535.92 | M38: =M84 -> 16086.804 | N38: =N84 -> 18877.855 | O38: =O84 -> 21840.146 | P38: =P84 -> 24911.373
C39: Distribution on Islamic deposits | G39: =-Data!D28 -> -631.241 | H39: =-Data!E28 -> -738 | I39: =-Data!F28 -> -2000 | J39: =-Data!G28 -> -2976 | K39: =-Data!H28 -> -3988 | L39: =-L38*L86 -> -4872.9312 | M39: =-M38*M86 -> -5791.2494 | N39: =-N38*N86 -> -6796.0277 | O39: =-O38*O86 -> -7862.4524 | P39: =-P38*P86 -> -8968.0944
C40: Net interest from IFIP | G40: =SUM(G38:G39) -> 2190.6889 | H40: =SUM(H38:H39) -> 3321 | I40: =SUM(I38:I39) -> 5288 | J40: =SUM(J38:J39) -> 6027 | K40: =SUM(K38:K39) -> 7095 | L40: =SUM(L38:L39) -> 8662.9888 | M40: =SUM(M38:M39) -> 10295.555 | N40: =SUM(N38:N39) -> 12081.827 | ... P40: =SUM(P38:P39) -> 15943.279
C42: Net interest income & Net interest from IFIP | G42: =G36+G40 -> 16924.481 | H42: =H36+H40 -> 23222 | I42: =I36+I40 -> 30080 | J42: =J36+J40 -> 32396 | K42: =K36+K40 -> 35502 | L42: =L36+L40 -> 37638.129 | M42: =M36+M40 -> 39995.073 | N42: =N36+N40 -> 42523.833 | ... P42: =P36+P40 -> 48239.204
C44: Fee and commission income | G44: =Data!D36 -> 6475.045 | H44: =Data!E36 -> 7004 | I44: =Data!F36 -> 8959 | J44: =Data!G36 -> 13347 | K44: =Data!H36 -> 15738 | L44: =L88 -> 18413.46 | M44: =M88 -> 21451.681 | N44: =N88 -> 24669.433 | O44: =O88 -> 27999.806 | P44: =P88 -> 31359.783
C45: Fee and commission expenses | G45: =Data!D37 -> -2639.234 | H45: =Data!E37 -> -2923 | I45: =Data!F37 -> -4086 | J45: =Data!G37 -> -6554 | K45: =Data!H37 -> -7706 | L45: =-L44*L94 -> -8286.057 | M45: =-M44*M94 -> -9653.2564 | N45: =-N44*N94 -> -11101.245 | O45: =-O44*O94 -> -12599.913 | P45: =-P44*P94 -> -14111.902
C46: Net fee and commission income | G46: =SUM(G44:G45) -> 3835.811 | H46: =SUM(H44:H45) -> 4081 | I46: =SUM(I44:I45) -> 4873 | J46: =SUM(J44:J45) -> 6793 | K46: =SUM(K44:K45) -> 8032 | L46: =SUM(L44:L45) -> 10127.403 | M46: =SUM(M44:M45) -> 11798.424 | N46: =SUM(N44:N45) -> 13568.188 | ... P46: =SUM(P44:P45) -> 17247.881
C47: Net gain on trading securities | G47: 150.818 | H47: 52 | I47: 480 | J47: 838 | K47: 2263 | L47: =L96 -> 2715.6 | M47: =M96 -> 3122.94 | N47: =N96 -> 3435.234 | O47: =O96 -> 3606.9957 | P47: =P96 -> 3606.9957
C48: Other operating income | G48: 2910.461 | H48: 5152 | I48: 7595 | J48: 4107 | K48: 3522 | L48: =L102 -> 4087.8638 | M48: =M102 -> 4121.7532 | N48: =N102 -> 3675.848 | O48: =O102 -> 3600.7987 | P48: =P102 -> 3637.1267
C50: Total operating income | G50: =G42+G46+G47+G48 -> 23821.571 | H50: =H42+H46+H47+H48 -> 32507 | I50: =I42+I46+I47+I48 -> 43028 | J50: =J42+J46+J47+J48 -> 44134 | K50: =K42+K46+K47+K48 -> 49319 | L50: =L42+L46+L47+L48 -> 54568.996 | M50: =M42+M46+M47+M48 -> 59038.191 | N50: =N42+N46+N47+N48 -> 63203.104 | ... P50: =P42+P46+P47+P48 -> 72731.207
C52: Profit Before Taxes | G52: 9900 | H52: 15000 | I52: 23700 | J52: 27100 | K52: 29800 | L52: =L50*L105 -> 32741.397 | M52: =M50*M105 -> 35422.914 | N52: =N50*N105 -> 37921.862 | O52: =O50*O105 -> 40764.389 | P52: =P50*P105 -> 43638.724
C53: Income Taxes | G53: =G52-G55 -> 600 | H53: =H52-H55 -> 2000 | I53: =I52-I55 -> 2200 | J53: =J52-J55 -> 4100 | K53: =K52-K55 -> 5800 | L53: =L52*L107 -> 5893.4515 | M53: =M52*M107 -> 6376.1246 | N53: =N52*N107 -> 6825.9352 | O53: =O52*O107 -> 7337.59 | P53: =P52*P107 -> 7854.9703
C55: Profit After Taxes | G55: 9300 | H55: 13000 | I55: 21500 | J55: 23000 | K55: 24000 | L55: =L52-L53 -> 26847.946 | M55: =M52-M53 -> 29046.79 | N55: =N52-N53 -> 31095.927 | O55: =O52-O53 -> 33426.799 | P55: =P52-P53 -> 35783.754
A57: # | C57: Assumptions (13/12 CYE) | G57: 44561 | H57: =EDATE(G57,12) -> 44926 | I57: =EDATE(H57,12) -> 45291 | J57: =EDATE(I57,12) -> 45657 | K57: =EDATE(J57,12) -> 46022 | L57: =EDATE(K57,12) -> 46387 | M57: =EDATE(L57,12) -> 46752 | N57: =EDATE(M57,12) -> 47118 | O57: =EDATE(N57,12) -> 47483 | P57: =EDATE(O57,12) -> 47848
C59: United Arab Emirates Nominal GDP: | G59: 422.4 | H59: 511.4 | I59: 522.6 | J59: 552.3 | K59: 569 | L59: =K59*(1+L60) -> 580.38 | M59: =L59*(1+M60) -> 594.8895 | N59: =M59*(1+N60) -> 609.76174 | O59: =N59*(1+O60) -> 628.05459 | P59: =O59*(1+P60) -> 646.89623
C60: % growth | H60: =H59/G59-1 -> 0.21070076 | I60: =I59/H59-1 -> 0.021900665 | J60: =J59/I59-1 -> 0.056831228 | K60: =K59/J59-1 -> 0.03023719 | L60: =OFFSET(L60,$D$27,0) -> 0.02 | M60: =OFFSET(M60,$D$27,0) -> 0.025 | N60: =OFFSET(N60,$D$27,0) -> 0.025 | O60: =OFFSET(O60,$D$27,0) -> 0.03 | P60: =OFFSET(P60,$D$27,0) -> 0.03
C61: Conservative | L61: =L62-1% -> 0.02 | M61: =M62-1% -> 0.025 | N61: =N62-1% -> 0.025 | O61: =O62-1% -> 0.03 | P61: =P62-1% -> 0.03
C62: Street | L62: 0.03 | M62: 0.035 | N62: 0.035 | O62: 0.04 | P62: 0.04
C63: Optimistic | L63: =L62+1% -> 0.04 | M63: =M62+1% -> 0.045 | N63: =N62+1% -> 0.045 | O63: =O62+1% -> 0.05 | P63: =P62+1% -> 0.05
C65: Income from Islamic financing & Investment products
C66: Murabaha | G66: =Data!D20 -> 1273.602 | H66: =Data!E20 -> 1946 | I66: =Data!F20 -> 3559 | J66: =Data!G20 -> 4153 | K66: =Data!H20 -> 4826 | L66: =K66*(1+L67) -> 5549.9 | M66: =L66*(1+M67) -> 6271.387 | N66: =M66*(1+N67) -> 7023.9534 | O66: =N66*(1+O67) -> 7796.5883 | P66: =O66*(1+P67) -> 8498.2813
C67: % growth | H67: =H66/G66-1 -> 0.52794986 | I67: =I66/H66-1 -> 0.82887975 | J67: =J66/I66-1 -> 0.16690081 | K67: =K66/J66-1 -> 0.16205153 | L67: =OFFSET(L67,$D$27,0) -> 0.15 | M67: =OFFSET(M67,$D$27,0) -> 0.13 | N67: =OFFSET(N67,$D$27,0) -> 0.12 | O67: =OFFSET(O67,$D$27,0) -> 0.11 | P67: =OFFSET(P67,$D$27,0) -> 0.09
C68: Conservative | L68: =L69-1% -> 0.15 | M68: =M69-1% -> 0.13 | N68: =N69-1% -> 0.12 | O68: =O69-1% -> 0.11 | P68: =P69-1% -> 0.09
C69: Street | L69: 0.16 | M69: 0.14 | N69: 0.13 | O69: 0.12 | P69: 0.1
C70: Optimistic | L70: =L69+1% -> 0.17 | M70: =M69+1% -> 0.15 | N70: =N69+1% -> 0.14 | O70: =O69+1% -> 0.13 | P70: =P69+1% -> 0.11
C72: Ijara | G72: =Data!D21 -> 595.96 | H72: =Data!E21 -> 853 | I72: =Data!F21 -> 1459 | J72: =Data!G21 -> 1544 | K72: =Data!H21 -> 1732 | L72: =K72*(1+L73) -> 1922.52 | M72: =L72*(1+M73) -> 2114.772 | N72: =M72*(1+N73) -> 2305.1015 | O72: =N72*(1+O73) -> 2489.5096 | P72: =O72*(1+P73) -> 2663.7753
C73: % growth | H73: =H72/G72-1 -> 0.43130411 | I73: =I72/H72-1 -> 0.71043376 | J73: =J72/I72-1 -> 0.058259082 | K73: =K72/J72-1 -> 0.12176166 | L73: =OFFSET(L73,$D$27,0) -> 0.11 | M73: =OFFSET(M73,$D$27,0) -> 0.1 | N73: =OFFSET(N73,$D$27,0) -> 0.09 | O73: =OFFSET(O73,$D$27,0) -> 0.08 | P73: =OFFSET(P73,$D$27,0) -> 0.07
C74: Conservative | L74: =L75-1% -> 0.11 | M74: =M75-1% -> 0.1 | N74: =N75-1% -> 0.09 | O74: =O75-1% -> 0.08 | P74: =P75-1% -> 0.07
C75: Street | L75: 0.12 | M75: 0.11 | N75: 0.1 | O75: 0.09 | P75: 0.08
C76: Optimistic | L76: =L75+1% -> 0.13 | M76: =M75+1% -> 0.12 | N76: =N75+1% -> 0.11 | O76: =O75+1% -> 0.1 | P76: =P75+1% -> 0.09
C78: Others | G78: =Data!D22 -> 952.3679 | H78: =Data!E22 -> 1260 | I78: =Data!F22 -> 2270 | J78: =Data!G22 -> 3306 | K78: =Data!H22 -> 4525 | L78: =K78*(1+L79) -> 6063.5 | M78: =L78*(1+M79) -> 7700.645 | N78: =M78*(1+N79) -> 9548.7998 | O78: =N78*(1+O79) -> 11554.048 | P78: =O78*(1+P79) -> 13749.317
C79: % growth | H79: =H78/G78-1 -> 0.32301813 | I79: =I78/H78-1 -> 0.8015873 | J79: =J78/I78-1 -> 0.45638767 | K79: =K78/J78-1 -> 0.36872353 | L79: =OFFSET(L79,$D$27,0) -> 0.34 | M79: =OFFSET(M79,$D$27,0) -> 0.27 | N79: =OFFSET(N79,$D$27,0) -> 0.24 | O79: =OFFSET(O79,$D$27,0) -> 0.21 | P79: =OFFSET(P79,$D$27,0) -> 0.19
C80: Conservative | L80: =L81-1% -> 0.34 | M80: =M81-1% -> 0.27 | N80: =N81-1% -> 0.24 | O80: =O81-1% -> 0.21 | P80: =P81-1% -> 0.19
C81: Street | L81: 0.35 | M81: 0.28 | N81: 0.25 | O81: 0.22 | P81: 0.2
C82: Optimistic | L82: =L81+1% -> 0.36 | M82: =M81+1% -> 0.29 | N82: =N81+1% -> 0.26 | O82: =O81+1% -> 0.23 | P82: =P81+1% -> 0.21
C84: Total Income from IFIP | G84: =G66+G72+G78 -> 2821.9299 | H84: =H66+H72+H78 -> 4059 | I84: =I66+I72+I78 -> 7288 | J84: =J66+J72+J78 -> 9003 | K84: =K66+K72+K78 -> 11083 | L84: =L66+L72+L78 -> 13535.92 | M84: =M66+M72+M78 -> 16086.804 | N84: =N66+N72+N78 -> 18877.855 | ... P84: =P66+P72+P78 -> 24911.373
C86: Distribution of Islamic Deposits as a % of Income from IFIP | G86: =ABS(G39/G38) -> 0.22369124 | H86: =ABS(H39/H38) -> 0.18181818 | I86: =ABS(I39/I38) -> 0.27442371 | J86: =ABS(J39/J38) -> 0.33055648 | K86: =ABS(K39/K38) -> 0.35983037 | L86: 0.36 | M86: =L86 -> 0.36 | N86: =M86 -> 0.36 | O86: =N86 -> 0.36 | P86: =O86 -> 0.36
C88: Net fee and commission income | G88: =G44 -> 6475.045 | H88: =H44 -> 7004 | I88: =I44 -> 8959 | J88: =J44 -> 13347 | K88: =K44 -> 15738 | L88: =K88*(1+L89) -> 18413.46 | M88: =L88*(1+M89) -> 21451.681 | N88: =M88*(1+N89) -> 24669.433 | O88: =N88*(1+O89) -> 27999.806 | P88: =O88*(1+P89) -> 31359.783
C89: % growth | H89: =H88/G88-1 -> 0.081691324 | I89: =I88/H88-1 -> 0.27912621 | J89: =J88/I88-1 -> 0.48978681 | K89: =K88/J88-1 -> 0.17914138 | L89: =OFFSET(L89,$D$27,0) -> 0.17 | M89: =OFFSET(M89,$D$27,0) -> 0.165 | N89: =OFFSET(N89,$D$27,0) -> 0.15 | O89: =OFFSET(O89,$D$27,0) -> 0.135 | P89: =OFFSET(P89,$D$27,0) -> 0.12
C90: Conservative | L90: =L91-1% -> 0.17 | M90: =M91-1% -> 0.165 | N90: =N91-1% -> 0.15 | O90: =O91-1% -> 0.135 | P90: =P91-1% -> 0.12
C91: Street | L91: 0.18 | M91: 0.175 | N91: 0.16 | O91: 0.145 | P91: 0.13
C92: Optimistic | L92: =L91+1% -> 0.19 | M92: =M91+1% -> 0.185 | N92: =N91+1% -> 0.17 | O92: =O91+1% -> 0.155 | P92: =P91+1% -> 0.14
C94: Fee & com. expense as a % of Total fee & com. income | G94: =ABS(G45/G44) -> 0.40760087 | H94: =ABS(H45/H44) -> 0.41733295 | I94: =ABS(I45/I44) -> 0.45607769 | J94: =ABS(J45/J44) -> 0.49104668 | K94: =ABS(K45/K44) -> 0.4896429 | L94: 0.45 | M94: =L94 -> 0.45 | N94: =M94 -> 0.45 | O94: =N94 -> 0.45 | P94: =O94 -> 0.45
C96: Net gain on trading securities | G96: =G47 -> 150.818 | H96: =H47 -> 52 | I96: =I47 -> 480 | J96: =J47 -> 838 | K96: =K47 -> 2263 | L96: =K96*(1+L97) -> 2715.6 | M96: =L96*(1+M97) -> 3122.94 | N96: =M96*(1+N97) -> 3435.234 | O96: =N96*(1+O97) -> 3606.9957 | P96: =O96*(1+P97) -> 3606.9957
C97: % growth | H97: =H96/G96-1 -> -0.65521357 | I97: =I96/H96-1 -> 8.2307692 | J97: =J96/I96-1 -> 0.74583333 | K97: =K96/J96-1 -> 1.7004773 | L97: =OFFSET(L97,$D$27,0) -> 0.2 | M97: =OFFSET(M97,$D$27,0) -> 0.15 | N97: =OFFSET(N97,$D$27,0) -> 0.1 | O97: =OFFSET(O97,$D$27,0) -> 0.05 | P97: =OFFSET(P97,$D$27,0) -> 0
C98: Conservative | L98: =L99-25% -> 0.2 | M98: =M99-25% -> 0.15 | N98: =N99-25% -> 0.1 | O98: =O99-25% -> 0.05 | P98: =P99-25% -> 0
C99: Street | L99: 0.45 | M99: 0.4 | N99: 0.35 | O99: 0.3 | P99: 0.25
C100: Optimistic | L100: =L99+5% -> 0.5 | M100: =M99+5% -> 0.45 | N100: =N99+5% -> 0.4 | O100: =O99+5% -> 0.35 | P100: =P99+5% -> 0.3
C102: Other operating income | G102: =G48 -> 2910.461 | H102: =H48 -> 5152 | I102: =I48 -> 7595 | J102: =J48 -> 4107 | K102: =K48 -> 3522 | L102: =K102*(1+L103) -> 4087.8638 | M102: =L102*(1+M103) -> 4121.7532 | N102: =M102*(1+N103) -> 3675.848 | O102: =N102*(1+O103) -> 3600.7987 | P102: =O102*(1+P103) -> 3637.1267
C103: % growth | H103: =H102/G102-1 -> 0.77016631 | I103: =I102/H102-1 -> 0.47418478 | J103: =J102/I102-1 -> -0.45924951 | K103: =K102/J102-1 -> -0.14243974 | L103: =AVERAGE(H103:K103) -> 0.16066546 | M103: =AVERAGE(I103:L103) -> 0.0082902502 | N103: =AVERAGE(J103:M103) -> -0.10818338 | O103: =AVERAGE(K103:N103) -> -0.020416852 | P103: =AVERAGE(L103:O103) -> 0.010088869
C105: PBT as a % of Operating Income | G105: =G52/G50 -> 0.41558972 | H105: =H52/H50 -> 0.46143907 | I105: =I52/I50 -> 0.55080413 | J105: =J52/J50 -> 0.61403906 | K105: =K52/K50 -> 0.60422961 | L105: 0.6 | M105: 0.6 | N105: 0.6 | O105: 0.6 | P105: 0.6
C107: Tax Rate (%) | G107: =G53/G52 -> 0.060606061 | H107: =H53/H52 -> 0.13333333 | I107: =I53/I52 -> 0.092827004 | J107: =J53/J52 -> 0.15129151 | K107: =K53/K52 -> 0.19463087 | L107: 0.18 | M107: 0.18 | N107: 0.18 | O107: 0.18 | P107: 0.18
A109: # | C109: Valuation Model (13/12 CYE) | G109: 44561 | H109: =EDATE(G109,12) -> 44926 | I109: =EDATE(H109,12) -> 45291 | J109: =EDATE(I109,12) -> 45657 | K109: =EDATE(J109,12) -> 46022 | L109: =EDATE(K109,12) -> 46387 | M109: =EDATE(L109,12) -> 46752 | N109: =EDATE(M109,12) -> 47118 | O109: =EDATE(N109,12) -> 47483 | P109: =EDATE(O109,12) -> 47848
B111: * | C111: Dividend Discount Model (DDM) | K111: Base Year | L111: 1 | M111: 2 | N111: 3 | O111: 4 | P111: 5 | Q111: Terminal Year
C113: Earnings Growth Rate | K113: =K55/J55-1 -> 0.043478261 | L113: =L55/K55-1 -> 0.11866441 | M113: =M55/L55-1 -> 0.081899898 | N113: =N55/M55-1 -> 0.070546079 | O113: =O55/N55-1 -> 0.074957462 | P113: =P55/O55-1 -> 0.07051094 | Q113: 0.04
C114: Return on Equity | K114: =CoC!$H$14 -> 0.173 | L114: =K114+($Q$114-$K$114)/5 -> 0.1754 | M114: =L114+($Q$114-$K$114)/5 -> 0.1778 | N114: =M114+($Q$114-$K$114)/5 -> 0.1802 | O114: =N114+($Q$114-$K$114)/5 -> 0.1826 | P114: =O114+($Q$114-$K$114)/5 -> 0.185 | Q114: 0.185
C115: Net Income | K115: =K55 -> 24000 | L115: =L55 -> 26847.946 | M115: =M55 -> 29046.79 | N115: =N55 -> 31095.927 | O115: =O55 -> 33426.799 | P115: =P55 -> 35783.754 | Q115: =P115*(1+Q113) -> 37215.104
C117: Dividends Issued | K117: 6311 | L117: =L118*L115 -> 8054.3837 | M117: =M118*M115 -> 8714.037 | N117: =N118*N115 -> 9328.7781 | O117: =O118*O115 -> 10028.04 | P117: =P118*P115 -> 10735.126 | Q117: =Q118*Q115 -> 29168.595
C118: Dividend Payout Ratio | K118: =K117/K55 -> 0.26295833 | L118: 0.3 | M118: 0.3 | N118: 0.3 | O118: 0.3 | P118: 0.3 | Q118: =1-Q113/Q114 -> 0.78378378
C120: Terminal Value | P120: =Q117/(coe-tgr) -> 240234.29
C121: Present Value of Dividends | L121: =L117/(1+coe)^L111 -> 6995.1909 | M121: =M117/(1+coe)^M111 -> 6572.8528 | N121: =N117/(1+coe)^N111 -> 6111.2005 | O121: =O117/(1+coe)^O111 -> 5705.3864 | P121: =(P117+P120)/(1+coe)^P111 -> 124010.11
C122: Present Value of Equity | K122: =SUM(L121:P121) -> 149394.74
C123: Number of Shares | K123: 6429.5918
C124: Value Per Share | K124: =K122/K123 -> 23.235493
B126: * | C126: Free-Cash Flow to Equity | K126: Base Year | L126: 1 | M126: 2 | N126: 3 | O126: 4 | P126: 5 | Q126: Steady State
C128: Risk-adjusted Assets | K128: 827618 | L128: =K128*(1+L60) -> 844170.36 | M128: =L128*(1+M60) -> 865274.62 | N128: =M128*(1+N60) -> 886906.48 | O128: =N128*(1+O60) -> 913513.68 | P128: =O128*(1+P60) -> 940919.09 | Q128: =P128*(1+3%) -> 969146.66
C129: Tier 1 Capital Ratio | K129: 0.1548 | L129: =K129 -> 0.1548 | M129: =L129 -> 0.1548 | N129: =M129 -> 0.1548 | O129: =N129 -> 0.1548 | P129: 0.15 | Q129: =P129 -> 0.15
C130: Tier 1 Capital | K130: 128128 | L130: =L128*L129 -> 130677.57 | M130: =M128*M129 -> 133944.51 | N130: =N128*N129 -> 137293.12 | O130: =O128*O129 -> 141411.92 | P130: =P128*P129 -> 141137.86 | Q130: =Q128*Q129 -> 145372
C131: Change in Regulatory Capital (Tier 1) | L131: =L130-K130 -> 2549.5717 | M131: =M130-L130 -> 3266.9393 | N131: =N130-M130 -> 3348.6128 | O131: =O130-N130 -> 4118.7937 | P131: =P130-O130 -> -274.0541 | Q131: =Q130-P130 -> 4234.1359
C132: Book Equity | K132: 144582 | L132: =K132+(L135-L137) -> 147131.57 | M132: =L132+(M135-M137) -> 150398.51 | N132: =M132+(N135-N137) -> 153747.12 | O132: =N132+(O135-O137) -> 157865.92 | P132: =O132+(P135-P137) -> 157591.86 | Q132: =Q134*Q135 -> 6884.7942
C134: ROE % | K134: =K114 -> 0.173 | L134: =L114 -> 0.1754 | M134: =M114 -> 0.1778 | N134: =N114 -> 0.1802 | O134: =O114 -> 0.1826 | P134: =P114 -> 0.185 | Q134: =Q114 -> 0.185
C135: Net Income | K135: =K115 -> 24000 | L135: =L115 -> 26847.946 | M135: =M115 -> 29046.79 | N135: =N115 -> 31095.927 | O135: =O115 -> 33426.799 | P135: =P115 -> 35783.754 | Q135: =Q115 -> 37215.104
C136: Less: Change in Regulatory Capital (Tier 1) | L136: =L131 -> 2549.5717 | M136: =M131 -> 3266.9393 | N136: =N131 -> 3348.6128 | O136: =O131 -> 4118.7937 | P136: =P131 -> -274.0541 | Q136: =Q131 -> 4234.1359
C137: FCFE | L137: =L135-L136 -> 24298.374 | M137: =M135-M136 -> 25779.851 | N137: =N135-N136 -> 27747.314 | O137: =O135-O136 -> 29308.005 | P137: =P135-P136 -> 36057.808 | Q137: =Q135-Q136 -> 32980.968
C139: Terminal Value of Equity | P139: =Q137/(coe-tgr) -> 271633.22
...

Sheet 52_week
C2: 52-week share price
C4: Date | D4: Close
C5: 46099 | D5: 27.55 | F5: Mean | H5: =AVERAGE($D$5:$D$276) -> 25.496324
C6: 46098 | D6: 27.8 | F6: Median | H6: =MEDIAN($D$5:$D$276) -> 25.5
C7: 46097 | D7: 26.5 | F7: 75th Percentile | H7: =PERCENTILE(($D$5:$D$276),75%) -> 27.8
C8: 46094 | D8: 26.95 | F8: 25th Percentile | H8: =PERCENTILE(($D$5:$D$276),25%) -> 21.9375
C9: 46093 | D9: 28.35
C10: 46092 | D10: 29.8
C11: 46091 | D11: 31.35
C12: 46090 | D12: 28.95
C13: 46087 | D13: 29.4
C14: 46086 | D14: 29.8
C15: 46085 | D15: 31.35
C16: 46080 | D16: 33
C17: 46079 | D17: 34.8
C18: 46078 | D18: 36.3
C19: 46077 | D19: 35.5
C20: 46076 | D20: 37
... C276: 45705 | D276: 21

Sheet CoC
B2: Comparable Companies - Financial Services & Commerical Banks with above $ 5 Billion in Market Cap
B3: (in AED millions, except Price per share and other ratios)
B5: Company Name | D5: Share Price | E5: Revenue | F5: Net Income | G5: P / BV | H5: ROE | J5: Median | L5: =MEDIAN($D$6:$D$12) -> 11.88
B6: First Abu Dhabi Bank | D6: 16.52 | E6: 31600 | F6: 17100 | G6: 1.57 | H6: 0.168 | J6: 75th Percentile | L6: =PERCENTILE(($D$6:$D$12),75%) -> 17.87
B7: Abu Dhabi Commercial Bank | D7: 11.88 | E7: 19100 | F7: 11400 | G7: 1.31 | H7: 0.153 | J7: 25th Percenile | L7: =PERCENTILE(($D$6:$D$12),25%) -> 9.775
B8: Abu Dhabi Islamic Bank | D8: 19.22 | E8: 10600 | F8: 6100 | G8: 4.2 | H8: 0.28
B9: Emirates Islamic Bank | D9: 10.85 | E9: 5400 | F9: 2800 | G9: 1.64 | H9: 0.197
B10: Dubai Islamic Bank | D10: 7.09 | E10: 23300 | F10: 8200 | G10: 1.62 | H10: 0.22
B11: MashreqBank | D11: 209 | E11: 13400 | F11: 9000 | G11: 1.6 | H11: 0.29
B12: Commerical Bank of Dubai | D12: 8.7 | E12: 5500 | F12: 3000 | G12: 2.7 | H12: 0.235
B14: Emirates NDB Bank | D14: 29.45 | E14: 49139 | F14: 24000 | G14: 1.44 | H14: 0.173
F16: Average | G16: =AVERAGE(G6:G12) -> 2.0914286 | H16: =AVERAGE(H6:H12) -> 0.22042857
F17: Median | G17: =MEDIAN(G6:G12) -> 1.62 | H17: =MEDIAN(H6:H12) -> 0.22
A19: * | B19: Cost of Equity
B20: Median P / BV | E20: =G17 -> 1.62
B21: Median ROE | E21: =H17 -> 0.22
B22: Expected growth rate | E22: 0.045
B23: Adj. Default spread | E23: 0.0042
B24: Adj. Expected growth rate (g) | E24: =E22-E23 -> 0.0408
B26: Cost of Equity | E26: =((E21-E24)/E20)+E24 -> 0.15141728 | F26: PBV = (ROE - g) / (Cost of equity - g)

Sheet Data
D2: AED Millions
B3: Interest & similar Income | D3: 21 | E3: 22 | F3: 23 | G3: 24 | H3: 25 | L3: To find cost of equity
B4: Loans and receivables to customers | D4: 20682.642 | E4: 24185 | F4: 35568 | G4: 47380 | H4: 50236
B5: Loans and receivables to banks | D5: 544.387 | E5: 1337 | F5: 6431 | G5: 11661 | H5: 9736 | L5: 1. Comparable comps of all the banks near to market cap
B6: Investment securities at FVOCI | D6: 1140.994 | E6: 2952 | F6: 2990 | G6: 3133 | H6: 3393 | L6: 2. Find median price to book ratio
B7: Trading securities at amortised cost | D7: 975.134 | E7: 1577 | F7: 3487 | G7: 4141 | H7: 3814 | L7: 3. Find median return on equity for big banks
B8: Trading securities & designated at | D8: 148.034 | E8: 136 | F8: 209 | G8: 591 | H8: 933 | L8: 4. Expected growth rate in perpetuity (set it to risk free rate)
B9: FVPTL invesetment securities | L9: PBV = (ROE-g) / (Cost of equity - g)
B10: Others | D10: 172.318 | E10: 592 | F10: 1346 | G10: 2223 | H10: 2780
D11: =SUM(D4:D10) -> 23663.509 | E11: =SUM(E4:E10) -> 30779 | F11: =SUM(F4:F10) -> 50031 | G11: =SUM(G4:G10) -> 69129 | H11: =SUM(H4:H10) -> 70892 | L11: Dividend Discount model
B12: Interest & similar expense
B13: Deposits from customers | D13: -5702.153 | E13: -7085 | F13: -19265 | G13: -34814 | H13: -34474 | L13: Expected growth in EPS = ROE x (1-Dividend Payout Ratio)
B14: Borrowings from banks & financial institutions | D14: -639.311 | E14: -974 | F14: -1622 | G14: -2088 | H14: -4159
B15: Debt issued & borrowed funds | D15: -2408.283 | E15: -2656 | F15: -4140 | G15: -5443 | H15: -3441 | L15: After year 5 expected perpetuity growth rate is reduced to stable rate
B16: Others | D16: -179.97 | E16: -163 | F16: -212 | G16: -415 | H16: -411 | L16: Payout ratio = 1 - Stable rate / ROE
D17: =SUM(D13:D16) -> -8929.717 | E17: =SUM(E13:E16) -> -10878 | F17: =SUM(F13:F16) -> -25239 | G17: =SUM(G13:G16) -> -42760 | H17: =SUM(H13:H16) -> -42485
L18: Terminal value = (Net income at year 6 x Stable payout) / (Cost of equity - Expected growth rate)
B19: Income from Islamic financing & Investment products
B20: Murabaha | D20: 1273.602 | E20: 1946 | F20: 3559 | G20: 4153 | H20: 4826 | L20: FCFE
B21: Ijara | D21: 595.96 | E21: 853 | F21: 1459 | G21: 1544 | H21: 1732
B22: Others | D22: =40.1199+912.248 -> 952.3679 | E22: 1260 | F22: 2270 | G22: 3306 | H22: 4525 | L22: Risk adjusted assets
D23: =SUM(D20:D22) -> 2821.9299 | E23: =SUM(E20:E22) -> 4059 | F23: =SUM(F20:F22) -> 7288 | G23: =SUM(G20:G22) -> 9003 | H23: =SUM(H20:H22) -> 11083 | L23: Tier 1 Capital
L24: Change in regulatory Capital (Tier 1)
B25: Distribution on Islamic deposits | L25: Book equity
B26: Distribution to depositors | D26: 537.834 | E26: 664 | F26: 1885 | G26: 2761 | H26: 3588
B27: Profit paid to sukuk holders | D27: 93.407 | E27: 74 | F27: 115 | G27: 215 | H27: 400 | L27: FCFE = Net income - Investment in regulatory capital
B28: Total | D28: =SUM(D26:D27) -> 631.241 | E28: =SUM(E26:E27) -> 738 | F28: =SUM(F26:F27) -> 2000 | G28: =SUM(G26:G27) -> 2976 | H28: =SUM(H26:H27) -> 3988
B31: Net fee and commission income
B32: Fee income | D32: 5304.812 | E32: 5878 | F32: 7581 | G32: 11716 | H32: 13696
B33: Commission income on trade finance products / services | D33: 831.195 | E33: 878 | F33: 1074 | G33: 1170 | H33: 1455
B34: Portfolio and other management fees | D34: 276.564 | E34: 54 | F34: 69 | G34: 385 | H34: 519
B35: Brokerage fees | D35: 62.474 | E35: 194 | F35: 235 | G35: 76 | H35: 68
B36: Total fee and commission income | D36: =SUM(D32:D35) -> 6475.045 | E36: =SUM(E32:E35) -> 7004 | F36: =SUM(F32:F35) -> 8959 | G36: =SUM(G32:G35) -> 13347 | H36: =SUM(H32:H35) -> 15738
B37: Fee and commission expense | D37: -2639.234 | E37: -2923 | F37: -4086 | G37: -6554 | H37: -7706
B38: Net | D38: =SUM(D36:D37) -> 3835.811 | E38: =SUM(E36:E37) -> 4081 | F38: =SUM(F36:F37) -> 4873 | G38: =SUM(G36:G37) -> 6793 | H38: =SUM(H36:H37) -> 8032
B41: Overview
B42: The valuation is done for Emirates NBD (Ticker: ENBD), which is a public joint stock company (PJSC) in the United Arab Emirates.
B43: The market cap for the stock is currently AED 174 Billion. Emirates NBD is recogonised as the 2nd largest bank of UAE.
B44: The stock price is currently trading between AED 26.20 to AED 27.55.
B46: Valutation Thesis
B47: The valuation is conducted using the dividend discount model and the free cash flow to equity model.
B48: The explicit forecast period is 5 years.
B50: The DDM is used to evalute banks, becasue money is inventory, not a capital expenditure. Therefore, traditional FCF formulas
B51: (operating cash flow minus capital expenditures) do not work, as it is hard to distinguish a bank's operating, investing, and financing activities.
B53: Since banks are constrained by regulatory capital requirements (e.g., Basel III), the Free Cash Flow to Equity (FCFE)
B54: is best represented by the dividends they are allowed to pay out after satisfying those capital constraints.
B56: Banks and financial institutions often have more stable, predictable, and long-term dividend payout policies compared to other industries,
... B79: The present value of equity is found by summing the present value of FCFE and the present value of terminal value.
