Workbook
Name BS: Financials!$B$47
Name CF: Financials!$B$101
Name days: Dashboard!$G$18
Name EF: Scenario!$B$45
Name IS: Financials!$B$13
Name PPE: Schedule!$B$10
Name RE: Schedule!$B$99
Name RF: Scenario!$B$17
Name tgr: DCF!$E$19
Name wacc: DCF!$E$18
Name WC: Schedule!$B$58

Sheet Dashboard
C2: Infosys Ltd.
C3: Dashboard
C4: (In ₹ Crore, except equity share and per equity share data)
B6: # | C6: Model Assumption
C8: Company Name: | G8: =C2 -> Infosys Ltd. | I8: Val.Using Free Cash Flow to Firm
C9: Ticker: | G9: INFY
C10: Sector: | G10: IT - Software & Consulting | I10: Current Share Price: | L10: 1280
I11: Implied Share Price: | L11: =DCF!G41 -> 1078.4773
C12: Selected Scenario | G12: Street | I12: Δ Price %: | L12: =L10/L11-1 -> 0.18685853
C13: Selected Scenario for Adoption of AI | G13: Low AI Impact
C15: Model Start Date | G15: =Financials!I6 -> 45747 | I15: Key Financial Metrices | L15: 45747 | M15: 46112 | N15: 46477
C16: Model End Date | G16: =Financials!N6 -> 47573 | I16: Gross Margin % | L16: ='Ratio Analysis'!H9 -> 0.25713428 | M16: ='Ratio Analysis'!I9 -> 0.2426101 | N16: ='Ratio Analysis'!J9 -> 0.23696325
C17: No. of Years Projected | G17: =YEARFRAC(G15,G16,1) -> 5.0004564 | I17: EBITDA Margin % | L17: ='Ratio Analysis'!H10 -> 0.22575185 | M17: ='Ratio Analysis'!I10 -> 0.23365543 | N17: ='Ratio Analysis'!J10 -> 0.2261837
C18: Days in an Year | G18: 365 | I18: Net Profit Margin % | L18: ='Ratio Analysis'!H12 -> 0.16057386 | M18: ='Ratio Analysis'!I12 -> 0.1635588 | N18: ='Ratio Analysis'!J12 -> 0.15832859
I19: ROE % | L19: ='Ratio Analysis'!H13 -> 0.27805786 | M19: ='Ratio Analysis'!I13 -> 0.26471995 | N19: ='Ratio Analysis'!J13 -> 0.27490185
B20: # | C20: Table of Contents | I20: ROCE % | L20: ='Ratio Analysis'!H15 -> 0.35461515 | M20: ='Ratio Analysis'!I15 -> 0.34452036 | N20: ='Ratio Analysis'!J15 -> 0.35752474
C21: Sl.No | D21: Particulars | I21: ROIC % | L21: ='Ratio Analysis'!H16 -> 0.67898483 | M21: ='Ratio Analysis'!I16 -> 0.6964309 | N21: ='Ratio Analysis'!J16 -> 0.67620646
C22: 1 | D22: Dashboard | I22: Asset Turnover | L22: ='Ratio Analysis'!H27 -> 1.118782 | M22: ='Ratio Analysis'!I27 -> 1.0666473 | N22: ='Ratio Analysis'!J27 -> 1.1224262
C23: 2 | D23: Equity Report | I23: Debt to Equity | L23: ='Ratio Analysis'!H37 -> 0.085517084 | M23: ='Ratio Analysis'!I37 -> 0.07673462 | N23: ='Ratio Analysis'!J37 -> 0.077851049
C24: 3 | D24: Financials
C25: 4 | D25: Scenario
C26: 5 | D26: Assumptions
C27: 6 | D27: Schedule
C28: 7 | D28: DCF
C29: 8 | D29: WACC
C30: 9 | D30: Beta
C31: 10 | D31: Comps
C32: 11 | D32: Ratio Analysis
C33: 12 | D33: Analysis

Sheet Equity_report
C2: =Dashboard!C2 -> Infosys Ltd.
C3: Equity Report
C4: =Dashboard!C4 -> (In ₹ Crore, except equity share and per equity share data)
C5: (Disclaimer - The valuation analysis is conducted only for educational purposes, not as a recommendation to buy/sell stock and securities.)
B7: # | C7: Overview
C8: Infosys Ltd (Ticker: INFY) provides consulting, technology, outsourcing and next-generation digital services to enable clients to execute strategies for their digital transformation.
C9: It is the 2nd largest Information Technology company in India behind TCS. Its market cap currently is around ₹ 5,21,813 Cr. And it's share price is around ₹ 1280.00.
B12: # | C12: Investment Thesis
C13: This report presents a fundamental valuation analysis of Infosys Limited, conducted through a structured three-statement financial model and a Free Cash Flow to Firm (FCFF) framework.
C14: The objective is to determine the intrinsic value of the stock through an explicit five-year forecast period, underpinned by scenario-based assumptions.
B16: # | C16: Forecasting Methodology
C17: Revenue and expense line items are projected across three distinct scenarios — Best Case, Street Consensus, and Worst Case — to capture the range of plausible operating outcomes.
C18: A distinguishing feature of this analysis is the explicit incorporation of Artificial Intelligence (AI) adoption as a value driver within the scenario framework. AI-related expenses are modelled
C19: separately for each scenario, with each outcome reflecting a different trajectory of AI integration by the company — from conservative adoption to an accelerated AI-led operating model.
C20: Revenue forecasts and cost assumptions in each scenario are calibrated to real-world developments, including management commentary, sector tailwinds, and observable AI productivity
C21: gains within the IT services industry. All remaining line items — those not directly classified as revenue or operating expenses — are projected using standard financial modelling
C22: conventions and general assumptions.
B24: # | C24: Discount Rate
C25: The Weighted Average Cost of Capital (WACC) is computed as:
C26: WACC = Ke × [E / (E + D)] + Kd × [D / (E + D)]
C28: The cost of equity (Ke) is derived using the Capital Asset Pricing Model (CAPM): Ke = Rf + β × (Rm − Rf), where the risk-free rate (Rf) represents the prevailing 10-year Indian Government
C29: Bond yield, and the market return (Rm) is estimated as the Compounded Annual Growth Rate (CAGR) of the Nifty 50 index.
C30: Beta is estimated through a regression of Infosys stock returns against the Nifty 50, utilising historical price data spanning from December 1995 to March 2026 — the full period since the
C31: inception of the National Stock Exchange — to ensure statistical robustness. The raw beta is subsequently adjusted using the Blume adjustment formula:
C32: Adjusted Beta = (Raw Beta × w₁) + (Market Beta × w₂), where the market beta is set to 1.0.
C34: The cost of debt (Kd) is derived from the company's prevailing credit ratings: CRISIL AAA/Stable/A1+ (domestic), Moody's A3/Stable, and S&P A−. The default spread corresponding to a
C35: CRISIL AAA rating — sourced from Aswath Damodaran's ratings and default spread framework for large non-financial service firms — is applied at 40 basis points. It is noted that at the
C36: time of this valuation, Infosys carries no net financial debt; accordingly, the capital structure reflects an equity-dominant weighting. Scenario-specific WACC assumptions and a terminal
C37: growth rate ranging from 3% to 6% — consistent with long-term growth expectations for Indian IT services companies — are applied independently across each of the three scenarios.
B39: # | C39: Valuation
C40: Intrinsic value is determined by discounting projected free cash flows to the firm at the scenario-specific WACC, deriving the present value of equity, and computing the implied value per share.
C41: A Football Field analysis is subsequently employed to consolidate the valuation outputs across all scenarios and methodologies, providing a visual representation of the fair value range and
C42: contextualising the stock's current market price relative to its estimated intrinsic value.
B45: # | C45: Football Field Analysis
C46: Metrices | E46: 25th Percentile | F46: Median | G46: 75th Percentile
C47: Company Comparables:
C48: Current Share Price | E48: =Comps!E24 -> 675.25 | F48: =Comps!E22 -> 1401.9 | G48: =Comps!E23 -> 2409
C49: EV / Rev | E49: {=TRANSPOSE(Comps!K37:N37)} -> 253.0575 | F49: {=TRANSPOSE(Comps!K35:N35)} -> 701.11369 | G49: {=TRANSPOSE(Comps!K36:N36)} -> 287.94447
C50: EV / EBITDA | E50: 264.64867 | F50: 843.36799 | G50: 413.15752
C51: P / Sales | E51: 925.45347 | F51: 793.69399 | G51: 701.01715
C52: P / E | E52: 778.04435 | F52: 595.6152 | G52: 468.89266
C54: Using DCF:
C55: Street | E55: =DCF!D86 -> 969.32715 | F55: =DCF!D84 -> 1115.2321 | G55: =DCF!D85 -> 1333.3568
C56: Best | E56: =DCF!L86 -> 1113.1404 | F56: =DCF!L84 -> 1286.3383 | G56: =DCF!L85 -> 1540.9986
C57: Worst | E57: =DCF!T86 -> 832.70447 | F57: =DCF!T84 -> 946.97005 | G57: =DCF!T85 -> 1122.7222
C59: 52-Week Share Price | E59: =Beta!P12 -> 1472.775 | F59: =Beta!P10 -> 1534.55 | G59: =Beta!P11 -> 1594.0125

Sheet Financials->

Sheet Financials
B2: =Dashboard!C2 -> Infosys Ltd.
B3: Financial statements
B4: =Dashboard!C4 -> (In ₹ Crore, except equity share and per equity share data)
B5: Actual / Forecast | F5: Actuals | J5: Forecast | O5: CAGR | Q5: Notes
B6: Date / Year | F6: 44651 | G6: =EDATE(F6,12) -> 45016 | H6: =EDATE(G6,12) -> 45382 | I6: =EDATE(H6,12) -> 45747 | J6: =EDATE(I6,12) -> 46112 | K6: =EDATE(J6,12) -> 46477 | L6: =EDATE(K6,12) -> 46843 | M6: =EDATE(L6,12) -> 47208 | N6: =EDATE(M6,12) -> 47573 | O6: 22A - 25A | P6: 25A - 30E
B8: <-Back to dashboard
B10: Templete: | C10: Standard | E10: Currency: | F10: INR | H10: Source: | I10: Company Website
B11: Period type: | C11: Annual | E11: Units: | F11: Crore | H11: Decimals: | I11: Default
A13: # | B13: Income statement | F13: 44651 | G13: =EDATE(F13,12) -> 45016 | H13: =EDATE(G13,12) -> 45382 | I13: =EDATE(H13,12) -> 45747 | J13: =EDATE(I13,12) -> 46112 | K13: =EDATE(J13,12) -> 46477 | L13: =EDATE(K13,12) -> 46843 | M13: =EDATE(L13,12) -> 47208 | N13: =EDATE(M13,12) -> 47573
B15: Revenue from operations | F15: 121641 | G15: 146767 | H15: 153670 | I15: 162990 | J15: =Scenario!J24 -> 169706.35 | K15: =Scenario!K24 -> 179444.66 | L15: =Scenario!L24 -> 190694.57 | M15: =Scenario!M24 -> 203696.63 | N15: =Scenario!N24 -> 218358.89 | O15: =_xlfn.RRI(4,F15,I15) -> 0.07589588 | P15: =_xlfn.RRI(5,J15,N15) -> 0.051706504
B16: Other income, net | F16: 2295 | G16: 2701 | H16: 4711 | I16: 3600 | J16: =Assumptions!K12 -> 3818.9935 | K16: =Assumptions!L12 -> 4038.1401 | L16: =Assumptions!M12 -> 4291.3029 | M16: =Assumptions!N12 -> 4583.8952 | N16: =Assumptions!O12 -> 4913.848 | O16: =_xlfn.RRI(4,F16,I16) -> 0.11912849 | P16: =_xlfn.RRI(5,J16,N16) -> 0.051706504
B17: Total Revenue | F17: =SUM(F15:F16) -> 123936 | G17: =SUM(G15:G16) -> 149468 | H17: =SUM(H15:H16) -> 158381 | I17: =SUM(I15:I16) -> 166590 | J17: =SUM(J15:J16) -> 173525.34 | K17: =SUM(K15:K16) -> 183482.8 | L17: =SUM(L15:L16) -> 194985.87 | M17: =SUM(M15:M16) -> 208280.52 | N17: =SUM(N15:N16) -> 223272.74 | O17: =_xlfn.RRI(4,F17,I17) -> 0.076744999 | P17: =_xlfn.RRI(5,J17,N17) -> 0.051706504
B19: Employee benefit expenses | F19: 63986 | G19: 78359 | H19: 82620 | I19: 85950 | J19: =Scenario!J52 -> 89559.9 | K19: =Scenario!K52 -> 93455.756 | L19: =Scenario!L52 -> 97661.265 | M19: =Scenario!M52 -> 102202.51 | N19: =Scenario!N52 -> 107108.23 | O19: =_xlfn.RRI(4,F19,I19) -> 0.076564934 | P19: =_xlfn.RRI(5,J19,N19) -> 0.036434478
B20: Cost of technical sub-contractors | F20: 12606 | G20: 14062 | H20: 12232 | I20: 12937 | J20: =Scenario!J90 -> 13713.22 | K20: =Scenario!K90 -> 14577.153 | L20: =Scenario!L90 -> 15539.245 | M20: =Scenario!M90 -> 16611.453 | N20: =Scenario!N90 -> 17807.477 | O20: =_xlfn.RRI(4,F20,I20) -> 0.0065006712 | P20: =_xlfn.RRI(5,J20,N20) -> 0.05364083
B21: Travel expenses | F21: 827 | G21: 1525 | H21: 1759 | I21: 1894 | J21: =Scenario!J91 -> 2045.52 | K21: =Scenario!K91 -> 2219.3892 | L21: =Scenario!L91 -> 2419.1342 | M21: =Scenario!M91 -> 2648.952 | N21: =Scenario!N91 -> 2913.8472 | O21: =_xlfn.RRI(4,F21,I21) -> 0.23017987 | P21: =_xlfn.RRI(5,J21,N21) -> 0.073328369
B22: Cost of software packages and others | F22: 6811 | G22: 10902 | H22: 13515 | I22: 15911 | J22: =Scenario!J62 -> 18774.98 | K22: =Scenario!K62 -> 22098.151 | L22: =Scenario!L62 -> 25943.23 | M22: =Scenario!M62 -> 30379.522 | N22: =Scenario!N62 -> 35483.282 | O22: =_xlfn.RRI(4,F22,I22) -> 0.23629368 | P22: =_xlfn.RRI(5,J22,N22) -> 0.13576599
B23: Communication expenses | F23: 611 | G23: 713 | H23: 677 | I23: 620 | J23: =Scenario!J92 -> 570.4 | K23: =Scenario!K92 -> 529.046 | L23: =Scenario!L92 -> 494.65801 | M23: =Scenario!M92 -> 466.21517 | N23: =Scenario!N92 -> 442.90442 | O23: =_xlfn.RRI(4,F23,I23) -> 0.0036623197 | P23: =_xlfn.RRI(5,J23,N23) -> -0.049338079
B24: Consultancy and professional charges | F24: 1885 | G24: 1684 | H24: 1726 | I24: 1655 | J24: =Scenario!J93 -> 1688.1 | K24: =Scenario!K93 -> 1728.1924 | L24: =Scenario!L93 -> 1775.7177 | M24: =Scenario!M93 -> 1831.2088 | N24: =Scenario!N93 -> 1895.3012 | O24: =_xlfn.RRI(4,F24,I24) -> -0.032008239 | P24: =_xlfn.RRI(5,J24,N24) -> 0.023424976
B25: Depreciation and amortisation expenses | F25: 3476 | G25: 4225 | H25: 4678 | I25: 4812 | J25: =Schedule!K37+Schedule!K32 -> 1553.8619 | K25: =Schedule!L37+Schedule!L32 -> 1977.8622 | L25: =Schedule!M37+Schedule!M32 -> 2339.7887 | M25: =Schedule!N37+Schedule!N32 -> 2829.4995 | N25: =Schedule!O37+Schedule!O32 -> 3356.1537 | O25: =_xlfn.RRI(4,F25,I25) -> 0.084704552 | P25: =_xlfn.RRI(5,J25,N25) -> 0.16650307
B26: Finance cost | F26: 200 | G26: 284 | H26: 470 | I26: 416 | J26: 0 | K26: 0 | L26: 0 | M26: 0 | N26: 0 | O26: =_xlfn.RRI(4,F26,I26) -> 0.20092486 | P26: =_xlfn.RRI(5,J26,N26) -> 0
B27: Other expenses | F27: 3424 | G27: 4392 | H27: 4716 | I27: 4787 | J27: =Scenario!J82 -> 5074.22 | K27: =Scenario!K82 -> 5396.433 | L27: =Scenario!L82 -> 5757.994 | M27: =Scenario!M82 -> 6163.9326 | N27: =Scenario!N82 -> 6620.0636 | O27: =_xlfn.RRI(4,F27,I27) -> 0.087382697 | P27: =_xlfn.RRI(5,J27,N27) -> 0.054626241
B28: Total Expenses | F28: =SUM(F19:F27) -> 93826 | G28: =SUM(G19:G27) -> 116146 | H28: =SUM(H19:H27) -> 122393 | I28: =SUM(I19:I27) -> 128982 | J28: =SUM(J19:J27) -> 132980.2 | K28: =SUM(K19:K27) -> 141981.98 | L28: =SUM(L19:L27) -> 151931.03 | M28: =SUM(M19:M27) -> 163133.3 | N28: =SUM(N19:N27) -> 175627.26 | O28: =_xlfn.RRI(4,F28,I28) -> 0.082808051 | P28: =_xlfn.RRI(5,J28,N28) -> 0.057209335
B30: Profit before tax | F30: =F17-F28 -> 30110 | G30: =G17-G28 -> 33322 | H30: =H17-H28 -> 35988 | I30: =I17-I28 -> 37608 | J30: =J17-J28 -> 40545.138 | K30: =K17-K28 -> 41500.818 | L30: =L17-L28 -> 43054.843 | M30: =M17-M28 -> 45147.228 | N30: =N17-N28 -> 47645.476 | O30: =_xlfn.RRI(4,F30,I30) -> 0.057164013 | P30: =_xlfn.RRI(5,J30,N30) -> 0.032800831
B32: Current tax | F32: 7811 | G32: 9287 | H32: 8390 | I32: 12130 | J32: =Assumptions!K15 -> 12163.541 | K32: =Assumptions!L15 -> 12450.245 | L32: =Assumptions!M15 -> 12916.453 | M32: =Assumptions!N15 -> 13544.169 | N32: =Assumptions!O15 -> 14293.643 | O32: =_xlfn.RRI(4,F32,I32) -> 0.11631958 | P32: =_xlfn.RRI(5,J32,N32) -> 0.032800831
B33: Deferred tax | F33: 153 | G33: -73 | H33: 1350 | I33: -1272 | J33: 0 | K33: 0 | L33: 0 | M33: 0 | N33: 0
B34: Profit for the year | F34: =F30-SUM(F32:F33) -> 22146 | G34: =G30-SUM(G32:G33) -> 24108 | H34: =H30-SUM(H32:H33) -> 26248 | I34: =I30-SUM(I32:I33) -> 26750 | J34: =J30-SUM(J32:J33) -> 28381.596 | K34: =K30-SUM(K32:K33) -> 29050.573 | L34: =L30-SUM(L32:L33) -> 30138.39 | M34: =M30-SUM(M32:M33) -> 31603.06 | N34: =N30-SUM(N32:N33) -> 33351.833 | O34: =_xlfn.RRI(4,F34,I34) -> 0.048351987 | P34: =_xlfn.RRI(5,J34,N34) -> 0.032800831
B36: Profit attributable to:
B37: Owners of the company | F37: 22110 | G37: 24095 | H37: 26233 | I37: 26713 | J37: =J34-J38 -> 28352.367 | K37: =K34-K38 -> 29020.654 | L37: =L34-L38 -> 30107.351 | M37: =M34-M38 -> 31570.513 | N37: =N34-N38 -> 33317.485
B38: Non-controlling interests | F38: 36 | G38: 13 | H38: 15 | I38: 37 | J38: =Assumptions!K18 -> 29.229252 | K38: =Assumptions!L18 -> 29.918208 | L38: =Assumptions!M18 -> 31.038514 | M38: =Assumptions!N18 -> 32.546929 | N38: =Assumptions!O18 -> 34.347932
B40: Equity per share:
B41: Basic (₹) | F41: =F37/F44 -> 52.52347 | G41: =G37/G44 -> 57.631162 | H41: =H37/H44 -> 63.386658 | I41: =I37/I44 -> 64.499045 | J41: =J37/J44 -> 68.457327 | K41: =K37/K44 -> 70.07092 | L41: =L37/L44 -> 72.69477 | M41: =M37/M44 -> 76.227601 | N41: =N37/N44 -> 80.4457 | O41: =_xlfn.RRI(4,F41,I41) -> 0.052688717 | P41: =_xlfn.RRI(5,J41,N41) -> 0.032800831
B43: Weighted average equity shares:
B44: Basic (in shares) | F44: 420.95467 | G44: 418.08979 | H44: 413.85681 | I44: 414.16117 | J44: =I44 -> 414.16117 | K44: =J44 -> 414.16117 | L44: =K44 -> 414.16117 | M44: =L44 -> 414.16117 | N44: =M44 -> 414.16117
A47: # | B47: Balance sheet | F47: 44651 | G47: =EDATE(F47,12) -> 45016 | H47: =EDATE(G47,12) -> 45382 | I47: =EDATE(H47,12) -> 45747 | J47: =EDATE(I47,12) -> 46112 | K47: =EDATE(J47,12) -> 46477 | L47: =EDATE(K47,12) -> 46843 | M47: =EDATE(L47,12) -> 47208 | N47: =EDATE(M47,12) -> 47573
B49: Non-current assets
B50: Property, plant and equipment | F50: 13075 | G50: 13346 | H50: 12370 | I50: 11778 | J50: =Schedule!K47 -> 12737.447 | K50: =Schedule!L47 -> 13376.667 | L50: =Schedule!M47 -> 14157.525 | M50: =Schedule!N47 -> 14997.931 | N50: =Schedule!O47 -> 15860.939
B51: Right of use assets | F51: 4823 | G51: 6882 | H51: 6552 | I51: 6311 | J51: =I51 -> 6311 | K51: =J51 -> 6311 | L51: =K51 -> 6311 | M51: =L51 -> 6311 | N51: =M51 -> 6311
B52: Capital work-in progress | F52: 416 | G52: 288 | H52: 293 | I52: 814 | J52: =I52-Schedule!K18 -> 238 | K52: =J52-Schedule!L18 -> 34 | L52: =K52-Schedule!M18 -> 12 | M52: =L52-Schedule!N18 -> 0 | N52: =M52-Schedule!O18 -> 0
B53: Goodwill | F53: 6195 | G53: 7248 | H53: 7303 | I53: 10106 | J53: =I53 -> 10106 | K53: =J53 -> 10106 | L53: =K53 -> 10106 | M53: =L53 -> 10106 | N53: =M53 -> 10106
B54: Other intangible assets | F54: 1707 | G54: 1749 | H54: 1397 | I54: 2766 | J54: =Schedule!K55 -> 2547.4684 | K54: =Schedule!L55 -> 2273.4898 | L54: =Schedule!M55 -> 2062.5655 | M54: =Schedule!N55 -> 1852.2544 | N54: =Schedule!O55 -> 1679.1169
B55: Financial assets:
B56: Invevstments | F56: 13651 | G56: 12569 | H56: 11708 | I56: 11059 | J56: =I56 -> 11059 | K56: =J56 -> 11059 | L56: =K56 -> 11059 | M56: =L56 -> 11059 | N56: =M56 -> 11059
B57: Loans | F57: 34 | G57: 39 | H57: 34 | I57: 16 | J57: =I57 -> 16 | K57: =J57 -> 16 | L57: =K57 -> 16 | M57: =L57 -> 16 | N57: =M57 -> 16
B58: Other financial assets | F58: 1460 | G58: 2798 | H58: 3105 | I58: 3511 | J58: =Schedule!K93 -> 3089.2324 | K58: =Schedule!L93 -> 3544.681 | L58: =Schedule!M93 -> 3799.7729 | M58: =Schedule!N93 -> 4044.6093 | N58: =Schedule!O93 -> 4243.7517
B59: Deferred tax assets (net) | F59: 1212 | G59: 1245 | H59: 454 | I59: 1108 | J59: =I59 -> 1108 | K59: =J59 -> 1108 | L59: =K59 -> 1108 | M59: =L59 -> 1108 | N59: =M59 -> 1108
B60: Income tax assets (net) | F60: 6098 | G60: 6453 | H60: 3045 | I60: 1622 | J60: =I60 -> 1622 | K60: =J60 -> 1622 | L60: =K60 -> 1622 | M60: =L60 -> 1622 | N60: =M60 -> 1622
B61: Other non-current assets | F61: 2029 | G61: 2318 | H61: 2121 | I61: 2713 | J61: =Schedule!K94 -> 2669.5431 | K61: =Schedule!L94 -> 2780.1184 | L61: =Schedule!M94 -> 2940.07 | M61: =Schedule!N94 -> 3222.794 | N61: =Schedule!O94 -> 3409.8105
B62: Total non-current assets | F62: =SUM(F50:F61) -> 50700 | G62: =SUM(G50:G61) -> 54935 | H62: =SUM(H50:H61) -> 48382 | I62: =SUM(I50:I61) -> 51804 | J62: =SUM(J50:J61) -> 51503.691 | K62: =SUM(K50:K61) -> 52230.956 | L62: =SUM(L50:L61) -> 53193.933 | M62: =SUM(M50:M61) -> 54339.588 | N62: =SUM(N50:N61) -> 55415.618
B63: Current Assets
B64: Financial assets:
B65: Invevstments | F65: 6673 | G65: 6909 | H65: 12915 | I65: 12482 | J65: =I65 -> 12482 | K65: =J65 -> 12482 | L65: =K65 -> 12482 | M65: =L65 -> 12482 | N65: =M65 -> 12482
B66: Trade receivables | F66: 22698 | G66: 25424 | H66: 30193 | I66: 31158 | J66: =Schedule!K61 -> 32441.931 | K66: =Schedule!L61 -> 34303.557 | L66: =Schedule!M61 -> 36454.147 | M66: =Schedule!N61 -> 38939.687 | N66: =Schedule!O61 -> 41742.6
B67: Cash and cash equivalents | F67: 17472 | G67: 12173 | H67: 14786 | I67: 24455 | J67: =J136 -> 36189.021 | K67: =K136 -> 32846.686 | L67: =L136 -> 41677.884 | M67: =M136 -> 50036.362 | N67: =N136 -> 49244.756
B68: Loans | F68: 248 | G68: 289 | H68: 248 | I68: 249 | J68: =I68 -> 249 | K68: =J68 -> 249 | L68: =K68 -> 249 | M68: =L68 -> 249 | N68: =M68 -> 249
B69: Other financial assets | F69: 8727 | G69: 11604 | H69: 12085 | I69: 13840 | J69: =Schedule!K62 -> 14410.306 | K69: =Schedule!L62 -> 15237.218 | L69: =Schedule!M62 -> 16192.483 | M69: =Schedule!N62 -> 17296.53 | N69: =Schedule!O62 -> 18541.549
B70: Income tax assets (net) | F70: 54 | G70: 6 | H70: 6397 | I70: 2975 | J70: =I70 -> 2975 | K70: =J70 -> 2975 | L70: =K70 -> 2975 | M70: =L70 -> 2975 | N70: =M70 -> 2975
B71: Other current assets | F71: 11313 | G71: 14476 | H71: 12808 | I71: 11940 | J71: =Schedule!K63 -> 12432.013 | K71: =Schedule!L63 -> 13145.403 | L71: =Schedule!M63 -> 13969.527 | M71: =Schedule!N63 -> 14922.006 | N71: =Schedule!O63 -> 15996.105
B72: Total current assets | F72: =SUM(F65:F71) -> 67185 | G72: =SUM(G65:G71) -> 70881 | H72: =SUM(H65:H71) -> 89432 | I72: =SUM(I65:I71) -> 97099 | J72: =SUM(J65:J71) -> 111179.27 | K72: =SUM(K65:K71) -> 111238.86 | L72: =SUM(L65:L71) -> 124000.04 | M72: =SUM(M65:M71) -> 136900.58 | N72: =SUM(N65:N71) -> 141231.01
B73: Total assets | F73: =F72+F62 -> 117885 | G73: =G72+G62 -> 125816 | H73: =H72+H62 -> 137814 | I73: =I72+I62 -> 148903 | J73: =J72+J62 -> 162682.96 | K73: =K72+K62 -> 163469.82 | L73: =L72+L62 -> 177193.98 | M73: =M72+M62 -> 191240.17 | N73: =N72+N62 -> 196646.63
B75: Equity
B76: Equity share capital | F76: 2098 | G76: 2069 | H76: 2071 | I76: 2073 | J76: =I76 -> 2073 | K76: =J76 -> 2073 | L76: =K76 -> 2073 | M76: =L76 -> 2073 | N76: =M76 -> 2073
B77: Other equity | F77: 73252 | G77: 73338 | H77: 86045 | I77: 93745 | J77: =Schedule!K104 -> 104726.44 | K77: =Schedule!L104 -> 103159.01 | L77: =Schedule!M104 -> 114057.64 | M77: =Schedule!N104 -> 124860.02 | N77: =Schedule!O104 -> 126589.17
B78: Non-controlling interests | F78: 386 | G78: 388 | H78: 345 | I78: 385 | J78: =I78+J38 -> 414.22925 | K78: =J78+K38 -> 444.14746 | L78: =K78+L38 -> 475.18597 | M78: =L78+M38 -> 507.7329 | N78: =M78+N38 -> 542.08083
B79: Total equity | F79: =SUM(F76:F78) -> 75736 | G79: =SUM(G76:G78) -> 75795 | H79: =SUM(H76:H78) -> 88461 | I79: =SUM(I76:I78) -> 96203 | J79: =SUM(J76:J78) -> 107213.67 | K79: =SUM(K76:K78) -> 105676.16 | L79: =SUM(L76:L78) -> 116605.82 | M79: =SUM(M76:M78) -> 127440.75 | N79: =SUM(N76:N78) -> 129204.25
B80: Non-current liabilities
B81: Financial liabilities:
B82: Lease liabilities | F82: 4602 | G82: 7057 | H82: 6400 | I82: 5772 | J82: =I82 -> 5772 | K82: =J82 -> 5772 | L82: =K82 -> 5772 | M82: =L82 -> 5772 | N82: =M82 -> 5772
B83: Other financial liabilities | F83: 2337 | G83: 2058 | H83: 2130 | I83: 2141 | J83: =Schedule!K86 -> 2555.4018 | K83: =Schedule!L86 -> 2515.6642 | L83: =Schedule!M86 -> 2673.2326 | M83: =Schedule!N86 -> 2863.5226 | N83: =Schedule!O86 -> 3119.9736
B84: Deferred tax liabilities (net) | F84: 1156 | G84: 1220 | H84: 1794 | I84: 1722 | J84: =I84 -> 1722 | K84: =J84 -> 1722 | L84: =K84 -> 1722 | M84: =L84 -> 1722 | N84: =M84 -> 1722
B85: Other non-current liabilities | F85: 451 | G85: 500 | H85: 235 | I85: 215 | J85: =Schedule!K87 -> 422.68514 | K85: =Schedule!L87 -> 392.34661 | L85: =Schedule!M87 -> 358.76728 | M85: =Schedule!N87 -> 401.16041 | N85: =Schedule!O87 -> 465.53609
B86: Total non-current liabilities | F86: =SUM(F82:F85) -> 8546 | G86: =SUM(G82:G85) -> 10835 | H86: =SUM(H82:H85) -> 10559 | I86: =SUM(I82:I85) -> 9850 | J86: =SUM(J82:J85) -> 10472.087 | K86: =SUM(K82:K85) -> 10402.011 | L86: =SUM(L82:L85) -> 10526 | M86: =SUM(M82:M85) -> 10758.683 | N86: =SUM(N82:N85) -> 11079.51
B87: Current liabilities
B88: Financial liabilities:
B89: Lease liabilities | F89: 872 | G89: 1242 | H89: 1959 | I89: 2455 | J89: =I89 -> 2455 | K89: =J89 -> 2455 | L89: =K89 -> 2455 | M89: =L89 -> 2455 | N89: =M89 -> 2455
B90: Trade payables | F90: 4134 | G90: 3865 | H90: 3956 | I90: 4164 | J90: =Schedule!K67 -> 4426.4527 | K90: =Schedule!L67 -> 4719.1243 | L90: =Schedule!M67 -> 5045.5393 | M90: =Schedule!N67 -> 5409.6107 | N90: =Schedule!O67 -> 5815.6738
B91: Other financial liabilities | F91: 15837 | G91: 18558 | H91: 16959 | I91: 18138 | J91: =Schedule!K68 -> 19281.22 | K91: =Schedule!L68 -> 20556.07 | L91: =Schedule!M68 -> 21977.904 | M91: =Schedule!N68 -> 23563.766 | N91: =Schedule!O68 -> 25332.539
B92: Other current liabilities | F92: 9178 | G92: 10830 | H92: 10539 | I92: 11765 | J92: =Schedule!K69 -> 12506.536 | K92: =Schedule!L69 -> 13333.453 | L92: =Schedule!M69 -> 14255.708 | M92: =Schedule!N69 -> 15284.359 | N92: =Schedule!O69 -> 16431.653
B93: Provisions | F93: 975 | G93: 1307 | H93: 1796 | I93: 1475 | J93: =I93 -> 1475 | K93: =J93 -> 1475 | L93: =K93 -> 1475 | M93: =L93 -> 1475 | N93: =M93 -> 1475
B94: Income tax liabilites (net) | F94: 2607 | G94: 3384 | H94: 3585 | I94: 4853 | J94: =I94 -> 4853 | K94: =J94 -> 4853 | L94: =K94 -> 4853 | M94: =L94 -> 4853 | N94: =M94 -> 4853
B95: Total current liabilities | F95: =SUM(F89:F94) -> 33603 | G95: =SUM(G89:G94) -> 39186 | H95: =SUM(H89:H94) -> 38794 | I95: =SUM(I89:I94) -> 42850 | J95: =SUM(J89:J94) -> 44997.208 | K95: =SUM(K89:K94) -> 47391.647 | L95: =SUM(L89:L94) -> 50062.152 | M95: =SUM(M89:M94) -> 53040.735 | N95: =SUM(N89:N94) -> 56362.865
B96: Total liabilities | F96: =F95+F86+F79 -> 117885 | G96: =G95+G86+G79 -> 125816 | H96: =H95+H86+H79 -> 137814 | I96: =I95+I86+I79 -> 148903 | J96: =J95+J86+J79 -> 162682.96 | K96: =K95+K86+K79 -> 163469.82 | L96: =L95+L86+L79 -> 177193.98 | M96: =M95+M86+M79 -> 191240.17 | N96: =N95+N86+N79 -> 196646.63
B98: Check | F98: =IF(F96=F73,TRUE,F73-F96) -> TRUE | G98: =IF(G96=G73,TRUE,G73-G96) -> TRUE | H98: =IF(H96=H73,TRUE,H73-H96) -> TRUE | I98: =IF(I96=I73,TRUE,I73-I96) -> TRUE | J98: =IF(J96=J73,TRUE,J73-J96) -> TRUE | K98: =IF(K96=K73,TRUE,K73-K96) -> TRUE | L98: =IF(L96=L73,TRUE,L73-L96) -> TRUE | M98: =IF(M96=M73,TRUE,M73-M96) -> TRUE | N98: =IF(N96=N73,TRUE,N73-N96) -> TRUE
A101: # | B101: Cash flow statement | F101: 44651 | G101: =EDATE(F101,12) -> 45016 | H101: =EDATE(G101,12) -> 45382 | I101: =EDATE(H101,12) -> 45747 | J101: =EDATE(I101,12) -> 46112 | K101: =EDATE(J101,12) -> 46477 | L101: =EDATE(K101,12) -> 46843 | M101: =EDATE(L101,12) -> 47208 | N101: =EDATE(M101,12) -> 47573
B103: Operating activities
B104: Net income | J104: =J34 -> 28381.596 | K104: =K34 -> 29050.573 | L104: =L34 -> 30138.39 | M104: =M34 -> 31603.06 | N104: =N34 -> 33351.833
B105: Add/Less: Non-cash items
B106: Depreciation and amortisation | J106: =J25 -> 1553.8619 | K106: =K25 -> 1977.8622 | L106: =L25 -> 2339.7887 | M106: =M25 -> 2829.4995 | N106: =N25 -> 3356.1537
B107: Changes in working capital
B108: Trade receivables | J108: =I66-J66 -> -1283.931 | K108: =J66-K66 -> -1861.6259 | L108: =K66-L66 -> -2150.5904 | M108: =L66-M66 -> -2485.5397 | N108: =M66-N66 -> -2802.9128
B109: Other financial assets | J109: =I69-J69 -> -570.30633 | K109: =J69-K69 -> -826.91131 | L109: =K69-L69 -> -955.26579 | M109: =L69-M69 -> -1104.0461 | N109: =M69-N69 -> -1245.0194
B110: Other current assets | J110: =I71-J71 -> -492.01283 | K110: =J71-K71 -> -713.39025 | L110: =K71-L71 -> -824.12381 | M110: =L71-M71 -> -952.47911 | N110: =M71-N71 -> -1074.0991
B111: Trade payables | J111: =J90-I90 -> 262.45265 | K111: =K90-J90 -> 292.67166 | L111: =L90-K90 -> 326.415 | M111: =M90-L90 -> 364.07144 | N111: =N90-M90 -> 406.06307
B112: Other financial liabilities | J112: =J91-I91 -> 1143.2196 | K112: =K91-J91 -> 1274.8507 | L112: =L91-K91 -> 1421.8336 | M112: =M91-L91 -> 1585.8616 | N112: =N91-M91 -> 1768.7733
B113: Other current liabilities | J113: =J92-I92 -> 741.53589 | K113: =K92-J92 -> 826.91692 | L113: =L92-K92 -> 922.25563 | M113: =M92-L92 -> 1028.6505 | N113: =N92-M92 -> 1147.294
B114: Cash flow from operations | J114: =SUM(J104:J113) -> 29736.416 | K114: =SUM(K104:K113) -> 30020.947 | L114: =SUM(L104:L113) -> 31218.703 | M114: =SUM(M104:M113) -> 32869.078 | N114: =SUM(N104:N113) -> 34908.086
B115: Non-controlling interests | J115: =J38 -> 29.229252 | K115: =K38 -> 29.918208 | L115: =L38 -> 31.038514 | M115: =M38 -> 32.546929 | N115: =N38 -> 34.347932
B116: Cash flow from operating activities | J116: =SUM(J114:J115) -> 29765.645 | K116: =SUM(K114:K115) -> 30050.865 | L116: =SUM(L114:L115) -> 31249.741 | M116: =SUM(M114:M115) -> 32901.625 | N116: =SUM(N114:N115) -> 34942.434
B118: Investing activites
B119: Proceeds from purchase of PPE | J119: =-Schedule!K42 -> -2796.3236 | K119: =-Schedule!L42 -> -3252.4646 | L119: =-Schedule!M42 -> -3770.5866 | M119: =-Schedule!N42 -> -4363.3148 | N119: =-Schedule!O42 -> -5037.1892
B120: Proceeds from disposal of PPE | J120: =Schedule!K44 -> 1675.3499 | K120: =Schedule!L44 -> 1808.6791 | L120: =Schedule!M44 -> 1688.9468 | M120: =Schedule!N44 -> 1848.5184 | N120: =Schedule!O44 -> 2068.0248
...

Sheet Scenario
B2: =Dashboard!C2 -> Infosys Ltd.
B3: Scenario
B4: =Dashboard!C4 -> (In ₹ Crore, except equity share and per equity share data)
B5: Date | F5: Acutals | J5: Forecast | O5: CAGR | Q5: Notes
B6: Actual / Forecast | F6: =Financials!F6 -> 44651 | G6: =EDATE(F6,12) -> 45016 | H6: =EDATE(G6,12) -> 45382 | I6: =EDATE(H6,12) -> 45747 | J6: =EDATE(I6,12) -> 46112 | K6: =EDATE(J6,12) -> 46477 | L6: =EDATE(K6,12) -> 46843 | M6: =EDATE(L6,12) -> 47208 | N6: =EDATE(M6,12) -> 47573 | O6: 22A - 25A | P6: 26E - 30E
B8: <-Back to dashboard
A10: # | B10: Assumptions
B12: Trigger | G12: Best | H12: 1 | J12: Low AI Impact | L12: 1
G13: Street | H13: 2 | J13: Moderate AI Adoption | L13: 2
B14: Selected Scenario | E14: =VLOOKUP(Dashboard!$G$12,Scenario!$G$12:$H$14,2,1) -> 2 | G14: Worst | H14: 3 | J14: High AI Adoption | L14: 3
B15: Selected Scen. for Adoption of AI | E15: =VLOOKUP(Dashboard!$G$13,Scenario!$J$12:$L$14,3,) -> 1
A17: # | B17: Revenue Forecast | F17: 44651 | G17: =EDATE(F17,12) -> 45016 | H17: =EDATE(G17,12) -> 45382 | I17: =EDATE(H17,12) -> 45747 | J17: =EDATE(I17,12) -> 46112 | K17: =EDATE(J17,12) -> 46477 | L17: =EDATE(K17,12) -> 46843 | M17: =EDATE(L17,12) -> 47208 | N17: =EDATE(M17,12) -> 47573
B19: Revenues by geography
B20: North America | F20: 75058 | G20: 90724 | H20: 92411 | I20: 94397 | J20: =I20*(1+J28) -> 96096.146 | K20: =J20*(1+K28) -> 99939.992 | L20: =K20*(1+L28) -> 104437.29 | M20: =L20*(1+M28) -> 109659.16 | N20: =M20*(1+N28) -> 115690.41 | O20: =_xlfn.RRI(4,F20,I20) -> 0.058986201 | P20: =_xlfn.RRI(5,J20,N20) -> 0.037811019
B21: Europe | F21: 30129 | G21: 37675 | H21: 42267 | I21: 48595 | J21: =I21*(1+J32) -> 52482.6 | K21: =J21*(1+K32) -> 57206.034 | L21: =K21*(1+L32) -> 62583.401 | M21: =L21*(1+M32) -> 68716.575 | N21: =M21*(1+N32) -> 75588.232 | O21: =_xlfn.RRI(4,F21,I21) -> 0.1269424 | P21: =_xlfn.RRI(5,J21,N21) -> 0.07569158
B22: India | F22: 3585 | G22: 3861 | H22: 3881 | I22: 5014 | J22: =I22*(1+J36) -> 6518.2 | K22: =J22*(1+K36) -> 7952.204 | L22: =K22*(1+L36) -> 9542.6448 | M22: =L22*(1+M36) -> 11260.321 | N22: =M22*(1+N36) -> 12949.369 | O22: =_xlfn.RRI(4,F22,I22) -> 0.087486295 | P22: =_xlfn.RRI(5,J22,N22) -> 0.1471605
B23: Rest of the world | F23: 12869 | G23: 14507 | H23: 15111 | I23: 14984 | J23: =I23*(1+J40) -> 14609.4 | K23: =J23*(1+K40) -> 14346.431 | L23: =K23*(1+L40) -> 14131.234 | M23: =L23*(1+M40) -> 14060.578 | N23: =M23*(1+N40) -> 14130.881 | O23: =_xlfn.RRI(4,F23,I23) -> 0.038773211 | P23: =_xlfn.RRI(5,J23,N23) -> -0.0066383896
B24: Total | F24: =SUM(F20:F23) -> 121641 | G24: =SUM(G20:G23) -> 146767 | H24: =SUM(H20:H23) -> 153670 | I24: =SUM(I20:I23) -> 162990 | J24: =SUM(J20:J23) -> 169706.35 | K24: =SUM(K20:K23) -> 179444.66 | L24: =SUM(L20:L23) -> 190694.57 | M24: =SUM(M20:M23) -> 203696.63 | N24: =SUM(N20:N23) -> 218358.89 | O24: =_xlfn.RRI(4,F24,I24) -> 0.07589588 | P24: =_xlfn.RRI(5,J24,N24) -> 0.051706504
B26: Revenue Growth Anlaysis (YoY %)
B27: Revenues by geography
B28: North America | F28: 0 | G28: =G20/F20-1 -> 0.20871859 | H28: =H20/G20-1 -> 0.018594859 | I28: =I20/H20-1 -> 0.021490948 | J28: =OFFSET(J28,$E$14,0) -> 0.018 | K28: =OFFSET(K28,$E$14,0) -> 0.04 | L28: =OFFSET(L28,$E$14,0) -> 0.045 | M28: =OFFSET(M28,$E$14,0) -> 0.05 | N28: =OFFSET(N28,$E$14,0) -> 0.055 | Q28: Due to tariffs, visa and other cost barriers.
B29: Best | J29: =J30+1% -> 0.028 | K29: =K30+1% -> 0.05 | L29: =L30+1% -> 0.055 | M29: =M30+1% -> 0.06 | N29: =N30+1% -> 0.065
B30: Street | J30: 0.018 | K30: 0.04 | L30: 0.045 | M30: 0.05 | N30: 0.055
B31: Worst | J31: =J30-1% -> 0.008 | K31: =K30-1% -> 0.03 | L31: =L30-1% -> 0.035 | M31: =M30-1% -> 0.04 | N31: =N30-1% -> 0.045
B32: Europe | F32: 0 | G32: =G21/F21-1 -> 0.25045637 | H32: =H24/G24-1 -> 0.047033734 | I32: =I24/H24-1 -> 0.060649444 | J32: =OFFSET(J32,$E$14,0) -> 0.08 | K32: =OFFSET(K32,$E$14,0) -> 0.09 | L32: =OFFSET(L32,$E$14,0) -> 0.094 | M32: =OFFSET(M32,$E$14,0) -> 0.098 | N32: =OFFSET(N32,$E$14,0) -> 0.1 | Q32: Due to high/steady growth in Europe, driven by diversification (New centres, New hubs, etc.)
B33: Best | J33: =J34+1% -> 0.09 | K33: =K34+1% -> 0.1 | L33: =L34+1% -> 0.104 | M33: =M34+1% -> 0.108 | N33: =N34+1% -> 0.11
B34: Street | J34: 0.08 | K34: 0.09 | L34: 0.094 | M34: 0.098 | N34: 0.1
B35: Worst | J35: =J34-1% -> 0.07 | K35: =K34-1% -> 0.08 | L35: =L34-1% -> 0.084 | M35: =M34-1% -> 0.088 | N35: =N34-1% -> 0.09
B36: India | F36: 0 | G36: =G22/F22-1 -> 0.076987448 | H36: =H22/G22-1 -> 0.0051800052 | I36: =I22/H22-1 -> 0.29193507 | J36: =OFFSET(J36,$E$14,0) -> 0.3 | K36: =OFFSET(K36,$E$14,0) -> 0.22 | L36: =OFFSET(L36,$E$14,0) -> 0.2 | M36: =OFFSET(M36,$E$14,0) -> 0.18 | N36: =OFFSET(N36,$E$14,0) -> 0.15 | Q36: Domestic revenue contribution is expected to rise as Indian enterprises increase IT budgets, partially offsetting slower international growth.
B37: Best | J37: =J38+1% -> 0.31 | K37: =K38+1% -> 0.23 | L37: =L38+1% -> 0.21 | M37: =M38+1% -> 0.19 | N37: =N38+1% -> 0.16
B38: Street | J38: 0.3 | K38: 0.22 | L38: 0.2 | M38: 0.18 | N38: 0.15
B39: Worst | J39: =J38-1% -> 0.29 | K39: =K38-1% -> 0.21 | L39: =L38-1% -> 0.19 | M39: =M38-1% -> 0.17 | N39: =N38-1% -> 0.14
B40: Rest of the world | F40: 0 | G40: =G23/F23-1 -> 0.12728262 | H40: =H23/G23-1 -> 0.041635073 | I40: =I23/H23-1 -> -0.0084044736 | J40: =OFFSET(J40,$E$14,0) -> -0.025 | K40: =OFFSET(K40,$E$14,0) -> -0.018 | L40: =OFFSET(L40,$E$14,0) -> -0.015 | M40: =OFFSET(M40,$E$14,0) -> -0.005 | N40: =OFFSET(N40,$E$14,0) -> 0.005 | Q40: Small revenue share; growth still driven by digital demand
B41: Best | J41: =J42+1% -> -0.015 | K41: =K42+1% -> -0.008 | L41: =L42+1% -> -0.005 | M41: =M42+1% -> 0.005 | N41: =N42+1% -> 0.015
B42: Street | J42: -0.025 | K42: -0.018 | L42: -0.015 | M42: -0.005 | N42: 0.005
B43: Worst | J43: =J42-1% -> -0.035 | K43: =K42-1% -> -0.028 | L43: =L42-1% -> -0.025 | M43: =M42-1% -> -0.015 | N43: =N42-1% -> -0.005
A45: # | B45: Expenses forecast
A47: * | B47: Employee benfit expenses
B48: Salaries including bonus | F48: 61522 | G48: 75239 | H48: 79315 | I48: 82232 | J48: 0 | K48: 0 | L48: 0 | M48: 0 | N48: 0 | O48: =_xlfn.RRI(4,F48,I48) -> 0.075233042
B49: Contribution to PPF and other funds | F49: 1617 | G49: 2143 | H49: 2213 | I49: 2338 | J49: 0 | K49: 0 | L49: 0 | M49: 0 | N49: 0 | O49: =_xlfn.RRI(4,F49,I49) -> 0.096563085
B50: Share-based payments to employees | F50: 415 | G50: 519 | H50: 652 | I50: 802 | J50: 0 | K50: 0 | L50: 0 | M50: 0 | N50: 0 | O50: =_xlfn.RRI(4,F50,I50) -> 0.17904822
B51: Staff welfare | F51: 432 | G51: 458 | H51: 440 | I51: 578 | J51: 0 | K51: 0 | L51: 0 | M51: 0 | N51: 0 | O51: =_xlfn.RRI(4,F51,I51) -> 0.075501506
B52: Total | F52: =SUM(F48:F51) -> 63986 | G52: =SUM(G48:G51) -> 78359 | H52: =SUM(H48:H51) -> 82620 | I52: =SUM(I48:I51) -> 85950 | J52: =I52*(1+J54) -> 89559.9 | K52: =J52*(1+K54) -> 93455.756 | L52: =K52*(1+L54) -> 97661.265 | M52: =L52*(1+M54) -> 102202.51 | N52: =M52*(1+N54) -> 107108.23 | O52: =_xlfn.RRI(4,F52,I52) -> 0.076564934 | P52: =_xlfn.RRI(5,J52,N52) -> 0.036434478
B54: Employee benfit expenses (YoY %) | F54: 0 | G54: =G52/F52-1 -> 0.22462726 | H54: =H52/G52-1 -> 0.054377927 | I54: =I52/H52-1 -> 0.040305011 | J54: =OFFSET(J54,$E$15,0) -> 0.042 | K54: =OFFSET(K54,$E$15,0) -> 0.0435 | L54: =OFFSET(L54,$E$15,0) -> 0.045 | M54: =OFFSET(M54,$E$15,0) -> 0.0465 | N54: =OFFSET(N54,$E$15,0) -> 0.048
B55: Low AI Impact | J55: 0.042 | K55: =J55+($N$55-$J$55)/4 -> 0.0435 | L55: =K55+($N$55-$J$55)/4 -> 0.045 | M55: =L55+($N$55-$J$55)/4 -> 0.0465 | N55: 0.048
B56: Moderate AI Adoption | J56: =J55-0.75% -> 0.0345 | K56: =K55-0.75% -> 0.036 | L56: =L55-0.75% -> 0.0375 | M56: =M55-0.75% -> 0.039 | N56: =N55-0.75% -> 0.0405
B57: High AI Adoption | J57: =J56-0.75% -> 0.027 | K57: =K56-0.75% -> 0.0285 | L57: =L56-0.75% -> 0.03 | M57: =M56-0.75% -> 0.0315 | N57: =N56-0.75% -> 0.033
A59: * | B59: Cost of software packages and others
B60: For own use | F60: 1417 | G60: 1937 | H60: 2145 | I60: 2467 | J60: 0 | K60: 0 | L60: 0 | M60: 0 | N60: 0 | O60: =_xlfn.RRI(4,F60,I60) -> 0.14868202
B61: Third-party items bought for service to clients | F61: 5394 | G61: 8965 | H61: 11370 | I61: 13444 | J61: 0 | K61: 0 | L61: 0 | M61: 0 | N61: 0 | O61: =_xlfn.RRI(4,F61,I61) -> 0.25647656
B62: Total | F62: =SUM(F60:F61) -> 6811 | G62: =SUM(G60:G61) -> 10902 | H62: =SUM(H60:H61) -> 13515 | I62: =SUM(I60:I61) -> 15911 | J62: =I62*(1+J64) -> 18774.98 | K62: =J62*(1+K64) -> 22098.151 | L62: =K62*(1+L64) -> 25943.23 | M62: =L62*(1+M64) -> 30379.522 | N62: =M62*(1+N64) -> 35483.282 | O62: =_xlfn.RRI(4,F62,I62) -> 0.23629368 | P62: =_xlfn.RRI(5,J62,N62) -> 0.13576599
B64: Cost of software packages and others (YoY %) | F64: 0 | G64: =G62/F62-1 -> 0.60064601 | H64: =H62/G62-1 -> 0.23968079 | I64: =I62/H62-1 -> 0.1772845 | J64: =OFFSET(J64,$E$15,0) -> 0.18 | K64: =OFFSET(K64,$E$15,0) -> 0.177 | L64: =OFFSET(L64,$E$15,0) -> 0.174 | M64: =OFFSET(M64,$E$15,0) -> 0.171 | N64: =OFFSET(N64,$E$15,0) -> 0.168
B65: Low AI Impact | J65: 0.18 | K65: =J65+($N$65-$J$65)/4 -> 0.177 | L65: =K65+($N$65-$J$65)/4 -> 0.174 | M65: =L65+($N$65-$J$65)/4 -> 0.171 | N65: 0.168
B66: Moderate AI Adoption | J66: =J65+0.75% -> 0.1875 | K66: =K65+0.75% -> 0.1845 | L66: =L65+0.75% -> 0.1815 | M66: =M65+0.75% -> 0.1785 | N66: =N65+0.75% -> 0.1755
B67: High AI Adoption | J67: =J66+0.75% -> 0.195 | K67: =K66+0.75% -> 0.192 | L67: =L66+0.75% -> 0.189 | M67: =M66+0.75% -> 0.186 | N67: =N66+0.75% -> 0.183
A69: * | B69: Other expenses
B70: Repairs and maintenance | F70: 1066 | G70: 1208 | H70: 1278 | I70: 1320 | J70: 0 | K70: 0 | L70: 0 | M70: 0 | N70: 0 | O70: =_xlfn.RRI(4,F70,I70) -> 0.054882728
B71: Power and fuel | F71: 132 | G71: 176 | H71: 199 | I71: 222 | J71: 0 | K71: 0 | L71: 0 | M71: 0 | N71: 0 | O71: =_xlfn.RRI(4,F71,I71) -> 0.13879293
B72: Brand and marketing | F72: 553 | G72: 905 | H72: 1007 | I72: 1223 | J72: 0 | K72: 0 | L72: 0 | M72: 0 | N72: 0 | O72: =_xlfn.RRI(4,F72,I72) -> 0.21948182
B73: Short-term leases | F73: 61 | G73: 92 | H73: 0 | I73: 0 | J73: 0 | K73: 0 | L73: 0 | M73: 0 | N73: 0 | O73: 0
B74: Rates and taxes | F74: 265 | G74: 299 | H74: 326 | I74: 346 | J74: 0 | K74: 0 | L74: 0 | M74: 0 | N74: 0 | O74: =_xlfn.RRI(4,F74,I74) -> 0.068950405
B75: Consumables | F75: 146 | G75: 158 | H75: 170 | I75: 227 | J75: 0 | K75: 0 | L75: 0 | M75: 0 | N75: 0 | O75: =_xlfn.RRI(4,F75,I75) -> 0.11665303
B76: Insurance | F76: 164 | G76: 174 | H76: 210 | I76: 301 | J76: 0 | K76: 0 | L76: 0 | M76: 0 | N76: 0 | O76: =_xlfn.RRI(4,F76,I76) -> 0.16394018
B77: Provision for post-sales client support and others | F77: 78 | G77: 120 | H77: 75 | I77: -110 | J77: 0 | K77: 0 | L77: 0 | M77: 0 | N77: 0 | O77: 0
B78: Commission to non-whole time directors | F78: 11 | G78: 15 | H78: 16 | I78: 18 | J78: 0 | K78: 0 | L78: 0 | M78: 0 | N78: 0 | O78: =_xlfn.RRI(4,F78,I78) -> 0.13101914
B79: Impairment loss recognized | F79: 170 | G79: 283 | H79: 121 | I79: 48 | J79: 0 | K79: 0 | L79: 0 | M79: 0 | N79: 0 | O79: =_xlfn.RRI(4,F79,I79) -> -0.27104943
B80: Contributions towards CSR | F80: 426 | G80: 471 | H80: 533 | I80: 585 | J80: 0 | K80: 0 | L80: 0 | M80: 0 | N80: 0 | O80: =_xlfn.RRI(4,F80,I80) -> 0.08252159
B81: Others | F81: 352 | G81: 491 | H81: 781 | I81: 607 | J81: 0 | K81: 0 | L81: 0 | M81: 0 | N81: 0 | O81: =_xlfn.RRI(4,F81,I81) -> 0.14593902
B82: Total | F82: =SUM(F70:F81) -> 3424 | G82: =SUM(G70:G81) -> 4392 | H82: =SUM(H70:H81) -> 4716 | I82: =SUM(I70:I81) -> 4787 | J82: =I82*(1+J84) -> 5074.22 | K82: =J82*(1+K84) -> 5396.433 | L82: =K82*(1+L84) -> 5757.994 | M82: =L82*(1+M84) -> 6163.9326 | N82: =M82*(1+N84) -> 6620.0636 | O82: =_xlfn.RRI(4,F82,I82) -> 0.087382697 | P82: =_xlfn.RRI(5,J82,N82) -> 0.054626241
A84: * | B84: Total other expenses | F84: 0 | G84: =G82/F82-1 -> 0.28271028 | H84: =H82/G82-1 -> 0.073770492 | I84: =I82/H82-1 -> 0.015055131 | J84: =OFFSET(J84,$E$15,0) -> 0.06 | K84: =OFFSET(K84,$E$15,0) -> 0.0635 | L84: =OFFSET(L84,$E$15,0) -> 0.067 | M84: =OFFSET(M84,$E$15,0) -> 0.0705 | N84: =OFFSET(N84,$E$15,0) -> 0.074
B85: Low AI Impact | J85: 0.06 | K85: =J85+($N$85-$J$85)/4 -> 0.0635 | L85: =K85+($N$85-$J$85)/4 -> 0.067 | M85: =L85+($N$85-$J$85)/4 -> 0.0705 | N85: 0.074
B86: Moderate AI Adoption | J86: =J85-1% -> 0.05 | K86: =K85-1% -> 0.0535 | L86: =L85-1% -> 0.057 | M86: =M85-1% -> 0.0605 | N86: =N85-1% -> 0.064
B87: High AI Adoption | J87: =J86-1% -> 0.04 | K87: =K86-1% -> 0.0435 | L87: =L86-1% -> 0.047 | M87: =M86-1% -> 0.0505 | N87: =N86-1% -> 0.054
A89: * | B89: Other costs
B90: Cost of technical sub-contractors | F90: =Financials!F20 -> 12606 | G90: =Financials!G20 -> 14062 | H90: =Financials!H20 -> 12232 | I90: =Financials!I20 -> 12937 | J90: =I90*(1+J95) -> 13713.22 | K90: =J90*(1+K95) -> 14577.153 | L90: =K90*(1+L95) -> 15539.245 | M90: =L90*(1+M95) -> 16611.453 | N90: =M90*(1+N95) -> 17807.477 | O90: =_xlfn.RRI(4,F90,I90) -> 0.0065006712 | P90: =_xlfn.RRI(5,J90,N90) -> 0.05364083
B91: Travel expenses | F91: =Financials!F21 -> 827 | G91: =Financials!G21 -> 1525 | H91: =Financials!H21 -> 1759 | I91: =Financials!I21 -> 1894 | J91: =I91*(1+J99) -> 2045.52 | K91: =J91*(1+K99) -> 2219.3892 | L91: =K91*(1+L99) -> 2419.1342 | M91: =L91*(1+M99) -> 2648.952 | N91: =M91*(1+N99) -> 2913.8472 | O91: =_xlfn.RRI(4,F91,I91) -> 0.23017987 | P91: =_xlfn.RRI(5,J91,N91) -> 0.073328369
B92: Communication expenses | F92: =Financials!F23 -> 611 | G92: =Financials!G23 -> 713 | H92: =Financials!H23 -> 677 | I92: =Financials!I23 -> 620 | J92: =I92*(1+J103) -> 570.4 | K92: =J92*(1+K103) -> 529.046 | L92: =K92*(1+L103) -> 494.65801 | M92: =L92*(1+M103) -> 466.21517 | N92: =M92*(1+N103) -> 442.90442 | O92: =_xlfn.RRI(4,F92,I92) -> 0.0036623197 | P92: =_xlfn.RRI(5,J92,N92) -> -0.049338079
B93: Consultancy and professional charges | F93: =Financials!F24 -> 1885 | G93: =Financials!G24 -> 1684 | H93: =Financials!H24 -> 1726 | I93: =Financials!I24 -> 1655 | J93: =I93*(1+J107) -> 1688.1 | K93: =J93*(1+K107) -> 1728.1924 | L93: =K93*(1+L107) -> 1775.7177 | M93: =L93*(1+M107) -> 1831.2088 | N93: =M93*(1+N107) -> 1895.3012 | O93: =_xlfn.RRI(4,F93,I93) -> -0.032008239 | P93: =_xlfn.RRI(5,J93,N93) -> 0.023424976
B95: Cost of technical sub-contractors | F95: 0 | G95: =G90/F90-1 -> 0.11550056 | H95: =H90/G90-1 -> -0.13013796 | I95: =I90/H90-1 -> 0.05763571 | J95: =OFFSET(J95,$E$15,0) -> 0.06 | K95: =OFFSET(K95,$E$15,0) -> 0.063 | L95: =OFFSET(L95,$E$15,0) -> 0.066 | M95: =OFFSET(M95,$E$15,0) -> 0.069 | N95: =OFFSET(N95,$E$15,0) -> 0.072
B96: Low AI Impact | J96: 0.06 | K96: =J96+($N$96-$J$96)/4 -> 0.063 | L96: =K96+($N$96-$J$96)/4 -> 0.066 | M96: =L96+($N$96-$J$96)/4 -> 0.069 | N96: 0.072
B97: Moderate AI Adoption | J97: =J96+0.75% -> 0.0675 | K97: =K96+0.75% -> 0.0705 | L97: =L96+0.75% -> 0.0735 | M97: =M96+0.75% -> 0.0765 | N97: =N96+0.75% -> 0.0795
B98: High AI Adoption | J98: =J97+0.75% -> 0.075 | K98: =K97+0.75% -> 0.078 | L98: =L97+0.75% -> 0.081 | M98: =M97+0.75% -> 0.084 | N98: =N97+0.75% -> 0.087
B99: Travel expenses | F99: 0 | G99: =G91/F91-1 -> 0.84401451 | H99: =H91/G91-1 -> 0.15344262 | I99: =I91/H91-1 -> 0.076748152 | J99: =OFFSET(J99,$E$15,0) -> 0.08 | K99: =OFFSET(K99,$E$15,0) -> 0.085 | L99: =OFFSET(L99,$E$15,0) -> 0.09 | M99: =OFFSET(M99,$E$15,0) -> 0.095 | N99: =OFFSET(N99,$E$15,0) -> 0.1
B100: Low AI Impact | J100: 0.08 | K100: =J100+($N$100-$J$100)/4 -> 0.085 | L100: =K100+($N$100-$J$100)/4 -> 0.09 | M100: =L100+($N$100-$J$100)/4 -> 0.095 | N100: 0.1
B101: Moderate AI Adoption | J101: =J100-1.5% -> 0.065 | K101: =J101+($N$101-$J$101)/4 -> 0.06 | L101: =K101+($N$100-$J$100)/4 -> 0.065 | M101: =L101+($N$100-$J$100)/4 -> 0.07 | N101: 0.045
B102: High AI Adoption | J102: =J101-1.5% -> 0.05 | K102: =J102+($N$102-$J$102)/4 -> 0.045 | L102: =K102+($N$100-$J$100)/4 -> 0.05 | M102: =L102+($N$100-$J$100)/4 -> 0.055 | N102: 0.03
B103: Communication expenses | F103: 0 | G103: =G92/F92-1 -> 0.16693944 | H103: =H92/G92-1 -> -0.050490884 | I103: =I92/H92-1 -> -0.084194978 | J103: =OFFSET(J103,$E$15,0) -> -0.08 | K103: =OFFSET(K103,$E$15,0) -> -0.0725 | L103: =OFFSET(L103,$E$15,0) -> -0.065 | M103: =OFFSET(M103,$E$15,0) -> -0.0575 | N103: =OFFSET(N103,$E$15,0) -> -0.05
B104: Low AI Impact | J104: -0.08 | K104: =J104+($N$104-$J$104)/4 -> -0.0725 | L104: =K104+($N$104-$J$104)/4 -> -0.065 | M104: =L104+($N$104-$J$104)/4 -> -0.0575 | N104: -0.05
B105: Moderate AI Adoption | J105: =J104+0.75% -> -0.0725 | K105: =K104+0.75% -> -0.065 | L105: =L104+0.75% -> -0.0575 | M105: =M104+0.75% -> -0.05 | N105: =N104+0.75% -> -0.0425
B106: High AI Adoption | J106: =J105+0.75% -> -0.065 | K106: =K105+0.75% -> -0.0575 | L106: =L105+0.75% -> -0.05 | M106: =M105+0.75% -> -0.0425 | N106: =N105+0.75% -> -0.035
B107: Consultancy and professional charges | F107: 0 | G107: =G93/F93-1 -> -0.1066313 | H107: =H93/G93-1 -> 0.024940618 | I107: =I93/H93-1 -> -0.041135574 | J107: =OFFSET(J107,$E$15,0) -> 0.02 | K107: =OFFSET(K107,$E$15,0) -> 0.02375 | L107: =OFFSET(L107,$E$15,0) -> 0.0275 | M107: =OFFSET(M107,$E$15,0) -> 0.03125 | N107: =OFFSET(N107,$E$15,0) -> 0.035
B108: Low AI Impact | J108: 0.02 | K108: =J108+($N$108-$J$108)/4 -> 0.02375 | L108: =K108+($N$108-$J$108)/4 -> 0.0275 | M108: =L108+($N$108-$J$108)/4 -> 0.03125 | N108: 0.035
B109: Moderate AI Adoption | J109: =J108+0.75% -> 0.0275 | K109: =K108+0.75% -> 0.03125 | L109: =L108+0.75% -> 0.035 | M109: =M108+0.75% -> 0.03875 | N109: =N108+0.75% -> 0.0425
B110: High AI Adoption | J110: =J109+0.75% -> 0.035 | K110: =K109+0.75% -> 0.03875 | L110: =L109+0.75% -> 0.0425 | M110: =M109+0.75% -> 0.04625 | N110: =N109+0.75% -> 0.05
B112: <- Go back to the top

Sheet Assumptions
B2: =Dashboard!C2 -> Infosys Ltd.
B3: Assumptions
B4: =Dashboard!C4 -> (In ₹ Crore, except equity share and per equity share data)
B5: Date | G5: Acutals | K5: Forecast | P5: CAGR | R5: Notes
B6: Actual / Forecast | G6: =Financials!F6 -> 44651 | H6: =EDATE(G6,12) -> 45016 | I6: =EDATE(H6,12) -> 45382 | J6: =EDATE(I6,12) -> 45747 | K6: =EDATE(J6,12) -> 46112 | L6: =EDATE(K6,12) -> 46477 | M6: =EDATE(L6,12) -> 46843 | N6: =EDATE(M6,12) -> 47208 | O6: =EDATE(N6,12) -> 47573 | P6: 22A - 25A | Q6: 26E - 30E
B8: <-Back to dashboard
A10: # | B10: Assumptions
B12: Other income | G12: =Financials!F16 -> 2295 | H12: =Financials!G16 -> 2701 | I12: =Financials!H16 -> 4711 | J12: =Financials!I16 -> 3600 | K12: =K13*Financials!J$15 -> 3818.9935 | L12: =L13*Financials!K$15 -> 4038.1401 | M12: =M13*Financials!L$15 -> 4291.3029 | N12: =N13*Financials!M$15 -> 4583.8952 | O12: =O13*Financials!N$15 -> 4913.848 | P12: =_xlfn.RRI(4,G12,J12) -> 0.11912849 | Q12: =_xlfn.RRI(5,K12,O12) -> 0.051706504 | R12: Other income projected as the average of other income to Revenue
B13: Other income as a % of Revenue from operations | G13: =G12/Financials!F$15 -> 0.018866994 | H13: =H12/Financials!G$15 -> 0.01840332 | I13: =I12/Financials!H$15 -> 0.030656602 | J13: =J12/Financials!I$15 -> 0.022087245 | K13: =AVERAGE(G13:J13) -> 0.02250354 | L13: =K13 -> 0.02250354 | M13: =L13 -> 0.02250354 | N13: =M13 -> 0.02250354 | O13: =N13 -> 0.02250354
B15: Current taxes | G15: =Financials!F32 -> 7811 | H15: =Financials!G32 -> 9287 | I15: =Financials!H32 -> 8390 | J15: =Financials!I32 -> 12130 | K15: =K16*Financials!J30 -> 12163.541 | L15: =L16*Financials!K30 -> 12450.245 | M15: =M16*Financials!L30 -> 12916.453 | N15: =N16*Financials!M30 -> 13544.169 | O15: =O16*Financials!N30 -> 14293.643 | P15: =_xlfn.RRI(4,G15,J15) -> 0.11631958 | Q15: =_xlfn.RRI(5,K15,O15) -> 0.032800831 | R15: Current taxes projected as average of current taxes to PBT
B16: Current taxes as a % of PBT | G16: =G15/Financials!F$30 -> 0.25941548 | H16: =H15/Financials!G$30 -> 0.27870476 | I16: =I15/Financials!H$30 -> 0.23313327 | J16: =J15/Financials!I$30 -> 0.32253776 | K16: 0.3 | L16: =K16 -> 0.3 | M16: =L16 -> 0.3 | N16: =M16 -> 0.3 | O16: =N16 -> 0.3
B18: Non-controlling interersts | G18: =Financials!F38 -> 36 | H18: =Financials!G38 -> 13 | I18: =Financials!H38 -> 15 | J18: =Financials!I38 -> 37 | K18: =K19*Financials!J34 -> 29.229252 | L18: =L19*Financials!K34 -> 29.918208 | M18: =M19*Financials!L34 -> 31.038514 | N18: =N19*Financials!M34 -> 32.546929 | O18: =O19*Financials!N34 -> 34.347932 | P18: =_xlfn.RRI(4,G18,J18) -> 0.0068732567 | Q18: =_xlfn.RRI(5,K18,O18) -> 0.032800831 | R18: NCI projected as average of NCI to PAT
B19: Non-controlling interersts as a % of Net income | G19: =G18/Financials!F$34 -> 0.0016255757 | H19: =H18/Financials!G$34 -> 0.00053924009 | I19: =I18/Financials!H$34 -> 0.00057147211 | J19: =J18/Financials!I$34 -> 0.0013831776 | K19: =AVERAGE(G19:J19) -> 0.0010298664 | L19: =K19 -> 0.0010298664 | M19: =L19 -> 0.0010298664 | N19: =M19 -> 0.0010298664 | O19: =N19 -> 0.0010298664
B21: Dividends paid | G21: 12652 | H21: 13631 | I21: 14692 | J21: 20287 | K21: =K22*Financials!J37 -> 17400.159 | L21: =L22*Financials!K37 -> 18117.996 | M21: =M22*Financials!L37 -> 19239.766 | N21: =N22*Financials!M37 -> 20800.676 | O21: =O22*Financials!N37 -> 21122.683 | P21: =_xlfn.RRI(4,G21,J21) -> 0.12529052 | Q21: =_xlfn.RRI(5,K21,O21) -> 0.039535138
B22: Dividends paid as a % of Net income | G22: =G21/Financials!F$34 -> 0.57129956 | H22: =H21/Financials!G$34 -> 0.56541397 | I22: =I21/Financials!H$34 -> 0.55973788 | J22: =J21/Financials!I$34 -> 0.75839252 | K22: =AVERAGE(G22:J22) -> 0.61371098 | L22: =AVERAGE(H22:K22) -> 0.62431384 | M22: =AVERAGE(I22:L22) -> 0.63903881 | N22: =AVERAGE(J22:M22) -> 0.65886404 | O22: =AVERAGE(K22:N22) -> 0.63398192
B24: Share buy-back | G24: 11125 | H24: 11499 | I24: 0 | J24: 0 | K24: 0 | L24: 12500 | M24: 0 | N24: 0 | O24: 10500
B25: Share buy-back as a % of Net income | G25: =IF(G24/Financials!F$34,G24/Financials!F$34,"-") -> 0.50234805 | H25: =IF(H24/Financials!G$34,H24/Financials!G$34,"-") -> 0.4769786 | I25: =IF(I24/Financials!H$34,I24/Financials!H$34,"-") -> - | J25: =IF(J24/Financials!I$34,J24/Financials!I$34,"-") -> - | K25: =IF(K24/Financials!J$34,K24/Financials!J$34,"-") -> - | L25: =IF(L24/Financials!K$34,L24/Financials!K$34,"-") -> 0.43028412 | M25: =IF(M24/Financials!L$34,M24/Financials!L$34,"-") -> - | N25: =IF(N24/Financials!M$34,N24/Financials!M$34,"-") -> - | O25: =IF(O24/Financials!M$34,O24/Financials!M$34,"-") -> 0.33224631
A28: # | B28: End

Sheet Schedule
B2: =Dashboard!C2 -> Infosys Ltd.
B3: Schedule
B4: =Dashboard!C4 -> (In ₹ Crore, except equity share and per equity share data)
B5: Date | G5: Acutals | K5: Forecast
B6: Actual / Forecast | G6: =Financials!F6 -> 44651 | H6: =EDATE(G6,12) -> 45016 | I6: =EDATE(H6,12) -> 45382 | J6: =EDATE(I6,12) -> 45747 | K6: =EDATE(J6,12) -> 46112 | L6: =EDATE(K6,12) -> 46477 | M6: =EDATE(L6,12) -> 46843 | N6: =EDATE(M6,12) -> 47208 | O6: =EDATE(N6,12) -> 47573
B8: <-Back to dashboard
A10: # | B10: Property, plant, and equipment and Intangible schedule
B12: CapEx on PPE and intangibles | I12: 2201 | J12: 2237 | K12: =K13*Financials!J15 -> 3394.1269 | L12: =L13*Financials!K15 -> 3947.7825 | M12: =M13*Financials!L15 -> 4576.6697 | N12: =N13*Financials!M15 -> 5296.1124 | O12: =O13*Financials!N15 -> 6114.049
B13: CapEx as a % of opearting revenue | I13: =I12/Financials!H$15 -> 0.0143229 | J13: =J12/Financials!I$15 -> 0.013724768 | K13: 0.02 | L13: =K13+($O$13-$K$13)/4 -> 0.022 | M13: =L13+($O$13-$K$13)/4 -> 0.024 | N13: =M13+($O$13-$K$13)/4 -> 0.026 | O13: 0.028
B15: CapEx on PPE | I15: 1761 | J15: 1843 | K15: =($J15/$J$12)*K$12 -> 2796.3236 | L15: =($J15/$J$12)*L$12 -> 3252.4646 | M15: =($J15/$J$12)*M$12 -> 3770.5866 | N15: =($J15/$J$12)*N$12 -> 4363.3148 | O15: =($J15/$J$12)*O$12 -> 5037.1892
B16: CapEx on Intangibles | I16: =I12-I15 -> 440 | J16: =J12-J15 -> 394 | K16: =($J16/$J$12)*K$12 -> 597.80331 | L16: =($J16/$J$12)*L$12 -> 695.31798 | M16: =($J16/$J$12)*M$12 -> 806.08309 | N16: =($J16/$J$12)*N$12 -> 932.79762 | O16: =($J16/$J$12)*O$12 -> 1076.8598
B18: CWIP | K18: 576 | L18: 204 | M18: 22 | N18: 12 | O18: 0
B20: Depreciation on PPE (old) | I20: 2685 | J20: 2360
B21: Average useful life (Years) | E21: 5
B23: Depreciation on PPE (new)
B24: Average useful life (Years) | E24: 12
B25: (old) | K25: =AVERAGE($I$20:$J$20)/$E$21 -> 504.5 | L25: =AVERAGE($I$20:$J$20)/$E$21 -> 504.5 | M25: =AVERAGE($I$20:$J$20)/$E$21 -> 504.5 | N25: =AVERAGE($I$20:$J$20)/$E$21 -> 504.5 | O25: =AVERAGE($I$20:$J$20)/$E$21 -> 504.5
B26: (new) | E26: 46112 | K26: =SLN($K$15,0,$E$24) -> 233.02697 | L26: =SLN($K$15,0,$E$24) -> 233.02697 | M26: =SLN($K$15,0,$E$24) -> 233.02697 | N26: =SLN($K$15,0,$E$24) -> 233.02697 | O26: =SLN($K$15,0,$E$24) -> 233.02697
B27: (new) | E27: 46477 | L27: =SLN($L$15,0,$E$24) -> 271.03871 | M27: =SLN($L$15,0,$E$24) -> 271.03871 | N27: =SLN($L$15,0,$E$24) -> 271.03871 | O27: =SLN($L$15,0,$E$24) -> 271.03871
B28: (new) | E28: 46843 | M28: =SLN($M$15,0,$E$24) -> 314.21555 | N28: =SLN($M$15,0,$E$24) -> 314.21555 | O28: =SLN($M$15,0,$E$24) -> 314.21555
B29: (new) | E29: 47208 | N29: =SLN($N$15,0,$E$24) -> 363.60956 | O29: =SLN($N$15,0,$E$24) -> 363.60956
B30: (new) | E30: 47573 | O30: =SLN($O$15,0,$E$24) -> 419.76577
B32: Total Depreciation | K32: =SUM(K25,K26:K30) -> 737.52697 | L32: =SUM(L25,L26:L30) -> 1008.5657 | M32: =SUM(M25,M26:M30) -> 1322.7812 | N32: =SUM(N25,N26:N30) -> 1686.3908 | O32: =SUM(O25,O26:O30) -> 2106.1566
B34: Disposal of PPE | G34: 1100 | H34: 2197 | I34: 1227 | J34: 1221 | K34: =K35*Financials!J15 -> 1675.3499 | L34: =L35*Financials!K15 -> 1808.6791 | M34: =M35*Financials!L15 -> 1688.9468 | N34: =N35*Financials!M15 -> 1848.5184 | O34: =O35*Financials!N15 -> 2068.0248
B35: Disposal of PPE as a % of operating revenue | G35: =G34/Financials!F$15 -> 0.0090430036 | H35: =H34/Financials!G$15 -> 0.014969305 | I35: =I34/Financials!H$15 -> 0.0079846424 | J35: =J34/Financials!I$15 -> 0.0074912571 | K35: =AVERAGE(G35:J35) -> 0.0098720521 | L35: =AVERAGE(H35:K35) -> 0.010079314 | M35: =AVERAGE(I35:L35) -> 0.0088568164 | N35: =AVERAGE(J35:M35) -> 0.00907486 | O35: =AVERAGE(K35:N35) -> 0.0094707607
B37: Amortisation on intangibles | I37: 432 | J37: 777 | K37: =K38*AVERAGE(K51,K53) -> 816.33491 | L37: =L38*AVERAGE(L51,L53) -> 969.29654 | M37: =M38*AVERAGE(M51,M53) -> 1017.0075 | N37: =N38*AVERAGE(N51,N53) -> 1143.1087 | O37: =O38*AVERAGE(O51,O53) -> 1249.9972
B38: Amortisation as a % on gross avg intangibles | I38: =I37/AVERAGE(I$51,I$53) -> 0.091787953 | J38: =J37/AVERAGE(J$51,J$53) -> 0.13239053 | K38: =AVERAGE(I38:J38) -> 0.11208924 | L38: =AVERAGE(J38:K38) -> 0.12223988 | M38: =AVERAGE(K38:L38) -> 0.11716456 | N38: =AVERAGE(L38:M38) -> 0.11970222 | O38: =AVERAGE(M38:N38) -> 0.11843339
B40: Property, plant and equipment
B41: Opening balance of gross PPE | I41: 30089 | J41: =I45 -> 30587 | K41: =J45 -> 31290 | L41: =K45 -> 32986.974 | M41: =L45 -> 34634.759 | N41: =M45 -> 36738.399 | O41: =N45 -> 39265.195
B42: Additions to PPE | K42: =K15 -> 2796.3236 | L42: =L15 -> 3252.4646 | M42: =M15 -> 3770.5866 | N42: =N15 -> 4363.3148 | O42: =O15 -> 5037.1892
B43: Transfers from CWIP | K43: =K18 -> 576 | L43: =L18 -> 204 | M43: =M18 -> 22 | N43: =N18 -> 12 | O43: =O18 -> 0
B44: Disposal of PPE | K44: =K34 -> 1675.3499 | L44: =L34 -> 1808.6791 | M44: =M34 -> 1688.9468 | N44: =N34 -> 1848.5184 | O44: =O34 -> 2068.0248
B45: Closing balance of gross PPE | I45: 30587 | J45: 31290 | K45: =K41+K42+K43-K44 -> 32986.974 | L45: =L41+L42+L43-L44 -> 34634.759 | M45: =M41+M42+M43-M44 -> 36738.399 | N45: =N41+N42+N43-N44 -> 39265.195 | O45: =O41+O42+O43-O44 -> 42234.36
B46: Accumulated depreciation | J46: -19512 | K46: =J46-K32 -> -20249.527 | L46: =K46-L32 -> -21258.093 | M46: =L46-M32 -> -22580.874 | N46: =M46-N32 -> -24267.265 | O46: =N46-O32 -> -26373.421
B47: Closing balance of Net PPE block | K47: =K45+K46 -> 12737.447 | L47: =L45+L46 -> 13376.667 | M47: =M45+M46 -> 14157.525 | N47: =N45+N46 -> 14997.931 | O47: =O45+O46 -> 15860.939
B50: Intangible assets
B51: Opening balance of gross intangible assets | I51: 4659 | J51: =I53 -> 4754 | K51: =J53 -> 6984 | L51: =K53 -> 7581.8033 | M51: =L53 -> 8277.1213 | N51: =M53 -> 9083.2044 | O51: =N53 -> 10016.002
B52: Additions to intangible assets | K52: =K16 -> 597.80331 | L52: =L16 -> 695.31798 | M52: =M16 -> 806.08309 | N52: =N16 -> 932.79762 | O52: =O16 -> 1076.8598
B53: Closing balance of gross intangible assets | I53: 4754 | J53: 6984 | K53: =K51+K52 -> 7581.8033 | L53: =L51+L52 -> 8277.1213 | M53: =M51+M52 -> 9083.2044 | N53: =N51+N52 -> 10016.002 | O53: =O51+O52 -> 11092.862
B54: Accumulated amortisation | J54: -4218 | K54: =J54-K37 -> -5034.3349 | L54: =K54-L37 -> -6003.6315 | M54: =L54-M37 -> -7020.6389 | N54: =M54-N37 -> -8163.7476 | O54: =N54-O37 -> -9413.7448
B55: Closing balance of Net intangible assets block | K55: =K53+K54 -> 2547.4684 | L55: =L53+L54 -> 2273.4898 | M55: =M53+M54 -> 2062.5655 | N55: =N53+N54 -> 1852.2544 | O55: =O53+O54 -> 1679.1169
A58: # | B58: Working capital schedule
B60: Current assets
B61: Trade receivables | G61: =Financials!F66 -> 22698 | H61: =Financials!G66 -> 25424 | I61: =Financials!H66 -> 30193 | J61: =Financials!I66 -> 31158 | K61: =K77*Financials!J$15/days -> 32441.931 | L61: =L77*Financials!K$15/days -> 34303.557 | M61: =M77*Financials!L$15/days -> 36454.147 | N61: =N77*Financials!M$15/days -> 38939.687 | O61: =O77*Financials!N$15/days -> 41742.6
B62: Other financial assets | G62: =Financials!F69 -> 8727 | H62: =Financials!G69 -> 11604 | I62: =Financials!H69 -> 12085 | J62: =Financials!I69 -> 13840 | K62: =K78*Financials!J$15/days -> 14410.306 | L62: =L78*Financials!K$15/days -> 15237.218 | M62: =M78*Financials!L$15/days -> 16192.483 | N62: =N78*Financials!M$15/days -> 17296.53 | O62: =O78*Financials!N$15/days -> 18541.549
B63: Other current assets | G63: =Financials!F71 -> 11313 | H63: =Financials!G71 -> 14476 | I63: =Financials!H71 -> 12808 | J63: =Financials!I71 -> 11940 | K63: =K79*Financials!J$15/days -> 12432.013 | L63: =L79*Financials!K$15/days -> 13145.403 | M63: =M79*Financials!L$15/days -> 13969.527 | N63: =N79*Financials!M$15/days -> 14922.006 | O63: =O79*Financials!N$15/days -> 15996.105
B64: Total current assets | G64: =SUM(G61:G63) -> 42738 | H64: =SUM(H61:H63) -> 51504 | I64: =SUM(I61:I63) -> 55086 | J64: =SUM(J61:J63) -> 56938 | K64: =SUM(K61:K63) -> 59284.25 | L64: =SUM(L61:L63) -> 62686.178 | M64: =SUM(M61:M63) -> 66616.158 | N64: =SUM(N61:N63) -> 71158.223 | O64: =SUM(O61:O63) -> 76280.254
B66: Current liabilities
B67: Trade payables | G67: =Financials!F90 -> 4134 | H67: =Financials!G90 -> 3865 | I67: =Financials!H90 -> 3956 | J67: =Financials!I90 -> 4164 | K67: =K81*(Financials!J$19+Financials!J$20+Financials!J$22+Financials!J$27)/days -> 4426.4527 | L67: =L81*(Financials!K$19+Financials!K$20+Financials!K$22+Financials!K$27)/days -> 4719.1243 | M67: =M81*(Financials!L$19+Financials!L$20+Financials!L$22+Financials!L$27)/days -> 5045.5393 | N67: =N81*(Financials!M$19+Financials!M$20+Financials!M$22+Financials!M$27)/days -> 5409.6107 | O67: =O81*(Financials!N$19+Financials!N$20+Financials!N$22+Financials!N$27)/days -> 5815.6738
B68: Other financial liabilities | G68: =Financials!F91 -> 15837 | H68: =Financials!G91 -> 18558 | I68: =Financials!H91 -> 16959 | J68: =Financials!I91 -> 18138 | K68: =K82*(Financials!J$19+Financials!J$20+Financials!J$22+Financials!J$27)/days -> 19281.22 | L68: =L82*(Financials!K$19+Financials!K$20+Financials!K$22+Financials!K$27)/days -> 20556.07 | M68: =M82*(Financials!L$19+Financials!L$20+Financials!L$22+Financials!L$27)/days -> 21977.904 | N68: =N82*(Financials!M$19+Financials!M$20+Financials!M$22+Financials!M$27)/days -> 23563.766 | O68: =O82*(Financials!N$19+Financials!N$20+Financials!N$22+Financials!N$27)/days -> 25332.539
B69: Other current liabilities | G69: =Financials!F92 -> 9178 | H69: =Financials!G92 -> 10830 | I69: =Financials!H92 -> 10539 | J69: =Financials!I92 -> 11765 | K69: =K83*(Financials!J$19+Financials!J$20+Financials!J$22+Financials!J$27)/days -> 12506.536 | L69: =L83*(Financials!K$19+Financials!K$20+Financials!K$22+Financials!K$27)/days -> 13333.453 | M69: =M83*(Financials!L$19+Financials!L$20+Financials!L$22+Financials!L$27)/days -> 14255.708 | N69: =N83*(Financials!M$19+Financials!M$20+Financials!M$22+Financials!M$27)/days -> 15284.359 | O69: =O83*(Financials!N$19+Financials!N$20+Financials!N$22+Financials!N$27)/days -> 16431.653
B70: Total current liabilities | G70: =SUM(G67:G69) -> 29149 | H70: =SUM(H67:H69) -> 33253 | I70: =SUM(I67:I69) -> 31454 | J70: =SUM(J67:J69) -> 34067 | K70: =SUM(K67:K69) -> 36214.208 | L70: =SUM(L67:L69) -> 38608.647 | M70: =SUM(M67:M69) -> 41279.152 | N70: =SUM(N67:N69) -> 44257.735 | O70: =SUM(O67:O69) -> 47579.865
B72: Net Working Capital | G72: =G61-G67 -> 18564 | H72: =H61-H67 -> 21559 | I72: =I61-I67 -> 26237 | J72: =J61-J67 -> 26994 | K72: =K61-K67 -> 28015.478 | L72: =L61-L67 -> 29584.433 | M72: =M61-M67 -> 31408.608 | N72: =N61-N67 -> 33530.076 | O72: =O61-O67 -> 35926.926
B74: Change in working capital | K74: =(J64-K64)+(K70-J70) -> -199.04203 | L74: =(K64-L64)+(L70-K70) -> -1007.4882 | M74: =(L64-M64)+(M70-L70) -> -1259.4758 | N74: =(M64-N64)+(N70-M70) -> -1563.4814 | O74: =(N64-O64)+(O70-N70) -> -1799.901
B76: Turnover ratio
B77: Trade receivables | G77: =G61*days/Financials!F$15 -> 68.108368 | H77: =H61*days/Financials!G$15 -> 63.227837 | I77: =I61*days/Financials!H$15 -> 71.715006 | J77: =J61*days/Financials!I$15 -> 69.775262 | K77: =J77 -> 69.775262 | L77: =K77 -> 69.775262 | M77: =L77 -> 69.775262 | N77: =M77 -> 69.775262 | O77: =N77 -> 69.775262
B78: Other financial assets | G78: =G62*days/Financials!F$15 -> 26.186524 | H78: =H62*days/Financials!G$15 -> 28.858395 | I78: =I62*days/Financials!H$15 -> 28.704529 | J78: =J62*days/Financials!I$15 -> 30.993312 | K78: =J78 -> 30.993312 | L78: =K78 -> 30.993312 | M78: =L78 -> 30.993312 | N78: =M78 -> 30.993312 | O78: =N78 -> 30.993312
B79: Other current assets | G79: =G63*days/Financials!F$15 -> 33.946161 | H79: =H63*days/Financials!G$15 -> 36.000872 | I79: =I63*days/Financials!H$15 -> 30.421813 | J79: =J63*days/Financials!I$15 -> 26.73845 | K79: =J79 -> 26.73845 | L79: =K79 -> 26.73845 | M79: =L79 -> 26.73845 | N79: =M79 -> 26.73845 | O79: =N79 -> 26.73845
B81: Trade payables | G81: =G67*days/(Financials!F$19+Financials!F$20+Financials!F$22+Financials!F$27) -> 17.37835 | H81: =H67*days/(Financials!G$19+Financials!G$20+Financials!G$22+Financials!G$27) -> 13.09683 | I81: =I67*days/(Financials!H$19+Financials!H$20+Financials!H$22+Financials!H$27) -> 12.768851 | J81: =J67*days/(Financials!I$19+Financials!I$20+Financials!I$22+Financials!I$27) -> 12.709454 | K81: =J81 -> 12.709454 | L81: =K81 -> 12.709454 | M81: =L81 -> 12.709454 | N81: =M81 -> 12.709454 | O81: =N81 -> 12.709454
B82: Other financial liabilities | G82: =G68*days/(Financials!F$19+Financials!F$20+Financials!F$22+Financials!F$27) -> 66.574971 | H82: =H68*days/(Financials!G$19+Financials!G$20+Financials!G$22+Financials!G$27) -> 62.885113 | I82: =I68*days/(Financials!H$19+Financials!H$20+Financials!H$22+Financials!H$27) -> 54.738864 | J82: =J68*days/(Financials!I$19+Financials!I$20+Financials!I$22+Financials!I$27) -> 55.361208 | K82: =J82 -> 55.361208 | L82: =K82 -> 55.361208 | M82: =L82 -> 55.361208 | N82: =M82 -> 55.361208 | O82: =N82 -> 55.361208
B83: Other current liabilities | G83: =G69*days/(Financials!F$19+Financials!F$20+Financials!F$22+Financials!F$27) -> 38.582123 | H83: =H69*days/(Financials!G$19+Financials!G$20+Financials!G$22+Financials!G$27) -> 36.698231 | I83: =I69*days/(Financials!H$19+Financials!H$20+Financials!H$22+Financials!H$27) -> 34.016917 | J83: =J69*days/(Financials!I$19+Financials!I$20+Financials!I$22+Financials!I$27) -> 35.909395 | K83: =J83 -> 35.909395 | L83: =K83 -> 35.909395 | M83: =L83 -> 35.909395 | N83: =M83 -> 35.909395 | O83: =N83 -> 35.909395
B85: Non-current liabilities
B86: Other financial liabilities | G86: =Financials!F83 -> 2337 | H86: =Financials!G83 -> 2058 | I86: =Financials!H83 -> 2130 | J86: =Financials!I83 -> 2141 | K86: =K89*Financials!J$15 -> 2555.4018 | L86: =L89*Financials!K$15 -> 2515.6642 | M86: =M89*Financials!L$15 -> 2673.2326 | N86: =N89*Financials!M$15 -> 2863.5226 | O86: =O89*Financials!N$15 -> 3119.9736
B87: Other non-current liabilities | G87: =Financials!F85 -> 451 | H87: =Financials!G85 -> 500 | I87: =Financials!H85 -> 235 | J87: =Financials!I85 -> 215 | K87: =K90*Financials!J$15 -> 422.68514 | L87: =L90*Financials!K$15 -> 392.34661 | M87: =M90*Financials!L$15 -> 358.76728 | N87: =N90*Financials!M$15 -> 401.16041 | O87: =O90*Financials!N$15 -> 465.53609
B89: Other FL as a % of operating revenue | G89: =G86/Financials!F$15 -> 0.019212272 | H89: =H86/Financials!G$15 -> 0.014022226 | I89: =I86/Financials!H$15 -> 0.013860871 | J89: =J86/Financials!I$15 -> 0.013135775 | K89: =AVERAGE(G89:J89) -> 0.015057786 | L89: =AVERAGE(H89:K89) -> 0.014019164 | M89: =AVERAGE(I89:L89) -> 0.014018399 | N89: =AVERAGE(J89:M89) -> 0.014057781 | O89: =AVERAGE(K89:N89) -> 0.014288283
B90: Other NCL as a % of opearting revenue | G90: =G87/Financials!F$15 -> 0.0037076315 | H90: =H87/Financials!G$15 -> 0.0034067604 | I90: =I87/Financials!H$15 -> 0.001529251 | J90: =J87/Financials!I$15 -> 0.0013190993 | K90: =AVERAGE(G90:J90) -> 0.0024906855 | L90: =AVERAGE(H90:K90) -> 0.0021864491 | M90: =AVERAGE(I90:L90) -> 0.0018813712 | N90: =AVERAGE(J90:M90) -> 0.0019694013 | O90: =AVERAGE(K90:N90) -> 0.0021319768
B92: Non-current assets
B93: Other financial assets | G93: =Financials!F58 -> 1460 | H93: =Financials!G58 -> 2798 | I93: =Financials!H58 -> 3105 | J93: =Financials!I58 -> 3511 | K93: =K96*Financials!J$15 -> 3089.2324 | L93: =L96*Financials!K$15 -> 3544.681 | M93: =M96*Financials!L$15 -> 3799.7729 | N93: =N96*Financials!M$15 -> 4044.6093 | O93: =O96*Financials!N$15 -> 4243.7517
B94: Other non-current assets | G94: =Financials!F61 -> 2029 | H94: =Financials!G61 -> 2318 | I94: =Financials!H61 -> 2121 | J94: =Financials!I61 -> 2713 | K94: =K97*Financials!J$15 -> 2669.5431 | L94: =L97*Financials!K$15 -> 2780.1184 | M94: =M97*Financials!L$15 -> 2940.07 | N94: =N97*Financials!M$15 -> 3222.794 | O94: =O97*Financials!N$15 -> 3409.8105
B96: Other FA as a % of operating revenue | G96: =G93/Financials!F$15 -> 0.012002532 | H96: =H93/Financials!G$15 -> 0.019064231 | I96: =I93/Financials!H$15 -> 0.020205635 | J96: =J93/Financials!I$15 -> 0.021541199 | K96: =AVERAGE(G96:J96) -> 0.018203399 | L96: =AVERAGE(H96:K96) -> 0.019753616 | M96: =AVERAGE(I96:L96) -> 0.019925962 | N96: =AVERAGE(J96:M96) -> 0.019856044 | O96: =AVERAGE(K96:N96) -> 0.019434756
B97: Other NCA as a % of opearting revenue | G97: =G94/Financials!F$15 -> 0.016680231 | H97: =H94/Financials!G$15 -> 0.015793741 | I97: =I94/Financials!H$15 -> 0.013802304 | J97: =J94/Financials!I$15 -> 0.016645193 | K97: =AVERAGE(G97:J97) -> 0.015730367 | L97: =AVERAGE(H97:K97) -> 0.015492901 | M97: =AVERAGE(I97:L97) -> 0.015417691 | N97: =AVERAGE(J97:M97) -> 0.015821538 | O97: =AVERAGE(K97:N97) -> 0.015615624
A99: # | B99: Retained earnings schedule
B100: Opening balance of retained earnings | K100: =Financials!I77 -> 93745 | L100: =K104 -> 104726.44 | M100: =L104 -> 103159.01 | N100: =M104 -> 114057.64 | O100: =N104 -> 124860.02
B101: Additions of profit for the year | K101: =Financials!J34 -> 28381.596 | L101: =Financials!K34 -> 29050.573 | M101: =Financials!L34 -> 30138.39 | N101: =Financials!M34 -> 31603.06 | O101: =Financials!N34 -> 33351.833
B102: Dividends paid for the year | K102: =Assumptions!K21 -> 17400.159 | L102: =Assumptions!L21 -> 18117.996 | M102: =Assumptions!M21 -> 19239.766 | N102: =Assumptions!N21 -> 20800.676 | O102: =Assumptions!O21 -> 21122.683
B103: Share buy-back for the year | K103: =Assumptions!K24 -> 0 | L103: =Assumptions!L24 -> 12500 | M103: =Assumptions!M24 -> 0 | N103: =Assumptions!N24 -> 0 | O103: =Assumptions!O24 -> 10500
B104: Closing balance of retained earnings | K104: =K100+K101-K102-K103 -> 104726.44 | L104: =L100+L101-L102-L103 -> 103159.01 | M104: =M100+M101-M102-M103 -> 114057.64 | N104: =N100+N101-N102-N103 -> 124860.02 | O104: =O100+O101-O102-O103 -> 126589.17
B106: <- Go back to the top

Sheet Valuation->
A1: \

Sheet DCF
B2: =Dashboard!C2 -> Infosys Ltd.
B3: FCFF
B4: =Dashboard!C4 -> (In ₹ Crore, except equity share and per equity share data)
B6: <-Back to dashboard
B8: Valuation as on specified date | E8: 46084
B9: Date of year ending | E9: 46387
A11: # | B11: Inputs
B13: Trigger | G13: Best | J13: Street | M13: Worst
B15: Selected Scenario: | E15: =VLOOKUP(Dashboard!$G$12,Scenario!$G$12:$H$14,2,TRUE) -> 2 | G15: WACC | H15: =K15-1% -> 0.099163543 | J15: WACC | K15: =WACC!H16 -> 0.10916354 | M15: WACC | N15: =K15+1% -> 0.11916354
B16: Selected Scen. for Adoption of AI: | E16: =VLOOKUP(Dashboard!$G$13,Scenario!$J$12:$L$14,3,) -> 1 | G16: TGR | H16: 0.05 | J16: TGR | K16: 0.04 | M16: TGR | N16: 0.03 | O16: (3%-6%) Google
B18: WACC: | E18: =CHOOSE($E$15,H15,K15,N15) -> 0.10916354
B19: TGR: | E19: =CHOOSE($E$15,H16,K16,N16) -> 0.04
A21: # | B21: Free Cash Flow to Firm | G21: =Financials!J6 -> 46112 | H21: =EDATE(G21,12) -> 46477 | I21: =EDATE(H21,12) -> 46843 | J21: =EDATE(I21,12) -> 47208 | K21: =EDATE(J21,12) -> 47573
B23: EBIT | G23: =Financials!J30 -> 40545.138 | H23: =Financials!K30 -> 41500.818 | I23: =Financials!L30 -> 43054.843 | J23: =Financials!M30 -> 45147.228 | K23: =Financials!N30 -> 47645.476
B24: Tax Rate | G24: 0.3 | H24: 0.3 | I24: 0.3 | J24: 0.3 | K24: 0.3
B25: NOPAT | G25: =G23*(1-G24) -> 28381.596 | H25: =H23*(1-H24) -> 29050.573 | I25: =I23*(1-I24) -> 30138.39 | J25: =J23*(1-J24) -> 31603.06 | K25: =K23*(1-K24) -> 33351.833
B27: Add: Deperciation & Amortisation | G27: =Financials!J106 -> 1553.8619 | H27: =Financials!K106 -> 1977.8622 | I27: =Financials!L106 -> 2339.7887 | J27: =Financials!M106 -> 2829.4995 | K27: =Financials!N106 -> 3356.1537
B28: Less: CapEx | G28: =Financials!J119+Financials!J121+Financials!J122+Financials!J123 -> -2928.9025 | H28: =Financials!K119+Financials!K121+Financials!K122+Financials!K123 -> -4513.8064 | I28: =Financials!L119+Financials!L121+Financials!L122+Financials!L123 -> -4991.7133 | J28: =Financials!M119+Financials!M121+Financials!M122+Financials!M123 -> -5823.6727 | K28: =Financials!N119+Financials!N121+Financials!N122+Financials!N123 -> -6500.2078
B29: Add/Less: Change in WC | G29: =SUM(Financials!J108:J113) -> -199.04203 | H29: =SUM(Financials!K108:K113) -> -1007.4882 | I29: =SUM(Financials!L108:L113) -> -1259.4758 | J29: =SUM(Financials!M108:M113) -> -1563.4814 | K29: =SUM(Financials!N108:N113) -> -1799.901
B30: FCF | G30: =SUM(G25:G29) -> 26807.514 | H30: =SUM(H25:H29) -> 25507.14 | I30: =SUM(I25:I29) -> 26226.99 | J30: =SUM(J25:J29) -> 27045.405 | K30: =SUM(K25:K29) -> 28407.878
B32: Dicsount Period | G32: =G33/2 -> 0.41506849 | H32: =G32+1 -> 1.4150685 | I32: =H32+1 -> 2.4150685 | J32: =I32+1 -> 3.4150685 | K32: =J32+1 -> 4.4150685
B33: Mid Year Discount | G33: =(E9-E8)/365 -> 0.83013699
B34: Terminal Value | K34: =K30*(1+tgr)/(wacc-tgr) -> 427164.26
B35: PV of FCF | G35: =G30/(1+wacc)^G32 -> 25679.129 | H35: =H30/(1+wacc)^H32 -> 22028.754 | I35: =I30/(1+wacc)^I32 -> 20421.189 | J35: =J30/(1+wacc)^J32 -> 18985.869 | K35: =(K30+K34)/(1+wacc)^K32 -> 288335.8
B36: Enterprise Value | G36: =SUM(G35:K35) -> 375450.74
B37: Add: Cash | G37: =Financials!I67+Financials!I69+Financials!I65+Financials!I56 -> 61836
B38: Less: Debt | G38: 0
B39: Equity Value | G39: =SUM(G36:G38) -> 437286.74
B40: Number of Shares | G40: =4054667899/10^7 -> 405.46679
B41: Price per Share | G41: =G39/G40 -> 1078.4773
A43: # | B43: Sensitivity Analysis
C45: Terminal Growth %
B46: WACC | C46: =G41 -> 1078.4773 | D46: 0.02 | E46: =D46+1% -> 0.03 | F46: =E46+1% -> 0.04 | G46: =F46+1% -> 0.05 | H46: =G46+1% -> 0.06
C47: =C48+1% -> 0.13 | D47: 779.94917 | E47: 821.90809 | F47: 873.19121 | G47: 937.29512 | H47: 1019.7144
C48: =C49+1% -> 0.12 | D48: 839.43515 | E48: 892.29892 | F48: 958.37862 | G48: 1043.3382 | H48: 1156.6177
C49: =C50+1% -> 0.11 | D49: 912.14655 | E49: 980.2815 | F49: 1067.8836 | G49: 1184.6863 | H49: 1348.2102
C50: =C51+1% -> 0.1 | D50: 1003.0439 | E50: 1093.3956 | F50: 1213.8647 | G50: 1382.5213 | H50: 1635.5062
C51: 0.09 | D51: 1119.9223 | E51: 1244.2077 | F51: 1418.2073 | G51: 1679.2066 | H51: 2114.2056
A53: # | B53: Street - Low AI Impact | J53: Best - Low AI Impact | R53: Worst - Low AI Impact
C55: Terminal Growth % | K55: Terminal Growth % | S55: Terminal Growth %
B56: WACC | C56: =G51 -> 1679.2066 | D56: 0.02 | E56: =D56+1% -> 0.03 | F56: =E56+1% -> 0.04 | G56: =F56+1% -> 0.05 | H56: =G56+1% -> 0.06 | J56: WACC | K56: =O51 -> 0 | L56: 0.02 | M56: =L56+1% -> 0.03 | N56: =M56+1% -> 0.04 | O56: =N56+1% -> 0.05 | P56: =O56+1% -> 0.06 | R56: WACC | S56: =W51 -> 0 | T56: 0.02 | U56: =T56+1% -> 0.03 | V56: =U56+1% -> 0.04 | W56: =V56+1% -> 0.05 | X56: =W56+1% -> 0.06
C57: =C58+1% -> 0.13 | D57: 779.94917 | E57: 821.90809 | F57: 873.19121 | G57: 937.29512 | H57: 1019.7144 | K57: =K58+1% -> 0.13 | L57: 888.94211 | M57: 940.04882 | N57: 1002.5126 | O57: 1080.5923 | P57: 1180.9804 | S57: =S58+1% -> 0.13 | T57: 674.21002 | U57: 707.31906 | V57: 747.78568 | W57: 798.36895 | X57: 863.40458
C58: =C59+1% -> 0.12 | D58: 839.43515 | E58: 892.29892 | F58: 958.37862 | G58: 1043.3382 | H58: 1156.6177 | K58: =K59+1% -> 0.12 | L58: 961.07078 | M58: 1025.4598 | N58: 1105.946 | O58: 1209.4284 | P58: 1347.4048 | S58: =S59+1% -> 0.12 | T58: 721.45959 | U58: 763.17346 | V58: 815.3158 | W58: 882.35595 | X58: 971.74282
C59: =C60+1% -> 0.11 | D59: 912.14655 | E59: 980.2815 | F59: 1067.8836 | G59: 1184.6863 | H59: 1348.2102 | K59: =K60+1% -> 0.11 | L59: 1049.2992 | M59: 1132.2888 | N59: 1238.9897 | O59: 1381.2576 | P59: 1580.4325 | S59: =S60+1% -> 0.11 | T59: 779.15362 | U59: 832.91771 | V59: 902.04298 | W59: 994.21 | X59: 1123.2438
C60: =C61+1% -> 0.1 | D60: 1003.0439 | E60: 1093.3956 | F60: 1213.8647 | G60: 1382.5213 | H60: 1635.5062 | K60: =K61+1% -> 0.1 | L60: 1159.6692 | M60: 1269.7192 | N60: 1416.4526 | O60: 1621.8794 | P60: 1930.0195 | S60: =S61+1% -> 0.1 | T60: 851.20669 | U60: 922.50168 | V60: 1017.5617 | W60: 1150.6457 | X60: 1350.2716
C61: 0.09 | D61: 1119.9223 | E61: 1244.2077 | F61: 1418.2073 | G61: 1679.2066 | H61: 2114.2056 | K61: 0.09 | L61: 1301.6748 | M61: 1453.0566 | N61: 1664.9912 | O61: 1982.8931 | P61: 2512.7295 | S61: 0.09 | T61: 943.77019 | U61: 1041.8416 | V61: 1179.1417 | W61: 1385.0917 | X61: 1728.3418
A63: # | B63: Street - Moderate AI Impact | J63: Best - Moderate AI Impact | R63: Worst - Moderate AI Impact
C65: Terminal Growth % | K65: Terminal Growth % | S65: Terminal Growth %
B66: WACC | C66: =G61 -> 1679.2066 | D66: 0.02 | E66: =D66+1% -> 0.03 | F66: =E66+1% -> 0.04 | G66: =F66+1% -> 0.05 | H66: =G66+1% -> 0.06 | J66: WACC | K66: =O61 -> 1982.8931 | L66: 0.02 | M66: =L66+1% -> 0.03 | N66: =M66+1% -> 0.04 | O66: =N66+1% -> 0.05 | P66: =O66+1% -> 0.06 | R66: WACC | S66: =W61 -> 1385.0917 | T66: 0.02 | U66: =T66+1% -> 0.03 | V66: =U66+1% -> 0.04 | W66: =V66+1% -> 0.05 | X66: =W66+1% -> 0.06
C67: =C68+1% -> 0.13 | D67: 810.33523 | E67: 854.78921 | F67: 909.12184 | G67: 977.03763 | H67: 1064.3579 | K67: =K68+1% -> 0.13 | L67: 919.32817 | M67: 972.92994 | N67: 1038.4432 | O67: 1120.3348 | P67: 1225.624 | S67: =S68+1% -> 0.13 | T67: 704.59608 | U67: 740.20018 | V67: 783.71631 | W67: 838.11147 | X67: 908.0481
C68: =C69+1% -> 0.12 | D68: 873.27993 | E68: 929.28719 | F68: 999.29627 | G68: 1089.3079 | H68: 1209.3235 | K68: =K69+1% -> 0.12 | L68: 994.91555 | M68: 1062.448 | N68: 1146.8637 | O68: 1255.3981 | P68: 1400.1106 | S68: =S69+1% -> 0.12 | T68: 755.30436 | U68: 800.16173 | V68: 856.23345 | W68: 928.32565 | X68: 1024.4486
C69: =C70+1% -> 0.11 | D69: 950.23433 | E69: 1022.4209 | F69: 1115.2321 | G69: 1238.9805 | H69: 1412.2282 | K69: =K70+1% -> 0.11 | L69: 1087.387 | M69: 1174.4282 | N69: 1286.3383 | O69: 1435.5517 | P69: 1644.4505 | S69: =S70+1% -> 0.11 | T69: 817.2414 | U69: 875.05708 | V69: 949.39154 | W69: 1048.5041 | X69: 1187.2618
C70: =C71+1% -> 0.1 | D70: 1046.4539 | E70: 1142.1783 | F70: 1269.8109 | G70: 1448.4966 | H70: 1716.525 | K70: =K71+1% -> 0.1 | L70: 1203.0791 | M70: 1318.5019 | N70: 1472.3989 | O70: 1687.8547 | P70: 2011.0383 | S70: =S71+1% -> 0.1 | T70: 894.61667 | U70: 971.28436 | V70: 1073.5079 | W70: 1216.621 | X70: 1431.2905
C71: 0.09 | D71: 1170.1971 | E71: 1301.873 | F71: 1486.2194 | G71: 1762.7389 | H71: 2223.6047 | K71: 0.09 | L71: 1351.9496 | M71: 1510.722 | N71: 1733.0033 | O71: 2066.4253 | P71: 2622.1286 | S71: 0.09 | T71: 994.04501 | U71: 1099.507 | V71: 1247.1538 | W71: 1468.6239 | X71: 1837.7408
A73: # | B73: Street - High AI Impact | J73: Best - High AI Impact | R73: Worst - High AI Impact
C75: Terminal Growth % | K75: Terminal Growth % | S75: Terminal Growth %
B76: WACC | C76: =G71 -> 1762.7389 | D76: 0.02 | E76: =D76+1% -> 0.03 | F76: =E76+1% -> 0.04 | G76: =F76+1% -> 0.05 | H76: =G76+1% -> 0.06 | J76: WACC | K76: =O71 -> 2066.4253 | L76: 0.02 | M76: =L76+1% -> 0.03 | N76: =M76+1% -> 0.04 | O76: =N76+1% -> 0.05 | P76: =O76+1% -> 0.06 | R76: WACC | S76: =W71 -> 1468.6239 | T76: 0.02 | U76: =T76+1% -> 0.03 | V76: =U76+1% -> 0.04 | W76: =V76+1% -> 0.05 | X76: =W76+1% -> 0.06
C77: =C78+1% -> 0.13 | D77: 836.96403 | E77: 883.56931 | F77: 940.53131 | G77: 1011.7338 | H77: 1103.2799 | K77: =K78+1% -> 0.13 | L77: 945.95697 | M77: 1001.71 | N77: 1069.8527 | O77: 1155.031 | P77: 1264.5459 | S77: =S78+1% -> 0.13 | T77: 731.22488 | U77: 768.98029 | V77: 815.12578 | W77: 872.80765 | X77: 946.97005
C78: =C79+1% -> 0.12 | D78: 902.899 | E78: 961.61667 | F78: 1035.0138 | G78: 1129.3815 | H78: 1255.2051 | K78: =K79+1% -> 0.12 | L78: 1024.5346 | M78: 1094.7775 | N78: 1182.5812 | O78: 1295.4716 | P78: 1445.9921 | S78: =S79+1% -> 0.12 | T78: 784.92344 | U78: 832.49122 | V78: 891.95095 | W78: 968.39917 | X78: 1070.3301
C79: =C80+1% -> 0.11 | D79: 983.52019 | E79: 1059.2001 | F79: 1156.5029 | G79: 1286.2399 | H79: 1467.8717 | K79: =K80+1% -> 0.11 | L79: 1120.6729 | M79: 1211.2074 | N79: 1327.609 | O79: 1482.8111 | P79: 1700.094 | S79: =S80+1% -> 0.11 | T79: 850.52726 | U79: 911.83633 | V79: 990.66229 | W79: 1095.7636 | X79: 1242.9053
C80: =C81+1% -> 0.1 | D80: 1084.3373 | E80: 1184.6942 | F80: 1318.5035 | G80: 1505.8364 | H80: 1786.8359 | K80: =K81+1% -> 0.1 | L80: 1240.9626 | M80: 1361.0178 | N80: 1521.0914 | O80: 1745.1945 | P80: 2081.3491 | S80: =S81+1% -> 0.1 | T80: 932.5001 | U80: 1013.8003 | V80: 1122.2005 | W80: 1273.9608 | X80: 1501.6013
C81: 0.09 | D81: 1214.0085 | E81: 1352.0568 | F81: 1545.3243 | G81: 1835.2257 | H81: 2318.3946 | K81: 0.09 | L81: 1395.761 | M81: 1560.9057 | N81: 1792.1082 | O81: 2138.9121 | P81: 2716.9185 | S81: 0.09 | T81: 1037.8564 | U81: 1149.6907 | V81: 1306.2587 | W81: 1541.1107 | X81: 1932.5307
B84: Median | D84: =MEDIAN($D$57:$H$61,$D$67:$H$71,$D$77:$H$81) -> 1115.2321 | J84: Median | L84: =MEDIAN($L$57:$P$61,$L$67:$P$71,$L$77:$P$81) -> 1286.3383 | R84: Median | T84: =MEDIAN($T$57:$X$61,$T$67:$X$71,$T$77:$X$81) -> 946.97005
B85: 75th Percentile | D85: =PERCENTILE(($D$57:$H$61,$D$67:$H$71,$D$77:$H$81),75%) -> 1333.3568 | J85: 75th Percentile | L85: =PERCENTILE(($L$57:$P$61,$L$67:$P$71,$L$77:$P$81),0.75) -> 1540.9986 | R85: 75th Percentile | T85: =PERCENTILE(($T$57:$X$61,$T$67:$X$71,$T$77:$X$81),0.75) -> 1122.7222
B86: 25th Percentile | D86: =PERCENTILE(($D$57:$H$61,$D$67:$H$71,$D$77:$H$81),25%) -> 969.32715 | J86: 25th Percentile | L86: =PERCENTILE(($L$57:$P$61,$L$67:$P$71,$L$77:$P$81),0.25) -> 1113.1404 | R86: 25th Percentile | T86: =PERCENTILE(($T$57:$X$61,$T$67:$X$71,$T$77:$X$81),0.25) -> 832.70447

Sheet WACC
B2: =Dashboard!C2 -> Infosys Ltd.
B3: WACC
B4: =Dashboard!C4 -> (In ₹ Crore, except equity share and per equity share data)
B6: <-Back to dashboard
B8: Cost of Equity | G8: Capital Structure
B9: Risk Free Rate | D9: 0.0668 | G9: Market Cap | H9: 589562
B10: Market Returns | D10: =Beta!L21 -> 0.11561994 | G10: Debt | H10: =0 -> 0
B11: Levered beta | D11: =Beta!L18 -> 0.8677508 | G11: Total Capital | H11: =H9+H10 -> 589562
B12: Cost of equity | D12: =D9+(D10-D9)*D11 -> 0.10916354
B14: Cost of Debt | G14: Cost of Equity | H14: =D12*(H9/H11) -> 0.10916354
B15: (Using credit rating) | G15: Cost of Debt | H15: =D20*(H10/H11) -> 0
B16: Risk Free Rate | D16: 0.0668 | G16: WACC | H16: =H14+H15 -> 0.10916354
B17: Risk premium | D17: 0.004
B18: Pre-tax cost of debt | D18: =D16+D17 -> 0.0708
B19: Tax Rate | D19: 0.3
B20: Post-tax cost of debt | D20: =D18*(1-D19) -> 0.04956
B22: End
A23: #

Sheet Beta
B2: =Dashboard!C2 -> Infosys Ltd.
B3: Beta
B4: =Dashboard!C4 -> (In ₹ Crore, except equity share and per equity share data)
B6: <-Back to dashboard
B8: Infosys LTD. | F8: Nifty-50 | J8: Beta
B10: Date | C10: Price | D10: Returns | F10: Date | G10: Price | H10: Returns | J10: Calculated beta | L10: =SLOPE(D12:D374,H12:H374) -> 0.82366773 | N10: Median | P10: =MEDIAN(C11:C24) -> 1534.55
B11: 46082 | C11: 1288.9 | F11: 46082 | G11: 24865.7 | N11: 75th Percentile | P11: =PERCENTILE(C11:C24,75%) -> 1594.0125
B12: 46054 | C12: 1300.1 | D12: =C12/C11-1 -> 0.0086895803 | F12: 46054 | G12: 25178.65 | H12: =G12/G11-1 -> 0.01258561 | J12: Levered beta | L12: =L10 -> 0.82366773 | N12: 25th Percentile | P12: =PERCENTILE(C11:C24,25%) -> 1472.775
B13: 46023 | C13: 1641 | D13: =C13/C12-1 -> 0.2622106 | F13: 46023 | G13: 25320.65 | H13: =G13/G12-1 -> 0.0056396987 | J13: Raw beta weight | L13: 0.75
B14: 45992 | C14: 1615.4 | D14: =C14/C13-1 -> -0.015600244 | F14: 45992 | G14: 26129.6 | H14: =G14/G13-1 -> 0.031948232
B15: 45962 | C15: 1560.1 | D15: =C15/C14-1 -> -0.034233007 | F15: 45962 | G15: 26202.95 | H15: =G15/G14-1 -> 0.0028071612 | J15: Market beta | L15: =SLOPE(H12:H374,H12:H374) -> 1
B16: 45931 | C16: 1482.3 | D16: =C16/C15-1 -> -0.049868598 | F16: 45931 | G16: 25722.1 | H16: =G16/G15-1 -> -0.018350987 | J16: Raw beta weight | L16: 0.25
B17: 45901 | C17: 1441.8 | D17: =C17/C16-1 -> -0.027322404 | F17: 45901 | G17: 24611.1 | H17: =G17/G16-1 -> -0.04319243
B18: 45870 | C18: 1469.6 | D18: =C18/C17-1 -> 0.019281454 | F18: 45870 | G18: 24426.85 | H18: =G18/G17-1 -> -0.0074864594 | J18: Adjusted beta | L18: =(L12*L13)+(L15*L16) -> 0.8677508
B19: 45839 | C19: 1509 | D19: =C19/C18-1 -> 0.026810016 | F19: 45839 | G19: 24768.35 | H19: =G19/G18-1 -> 0.013980517
B20: 45809 | C20: 1601.8 | D20: =C20/C19-1 -> 0.061497681 | F20: 45809 | G20: 25517.05 | H20: =G20/G19-1 -> 0.030228094 | J20: Total years | L20: =YEARFRAC(F374,F11,1) -> 30.247775
B21: 45778 | C21: 1562.7 | D21: =C21/C20-1 -> -0.024410039 | F21: 45778 | G21: 24750.7 | H21: =G21/G20-1 -> -0.03003286 | J21: Market returns (%) | L21: =_xlfn.RRI(L20,G374,G11) -> 0.11561994
B22: 45748 | C22: 1500.1 | D22: =C22/C21-1 -> -0.040058872 | F22: 45748 | G22: 24334.2 | H22: =G22/G21-1 -> -0.016827807
B23: 45717 | C23: 1570.65 | D23: =C23/C22-1 -> 0.047030198 | F23: 45717 | G23: 23519.35 | H23: =G23/G22-1 -> -0.033485794
B24: 45689 | C24: 1687.7 | D24: =C24/C23-1 -> 0.074523287 | F24: 45689 | G24: 22124.7 | H24: =G24/G23-1 -> -0.059297982
B25: 45658 | C25: 1879.8 | D25: =C25/C24-1 -> 0.11382355 | F25: 45658 | G25: 23508.4 | H25: =G25/G24-1 -> 0.062540961
B26: 45627 | C26: 1880 | D26: =C26/C25-1 -> 0.0001063943 | F26: 45627 | G26: 23644.8 | H26: =G26/G25-1 -> 0.0058021813
B27: 45597 | C27: 1857.85 | D27: =C27/C26-1 -> -0.011781915 | F27: 45597 | G27: 24131.1 | H27: =G27/G26-1 -> 0.02056689
B28: 45566 | C28: 1757.25 | D28: =C28/C27-1 -> -0.054148613 | F28: 45566 | G28: 24205.35 | H28: =G28/G27-1 -> 0.0030769422
B29: 45536 | C29: 1875.6 | D29: =C29/C28-1 -> 0.067349552 | F29: 45536 | G29: 25810.85 | H29: =G29/G28-1 -> 0.066328312
B30: 45505 | C30: 1943.7 | D30: =C30/C29-1 -> 0.036308381 | F30: 45505 | G30: 25235.9 | H30: =G30/G29-1 -> -0.022275516
B31: 45474 | C31: 1868.25 | D31: =C31/C30-1 -> -0.038817719 | F31: 45474 | G31: 24951.15 | H31: =G31/G30-1 -> -0.011283529
B32: 45444 | C32: 1566.75 | D32: =C32/C31-1 -> -0.16138097 | F32: 45444 | G32: 24010.6 | H32: =G32/G31-1 -> -0.037695657
B33: 45413 | C33: 1406.9 | D33: =C33/C32-1 -> -0.10202649 | F33: 45413 | G33: 22530.7 | H33: =G33/G32-1 -> -0.061635278
... B374: 35034 | C374: 0.79 | D374: =C374/C373-1 -> 0.012820513 | F374: 35034 | G374: 908.53 | H374: =G374/G373-1 -> 0.070849343

Sheet Comps
B2: # | C2: Comparable Company Analysis of Indian IT - Software and Consulting Companies with Market Cap of above 10 Thousand Crore.
C3: (In ₹ Crore, except equity share and per equity share data)
C5: Company Name | E5: Share Price (₹) | F5: Revenue | G5: EBITDA | H5: Net Income | I5: Enterprise Value | J5: EV / Rev | K5: EV / EBITDA | L5: P / S | M5: P / E
C6: Infosys | E6: 1285 | F6: 173173 | G6: =40563+4776 -> 45339 | H6: 28003 | I6: 510024.58 | J6: =I$6/F6 -> 2.9451738 | K6: =J$6*10^5/G6 -> 6.4958949 | L6: 3.01 | M6: 18.01
C7: TCS | E7: 2409 | F7: 260802 | G7: 74775 | H7: 47963 | I7: 868076.38 | J7: =I$6/F7 -> 1.9556007 | K7: =J$6*10^5/G7 -> 3.9387145 | L7: 3.34 | M7: 17.06
C8: HCL Technologies | E8: 1401.9 | F8: 126409 | G8: 28179 | H8: 16471 | I8: 363460.66 | J8: =I$6/F8 -> 4.0347173 | K8: =J$6*10^5/G8 -> 10.451662 | L8: 3.01 | M8: 22.11
C9: Wipro | E9: 189.9 | F9: 90891.9 | G9: 21785.8 | H9: 13332 | I9: 202254.96 | J9: =I$6/F9 -> 5.6113315 | K9: =J$6*10^5/G9 -> 13.518777 | L9: 2.19 | M9: 15.02
C10: Tech Mahindra | E10: 1421.75 | F10: 55123.3 | G10: 8715.6 | H10: 4591 | I10: 136976.69 | J10: =I$6/F10 -> 9.2524319 | K10: =J$6*10^5/G10 -> 33.79198 | L10: 2.53 | M10: 28.97
C11: LTIMindtree | E11: 4288 | F11: 40787.6 | G11: 8349.3 | H11: 4724 | I11: 126533.56 | J11: =I$6/F11 -> 12.504403 | K11: =J$6*10^5/G11 -> 35.274499 | L11: 3.12 | M11: 24.59
C12: Persistent Systems | E12: 4911 | F12: 13934.63 | G12: 2777.44 | H12: 1731.62 | I12: 76671.71 | J12: =I$6/F12 -> 36.601229 | K12: =J$6*10^5/G12 -> 106.03915 | L12: 5.56 | M12: 43.11
C13: Mphasis | E13: 2131.5 | F13: 15347.02 | G13: 3155.15 | H13: 1799.45 | I13: 41036.33 | J13: =I$6/F13 -> 33.232809 | K13: =J$6*10^5/G13 -> 93.344969 | L13: 2.65 | M13: 22.24
C14: Coforge | E14: 1154.5 | F14: 15272.3 | G14: 2669.1 | H14: 1385.8 | I14: 39207.25 | J14: =I$6/F14 -> 33.395401 | K14: =J$6*10^5/G14 -> 110.34333 | L14: 2.54 | M14: 30.88
C15: Hexaware Tech. | E15: 442.5 | F15: 13430.4 | G15: 2299.7 | H15: 1368.3 | I15: 25735.6 | J15: =I$6/F15 -> 37.975383 | K15: =J$6*10^5/G15 -> 128.06774 | L15: 2.01 | M15: 18.61
C16: Tata Elxsi | E16: 4250.35 | F16: 3672.01 | G16: 986.41 | H16: 580.5 | I16: 25378.12 | J16: =I$6/F16 -> 138.8952 | K16: =J$6*10^5/G16 -> 298.57501 | L16: 7.21 | M16: 41.99
C17: KPIT Technologi. | E17: 675.25 | F17: 6272.27 | G17: 1360.64 | H17: 719.13 | I17: 18096.68 | J17: =I$6/F17 -> 81.314194 | K17: =J$6*10^5/G17 -> 216.45503 | L17: 2.95 | M17: 24.31
C18: Fractal Analyt. | E18: 841.35 | F18: 2765.4 | G18: 341.9 | H18: 220.6 | I18: 14609.46 | J18: =I$6/F18 -> 184.43067 | K18: =J$6*10^5/G18 -> 861.4138 | L18: 5.23 | M18: 69.16
C19: Zensar Tech. | E19: 542.05 | F19: 5595.9 | G19: 1107.9 | H19: 740.4 | I19: 11628.2 | J19: =I$6/F19 -> 91.142547 | K19: =J$6*10^5/G19 -> 265.8339 | L19: 2.2 | M19: 16.2
C21: Mean | E21: =AVERAGE(E7:E19) -> 1896.85 | J21: =AVERAGE(J7:J19) -> 51.565071 | K21: =AVERAGE(K7:K19) -> 167.46527 | L21: =AVERAGE(L7:L19) -> 3.4261538 | M21: =AVERAGE(M7:M19) -> 28.788462
C22: Median | E22: =MEDIAN(E7:E19) -> 1401.9 | J22: =MEDIAN(J7:J19) -> 33.395401 | K22: =MEDIAN(K7:K19) -> 106.03915 | L22: =MEDIAN(L7:L19) -> 2.95 | M22: =MEDIAN(M7:M19) -> 24.31
C23: 75th Percentile | E23: =PERCENTILE(E7:E19,75%) -> 2409 | J23: =PERCENTILE(J7:J19,75%) -> 81.314194 | K23: =PERCENTILE(K7:K19,75%) -> 216.45503 | L23: =PERCENTILE(L7:L19,75%) -> 3.34 | M23: =PERCENTILE(M7:M19,75%) -> 30.88
C24: 25th Percentile | E24: =PERCENTILE(E7:E19,25%) -> 675.25 | J24: =PERCENTILE(J7:J19,25%) -> 9.2524319 | K24: =PERCENTILE(K7:K19,25%) -> 33.79198 | L24: =PERCENTILE(L7:L19,25%) -> 2.53 | M24: =PERCENTILE(M7:M19,25%) -> 18.61
B26: # | C26: Valuation Summary
K27: Range of valuation | O27: Equity Value | S27: Equity Value
C28: Infosys Ltd. | E28: Revenue | F28: EBITDA | G28: Net Income | H28: # Share outst. | I28: Cash | J28: Debt | K28: EV / Rev | L28: EV / EBITDA | M28: P / Sales | N28: P / E | O28: EV / Rev | P28: EV / EBITDA | Q28: P / Sales | R28: P / E | S28: EV / Rev | T28: EV / EBITDA | U28: P / Sales | V28: P / E
C29: Mean | E29: =F6 -> 173173 | F29: =G6 -> 45339 | G29: =H6 -> 28003 | H29: =4054667899 -> 4054667899 | I29: 61836 | J29: 0 | K29: =J21 -> 51.565071 | L29: =K21 -> 167.46527 | M29: =L21 -> 3.4261538 | N29: =M21 -> 28.788462 | O29: =K29*E29 -> 8929678 | P29: =L29*F29 -> 7592708.1 | Q29: =M29*E29 -> 593317.34 | R29: =N29*G29 -> 806163.29 | S29: =$H29/O29 -> 454.06653 | T29: =$H29/P29 -> 534.02131 | U29: =$H29/10^1/Q29 -> 683.38942 | V29: =$H29/10^1/R29 -> 502.95864
C30: Median | E30: =E29 -> 173173 | F30: =F29 -> 45339 | G30: =G29 -> 28003 | H30: =4054667899 -> 4054667899 | I30: =I29 -> 61836 | J30: =J29 -> 0 | K30: =J22 -> 33.395401 | L30: =K22 -> 106.03915 | M30: =L22 -> 2.95 | N30: =M22 -> 24.31 | O30: =K30*E30 -> 5783181.7 | P30: =L30*F30 -> 4807709.1 | Q30: =M30*E30 -> 510860.35 | R30: =N30*G30 -> 680752.93 | S30: =$H30/O30 -> 701.11369 | T30: =$H30/P30 -> 843.36799 | U30: =$H30/10^1/Q30 -> 793.69399 | V30: =$H30/10^1/R30 -> 595.6152
C31: 75th Percentile | E31: =E30 -> 173173 | F31: =F30 -> 45339 | G31: =G30 -> 28003 | H31: =4054667899 -> 4054667899 | I31: =I30 -> 61836 | J31: =J30 -> 0 | K31: =J23 -> 81.314194 | L31: =K23 -> 216.45503 | M31: =L23 -> 3.34 | N31: =M23 -> 30.88 | O31: =K31*E31 -> 14081423 | P31: =L31*F31 -> 9813854.8 | Q31: =M31*E31 -> 578397.82 | R31: =N31*G31 -> 864732.64 | S31: =$H31/O31 -> 287.94447 | T31: =$H31/P31 -> 413.15752 | U31: =$H31/10^1/Q31 -> 701.01715 | V31: =$H31/10^1/R31 -> 468.89266
C32: 25th Percentile | E32: =E31 -> 173173 | F32: =F31 -> 45339 | G32: =G31 -> 28003 | H32: =4054667899 -> 4054667899 | I32: =I31 -> 61836 | J32: =J31 -> 0 | K32: =J24 -> 9.2524319 | L32: =K24 -> 33.79198 | M32: =L24 -> 2.53 | N32: =M24 -> 18.61 | O32: =K32*E32 -> 1602271.4 | P32: =L32*F32 -> 1532094.6 | Q32: =M32*E32 -> 438127.69 | R32: =N32*G32 -> 521135.83 | S32: =$H32/10^1/O32 -> 253.0575 | T32: =$H32/10^1/P32 -> 264.64867 | U32: =$H32/10^1/Q32 -> 925.45347 | V32: =$H32/10^1/R32 -> 778.04435
C34: Mean | K34: =S29 -> 454.06653 | L34: =T29 -> 534.02131 | M34: =U29 -> 683.38942 | N34: =V29 -> 502.95864
C35: Median | K35: =S30 -> 701.11369 | L35: =T30 -> 843.36799 | M35: =U30 -> 793.69399 | N35: =V30 -> 595.6152
C36: 75th Percentile | K36: =S31 -> 287.94447 | L36: =T31 -> 413.15752 | M36: =U31 -> 701.01715 | N36: =V31 -> 468.89266
C37: 25th Percentile | K37: =S32 -> 253.0575 | L37: =T32 -> 264.64867 | M37: =U32 -> 925.45347 | N37: =V32 -> 778.04435

Sheet Ratio Analysis
B2: =Dashboard!C2 -> Infosys Ltd.
B3: Ratio Analysis
B4: =Dashboard!C4 -> (In ₹ Crore, except equity share and per equity share data)
B6: <-Back to dashboard
A8: # | B8: Profitability Ratios | E8: 44651 | F8: =EDATE(E8,12) -> 45016 | G8: =EDATE(F8,12) -> 45382 | H8: =EDATE(G8,12) -> 45747 | I8: =EDATE(H8,12) -> 46112 | J8: =EDATE(I8,12) -> 46477 | K8: =EDATE(J8,12) -> 46843 | L8: =EDATE(K8,12) -> 47208 | M8: =EDATE(L8,12) -> 47573
B9: Gross profit margin | E9: =(Financials!F17-(Financials!F19+Financials!F20+Financials!F21+Financials!F22+Financials!F23+Financials!F24+Financials!F27))/Financials!F$17 -> 0.27260844 | F9: =(Financials!G17-(Financials!G19+Financials!G20+Financials!G21+Financials!G22+Financials!G23+Financials!G24+Financials!G27))/Financials!G$17 -> 0.25310434 | G9: =(Financials!H17-(Financials!H19+Financials!H20+Financials!H21+Financials!H22+Financials!H23+Financials!H24+Financials!H27))/Financials!H$17 -> 0.25972812 | H9: =(Financials!I17-(Financials!I19+Financials!I20+Financials!I21+Financials!I22+Financials!I23+Financials!I24+Financials!I27))/Financials!I$17 -> 0.25713428 | I9: =(Financials!J17-(Financials!J19+Financials!J20+Financials!J21+Financials!J22+Financials!J23+Financials!J24+Financials!J27))/Financials!J$17 -> 0.2426101 | J9: =(Financials!K17-(Financials!K19+Financials!K20+Financials!K21+Financials!K22+Financials!K23+Financials!K24+Financials!K27))/Financials!K$17 -> 0.23696325 | K9: =(Financials!L17-(Financials!L19+Financials!L20+Financials!L21+Financials!L22+Financials!L23+Financials!L24+Financials!L27))/Financials!L$17 -> 0.23280985 | L9: =(Financials!M17-(Financials!M19+Financials!M20+Financials!M21+Financials!M22+Financials!M23+Financials!M24+Financials!M27))/Financials!M$17 -> 0.23034668 | M9: =(Financials!N17-(Financials!N19+Financials!N20+Financials!N21+Financials!N22+Financials!N23+Financials!N24+Financials!N27))/Financials!N$17 -> 0.22842748
B10: EBITDA margin | E10: =Financials!F30/Financials!F$17 -> 0.24294797 | F10: =Financials!G30/Financials!G$17 -> 0.22293735 | G10: =Financials!H30/Financials!H$17 -> 0.22722423 | H10: =Financials!I30/Financials!I$17 -> 0.22575185 | I10: =Financials!J30/Financials!J$17 -> 0.23365543 | J10: =Financials!K30/Financials!K$17 -> 0.2261837 | K10: =Financials!L30/Financials!L$17 -> 0.22081006 | L10: =Financials!M30/Financials!M$17 -> 0.21676164 | M10: =Financials!N30/Financials!N$17 -> 0.21339585
B11: EBIT margin | E11: =(Financials!F17-(Financials!F28-Financials!F25))/Financials!F17 -> 0.27099471 | F11: =(Financials!G17-(Financials!G28-Financials!G25))/Financials!G17 -> 0.25120427 | G11: =(Financials!H17-(Financials!H28-Financials!H25))/Financials!H17 -> 0.2567606 | H11: =(Financials!I17-(Financials!I28-Financials!I25))/Financials!I17 -> 0.25463713 | I11: =(Financials!J17-(Financials!J28-Financials!J25))/Financials!J17 -> 0.2426101 | J11: =(Financials!K17-(Financials!K28-Financials!K25))/Financials!K17 -> 0.23696325 | K11: =(Financials!L17-(Financials!L28-Financials!L25))/Financials!L17 -> 0.23280985 | L11: =(Financials!M17-(Financials!M28-Financials!M25))/Financials!M17 -> 0.23034668 | M11: =(Financials!N17-(Financials!N28-Financials!N25))/Financials!N17 -> 0.22842748
B12: Net profit margin | E12: =Financials!F34/Financials!F17 -> 0.178689 | F12: =Financials!G34/Financials!G17 -> 0.16129205 | G12: =Financials!H34/Financials!H17 -> 0.16572695 | H12: =Financials!I34/Financials!I17 -> 0.16057386 | I12: =Financials!J34/Financials!J17 -> 0.1635588 | J12: =Financials!K34/Financials!K17 -> 0.15832859 | K12: =Financials!L34/Financials!L17 -> 0.15456704 | L12: =Financials!M34/Financials!M17 -> 0.15173315 | M12: =Financials!N34/Financials!N17 -> 0.1493771
B13: ROE | E13: =Financials!F34/Financials!F79 -> 0.29241048 | F13: =Financials!G34/Financials!G79 -> 0.31806847 | G13: =Financials!H34/Financials!H79 -> 0.29671833 | H13: =Financials!I34/Financials!I79 -> 0.27805786 | I13: =Financials!J34/Financials!J79 -> 0.26471995 | J13: =Financials!K34/Financials!K79 -> 0.27490185 | K13: =Financials!L34/Financials!L79 -> 0.25846385 | L13: =Financials!M34/Financials!M79 -> 0.24798237 | M13: =Financials!N34/Financials!N79 -> 0.25813263
B14: ROA | E14: =Financials!F34/Financials!F73 -> 0.18786105 | F14: =Financials!G34/Financials!G73 -> 0.19161315 | G14: =Financials!H34/Financials!H73 -> 0.1904596 | H14: =Financials!I34/Financials!I73 -> 0.17964715 | I14: =Financials!J34/Financials!J73 -> 0.17445955 | J14: =Financials!K34/Financials!K73 -> 0.17771215 | K14: =Financials!L34/Financials!L73 -> 0.17008699 | L14: =Financials!M34/Financials!M73 -> 0.16525325 | M14: =Financials!N34/Financials!N73 -> 0.16960287
B15: ROCE | E15: =Financials!F30/(Financials!F73-Financials!F95) -> 0.35725303 | F15: =Financials!G30/(Financials!G73-Financials!G95) -> 0.38464735 | G15: =Financials!H30/(Financials!H73-Financials!H95) -> 0.36344173 | H15: =Financials!I30/(Financials!I73-Financials!I95) -> 0.35461515 | I15: =Financials!J30/(Financials!J73-Financials!J95) -> 0.34452036 | J15: =Financials!K30/(Financials!K73-Financials!K95) -> 0.35752474 | K15: =Financials!L30/(Financials!L73-Financials!L95) -> 0.33866298 | L15: =Financials!M30/(Financials!M73-Financials!M95) -> 0.32668171 | M15: =Financials!N30/(Financials!N73-Financials!N95) -> 0.33963643
B16: ROIC | E16: =(Financials!F30*(1-30%))/(Schedule!G72+Financials!F50) -> 0.6661715 | F16: =(Financials!G30*(1-30%))/(Schedule!H72+Financials!G50) -> 0.66825383 | G16: =(Financials!H30*(1-30%))/(Schedule!I72+Financials!H50) -> 0.65251379 | H16: =(Financials!I30*(1-30%))/(Schedule!J72+Financials!I50) -> 0.67898483 | I16: =(Financials!J30*(1-30%))/(Schedule!K72+Financials!J50) -> 0.6964309 | J16: =(Financials!K30*(1-30%))/(Schedule!L72+Financials!K50) -> 0.67620646 | K16: =(Financials!L30*(1-30%))/(Schedule!M72+Financials!L50) -> 0.66142084 | L16: =(Financials!M30*(1-30%))/(Schedule!N72+Financials!M50) -> 0.65123342 | M16: =(Financials!N30*(1-30%))/(Schedule!O72+Financials!N50) -> 0.64400866
A18: # | B18: Liquidity Ratios | E18: 44651 | F18: =EDATE(E18,12) -> 45016 | G18: =EDATE(F18,12) -> 45382 | H18: =EDATE(G18,12) -> 45747 | I18: =EDATE(H18,12) -> 46112 | J18: =EDATE(I18,12) -> 46477 | K18: =EDATE(J18,12) -> 46843 | L18: =EDATE(K18,12) -> 47208 | M18: =EDATE(L18,12) -> 47573
B19: Current ratio | E19: =Financials!F72/Financials!F95 -> 1.9993751 | F19: =Financials!G72/Financials!G95 -> 1.8088348 | G19: =Financials!H72/Financials!H95 -> 2.3053049 | H19: =Financials!I72/Financials!I95 -> 2.266021 | I19: =Financials!J72/Financials!J95 -> 2.4708038 | J19: =Financials!K72/Financials!K95 -> 2.3472251 | K19: =Financials!L72/Financials!L95 -> 2.4769219 | L19: =Financials!M72/Financials!M95 -> 2.5810461 | M19: =Financials!N72/Financials!N95 -> 2.5057457
B20: Quick ratio | E20: =Financials!F72/Financials!F95 -> 1.9993751 | F20: =Financials!G72/Financials!G95 -> 1.8088348 | G20: =Financials!H72/Financials!H95 -> 2.3053049 | H20: =Financials!I72/Financials!I95 -> 2.266021 | I20: =Financials!J72/Financials!J95 -> 2.4708038 | J20: =Financials!K72/Financials!K95 -> 2.3472251 | K20: =Financials!L72/Financials!L95 -> 2.4769219 | L20: =Financials!M72/Financials!M95 -> 2.5810461 | M20: =Financials!N72/Financials!N95 -> 2.5057457
B21: Cash ratio | E21: =(Financials!G67+Financials!G65)/Financials!F95 -> 0.56786596 | F21: =(Financials!H67+Financials!H65)/Financials!G95 -> 0.70691063 | G21: =(Financials!I67+Financials!I65)/Financials!H95 -> 0.95213177 | H21: =(Financials!J67+Financials!J65)/Financials!I95 -> 1.1358465 | I21: =(Financials!K67+Financials!K65)/Financials!J95 -> 1.0073666 | J21: =(Financials!L67+Financials!L65)/Financials!K95 -> 1.142815 | K21: =(Financials!M67+Financials!M65)/Financials!L95 -> 1.2488149 | L21: =(Financials!N67+Financials!N65)/Financials!M95 -> 1.1637613 | M21: =(Financials!O67+Financials!O65)/Financials!N95 -> 0
B22: Operating cash flow ratio | E22: - | F22: - | G22: - | H22: - | I22: =Financials!J116/Financials!J95 -> 0.66149983 | J22: =Financials!K116/Financials!K95 -> 0.63409623 | K22: =Financials!L116/Financials!L95 -> 0.6242189 | L22: =Financials!M116/Financials!M95 -> 0.62030861 | M22: =Financials!N116/Financials!N95 -> 0.61995489
B23: Net working capital | E23: =Financials!F72-Financials!F95 -> 33582 | F23: =Financials!G72-Financials!G95 -> 31695 | G23: =Financials!H72-Financials!H95 -> 50638 | H23: =Financials!I72-Financials!I95 -> 54249 | I23: =Financials!J72-Financials!J95 -> 66182.063 | J23: =Financials!K72-Financials!K95 -> 63847.216 | K23: =Financials!L72-Financials!L95 -> 73937.89 | L23: =Financials!M72-Financials!M95 -> 83859.849 | M23: =Financials!N72-Financials!N95 -> 84868.145
B24: NWC as a % of revenue | E24: =E23/Financials!F17 -> 0.27096243 | F24: =F23/Financials!G17 -> 0.21205208 | G24: =G23/Financials!H17 -> 0.31972269 | H24: =H23/Financials!I17 -> 0.3256438 | I24: =I23/Financials!J17 -> 0.38139711 | J24: =J23/Financials!K17 -> 0.34797385 | K24: =K23/Financials!L17 -> 0.37919613 | L24: =L23/Financials!M17 -> 0.40262934 | M24: =M23/Financials!N17 -> 0.38010975
A26: # | B26: Efficiency Ratios | E26: 44651 | F26: =EDATE(E26,12) -> 45016 | G26: =EDATE(F26,12) -> 45382 | H26: =EDATE(G26,12) -> 45747 | I26: =EDATE(H26,12) -> 46112 | J26: =EDATE(I26,12) -> 46477 | K26: =EDATE(J26,12) -> 46843 | L26: =EDATE(K26,12) -> 47208 | M26: =EDATE(L26,12) -> 47573
B27: Asset turnover | E27: =Financials!F17/Financials!F73 -> 1.0513297 | F27: =Financials!G17/Financials!G73 -> 1.1879888 | G27: =Financials!H17/Financials!H73 -> 1.1492374 | H27: =Financials!I17/Financials!I73 -> 1.118782 | I27: =Financials!J17/Financials!J73 -> 1.0666473 | J27: =Financials!K17/Financials!K73 -> 1.1224262 | K27: =Financials!L17/Financials!L73 -> 1.1004092 | L27: =Financials!M17/Financials!M73 -> 1.0891045 | M27: =Financials!N17/Financials!N73 -> 1.1354008
B28: Fixed asset turnover | E28: =Financials!F17/Financials!F50 -> 9.4788528 | F28: =Financials!G17/Financials!G50 -> 11.199461 | G28: =Financials!H17/Financials!H50 -> 12.803638 | H28: =Financials!I17/Financials!I50 -> 14.144167 | I28: =Financials!J17/Financials!J50 -> 13.623244 | J28: =Financials!K17/Financials!K50 -> 13.716631 | K28: =Financials!L17/Financials!L50 -> 13.772596 | L28: =Financials!M17/Financials!M50 -> 13.887284 | M28: =Financials!N17/Financials!N50 -> 14.076893
B29: Receivables turnover | E29: =Financials!F17/Financials!F66 -> 5.4602168 | F29: =Financials!G17/Financials!G66 -> 5.879012 | G29: =Financials!H17/Financials!H66 -> 5.2456198 | H29: =Financials!I17/Financials!I66 -> 5.3466205 | I29: =Financials!J17/Financials!J66 -> 5.3487981 | J29: =Financials!K17/Financials!K66 -> 5.3487981 | K29: =Financials!L17/Financials!L66 -> 5.3487981 | L29: =Financials!M17/Financials!M66 -> 5.3487981 | M29: =Financials!N17/Financials!N66 -> 5.3487981
B30: Payable turnover | E30: =Financials!F17/Financials!F90 -> 29.979681 | F30: =Financials!G17/Financials!G90 -> 38.672186 | G30: =Financials!H17/Financials!H90 -> 40.035642 | H30: =Financials!I17/Financials!I90 -> 40.007205 | I30: =Financials!J17/Financials!J90 -> 39.201897 | J30: =Financials!K17/Financials!K90 -> 38.880688 | K30: =Financials!L17/Financials!L90 -> 38.6452 | L30: =Financials!M17/Financials!M90 -> 38.501943 | M30: =Financials!N17/Financials!N90 -> 38.391551
B31: DSO | E31: =365/E29 -> 66.847163 | F31: =365/F29 -> 62.085262 | G31: =365/G29 -> 69.581863 | H31: =365/H29 -> 68.267423 | I31: =365/I29 -> 68.239629 | J31: =365/J29 -> 68.239629 | K31: =365/K29 -> 68.239629 | L31: =365/L29 -> 68.239629 | M31: =365/M29 -> 68.239629
B32: DPO | E32: =365/E30 -> 12.174913 | F32: =365/F30 -> 9.4383079 | G32: =365/G30 -> 9.1168764 | H32: =365/H30 -> 9.1233567 | I32: =365/I30 -> 9.310774 | J32: =365/J30 -> 9.3876939 | K32: =365/K30 -> 9.4448988 | L32: =365/L30 -> 9.480041 | M32: =365/M30 -> 9.5073001
B33: Cash conversion cycle | E33: =E31-E32 -> 54.67225 | F33: =F31-F32 -> 52.646955 | G33: =G31-G32 -> 60.464986 | H33: =H31-H32 -> 59.144066 | I33: =I31-I32 -> 58.928855 | J33: =J31-J32 -> 58.851935 | K33: =K31-K32 -> 58.79473 | L33: =L31-L32 -> 58.759588 | M33: =M31-M32 -> 58.732329
B34: Working capital turnover | E34: =Financials!F17/(Financials!F72-Financials!F95) -> 3.6905485 | F34: =Financials!G17/(Financials!G72-Financials!G95) -> 4.7158227 | G34: =Financials!H17/(Financials!H72-Financials!H95) -> 3.1277104 | H34: =Financials!I17/(Financials!I72-Financials!I95) -> 3.07084 | I34: =Financials!J17/(Financials!J72-Financials!J95) -> 2.6219391 | J34: =Financials!K17/(Financials!K72-Financials!K95) -> 2.8737792 | K34: =Financials!L17/(Financials!L72-Financials!L95) -> 2.6371577 | L34: =Financials!M17/(Financials!M72-Financials!M95) -> 2.483674 | M34: =Financials!N17/(Financials!N72-Financials!N95) -> 2.6308191
A36: # | B36: Leverage Ratios | E36: 44651 | F36: =EDATE(E36,12) -> 45016 | G36: =EDATE(F36,12) -> 45382 | H36: =EDATE(G36,12) -> 45747 | I36: =EDATE(H36,12) -> 46112 | J36: =EDATE(I36,12) -> 46477 | K36: =EDATE(J36,12) -> 46843 | L36: =EDATE(K36,12) -> 47208 | M36: =EDATE(L36,12) -> 47573
B37: Debt to Equity | E37: =(Financials!F82+Financials!F89)/Financials!F79 -> 0.072277385 | F37: =(Financials!G82+Financials!G89)/Financials!G79 -> 0.10949271 | G37: =(Financials!H82+Financials!H89)/Financials!H79 -> 0.094493619 | H37: =(Financials!I82+Financials!I89)/Financials!I79 -> 0.085517084 | I37: =(Financials!J82+Financials!J89)/Financials!J79 -> 0.07673462 | J37: =(Financials!K82+Financials!K89)/Financials!K79 -> 0.077851049 | K37: =(Financials!L82+Financials!L89)/Financials!L79 -> 0.070553938 | L37: =(Financials!M82+Financials!M89)/Financials!M79 -> 0.064555487 | M37: =(Financials!N82+Financials!N89)/Financials!N79 -> 0.063674375
B38: Debt to Assets | E38: =(Financials!F82+Financials!F89)/Financials!F73 -> 0.046435085 | F38: =(Financials!G82+Financials!G89)/Financials!G73 -> 0.065961404 | G38: =(Financials!H82+Financials!H89)/Financials!H73 -> 0.060654215 | H38: =(Financials!I82+Financials!I89)/Financials!I73 -> 0.055250734 | I38: =(Financials!J82+Financials!J89)/Financials!J73 -> 0.050570754 | J38: =(Financials!K82+Financials!K89)/Financials!K73 -> 0.050327333 | K38: =(Financials!L82+Financials!L89)/Financials!L73 -> 0.046429344 | L38: =(Financials!M82+Financials!M89)/Financials!M73 -> 0.043019204 | M38: =(Financials!N82+Financials!N89)/Financials!N73 -> 0.041836466
B39: Equity Multiplier | E39: =Financials!F73/Financials!F79 -> 1.5565253 | F39: =Financials!G73/Financials!G79 -> 1.6599512 | G39: =Financials!H73/Financials!H79 -> 1.5579069 | H39: =Financials!I73/Financials!I79 -> 1.5478 | I39: =Financials!J73/Financials!J79 -> 1.5173715 | J39: =Financials!K73/Financials!K79 -> 1.546894 | K39: =Financials!L73/Financials!L79 -> 1.519598 | L39: =Financials!M73/Financials!M79 -> 1.5006202 | M39: =Financials!N73/Financials!N79 -> 1.5219826
B40: Interest coverage (ICR) | E40: =Financials!F30/Financials!F26 -> 150.55 | F40: =Financials!G30/Financials!G26 -> 117.33099 | G40: =Financials!H30/Financials!H26 -> 76.570213 | H40: =Financials!I30/Financials!I26 -> 90.403846 | I40: - | J40: - | K40: - | L40: - | M40: -
A42: # | B42: Dupont Analysis | E42: 44651 | F42: =EDATE(E42,12) -> 45016 | G42: =EDATE(F42,12) -> 45382 | H42: =EDATE(G42,12) -> 45747 | I42: =EDATE(H42,12) -> 46112 | J42: =EDATE(I42,12) -> 46477 | K42: =EDATE(J42,12) -> 46843 | L42: =EDATE(K42,12) -> 47208 | M42: =EDATE(L42,12) -> 47573
B43: Net profit margin | E43: =E12 -> 0.178689 | F43: =F12 -> 0.16129205 | G43: =G12 -> 0.16572695 | H43: =H12 -> 0.16057386 | I43: =I12 -> 0.1635588 | J43: =J12 -> 0.15832859 | K43: =K12 -> 0.15456704 | L43: =L12 -> 0.15173315 | M43: =M12 -> 0.1493771
B44: Asset turnover | E44: =E27 -> 1.0513297 | F44: =F27 -> 1.1879888 | G44: =G27 -> 1.1492374 | H44: =H27 -> 1.118782 | I44: =I27 -> 1.0666473 | J44: =J27 -> 1.1224262 | K44: =K27 -> 1.1004092 | L44: =L27 -> 1.0891045 | M44: =M27 -> 1.1354008
B45: Equity multiplier | E45: =E39 -> 1.5565253 | F45: =F39 -> 1.6599512 | G45: =G39 -> 1.5579069 | H45: =H39 -> 1.5478 | I45: =I39 -> 1.5173715 | J45: =J39 -> 1.546894 | K45: =K39 -> 1.519598 | L45: =L39 -> 1.5006202 | M45: =M39 -> 1.5219826
B46: Dupont ratio | E46: =E43*E44*E45 -> 0.29241048 | F46: =F43*F44*F45 -> 0.31806847 | G46: =G43*G44*G45 -> 0.29671833 | H46: =H43*H44*H45 -> 0.27805786 | I46: =I43*I44*I45 -> 0.26471995 | J46: =J43*J44*J45 -> 0.27490185 | K46: =K43*K44*K45 -> 0.25846385 | L46: =L43*L44*L45 -> 0.24798237 | M46: =M43*M44*M45 -> 0.25813263

Sheet Analysis
B2: =Dashboard!C2 -> Infosys Ltd.
B3: Analysis
B4: =Dashboard!C4 -> (In ₹ Crore, except equity share and per equity share data)
A6: # | B6: Common-size Analysis | E6: 44651 | F6: =EDATE(E6,12) -> 45016 | G6: =EDATE(F6,12) -> 45382 | H6: =EDATE(G6,12) -> 45747 | I6: =EDATE(H6,12) -> 46112 | J6: =EDATE(I6,12) -> 46477 | K6: =EDATE(J6,12) -> 46843 | L6: =EDATE(K6,12) -> 47208 | M6: =EDATE(L6,12) -> 47573
B7: Revenue from operations | E7: =Financials!F15/Financials!F$17 -> 0.98148238 | F7: =Financials!G15/Financials!G$17 -> 0.98192924 | G7: =Financials!H15/Financials!H$17 -> 0.97025527 | H7: =Financials!I15/Financials!I$17 -> 0.97839006 | I7: =Financials!J15/Financials!J$17 -> 0.97799172 | J7: =Financials!K15/Financials!K$17 -> 0.97799172 | K7: =Financials!L15/Financials!L$17 -> 0.97799172 | L7: =Financials!M15/Financials!M$17 -> 0.97799172 | M7: =Financials!N15/Financials!N$17 -> 0.97799172
B8: Other income, net | E8: =Financials!F16/Financials!F$17 -> 0.018517622 | F8: =Financials!G16/Financials!G$17 -> 0.018070758 | G8: =Financials!H16/Financials!H$17 -> 0.029744729 | H8: =Financials!I16/Financials!I$17 -> 0.021609941 | I8: =Financials!J16/Financials!J$17 -> 0.022008276 | J8: =Financials!K16/Financials!K$17 -> 0.022008276 | K8: =Financials!L16/Financials!L$17 -> 0.022008276 | L8: =Financials!M16/Financials!M$17 -> 0.022008276 | M8: =Financials!N16/Financials!N$17 -> 0.022008276
B9: Total Revenue | E9: =Financials!F17/Financials!F$17 -> 1 | F9: =Financials!G17/Financials!G$17 -> 1 | G9: =Financials!H17/Financials!H$17 -> 1 | H9: =Financials!I17/Financials!I$17 -> 1 | I9: =Financials!J17/Financials!J$17 -> 1 | J9: =Financials!K17/Financials!K$17 -> 1 | K9: =Financials!L17/Financials!L$17 -> 1 | L9: =Financials!M17/Financials!M$17 -> 1 | M9: =Financials!N17/Financials!N$17 -> 1
B11: Employee benefit expenses | E11: =Financials!F19/Financials!F$17 -> 0.5162826 | F11: =Financials!G19/Financials!G$17 -> 0.52425268 | G11: =Financials!H19/Financials!H$17 -> 0.52165348 | H11: =Financials!I19/Financials!I$17 -> 0.51593733 | I11: =Financials!J19/Financials!J$17 -> 0.51612001 | J11: =Financials!K19/Financials!K$17 -> 0.50934341 | K11: =Financials!L19/Financials!L$17 -> 0.50086328 | L11: =Financials!M19/Financials!M$17 -> 0.49069645 | M11: =Financials!N19/Financials!N$17 -> 0.47971926
B12: Cost of technical sub-contractors | E12: =Financials!F20/Financials!F$17 -> 0.10171379 | F12: =Financials!G20/Financials!G$17 -> 0.094080338 | G12: =Financials!H20/Financials!H$17 -> 0.077231486 | H12: =Financials!I20/Financials!I$17 -> 0.077657723 | I12: =Financials!J20/Financials!J$17 -> 0.07902719 | J12: =Financials!K20/Financials!K$17 -> 0.079446972 | K12: =Financials!L20/Financials!L$17 -> 0.079694208 | L12: =Financials!M20/Financials!M$17 -> 0.07975519 | M12: =Financials!N20/Financials!N$17 -> 0.079756613
B13: Travel expenses | E13: =Financials!F21/Financials!F$17 -> 0.0066727989 | F13: =Financials!G21/Financials!G$17 -> 0.010202853 | G13: =Financials!H21/Financials!H$17 -> 0.01110613 | H13: =Financials!I21/Financials!I$17 -> 0.01136923 | I13: =Financials!J21/Financials!J$17 -> 0.011788019 | J13: =Financials!K21/Financials!K$17 -> 0.012095898 | K13: =Financials!L21/Financials!L$17 -> 0.012406715 | L13: =Financials!M21/Financials!M$17 -> 0.012718193 | M13: =Financials!N21/Financials!N$17 -> 0.013050618
B14: Cost of software packages and others | E14: =Financials!F22/Financials!F$17 -> 0.054955784 | F14: =Financials!G22/Financials!G$17 -> 0.072938689 | G14: =Financials!H22/Financials!H$17 -> 0.085332205 | H14: =Financials!I22/Financials!I$17 -> 0.095509935 | I14: =Financials!J22/Financials!J$17 -> 0.10819734 | J14: =Financials!K22/Financials!K$17 -> 0.12043718 | K14: =Financials!L22/Financials!L$17 -> 0.13305184 | L14: =Financials!M22/Financials!M$17 -> 0.14585868 | M14: =Financials!N22/Financials!N$17 -> 0.15892348
B15: Communication expenses | E15: =Financials!F23/Financials!F$17 -> 0.0049299639 | F15: =Financials!G23/Financials!G$17 -> 0.0047702518 | G15: =Financials!H23/Financials!H$17 -> 0.0042745026 | H15: =Financials!I23/Financials!I$17 -> 0.003721712 | I15: =Financials!J23/Financials!J$17 -> 0.003287128 | J15: =Financials!K23/Financials!K$17 -> 0.0028833547 | K15: =Financials!L23/Financials!L$17 -> 0.0025368915 | L15: =Financials!M23/Financials!M$17 -> 0.0022384002 | M15: =Financials!N23/Financials!N$17 -> 0.0019836923
B16: Consultancy and professional charges | E16: =Financials!F24/Financials!F$17 -> 0.015209463 | F16: =Financials!G24/Financials!G$17 -> 0.011266626 | G16: =Financials!H24/Financials!H$17 -> 0.010897772 | H16: =Financials!I24/Financials!I$17 -> 0.0099345699 | I16: =Financials!J24/Financials!J$17 -> 0.0097282622 | J16: =Financials!K24/Financials!K$17 -> 0.0094188249 | K16: =Financials!L24/Financials!L$17 -> 0.0091069041 | L16: =Financials!M24/Financials!M$17 -> 0.0087920311 | M16: =Financials!N24/Financials!N$17 -> 0.0084887262
B17: Depreciation and amortisation expenses | E17: =Financials!F25/Financials!F$17 -> 0.028046734 | F17: =Financials!G25/Financials!G$17 -> 0.02826692 | G17: =Financials!H25/Financials!H$17 -> 0.029536371 | H17: =Financials!I25/Financials!I$17 -> 0.028885287 | I17: =Financials!J25/Financials!J$17 -> 0.0089546684 | J17: =Financials!K25/Financials!K$17 -> 0.010779551 | K17: =Financials!L25/Financials!L$17 -> 0.011999786 | L17: =Financials!M25/Financials!M$17 -> 0.013585041 | M17: =Financials!N25/Financials!N$17 -> 0.015031632
B18: Finance cost | E18: =Financials!F26/Financials!F$17 -> 0.0016137361 | F18: =Financials!G26/Financials!G$17 -> 0.0019000723 | G18: =Financials!H26/Financials!H$17 -> 0.0029675277 | H18: =Financials!I26/Financials!I$17 -> 0.0024971487 | I18: =Financials!J26/Financials!J$17 -> 0 | J18: =Financials!K26/Financials!K$17 -> 0 | K18: =Financials!L26/Financials!L$17 -> 0 | L18: =Financials!M26/Financials!M$17 -> 0 | M18: =Financials!N26/Financials!N$17 -> 0
B19: Other expenses | E19: =Financials!F27/Financials!F$17 -> 0.027627162 | F19: =Financials!G27/Financials!G$17 -> 0.029384216 | G19: =Financials!H27/Financials!H$17 -> 0.029776299 | H19: =Financials!I27/Financials!I$17 -> 0.028735218 | I19: =Financials!J27/Financials!J$17 -> 0.029241954 | J19: =Financials!K27/Financials!K$17 -> 0.029411111 | K19: =Financials!L27/Financials!L$17 -> 0.029530313 | L19: =Financials!M27/Financials!M$17 -> 0.029594378 | M19: =Financials!N27/Financials!N$17 -> 0.02965012
... B26: Profit for the year | E26: =Financials!F34/Financials!F$17 -> 0.178689 | F26: =Financials!G34/Financials!G$17 -> 0.16129205 | G26: =Financials!H34/Financials!H$17 -> 0.16572695 | H26: =Financials!I34/Financials!I$17 -> 0.16057386 | I26: =Financials!J34/Financials!J$17 -> 0.1635588 | J26: =Financials!K34/Financials!K$17 -> 0.15832859 | K26: =Financials!L34/Financials!L$17 -> 0.15456704 | L26: =Financials!M34/Financials!M$17 -> 0.15173315 | M26: =Financials!N34/Financials!N$17 -> 0.1493771
A28: # | B28: Trend Analysis | E28: 44651 | F28: =EDATE(E28,12) -> 45016 | G28: =EDATE(F28,12) -> 45382 | H28: =EDATE(G28,12) -> 45747 | I28: =EDATE(H28,12) -> 46112 | J28: =EDATE(I28,12) -> 46477 | K28: =EDATE(J28,12) -> 46843 | L28: =EDATE(K28,12) -> 47208 | M28: =EDATE(L28,12) -> 47573
B29: Revenue from operations | E29: -- | F29: =Financials!G15/Financials!F15-1 -> 0.20655864 | G29: =Financials!H15/Financials!G15-1 -> 0.047033734 | H29: =Financials!I15/Financials!H15-1 -> 0.060649444 | I29: =Financials!J15/Financials!I15-1 -> 0.041207105 | J29: =Financials!K15/Financials!J15-1 -> 0.057383326 | K29: =Financials!L15/Financials!K15-1 -> 0.062692928 | L29: =Financials!M15/Financials!L15-1 -> 0.068182632 | M29: =Financials!N15/Financials!M15-1 -> 0.071980877
B30: Other income, net | E30: -- | F30: =Financials!G16/Financials!F16-1 -> 0.17690632 | G30: =Financials!H16/Financials!G16-1 -> 0.74416883 | H30: =Financials!I16/Financials!H16-1 -> -0.23583103 | I30: =Financials!J16/Financials!I16-1 -> 0.060831538 | J30: =Financials!K16/Financials!J16-1 -> 0.057383326 | K30: =Financials!L16/Financials!K16-1 -> 0.062692928 | L30: =Financials!M16/Financials!L16-1 -> 0.068182632 | M30: =Financials!N16/Financials!M16-1 -> 0.071980877
B31: Total Revenue | E31: -- | F31: =Financials!G17/Financials!F17-1 -> 0.20600955 | G31: =Financials!H17/Financials!G17-1 -> 0.059631493 | H31: =Financials!I17/Financials!H17-1 -> 0.051830712 | I31: =Financials!J17/Financials!I17-1 -> 0.041631188 | J31: =Financials!K17/Financials!J17-1 -> 0.057383326 | K31: =Financials!L17/Financials!K17-1 -> 0.062692928 | L31: =Financials!M17/Financials!L17-1 -> 0.068182632 | M31: =Financials!N17/Financials!M17-1 -> 0.071980877
B33: Employee benefit expenses | E33: -- | F33: =Financials!G19/Financials!F19-1 -> 0.22462726 | G33: =Financials!H19/Financials!G19-1 -> 0.054377927 | H33: =Financials!I19/Financials!H19-1 -> 0.040305011 | I33: =Financials!J19/Financials!I19-1 -> 0.042 | J33: =Financials!K19/Financials!J19-1 -> 0.0435 | K33: =Financials!L19/Financials!K19-1 -> 0.045 | L33: =Financials!M19/Financials!L19-1 -> 0.0465 | M33: =Financials!N19/Financials!M19-1 -> 0.048
B34: Cost of technical sub-contractors | E34: -- | F34: =Financials!G20/Financials!F20-1 -> 0.11550056 | G34: =Financials!H20/Financials!G20-1 -> -0.13013796 | H34: =Financials!I20/Financials!H20-1 -> 0.05763571 | I34: =Financials!J20/Financials!I20-1 -> 0.06 | J34: =Financials!K20/Financials!J20-1 -> 0.063 | K34: =Financials!L20/Financials!K20-1 -> 0.066 | L34: =Financials!M20/Financials!L20-1 -> 0.069 | M34: =Financials!N20/Financials!M20-1 -> 0.072
B35: Travel expenses | E35: -- | F35: =Financials!G21/Financials!F21-1 -> 0.84401451 | G35: =Financials!H21/Financials!G21-1 -> 0.15344262 | H35: =Financials!I21/Financials!H21-1 -> 0.076748152 | I35: =Financials!J21/Financials!I21-1 -> 0.08 | J35: =Financials!K21/Financials!J21-1 -> 0.085 | K35: =Financials!L21/Financials!K21-1 -> 0.09 | L35: =Financials!M21/Financials!L21-1 -> 0.095 | M35: =Financials!N21/Financials!M21-1 -> 0.1
B36: Cost of software packages and others | E36: -- | F36: =Financials!G22/Financials!F22-1 -> 0.60064601 | G36: =Financials!H22/Financials!G22-1 -> 0.23968079 | H36: =Financials!I22/Financials!H22-1 -> 0.1772845 | I36: =Financials!J22/Financials!I22-1 -> 0.18 | J36: =Financials!K22/Financials!J22-1 -> 0.177 | K36: =Financials!L22/Financials!K22-1 -> 0.174 | L36: =Financials!M22/Financials!L22-1 -> 0.171 | M36: =Financials!N22/Financials!M22-1 -> 0.168
B37: Communication expenses | E37: -- | F37: =Financials!G23/Financials!F23-1 -> 0.16693944 | G37: =Financials!H23/Financials!G23-1 -> -0.050490884 | H37: =Financials!I23/Financials!H23-1 -> -0.084194978 | I37: =Financials!J23/Financials!I23-1 -> -0.08 | J37: =Financials!K23/Financials!J23-1 -> -0.0725 | K37: =Financials!L23/Financials!K23-1 -> -0.065 | L37: =Financials!M23/Financials!L23-1 -> -0.0575 | M37: =Financials!N23/Financials!M23-1 -> -0.05
B38: Consultancy and professional charges | E38: -- | F38: =Financials!G24/Financials!F24-1 -> -0.1066313 | G38: =Financials!H24/Financials!G24-1 -> 0.024940618 | H38: =Financials!I24/Financials!H24-1 -> -0.041135574 | I38: =Financials!J24/Financials!I24-1 -> 0.02 | J38: =Financials!K24/Financials!J24-1 -> 0.02375 | K38: =Financials!L24/Financials!K24-1 -> 0.0275 | L38: =Financials!M24/Financials!L24-1 -> 0.03125 | M38: =Financials!N24/Financials!M24-1 -> 0.035
B39: Depreciation and amortisation expenses | E39: -- | F39: =Financials!G25/Financials!F25-1 -> 0.21547756 | G39: =Financials!H25/Financials!G25-1 -> 0.10721893 | H39: =Financials!I25/Financials!H25-1 -> 0.02864472 | I39: =Financials!J25/Financials!I25-1 -> -0.67708606 | J39: =Financials!K25/Financials!J25-1 -> 0.27286875 | K39: =Financials!L25/Financials!K25-1 -> 0.18298872 | L39: =Financials!M25/Financials!L25-1 -> 0.20929702 | M39: =Financials!N25/Financials!M25-1 -> 0.18612981
B40: Finance cost | E40: -- | F40: =Financials!G26/Financials!F26-1 -> 0.42 | G40: =Financials!H26/Financials!G26-1 -> 0.65492958 | H40: =Financials!I26/Financials!H26-1 -> -0.11489362 | I40: =Financials!J26/Financials!I26-1 -> -1 | J40: -- | K40: -- | L40: -- | M40: --
B41: Other expenses | E41: -- | F41: =Financials!G27/Financials!F27-1 -> 0.28271028 | G41: =Financials!H27/Financials!G27-1 -> 0.073770492 | H41: =Financials!I27/Financials!H27-1 -> 0.015055131 | I41: =Financials!J27/Financials!I27-1 -> 0.06 | J41: =Financials!K27/Financials!J27-1 -> 0.0635 | K41: =Financials!L27/Financials!K27-1 -> 0.067 | L41: =Financials!M27/Financials!L27-1 -> 0.0705 | M41: =Financials!N27/Financials!M27-1 -> 0.074
B42: Total Expenses | E42: -- | F42: =Financials!G28/Financials!F28-1 -> 0.23788715 | G42: =Financials!H28/Financials!G28-1 -> 0.053785752 | H42: =Financials!I28/Financials!H28-1 -> 0.053834778 | I42: =Financials!J28/Financials!I28-1 -> 0.030998138 | J42: =Financials!K28/Financials!J28-1 -> 0.067692639 | K42: =Financials!L28/Financials!K28-1 -> 0.070072618 | L42: =Financials!M28/Financials!L28-1 -> 0.073732564 | M42: =Financials!N28/Financials!M28-1 -> 0.076587473
B44: Profit before tax | E44: -- | F44: =Financials!G30/Financials!F30-1 -> 0.10667552 | G44: =Financials!H30/Financials!G30-1 -> 0.080007202 | H44: =Financials!I30/Financials!H30-1 -> 0.045015005 | I44: =Financials!J30/Financials!I30-1 -> 0.078098747 | J44: =Financials!K30/Financials!J30-1 -> 0.023570775 | K44: =Financials!L30/Financials!K30-1 -> 0.037445641 | L44: =Financials!M30/Financials!L30-1 -> 0.048598148 | M44: =Financials!N30/Financials!M30-1 -> 0.055335577
B46: Current tax | E46: -- | F46: =Financials!G32/Financials!F32-1 -> 0.18896428 | G46: =Financials!H32/Financials!G32-1 -> -0.096586626 | H46: =Financials!I32/Financials!H32-1 -> 0.44576877 | I46: =Financials!J32/Financials!I32-1 -> 0.0027651524 | J46: =Financials!K32/Financials!J32-1 -> 0.023570775 | K46: =Financials!L32/Financials!K32-1 -> 0.037445641 | L46: =Financials!M32/Financials!L32-1 -> 0.048598148 | M46: =Financials!N32/Financials!M32-1 -> 0.055335577
B47: Deferred tax | E47: -- | F47: =Financials!G33/Financials!F33-1 -> -1.4771242 | G47: =Financials!H33/Financials!G33-1 -> -19.493151 | H47: =Financials!I33/Financials!H33-1 -> -1.9422222 | I47: =Financials!J33/Financials!I33-1 -> -1 | J47: -- | K47: -- | L47: -- | M47: --
B48: Profit for the year | E48: -- | F48: =Financials!G34/Financials!F34-1 -> 0.088593877 | G48: =Financials!H34/Financials!G34-1 -> 0.088767214 | H48: =Financials!I34/Financials!H34-1 -> 0.019125267 | I48: =Financials!J34/Financials!I34-1 -> 0.060994257 | J48: =Financials!K34/Financials!J34-1 -> 0.023570775 | K48: =Financials!L34/Financials!K34-1 -> 0.037445641 | L48: =Financials!M34/Financials!L34-1 -> 0.048598148 | M48: =Financials!N34/Financials!M34-1 -> 0.055335577

Sheet Others
A1: \

Sheet Price prediction
B1: (Infosys closing from Dec 1995 to March 2026) | G1: (Infosys closing from Jan 2026 to March 2026)
B2: Date | C2: Price | D2: Returns | G2: Date | H2: Closing | I2: Forecast | J2: ABS Error | K2: Error ^2 | L2: % Error | N2: y= | O2: 0.1471x - 5463.8
B4: 46082 | C4: 1288.9 | G4: 46054 | H4: 1654.5 | I4: =0.1471*G4-5463.8 -> 1310.7434 | J4: =ABS(I4-H4) -> 343.7566 | K4: =J4^2 -> 118168.6 | L4: =J4/H4 -> 0.20777069
B5: 46054 | C5: 1300.1 | D5: =C5/C4-1 -> 0.0086895803 | G5: 46055 | H5: 1629.4 | I5: =0.1471*G5-5463.8 -> 1310.8905 | J5: =ABS(I5-H5) -> 318.5095 | K5: =J5^2 -> 101448.3 | L5: =J5/H5 -> 0.19547656
B6: 46023 | C6: 1641 | D6: =C6/C5-1 -> 0.2622106 | G6: 46056 | H6: 1656 | I6: =0.1471*G6-5463.8 -> 1311.0376 | J6: =ABS(I6-H6) -> 344.9624 | K6: =J6^2 -> 118999.06 | L6: =J6/H6 -> 0.20831063
B7: 45992 | C7: 1615.4 | D7: =C7/C6-1 -> -0.015600244 | G7: 46057 | H7: 1535.8 | I7: =0.1471*G7-5463.8 -> 1311.1847 | J7: =ABS(I7-H7) -> 224.6153 | K7: =J7^2 -> 50452.033 | L7: =J7/H7 -> 0.14625296
B8: 45962 | C8: 1560.1 | D8: =C8/C7-1 -> -0.034233007 | G8: 46058 | H8: 1520.2 | I8: =0.1471*G8-5463.8 -> 1311.3318 | J8: =ABS(I8-H8) -> 208.8682 | K8: =J8^2 -> 43625.925 | L8: =J8/H8 -> 0.13739521
B9: 45931 | C9: 1482.3 | D9: =C9/C8-1 -> -0.049868598 | G9: 46059 | H9: 1507.1 | I9: =0.1471*G9-5463.8 -> 1311.4789 | J9: =ABS(I9-H9) -> 195.6211 | K9: =J9^2 -> 38267.615 | L9: =J9/H9 -> 0.12979968
B10: 45901 | C10: 1441.8 | D10: =C10/C9-1 -> -0.027322404 | G10: 46062 | H10: 1497.2 | I10: =0.1471*G10-5463.8 -> 1311.9202 | J10: =ABS(I10-H10) -> 185.2798 | K10: =J10^2 -> 34328.604 | L10: =J10/H10 -> 0.12375087
B11: 45870 | C11: 1469.6 | D11: =C11/C10-1 -> 0.019281454 | G11: 46063 | H11: 1497.8 | I11: =0.1471*G11-5463.8 -> 1312.0673 | J11: =ABS(I11-H11) -> 185.7327 | K11: =J11^2 -> 34496.636 | L11: =J11/H11 -> 0.12400367
B12: 45839 | C12: 1509 | D12: =C12/C11-1 -> 0.026810016 | G12: 46064 | H12: 1471.9 | I12: =0.1471*G12-5463.8 -> 1312.2144 | J12: =ABS(I12-H12) -> 159.6856 | K12: =J12^2 -> 25499.491 | L12: =J12/H12 -> 0.10848944
B13: 45809 | C13: 1601.8 | D13: =C13/C12-1 -> 0.061497681 | G13: 46065 | H13: 1386 | I13: =0.1471*G13-5463.8 -> 1312.3615 | J13: =ABS(I13-H13) -> 73.6385 | K13: =J13^2 -> 5422.6287 | L13: =J13/H13 -> 0.053130231
B14: 45778 | C14: 1562.7 | D14: =C14/C13-1 -> -0.024410039 | G14: 46066 | H14: 1369.1 | I14: =0.1471*G14-5463.8 -> 1312.5086 | J14: =ABS(I14-H14) -> 56.5914 | K14: =J14^2 -> 3202.5866 | L14: =J14/H14 -> 0.041334745
B15: 45748 | C15: 1500.1 | D15: =C15/C14-1 -> -0.040058872 | G15: 46069 | H15: 1365.6 | I15: =0.1471*G15-5463.8 -> 1312.9499 | J15: =ABS(I15-H15) -> 52.6501 | K15: =J15^2 -> 2772.033 | L15: =J15/H15 -> 0.038554555
B16: 45717 | C16: 1570.65 | D16: =C16/C15-1 -> 0.047030198 | G16: 46070 | H16: 1391.2 | I16: =0.1471*G16-5463.8 -> 1313.097 | J16: =ABS(I16-H16) -> 78.103 | K16: =J16^2 -> 6100.0786 | L16: =J16/H16 -> 0.056140742
... B25: 45444 | C25: 1566.75 | D25: =C25/C24-1 -> -0.16138097 | G25: 46083 | H25: 1288.9 | I25: =0.1471*G25-5463.8 -> 1315.0093 | J25: =ABS(I25-H25) -> 26.1093 | K25: =J25^2 -> 681.69555 | L25: =J25/H25 -> 0.020257041
B26: 45413 | C26: 1406.9 | D26: =C26/C25-1 -> -0.10202649 | I26: RMSE | J26: =AVERAGE(J4:J25) -> 123.97544 | K26: =AVERAGE(K4:K25) -> 27048.379 | L26: =AVERAGE(L4:L25) -> 0.081619691
B27: 45383 | C27: 1412.59 | D27: =C27/C26-1 -> 0.0040443528
B28: 45352 | C28: 1489.66 | D28: =C28/C27-1 -> 0.054559356
B29: 45323 | C29: 1664.52 | D29: =C29/C28-1 -> 0.11738249
B30: 45292 | C30: 1651.59 | D30: =C30/C29-1 -> -0.0077680052 | H30: # | I30: Investment Thesis
B31: 45261 | C31: 1534.25 | D31: =C31/C30-1 -> -0.071046688 | I31: Fundamental Analysis of Infosys Ltd. Is conducted using 3 - Statement analysis, and Free Cash Flow to Firm, which are used to explicitly forecast and determine the intrinsic value of the stock.
B32: 45231 | C32: 1446.99 | D32: =C32/C31-1 -> -0.056874694 | I32: The implicit forecast period is of five years.
B33: 45200 | C33: 1360.73 | D33: =C33/C32-1 -> -0.059613404 | I33: The items are forecasted using scenarios which are: Best , Street, Worst. Also we have adapted the use of AI by the company in scenario's aswell as real time casues and gains for forecasting.
B34: 45170 | C34: 1427.41 | D34: =C34/C33-1 -> 0.049003109 | I34: The AI scenarios are linked to the expenses of the company with each scenario outcome depticts on the use of AI adopted by the company
B35: 45139 | C35: 1427.41 | D35: =C35/C34-1 -> 0 | I35: Other items (which are not revenue or expenses) are considered as general assumptions.
B36: 45108 | C36: 1348.1 | D36: =C36/C35-1 -> -0.055562172 | I36: To find the intrinsic value we have used the Free Cash Flow to Firm method, which is derived firom finding the present value of equity by discounting future values of cash flows using an discount factor.
B37: 45078 | C37: 1328.02 | D37: =C37/C36-1 -> -0.014895037
B38: 45047 | C38: 1310.91 | D38: =C38/C37-1 -> -0.012883842 | I38: The weighted average cost of capital is calculated using cost of equity to its weight and cost of debt to its weight (Ke*E/(E+D) + Kd*D/(E+D)).
B39: 45017 | C39: 1245.73 | D39: =C39/C38-1 -> -0.049721186 | I39: Cost of equity is calculated using a simple approach which is Rf + (Rm - Rf)*Beta
B40: 44986 | C40: 1419.95 | D40: =C40/C39-1 -> 0.13985374 | I40: The Beta is derived from rhe tegression analysis of Infosys stock to The Nifty 50 (Historical data used is from 001-12-1995 to 01-03-2026, Since inception of NSE)
B41: 44958 | C41: 1479.21 | D41: =C41/C40-1 -> 0.041733864 | I41: The formula used for Adjusted Beta is (levered beta*Raw beta weight) + (Market beta*Market weight)
B42: 44927 | C42: 1525.16 | D42: =C42/C41-1 -> 0.031063879 | I42: Market returns (Rm) is calculated using CAGR of Nifty 50
B43: 44896 | C43: 1499.75 | D43: =C43/C42-1 -> -0.016660547 | I43: Risk free rate (Rf) is the 10-year govt bond yield which is considered as the risk free rate in indian markets
B44: 44866 | C44: 1625.79 | D44: =C44/C43-1 -> 0.084040673 | I44: Cost of debt is calculated using credit ratings. The credit rating for INFY is from CRISIL Ratings: CRISIL AAA/Stable/CRISIL A1+, Moody's Investors Service: A3/Stable, S&P Global Ratings: A-.
B45: 44835 | C45: 1529.03 | D45: =C45/C44-1 -> -0.059515682 | I45: using the credit rating the risk premium is derived from aswath damodaran's (Ratings, Interest Coverage Ratios and Default Spread) for For large non-financial service firms.
B46: 44805 | C46: 1405.53 | D46: =C46/C45-1 -> -0.080770161 | I46: using crisils AAA rating the spread is 0.40%.
B47: 44774 | C47: 1484.58 | D47: =C47/C46-1 -> 0.056242129 | I47: Since (at the time of our valuation) Infosysis Ltd. is considered as a debt free company.
B48: 44743 | C48: 1541.02 | D48: =C48/C47-1 -> 0.038017486 | I48: The WACC and terminal growth rate (which is 3% to 6% for IT companies in India) then defined for each of the scenarios.
B49: 44713 | C49: 1453.71 | D49: =C49/C48-1 -> -0.056657279 | I49: Using these parameters the intrinsic value of the stock is found.
B50: 44682 | C50: 1495.17 | D50: =C50/C49-1 -> 0.028520131 | I50: Football field analysis is then conducted to get the fair value of the stock.
B51: 44652 | C51: 1558.77 | D51: =C51/C50-1 -> 0.042536969
B52: 44621 | C52: 1896.16 | D52: =C52/C51-1 -> 0.2164463
B53: 44593 | C53: 1705.99 | D53: =C53/C52-1 -> -0.10029217
B54: 44562 | C54: 1726.47 | D54: =C54/C53-1 -> 0.01200476
B55: 44531 | C55: 1877.17 | D55: =C55/C54-1 -> 0.087287934
B56: 44501 | C56: 1703.05 | D56: =C56/C55-1 -> -0.09275665
B57: 44470 | C57: 1658.4 | D57: =C57/C56-1 -> -0.026217668
B58: 44440 | C58: 1665.81 | D58: =C58/C57-1 -> 0.0044681621
B59: 44409 | C59: 1696.89 | D59: =C59/C58-1 -> 0.01865759
B60: 44378 | C60: 1601.47 | D60: =C60/C59-1 -> -0.056232284
B61: 44348 | C61: 1571.94 | D61: =C61/C60-1 -> -0.018439309
B62: 44317 | C62: 1385.94 | D62: =C62/C61-1 -> -0.11832513
... B367: 35034 | C367: 0.79 | D367: =C367/C366-1 -> 0.012820513
