Workbook

Sheet IT_Comps
B2: IT - Software | Sector Comps - Relative Value Analysis
B3: (Figures in Rs. Cr., except price per share, shares outstanding, and other ratios)
B6: IT - Software Companies (Ranked in order of Market Cap in Rs. Cr)
B8: S.No. | C8: Name | D8: # Ticker | E8: CMP | F8: No. Eq. Shares Cr. | G8: Equity Value | H8: Debt | I8: Cash | J8: Enterprise Value | K8: Revenue | L8: EBITDA | M8: EBIT | N8: Net Income | O8: Book Value
B10: 1 | C10: ='Data Sheet'!B4 -> TCS | D10: TCS | E10: ='Data Sheet'!C4 -> 2488.4 | F10: ='Data Sheet'!D4 -> 361.81 | G10: =E10*F10 -> 900328 | H10: ='Data Sheet'!E4 -> 10932 | I10: ='Data Sheet'!F4 -> 15463 | J10: =G10+H10-I10 -> 895797 | K10: ='Data Sheet'!H4 -> 260802 | L10: ='Data Sheet'!I4+'Data Sheet'!J4 -> 74775 | M10: ='Data Sheet'!I4 -> 69242 | N10: ='Data Sheet'!K4 -> 47963 | O10: ='Data Sheet'!N4 -> 294.12
B11: 2 | C11: ='Data Sheet'!B5 -> Infosys | D11: INFY | E11: ='Data Sheet'!C5 -> 1284.7 | F11: ='Data Sheet'!D5 -> 405.54 | G11: =E11*F11 -> 520997.24 | H11: ='Data Sheet'!E5 -> 8796 | I11: ='Data Sheet'!F5 -> 24455 | J11: =G11+H11-I11 -> 505338.24 | K11: ='Data Sheet'!H5 -> 173173 | L11: ='Data Sheet'!I5+'Data Sheet'!J5 -> 45339 | M11: ='Data Sheet'!I5 -> 40563 | N11: ='Data Sheet'!K5 -> 28003 | O11: ='Data Sheet'!N5 -> 204.77
B12: 3 | C12: ='Data Sheet'!B6 -> HCL Technologies | D12: HCLTECH | E12: ='Data Sheet'!C6 -> 1359.45 | F12: ='Data Sheet'!D6 -> 271.37 | G12: =E12*F12 -> 368913.95 | H12: ='Data Sheet'!E6 -> 6780 | I12: ='Data Sheet'!F6 -> 21289 | J12: =G12+H12-I12 -> 354404.95 | K12: ='Data Sheet'!H6 -> 126409 | L12: ='Data Sheet'!I6+'Data Sheet'!J6 -> 28179 | M12: ='Data Sheet'!I6 -> 23876 | N12: ='Data Sheet'!K6 -> 16471 | O12: ='Data Sheet'!N6 -> 262.56
B13: 4 | C13: ='Data Sheet'!B7 -> Wipro | D13: WIPRO | E13: ='Data Sheet'!C7 -> 203.35 | F13: ='Data Sheet'!D7 -> 1048.8 | G13: =E13*F13 -> 213273.48 | H13: ='Data Sheet'!E7 -> 16163.7 | I13: ='Data Sheet'!F7 -> 12197.4 | J13: =G13+H13-I13 -> 217239.78 | K13: ='Data Sheet'!H7 -> 90891.9 | L13: ='Data Sheet'!I7+'Data Sheet'!J7 -> 21785.8 | M13: ='Data Sheet'!I7 -> 18881.9 | N13: ='Data Sheet'!K7 -> 13332 | O13: ='Data Sheet'!N7 -> 81.61
B14: 5 | C14: ='Data Sheet'!B8 -> Tech Mahindra | D14: TECHM | E14: ='Data Sheet'!C8 -> 1346.2 | F14: ='Data Sheet'!D8 -> 97.98 | G14: =E14*F14 -> 131900.68 | H14: ='Data Sheet'!E8 -> 1954.4 | I14: ='Data Sheet'!F8 -> 4542.2 | J14: =G14+H14-I14 -> 129312.88 | K14: ='Data Sheet'!H8 -> 55123.3 | L14: ='Data Sheet'!I8+'Data Sheet'!J8 -> 8715.6 | M14: ='Data Sheet'!I8 -> 6853 | N14: ='Data Sheet'!K8 -> 4591 | O14: ='Data Sheet'!N8 -> 280.73
B15: 6 | C15: ='Data Sheet'!B9 -> LTIMindtree | D15: LTM | E15: ='Data Sheet'!C9 -> 4303.6 | F15: ='Data Sheet'!D9 -> 29.65 | G15: =E15*F15 -> 127601.74 | H15: ='Data Sheet'!E9 -> 2382.6 | I15: ='Data Sheet'!F9 -> 3588.2 | J15: =G15+H15-I15 -> 126396.14 | K15: ='Data Sheet'!H9 -> 40787.6 | L15: ='Data Sheet'!I9+'Data Sheet'!J9 -> 8349.3 | M15: ='Data Sheet'!I9 -> 7308 | N15: ='Data Sheet'!K9 -> 4724 | O15: ='Data Sheet'!N9 -> 789.34
B16: 7 | C16: ='Data Sheet'!B10 -> Persistent Systems | D16: PERSISTENT | E16: ='Data Sheet'!C10 -> 4789.3 | F16: ='Data Sheet'!D10 -> 15.78 | G16: =E16*F16 -> 75575.154 | H16: ='Data Sheet'!E10 -> 403.94 | I16: ='Data Sheet'!F10 -> 1025.47 | J16: =G16+H16-I16 -> 74953.624 | K16: ='Data Sheet'!H10 -> 13934.63 | L16: ='Data Sheet'!I10+'Data Sheet'!J10 -> 2777.44 | M16: ='Data Sheet'!I10 -> 2403.93 | N16: ='Data Sheet'!K10 -> 1731.62 | O16: ='Data Sheet'!N10 -> 453.09
B17: 8 | C17: ='Data Sheet'!B11 -> Oracle Fin.Serv. | D17: OFSLL | E17: ='Data Sheet'!C11 -> 6764.5 | F17: ='Data Sheet'!D11 -> 8.7 | G17: =E17*F17 -> 58851.15 | H17: ='Data Sheet'!E11 -> 34 | I17: ='Data Sheet'!F11 -> 5951.4 | J17: =G17+H17-I17 -> 52933.75 | K17: ='Data Sheet'!H11 -> 7323.2 | L17: ='Data Sheet'!I11+'Data Sheet'!J11 -> 3467 | M17: ='Data Sheet'!I11 -> 3400.1 | N17: ='Data Sheet'!K11 -> 2441.5 | O17: ='Data Sheet'!N11 -> 846.77
B18: 9 | C18: ='Data Sheet'!B12 -> Mphasis | D18: MPHASIS | E18: ='Data Sheet'!C12 -> 2199.35 | F18: ='Data Sheet'!D12 -> 19.07 | G18: =E18*F18 -> 41941.605 | H18: ='Data Sheet'!E12 -> 1979.03 | I18: ='Data Sheet'!F12 -> 1612.58 | J18: =G18+H18-I18 -> 42308.054 | K18: ='Data Sheet'!H12 -> 15347.02 | L18: ='Data Sheet'!I12+'Data Sheet'!J12 -> 3155.15 | M18: ='Data Sheet'!I12 -> 2617.33 | N18: ='Data Sheet'!K12 -> 1799.45 | O18: ='Data Sheet'!N12 -> 504.96
B19: 10 | C19: ='Data Sheet'!B13 -> Coforge | D19: COFORGE | E19: ='Data Sheet'!C13 -> 1123.35 | F19: ='Data Sheet'!D13 -> 33.58 | G19: =E19*F19 -> 37722.093 | H19: ='Data Sheet'!E13 -> 971.5 | I19: ='Data Sheet'!F13 -> 883.2 | J19: =G19+H19-I19 -> 37810.393 | K19: ='Data Sheet'!H13 -> 15272.3 | L19: ='Data Sheet'!I13+'Data Sheet'!J13 -> 2669.1 | M19: ='Data Sheet'!I13 -> 2041.8 | N19: ='Data Sheet'!K13 -> 1385.8 | O19: ='Data Sheet'!N13 -> 205.79
B21: 1. Multiples Ratio
B23: S.No. | C23: Name | D23: EV/Revenue | E23: EV/EBITDA | F23: P/E | G23: P/BV | H23: EV/EBIT | I23: ROE % | J23: Dividend Yield % | K23: FCF Yield %
B25: 1 | C25: =C10 -> TCS | D25: =J10/K10 -> 3.4347781 | E25: =J10/L10 -> 11.9799 | F25: =E10/(N10/F10) -> 18.771303 | G25: =E10/O10 -> 8.4604923 | H25: =J10/M10 -> 12.937191 | I25: ='Data Sheet'!G28 -> 52.38 | J25: ='Data Sheet'!P4/10 -> 0.24 | K25: ='Data Sheet'!O4/J10 -> 0.050227897
B26: 2 | C26: =C11 -> Infosys | D26: =J11/K11 -> 2.9181122 | E26: =J11/L11 -> 11.145774 | F26: =E11/(N11/F11) -> 18.605051 | G26: =E11/O11 -> 6.2738682 | H26: =J11/M11 -> 12.458108 | I26: ='Data Sheet'!G29 -> 28.83 | J26: ='Data Sheet'!P5/10 -> 0.334 | K26: ='Data Sheet'!O5/J11 -> 0.066207141
B27: 3 | C27: =C12 -> HCL Technologies | D27: =J12/K12 -> 2.803637 | E27: =J12/L12 -> 12.576917 | F27: =E12/(N12/F12) -> 22.397787 | G27: =E12/O12 -> 5.1776737 | H27: =J12/M12 -> 14.843565 | I27: ='Data Sheet'!G30 -> 25 | J27: ='Data Sheet'!P6/10 -> 0.395 | K27: ='Data Sheet'!O6/J12 -> 0.059756502
B28: 4 | C28: =C13 -> Wipro | D28: =J13/K13 -> 2.3900895 | E28: =J13/L13 -> 9.9716228 | F28: =E13/(N13/F13) -> 15.997111 | G28: =E13/O13 -> 2.491729 | H28: =J13/M13 -> 11.505186 | I28: ='Data Sheet'!G31 -> 16.59 | J28: ='Data Sheet'!P7/10 -> 0.541 | K28: ='Data Sheet'!O7/J13 -> 0.072045276
B29: 5 | C29: =C14 -> Tech Mahindra | D29: =J14/K14 -> 2.3458842 | E29: =J14/L14 -> 14.836945 | F29: =E14/(N14/F14) -> 28.730271 | G29: =E14/O14 -> 4.795355 | H29: =J14/M14 -> 18.869528 | I29: ='Data Sheet'!G32 -> 14.62 | J29: ='Data Sheet'!P8/10 -> 0.337 | K29: ='Data Sheet'!O8/J14 -> 0.041007517
B30: 6 | C30: =C15 -> LTIMindtree | D30: =J15/K15 -> 3.0988864 | E30: =J15/L15 -> 15.138531 | F30: =E15/(N15/F15) -> 27.011376 | G30: =E15/O15 -> 5.4521499 | H30: =J15/M15 -> 17.295586 | I30: ='Data Sheet'!G33 -> 21.53 | J30: ='Data Sheet'!P9/10 -> 0.15 | K30: ='Data Sheet'!O9/J15 -> 0.028578404
B31: 7 | C31: =C16 -> Persistent Systems | D31: =J16/K16 -> 5.3789461 | E31: =J16/L16 -> 26.986586 | F31: =E16/(N16/F16) -> 43.644191 | G31: =E16/O16 -> 10.570306 | H31: =J16/M16 -> 31.17962 | I31: ='Data Sheet'!G34 -> 24.08 | J31: ='Data Sheet'!P10/10 -> 0.071 | K31: ='Data Sheet'!O10/J16 -> 0.012859151
B32: 8 | C32: =C17 -> Oracle Fin.Serv. | D32: =J17/K17 -> 7.2282267 | E32: =J17/L17 -> 15.267883 | F32: =E17/(N17/F17) -> 24.104505 | G32: =E17/O17 -> 7.9885919 | H32: =J17/M17 -> 15.568292 | I32: ='Data Sheet'!G35 -> 29.34 | J32: ='Data Sheet'!P11/10 -> 0.389 | K32: ='Data Sheet'!O11/J17 -> 0.040886958
B33: 9 | C33: =C18 -> Mphasis | D33: =J18/K18 -> 2.7567602 | E33: =J18/L18 -> 13.409205 | F33: =E18/(N18/F18) -> 23.308013 | G33: =E18/O18 -> 4.3554935 | H33: =J18/M18 -> 16.164585 | I33: ='Data Sheet'!G36 -> 18.22 | J33: ='Data Sheet'!P12/10 -> 0.255 | K33: ='Data Sheet'!O12/J18 -> 0.043616518
B34: 10 | C34: =C19 -> Coforge | D34: =J19/K19 -> 2.4757498 | E34: =J19/L19 -> 14.165971 | F34: =E19/(N19/F19) -> 27.220445 | G34: =E19/O19 -> 5.4587201 | H34: =J19/M19 -> 18.518167 | I34: ='Data Sheet'!G37 -> 15.98 | J34: ='Data Sheet'!P13/10 -> 0.135 | K34: ='Data Sheet'!O13/J19 -> 0.017981828
C36: Maximum | D36: =MAX(D25:D34) -> 7.2282267 | E36: =MAX(E25:E34) -> 26.986586 | F36: =MAX(F25:F34) -> 43.644191 | G36: =MAX(G25:G34) -> 10.570306 | H36: =MAX(H25:H34) -> 31.17962 | I36: =MAX(I25:I34)/100 -> 0.5238 | J36: =MAX(J25:J34) -> 0.541 | K36: =MAX(K25:K34) -> 0.072045276
C37: 75th Percentile | D37: =QUARTILE(D25:D34,3) -> 3.3508052 | E37: =QUARTILE(E25:E34,3) -> 15.063135 | F37: =QUARTILE(F25:F34,3) -> 27.168178 | G37: =QUARTILE(G25:G34,3) -> 7.559911 | H37: =QUARTILE(H25:H34,3) -> 18.212522 | I37: =QUARTILE(I25:I34,3)/100 -> 0.278725 | J37: =QUARTILE(J25:J34,3) -> 0.376 | K37: =QUARTILE(K25:K34,3) -> 0.057374351
C38: Average | D38: =AVERAGE(D25:D34) -> 3.483107 | E38: =AVERAGE(E25:E34) -> 14.547934 | F38: =AVERAGE(F25:F34) -> 24.979005 | G38: =AVERAGE(G25:G34) -> 6.102438 | H38: =AVERAGE(H25:H34) -> 16.933983 | I38: =AVERAGE(I25:I34)/100 -> 0.24657 | J38: =AVERAGE(J25:J34) -> 0.2847 | K38: =AVERAGE(K25:K34) -> 0.043316719
C39: Median | D39: =MEDIAN(D25:D34) -> 2.8608746 | E39: =MEDIAN(E25:E34) -> 13.787588 | F39: =MEDIAN(F25:F34) -> 23.706259 | G39: =MEDIAN(G25:G34) -> 5.455435 | H39: =MEDIAN(H25:H34) -> 15.866439 | I39: =MEDIAN(I25:I34)/100 -> 0.22805 | J39: =MEDIAN(J25:J34) -> 0.2945 | K39: =MEDIAN(K25:K34) -> 0.042312017
C40: 25th Percentile | D40: =QUARTILE(D25:D34,1) -> 2.5460024 | E40: =QUARTILE(E25:E34,1) -> 12.129154 | F40: =QUARTILE(F25:F34,1) -> 19.677924 | G40: =QUARTILE(G25:G34,1) -> 4.8909346 | H40: =QUARTILE(H25:H34,1) -> 13.413785 | I40: =QUARTILE(I25:I34,1)/100 -> 0.169975 | J40: =QUARTILE(J25:J34,1) -> 0.1725 | K40: =QUARTILE(K25:K34,1) -> 0.031655543
C41: Minimum | D41: =MIN(D25:D34) -> 2.3458842 | E41: =MIN(E25:E34) -> 9.9716228 | F41: =MIN(F25:F34) -> 15.997111 | G41: =MIN(G25:G34) -> 2.491729 | H41: =MIN(H25:H34) -> 11.505186 | I41: =MIN(I25:I34)/100 -> 0.1462 | J41: =MIN(J25:J34) -> 0.071 | K41: =MIN(K25:K34) -> 0.012859151
B43: 2. Quality & Momentum Signals
B45: S.No. | C45: Name | D45: Sales CAGR 3Yrs % | E45: Profit CAGR 3Yrs % | F45: Return 3Yrs% | G45: ROE 3Yr % | H45: ROCE 3Yr % | I45: Debt / Equity | J45: Int Coverage
B47: 1 | C47: =C10 -> TCS | D47: ='Data Sheet'!G16/100 -> 0.1001 | E47: ='Data Sheet'!H16/100 -> 0.0819 | F47: ='Data Sheet'!I16/100 -> -0.0896 | G47: ='Data Sheet'!J16/100 -> 0.503 | H47: ='Data Sheet'!L16/100 -> 0.6252 | I47: ='Data Sheet'!K16 -> 0.1 | J47: ='Data Sheet'!M16 -> 58.24
B48: 2 | C48: =C11 -> Infosys | D48: ='Data Sheet'!G17/100 -> 0.1025 | E48: ='Data Sheet'!H17/100 -> 0.0645 | F48: ='Data Sheet'!I17/100 -> -0.0416 | G48: ='Data Sheet'!J17/100 -> 0.3072 | H48: ='Data Sheet'!L17/100 -> 0.3932 | I48: ='Data Sheet'!K17 -> 0.11 | J48: ='Data Sheet'!M17 -> 98.22
B49: 3 | C49: =C12 -> HCL Technologies | D49: ='Data Sheet'!G18/100 -> 0.1097 | E49: ='Data Sheet'!H18/100 -> 0.0875 | F49: ='Data Sheet'!I18/100 -> 0.0684 | G49: ='Data Sheet'!J18/100 -> 0.238 | H49: ='Data Sheet'!L18/100 -> 0.2982 | I49: ='Data Sheet'!K18 -> 0.1 | J49: ='Data Sheet'!M18 -> 30.42
B50: 4 | C50: =C13 -> Wipro | D50: ='Data Sheet'!G19/100 -> 0.0395 | E50: ='Data Sheet'!H19/100 -> 0.0229 | F50: ='Data Sheet'!I19/100 -> 0.0108 | G50: ='Data Sheet'!J19/100 -> 0.1558 | H50: ='Data Sheet'!L19/100 -> 0.1803 | I50: ='Data Sheet'!K19 -> 0.19 | J50: ='Data Sheet'!M19 -> 12.89
B51: 5 | C51: =C14 -> Tech Mahindra | D51: ='Data Sheet'!G20/100 -> 0.0588 | E51: ='Data Sheet'!H20/100 -> -0.1077 | F51: ='Data Sheet'!I20/100 -> 0.0799 | G51: ='Data Sheet'!J20/100 -> 0.1363 | H51: ='Data Sheet'!L20/100 -> 0.1753 | I51: ='Data Sheet'!K20 -> 0.07 | J51: ='Data Sheet'!M20 -> 20.52
B52: 6 | C52: =C15 -> LTIMindtree | D52: ='Data Sheet'!G21/100 -> 0.1333 | E52: ='Data Sheet'!H21/100 -> 0.0521 | F52: ='Data Sheet'!I21/100 -> -0.0233 | G52: ='Data Sheet'!J21/100 -> 0.2466 | H52: ='Data Sheet'!L21/100 -> 0.3249 | I52: ='Data Sheet'!K21 -> 0.1 | J52: ='Data Sheet'!M21 -> 26.26
B53: 7 | C53: =C16 -> Persistent Systems | D53: ='Data Sheet'!G22/100 -> 0.2787 | E53: ='Data Sheet'!H22/100 -> 0.27 | F53: ='Data Sheet'!I22/100 -> 0.2668 | G53: ='Data Sheet'!J22/100 -> 0.2438 | H53: ='Data Sheet'!L22/100 -> 0.2997 | I53: ='Data Sheet'!K22 -> 0.06 | J53: ='Data Sheet'!M22 -> 33.18
B54: 8 | C54: =C17 -> Oracle Fin.Serv. | D54: ='Data Sheet'!G23/100 -> 0.0945 | E54: ='Data Sheet'!H23/100 -> 0.08 | F54: ='Data Sheet'!I23/100 -> 0.2815 | G54: ='Data Sheet'!J23/100 -> 0.2779 | H54: ='Data Sheet'!L23/100 -> 0.3842 | I54: ='Data Sheet'!K23 -> 0 | J54: ='Data Sheet'!M23 -> 30.91
B55: 9 | C55: =C18 -> Mphasis | D55: ='Data Sheet'!G24/100 -> 0.0596 | E55: ='Data Sheet'!H24/100 -> 0.0566 | F55: ='Data Sheet'!I24/100 -> 0.026 | G55: ='Data Sheet'!J24/100 -> 0.1938 | H55: ='Data Sheet'!L24/100 -> 0.2519 | I55: ='Data Sheet'!K24 -> 0.21 | J55: ='Data Sheet'!M24 -> 16.08
B56: 10 | C56: =C19 -> Coforge | D56: ='Data Sheet'!G25/100 -> 0.2328 | E56: ='Data Sheet'!H25/100 -> 0.0653 | F56: ='Data Sheet'!I25/100 -> 0.1125 | G56: ='Data Sheet'!J25/100 -> 0.2087 | H56: ='Data Sheet'!L25/100 -> 0.2678 | I56: ='Data Sheet'!K25 -> 0.14 | J56: ='Data Sheet'!M25 -> 12.13
C58: Maximum | D58: =MAX(D47:D56) -> 0.2787 | E58: =MAX(E47:E56) -> 0.27 | F58: =MAX(F47:F56) -> 0.2815 | G58: =MAX(G47:G56) -> 0.503 | H58: =MAX(H47:H56) -> 0.6252 | I58: =MAX(I47:I56) -> 0.21 | J58: =MAX(J47:J56) -> 98.22
C59: 75th Percentile | D59: =QUARTILE(D47:D56,3) -> 0.1274 | E59: =QUARTILE(E47:E56,3) -> 0.081425 | F59: =QUARTILE(F47:F56,3) -> 0.10435 | G59: =QUARTILE(G47:G56,3) -> 0.270075 | H59: =QUARTILE(H47:H56,3) -> 0.369375 | I59: =QUARTILE(I47:I56,3) -> 0.1325 | J59: =QUARTILE(J47:J56,3) -> 32.6125
C60: Average | D60: =AVERAGE(D47:D56) -> 0.12095 | E60: =AVERAGE(E47:E56) -> 0.06731 | F60: =AVERAGE(F47:F56) -> 0.06914 | G60: =AVERAGE(G47:G56) -> 0.25111 | H60: =AVERAGE(H47:H56) -> 0.32007 | I60: =AVERAGE(I47:I56) -> 0.108 | J60: =AVERAGE(J47:J56) -> 33.885
C61: Median | D61: =MEDIAN(D47:D56) -> 0.1013 | E61: =MEDIAN(E47:E56) -> 0.0649 | F61: =MEDIAN(F47:F56) -> 0.0472 | G61: =MEDIAN(G47:G56) -> 0.2409 | H61: =MEDIAN(H47:H56) -> 0.29895 | I61: =MEDIAN(I47:I56) -> 0.1 | J61: =MEDIAN(J47:J56) -> 28.34
C62: 25th Percentile | D62: =QUARTILE(D47:D56,1) -> 0.068325 | E62: =QUARTILE(E47:E56,1) -> 0.053225 | F62: =QUARTILE(F47:F56,1) -> -0.014775 | G62: =QUARTILE(G47:G56,1) -> 0.197525 | H62: =QUARTILE(H47:H56,1) -> 0.255875 | I62: =QUARTILE(I47:I56,1) -> 0.0775 | J62: =QUARTILE(J47:J56,1) -> 17.19
C63: Minimum | D63: =MIN(D47:D56) -> 0.0395 | E63: =MIN(E47:E56) -> -0.1077 | F63: =MIN(F47:F56) -> -0.0896 | G63: =MIN(G47:G56) -> 0.1363 | H63: =MIN(H47:H56) -> 0.1753 | I63: =MIN(I47:I56) -> 0 | J63: =MIN(J47:J56) -> 12.13
B65: 3. Sector Specific KPI's
B67: S.No. | C67: Name | D67: Revenue | E67: Avg Revenue 5Yrs % | F67: Avg OPM 5Yrs % | G67: Avg Head Count FY 25 | H67: Revenue / Headcount | I67: Attrition % | J67: Utilisation %
B69: 1 | C69: TCS | D69: =K10 -> 260802 | E69: ='Data Sheet'!E28 -> 10.22 | F69: ='Data Sheet'!F28 -> 26.96 | G69: 607354 | H69: =D69/G69 -> 0.4294069 | I69: 0.133 | J69: 0.851
B70: 2 | C70: Infosys | D70: =K11 -> 173173 | E70: ='Data Sheet'!E29 -> 12.41 | F70: ='Data Sheet'!F29 -> 24.82 | G70: 323578 | H70: =D70/G70 -> 0.53518163 | I70: 0.137 | J70: 0.84
B71: 3 | C71: HCL Technologies | D71: =K12 -> 126409 | E71: ='Data Sheet'!E30 -> 10.62 | F71: ='Data Sheet'!F30 -> 23.07 | G71: 223420 | H71: =D71/G71 -> 0.56579089 | I71: 0.129 | J71: 0.83
B72: 4 | C72: Wipro | D72: =K13 -> 90891.9 | E72: ='Data Sheet'!E31 -> 7.82 | F72: ='Data Sheet'!F31 -> 20.23 | G72: 233346 | H72: =D72/G72 -> 0.38951557 | I72: 0.151 | J72: 0.82
B73: 5 | C73: Tech Mahindra | D73: =K14 -> 55123.3 | E73: ='Data Sheet'!E32 -> 7.52 | F73: ='Data Sheet'!F32 -> 14.14 | G73: 148731 | H73: =D73/G73 -> 0.37062415 | I73: 0.124 | J73: 0.81
B74: 6 | C74: LTIMindtree | D74: =K15 -> 40787.6 | E74: ='Data Sheet'!E33 -> 28.43 | F74: ='Data Sheet'!F33 -> 18.57 | G74: 81000 | H74: =D74/G74 -> 0.50355062 | I74: 0.146 | J74: 0.835
B75: 7 | C75: Persistent Systems | D75: =K16 -> 13934.63 | E75: ='Data Sheet'!E34 -> 27.34 | F75: ='Data Sheet'!F34 -> 17.23 | G75: 25000 | H75: =D75/G75 -> 0.5573852 | I75: 0.118 | J75: 0.855
B76: 8 | C76: Oracle Fin.Serv. | D76: =K17 -> 7323.2 | E76: ='Data Sheet'!E35 -> 7.09 | F76: ='Data Sheet'!F35 -> 45.66 | G76: 32500 | H76: =D76/G76 -> 0.22532923 | I76: 0.102 | J76: ~
B77: 9 | C77: Mphasis | D77: =K18 -> 15347.02 | E77: ='Data Sheet'!E36 -> 9.98 | F77: ='Data Sheet'!F36 -> 18.13 | G77: 30000 | H77: =D77/G77 -> 0.51156733 | I77: 0.172 | J77: 0.828
B78: 10 | C78: Coforge | D78: =K19 -> 15272.3 | E78: ='Data Sheet'!E37 -> 23.56 | F78: ='Data Sheet'!F37 -> 15.7 | G78: 7000 | H78: =D78/G78 -> 2.1817571 | I78: 0.158 | J78: 0.83
C80: Maximum | D80: =MAX(D69:D78) -> 260802 | E80: =MAX(E69:E78)/100 -> 0.2843 | F80: =MAX(F69:F78)/100 -> 0.4566 | G80: =MAX(G69:G78) -> 607354 | H80: =MAX(H69:H78) -> 2.1817571 | I80: =MAX(I69:I78) -> 0.172 | J80: =MAX(J69:J78) -> 0.855
C81: 75th Percentile | D81: =QUARTILE(D69:D78,3) -> 117529.73 | E81: =QUARTILE(E69:E78,3)/100 -> 0.207725 | F81: =QUARTILE(F69:F78,3)/100 -> 0.243825 | G81: =QUARTILE(G69:G78,3) -> 230864.5 | H81: =QUARTILE(H69:H78,3) -> 0.55183431 | I81: =QUARTILE(I69:I78,3) -> 0.14975 | J81: =QUARTILE(J69:J78,3) -> 0.84
C82: Average | D82: =AVERAGE(D69:D78) -> 79906.395 | E82: =AVERAGE(E69:E78)/100 -> 0.14499 | F82: =AVERAGE(F69:F78)/100 -> 0.22451 | G82: =AVERAGE(G69:G78) -> 171192.9 | H82: =AVERAGE(H69:H78) -> 0.62701087 | I82: =AVERAGE(I69:I78) -> 0.137 | J82: =AVERAGE(J69:J78) -> 0.83322222
C83: Median | D83: =MEDIAN(D69:D78) -> 47955.45 | E83: =MEDIAN(E69:E78)/100 -> 0.1042 | F83: =MEDIAN(F69:F78)/100 -> 0.194 | G83: =MEDIAN(G69:G78) -> 114865.5 | H83: =MEDIAN(H69:H78) -> 0.50755898 | I83: =MEDIAN(I69:I78) -> 0.135 | J83: =MEDIAN(J69:J78) -> 0.83
C84: 25th Percentile | D84: =QUARTILE(D69:D78,1) -> 15290.98 | E84: =QUARTILE(E69:E78,1)/100 -> 0.0836 | F84: =QUARTILE(F69:F78,1)/100 -> 0.17455 | G84: =QUARTILE(G69:G78,1) -> 30625 | H84: =QUARTILE(H69:H78,1) -> 0.3994884 | I84: =QUARTILE(I69:I78,1) -> 0.12525 | J84: =QUARTILE(J69:J78,1) -> 0.828
C85: Minimum | D85: =MIN(D69:D78) -> 7323.2 | E85: =MIN(E69:E78)/100 -> 0.0709 | F85: =MIN(F69:F78)/100 -> 0.1414 | G85: =MIN(G69:G78) -> 7000 | H85: =MIN(H69:H78) -> 0.22532923 | I85: =MIN(I69:I78) -> 0.102 | J85: =MIN(J69:J78) -> 0.81
B88: 4. Historical Price of Indices and Stocks, for 5 year period (investing.com)
B89: (14-Mar-2021 to 08-Mar-2026)
B91: Date | C91: Nifty 50 | D91: Nifty IT | E91: TCS | F91: Infosys | G91: HCL Technologies | H91: Wipro | I91: Tech Mahindra | J91: LTIMindtree | K91: Persistent Systems | L91: Oracle Fin.Serv. | M91: Mphasis | N91: Coforge
B93: 46089 | C93: 23866.85 | D93: 29651.7 | E93: 2461 | F93: 1275.8 | G93: 1350.6 | H93: 201.8 | I93: 1334.2 | J93: 4274 | K93: 4747.9 | L93: 6770.5 | M93: 2178 | N93: 1111
B94: 46082 | C94: 24450.45 | D94: 30138.4 | E94: 2557.6 | F94: 1308.4 | G94: 1356.7 | H94: 195.4 | I94: 1331.7 | J94: 4292 | K94: 4777.5 | L94: 6718 | M94: 2214.8 | N94: 1162.9
B95: 46075 | C95: 25178.65 | D95: 30603.85 | E95: 2637.4 | F95: 1300.1 | G95: 1389.1 | H95: 200.96 | I95: 1357.8 | J95: 4462 | K95: 4733 | L95: 6932 | M95: 2296.5 | N95: 1185.8
B96: 46068 | C96: 25571.25 | D96: 32004.05 | E96: 2686.2 | F96: 1353.2 | G96: 1436.5 | H96: 209.86 | I96: 1456.9 | J96: 4889.5 | K96: 5092 | L96: 6642.5 | M96: 2373.8 | N96: 1340.6
B97: 46061 | C97: 25471.1 | D97: 32681.5 | E97: 2692.2 | F97: 1369.1 | G97: 1455.2 | H97: 214.09 | I97: 1534.4 | J97: 5115.5 | K97: 5479 | L97: 6639 | M97: 2458.4 | N97: 1361.8
B98: 46054 | C98: 25693.7 | D98: 35611.05 | E98: 2941.6 | F98: 1507.1 | G98: 1593.7 | H98: 230.72 | I98: 1619.9 | J98: 5561.5 | K98: 5852 | L98: 7264 | M98: 2610.5 | N98: 1546
B99: 46047 | C99: 25320.65 | D99: 38036.15 | E99: 3123.9 | F99: 1641 | G99: 1695.6 | H99: 236.9 | I99: 1743.1 | J99: 5974.5 | K99: 6035 | L99: 7760 | M99: 2759 | N99: 1653.8
B100: 46040 | C100: 25048.65 | D100: 38238.5 | E100: 3162.5 | F100: 1670.8 | G100: 1707 | H100: 238.4 | I100: 1701.1 | J100: 5893.5 | K100: 6155 | L100: 7956 | M100: 2752.8 | N100: 1636.4
B101: 46033 | C101: 25694.35 | D101: 39086.65 | E101: 3206.7 | F101: 1689.8 | G101: 1698 | H101: 267.45 | I101: 1670.5 | J101: 6308 | K101: 6403 | L101: 7959.5 | M101: 2886.5 | N101: 1732.3
B102: 46026 | C102: 25683.3 | D102: 38027.2 | E102: 3161.58 | F102: 1614.1 | G102: 1661.4 | H102: 261.95 | I102: 1582.2 | J102: 6037 | K102: 6417 | L102: 7597.5 | M102: 2838.2 | N102: 1681.6
B103: 46019 | C103: 26328.55 | D103: 38320.3 | E103: 3203.86 | F103: 1640.4 | G103: 1640.2 | H103: 269 | I103: 1612 | J103: 6067 | K103: 6289.5 | L103: 7731.5 | M103: 2807.2 | N103: 1650.3
B104: 46012 | C104: 26042.3 | D104: 38572.3 | E104: 3232.74 | F104: 1656.1 | G104: 1660.9 | H104: 266.3 | I104: 1612.3 | J104: 6035.5 | K104: 6300.5 | L104: 7777 | M104: 2850.6 | N104: 1673.3
... B353: 44269 | C353: 14744 | D353: 25562.75 | E353: 2929.16 | F353: 1336.92 | G353: 946.87 | H353: 205.25 | I353: 936.76 | J353: 4066.32 | K353: 969.05 | L353: 3205.15 | M353: 1651.27 | N353: 593.35
B355: 5. Returns Table of Indices & Stocks
B356: (14-Mar-2021 to 08-Mar-2026)
B358: Date | C358: Nifty 50 | D358: Nifty IT | E358: TCS | F358: Infosys | G358: HCL Technologies | H358: Wipro | I358: Tech Mahindra | J358: LTIMindtree | K358: Persistent Systems | L358: Oracle Fin.Serv. | M358: Mphasis | N358: Coforge
B360: 46089
B361: 46082 | C361: =C94/C93-1 -> 0.024452326 | D361: =D94/D93-1 -> 0.016413899 | E361: =E94/E93-1 -> 0.039252336 | F361: =F94/F93-1 -> 0.025552594 | G361: =G94/G93-1 -> 0.0045165112 | H361: =H94/H93-1 -> -0.031714569 | I361: =I94/I93-1 -> -0.001873782 | J361: =J94/J93-1 -> 0.0042115115 | ... N361: =N94/N93-1 -> 0.046714671
B362: 46075 | C362: =C95/C94-1 -> 0.029782683 | D362: =D95/D94-1 -> 0.015443753 | E362: =E95/E94-1 -> 0.031201126 | F362: =F95/F94-1 -> -0.0063436258 | G362: =G95/G94-1 -> 0.023881477 | H362: =H95/H94-1 -> 0.028454452 | I362: =I95/I94-1 -> 0.019599009 | J362: =J95/J94-1 -> 0.039608574 | ... N362: =N95/N94-1 -> 0.019692149
B363: 46068 | C363: =C96/C95-1 -> 0.015592575 | D363: =D96/D95-1 -> 0.045752414 | E363: =E96/E95-1 -> 0.018503071 | F363: =F96/F95-1 -> 0.040843012 | G363: =G96/G95-1 -> 0.034122813 | H363: =H96/H95-1 -> 0.04428742 | I363: =I96/I95-1 -> 0.072985712 | J363: =J96/J95-1 -> 0.095809054 | ... N363: =N96/N95-1 -> 0.13054478
B364: 46061 | C364: =C97/C96-1 -> -0.0039165078 | D364: =D97/D96-1 -> 0.021167633 | E364: =E97/E96-1 -> 0.0022336386 | F364: =F97/F96-1 -> 0.011749926 | G364: =G97/G96-1 -> 0.013017751 | H364: =H97/H96-1 -> 0.020156295 | I364: =I97/I96-1 -> 0.05319514 | J364: =J97/J96-1 -> 0.046221495 | ... N364: =N97/N96-1 -> 0.015813815
B365: 46054 | C365: =C98/C97-1 -> 0.0087393163 | D365: =D98/D97-1 -> 0.089639398 | E365: =E98/E97-1 -> 0.092637991 | F365: =F98/F97-1 -> 0.10079614 | G365: =G98/G97-1 -> 0.095175921 | H365: =H98/H97-1 -> 0.077677612 | I365: =I98/I97-1 -> 0.055722106 | J365: =J98/J97-1 -> 0.087186003 | ... N365: =N98/N97-1 -> 0.13526215
B366: 46047 | C366: =C99/C98-1 -> -0.014519123 | D366: =D99/D98-1 -> 0.068099649 | E366: =E99/E98-1 -> 0.061973076 | F366: =F99/F98-1 -> 0.088846128 | G366: =G99/G98-1 -> 0.063939261 | H366: =H99/H98-1 -> 0.026785714 | I366: =I99/I98-1 -> 0.076054077 | J366: =J99/J98-1 -> 0.074260541 | ... N366: =N99/N98-1 -> 0.069728331
B367: 46040 | C367: =C100/C99-1 -> -0.01074222 | D367: =D100/D99-1 -> 0.0053199391 | E367: =E100/E99-1 -> 0.012356349 | F367: =F100/F99-1 -> 0.018159659 | G367: =G100/G99-1 -> 0.0067232838 | H367: =H100/H99-1 -> 0.0063317856 | I367: =I100/I99-1 -> -0.024095003 | J367: =J100/J99-1 -> -0.01355762 | ... N367: =N100/N99-1 -> -0.010521224
B368: 46033 | C368: =C101/C100-1 -> 0.025777836 | D368: =D101/D100-1 -> 0.022180525 | E368: =E101/E100-1 -> 0.013976285 | F368: =F101/F100-1 -> 0.011371798 | G368: =G101/G100-1 -> -0.0052724077 | H368: =H101/H100-1 -> 0.12185403 | I368: =I101/I100-1 -> -0.01798836 | J368: =J101/J100-1 -> 0.070331721 | ... N368: =N101/N100-1 -> 0.058604253
B369: 46026 | C369: =C102/C101-1 -> -0.00043005563 | D369: =D102/D101-1 -> -0.027105163 | E369: =E102/E101-1 -> -0.01407054 | F369: =F102/F101-1 -> -0.044798201 | G369: =G102/G101-1 -> -0.02155477 | H369: =H102/H101-1 -> -0.020564592 | I369: =I102/I101-1 -> -0.052858426 | J369: =J102/J101-1 -> -0.042961319 | ... N369: =N102/N101-1 -> -0.029267448
B370: 46019 | C370: =C103/C102-1 -> 0.025123329 | D370: =D103/D102-1 -> 0.0077076408 | E370: =E103/E102-1 -> 0.01337306 | F370: =F103/F102-1 -> 0.01629391 | G370: =G103/G102-1 -> -0.012760323 | H370: =H103/H102-1 -> 0.026913533 | I370: =I103/I102-1 -> 0.018834534 | J370: =J103/J102-1 -> 0.0049693556 | ... N370: =N103/N102-1 -> -0.018613225
B371: 46012 | C371: =C104/C103-1 -> -0.010872228 | D371: =D104/D103-1 -> 0.0065761489 | E371: =E104/E103-1 -> 0.0090141267 | F371: =F104/F103-1 -> 0.0095708364 | G371: =G104/G103-1 -> 0.012620412 | H371: =H104/H103-1 -> -0.010037175 | I371: =I104/I103-1 -> 0.00018610422 | J371: =J104/J103-1 -> -0.0051920224 | ... N371: =N104/N103-1 -> 0.01393686
B372: 46005 | C372: =C105/C104-1 -> -0.0029144891 | D372: =D105/D104-1 -> 0.0030928931 | E372: =E105/E104-1 -> 0.015237848 | F372: =F105/F104-1 -> -0.010506612 | G372: =G105/G104-1 -> -0.011138539 | H372: =H105/H104-1 -> -0.0069470522 | I372: =I105/I104-1 -> 0.00012404639 | J372: =J105/J104-1 -> 0.02684119 | ... N372: =N105/N104-1 -> 0.10285065
...

Sheet Charts
B2: IT - Software | Sector Comps - Relative Value Analysis
B3: (Figures in Rs. Cr., except price per share, shares outstanding, and other ratios)
B6: 1. Sector Summary

Sheet Data Sheet
A1: Indian IT-Software
A3: S.No. | B3: Name | C3: CMP Rs. | D3: No. Eq. Shares Cr. | E3: Debt Rs.Cr. | F3: Cash End Rs.Cr. | G3: EV Rs.Cr. | H3: Sales Rs.Cr. | I3: EBIT 12M Rs.Cr. | J3: Dep 12M Rs.Cr. | K3: NP 12M Rs.Cr. | L3: P/E | M3: OPM % | N3: B.V. Rs. | O3: Free Cash Flow Rs.Cr. | P3: Div Yld %
A4: 1 | B4: TCS | C4: 2488.4 | D4: 361.81 | E4: 10932 | F4: 15463 | G4: 896803.87 | H4: 260802 | I4: 69242 | J4: 5533 | K4: 47963 | L4: 17.6 | M4: 26.88 | N4: 294.12 | O4: 44994 | P4: 2.4
A5: 2 | B5: Infosys | C5: 1284.7 | D5: 405.54 | E5: 8796 | F5: 24455 | G5: 509877.1 | H5: 173173 | I5: 40563 | J5: 4776 | K5: 28003 | L5: 18.02 | M5: 23.67 | N5: 204.77 | O5: 33457 | P5: 3.34
A6: 3 | B6: HCL Technologies | C6: 1359.45 | D6: 271.37 | E6: 6780 | F6: 21289 | G6: 351941.21 | H6: 126409 | I6: 23876 | J6: 4303 | K6: 16471 | L6: 21.48 | M6: 20.94 | N6: 262.56 | O6: 21178 | P6: 3.95
A7: 4 | B7: Wipro | C7: 203.35 | D7: 1048.8 | E7: 16163.7 | F7: 12197.4 | G7: 216354.45 | H7: 90891.9 | I7: 18881.9 | J7: 2903.9 | K7: 13332 | L7: 16.07 | M7: 19.28 | N7: 81.61 | O7: 15651.1 | P7: 5.41
A8: 5 | B8: Tech Mahindra | C8: 1346.2 | D8: 97.98 | E8: 1954.4 | F8: 4542.2 | G8: 129565.74 | H8: 55123.3 | I8: 6853 | J8: 1862.6 | K8: 4591 | L8: 27.4 | M8: 15.07 | N8: 280.73 | O8: 5302.8 | P8: 3.37
A9: 6 | B9: LTIMindtree | C9: 4303.6 | D9: 29.65 | E9: 2382.6 | F9: 3588.2 | G9: 126996.05 | H9: 40787.6 | I9: 7308 | J9: 1041.3 | K9: 4724 | L9: 24.61 | M9: 17.6 | N9: 789.34 | O9: 3612.2 | P9: 1.5
A10: 7 | B10: Persistent Systems | C10: 4789.3 | D10: 15.78 | E10: 403.94 | F10: 1025.47 | G10: 74751.83 | H10: 13934.63 | I10: 2403.93 | J10: 373.51 | K10: 1731.62 | L10: 42.04 | M10: 18.75 | N10: 453.09 | O10: 963.84 | P10: 0.71
A11: 8 | B11: Oracle Fin.Serv. | C11: 6764.5 | D11: 8.7 | E11: 34 | F11: 5951.4 | G11: 54061.87 | H11: 7323.2 | I11: 3400.1 | J11: 66.9 | K11: 2441.5 | L11: 24.11 | M11: 43.5 | N11: 846.77 | O11: 2164.3 | P11: 3.89
A12: 9 | B12: Mphasis | C12: 2199.35 | D12: 19.07 | E12: 1979.03 | F12: 1612.58 | G12: 42297.76 | H12: 15347.02 | I12: 2617.33 | J12: 537.82 | K12: 1799.45 | L12: 22.99 | M12: 18.75 | N12: 504.96 | O12: 1845.33 | P12: 2.55
A13: 10 | B13: Coforge | C13: 1123.35 | D13: 33.58 | E13: 971.5 | F13: 883.2 | G13: 38161.22 | H13: 15272.3 | I13: 2041.8 | J13: 627.3 | K13: 1385.8 | L13: 30.02 | M13: 16.81 | N13: 205.79 | O13: 679.9 | P13: 1.35
A15: S.No. | B15: Name | C15: CMP Rs. | D15: No. Eq. Shares Cr. | E15: Sales Rs.Cr. | F15: NP 12M Rs.Cr. | G15: Sales Var 3Yrs % | H15: Profit Var 3Yrs % | I15: 3Yrs return % | J15: ROE 3Yr % | K15: Debt / Eq | L15: ROCE 3Yr % | M15: Int Coverage
A16: 1 | B16: TCS | C16: 2483.95 | D16: 361.81 | E16: 260802 | F16: 47963 | G16: 10.01 | H16: 8.19 | I16: -8.96 | J16: 50.3 | K16: 0.1 | L16: 62.52 | M16: 58.24
A17: 2 | B17: Infosys | C17: 1283.7 | D17: 405.54 | E17: 173173 | F17: 28003 | G17: 10.25 | H17: 6.45 | I17: -4.16 | J17: 30.72 | K17: 0.11 | L17: 39.32 | M17: 98.22
A18: 3 | B18: HCL Technologies | C18: 1361 | D18: 271.37 | E18: 126409 | F18: 16471 | G18: 10.97 | H18: 8.75 | I18: 6.84 | J18: 23.8 | K18: 0.1 | L18: 29.82 | M18: 30.42
A19: 4 | B19: Wipro | C19: 203.3 | D19: 1048.8 | E19: 90891.9 | F19: 13332 | G19: 3.95 | H19: 2.29 | I19: 1.08 | J19: 15.58 | K19: 0.19 | L19: 18.03 | M19: 12.89
A20: 5 | B20: Tech Mahindra | C20: 1346.9 | D20: 97.98 | E20: 55123.3 | F20: 4591 | G20: 5.88 | H20: -10.77 | I20: 7.99 | J20: 13.63 | K20: 0.07 | L20: 17.53 | M20: 20.52
A21: 6 | B21: LTIMindtree | C21: 4303.7 | D21: 29.65 | E21: 40787.6 | F21: 4724 | G21: 13.33 | H21: 5.21 | I21: -2.33 | J21: 24.66 | K21: 0.1 | L21: 32.49 | M21: 26.26
A22: 7 | B22: Persistent Systems | C22: 4774.4 | D22: 15.78 | E22: 13934.63 | F22: 1731.62 | G22: 27.87 | H22: 27 | I22: 26.68 | J22: 24.38 | K22: 0.06 | L22: 29.97 | M22: 33.18
A23: 8 | B23: Oracle Fin.Serv. | C23: 6769.95 | D23: 8.7 | E23: 7323.2 | F23: 2441.5 | G23: 9.45 | H23: 8 | I23: 28.15 | J23: 27.79 | K23: 0 | L23: 38.42 | M23: 30.91
A24: 9 | B24: Mphasis | C24: 2184.6 | D24: 19.07 | E24: 15347.02 | F24: 1799.45 | G24: 5.96 | H24: 5.66 | I24: 2.6 | J24: 19.38 | K24: 0.21 | L24: 25.19 | M24: 16.08
A25: 10 | B25: Coforge | C25: 1120 | D25: 33.58 | E25: 15272.3 | F25: 1385.8 | G25: 23.28 | H25: 6.53 | I25: 11.25 | J25: 20.87 | K25: 0.14 | L25: 26.78 | M25: 12.13
A27: S.No. | B27: Name | C27: CMP Rs. | D27: Avg EBIT 5Yrs Rs.Cr. | E27: Sales Var 5Yrs % | F27: 5Yr OPM % | G27: ROE %
A28: 1 | B28: TCS | C28: 2465.15 | D28: 57099 | E28: 10.22 | F28: 26.96 | G28: 52.38
A29: 2 | B29: Infosys | C29: 1276.35 | D29: 32849.2 | E29: 12.41 | F29: 24.82 | G29: 28.83
A30: 3 | B30: HCL Technologies | C30: 1352 | D30: 19585.6 | E30: 10.62 | F30: 23.07 | G30: 25
A31: 4 | B31: Wipro | C31: 202.1 | D31: 16106.12 | E31: 7.82 | F31: 20.23 | G31: 16.59
A32: 5 | B32: Tech Mahindra | C32: 1333.95 | D32: 5927.24 | E32: 7.52 | F32: 14.14 | G32: 14.62
A33: 6 | B33: LTIMindtree | C33: 4265 | D33: 5357.94 | E33: 28.43 | F33: 18.57 | G33: 21.53
A34: 7 | B34: Persistent Systems | C34: 4736.85 | D34: 1214.7 | E34: 27.34 | F34: 17.23 | G34: 24.08
A35: 8 | B35: Oracle Fin.Serv. | C35: 6777.15 | D35: 2796.25 | E35: 7.09 | F35: 45.66 | G35: 29.34
A36: 9 | B36: Mphasis | C36: 2184.35 | D36: 2106.16 | E36: 9.98 | F36: 18.13 | G36: 18.22
A37: 10 | B37: Coforge | C37: 1108.8 | D37: 1049.1 | E37: 23.56 | F37: 15.7 | G37: 15.98
