Workbook
Name days: Dashboard!$E$12
Name tgr: DCF!$E$15
Name tgrth1: DCF!$E$91
Name wacc: DCF!$E$14
Name wacc1: DCF!$E$90

Sheet Dashboard
C2: Lloyds Metal & Energy Ltd.
C3: Dashboard
C4: (₹ in 'Cr, except share price and shares outstanding)
B6: # | C6: Dashboard
C8: Company Name: | E8: =C2 -> Lloyds Metal & Energy Ltd.
C9: Ticker: | E9: LLOYDME
C10: Date: | E10: =TODAY() -> 46106
C11: Sector: | E11: Industrial Minerals
C12: Days: | E12: 365
C14: Scenario Selected: | E14: 1
B16: # | C16: Table of Content | H16: # | I16: Key Financial Metrices
C17: Sl No | E17: Particulars | I17: Valuation | K17: FY 25 A | L17: FY 26 E
C18: 1 | E18: Dashboard | I18: Current Price (₹) | K18: 1246 | L18: =K18 -> 1246
C19: 2 | E19: Summary | I19: Implied Price (₹) | K19: =DCF!G39 -> 922.84986 | L19: =DCF!G115 -> 1204.5544
C20: 3 | E20: Financials | I20: Premium / (Discount) | K20: =K19/K18-1 -> -0.25935003 | L20: =L19/L18-1 -> -0.033262906
C21: 4 | E21: Assuptions | I21: P/E (x) | K21: =K18/Financials!J41 -> 47.70291 | L21: =L18/Financials!K41 -> 21.920665
C22: 5 | E22: Schedule | I22: ROE % | K22: =Financials!J37/Financials!J77 -> 0.22647498 | L22: =Financials!K37/Financials!K77 -> 0.3349242
C23: 6 | E23: Company Comparables | I23: ROA % | K23: =Financials!J37/Financials!J72 -> 0.15396999 | L23: =Financials!K37/Financials!K72 -> 0.18320357
C24: 7 | E24: DCF | I24: ROCE % | K24: =Financials!J32/(Financials!J72-Financials!J96) -> 0.25964577 | L24: =Financials!K32/(Financials!K72-Financials!K96) -> 0.27443034
C25: 8 | E25: WACC | I25: EPS (₹) | K25: =Financials!J41 -> 26.12 | L25: =Financials!K41 -> 56.841342
C26: 9 | E26: Beta | I26: Annual Dividends (₹ in Cr.) | K26: =Assumptions!J81 -> 52.28 | L26: =Assumptions!K81 -> 315.63997
C27: 10 | E27: Ratio Analysis | I27: Dividend Yield % | K27: =K26/Financials!J37 -> 0.036057162 | L27: =L26/Financials!K37 -> 0.1
C28: 11 | E28: Analysis
B30: # | C30: End

Sheet Summary
C2: =Dashboard!C2 -> Lloyds Metal & Energy Ltd.
C3: Summary
C4: =Dashboard!C4 -> (₹ in 'Cr, except share price and shares outstanding)
C6: <-Back to Dashboard
B8: # | C8: Valuation
C10: Metrics | D10: DCF | E10: EV / Revenue | F10: EV / EBITDA | G10: P / Sales | H10: P / E | I10: 52 - wk range
C11: 75th Percentile | D11: =DCF!M45 -> 962.10736 | E11: =Comps!S31 -> 411.08173 | F11: =Comps!T31 -> 13.582106 | G11: =Comps!U31 -> 398.57591 | H11: =Comps!V31 -> 0.0088381485 | I11: =Comps!E40 -> 1302.2736
C12: Average | D12: =DCF!M46 -> 922.84986 | E12: =Comps!S32 -> 439.52696 | F12: =Comps!T32 -> 19.295346 | G12: =Comps!U32 -> 759.41962 | H12: =Comps!V32 -> 0.068709482 | I12: =Comps!E41 -> 1293.4
C13: Median | D13: =DCF!M47 -> 1341.0953 | E13: =Comps!S33 -> 383.2586 | F13: =Comps!T33 -> 9.3316268 | G13: =Comps!U33 -> 437.76768 | H13: =Comps!V33 -> 0.028283968 | I13: =Comps!E42 -> 1351.25
C14: 25th Percentile | D14: =DCF!M48 -> 392.24085 | E14: =Comps!S34 -> 657.6448 | F14: =Comps!T34 -> 30.366262 | G14: =Comps!U34 -> 920.74463 | H14: =Comps!V34 -> 0.065404875 | I14: =Comps!E43 -> 1226
B16: # | C16: Football Chart
C18: Metrics | D18: Min | E18: Median | F18: Max
C19: {=TRANSPOSE(D10:I10)} -> DCF | D19: {=TRANSPOSE(D14:I14)} -> 392.24085 | E19: {=TRANSPOSE(D12:I12)} -> 922.84986 | F19: {=TRANSPOSE(D11:I11)} -> 962.10736
C20: EV / Revenue | D20: 657.6448 | E20: 439.52696 | F20: 411.08173
C21: EV / EBITDA | D21: 30.366262 | E21: 19.295346 | F21: 13.582106
C22: P / Sales | D22: 920.74463 | E22: 759.41962 | F22: 398.57591
C23: P / E | D23: 0.065404875 | E23: 0.068709482 | F23: 0.0088381485
C24: 52 - wk range | D24: 1226 | E24: 1293.4 | F24: 1302.2736
B26: # | C26: End

Sheet Financials->

Sheet Financials
C2: =Dashboard!C2 -> Lloyds Metal & Energy Ltd.
C3: Financials
C4: =Dashboard!C4 -> (₹ in 'Cr, except share price and shares outstanding)
C5: Actuals / Projections | G5: Acutals | K5: Projections
C6: Date / Year | G6: 44651 | H6: =EOMONTH(G6,12) -> 45016 | I6: =EOMONTH(H6,12) -> 45382 | J6: =EOMONTH(I6,12) -> 45747 | K6: =EOMONTH(J6,12) -> 46112 | L6: =EOMONTH(K6,12) -> 46477 | M6: =EOMONTH(L6,12) -> 46843 | N6: =EOMONTH(M6,12) -> 47208 | O6: =EOMONTH(N6,12) -> 47573
C8: <-Back to Dashboard
C10: Templete: | D10: Standard | F10: Currency: | G10: INR
C11: Period type: | D11: Annual | F11: Units: | G11: Crore
C12: Source: | D12: Company Website | F12: Decimals: | G12: Default
B14: # | C14: Income Statement | G14: 44651 | H14: =EOMONTH(G14,12) -> 45016 | I14: =EOMONTH(H14,12) -> 45382 | J14: =EOMONTH(I14,12) -> 45747 | K14: =EOMONTH(J14,12) -> 46112 | L14: =EOMONTH(K14,12) -> 46477 | M14: =EOMONTH(L14,12) -> 46843 | N14: =EOMONTH(M14,12) -> 47208 | O14: =EOMONTH(N14,12) -> 47573 | Q14: Q3 2026
C16: Gross Sales From Operations | G16: 697.5 | H16: 3392.31 | I16: 6481.01 | J16: 6626.31 | K16: =Assumptions!K18 -> 14436.08 | L16: =Assumptions!L18 -> 18766.904 | M16: =Assumptions!M18 -> 23458.63 | N16: =Assumptions!N18 -> 28150.356 | O16: =Assumptions!O18 -> 33217.42 | Q16: 10827.06
C17: Gross Operating Revenues | G17: 0 | H17: 0 | I17: 43.64 | J17: 95.09 | K17: =Assumptions!K24 -> 354.52 | L17: =Assumptions!L24 -> 638.136 | M17: =Assumptions!M24 -> 1116.738 | N17: =Assumptions!N24 -> 1898.4546 | O17: =Assumptions!O24 -> 3189.4037 | Q17: 265.89
C18: Other Income | G18: 29.75 | H18: 74.46 | I18: 49.95 | J18: 51.22 | K18: =Assumptions!K30 -> 241.18667 | L18: =Assumptions!L30 -> 265.30533 | M18: =Assumptions!M30 -> 305.10113 | N18: =Assumptions!N30 -> 366.12136 | O18: =Assumptions!O30 -> 410.05592 | Q18: 180.89
C19: Total Income | G19: 727.25 | H19: 3466.77 | I19: 6574.6 | J19: 6772.62 | K19: =SUM(K16:K18) -> 15031.787 | L19: =SUM(L16:L18) -> 19670.345 | M19: =SUM(M16:M18) -> 24880.469 | N19: =SUM(N16:N18) -> 30414.932 | O19: =SUM(O16:O18) -> 36816.88 | Q19: =SUM(Q16:Q18) -> 11273.84
C21: Expenses:
C22: Cost Of Materials Consumed | G22: 373.27 | H22: 504.35 | I22: 536.62 | J22: 533.41 | K22: =Assumptions!K39 -> 1645.32 | L22: =Assumptions!L39 -> 2303.448 | M22: =Assumptions!M39 -> 3339.9996 | N22: =Assumptions!N39 -> 4943.1994 | O22: =Assumptions!O39 -> 7167.6391 | Q22: 1233.99
C23: Purchases Of Stock-In-Trade | G23: 0 | H23: 0 | I23: 370.23 | J23: 182.24 | K23: =Assumptions!K45 -> 624.34667 | L23: =Assumptions!L45 -> 780.43333 | M23: =Assumptions!M45 -> 959.933 | N23: =Assumptions!N45 -> 1161.5189 | O23: =Assumptions!O45 -> 1393.8227 | Q23: 468.26
C24: Changes In Inventories Of Finished Goods | G24: -60.4 | H24: 35.78 | I24: -14.89 | J24: 90.41 | K24: =Assumptions!K51 -> -302.57333 | L24: =Assumptions!L51 -> 121.02933 | M24: =Assumptions!M51 -> -181.544 | N24: =Assumptions!N51 -> 72.6176 | O24: =Assumptions!O51 -> -94.40288 | Q24: -226.93
C25: Employee Benefit Expenses | G25: 18.35 | H25: 54.26 | I25: 117.76 | J25: 163.27 | K25: =Assumptions!K57+Assumptions!K84 -> 1304.5814 | L25: =Assumptions!L57+Assumptions!L84 -> 1978.5541 | M25: =Assumptions!M57+Assumptions!M84 -> 2738.0796 | N25: =Assumptions!N57+Assumptions!N84 -> 3658.3231 | O25: =Assumptions!O57+Assumptions!O84 -> 4821.9499 | Q25: 843.15
C26: Finance Costs | G26: 18.14 | H26: 65.04 | I26: 5.68 | J26: 27.22 | K26: =Schedule!K63 -> 258.895 | L26: =Schedule!L63 -> 471.65881 | M26: =Schedule!M63 -> 543.96796 | N26: =Schedule!N63 -> 643.16421 | O26: =Schedule!O63 -> 746.14925 | Q26: 342.8
C27: Depreciation & Amotization Expenses | G27: 17.98 | H27: 23 | I27: 48.99 | J27: 80.8 | K27: =Schedule!K21+Schedule!K30 -> 481.01717 | L27: =Schedule!L21+Schedule!L30 -> 334.39587 | M27: =Schedule!M21+Schedule!M30 -> 380.67118 | N27: =Schedule!N21+Schedule!N30 -> 413.64307 | O27: =Schedule!O21+Schedule!O30 -> 438.12087 | Q27: 382.81
C28: Mining, Royalty And Freight Expenses | G28: 0 | H28: 0 | I28: 3239.77 | J28: 3323.96 | K28: =Assumptions!K63 -> 5380.72 | L28: =Assumptions!L63 -> 6994.936 | M28: =Assumptions!M63 -> 8813.6194 | N28: =Assumptions!N63 -> 10928.888 | O28: =Assumptions!O63 -> 13333.243 | Q28: 4035.54
C29: Other Expenses | G29: 220.74 | H29: 1987.62 | I29: 543.9 | J29: 475.2 | K29: =Assumptions!K69 -> 1523.2667 | L29: =Assumptions!L69 -> 1340.4747 | M29: =Assumptions!M69 -> 1742.6171 | N29: =Assumptions!N69 -> 2056.2881 | O29: =Assumptions!O69 -> 1439.4017 | Q29: 1142.45
C30: Total Expenses | G30: 588.08 | H30: 2670.05 | I30: 4848.06 | J30: 4876.51 | K30: =SUM(K22:K29) -> 10915.574 | L30: =SUM(L22:L29) -> 14324.93 | M30: =SUM(M22:M29) -> 18337.344 | N30: =SUM(N22:N29) -> 23877.642 | O30: =SUM(O22:O29) -> 29245.924 | Q30: =SUM(Q22:Q29) -> 8222.07
C32: Profit / (Loss) Before Execptional Items & Tax | G32: 139.17 | H32: 796.72 | I32: 1726.54 | J32: 1896.11 | K32: =K19-K30 -> 4116.2131 | L32: =L19-L30 -> 5345.4152 | M32: =M19-M30 -> 6543.1253 | N32: =N19-N30 -> 6537.2895 | O32: =O19-O30 -> 7570.9556 | Q32: =Q19-Q30 -> 3051.77
C33: Exceptional Items | G33: 51.36 | H33: 1194.4 | I33: 0 | J33: 0 | K33: =J33 -> 0 | L33: =K33 -> 0 | M33: =L33 -> 0 | N33: =M33 -> 0 | O33: =N33 -> 0 | Q33: -1.95
C34: Profit / (Loss) Before Tax | G34: 87.81 | H34: -397.68 | I34: 1726.54 | J34: 1896.11 | K34: =K32+K33 -> 4116.2131 | L34: =L32+L33 -> 5345.4152 | M34: =M32+M33 -> 6543.1253 | N34: =N32+N33 -> 6537.2895 | O34: =O32+O33 -> 7570.9556 | Q34: =SUM(Q32:Q33) -> 3049.82
C35: Current Tax | G35: 0 | H35: 0 | I35: -259.78 | J35: -456.72 | K35: =-Assumptions!K75 -> -959.81333 | L35: =-Assumptions!L75 -> -1247.7573 | M35: =-Assumptions!M75 -> -1622.0845 | N35: =-Assumptions!N75 -> -2108.7099 | O35: =-Assumptions!O75 -> -2741.3229 | Q35: -719.86
C36: Deferred Tax Income / (Expenses) | G36: 9.51 | H36: 109.14 | I36: -223.82 | J36: 10.53 | K36: 0 | L36: 0 | M36: 0 | N36: 0 | O36: 0 | Q36: -31.42
C37: Profit For The Period | G37: 97.32 | H37: -288.54 | I37: 1242.94 | J37: 1449.92 | K37: =K34+K35+K36 -> 3156.3997 | L37: =L34+L35+L36 -> 4097.6578 | M37: =M34+M35+M36 -> 4921.0408 | N37: =N34+N35+N36 -> 4428.5796 | O37: =O34+O35+O36 -> 4829.6328 | Q37: =SUM(Q34:Q36) -> 2298.54
C39: Earnings Per Share:
C40: Basic | G40: 2.85 | H40: -6.53 | I40: 24.62 | J40: 28.01 | K40: =K$37/K44 -> 60.969668 | L40: =L$37/L44 -> 79.151204 | M40: =M$37/M44 -> 95.055839 | N40: =N$37/N44 -> 85.543358 | O40: =O$37/O44 -> 93.290183
C41: Diluted | G41: 2.78 | H41: -4.74 | I41: 24.43 | J41: 26.12 | K41: =K$37/K45 -> 56.841342 | L41: =L$37/L45 -> 73.791785 | M41: =M$37/M45 -> 88.619499 | N41: =N$37/N45 -> 79.751119 | O41: =O$37/O45 -> 86.973398
C43: Shares Outstanding:
C44: Basic | G44: 34.08 | H44: 44.16 | I44: 50.49 | J44: 51.77 | K44: =J44 -> 51.77 | L44: =K44 -> 51.77 | M44: =L44 -> 51.77 | N44: =M44 -> 51.77 | O44: =N44 -> 51.77
C45: Diluted | G45: 35.56 | H45: 48.95 | I45: 50.88 | J45: 55.53 | K45: =J45 -> 55.53 | L45: =K45 -> 55.53 | M45: =L45 -> 55.53 | N45: =M45 -> 55.53 | O45: =N45 -> 55.53
B48: # | C48: Balance Sheet | G48: 44651 | H48: =EOMONTH(G48,12) -> 45016 | I48: =EOMONTH(H48,12) -> 45382 | J48: =EOMONTH(I48,12) -> 45747 | K48: =EOMONTH(J48,12) -> 46112 | L48: =EOMONTH(K48,12) -> 46477 | M48: =EOMONTH(L48,12) -> 46843 | N48: =EOMONTH(M48,12) -> 47208 | O48: =EOMONTH(N48,12) -> 47573
C50: Assets
C51: Non-Current Assets
C52: Property, Plant & Equipment | G52: 399.06 | H52: 474.6 | I52: 1156.75 | J52: 1531.51 | K52: =Schedule!K16 -> 5717.6577 | L52: =Schedule!L16 -> 6000.4735 | M52: =Schedule!M16 -> 6012.7312 | N52: =Schedule!N16 -> 5703.2095 | O52: =Schedule!O16 -> 5092.4224 | P52: x
C53: Capital Work In Progress | G53: 85.88 | H53: 373.1 | I53: 1268.15 | J53: 4181.07 | K53: =J53 -> 4181.07 | L53: =K53 -> 4181.07 | M53: =L53 -> 4181.07 | N53: =M53 -> 4181.07 | O53: =N53 -> 4181.07
C54: Right To Use Account | G54: 0.6 | H54: 57.77 | I54: 77.95 | J54: 81 | K54: =J54 -> 81 | L54: =K54 -> 81 | M54: =L54 -> 81 | N54: =M54 -> 81 | O54: =N54 -> 81
C55: Financial Assest:
C56: Investment | G56: 0.14 | H56: 0.04 | I56: 0.04 | J56: 0.04 | K56: =J56 -> 0.04 | L56: =K56 -> 0.04 | M56: =L56 -> 0.04 | N56: =M56 -> 0.04 | O56: =N56 -> 0.04
C57: Loans | G57: 0 | H57: 0 | I57: 0 | J57: 32.34 | K57: =J57 -> 32.34 | L57: =K57 -> 32.34 | M57: =L57 -> 32.34 | N57: =M57 -> 32.34 | O57: =N57 -> 32.34
C58: Deferred Tax Assets (Net) | G58: 28.24 | H58: 137.38 | I58: 0.04 | J58: 0.2 | K58: =J58 -> 0.2 | L58: =K58 -> 0.2 | M58: =L58 -> 0.2 | N58: =M58 -> 0.2 | O58: =N58 -> 0.2
C59: Other Non-Current Assets | G59: 0.87 | H59: 36.32 | I59: 307.19 | J59: 570.55 | K59: =Schedule!K28 -> 1712.9658 | L59: =Schedule!L28 -> 2067.032 | M59: =Schedule!M28 -> 2470.0956 | N59: =Schedule!N28 -> 2908.0706 | O59: =Schedule!O28 -> 3371.9633 | P59: x
C60: Total Non-Current Assets | G60: 514.79 | H60: 1079.21 | I60: 2810.12 | J60: 6396.71 | K60: =SUM(K52:K59) -> 11725.273 | L60: =SUM(L52:L59) -> 12362.155 | M60: =SUM(M52:M59) -> 12777.477 | N60: =SUM(N52:N59) -> 12905.93 | O60: =SUM(O52:O59) -> 12759.036
C62: Current Assets
C63: Inventories | G63: 166.84 | H63: 269.75 | I63: 231.09 | J63: 431.76 | K63: =Schedule!K36 -> 958.28855 | L63: =Schedule!L36 -> 1254.0004 | M63: =Schedule!M36 -> 1586.15 | N63: =Schedule!N36 -> 1938.9765 | O63: =Schedule!O36 -> 2347.1058 | P63: x
C64: Financial Assets:
C65: Investments | G65: 0 | H65: 36.79 | I65: 29.03 | J65: 75.06 | K65: =J65 -> 75.06 | L65: =K65 -> 75.06 | M65: =L65 -> 75.06 | N65: =M65 -> 75.06 | O65: =N65 -> 75.06
C66: Trade Receivables | G66: 23.7367 | H66: 24.51 | I66: 79.91 | J66: 171.42 | K66: =Schedule!K37 -> 383.7063 | L66: =Schedule!L37 -> 503.55265 | M66: =Schedule!M37 -> 644.59777 | N66: =Schedule!N37 -> 839.35139 | O66: =Schedule!O37 -> 1028.0582 | P66: x
C67: Cash And Cash Equivalents | G67: 13.73 | H67: 27.58 | I67: 2.59 | J67: 39.95 | K67: =K133 -> 1249.1234 | L67: =L133 -> 5205.2344 | M67: =M133 -> 10050.417 | N67: =N133 -> 15274.534 | O67: =O133 -> 21295.194 | P67: x
C68: Bank Balances Other Than Above | G68: 8.14 | H68: 236.98 | I68: 284.54 | J68: 699.32 | K68: =J68 -> 699.32 | L68: =K68 -> 699.32 | M68: =L68 -> 699.32 | N68: =M68 -> 699.32 | O68: =N68 -> 699.32
C69: Loans & Advances | G69: 0 | H69: 25.07 | I69: 1.5 | J69: 250.83 | K69: =J69 -> 250.83 | L69: =K69 -> 250.83 | M69: =L69 -> 250.83 | N69: =M69 -> 250.83 | O69: =N69 -> 250.83
C70: Other Current Assets | G70: 96.49 | H70: 326.14 | I70: 498.76 | J70: 1351.85 | K70: =Schedule!K45 -> 1887.3188 | L70: =Schedule!L45 -> 2434.6874 | M70: =Schedule!M45 -> 3264.296 | N70: =Schedule!N45 -> 4411.1841 | O70: =Schedule!O45 -> 4837.3914 | P70: x
C71: Total Current Assets | G71: 308.9367 | H71: 946.82 | I71: 1127.42 | J71: 3020.19 | K71: =SUM(K63:K70) -> 5503.6471 | L71: =SUM(L63:L70) -> 10422.685 | M71: =SUM(M63:M70) -> 16570.671 | N71: =SUM(N63:N70) -> 23489.256 | O71: =SUM(O63:O70) -> 30532.959
C72: Total Assets | G72: 823.7267 | H72: 2026.03 | I72: 3937.54 | J72: 9416.9 | K72: =K60+K71 -> 17228.921 | L72: =L60+L71 -> 22784.84 | M72: =M60+M71 -> 29348.148 | N72: =N60+N71 -> 36395.186 | O72: =O60+O71 -> 43291.995
C74: Equity
C75: Equity Share Capital | G75: 37.04 | H75: 50.48 | I75: 50.53 | J75: 52.32 | K75: =J75 -> 52.32 | L75: =K75 -> 52.32 | M75: =L75 -> 52.32 | N75: =M75 -> 52.32 | O75: =N75 -> 52.32
C76: Other Equity | G76: 444.54 | H76: 1478.47 | I76: 2760.34 | J76: 6350.76 | K76: =Schedule!K73 -> 9371.9012 | L76: =Schedule!L73 -> 13295.837 | M76: =Schedule!M73 -> 18023.34 | N76: =Schedule!N73 -> 22374.041 | O76: =Schedule!O73 -> 27162.513 | P76: x
C77: Total Equity | G77: 481.58 | H77: 1528.95 | I77: 2810.87 | J77: 6402.12 | K77: =SUM(K75:K76) -> 9424.2212 | L77: =SUM(L75:L76) -> 13348.157 | M77: =SUM(M75:M76) -> 18075.66 | N77: =SUM(N75:N76) -> 22426.361 | O77: =SUM(O75:O76) -> 27214.833
C79: Non-Current Liabilities
C80: Financial Liabilities:
C81: Borrowings | G81: 56.72 | H81: 0 | I81: 0 | J81: 753.91 | K81: =Schedule!K60 -> 5337.737 | L81: =Schedule!L60 -> 6096.4159 | M81: =Schedule!M60 -> 7252.4911 | N81: =Schedule!N60 -> 8726.7438 | O81: =Schedule!O60 -> 10528.721 | P81: x
C82: Lease Liability | G82: 0.43 | H82: 2.19 | I82: 29.44 | J82: 35.92 | K82: =J82 -> 35.92 | L82: =K82 -> 35.92 | M82: =L82 -> 35.92 | N82: =M82 -> 35.92 | O82: =N82 -> 35.92
C83: Provisions | G83: 5.36 | H83: 22.56 | I83: 24.89 | J83: 35.01 | K83: =J83 -> 35.01 | L83: =K83 -> 35.01 | M83: =L83 -> 35.01 | N83: =M83 -> 35.01 | O83: =N83 -> 35.01
C84: Other Non-Current Liabilities | G84: 161.43 | H84: 0 | I84: 86.4 | J84: 75.72 | K84: =Schedule!K51 -> 165.34965 | L84: =Schedule!L51 -> 216.3738 | M84: =Schedule!M51 -> 273.68516 | N84: =Schedule!N51 -> 334.56425 | O84: =Schedule!O51 -> 404.98568 | P84: x
C85: Total Non-Current Liabilities | G85: 223.94 | H85: 24.75 | I85: 140.73 | J85: 900.56 | K85: =SUM(K81:K84) -> 5574.0167 | L85: =SUM(L81:L84) -> 6383.7197 | M85: =SUM(M81:M84) -> 7597.1063 | N85: =SUM(N81:N84) -> 9132.238 | O85: =SUM(O81:O84) -> 11004.636
C87: Current Liabilities
C88: Financial Liabilities:
C89: Borrowings | G89: 0 | H89: 0 | I89: 0 | J89: 1.84 | K89: 0 | L89: 0 | M89: 0 | N89: 0 | O89: 0
C90: Lease Liability | G90: 0.21 | H90: 0.61 | I90: 3.69 | J90: 3.5 | K90: =J90 -> 3.5 | L90: =K90 -> 3.5 | M90: =L90 -> 3.5 | N90: =M90 -> 3.5 | O90: =N90 -> 3.5
C91: Trade Payables | G91: 15.18 | H91: 74.53 | I91: 395.08 | J91: 36.28 | K91: =Schedule!K39 -> 81.209105 | L91: =Schedule!L39 -> 106.57385 | M91: =Schedule!M39 -> 136.4252 | N91: =Schedule!N39 -> 177.64362 | O91: =Schedule!O39 -> 217.58227 | P91: x
C92: Other Financial Liabilities | G92: 74.47 | H92: 1.57 | I92: 0 | J92: 0 | K92: =J92 -> 0 | L92: =K92 -> 0 | M92: =L92 -> 0 | N92: =M92 -> 0 | O92: =N92 -> 0
C93: Other Current Liabilities | G93: 14.42 | H93: 383.49 | I93: 308.39 | J93: 1334.43 | K93: =Schedule!K48 -> 1406.9236 | L93: =Schedule!L48 -> 2203.8395 | M93: =Schedule!M48 -> 2796.4066 | N93: =Schedule!N48 -> 3916.3935 | O93: =Schedule!O48 -> 4112.3937 | P93: x
C94: Provisions | G94: 13.93 | H94: 12.13 | I94: 18.99 | J94: 21.67 | K94: =J94 -> 21.67 | L94: =K94 -> 21.67 | M94: =L94 -> 21.67 | N94: =M94 -> 21.67 | O94: =N94 -> 21.67
C95: Current Tax Liabilities (Net) | G95: 0 | H95: 0 | I95: 259.79 | J95: 716.5 | K95: =J95 -> 716.5 | L95: =K95 -> 716.5 | M95: =L95 -> 716.5 | N95: =M95 -> 716.5 | O95: =N95 -> 716.5
C96: Total Current Liabilties | G96: 118.21 | H96: 472.33 | I96: 985.94 | J96: 2114.22 | K96: =SUM(K89:K95) -> 2229.8027 | L96: =SUM(L89:L95) -> 3052.0834 | M96: =SUM(M89:M95) -> 3674.5018 | N96: =SUM(N89:N95) -> 4835.7071 | O96: =SUM(O89:O95) -> 5071.646
C97: Total Equity And Liabilities | G97: 823.73 | H97: 2026.03 | I97: 3937.54 | J97: 9416.9 | K97: =K77+K85+K96 -> 17228.041 | L97: =L77+L85+L96 -> 22783.96 | M97: =M77+M85+M96 -> 29347.268 | N97: =N77+N85+N96 -> 36394.306 | O97: =O77+O85+O96 -> 43291.115
C99: B.S Check | G99: =G97=G72 -> FALSE | H99: =H97=H72 -> TRUE | I99: =I97=I72 -> TRUE | J99: =J97=J72 -> TRUE | K99: =ROUNDDOWN(IF(K97=K72,TRUE,K72-K97),0) -> 0 | L99: =ROUNDDOWN(IF(L97=L72,TRUE,L72-L97),0) -> 0 | M99: =ROUNDDOWN(IF(M97=M72,TRUE,M72-M97),0) -> 0 | N99: =ROUNDDOWN(IF(N97=N72,TRUE,N72-N97),0) -> 0 | O99: =ROUNDDOWN(IF(O97=O72,TRUE,O72-O97),0) -> 0
B103: # | C103: Cash Flow Statement | G103: 44651 | H103: =EOMONTH(G103,12) -> 45016 | I103: =EOMONTH(H103,12) -> 45382 | J103: =EOMONTH(I103,12) -> 45747 | K103: =EOMONTH(J103,12) -> 46112 | L103: =EOMONTH(K103,12) -> 46477 | M103: =EOMONTH(L103,12) -> 46843 | N103: =EOMONTH(M103,12) -> 47208 | O103: =EOMONTH(N103,12) -> 47573
C105: Net Income | K105: =K37 -> 3156.3997 | L105: =L37 -> 4097.6578 | M105: =M37 -> 4921.0408 | N105: =N37 -> 4428.5796 | O105: =O37 -> 4829.6328
C106: Add / Less: Non-cash items
C107: Depreciation & Amortisation Exp | K107: =K27 -> 481.01717 | L107: =L27 -> 334.39587 | M107: =M27 -> 380.67118 | N107: =N27 -> 413.64307 | O107: =O27 -> 438.12087
C108: Share-based Compensation | K108: =Assumptions!K84 -> 180.38144 | L108: =Assumptions!L84 -> 236.04414 | M108: =Assumptions!M84 -> 298.56563 | N108: =Assumptions!N84 -> 364.97918 | O108: =Assumptions!O84 -> 441.80256
C109: Finance Costs | K109: =K26 -> 258.895 | L109: =L26 -> 471.65881 | M109: =M26 -> 543.96796 | N109: =N26 -> 643.16421 | O109: =O26 -> 746.14925
C110: Change in Working Capital:
C111: Inventories | K111: =J63-K63 -> -526.52855 | L111: =K63-L63 -> -295.71186 | M111: =L63-M63 -> -332.1496 | N111: =M63-N63 -> -352.82648 | O111: =N63-O63 -> -408.12935
C112: Trade Receivables | K112: =J66-K66 -> -212.2863 | L112: =K66-L66 -> -119.84634 | M112: =L66-M66 -> -141.04512 | N112: =M66-N66 -> -194.75362 | O112: =N66-O66 -> -188.70685
C113: Trade Payables | K113: =K91-J91 -> 44.929105 | L113: =L91-K91 -> 25.36475 | M113: =M91-L91 -> 29.851342 | N113: =N91-M91 -> 41.21842 | O113: =O91-N91 -> 39.938657
C114: Other Current Assets | K114: =J70-K70 -> -535.46884 | L114: =K70-L70 -> -547.3686 | M114: =L70-M70 -> -829.60852 | N114: =M70-N70 -> -1146.8882 | O114: =N70-O70 -> -426.20724
C115: Other Current Liabilities | K115: =K93-J93 -> 72.493624 | L115: =L93-K93 -> 796.91587 | M115: =M93-L93 -> 592.56708 | N115: =N93-M93 -> 1119.9869 | O115: =O93-N93 -> 196.0002
C116: Other Non-Current Liabilities | K116: =K84-J84 -> 89.629653 | L116: =L84-K84 -> 51.024145 | M116: =M84-L84 -> 57.311362 | N116: =N84-M84 -> 60.879091 | O116: =O84-N84 -> 70.421425
C117: Cash from Operating Activities | K117: =SUM(K105:K116) -> 3009.462 | L117: =SUM(L105:L116) -> 5050.1346 | M117: =SUM(M105:M116) -> 5521.1721 | N117: =SUM(N105:N116) -> 5377.9822 | O117: =SUM(O105:O116) -> 5739.0223
C119: Purchase of Property, Plant & Equipment | K119: =-Schedule!K12 -> -4810.1717 | L119: =-Schedule!L12 -> -1573.6276 | M119: =-Schedule!M12 -> -1791.3938 | N119: =-Schedule!N12 -> -1946.5556 | O119: =-Schedule!O12 -> -2061.7453
C120: Disposal of Property, Plant & Equipment | K120: =-Schedule!K13 -> 203.134 | L120: =-Schedule!L13 -> 995.75666 | M120: =-Schedule!M13 -> 1443.2497 | N120: =-Schedule!N13 -> 1891.0982 | O120: =-Schedule!O13 -> 2285.9551
C121: Additions/ (Disposal) of NCA | K121: =-Schedule!K26 -> -1202.5429 | L121: =-Schedule!L26 -> -393.40691 | M121: =-Schedule!M26 -> -447.84844 | N121: =-Schedule!N26 -> -486.63891 | O121: =-Schedule!O26 -> -515.43632
C122: Cash from Investing Activities | K122: =SUM(K119:K121) -> -5809.5807 | L122: =SUM(L119:L121) -> -971.27787 | M122: =SUM(M119:M121) -> -795.99248 | N122: =SUM(N119:N121) -> -542.09637 | O122: =SUM(O119:O121) -> -291.22652
...

Sheet Assumptions
C2: =Dashboard!C2 -> Lloyds Metal & Energy Ltd.
C3: Assumptions
C4: =Dashboard!C4 -> (₹ in 'Cr, except share price and shares outstanding)
C5: Actuals / Projections | G5: Acutals | K5: Projections
C6: Date / Year | G6: 44651 | H6: =EOMONTH(G6,12) -> 45016 | I6: =EOMONTH(H6,12) -> 45382 | J6: =EOMONTH(I6,12) -> 45747 | K6: =EOMONTH(J6,12) -> 46112 | L6: =EOMONTH(K6,12) -> 46477 | M6: =EOMONTH(L6,12) -> 46843 | N6: =EOMONTH(M6,12) -> 47208 | O6: =EOMONTH(N6,12) -> 47573
C8: <-Back to Dashboard
C10: Trigger
C12: Scenario | E12: =Dashboard!E14 -> 1
B15: # | C15: Assumptions | G15: 44651 | H15: =EOMONTH(G15,12) -> 45016 | I15: =EOMONTH(H15,12) -> 45382 | J15: =EOMONTH(I15,12) -> 45747 | K15: =EOMONTH(J15,12) -> 46112 | L15: =EOMONTH(K15,12) -> 46477 | M15: =EOMONTH(L15,12) -> 46843 | N15: =EOMONTH(M15,12) -> 47208 | O15: =EOMONTH(N15,12) -> 47573
C17: Revenue:
C18: Revenue from operations | G18: =Financials!G16 -> 697.5 | H18: =Financials!H16 -> 3392.31 | I18: =Financials!I16 -> 6481.01 | J18: =Financials!J16 -> 6626.31 | K18: =Financials!Q16*(4/3) -> 14436.08 | L18: =K18*(1+L19) -> 18766.904 | M18: =L18*(1+M19) -> 23458.63 | N18: =M18*(1+N19) -> 28150.356 | O18: =N18*(1+O19) -> 33217.42
C19: Growth % | H19: =H18/G18-1 -> 3.8635269 | I19: =I18/H18-1 -> 0.91050051 | J19: =J18/I18-1 -> 0.022419345 | K19: =K18/J18-1 -> 1.1786002 | L19: =OFFSET(L19,$E$12,0) -> 0.3 | M19: =OFFSET(M19,$E$12,0) -> 0.25 | N19: =OFFSET(N19,$E$12,0) -> 0.2 | O19: =OFFSET(O19,$E$12,0) -> 0.18
C20: 1. Base | L20: 0.3 | M20: 0.25 | N20: 0.2 | O20: 0.18
C21: 2. Conservative | L21: =L20-1% -> 0.29 | M21: =M20-1% -> 0.24 | N21: =N20-1% -> 0.19 | O21: =O20-1% -> 0.17
C22: 3. Optimistic | L22: =L20+1.5% -> 0.315 | M22: =M20+1.5% -> 0.265 | N22: =N20+1.5% -> 0.215 | O22: =O20+1.5% -> 0.195
C24: Gross Opearting Revenues | G24: =Financials!G17 -> 0 | H24: =Financials!H17 -> 0 | I24: =Financials!I17 -> 43.64 | J24: =Financials!J17 -> 95.09 | K24: =Financials!Q17*(4/3) -> 354.52 | L24: =K24*(1+L25) -> 638.136 | M24: =L24*(1+M25) -> 1116.738 | N24: =M24*(1+N25) -> 1898.4546 | O24: =N24*(1+O25) -> 3189.4037
C25: Growth % | H25: =H24/G24-1 -> #DIV/0! | I25: =I24/H24-1 -> #DIV/0! | J25: =J24/I24-1 -> 1.1789643 | K25: =K24/J24-1 -> 2.7282574 | L25: =OFFSET(L25,$E$12,0) -> 0.8 | M25: =OFFSET(M25,$E$12,0) -> 0.75 | N25: =OFFSET(N25,$E$12,0) -> 0.7 | O25: =OFFSET(O25,$E$12,0) -> 0.68
C26: 1. Base | L26: 0.8 | M26: 0.75 | N26: 0.7 | O26: 0.68
C27: 2. Conservative | L27: =L26-1% -> 0.79 | M27: =M26-1% -> 0.74 | N27: =N26-1% -> 0.69 | O27: =O26-1% -> 0.67
C28: 3. Optimistic | L28: =L26+1.5% -> 0.815 | M28: =M26+1.5% -> 0.765 | N28: =N26+1.5% -> 0.715 | O28: =O26+1.5% -> 0.695
C30: Other Income | G30: =Financials!G18 -> 29.75 | H30: =Financials!H18 -> 74.46 | I30: =Financials!I18 -> 49.95 | J30: =Financials!J18 -> 51.22 | K30: =Financials!Q18*(4/3) -> 241.18667 | L30: =K30*(1+L31) -> 265.30533 | M30: =L30*(1+M31) -> 305.10113 | N30: =M30*(1+N31) -> 366.12136 | O30: =N30*(1+O31) -> 410.05592
C31: Growth % | H31: =H30/G30-1 -> 1.5028571 | I31: =I30/H30-1 -> -0.32917002 | J31: =J30/I30-1 -> 0.025425425 | K31: =K30/J30-1 -> 3.7088377 | L31: =OFFSET(L31,$E$12,0) -> 0.1 | M31: =OFFSET(M31,$E$12,0) -> 0.15 | N31: =OFFSET(N31,$E$12,0) -> 0.2 | O31: =OFFSET(O31,$E$12,0) -> 0.12
C32: 1. Base | L32: 0.1 | M32: 0.15 | N32: 0.2 | O32: 0.12
C33: 2. Conservative | L33: =L32-1% -> 0.09 | M33: =M32-1% -> 0.14 | N33: =N32-1% -> 0.19 | O33: =O32-1% -> 0.11
C34: 3. Optimistic | L34: =L32+1.5% -> 0.115 | M34: =M32+1.5% -> 0.165 | N34: =N32+1.5% -> 0.215 | O34: =O32+1.5% -> 0.135
C36: Total Income | G36: =G18+G24+G30 -> 727.25 | H36: =H18+H24+H30 -> 3466.77 | I36: =I18+I24+I30 -> 6574.6 | J36: =J18+J24+J30 -> 6772.62 | K36: =K18+K24+K30 -> 15031.787 | L36: =L18+L24+L30 -> 19670.345 | M36: =M18+M24+M30 -> 24880.469 | N36: =N18+N24+N30 -> 30414.932 | O36: =O18+O24+O30 -> 36816.88
C38: Expenses:
C39: Cost Of Materials Consumed | G39: =Financials!G22 -> 373.27 | H39: =Financials!H22 -> 504.35 | I39: =Financials!I22 -> 536.62 | J39: =Financials!J22 -> 533.41 | K39: =Financials!Q22*(4/3) -> 1645.32 | L39: =K39*(1+L40) -> 2303.448 | M39: =L39*(1+M40) -> 3339.9996 | N39: =M39*(1+N40) -> 4943.1994 | O39: =N39*(1+O40) -> 7167.6391
C40: Growth % | H40: =H39/G39-1 -> 0.35116672 | I40: =I39/H39-1 -> 0.063983345 | J40: =J39/I39-1 -> -0.0059818866 | K40: =K39/J39-1 -> 2.0845316 | L40: =OFFSET(L40,$E$12,0) -> 0.4 | M40: =OFFSET(M40,$E$12,0) -> 0.45 | N40: =OFFSET(N40,$E$12,0) -> 0.48 | O40: =OFFSET(O40,$E$12,0) -> 0.45
C41: 1. Base | L41: 0.4 | M41: 0.45 | N41: 0.48 | O41: 0.45
C42: 2. Conservative | L42: =L41+1% -> 0.41 | M42: =M41+1% -> 0.46 | N42: =N41+1% -> 0.49 | O42: =O41+1% -> 0.46
C43: 3. Optimistic | L43: =L41-1.5% -> 0.385 | M43: =M41-1.5% -> 0.435 | N43: =N41-1.5% -> 0.465 | O43: =O41-1.5% -> 0.435
Q44: z
C45: Purchases Of Stock-In-Trade | G45: =Financials!G23 -> 0 | H45: =Financials!H23 -> 0 | I45: =Financials!I23 -> 370.23 | J45: =Financials!J23 -> 182.24 | K45: =Financials!Q23*(4/3) -> 624.34667 | L45: =K45*(1+L46) -> 780.43333 | M45: =L45*(1+M46) -> 959.933 | N45: =M45*(1+N46) -> 1161.5189 | O45: =N45*(1+O46) -> 1393.8227
C46: Growth % | H46: =H45/G45-1 -> #DIV/0! | I46: =I45/H45-1 -> #DIV/0! | J46: =J45/I45-1 -> -0.50776544 | K46: =K45/J45-1 -> 2.4259584 | L46: =OFFSET(L46,$E$12,0) -> 0.25 | M46: =OFFSET(M46,$E$12,0) -> 0.23 | N46: =OFFSET(N46,$E$12,0) -> 0.21 | O46: =OFFSET(O46,$E$12,0) -> 0.2
C47: 1. Base | L47: 0.25 | M47: 0.23 | N47: 0.21 | O47: 0.2
C48: 2. Conservative | L48: =L47+1% -> 0.26 | M48: =M47+1% -> 0.24 | N48: =N47+1% -> 0.22 | O48: =O47+1% -> 0.21
C49: 3. Optimistic | L49: =L47-1.5% -> 0.235 | M49: =M47-1.5% -> 0.215 | N49: =N47-1.5% -> 0.195 | O49: =O47-1.5% -> 0.185
C51: Changes In Inventories Of Finished Goods | G51: =Financials!G24 -> -60.4 | H51: =Financials!H24 -> 35.78 | I51: =Financials!I24 -> -14.89 | J51: =Financials!J24 -> 90.41 | K51: =Financials!Q24*(4/3) -> -302.57333 | L51: =K51*(1+L52) -> 121.02933 | M51: =L51*(1+M52) -> -181.544 | N51: =M51*(1+N52) -> 72.6176 | O51: =N51*(1+O52) -> -94.40288
C52: Growth % | H52: =H51/G51-1 -> -1.5923841 | I52: =I51/H51-1 -> -1.4161543 | J52: =J51/I51-1 -> -7.0718603 | K52: =K51/J51-1 -> -4.3466799 | L52: =OFFSET(L52,$E$12,0) -> -1.4 | M52: =OFFSET(M52,$E$12,0) -> -2.5 | N52: =OFFSET(N52,$E$12,0) -> -1.4 | O52: =OFFSET(O52,$E$12,0) -> -2.3
C53: 1. Base | L53: -1.4 | M53: -2.5 | N53: -1.4 | O53: -2.3
C54: 2. Conservative | L54: =L53+1% -> -1.39 | M54: =M53+1% -> -2.49 | N54: =N53+1% -> -1.39 | O54: =O53+1% -> -2.29
C55: 3. Optimistic | L55: =L53-1.5% -> -1.415 | M55: =M53-1.5% -> -2.515 | N55: =N53-1.5% -> -1.415 | O55: =O53-1.5% -> -2.315
C57: Employee Benefit Expenses | G57: =Financials!G25 -> 18.35 | H57: =Financials!H25 -> 54.26 | I57: =Financials!I25 -> 117.76 | J57: =Financials!J25 -> 163.27 | K57: =Financials!Q25*(4/3) -> 1124.2 | L57: =K57*(1+L58) -> 1742.51 | M57: =L57*(1+M58) -> 2439.514 | N57: =M57*(1+N58) -> 3293.3439 | O57: =N57*(1+O58) -> 4380.1474
C58: Growth % | H58: =H57/G57-1 -> 1.9569482 | I58: =I57/H57-1 -> 1.1702912 | J58: =J57/I57-1 -> 0.38646399 | K58: =K57/J57-1 -> 5.885527 | L58: =OFFSET(L58,$E$12,0) -> 0.55 | M58: =OFFSET(M58,$E$12,0) -> 0.4 | N58: =OFFSET(N58,$E$12,0) -> 0.35 | O58: =OFFSET(O58,$E$12,0) -> 0.33
C59: 1. Base | L59: 0.55 | M59: 0.4 | N59: 0.35 | O59: 0.33
C60: 2. Conservative | L60: =L59+1% -> 0.56 | M60: =M59+1% -> 0.41 | N60: =N59+1% -> 0.36 | O60: =O59+1% -> 0.34
C61: 3. Optimistic | L61: =L59-1.5% -> 0.535 | M61: =M59-1.5% -> 0.385 | N61: =N59-1.5% -> 0.335 | O61: =O59-1.5% -> 0.315
C63: Mining, Royalty And Freight Expenses | G63: =Financials!G28 -> 0 | H63: =Financials!H28 -> 0 | I63: =Financials!I28 -> 3239.77 | J63: =Financials!J28 -> 3323.96 | K63: =Financials!Q28*(4/3) -> 5380.72 | L63: =K63*(1+L64) -> 6994.936 | M63: =L63*(1+M64) -> 8813.6194 | N63: =M63*(1+N64) -> 10928.888 | O63: =N63*(1+O64) -> 13333.243
C64: Growth % | H64: =H63/G63-1 -> #DIV/0! | I64: =I63/H63-1 -> #DIV/0! | J64: =J63/I63-1 -> 0.025986413 | K64: =K63/J63-1 -> 0.61876798 | L64: =OFFSET(L64,$E$12,0) -> 0.3 | M64: =OFFSET(M64,$E$12,0) -> 0.26 | N64: =OFFSET(N64,$E$12,0) -> 0.24 | O64: =OFFSET(O64,$E$12,0) -> 0.22
C65: 1. Base | L65: 0.3 | M65: 0.26 | N65: 0.24 | O65: 0.22
C66: 2. Conservative | L66: =L65+1% -> 0.31 | M66: =M65+1% -> 0.27 | N66: =N65+1% -> 0.25 | O66: =O65+1% -> 0.23
C67: 3. Optimistic | L67: =L65-1.5% -> 0.285 | M67: =M65-1.5% -> 0.245 | N67: =N65-1.5% -> 0.225 | O67: =O65-1.5% -> 0.205
C69: Other Expenses | G69: =Financials!G29 -> 220.74 | H69: =Financials!H29 -> 1987.62 | I69: =Financials!I29 -> 543.9 | J69: =Financials!J29 -> 475.2 | K69: =Financials!Q29*(4/3) -> 1523.2667 | L69: =K69*(1+L70) -> 1340.4747 | M69: =L69*(1+M70) -> 1742.6171 | N69: =M69*(1+N70) -> 2056.2881 | O69: =N69*(1+O70) -> 1439.4017
C70: Growth % | H70: =H69/G69-1 -> 8.004349 | I70: =I69/H69-1 -> -0.72635614 | J70: =J69/I69-1 -> -0.12630998 | K70: =K69/J69-1 -> 2.2055275 | L70: =OFFSET(L70,$E$12,0) -> -0.12 | M70: =OFFSET(M70,$E$12,0) -> 0.3 | N70: =OFFSET(N70,$E$12,0) -> 0.18 | O70: =OFFSET(O70,$E$12,0) -> -0.3
C71: 1. Base | L71: -0.12 | M71: 0.3 | N71: 0.18 | O71: -0.3
C72: 2. Conservative | L72: =L71+1% -> -0.11 | M72: =M71+1% -> 0.31 | N72: =N71+1% -> 0.19 | O72: =O71+1% -> -0.29
C73: 3. Optimistic | L73: =L71-1.5% -> -0.135 | M73: =M71-1.5% -> 0.285 | N73: =N71-1.5% -> 0.165 | O73: =O71-1.5% -> -0.315
C75: Taxes | G75: =-Financials!G35 -> 0 | H75: =-Financials!H35 -> 0 | I75: =-Financials!I35 -> 259.78 | J75: =-Financials!J35 -> 456.72 | K75: =-Financials!Q35*(4/3) -> 959.81333 | L75: =K75*(1+L76) -> 1247.7573 | M75: =L75*(1+M76) -> 1622.0845 | N75: =M75*(1+N76) -> 2108.7099 | O75: =N75*(1+O76) -> 2741.3229
C76: Tax Rate | H76: =H75/G75-1 -> #DIV/0! | I76: =I75/H75-1 -> #DIV/0! | J76: =J75/I75-1 -> 0.75810301 | K76: =K75/J75-1 -> 1.1015356 | L76: =OFFSET(L76,$E$12,0) -> 0.3 | M76: =OFFSET(M76,$E$12,0) -> 0.3 | N76: =OFFSET(N76,$E$12,0) -> 0.3 | O76: =OFFSET(O76,$E$12,0) -> 0.3
C77: 1. Base | L77: 0.3 | M77: 0.3 | N77: 0.3 | O77: 0.3
C78: 2. Conservative | L78: =L77+1% -> 0.31 | M78: =M77+1% -> 0.31 | N78: =N77+1% -> 0.31 | O78: =O77+1% -> 0.31
C79: 3. Optimistic | L79: =L77-1.5% -> 0.285 | M79: =M77-1.5% -> 0.285 | N79: =N77-1.5% -> 0.285 | O79: =O77-1.5% -> 0.285
C81: Annual Dividends Paid | G81: 0 | H81: 22.24 | I81: 0 | J81: 52.28 | K81: =K82*Financials!K37 -> 315.63997 | L81: =L82*Financials!L37 -> 409.76578 | M81: =M82*Financials!M37 -> 492.10408 | N81: =N82*Financials!N37 -> 442.85796 | O81: =O82*Financials!O37 -> 482.96328
C82: Dividends as a % of Net Income | G82: =G81/Financials!G37 -> 0 | H82: =-H81/Financials!H37 -> 0.077077702 | I82: =I81/Financials!I37 -> 0 | J82: =J81/Financials!J37 -> 0.036057162 | K82: 0.1 | L82: 0.1 | M82: 0.1 | N82: 0.1 | O82: 0.1
C84: Share-Based Compensation (ESOPs) | G84: 0 | H84: 0 | I84: 48.99 | J84: 80.8 | K84: =K85*Financials!K19 -> 180.38144 | L84: =L85*Financials!L19 -> 236.04414 | M84: =M85*Financials!M19 -> 298.56563 | N84: =N85*Financials!N19 -> 364.97918 | O84: =O85*Financials!O19 -> 441.80256
C85: ESOPs as a % of Revenue | G85: =G84/Financials!G19 -> 0 | H85: =H84/Financials!H19 -> 0 | I85: =I84/Financials!I19 -> 0.0074514039 | J85: =J84/Financials!J19 -> 0.01193039 | K85: 0.012 | L85: 0.012 | M85: 0.012 | N85: 0.012 | O85: 0.012
B88: # | C88: End

Sheet Schedule
C2: =Dashboard!C2 -> Lloyds Metal & Energy Ltd.
C3: Schedules
C4: =Dashboard!C4 -> (₹ in 'Cr, except share price and shares outstanding)
C6: <-Back to Dashboard
B8: # | C8: Property, Plant & Equipment | G8: 44651 | H8: =EOMONTH(G8,12) -> 45016 | I8: =EOMONTH(H8,12) -> 45382 | J8: =EOMONTH(I8,12) -> 45747 | K8: =EOMONTH(J8,12) -> 46112 | L8: =EOMONTH(K8,12) -> 46477 | M8: =EOMONTH(L8,12) -> 46843 | N8: =EOMONTH(M8,12) -> 47208 | O8: =EOMONTH(N8,12) -> 47573
C10: Property, Plant & Equipment
C11: Opening balance of Gross PP&E | K11: 2031.34 | L11: =K14 -> 6638.3777 | M11: =L14 -> 7216.2487 | N11: =M14 -> 7564.3927 | O11: =N14 -> 7619.8502
C12: Additons to PP&E | K12: =K18*80% -> 4810.1717 | L12: =L18*80% -> 1573.6276 | M12: =M18*80% -> 1791.3938 | N12: =N18*80% -> 1946.5556 | O12: =O18*80% -> 2061.7453
C13: Sale of PP&E | K13: =-K11*10% -> -203.134 | L13: =-L11*15% -> -995.75666 | M13: =-M11*20% -> -1443.2497 | N13: =-N11*25% -> -1891.0982 | O13: =-O11*30% -> -2285.9551
C14: Closing balance of Gross PP&E | K14: =SUM(K11:K13) -> 6638.3777 | L14: =SUM(L11:L13) -> 7216.2487 | M14: =SUM(M11:M13) -> 7564.3927 | N14: =SUM(N11:N13) -> 7619.8502 | O14: =SUM(O11:O13) -> 7395.6404
C15: Accumulated Depreciation | J15: -499.83 | K15: =J15-K21 -> -920.72003 | L15: =K15-L21 -> -1215.7752 | M15: =L15-M21 -> -1551.6615 | N15: =M15-N21 -> -1916.6407 | O15: =N15-O21 -> -2303.218
C16: Closing balance of Net PP&E | K16: =SUM(K14:K15) -> 5717.6577 | L16: =SUM(L14:L15) -> 6000.4735 | M16: =SUM(M14:M15) -> 6012.7312 | N16: =SUM(N14:N15) -> 5703.2095 | O16: =SUM(O14:O15) -> 5092.4224
C18: CapEx | G18: 56.24 | H18: 99.63 | I18: 724.01 | J18: 782.66 | K18: =K19*Financials!K19 -> 6012.7147 | L18: =L19*Financials!L19 -> 1967.0345 | M18: =M19*Financials!M19 -> 2239.2422 | N18: =N19*Financials!N19 -> 2433.1946 | O18: =O19*Financials!O19 -> 2577.1816
C19: % of Revenue | G19: =G18/Financials!G19 -> 0.077332417 | H19: =H18/Financials!H19 -> 0.028738566 | I19: =I18/Financials!I19 -> 0.11012229 | J19: =J18/Financials!J19 -> 0.11556237 | K19: 0.4 | L19: 0.1 | M19: 0.09 | N19: 0.08 | O19: 0.07
C21: Depreciation on PP&E | G21: 17.8 | H21: 21.95 | I21: 44.25 | J21: 75.48 | K21: =K22*K18 -> 420.89003 | L21: =L22*L18 -> 295.05518 | M21: =M22*M18 -> 335.88633 | N21: =N22*N18 -> 364.97918 | O21: =O22*O18 -> 386.57724
C22: % of CapEx | G22: =G21/G18 -> 0.31650071 | H22: =H21/H18 -> 0.22031517 | I22: =I21/I18 -> 0.06111794 | J22: =J21/J18 -> 0.096440344 | K22: 0.07 | L22: 0.15 | M22: 0.15 | N22: 0.15 | O22: 0.15
C24: Non-Current Assets
C25: Opening balance of Net NCA | K25: =J28 -> 570.55 | L25: =K28 -> 1712.9658 | M25: =L28 -> 2067.032 | N25: =M28 -> 2470.0956 | O25: =N28 -> 2908.0706
C26: Additions to NCA | K26: =K18*20% -> 1202.5429 | L26: =L18*20% -> 393.40691 | M26: =M18*20% -> 447.84844 | N26: =N18*20% -> 486.63891 | O26: =O18*20% -> 515.43632
C27: Depreciation on NCA | K27: =-K30 -> -60.127147 | L27: =-L30 -> -39.340691 | M27: =-M30 -> -44.784844 | N27: =-N30 -> -48.663891 | O27: =-O30 -> -51.543632
C28: Closing balance of Net NCA | G28: =Financials!G59 -> 0.87 | H28: =Financials!H59 -> 36.32 | I28: =Financials!I59 -> 307.19 | J28: =Financials!J59 -> 570.55 | K28: =K25+K26+K27 -> 1712.9658 | L28: =L25+L26+L27 -> 2067.032 | M28: =M25+M26+M27 -> 2470.0956 | N28: =N25+N26+N27 -> 2908.0706 | O28: =O25+O26+O27 -> 3371.9633
C30: Depreciation related to NCA | K30: =K31*K18 -> 60.127147 | L30: =L31*L18 -> 39.340691 | M30: =M31*M18 -> 44.784844 | N30: =N31*N18 -> 48.663891 | O30: =O31*O18 -> 51.543632
C31: % of CapEx | K31: 0.01 | L31: 0.02 | M31: 0.02 | N31: 0.02 | O31: 0.02
B34: # | C34: Working Capital Schedule | G34: 44651 | H34: =EOMONTH(G34,12) -> 45016 | I34: =EOMONTH(H34,12) -> 45382 | J34: =EOMONTH(I34,12) -> 45747 | K34: =EOMONTH(J34,12) -> 46112 | L34: =EOMONTH(K34,12) -> 46477 | M34: =EOMONTH(L34,12) -> 46843 | N34: =EOMONTH(M34,12) -> 47208 | O34: =EOMONTH(N34,12) -> 47573
C36: Inventories | G36: =Financials!G63 -> 166.84 | H36: =Financials!H63 -> 269.75 | I36: =Financials!I63 -> 231.09 | J36: =Financials!J63 -> 431.76 | K36: =K41*Financials!K19/days -> 958.28855 | L36: =L41*Financials!L19/days -> 1254.0004 | M36: =M41*Financials!M19/days -> 1586.15 | N36: =N41*Financials!N19/days -> 1938.9765 | O36: =O41*Financials!O19/days -> 2347.1058
C37: Trade Receivables | G37: =Financials!G66 -> 23.7367 | H37: =Financials!H66 -> 24.51 | I37: =Financials!I66 -> 79.91 | J37: =Financials!J66 -> 171.42 | K37: =K42*Financials!K30/days -> 383.7063 | L37: =L42*Financials!L30/days -> 503.55265 | M37: =M42*Financials!M30/days -> 644.59777 | N37: =N42*Financials!N30/days -> 839.35139 | O37: =O42*Financials!O30/days -> 1028.0582
C39: Trade Payables | G39: =Financials!G91 -> 15.18 | H39: =Financials!H91 -> 74.53 | I39: =Financials!I91 -> 395.08 | J39: =Financials!J91 -> 36.28 | K39: =K43*Financials!K30/days -> 81.209105 | L39: =L43*Financials!L30/days -> 106.57385 | M39: =M43*Financials!M30/days -> 136.4252 | N39: =N43*Financials!N30/days -> 177.64362 | O39: =O43*Financials!O30/days -> 217.58227
C41: Inventories | G41: =G36*days/Financials!G19 -> 83.735442 | H41: =H36*days/Financials!H19 -> 28.400716 | I41: =I36*days/Financials!I19 -> 12.829351 | J41: =J36*days/Financials!J19 -> 23.269045 | K41: =J41 -> 23.269045 | L41: =K41 -> 23.269045 | M41: =L41 -> 23.269045 | N41: =M41 -> 23.269045 | O41: =N41 -> 23.269045
C42: Trade Receivables | G42: =G37*days/Financials!G$30 -> 14.732512 | H42: =H37*days/Financials!H$30 -> 3.3505552 | I42: =I37*days/Financials!I$30 -> 6.0162519 | J42: =J37*days/Financials!J$30 -> 12.830549 | K42: =J42 -> 12.830549 | L42: =K42 -> 12.830549 | M42: =L42 -> 12.830549 | N42: =M42 -> 12.830549 | O42: =N42 -> 12.830549
C43: Trade Payables | G43: =G39*days/Financials!G$30 -> 9.4216773 | H43: =H39*days/Financials!H$30 -> 10.188367 | I43: =I39*days/Financials!I$30 -> 29.744723 | J43: =J39*days/Financials!J$30 -> 2.7155076 | K43: =J43 -> 2.7155076 | L43: =K43 -> 2.7155076 | M43: =L43 -> 2.7155076 | N43: =M43 -> 2.7155076 | O43: =N43 -> 2.7155076
C45: Other Current Assets | G45: =Financials!G70 -> 96.49 | H45: =Financials!H70 -> 326.14 | I45: =Financials!I70 -> 498.76 | J45: =Financials!J70 -> 1351.85 | K45: =K46*Financials!K$19 -> 1887.3188 | L45: =L46*Financials!L$19 -> 2434.6874 | M45: =M46*Financials!M$19 -> 3264.296 | N45: =N46*Financials!N$19 -> 4411.1841 | O45: =O46*Financials!O$19 -> 4837.3914
C46: % of Revenue | G46: =G45/Financials!G$19 -> 0.1326779 | H46: =H45/Financials!H$19 -> 0.094076042 | I46: =I45/Financials!I$19 -> 0.075861649 | J46: =J45/Financials!J$19 -> 0.19960517 | K46: =AVERAGE(G46:J46) -> 0.12555519 | L46: =AVERAGE(H46:K46) -> 0.12377451 | M46: =AVERAGE(I46:L46) -> 0.13119913 | N46: =AVERAGE(J46:M46) -> 0.1450335 | O46: =AVERAGE(K46:N46) -> 0.13139059
C48: Other Current Liabilities | G48: =Financials!G93 -> 14.42 | H48: =Financials!H93 -> 383.49 | I48: =Financials!I93 -> 308.39 | J48: =Financials!J93 -> 1334.43 | K48: =K49*Financials!K$19 -> 1406.9236 | L48: =L49*Financials!L$19 -> 2203.8395 | M48: =M49*Financials!M$19 -> 2796.4066 | N48: =N49*Financials!N$19 -> 3916.3935 | O48: =O49*Financials!O$19 -> 4112.3937
C49: % of Revenue | G49: =G48/Financials!G$19 -> 0.01982812 | H49: =H48/Financials!H$19 -> 0.11061882 | I49: =I48/Financials!I$19 -> 0.046906276 | J49: =J48/Financials!J$19 -> 0.19703305 | K49: =AVERAGE(G49:J49) -> 0.093596567 | L49: =AVERAGE(H49:K49) -> 0.11203868 | M49: =AVERAGE(I49:L49) -> 0.11239364 | N49: =AVERAGE(J49:M49) -> 0.12876549 | O49: =AVERAGE(K49:N49) -> 0.11169859
C51: Other Non-Current Liabilities | G51: =Financials!G84 -> 161.43 | H51: =Financials!H84 -> 0 | I51: =Financials!I84 -> 86.4 | J51: =Financials!J84 -> 75.72 | K51: =K52*Financials!K$19 -> 165.34965 | L51: =L52*Financials!L$19 -> 216.3738 | M51: =M52*Financials!M$19 -> 273.68516 | N51: =N52*Financials!N$19 -> 334.56425 | O51: =O52*Financials!O$19 -> 404.98568
C52: % of Revenue | G52: =G51/Financials!G$19 -> 0.22197319 | H52: =H51/Financials!H$19 -> 0 | I52: =I51/Financials!I$19 -> 0.013141484 | J52: =J51/Financials!J$19 -> 0.011180311 | K52: 0.011 | L52: 0.011 | M52: 0.011 | N52: 0.011 | O52: 0.011
B55: # | C55: Debt Schedule | G55: 44651 | H55: =EOMONTH(G55,12) -> 45016 | I55: =EOMONTH(H55,12) -> 45382 | J55: =EOMONTH(I55,12) -> 45747 | K55: =EOMONTH(J55,12) -> 46112 | L55: =EOMONTH(K55,12) -> 46477 | M55: =EOMONTH(L55,12) -> 46843 | N55: =EOMONTH(M55,12) -> 47208 | O55: =EOMONTH(N55,12) -> 47573
C57: Opening balance of LT borrowings | K57: =Financials!J81 -> 753.91 | L57: =K60 -> 5337.737 | M57: =L60 -> 6096.4159 | N57: =M60 -> 7252.4911 | O57: =N60 -> 8726.7438
C58: Issuance of New Debt | K58: 4810 | L58: 2360 | M58: 2985 | N58: 3650 | O58: 4420 | P58: (80% of Capex issued)
C59: Repayment of Debt | K59: =-K57*30% -> -226.173 | L59: =-L57*30% -> -1601.3211 | M59: =-M57*30% -> -1828.9248 | N59: =-N57*30% -> -2175.7473 | O59: =-O57*30% -> -2618.0231
C60: Closing balance of LT borrowings | K60: =SUM(K57:K59) -> 5337.737 | L60: =SUM(L57:L59) -> 6096.4159 | M60: =SUM(M57:M59) -> 7252.4911 | N60: =SUM(N57:N59) -> 8726.7438 | O60: =SUM(O57:O59) -> 10528.721
C62: Interest Rate (%) | K62: 0.085 | L62: 0.0825 | M62: 0.0815 | N62: 0.0805 | O62: 0.0775
C63: Finance Costs | K63: =AVERAGE(K57,K60)*K62 -> 258.895 | L63: =AVERAGE(L57,L60)*L62 -> 471.65881 | M63: =AVERAGE(M57,M60)*M62 -> 543.96796 | N63: =AVERAGE(N57,N60)*N62 -> 643.16421 | O63: =AVERAGE(O57,O60)*O62 -> 746.14925
B67: # | C67: Retained Earnings Schedule | G67: 44651 | H67: =EOMONTH(G67,12) -> 45016 | I67: =EOMONTH(H67,12) -> 45382 | J67: =EOMONTH(I67,12) -> 45747 | K67: =EOMONTH(J67,12) -> 46112 | L67: =EOMONTH(K67,12) -> 46477 | M67: =EOMONTH(L67,12) -> 46843 | N67: =EOMONTH(M67,12) -> 47208 | O67: =EOMONTH(N67,12) -> 47573
C69: Opening balance of RE | K69: =Financials!J76 -> 6350.76 | L69: =K73 -> 9371.9012 | M69: =L73 -> 13295.837 | N69: =M73 -> 18023.34 | O69: =N73 -> 22374.041
C70: Add: Net Income | K70: =Financials!K37 -> 3156.3997 | L70: =Financials!L37 -> 4097.6578 | M70: =Financials!M37 -> 4921.0408 | N70: =Financials!N37 -> 4428.5796 | O70: =Financials!O37 -> 4829.6328
C71: Less: Dividends Paid | K71: =-Assumptions!K81 -> -315.63997 | L71: =-Assumptions!L81 -> -409.76578 | M71: =-Assumptions!M81 -> -492.10408 | N71: =-Assumptions!N81 -> -442.85796 | O71: =-Assumptions!O81 -> -482.96328
C72: Add: Share-based Compensations | K72: =Assumptions!K84 -> 180.38144 | L72: =Assumptions!L84 -> 236.04414 | M72: =Assumptions!M84 -> 298.56563 | N72: =Assumptions!N84 -> 364.97918 | O72: =Assumptions!O84 -> 441.80256
C73: Closing balance of RE | K73: =SUM(K69:K72) -> 9371.9012 | L73: =SUM(L69:L72) -> 13295.837 | M73: =SUM(M69:M72) -> 18023.34 | N73: =SUM(N69:N72) -> 22374.041 | O73: =SUM(O69:O72) -> 27162.513
B77: # | C77: End

Sheet Valuation->

Sheet DCF
C2: =Dashboard!C2 -> Lloyds Metal & Energy Ltd.
C3: DCF Model
C4: =Dashboard!C4 -> (₹ in 'Cr, except share price and shares outstanding)
C6: <-Back to Dashboard
B8: # | C8: Assumptions
C10: Triggers | G10: Conservative | I10: Average | K10: Base/Street | M10: Average | O10: Optimistic | Q10: Average
C12: Scenario: | E12: =Dashboard!E14 -> 1 | G12: WACC | I12: =M12+2% -> 0.21887821 | K12: WACC | M12: =WACC!J13 -> 0.19887821 | O12: WACC | Q12: =M12-2% -> 0.17887821
G13: TGR | I13: 0.02 | K13: TGR | M13: 0.03 | O13: TGR | Q13: 0.04
C14: WACC | E14: =CHOOSE(E12,M12,I12,Q12) -> 0.19887821
C15: TGR | E15: =CHOOSE(E12,M13,I13,Q13) -> 0.03
B17: # | C17: DCF | G17: 46112 | H17: =EOMONTH(G17,12) -> 46477 | I17: =EOMONTH(H17,12) -> 46843 | J17: =EOMONTH(I17,12) -> 47208 | K17: =EOMONTH(J17,12) -> 47573
C19: EBIT | G19: =Financials!K32 -> 4116.2131 | H19: =Financials!L32 -> 5345.4152 | I19: =Financials!M32 -> 6543.1253 | J19: =Financials!N32 -> 6537.2895 | K19: =Financials!O32 -> 7570.9556
C20: Tax Rate (%) | G20: 0.3 | H20: 0.3 | I20: 0.3 | J20: 0.3 | K20: 0.3
C21: NOPAT | G21: =G19*(1-G20) -> 2881.3491 | H21: =H19*(1-H20) -> 3741.7906 | I21: =I19*(1-I20) -> 4580.1877 | J21: =J19*(1-J20) -> 4576.1027 | K21: =K19*(1-K20) -> 5299.6689
C23: Add: Depreciation & Amortization | G23: =Financials!K27 -> 481.01717 | H23: =Financials!L27 -> 334.39587 | I23: =Financials!M27 -> 380.67118 | J23: =Financials!N27 -> 413.64307 | K23: =Financials!O27 -> 438.12087
C24: Add: Share-based Compensation | G24: =Assumptions!K84 -> 180.38144 | H24: =Assumptions!L84 -> 236.04414 | I24: =Assumptions!M84 -> 298.56563 | J24: =Assumptions!N84 -> 364.97918 | K24: =Assumptions!O84 -> 441.80256
C25: Less: CapEx | G25: =-Schedule!K18 -> -6012.7147 | H25: =-Schedule!L18 -> -1967.0345 | I25: =-Schedule!M18 -> -2239.2422 | J25: =-Schedule!N18 -> -2433.1946 | K25: =-Schedule!O18 -> -2577.1816
C26: Add / Less: Change in Working Capital | G26: =SUM(Financials!K111:K113) -> -693.88575 | H26: =SUM(Financials!L111:L113) -> -390.19346 | I26: =SUM(Financials!M111:M113) -> -443.34338 | J26: =SUM(Financials!N111:N113) -> -506.36168 | K26: =SUM(Financials!O111:O113) -> -556.89754
C27: FCF | G27: =SUM(G21:G26) -> -3163.8527 | H27: =SUM(H21:H26) -> 1955.0026 | I27: =SUM(I21:I26) -> 2576.8389 | J27: =SUM(J21:J26) -> 2415.1687 | K27: =SUM(K21:K26) -> 3045.5132
C29: Discount Period | G29: 1 | H29: =G29+1 -> 2 | I29: =H29+1 -> 3 | J29: =I29+1 -> 4 | K29: =J29+1 -> 5
C30: Mid Year Discount | G30: 0.5 | H30: =G30+1 -> 1.5 | I30: =H30+1 -> 2.5 | J30: =I30+1 -> 3.5 | K30: =J30+1 -> 4.5
C31: Terminal Value | K31: =K27*(1+tgr)/(wacc-tgr) -> 18574.798
C32: Discounted FCF | G32: =G27/(1+wacc)^G30 -> -2889.54 | H32: =H27/(1+wacc)^H30 -> 1489.3088 | I32: =I27/(1+wacc)^I30 -> 1637.3805 | J32: =J27/(1+wacc)^J30 -> 1280.073 | K32: =(K27+K31)/(1+wacc)^K30 -> 9558.1568
C34: Enterprise Value | G34: =SUM(G32:K32) -> 11075.379
C35: Add: Cash | G35: =Financials!J67+Financials!J68+Financials!J65+Financials!J56 -> 814.37
C36: Less: Debt | G36: =Financials!J81+Financials!J89 -> 755.75
C37: Equity Value | G37: =G34+G35-G36 -> 11133.999
C38: Number of Shares | G38: 120648
C39: Price Per Share | G39: =G37/G38*10^4 -> 922.84986
B42: # | C42: Sensitivity Analysis - Terminal Growth Rate (%) to WACC (%)
D44: Terminal Growth Rate %
C45: WACC | D45: =G39 -> 922.84986 | E45: 0.01 | F45: =E45+1% -> 0.02 | G45: =F45+1% -> 0.03 | H45: =G45+1% -> 0.04 | I45: =H45+1% -> 0.05 | K45: Mean | M45: =AVERAGE($E$56:$I$60,$E$66:$I$70,$E$76:$I$80) -> 962.10736
D46: 0.24 | E46: 622.67976 | F46: 646.17684 | G46: 671.91174 | H46: 700.22014 | I46: 731.50836 | K46: Median | M46: =MEDIAN($E$56:$I$60,$E$66:$I$70,$E$76:$I$80) -> 922.84986
D47: 0.22 | E47: 716.74008 | F47: 746.70628 | G47: 779.82682 | H47: 816.62741 | I47: 857.75749 | K47: 75th Percentile | M47: =QUARTILE(($E$56:$I$60,$E$66:$I$70,$E$76:$I$80),3) -> 1341.0953
D48: 0.19887821 | E48: 838.96141 | F48: 878.56079 | G48: 922.84986 | H48: 972.71415 | I48: 1029.2771 | K48: 25th Percentile | M48: =QUARTILE(($E$56:$I$60,$E$66:$I$70,$E$76:$I$80),1) -> 392.24085
D49: 0.18 | E49: 975.19876 | F49: 1027.1965 | G49: 1086.1273 | H49: 1153.4767 | I49: 1231.1876
D50: 0.16 | E50: 1158.555 | F50: 1230.057 | G50: 1312.5593 | H50: 1408.8119 | I50: 1522.5651
C52: Base Case
D54: Terminal Growth Rate %
C55: WACC | D55: =G49 -> 1086.1273 | E55: 0.01 | F55: =E55+1% -> 0.02 | G55: =F55+1% -> 0.03 | H55: =G55+1% -> 0.04 | I55: =H55+1% -> 0.05
D56: 0.24 | E56: 622.67976 | F56: 646.17684 | G56: 671.91174 | H56: 700.22014 | I56: 731.50836
D57: 0.22 | E57: 716.74008 | F57: 746.70628 | G57: 779.82682 | H57: 816.62741 | I57: 857.75749
D58: 0.19887821 | E58: 838.96141 | F58: 878.56079 | G58: 922.84986 | H58: 972.71415 | I58: 1029.2771
D59: 0.18 | E59: 975.19876 | F59: 1027.1965 | G59: 1086.1273 | H59: 1153.4767 | I59: 1231.1876
D60: 0.16 | E60: 1158.555 | F60: 1230.057 | G60: 1312.5593 | H60: 1408.8119 | I60: 1522.5651
C62: Conservative Case
D64: Terminal Growth Rate %
C65: WACC | D65: =G59 -> 1086.1273 | E65: 0.01 | F65: =E65+1% -> 0.02 | G65: =F65+1% -> 0.03 | H65: =G65+1% -> 0.04 | I65: =H65+1% -> 0.05
D66: 0.24 | E66: 194.4497 | F66: 202.60929 | G66: 211.546 | H66: 221.37637 | I66: 232.24151
D67: 0.22 | E67: 230.40455 | F67: 240.81061 | G67: 252.31205 | H67: 265.09142 | I67: 279.37425
D68: 0.19887821 | E68: 276.56901 | F68: 290.32028 | G68: 305.70011 | H68: 323.01598 | I68: 342.65803
D69: 0.18 | E69: 327.43663 | F69: 345.49336 | G69: 365.95765 | H69: 389.34542 | I69: 416.3313
D70: 0.16 | E70: 395.13629 | F70: 419.96606 | G70: 448.61581 | H70: 482.04051 | I70: 521.54243
C72: Optimistic Case
D74: Terminal Growth Rate %
C75: WACC | D75: =G69 -> 365.95765 | E75: 0.01 | F75: =E75+1% -> 0.02 | G75: =F75+1% -> 0.03 | H75: =G75+1% -> 0.04 | I75: =H75+1% -> 0.05
D76: 0.24 | E76: 1052.0146 | F76: 1090.8954 | G76: 1133.4791 | H76: 1180.3211 | I76: 1232.0939
D77: 0.22 | E77: 1204.3472 | F77: 1253.9324 | G77: 1308.7371 | H77: 1369.6312 | I77: 1437.6894
D78: 0.19887821 | E78: 1402.8451 | F78: 1468.3704 | G78: 1541.6557 | H78: 1624.1664 | I78: 1717.7615
D79: 0.18 | E79: 1624.7003 | F79: 1710.7413 | G79: 1808.2543 | H79: 1919.6978 | I79: 2048.2864
D80: 0.16 | E80: 1924.0513 | F80: 2042.366 | G80: 2178.883 | H80: 2338.1528 | I80: 2526.3807
C83: Share Price Forecast for 2026
B84: # | C84: Assumptions
C86: Triggers | G86: Conservative | I86: Average | K86: Base/Street | M86: Average | O86: Optimistic | Q86: Average
C88: Scenario: | E88: =Dashboard!E14 -> 1 | G88: WACC | I88: =M88+2% -> 0.20833164 | K88: WACC | M88: 0.18833164 | O88: WACC | Q88: =M88-2% -> 0.16833164
G89: TGR | I89: 0.02 | K89: TGR | M89: 0.03 | O89: TGR | Q89: 0.04
C90: WACC | E90: =CHOOSE(E88,M88,I88,Q88) -> 0.18833164
C91: TGR | E91: =CHOOSE(E88,M89,I89,Q89) -> 0.03
B93: # | C93: DCF | G93: 46477 | H93: =EOMONTH(G93,12) -> 46843 | I93: =EOMONTH(H93,12) -> 47208 | J93: =EOMONTH(I93,12) -> 47573
C95: EBIT | G95: =H19 -> 5345.4152 | H95: =I19 -> 6543.1253 | I95: =J19 -> 6537.2895 | J95: =K19 -> 7570.9556
C96: Tax Rate (%) | G96: =H20 -> 0.3 | H96: =I20 -> 0.3 | I96: =J20 -> 0.3 | J96: =K20 -> 0.3
C97: NOPAT | G97: =H21 -> 3741.7906 | H97: =I21 -> 4580.1877 | I97: =J21 -> 4576.1027 | J97: =K21 -> 5299.6689
C99: Add: Depreciation & Amortization | G99: =H23 -> 334.39587 | H99: =I23 -> 380.67118 | I99: =J23 -> 413.64307 | J99: =K23 -> 438.12087
C100: Add: Share-based Compensation | G100: =H24 -> 236.04414 | H100: =I24 -> 298.56563 | I100: =J24 -> 364.97918 | J100: =K24 -> 441.80256
C101: Less: CapEx | G101: =H25 -> -1967.0345 | H101: =I25 -> -2239.2422 | I101: =J25 -> -2433.1946 | J101: =K25 -> -2577.1816
C102: Add / Less: Change in Working Capital | G102: =H26 -> -390.19346 | H102: =I26 -> -443.34338 | I102: =J26 -> -506.36168 | J102: =K26 -> -556.89754
C103: FCF | G103: =SUM(G97:G102) -> 1955.0026 | H103: =SUM(H97:H102) -> 2576.8389 | I103: =SUM(I97:I102) -> 2415.1687 | J103: =SUM(J97:J102) -> 3045.5132
C105: Discount Period | G105: 1 | H105: =G105+1 -> 2 | I105: =H105+1 -> 3 | J105: =I105+1 -> 4
C106: Mid Year Discount | G106: 0.5 | H106: =G106+1 -> 1.5 | I106: =H106+1 -> 2.5 | J106: =I106+1 -> 3.5
C107: Terminal Value | J107: =J103*(1+tgrth1)/(wacc1-tgrth1) -> 19812.078
C108: Discounted FCF | G108: =G103/(1+wacc1)^G106 -> 1793.4056 | H108: =H103/(1+wacc1)^H106 -> 1989.2107 | I108: =I103/(1+wacc1)^I106 -> 1568.9291 | J108: =(J103+J107)/(1+wacc1)^J106 -> 12495.356
C110: Enterprise Value | G110: {=SUM(G108:J108)} -> 17846.902
C111: Add: Cash | G111: =Financials!K67+Financials!K68+Financials!K65+Financials!K56 -> 2023.5434
C112: Less: Debt | G112: =Financials!K81 -> 5337.737
C113: Equity Value | G113: =G110+G111-G112 -> 14532.708
C114: Number of Shares | G114: =G38 -> 120648
C115: Price Per Share | G115: =G113/G114*10^4 -> 1204.5544

Sheet WACC
C2: =Dashboard!C2 -> Lloyds Metal & Energy Ltd.
C3: WACC
C4: =Dashboard!C4 -> (₹ in 'Cr, except share price and shares outstanding)
C6: <-Back to Dashboard
C8: Cost of Capital | H8: Capital Structure
C9: Risk Free Rate | E9: 0.06737 | F9: Investing.com | H9: Market Cap | J9: 70112
C10: Equity Risk Premium | E10: 0.0708 | F10: Aswath Damodaran | H10: Total Debt | J10: 755.75
C11: Country Risk Premium | E11: 0.0285 | F11: Aswath Damodaran | H11: Total Capital | J11: =SUM(J9:J10) -> 70867.75
C12: Beta | E12: =Beta!L25 -> 1.4813586 | F12: Regression
C13: Cost of Equity | E13: =E9+(E10*E12)+E11 -> 0.20075019 | H13: WACC | J13: =E13*(J9/J11)+E22*(J10/J11) -> 0.19887821
C15: Cost of Debt
C16: (Using Interest Expense)
C17: Finance Cost | E17: =Financials!J26 -> 27.22
C18: Total Borrowings | E18: =Financials!J81+Financials!J89 -> 755.75
C19: Cost of Debt | E19: =E17/E18 -> 0.036017201
C21: Tax Rate (%) | E21: 0.3
C22: Cost of Debt Post Tax | E22: =E19*(1-E21) -> 0.025212041
B24: # | C24: End

Sheet Beta
C2: <-Back to Dashboard
C4: Beta
C6: LLOYDSME | G6: Nifty 500 | K6: SUMMARY OUTPUT
C8: Date | D8: Price | G8: Date | H8: Price | K8: Regression Statistics
C9: 46096 | D9: 1245.8 | G9: 46096 | H9: 21327.9 | K9: Multiple R | L9: 0.50588928
C10: 46089 | D10: 1140.8 | E10: =D9/D10-1 -> 0.092040673 | G10: 46089 | H10: 21391.2 | I10: =H9/H10-1 -> -0.0029591608 | K10: R Square | L10: 0.25592396
C11: 46082 | D11: 1184 | E11: =D10/D11-1 -> -0.036486486 | G11: 46082 | H11: 22481.3 | I11: =H10/H11-1 -> -0.048489189 | K11: Adjusted R Square | L11: 0.25045281
C12: 46075 | D12: 1233 | E12: =D11/D12-1 -> -0.03974047 | G12: 46075 | H12: 23166.85 | I12: =H11/H12-1 -> -0.029591852 | K12: Standard Error | L12: 0.04826755
C13: 46068 | D13: 1143 | E13: =D12/D13-1 -> 0.078740157 | G13: 46068 | H13: 23395 | I13: =H12/H13-1 -> -0.0097520838 | K13: Observations | L13: 138
C14: 46061 | D14: 1190.4 | E14: =D13/D14-1 -> -0.039818548 | G14: 46061 | H14: 23313.15 | I14: =H13/H14-1 -> 0.0035108941
C15: 46054 | D15: 1261.3 | E15: =D14/D15-1 -> -0.056211845 | G15: 46054 | H15: 23434 | I15: =H14/H15-1 -> -0.0051570368 | K15: ANOVA
C16: 46047 | D16: 1103.8 | E16: =D15/D16-1 -> 0.14268889 | G16: 46047 | H16: 23079.5 | I16: =H15/H16-1 -> 0.015359951 | L16: df | M16: SS | N16: MS | O16: F | P16: Significance F
C17: 46040 | D17: 1115.5 | E17: =D16/D17-1 -> -0.01048857 | G17: 46040 | H17: 22706.2 | I17: =H16/H17-1 -> 0.016440444 | K17: Regression | L17: 1 | M17: 0.10897906 | N17: 0.10897906 | O17: 46.777019 | P17: 2.4636358e-10
C18: 46033 | D18: 1229 | E18: =D17/D18-1 -> -0.092351505 | G18: 46033 | H18: 23485.3 | I18: =H17/H18-1 -> -0.033173943 | K18: Residual | L18: 136 | M18: 0.31684687 | N18: 0.0023297564
C19: 46026 | D19: 1265.2 | E19: =D18/D19-1 -> -0.028612077 | G19: 46026 | H19: 23467.35 | I19: =H18/H19-1 -> 0.0007648925 | K19: Total | L19: 137 | M19: 0.42582593
C20: 46019 | D20: 1348.8 | E20: =D19/D20-1 -> -0.06198102 | G20: 46019 | H20: 24099 | I20: =H19/H20-1 -> -0.026210631
C21: 46012 | D21: 1369.8 | E21: =D20/D21-1 -> -0.015330705 | G21: 46012 | H21: 23780.25 | I21: =H20/H21-1 -> 0.01340398 | L21: Coefficients | M21: Standard Error | N21: t Stat | O21: P-value | P21: Lower 95% | Q21: Upper 95% | R21: Lower 95.0% | S21: Upper 95.0%
C22: 46005 | D22: 1300.9 | E22: =D21/D22-1 -> 0.052963333 | G22: 46005 | H22: 23677.55 | I22: =H21/H22-1 -> 0.004337442 | K22: Intercept | L22: 0.0041052294 | M22: 0.004128244 | N22: 0.99442508 | O22: 0.32178197 | P22: -0.0040586241 | Q22: 0.012269083 | R22: -0.0040586241 | S22: 0.012269083
C23: 45998 | D23: 1288.3 | E23: =D22/D23-1 -> 0.0097803307 | G23: 45998 | H23: 23726.2 | I23: =H22/H23-1 -> -0.0020504758 | K23: X Variable 1 | L23: 1.4813586 | M23: 0.21659276 | N23: 6.8393727 | O23: 2.4636358e-10 | P23: 1.0530332 | Q23: 1.9096839 | R23: 1.0530332 | S23: 1.9096839
C24: 45991 | D24: 1220.3 | E24: =D23/D24-1 -> 0.055724002 | G24: 45991 | H24: 23835.25 | I24: =H23/H24-1 -> -0.0045751565
C25: 45984 | D25: 1220.4 | E25: =D24/D25-1 -> -8.1940347e-05 | G25: 45984 | H25: 23933.2 | I25: =H24/H25-1 -> -0.0040926412 | K25: Beta | L25: =L23 -> 1.4813586
C26: 45977 | D26: 1223 | E26: =D25/D26-1 -> -0.0021259199 | G26: 45977 | H26: 23790.25 | I26: =H25/H26-1 -> 0.0060087641
C27: 45970 | D27: 1287.3 | E27: =D26/D27-1 -> -0.049949507 | G27: 45970 | H27: 23836.35 | I27: =H26/H27-1 -> -0.0019340209 | K27: Mean | L27: =AVERAGE($D$9:$D$63) -> 1302.2736
C28: 45963 | D28: 1315.6 | E28: =D27/D28-1 -> -0.021511098 | G28: 45963 | H28: 23521.5 | I28: =H27/H28-1 -> 0.013385626 | K28: Median | L28: =MEDIAN($D$9:$D$63) -> 1293.4
C29: 45956 | D29: 1304.8 | E29: =D28/D29-1 -> 0.0082771306 | G29: 45956 | H29: 23710.4 | I29: =H28/H29-1 -> -0.0079669681 | K29: 75th Percentile | L29: =QUARTILE($D$9:$D$63,3) -> 1351.25
C30: 45949 | D30: 1336.3 | E30: =D29/D30-1 -> -0.023572551 | G30: 45949 | H30: 23686.6 | I30: =H29/H30-1 -> 0.0010047875 | K30: 25th Percentile | L30: =QUARTILE($D$9:$D$63,1) -> 1226
C31: 45942 | D31: 1323.4 | E31: =D30/D31-1 -> 0.0097476198 | G31: 45942 | H31: 23598.05 | I31: =H30/H31-1 -> 0.0037524287
C32: 45935 | D32: 1344.2 | E32: =D31/D32-1 -> -0.015473888 | G32: 45935 | H32: 23337.55 | I32: =H31/H32-1 -> 0.011162269
C33: 45928 | D33: 1312.3 | E33: =D32/D33-1 -> 0.024308466 | G33: 45928 | H33: 23027.7 | I33: =H32/H33-1 -> 0.013455534
C34: 45921 | D34: 1246 | E34: =D33/D34-1 -> 0.053210273 | G34: 45921 | H34: 22713.15 | I34: =H33/H34-1 -> 0.013848806
C35: 45914 | D35: 1328.5 | E35: =D34/D35-1 -> -0.062100113 | G35: 45914 | H35: 23486.65 | I35: =H34/H35-1 -> -0.032933603
C36: 45907 | D36: 1296.5 | E36: =D35/D36-1 -> 0.024681836 | G36: 45907 | H36: 23190.25 | I36: =H35/H36-1 -> 0.012781233
C37: 45900 | D37: 1293.4 | E37: =D36/D37-1 -> 0.0023967837 | G37: 45900 | H37: 22829.15 | I37: =H36/H37-1 -> 0.015817496
C38: 45893 | D38: 1288.8 | E38: =D37/D38-1 -> 0.0035692117 | G38: 45893 | H38: 22462.95 | I38: =H37/H38-1 -> 0.0163024
C39: 45886 | D39: 1353.7 | E39: =D38/D39-1 -> -0.047942676 | G39: 45886 | H39: 22991.3 | I39: =H38/H39-1 -> -0.022980432
C40: 45879 | D40: 1398.7 | E40: =D39/D40-1 -> -0.032172732 | G40: 45879 | H40: 22680.25 | I40: =H39/H40-1 -> 0.013714575
C41: 45872 | D41: 1400.3 | E41: =D40/D41-1 -> -0.0011426123 | G41: 45872 | H41: 22443.15 | I41: =H40/H41-1 -> 0.010564471
C42: 45865 | D42: 1445.6 | E42: =D41/D42-1 -> -0.031336469 | G42: 45865 | H42: 22673.65 | I42: =H41/H42-1 -> -0.010165986
... C147: 45130 | D147: 596.9 | E147: =D146/D147-1 -> 0.074719383 | G147: 45130 | H147: 16948.35 | I147: =H146/H147-1 -> -0.0034074113

Sheet Comps
C2: =Dashboard!C2 -> Lloyds Metal & Energy Ltd.
C3: Comparable Companies
C4: =Dashboard!C4 -> (₹ in 'Cr, except share price and shares outstanding)
C6: <-Back to Dashboard
B8: # | C8: Overview
C10: Company | E10: Revenue | F10: EBITDA | G10: EBITDA % | H10: Net Income | I10: NI % | J10: Price / Share (₹) | K10: Market Cap | L10: Enterprise Value | M10: EV / Rev | N10: EV / EBITDA | O10: P / Sales | P10: P / E
C11: Lloyds Metal & Energy | E11: 12286 | F11: =3651+405 -> 4056 | G11: =F11/$E11 -> 0.33013186 | H11: 2463 | I11: =H11/$E11 -> 0.20047208 | J11: 1246 | K11: 70112 | L11: 77299 | M11: =L11/E11 -> 6.2916328 | N11: =L11/F11 -> 19.057939 | O11: =J11/E11 -> 0.10141625 | P11: =J11/H11 -> 0.50588713
C12: NMDC | E12: 27732 | F12: =9749+466 -> 10215 | G12: =F12/$E12 -> 0.36834704 | H12: 6902 | I12: =H12/$E12 -> 0.24888216 | J12: 79.8 | K12: 70141 | L12: 63249 | M12: =L12/E12 -> 2.2807226 | N12: =L12/F12 -> 6.1917768 | O12: =J12/E12 -> 0.0028775422 | P12: =J12/H12 -> 0.011561866
C13: GMDC | E13: 2626 | F13: =846+92.6 -> 938.6 | G13: =F13/$E13 -> 0.35742574 | H13: 640 | I13: =H13/$E13 -> 0.24371668 | J13: 576 | K13: 18307 | L13: 17990 | M13: =L13/E13 -> 6.8507235 | N13: =L13/F13 -> 19.166844 | O13: =J13/E13 -> 0.21934501 | P13: =J13/H13 -> 0.9
C14: Gravita | E14: 4130 | F14: =483+35.5 -> 518.5 | G14: =F14/$E14 -> 0.12554479 | H14: 382 | I14: =H14/$E14 -> 0.092493947 | J14: 1405 | K14: 10372 | L14: 10582 | M14: =L14/E14 -> 2.5622276 | N14: =L14/F14 -> 20.408872 | O14: =J14/E14 -> 0.3401937 | P14: =J14/H14 -> 3.6780105
C15: MOIL | E15: 1489 | F15: =349+161 -> 510 | G15: =F15/$E15 -> 0.34251175 | H15: 291 | I15: =H15/$E15 -> 0.19543318 | J15: 292 | K15: 5934 | L15: 5097 | M15: =L15/E15 -> 3.4231028 | N15: =L15/F15 -> 9.9941176 | O15: =J15/E15 -> 0.19610477 | P15: =J15/H15 -> 1.0034364
C16: Ashapura Minechem Ltd | E16: 3824 | F16: =489+127 -> 616 | G16: =F16/$E16 -> 0.16108787 | H16: 381 | I16: =H16/$E16 -> 0.099633891 | J16: 503 | K16: 4804 | L16: 5710 | M16: =L16/E16 -> 1.4932008 | N16: =L16/F16 -> 9.2694805 | O16: =J16/E16 -> 0.13153766 | P16: =J16/H16 -> 1.32021
C17: Petro Carbon & Chemicals | E17: 380 | F17: =18.2+4.55 -> 22.75 | G17: =F17/$E17 -> 0.059868421 | H17: 4.15 | I17: =H17/$E17 -> 0.010921053 | J17: 246 | K17: 608 | L17: 849 | M17: =L17/E17 -> 2.2342105 | N17: =L17/F17 -> 37.318681 | O17: =J17/E17 -> 0.64736842 | P17: =J17/H17 -> 59.277108
C18: 20 Microns Ltd | E18: 920 | F18: =104+20.3 -> 124.3 | G18: =F18/$E18 -> 0.1351087 | H18: 64.8 | I18: =H18/$E18 -> 0.070434783 | J18: 151 | K18: 533 | L18: 638 | M18: =L18/E18 -> 0.69347826 | N18: =L18/F18 -> 5.1327434 | O18: =J18/E18 -> 0.16413043 | P18: =J18/H18 -> 2.3302469
C19: NILE Ltd | E19: 1001 | F19: =72.9+3.84 -> 76.74 | G19: =F19/$E19 -> 0.076663337 | H19: 51.2 | I19: =H19/$E19 -> 0.051148851 | J19: 1501 | K19: 450 | L19: 452 | M19: =L19/E19 -> 0.45154845 | N19: =L19/F19 -> 5.8900182 | O19: =J19/E19 -> 1.4995005 | P19: =J19/H19 -> 29.316406
C20: Asi Industries Ltd | E20: 149 | F20: =39.1+4.63 -> 43.73 | G20: =F20/$E20 -> 0.29348993 | H20: 26 | I20: =H20/$E20 -> 0.17449664 | J20: 24.1 | K20: 217 | L20: 225 | M20: =L20/E20 -> 1.5100671 | N20: =L20/F20 -> 5.1452092 | O20: =J20/E20 -> 0.16174497 | P20: =J20/H20 -> 0.92692308
C22: Mean | M22: =AVERAGE(M12:M20) -> 2.3888091 | N22: =AVERAGE(N12:N20) -> 13.168638 | O22: =AVERAGE(O12:O20) -> 0.37364478 | P22: =AVERAGE(P12:P20) -> 10.973767
C23: Median | M23: =MEDIAN(M12:M20) -> 2.2342105 | N23: =MEDIAN(N12:N20) -> 9.2694805 | O23: =MEDIAN(O12:O20) -> 0.19610477 | P23: =MEDIAN(P12:P20) -> 1.32021
C24: 75th Percentile | M24: =QUARTILE(M12:M20,3) -> 2.5622276 | N24: =QUARTILE(N12:N20,3) -> 19.166844 | O24: =QUARTILE(O12:O20,3) -> 0.3401937 | P24: =QUARTILE(P12:P20,3) -> 3.6780105
C25: 25th Percentile | M25: =QUARTILE(M12:M20,1) -> 1.4932008 | N25: =QUARTILE(N12:N20,1) -> 5.8900182 | O25: =QUARTILE(O12:O20,1) -> 0.16174497 | P25: =QUARTILE(P12:P20,1) -> 0.92692308
B28: # | C28: Valuation
O29: Equity Value | S29: Price Per Share
C30: Lloyds Metal & Energy Ltd. | E30: Revenue | F30: EBITDA | G30: Net Income | H30: # Shares | I30: Cash | J30: Debt | K30: EV / Revenue | L30: EV / EBITDA | M30: P / Sales | N30: P / E | O30: EV / Revenue | P30: EV / EBITDA | Q30: P / Sales | R30: P / E | S30: EV / Revenue | T30: EV / EBITDA | U30: P / Sales | V30: P / E
C31: Mean | E31: =E11 -> 12286 | F31: =F11 -> 4056 | G31: =H11 -> 2463 | H31: 120648 | I31: =Financials!L63+Financials!L64+Financials!L61+Financials!L52 -> 7254.4739 | J31: =Financials!M76+Financials!M84 -> 18297.025 | K31: =M22 -> 2.3888091 | L31: =N22 -> 13.168638 | M31: =O22 -> 0.37364478 | N31: =P22 -> 10.973767 | O31: =K31*E31 -> 29348.908 | P31: =L31*F31 -> 53411.996 | Q31: =M31*E31 -> 4590.5997 | R31: =N31*G31 -> 27028.388 | S31: =H31*10^2/O31 -> 411.08173 | T31: =I31*10^2/P31 -> 13.582106 | U31: =J31*10^2/Q31 -> 398.57591 | V31: =K31*10^2/R31 -> 0.0088381485
C32: Median | E32: =E31 -> 12286 | F32: =F31 -> 4056 | G32: =G31 -> 2463 | H32: =H31 -> 120648 | I32: =I31 -> 7254.4739 | J32: =J31 -> 18297.025 | K32: =M23 -> 2.2342105 | L32: =N23 -> 9.2694805 | M32: =O23 -> 0.19610477 | N32: =P23 -> 1.32021 | O32: =K32*E32 -> 27449.511 | P32: =L32*F32 -> 37597.013 | Q32: =M32*E32 -> 2409.3432 | R32: =N32*G32 -> 3251.6772 | S32: =H32*10^2/O32 -> 439.52696 | T32: =I32*10^2/P32 -> 19.295346 | U32: =J32*10^2/Q32 -> 759.41962 | V32: =K32*10^2/R32 -> 0.068709482
C33: 75th Percentile | E33: =E32 -> 12286 | F33: =F32 -> 4056 | G33: =G32 -> 2463 | H33: =H32 -> 120648 | I33: =I32 -> 7254.4739 | J33: =J32 -> 18297.025 | K33: =M24 -> 2.5622276 | L33: =N24 -> 19.166844 | M33: =O24 -> 0.3401937 | N33: =P24 -> 3.6780105 | O33: =K33*E33 -> 31479.528 | P33: =L33*F33 -> 77740.72 | Q33: =M33*E33 -> 4179.6199 | R33: =N33*G33 -> 9058.9398 | S33: =H33*10^2/O33 -> 383.2586 | T33: =I33*10^2/P33 -> 9.3316268 | U33: =J33*10^2/Q33 -> 437.76768 | V33: =K33*10^2/R33 -> 0.028283968
C34: 25th Percentile | E34: =E33 -> 12286 | F34: =F33 -> 4056 | G34: =G33 -> 2463 | H34: =H33 -> 120648 | I34: =I33 -> 7254.4739 | J34: =J33 -> 18297.025 | K34: =M25 -> 1.4932008 | L34: =N25 -> 5.8900182 | M34: =O25 -> 0.16174497 | N34: =P25 -> 0.92692308 | O34: =K34*E34 -> 18345.465 | P34: =L34*F34 -> 23889.914 | Q34: =M34*E34 -> 1987.1987 | R34: =N34*G34 -> 2283.0115 | S34: =H34*10^2/O34 -> 657.6448 | T34: =I34*10^2/P34 -> 30.366262 | U34: =J34*10^2/Q34 -> 920.74463 | V34: =K34*10^2/R34 -> 0.065404875
B37: # | C37: 52-Week Share Price
C39: Valuation
C40: Mean | E40: 1302.2736
C41: Median | E41: 1293.4
C42: 75th Percentile | E42: 1351.25
C43: 25th Percentile | E43: 1226
B45: # | C45: End

Sheet Ratio Analysis
C2: =Dashboard!C2 -> Lloyds Metal & Energy Ltd.
C3: Ratio Analysis
C4: =Dashboard!C4 -> (₹ in 'Cr, except share price and shares outstanding)
C6: <-Back to Dashboard
B8: 1 | C8: Profitablity Ratios | F8: 44651 | G8: =EOMONTH(F8,12) -> 45016 | H8: =EOMONTH(G8,12) -> 45382 | I8: =EOMONTH(H8,12) -> 45747 | J8: =EOMONTH(I8,12) -> 46112 | K8: =EOMONTH(J8,12) -> 46477 | L8: =EOMONTH(K8,12) -> 46843 | M8: =EOMONTH(L8,12) -> 47208 | N8: =EOMONTH(M8,12) -> 47573
C9: Gross Profit Margin | F9: =Financials!G32/Financials!G$19 -> 0.19136473 | G9: =Financials!H32/Financials!H$19 -> 0.22981623 | H9: =Financials!I32/Financials!I$19 -> 0.26260761 | I9: =Financials!J32/Financials!J$19 -> 0.27996698 | J9: =Financials!K32/Financials!K$19 -> 0.27383392 | K9: =Financials!L32/Financials!L$19 -> 0.27174994 | L9: =Financials!M32/Financials!M$19 -> 0.26298239 | M9: =Financials!N32/Financials!N$19 -> 0.21493684 | N9: =Financials!O32/Financials!O$19 -> 0.20563817
C10: EBITDA | F10: =Financials!G32+Financials!G27+Financials!G26 -> 175.29 | G10: =Financials!H32+Financials!H27+Financials!H26 -> 884.76 | H10: =Financials!I32+Financials!I27+Financials!I26 -> 1781.21 | I10: =Financials!J32+Financials!J27+Financials!J26 -> 2004.13 | J10: =Financials!K32+Financials!K27+Financials!K26 -> 4856.1252 | K10: =Financials!L32+Financials!L27+Financials!L26 -> 6151.4699 | L10: =Financials!M32+Financials!M27+Financials!M26 -> 7467.7645 | M10: =Financials!N32+Financials!N27+Financials!N26 -> 7594.0968 | N10: =Financials!O32+Financials!O27+Financials!O26 -> 8755.2257
C11: EBITDA Margin | F11: =F10/Financials!G19 -> 0.24103128 | G11: =G10/Financials!H19 -> 0.25521162 | H11: =H10/Financials!I19 -> 0.27092295 | I11: =I10/Financials!J19 -> 0.2959165 | J11: =J10/Financials!K19 -> 0.32305709 | K11: =K10/Financials!L19 -> 0.31272811 | L11: =L10/Financials!M19 -> 0.30014565 | M11: =M10/Financials!N19 -> 0.24968318 | N11: =N10/Financials!O19 -> 0.23780466
C12: EBIT Margin | F12: =(Financials!G32+Financials!G26)/Financials!G19 -> 0.21630801 | G12: =(Financials!H32+Financials!H26)/Financials!H19 -> 0.24857721 | H12: =(Financials!I32+Financials!I26)/Financials!I19 -> 0.26347154 | I12: =(Financials!J32+Financials!J26)/Financials!J19 -> 0.28398611 | J12: =(Financials!K32+Financials!K26)/Financials!K19 -> 0.29105709 | K12: =(Financials!L32+Financials!L26)/Financials!L19 -> 0.29572811 | L12: =(Financials!M32+Financials!M26)/Financials!M19 -> 0.28484565 | M12: =(Financials!N32+Financials!N26)/Financials!N19 -> 0.23608318 | N12: =(Financials!O32+Financials!O26)/Financials!O19 -> 0.22590466
C13: PBT Margin | F13: =Financials!G34/Financials!G19 -> 0.12074252 | G13: =Financials!H34/Financials!H19 -> -0.11471197 | H13: =Financials!I34/Financials!I19 -> 0.26260761 | I13: =Financials!J34/Financials!J19 -> 0.27996698 | J13: =Financials!K34/Financials!K19 -> 0.27383392 | K13: =Financials!L34/Financials!L19 -> 0.27174994 | L13: =Financials!M34/Financials!M19 -> 0.26298239 | M13: =Financials!N34/Financials!N19 -> 0.21493684 | N13: =Financials!O34/Financials!O19 -> 0.20563817
C14: Net Profit Margin | F14: =Financials!G37/Financials!G19 -> 0.13381918 | G14: =Financials!H37/Financials!H19 -> -0.083230211 | H14: =Financials!I37/Financials!I19 -> 0.18905181 | I14: =Financials!J37/Financials!J19 -> 0.21408554 | J14: =Financials!K37/Financials!K19 -> 0.20998167 | K14: =Financials!L37/Financials!L19 -> 0.20831652 | L14: =Financials!M37/Financials!M19 -> 0.1977873 | M14: =Financials!N37/Financials!N19 -> 0.14560544 | N14: =Financials!O37/Financials!O19 -> 0.13117985
C15: ROE | F15: =Financials!G37/Financials!G77 -> 0.2020848 | G15: =Financials!H37/Financials!H77 -> -0.18871775 | H15: =Financials!I37/Financials!I77 -> 0.4421905 | I15: =Financials!J37/Financials!J77 -> 0.22647498 | J15: =Financials!K37/Financials!K77 -> 0.3349242 | K15: =Financials!L37/Financials!L77 -> 0.30698303 | L15: =Financials!M37/Financials!M77 -> 0.27224682 | M15: =Financials!N37/Financials!N77 -> 0.19747206 | N15: =Financials!O37/Financials!O77 -> 0.17746325
C16: ROA | F16: =Financials!G37/Financials!G72 -> 0.11814598 | G16: =Financials!H37/Financials!H72 -> -0.14241645 | H16: =Financials!I37/Financials!I72 -> 0.31566409 | I16: =Financials!J37/Financials!J72 -> 0.15396999 | J16: =Financials!K37/Financials!K72 -> 0.18320357 | K16: =Financials!L37/Financials!L72 -> 0.17984141 | L16: =Financials!M37/Financials!M72 -> 0.16767807 | M16: =Financials!N37/Financials!N72 -> 0.12168037 | N16: =Financials!O37/Financials!O72 -> 0.11155949
C17: ROCE | F17: =Financials!G37/(Financials!G72-Financials!G96) -> 0.13794145 | G17: =Financials!H37/(Financials!H72-Financials!H96) -> -0.18571153 | H17: =Financials!I37/(Financials!I72-Financials!I96) -> 0.4211072 | I17: =Financials!J37/(Financials!J72-Financials!J96) -> 0.19854629 | J17: =Financials!K37/(Financials!K72-Financials!K96) -> 0.21043902 | K17: =Financials!L37/(Financials!L72-Financials!L96) -> 0.20765764 | L17: =Financials!M37/(Financials!M72-Financials!M96) -> 0.19167674 | M17: =Financials!N37/(Financials!N72-Financials!N96) -> 0.14032487 | N17: =Financials!O37/(Financials!O72-Financials!O96) -> 0.12636286
C18: ROIC | F18: =(Financials!G32+Financials!G35+Financials!G36)/(Financials!G72-Financials!G96) -> 0.21073916 | G18: =(Financials!H32+Financials!H35+Financials!H36)/(Financials!H72-Financials!H96) -> 0.58303405 | H18: =(Financials!I32+Financials!I35+Financials!I36)/(Financials!I72-Financials!I96) -> 0.4211072 | I18: =(Financials!J32+Financials!J35+Financials!J36)/(Financials!J72-Financials!J96) -> 0.19854629 | J18: =(Financials!K32+Financials!K35+Financials!K36)/(Financials!K72-Financials!K96) -> 0.21043902 | K18: =(Financials!L32+Financials!L35+Financials!L36)/(Financials!L72-Financials!L96) -> 0.20765764 | L18: =(Financials!M32+Financials!M35+Financials!M36)/(Financials!M72-Financials!M96) -> 0.19167674 | M18: =(Financials!N32+Financials!N35+Financials!N36)/(Financials!N72-Financials!N96) -> 0.14032487 | N18: =(Financials!O32+Financials!O35+Financials!O36)/(Financials!O72-Financials!O96) -> 0.12636286
B20: 2 | C20: Liquidity Ratios | F20: 44651 | G20: =EOMONTH(F20,12) -> 45016 | H20: =EOMONTH(G20,12) -> 45382 | I20: =EOMONTH(H20,12) -> 45747 | J20: =EOMONTH(I20,12) -> 46112 | K20: =EOMONTH(J20,12) -> 46477 | L20: =EOMONTH(K20,12) -> 46843 | M20: =EOMONTH(L20,12) -> 47208 | N20: =EOMONTH(M20,12) -> 47573
C21: Current Ratio | F21: =Financials!G71/Financials!G96 -> 2.6134566 | G21: =Financials!H71/Financials!H96 -> 2.0045731 | H21: =Financials!I71/Financials!I96 -> 1.1434976 | I21: =Financials!J71/Financials!J96 -> 1.4285126 | J21: =Financials!K71/Financials!K96 -> 2.4682215 | K21: =Financials!L71/Financials!L96 -> 3.4149411 | L21: =Financials!M71/Financials!M96 -> 4.5096375 | M21: =Financials!N71/Financials!N96 -> 4.8574604 | N21: =Financials!O71/Financials!O96 -> 6.0203254
C22: Quick Ratio | F22: =(Financials!G71-Financials!G63)/Financials!G96 -> 1.20207 | G22: =(Financials!H71-Financials!H63)/Financials!H96 -> 1.4334681 | H22: =(Financials!I71-Financials!I63)/Financials!I96 -> 0.90911212 | I22: =(Financials!J71-Financials!J63)/Financials!J96 -> 1.2242955 | J22: =(Financials!K71-Financials!K63)/Financials!K96 -> 2.0384577 | K22: =(Financials!L71-Financials!L63)/Financials!L96 -> 3.0040741 | L22: =(Financials!M71-Financials!M63)/Financials!M96 -> 4.0779735 | M22: =(Financials!N71-Financials!N63)/Financials!N96 -> 4.4564898 | N22: =(Financials!O71-Financials!O63)/Financials!O96 -> 5.5575357
C23: Cash Ratio | F23: =(Financials!G67+Financials!G68)/Financials!G96 -> 0.18500973 | G23: =(Financials!H67+Financials!H68)/Financials!H96 -> 0.56011687 | H23: =(Financials!I67+Financials!I68)/Financials!I96 -> 0.29122462 | I23: =(Financials!J67+Financials!J68)/Financials!J96 -> 0.3496656 | J23: =(Financials!K67+Financials!K68)/Financials!K96 -> 0.87381873 | K23: =(Financials!L67+Financials!L68)/Financials!L96 -> 1.934598 | L23: =(Financials!M67+Financials!M68)/Financials!M96 -> 2.9254952 | M23: =(Financials!N67+Financials!N68)/Financials!N96 -> 3.3033129 | N23: =(Financials!O67+Financials!O68)/Financials!O96 -> 4.3367605
C24: Operating Cash Flow Ratio | J24: =Financials!K117/Financials!K96 -> 1.3496539 | K24: =Financials!L117/Financials!L96 -> 1.6546516 | L24: =Financials!M117/Financials!M96 -> 1.5025635 | M24: =Financials!N117/Financials!N96 -> 1.1121398 | N24: =Financials!O117/Financials!O96 -> 1.1315897
C25: Net Working Capital | F25: =Financials!G71-Financials!G96 -> 190.7267 | G25: =Financials!H71-Financials!H96 -> 474.49 | H25: =Financials!I71-Financials!I96 -> 141.48 | I25: =Financials!J71-Financials!J96 -> 905.97 | J25: =Financials!K71-Financials!K96 -> 3273.8444 | K25: =Financials!L71-Financials!L96 -> 7370.6016 | L25: =Financials!M71-Financials!M96 -> 12896.169 | M25: =Financials!N71-Financials!N96 -> 18653.549 | N25: =Financials!O71-Financials!O96 -> 25461.313
C26: NWC as a % of Revenue | F26: =F25/Financials!G19 -> 0.26225741 | G26: =G25/Financials!H19 -> 0.13686804 | H26: =H25/Financials!I19 -> 0.02151918 | I26: =I25/Financials!J19 -> 0.1337695 | J26: =J25/Financials!K19 -> 0.21779476 | K26: =K25/Financials!L19 -> 0.37470626 | L26: =L25/Financials!M19 -> 0.518325 | M26: =M25/Financials!N19 -> 0.61330233 | N26: =N25/Financials!O19 -> 0.6915663
B28: 3 | C28: Efficiency Ratios | F28: 44651 | G28: =EOMONTH(F28,12) -> 45016 | H28: =EOMONTH(G28,12) -> 45382 | I28: =EOMONTH(H28,12) -> 45747 | J28: =EOMONTH(I28,12) -> 46112 | K28: =EOMONTH(J28,12) -> 46477 | L28: =EOMONTH(K28,12) -> 46843 | M28: =EOMONTH(L28,12) -> 47208 | N28: =EOMONTH(M28,12) -> 47573
C29: Asset Turnover | F29: =Financials!G19/Financials!G72 -> 0.88287778 | G29: =Financials!H19/Financials!H72 -> 1.7111148 | H29: =Financials!I19/Financials!I72 -> 1.6697227 | I29: =Financials!J19/Financials!J72 -> 0.71919846 | J29: =Financials!K19/Financials!K72 -> 0.87247408 | K29: =Financials!L19/Financials!L72 -> 0.86330845 | L29: =Financials!M19/Financials!M72 -> 0.84776965 | M29: =Financials!N19/Financials!N72 -> 0.83568558 | N29: =Financials!O19/Financials!O72 -> 0.85043158
C30: Fixed Asset Turnover Ratio | F30: =Financials!G19/Financials!G52 -> 1.8224077 | G30: =Financials!H19/Financials!H52 -> 7.3046144 | H30: =Financials!I19/Financials!I52 -> 5.6836827 | I30: =Financials!J19/Financials!J52 -> 4.4221846 | J30: =Financials!K19/Financials!K52 -> 2.6290113 | K30: =Financials!L19/Financials!L52 -> 3.2781322 | L30: =Financials!M19/Financials!M52 -> 4.1379646 | M30: =Financials!N19/Financials!N52 -> 5.3329502 | N30: =Financials!O19/Financials!O52 -> 7.2297379
C31: Receivables Turnover | F31: =Financials!G19/Financials!G66 -> 30.63821 | G31: =Financials!H19/Financials!H66 -> 141.44308 | H31: =Financials!I19/Financials!I66 -> 82.275059 | I31: =Financials!J19/Financials!J66 -> 39.508925 | J31: =Financials!K19/Financials!K66 -> 39.17524 | K31: =Financials!L19/Financials!L66 -> 39.063135 | L31: =Financials!M19/Financials!M66 -> 38.598441 | M31: =Financials!N19/Financials!N66 -> 36.236232 | N31: =Financials!O19/Financials!O66 -> 35.812056
C32: Inventory Turnover | F32: =Financials!G30/Financials!G63 -> 3.5248142 | G32: =Financials!H30/Financials!H63 -> 9.8982391 | H32: =Financials!I30/Financials!I63 -> 20.979099 | I32: =Financials!J30/Financials!J63 -> 11.294492 | J32: =Financials!K30/Financials!K63 -> 11.390696 | K32: =Financials!L30/Financials!L63 -> 11.423385 | L32: =Financials!M30/Financials!M63 -> 11.560914 | M32: =Financials!N30/Financials!N63 -> 12.31456 | N32: =Financials!O30/Financials!O63 -> 12.46042
C33: Payable Turnover | F33: =Financials!G30/Financials!G91 -> 38.740448 | G33: =Financials!H30/Financials!H91 -> 35.825171 | H33: =Financials!I30/Financials!I91 -> 12.271084 | I33: =Financials!J30/Financials!J91 -> 134.41318 | J33: =Financials!K30/Financials!K91 -> 134.41318 | K33: =Financials!L30/Financials!L91 -> 134.41318 | L33: =Financials!M30/Financials!M91 -> 134.41318 | M33: =Financials!N30/Financials!N91 -> 134.41318 | N33: =Financials!O30/Financials!O91 -> 134.41318
C34: DSO | F34: =Schedule!G42 -> 14.732512 | G34: =Schedule!H42 -> 3.3505552 | H34: =Schedule!I42 -> 6.0162519 | I34: =Schedule!J42 -> 12.830549 | J34: =Schedule!K42 -> 12.830549 | K34: =Schedule!L42 -> 12.830549 | L34: =Schedule!M42 -> 12.830549 | M34: =Schedule!N42 -> 12.830549 | N34: =Schedule!O42 -> 12.830549
C35: DIO | F35: =Schedule!G41 -> 83.735442 | G35: =Schedule!H41 -> 28.400716 | H35: =Schedule!I41 -> 12.829351 | I35: =Schedule!J41 -> 23.269045 | J35: =Schedule!K41 -> 23.269045 | K35: =Schedule!L41 -> 23.269045 | L35: =Schedule!M41 -> 23.269045 | M35: =Schedule!N41 -> 23.269045 | N35: =Schedule!O41 -> 23.269045
C36: DPO | F36: =Schedule!G43 -> 9.4216773 | G36: =Schedule!H43 -> 10.188367 | H36: =Schedule!I43 -> 29.744723 | I36: =Schedule!J43 -> 2.7155076 | J36: =Schedule!K43 -> 2.7155076 | K36: =Schedule!L43 -> 2.7155076 | L36: =Schedule!M43 -> 2.7155076 | M36: =Schedule!N43 -> 2.7155076 | N36: =Schedule!O43 -> 2.7155076
C37: CCC | F37: =F34+F35-F36 -> 89.046276 | G37: =G34+G35-G36 -> 21.562904 | H37: =H34+H35-H36 -> -10.89912 | I37: =I34+I35-I36 -> 33.384086 | J37: =J34+J35-J36 -> 33.384086 | K37: =K34+K35-K36 -> 33.384086 | L37: =L34+L35-L36 -> 33.384086 | M37: =M34+M35-M36 -> 33.384086 | N37: =N34+N35-N36 -> 33.384086
C38: Working Capital Turnover | F38: =Financials!G19/'Ratio Analysis'!F25 -> 3.8130477 | G38: =Financials!H19/'Ratio Analysis'!G25 -> 7.3063078 | H38: =Financials!I19/'Ratio Analysis'!H25 -> 46.470172 | I38: =Financials!J19/'Ratio Analysis'!I25 -> 7.4755455 | J38: =Financials!K19/'Ratio Analysis'!J25 -> 4.5914787 | K38: =Financials!L19/'Ratio Analysis'!K25 -> 2.6687571 | L38: =Financials!M19/'Ratio Analysis'!L25 -> 1.9292915 | M38: =Financials!N19/'Ratio Analysis'!M25 -> 1.6305172 | N38: =Financials!O19/'Ratio Analysis'!N25 -> 1.445993
B40: 4 | C40: Leverage Ratios | F40: 44651 | G40: =EOMONTH(F40,12) -> 45016 | H40: =EOMONTH(G40,12) -> 45382 | I40: =EOMONTH(H40,12) -> 45747 | J40: =EOMONTH(I40,12) -> 46112 | K40: =EOMONTH(J40,12) -> 46477 | L40: =EOMONTH(K40,12) -> 46843 | M40: =EOMONTH(L40,12) -> 47208 | N40: =EOMONTH(M40,12) -> 47573
C41: Debt to Equity | F41: =(Financials!G89+Financials!G81)/Financials!G77 -> 0.11777898 | G41: =(Financials!H89+Financials!H81)/Financials!H77 -> 0 | H41: =(Financials!I89+Financials!I81)/Financials!I77 -> 0 | I41: =(Financials!J89+Financials!J81)/Financials!J77 -> 0.11804683 | J41: =(Financials!K89+Financials!K81)/Financials!K77 -> 0.56638494 | K41: =(Financials!L89+Financials!L81)/Financials!L77 -> 0.45672341 | L41: =(Financials!M89+Financials!M81)/Financials!M77 -> 0.40122968 | M41: =(Financials!N89+Financials!N81)/Financials!N77 -> 0.38912884 | N41: =(Financials!O89+Financials!O81)/Financials!O77 -> 0.38687435
C42: Debt to Assets | F42: =(Financials!G81+Financials!G89)/Financials!G72 -> 0.06885779 | G42: =(Financials!H81+Financials!H89)/Financials!H72 -> 0 | H42: =(Financials!I81+Financials!I89)/Financials!I72 -> 0 | I42: =(Financials!J81+Financials!J89)/Financials!J72 -> 0.080254649 | J42: =(Financials!K81+Financials!K89)/Financials!K72 -> 0.30981262 | K42: =(Financials!L81+Financials!L89)/Financials!L72 -> 0.26756456 | L42: =(Financials!M81+Financials!M89)/Financials!M72 -> 0.24711921 | M42: =(Financials!N81+Financials!N89)/Financials!N72 -> 0.23977742 | N42: =(Financials!O81+Financials!O89)/Financials!O72 -> 0.24320248
C43: Debt to EBITDA | F43: =(Financials!G81+Financials!G89)/'Ratio Analysis'!F10 -> 0.32357807 | G43: =(Financials!H81+Financials!H89)/'Ratio Analysis'!G10 -> 0 | H43: =(Financials!I81+Financials!I89)/'Ratio Analysis'!H10 -> 0 | I43: =(Financials!J81+Financials!J89)/'Ratio Analysis'!I10 -> 0.3770963 | J43: =(Financials!K81+Financials!K89)/'Ratio Analysis'!J10 -> 1.0991761 | K43: =(Financials!L81+Financials!L89)/'Ratio Analysis'!K10 -> 0.99105028 | L43: =(Financials!M81+Financials!M89)/'Ratio Analysis'!L10 -> 0.97117299 | M43: =(Financials!N81+Financials!N89)/'Ratio Analysis'!M10 -> 1.1491483 | N43: =(Financials!O81+Financials!O89)/'Ratio Analysis'!N10 -> 1.2025642
C44: Equity Multiplier | F44: =Financials!G72/Financials!G77 -> 1.710467 | G44: =Financials!H72/Financials!H77 -> 1.325112 | H44: =Financials!I72/Financials!I77 -> 1.4008261 | I44: =Financials!J72/Financials!J77 -> 1.4709034 | J44: =Financials!K72/Financials!K77 -> 1.8281532 | K44: =Financials!L72/Financials!L77 -> 1.7069652 | L44: =Financials!M72/Financials!M77 -> 1.623628 | M44: =Financials!N72/Financials!N77 -> 1.6228753 | N44: =Financials!O72/Financials!O77 -> 1.59075
C45: Interest Coverage | F45: =Financials!G32/Financials!G26 -> 7.6719956 | G45: =Financials!H32/Financials!H26 -> 12.249692 | H45: =Financials!I32/Financials!I26 -> 303.96831 | I45: =Financials!J32/Financials!J26 -> 69.658707 | J45: =Financials!K32/Financials!K26 -> 15.89916 | K45: =Financials!L32/Financials!L26 -> 11.333225 | L45: =Financials!M32/Financials!M26 -> 12.028512 | M45: =Financials!N32/Financials!N26 -> 10.164262 | N45: =Financials!O32/Financials!O26 -> 10.146704
C46: Debt Service Coverage Ratio | F46: 0 | G46: 0 | H46: 0 | I46: 0 | J46: =Financials!K32/(Schedule!K63-Schedule!K59) -> 8.4858475 | K46: =Financials!L32/(Schedule!L63-Schedule!L59) -> 2.5786141 | L46: =Financials!M32/(Schedule!M63-Schedule!M59) -> 2.7574467 | M46: =Financials!N32/(Schedule!N63-Schedule!N59) -> 2.3190829 | N46: =Financials!O32/(Schedule!O63-Schedule!O59) -> 2.250466
B48: 5 | C48: Du-Pont Analysis | F48: 44651 | G48: =EOMONTH(F48,12) -> 45016 | H48: =EOMONTH(G48,12) -> 45382 | I48: =EOMONTH(H48,12) -> 45747 | J48: =EOMONTH(I48,12) -> 46112 | K48: =EOMONTH(J48,12) -> 46477 | L48: =EOMONTH(K48,12) -> 46843 | M48: =EOMONTH(L48,12) -> 47208 | N48: =EOMONTH(M48,12) -> 47573
C49: Net Profit Margin | F49: =F14 -> 0.13381918 | G49: =G14 -> -0.083230211 | H49: =H14 -> 0.18905181 | I49: =I14 -> 0.21408554 | J49: =J14 -> 0.20998167 | K49: =K14 -> 0.20831652 | L49: =L14 -> 0.1977873 | M49: =M14 -> 0.14560544 | N49: =N14 -> 0.13117985
C50: Asset Turnover | F50: =F29 -> 0.88287778 | G50: =G29 -> 1.7111148 | H50: =H29 -> 1.6697227 | I50: =I29 -> 0.71919846 | J50: =J29 -> 0.87247408 | K50: =K29 -> 0.86330845 | L50: =L29 -> 0.84776965 | M50: =M29 -> 0.83568558 | N50: =N29 -> 0.85043158
C51: Equity Multiplier | F51: =F44 -> 1.710467 | G51: =G44 -> 1.325112 | H51: =H44 -> 1.4008261 | I51: =I44 -> 1.4709034 | J51: =J44 -> 1.8281532 | K51: =K44 -> 1.7069652 | L51: =L44 -> 1.623628 | M51: =M44 -> 1.6228753 | N51: =N44 -> 1.59075
C52: Dupont Ratio | F52: =F49*F50*F51 -> 0.2020848 | G52: =G49*G50*G51 -> -0.18871775 | H52: =H49*H50*H51 -> 0.4421905 | I52: =I49*I50*I51 -> 0.22647498 | J52: =J49*J50*J51 -> 0.3349242 | K52: =K49*K50*K51 -> 0.30698303 | L52: =L49*L50*L51 -> 0.27224682 | M52: =M49*M50*M51 -> 0.19747206 | N52: =N49*N50*N51 -> 0.17746325

Sheet Analysis
C2: =Dashboard!C2 -> Lloyds Metal & Energy Ltd.
C3: Analysis
C4: =Dashboard!C4 -> (₹ in 'Cr, except share price and shares outstanding)
B6: # | C6: Horizontal Analysis | F6: 44651 | G6: =EOMONTH(F6,12) -> 45016 | H6: =EOMONTH(G6,12) -> 45382 | I6: =EOMONTH(H6,12) -> 45747 | J6: =EOMONTH(I6,12) -> 46112 | K6: =EOMONTH(J6,12) -> 46477 | L6: =EOMONTH(K6,12) -> 46843 | M6: =EOMONTH(L6,12) -> 47208 | N6: =EOMONTH(M6,12) -> 47573
C8: Gross Sales From Operations | F8: =Financials!G16/Financials!G$19 -> 0.95909247 | G8: =Financials!H16/Financials!H$19 -> 0.97852179 | H8: =Financials!I16/Financials!I$19 -> 0.98576491 | I8: =Financials!J16/Financials!J$19 -> 0.97839684 | J8: =Financials!K16/Financials!K$19 -> 0.9603702 | K8: =Financials!L16/Financials!L$19 -> 0.9540709 | L8: =Financials!M16/Financials!M$19 -> 0.9428532 | M8: =Financials!N16/Financials!N$19 -> 0.92554394 | N8: =Financials!O16/Financials!O$19 -> 0.90223344
C9: Gross Operating Revenues | F9: =Financials!G17/Financials!G$19 -> 0 | G9: =Financials!H17/Financials!H$19 -> 0 | H9: =Financials!I17/Financials!I$19 -> 0.0066376662 | I9: =Financials!J17/Financials!J$19 -> 0.014040357 | J9: =Financials!K17/Financials!K$19 -> 0.023584688 | K9: =Financials!L17/Financials!L$19 -> 0.032441525 | L9: =Financials!M17/Financials!M$19 -> 0.044884122 | M9: =Financials!N17/Financials!N$19 -> 0.062418506 | N9: =Financials!O17/Financials!O$19 -> 0.086628844
C10: Other Income | F10: =Financials!G18/Financials!G$19 -> 0.040907528 | G10: =Financials!H18/Financials!H$19 -> 0.021478206 | H10: =Financials!I18/Financials!I$19 -> 0.0075974204 | I10: =Financials!J18/Financials!J$19 -> 0.0075628044 | J10: =Financials!K18/Financials!K$19 -> 0.01604511 | K10: =Financials!L18/Financials!L$19 -> 0.013487579 | L10: =Financials!M18/Financials!M$19 -> 0.012262676 | M10: =Financials!N18/Financials!N$19 -> 0.012037553 | N10: =Financials!O18/Financials!O$19 -> 0.011137715
C11: Total Income | F11: =Financials!G19/Financials!G$19 -> 1 | G11: =Financials!H19/Financials!H$19 -> 1 | H11: =Financials!I19/Financials!I$19 -> 1 | I11: =Financials!J19/Financials!J$19 -> 1 | J11: =Financials!K19/Financials!K$19 -> 1 | K11: =Financials!L19/Financials!L$19 -> 1 | L11: =Financials!M19/Financials!M$19 -> 1 | M11: =Financials!N19/Financials!N$19 -> 1 | N11: =Financials!O19/Financials!O$19 -> 1
C13: Expenses:
C14: Cost Of Materials Consumed | F14: =Financials!G22/Financials!G$19 -> 0.51326229 | G14: =Financials!H22/Financials!H$19 -> 0.14548124 | H14: =Financials!I22/Financials!I$19 -> 0.081620175 | I14: =Financials!J22/Financials!J$19 -> 0.078759771 | J14: =Financials!K22/Financials!K$19 -> 0.10945605 | K14: =Financials!L22/Financials!L$19 -> 0.11710257 | L14: =Financials!M22/Financials!M$19 -> 0.13424183 | M14: =Financials!N22/Financials!N$19 -> 0.16252541 | N14: =Financials!O22/Financials!O$19 -> 0.1946835
C15: Purchases Of Stock-In-Trade | F15: =Financials!G23/Financials!G$19 -> 0 | G15: =Financials!H23/Financials!H$19 -> 0 | H15: =Financials!I23/Financials!I$19 -> 0.056312171 | I15: =Financials!J23/Financials!J$19 -> 0.026908346 | J15: =Financials!K23/Financials!K$19 -> 0.041535094 | K15: =Financials!L23/Financials!L$19 -> 0.039675629 | L15: =Financials!M23/Financials!M$19 -> 0.038581789 | M15: =Financials!N23/Financials!N$19 -> 0.038189102 | N15: =Financials!O23/Financials!O$19 -> 0.037858252
C16: Changes In Inventories Of Finished Goods | F16: =Financials!G24/Financials!G$19 -> -0.083052595 | G16: =Financials!H24/Financials!H$19 -> 0.010320846 | H16: =Financials!I24/Financials!I$19 -> -0.0022647766 | I16: =Financials!J24/Financials!J$19 -> 0.013349339 | J16: =Financials!K24/Financials!K$19 -> -0.0201289 | K16: =Financials!L24/Financials!L$19 -> 0.006152883 | L16: =Financials!M24/Financials!M$19 -> -0.007296647 | M16: =Financials!N24/Financials!N$19 -> 0.0023875641 | N16: =Financials!O24/Financials!O$19 -> -0.0025641195
C17: Employee Benefit Expenses | F17: =Financials!G25/Financials!G$19 -> 0.025232039 | G17: =Financials!H25/Financials!H$19 -> 0.015651457 | H17: =Financials!I25/Financials!I$19 -> 0.017911356 | I17: =Financials!J25/Financials!J$19 -> 0.024107362 | J17: =Financials!K25/Financials!K$19 -> 0.086788182 | K17: =Financials!L25/Financials!L$19 -> 0.10058563 | L17: =Financials!M25/Financials!M$19 -> 0.11004936 | M17: =Financials!N25/Financials!N$19 -> 0.1202805 | N17: =Financials!O25/Financials!O$19 -> 0.13097117
C18: Finance Costs | F18: =Financials!G26/Financials!G$19 -> 0.024943279 | G18: =Financials!H26/Financials!H$19 -> 0.018760979 | H18: =Financials!I26/Financials!I$19 -> 0.00086393089 | I18: =Financials!J26/Financials!J$19 -> 0.0040191241 | J18: =Financials!K26/Financials!K$19 -> 0.017223169 | K18: =Financials!L26/Financials!L$19 -> 0.023978166 | L18: =Financials!M26/Financials!M$19 -> 0.021863252 | M18: =Financials!N26/Financials!N$19 -> 0.021146331 | N18: =Financials!O26/Financials!O$19 -> 0.020266499
C19: Depreciation & Amotization Expenses | F19: =Financials!G27/Financials!G$19 -> 0.024723273 | G19: =Financials!H27/Financials!H$19 -> 0.0066344176 | H19: =Financials!I27/Financials!I$19 -> 0.0074514039 | I19: =Financials!J27/Financials!J$19 -> 0.01193039 | J19: =Financials!K27/Financials!K$19 -> 0.032 | K19: =Financials!L27/Financials!L$19 -> 0.017 | L19: =Financials!M27/Financials!M$19 -> 0.0153 | M19: =Financials!N27/Financials!N$19 -> 0.0136 | N19: =Financials!O27/Financials!O$19 -> 0.0119
C20: Mining, Royalty And Freight Expenses | F20: =Financials!G28/Financials!G$19 -> 0 | G20: =Financials!H28/Financials!H$19 -> 0 | H20: =Financials!I28/Financials!I$19 -> 0.49277066 | I20: =Financials!J28/Financials!J$19 -> 0.49079381 | J20: =Financials!K28/Financials!K$19 -> 0.35795612 | K20: =Financials!L28/Financials!L$19 -> 0.3556082 | L20: =Financials!M28/Financials!M$19 -> 0.35423847 | M20: =Financials!N28/Financials!N$19 -> 0.3593264 | N20: =Financials!O28/Financials!O$19 -> 0.36215028
C21: Other Expenses | F21: =Financials!G29/Financials!G$19 -> 0.30352699 | G21: =Financials!H29/Financials!H$19 -> 0.57333483 | H21: =Financials!I29/Financials!I$19 -> 0.082727466 | I21: =Financials!J29/Financials!J$19 -> 0.07016487 | J21: =Financials!K29/Financials!K$19 -> 0.10133637 | K21: =Financials!L29/Financials!L$19 -> 0.068146982 | L21: =Financials!M29/Financials!M$19 -> 0.070039558 | M21: =Financials!N29/Financials!N$19 -> 0.067607849 | N21: =Financials!O29/Financials!O$19 -> 0.039096244
C22: Total Expenses | F22: =Financials!G30/Financials!G$19 -> 0.80863527 | G22: =Financials!H30/Financials!H$19 -> 0.77018377 | H22: =Financials!I30/Financials!I$19 -> 0.73739239 | I22: =Financials!J30/Financials!J$19 -> 0.72003302 | J22: =Financials!K30/Financials!K$19 -> 0.72616608 | K22: =Financials!L30/Financials!L$19 -> 0.72825006 | L22: =Financials!M30/Financials!M$19 -> 0.73701761 | M22: =Financials!N30/Financials!N$19 -> 0.78506316 | N22: =Financials!O30/Financials!O$19 -> 0.79436183
C24: Profit / (Loss) Before Execptional Items & Tax | F24: =Financials!G32/Financials!G$19 -> 0.19136473 | G24: =Financials!H32/Financials!H$19 -> 0.22981623 | H24: =Financials!I32/Financials!I$19 -> 0.26260761 | I24: =Financials!J32/Financials!J$19 -> 0.27996698 | J24: =Financials!K32/Financials!K$19 -> 0.27383392 | K24: =Financials!L32/Financials!L$19 -> 0.27174994 | L24: =Financials!M32/Financials!M$19 -> 0.26298239 | M24: =Financials!N32/Financials!N$19 -> 0.21493684 | N24: =Financials!O32/Financials!O$19 -> 0.20563817
C25: Exceptional Items | F25: =Financials!G33/Financials!G$19 -> 0.070622207 | G25: =Financials!H33/Financials!H$19 -> 0.34452819 | H25: =Financials!I33/Financials!I$19 -> 0 | I25: =Financials!J33/Financials!J$19 -> 0 | J25: =Financials!K33/Financials!K$19 -> 0 | K25: =Financials!L33/Financials!L$19 -> 0 | L25: =Financials!M33/Financials!M$19 -> 0 | M25: =Financials!N33/Financials!N$19 -> 0 | N25: =Financials!O33/Financials!O$19 -> 0
C26: Profit / (Loss) Before Tax | F26: =Financials!G34/Financials!G$19 -> 0.12074252 | G26: =Financials!H34/Financials!H$19 -> -0.11471197 | H26: =Financials!I34/Financials!I$19 -> 0.26260761 | I26: =Financials!J34/Financials!J$19 -> 0.27996698 | J26: =Financials!K34/Financials!K$19 -> 0.27383392 | K26: =Financials!L34/Financials!L$19 -> 0.27174994 | L26: =Financials!M34/Financials!M$19 -> 0.26298239 | M26: =Financials!N34/Financials!N$19 -> 0.21493684 | N26: =Financials!O34/Financials!O$19 -> 0.20563817
... C29: Profit For The Period | F29: =Financials!G37/Financials!G$19 -> 0.13381918 | G29: =Financials!H37/Financials!H$19 -> -0.083230211 | H29: =Financials!I37/Financials!I$19 -> 0.18905181 | I29: =Financials!J37/Financials!J$19 -> 0.21408554 | J29: =Financials!K37/Financials!K$19 -> 0.20998167 | K29: =Financials!L37/Financials!L$19 -> 0.20831652 | L29: =Financials!M37/Financials!M$19 -> 0.1977873 | M29: =Financials!N37/Financials!N$19 -> 0.14560544 | N29: =Financials!O37/Financials!O$19 -> 0.13117985
C30: =Financials!C38
B31: # | C31: Trend Analysis | F31: 44651 | G31: =EOMONTH(F31,12) -> 45016 | H31: =EOMONTH(G31,12) -> 45382 | I31: =EOMONTH(H31,12) -> 45747 | J31: =EOMONTH(I31,12) -> 46112 | K31: =EOMONTH(J31,12) -> 46477 | L31: =EOMONTH(K31,12) -> 46843 | M31: =EOMONTH(L31,12) -> 47208 | N31: =EOMONTH(M31,12) -> 47573
C33: Gross Sales From Operations | F33: 0 | G33: =Financials!H16/Financials!G16-1 -> 3.8635269 | H33: =Financials!I16/Financials!H16-1 -> 0.91050051 | I33: =Financials!J16/Financials!I16-1 -> 0.022419345 | J33: =Financials!K16/Financials!J16-1 -> 1.1786002 | K33: =Financials!L16/Financials!K16-1 -> 0.3 | L33: =Financials!M16/Financials!L16-1 -> 0.25 | M33: =Financials!N16/Financials!M16-1 -> 0.2 | N33: =Financials!O16/Financials!N16-1 -> 0.18
C34: Gross Operating Revenues | F34: 0 | G34: 0 | H34: 0 | I34: =Financials!J17/Financials!I17-1 -> 1.1789643 | J34: =Financials!K17/Financials!J17-1 -> 2.7282574 | K34: =Financials!L17/Financials!K17-1 -> 0.8 | L34: =Financials!M17/Financials!L17-1 -> 0.75 | M34: =Financials!N17/Financials!M17-1 -> 0.7 | N34: =Financials!O17/Financials!N17-1 -> 0.68
C35: Other Income | F35: 0 | G35: =Financials!H18/Financials!G18-1 -> 1.5028571 | H35: =Financials!I18/Financials!H18-1 -> -0.32917002 | I35: =Financials!J18/Financials!I18-1 -> 0.025425425 | J35: =Financials!K18/Financials!J18-1 -> 3.7088377 | K35: =Financials!L18/Financials!K18-1 -> 0.1 | L35: =Financials!M18/Financials!L18-1 -> 0.15 | M35: =Financials!N18/Financials!M18-1 -> 0.2 | N35: =Financials!O18/Financials!N18-1 -> 0.12
C36: Total Income | F36: 0 | G36: =Financials!H19/Financials!G19-1 -> 3.7669577 | H36: =Financials!I19/Financials!H19-1 -> 0.8964627 | I36: =Financials!J19/Financials!I19-1 -> 0.030118943 | J36: =Financials!K19/Financials!J19-1 -> 1.2194936 | K36: =Financials!L19/Financials!K19-1 -> 0.30858332 | L36: =Financials!M19/Financials!L19-1 -> 0.264872 | M36: =Financials!N19/Financials!M19-1 -> 0.22244206 | N36: =Financials!O19/Financials!N19-1 -> 0.210487
C38: Expenses:
C39: Cost Of Materials Consumed | F39: 0 | G39: =Financials!H22/Financials!G22-1 -> 0.35116672 | H39: =Financials!I22/Financials!H22-1 -> 0.063983345 | I39: =Financials!J22/Financials!I22-1 -> -0.0059818866 | J39: =Financials!K22/Financials!J22-1 -> 2.0845316 | K39: =Financials!L22/Financials!K22-1 -> 0.4 | L39: =Financials!M22/Financials!L22-1 -> 0.45 | M39: =Financials!N22/Financials!M22-1 -> 0.48 | N39: =Financials!O22/Financials!N22-1 -> 0.45
C40: Purchases Of Stock-In-Trade | F40: 0 | G40: 0 | H40: 0 | I40: =Financials!J23/Financials!I23-1 -> -0.50776544 | J40: =Financials!K23/Financials!J23-1 -> 2.4259584 | K40: =Financials!L23/Financials!K23-1 -> 0.25 | L40: =Financials!M23/Financials!L23-1 -> 0.23 | M40: =Financials!N23/Financials!M23-1 -> 0.21 | N40: =Financials!O23/Financials!N23-1 -> 0.2
C41: Changes In Inventories Of Finished Goods | F41: 0 | G41: =Financials!H24/Financials!G24-1 -> -1.5923841 | H41: =Financials!I24/Financials!H24-1 -> -1.4161543 | I41: =Financials!J24/Financials!I24-1 -> -7.0718603 | J41: =Financials!K24/Financials!J24-1 -> -4.3466799 | K41: =Financials!L24/Financials!K24-1 -> -1.4 | L41: =Financials!M24/Financials!L24-1 -> -2.5 | M41: =Financials!N24/Financials!M24-1 -> -1.4 | N41: =Financials!O24/Financials!N24-1 -> -2.3
C42: Employee Benefit Expenses | F42: 0 | G42: =Financials!H25/Financials!G25-1 -> 1.9569482 | H42: =Financials!I25/Financials!H25-1 -> 1.1702912 | I42: =Financials!J25/Financials!I25-1 -> 0.38646399 | J42: =Financials!K25/Financials!J25-1 -> 6.9903316 | K42: =Financials!L25/Financials!K25-1 -> 0.51661988 | L42: =Financials!M25/Financials!L25-1 -> 0.38387905 | M42: =Financials!N25/Financials!M25-1 -> 0.33609083 | N42: =Financials!O25/Financials!N25-1 -> 0.31807657
C43: Finance Costs | F43: 0 | G43: =Financials!H26/Financials!G26-1 -> 2.5854465 | H43: =Financials!I26/Financials!H26-1 -> -0.91266913 | I43: =Financials!J26/Financials!I26-1 -> 3.7922535 | J43: =Financials!K26/Financials!J26-1 -> 8.5112049 | K43: =Financials!L26/Financials!K26-1 -> 0.82181507 | L43: =Financials!M26/Financials!L26-1 -> 0.15330818 | M43: =Financials!N26/Financials!M26-1 -> 0.18235678 | N43: =Financials!O26/Financials!N26-1 -> 0.16012247
C44: Depreciation & Amotization Expenses | F44: 0 | G44: =Financials!H27/Financials!G27-1 -> 0.27919911 | H44: =Financials!I27/Financials!H27-1 -> 1.13 | I44: =Financials!J27/Financials!I27-1 -> 0.64931619 | J44: =Financials!K27/Financials!J27-1 -> 4.9531828 | K44: =Financials!L27/Financials!K27-1 -> -0.30481511 | L44: =Financials!M27/Financials!L27-1 -> 0.1383848 | M44: =Financials!N27/Financials!M27-1 -> 0.086615165 | N44: =Financials!O27/Financials!N27-1 -> 0.059176125
C45: Mining, Royalty And Freight Expenses | F45: 0 | G45: 0 | H45: 0 | I45: =Financials!J28/Financials!I28-1 -> 0.025986413 | J45: =Financials!K28/Financials!J28-1 -> 0.61876798 | K45: =Financials!L28/Financials!K28-1 -> 0.3 | L45: =Financials!M28/Financials!L28-1 -> 0.26 | M45: =Financials!N28/Financials!M28-1 -> 0.24 | N45: =Financials!O28/Financials!N28-1 -> 0.22
C46: Other Expenses | F46: 0 | G46: =Financials!H29/Financials!G29-1 -> 8.004349 | H46: =Financials!I29/Financials!H29-1 -> -0.72635614 | I46: =Financials!J29/Financials!I29-1 -> -0.12630998 | J46: =Financials!K29/Financials!J29-1 -> 2.2055275 | K46: =Financials!L29/Financials!K29-1 -> -0.12 | L46: =Financials!M29/Financials!L29-1 -> 0.3 | M46: =Financials!N29/Financials!M29-1 -> 0.18 | N46: =Financials!O29/Financials!N29-1 -> -0.3
C47: Total Expenses | F47: 0 | G47: =Financials!H30/Financials!G30-1 -> 3.5402836 | H47: =Financials!I30/Financials!H30-1 -> 0.81571881 | I47: =Financials!J30/Financials!I30-1 -> 0.0058683267 | J47: =Financials!K30/Financials!J30-1 -> 1.2383987 | K47: =Financials!L30/Financials!K30-1 -> 0.31233874 | L47: =Financials!M30/Financials!L30-1 -> 0.28010005 | M47: =Financials!N30/Financials!M30-1 -> 0.30213202 | N47: =Financials!O30/Financials!N30-1 -> 0.22482461
C49: Profit / (Loss) Before Execptional Items & Tax | F49: 0 | G49: =Financials!H32/Financials!G32-1 -> 4.724797 | H49: =Financials!I32/Financials!H32-1 -> 1.1670599 | I49: =Financials!J32/Financials!I32-1 -> 0.098213769 | J49: =Financials!K32/Financials!J32-1 -> 1.1708725 | K49: =Financials!L32/Financials!K32-1 -> 0.29862451 | L49: =Financials!M32/Financials!L32-1 -> 0.22406307 | M49: =Financials!N32/Financials!M32-1 -> -0.00089190171 | N49: =Financials!O32/Financials!N32-1 -> 0.15811845
C50: Exceptional Items | F50: 0 | G50: =Financials!H33/Financials!G33-1 -> 22.255452 | H50: =Financials!I33/Financials!H33-1 -> -1 | I50: 0 | J50: 0 | K50: 0 | L50: 0 | M50: 0 | N50: 0
C51: Profit / (Loss) Before Tax | F51: 0 | G51: =Financials!H34/Financials!G34-1 -> -5.5288691 | H51: =Financials!I34/Financials!H34-1 -> -5.3415309 | I51: =Financials!J34/Financials!I34-1 -> 0.098213769 | J51: =Financials!K34/Financials!J34-1 -> 1.1708725 | K51: =Financials!L34/Financials!K34-1 -> 0.29862451 | L51: =Financials!M34/Financials!L34-1 -> 0.22406307 | M51: =Financials!N34/Financials!M34-1 -> -0.00089190171 | N51: =Financials!O34/Financials!N34-1 -> 0.15811845
C52: Current Tax | F52: 0 | G52: 0 | H52: 0 | I52: =Financials!J35/Financials!I35-1 -> 0.75810301 | J52: =Financials!K35/Financials!J35-1 -> 1.1015356 | K52: =Financials!L35/Financials!K35-1 -> 0.3 | L52: =Financials!M35/Financials!L35-1 -> 0.3 | M52: =Financials!N35/Financials!M35-1 -> 0.3 | N52: =Financials!O35/Financials!N35-1 -> 0.3
C53: Deferred Tax Income / (Expenses) | F53: 0 | G53: =Financials!H36/Financials!G36-1 -> 10.476341 | H53: =Financials!I36/Financials!H36-1 -> -3.0507605 | I53: =Financials!J36/Financials!I36-1 -> -1.0470467 | J53: =Financials!K36/Financials!J36-1 -> -1 | K53: 0 | L53: 0 | M53: 0 | N53: 0
C54: Profit For The Period | F54: 0 | G54: =Financials!H37/Financials!G37-1 -> -3.9648582 | H54: =Financials!I37/Financials!H37-1 -> -5.307687 | I54: =Financials!J37/Financials!I37-1 -> 0.16652453 | J54: =Financials!K37/Financials!J37-1 -> 1.1769475 | K54: =Financials!L37/Financials!K37-1 -> 0.29820625 | L54: =Financials!M37/Financials!L37-1 -> 0.2009399 | M54: =Financials!N37/Financials!M37-1 -> -0.10007257 | N54: =Financials!O37/Financials!N37-1 -> 0.090560221
B56: # | C56: End

Sheet Data->

Sheet Input
A1: Do not make changes in this sheet
A3: Assets | B3: 22 | C3: 23 | D3: 24 | E3: 25
A4: Non-Current Assets
A5: Property, Plant & Equipment | B5: 399.06 | C5: 474.6 | D5: 1156.75 | E5: 1531.51
A6: Capital Work in Progress | B6: 85.88 | C6: 373.1 | D6: 1268.15 | E6: 4181.07
A7: Right to use account | B7: 0.6 | C7: 57.77 | D7: 77.95 | E7: 81
A8: Financial Assest
A9: Investment | B9: 0.14 | C9: 0.04 | D9: 0.04 | E9: 0.04
A10: Loans | B10: 0 | C10: 0 | D10: 0 | E10: 32.34
A11: Deferred tax assets (net) | B11: 28.24 | C11: 137.38 | D11: 0.04 | E11: 0.2
A12: Other Non-current assets | B12: 0.87 | C12: 36.32 | D12: 307.19 | E12: 570.55
A13: Total Non-current assets | B13: =SUM(B5:B12) -> 514.79 | C13: =SUM(C5:C12) -> 1079.21 | D13: =SUM(D5:D12) -> 2810.12 | E13: =SUM(E5:E12) -> 6396.71
A15: Current Assets
A16: Inventories | B16: 166.84 | C16: 269.75 | D16: 231.09 | E16: 431.76
A17: Financial Assets
A18: Investments | B18: 0 | C18: 36.79 | D18: 29.03 | E18: 75.06
A19: Trade receivables | B19: 23.7367 | C19: 24.51 | D19: 79.91 | E19: 171.42
A20: Cash and cash equivalents | B20: 13.73 | C20: 27.58 | D20: 2.59 | E20: 39.95
A21: Bank balances Other than above | B21: 8.14 | C21: 236.98 | D21: 284.54 | E21: 699.32
A22: Loans & Advances | B22: 0 | C22: 25.07 | D22: 1.5 | E22: 250.83
A23: Other current assets | B23: 96.49 | C23: 326.14 | D23: 498.76 | E23: 1351.85
A24: Total Current assets | B24: =SUM(B16:B23) -> 308.9367 | C24: =SUM(C16:C23) -> 946.82 | D24: =SUM(D16:D23) -> 1127.42 | E24: =SUM(E16:E23) -> 3020.19
A25: Total Assets | B25: =B13+B24 -> 823.7267 | C25: =C13+C24 -> 2026.03 | D25: =D13+D24 -> 3937.54 | E25: =E13+E24 -> 9416.9
A27: Equity
A28: Equity Share capital | B28: 37.04 | C28: 50.48 | D28: 50.53 | E28: 52.32
A29: Other Equity | B29: 444.54 | C29: 1478.47 | D29: 2760.34 | E29: 6349.8
A30: Total Equity | B30: =SUM(B28:B29) -> 481.58 | C30: =SUM(C28:C29) -> 1528.95 | D30: =SUM(D28:D29) -> 2810.87 | E30: =SUM(E28:E29) -> 6402.12
A32: Non-current Liabilities
A33: Financial liabilities
A34: Borrowings | B34: 56.72 | C34: 0 | D34: 0 | E34: 753.91
A35: Lease liability | B35: 0.43 | C35: 2.19 | D35: 29.44 | E35: 35.92
A36: Provisions | B36: 5.36 | C36: 22.56 | D36: 24.89 | E36: 35.01
A37: Other non-current liabilities | B37: 161.43 | C37: 0 | D37: 86.4 | E37: 75.72
A38: Total Non-current liabilities | B38: =SUM(B34:B37) -> 223.94 | C38: =SUM(C34:C37) -> 24.75 | D38: =SUM(D34:D37) -> 140.73 | E38: =SUM(E34:E37) -> 900.56
A40: Current Liabilities
A41: Financial liabilities
A42: Borrowings | B42: 0 | C42: 0 | D42: 0 | E42: 1.84
A43: Lease liability | B43: 0.21 | C43: 0.61 | D43: 3.69 | E43: 3.5
A44: Trade Payables | B44: 15.18 | C44: 74.53 | D44: =7.04+388.04 -> 395.08 | E44: 36.28
A45: Other financial liabilities | B45: 74.47 | C45: 1.57 | D45: 0 | E45: 0
A46: Other current liabilities | B46: 14.42 | C46: 383.49 | D46: 308.39 | E46: 1334.43
A47: Provisions | B47: 13.93 | C47: 12.13 | D47: 18.99 | E47: 21.67
A48: Current tax liabilities (net) | B48: 0 | C48: 0 | D48: 259.79 | E48: 716.5
A49: Total Current liabilties | B49: =SUM(B42:B48) -> 118.21 | C49: =SUM(C42:C48) -> 472.33 | D49: =SUM(D42:D48) -> 985.94 | E49: =SUM(E42:E48) -> 2114.22
A50: Total Equity and Liabilities | B50: =B30+B38+B49 -> 823.73 | C50: =C30+C38+C49 -> 2026.03 | D50: =D30+D38+D49 -> 3937.54 | E50: =E30+E38+E49 -> 9416.9
A52: Income Statement
A53: Gross sales from operations | B53: 697.5 | C53: 3392.31 | D53: 6481.01 | E53: 6626.31
A54: Gross operating revenues | B54: 0 | C54: 0 | D54: 43.64 | E54: 95.09
A55: Other income | B55: 29.75 | C55: 74.46 | D55: 49.95 | E55: 51.22
A56: Total Income | B56: =SUM(B53:B55) -> 727.25 | C56: =SUM(C53:C55) -> 3466.77 | D56: =SUM(D53:D55) -> 6574.6 | E56: =SUM(E53:E55) -> 6772.62
A58: Expenses:
A59: Cost of materials consumed | B59: 373.27 | C59: 504.35 | D59: 536.62 | E59: 533.41
A60: purchases of stock-in-trade | C60: 0 | D60: 370.23 | E60: 182.24
A61: Changes in inventories of finished goods | B61: -60.4 | C61: 35.78 | D61: -14.89 | E61: 90.41
A62: Employee benefit expenses | B62: 18.35 | C62: 54.26 | D62: 117.76 | E62: 163.27
A63: finance costs | B63: 18.14 | C63: 65.04 | D63: 5.68 | E63: 27.22
A64: depreciation & amotization expenses | B64: 17.98 | C64: 23 | D64: 48.99 | E64: 80.8
A65: mining, royalty and freight expenses | B65: 0 | C65: 0 | D65: 3239.77 | E65: 3323.96
A66: other expenses | B66: 220.74 | C66: 1987.62 | D66: 543.9 | E66: 475.2
A67: Total expenses | B67: =SUM(B59:B66) -> 588.08 | C67: =SUM(C59:C66) -> 2670.05 | D67: =SUM(D59:D66) -> 4848.06 | E67: =SUM(E59:E66) -> 4876.51
A69: profit / (loss) before execptional items and tax | B69: =B56-B67 -> 139.17 | C69: =C56-C67 -> 796.72 | D69: =D56-D67 -> 1726.54 | E69: =E56-E67 -> 1896.11
A70: exceptional items | B70: 51.36 | C70: 1194.4 | D70: 0 | E70: 0
A71: profit / (loss) before tax | B71: =B69-B70 -> 87.81 | C71: =C69-C70 -> -397.68 | D71: =D69-D70 -> 1726.54 | E71: =E69-E70 -> 1896.11
A72: current tax | B72: 0 | C72: 0 | D72: -259.78 | E72: -456.72
A73: deferred tax income / (expenses) | B73: 9.51 | C73: 109.14 | D73: -223.82 | E73: 10.53
A74: Profit for the period | B74: =B71+B72+B73 -> 97.32 | C74: =C71+C72+C73 -> -288.54 | D74: =D71+D72+D73 -> 1242.94 | E74: =E71+E72+E73 -> 1449.92
