Workbook
Name UPDATE: 'Data Sheet'!$E$1

Sheet Research_Paper
D3: April 22, 2026
D5: UltraTech Cement
D7: NSE: ULTRACEMCO | BSE: 532538
D8: Sector: Construction Materials - Cement | Country: India
D11: About The Company
N12: Stock Data (As on April 22, 2026)
N13: Nifty | Q13: 24378.1
N14: CMP | Q14: 12039
N15: 52-week High/Low | Q15: ₹ 13,110/10,325
N16: Market Cap (₹ Cr.) | Q16: 359505
D17: Analyst Rating | N17: Outstanding Shares (Cr.) | Q17: 29.47
N18: Div yield (%) | Q18: 0.0064
N19: P/E Ratio | Q19: 46.3
N20: EPS (FY25 A) | Q20: =DCF!I28/Inc_Stat!O36 -> 191.47947
N21: EPS (FY26 E) | Q21: =DCF!K28/Inc_Stat!O36 -> 252.57601
D22: Key Assumptions
N23: Recommendation (As on April 22, 2026)
N24: Rating | Q24: HOLD
N25: Last Price | Q25: 12039
N26: Target Price | Q26: 13500
N27: Implied Upside | Q27: =Q26/Q25-1 -> 0.12135559
N29: Stock Performance
D32: Exhibit 1: Scale & Network [1] | I32: Figure 1: Operational Production (MMT)
D33: Particulars
D34: Installed capacity in India (MTPA) | G34: 200+ MTPA
D35: Global Capacity | G35: 205.5 MTPA
D36: Production (MMT) | G36: 34
D37: Grinding Units | G37: 35
D38: Bulk Terminals | G38: 10
D39: Channel Partner Network | G39: 145000
D40: India Market Coverage | G40: 0.8
D41: Grey Cement Market Share | G41: 0.262
D42: MTPA – Million Metric Tonnes Per Annum | I42: MMT - Million Metric Tonnes
P43: 3M | Q43: 1Y
N44: Absolute Return | P44: =AVERAGE(StockData!E4:E268) -> 0.00047400547 | Q44: =AVERAGE(StockData!F4:F268) -> 0.00015240775
N46: Shareholding Pattern (As on April 22, 2026)
N47: Promoters | Q47: 0.5933
N48: FII + DII | Q48: =13.61%+18.42% -> 0.3203
N49: Others | Q49: =0.05%+8.41%+0.17% -> 0.0863
Q50: Prepared By: Eldric Gregory Sequeira
Q51: LinkedIn: Eldric Sequeira
D55: Recent Financial Performance
D56: Q3 FY26 Results (Quarter Ended December 31, 2025 | Announced January 24, 2026) | M56: Figure 2: Sales Volume - Grey Cement (MMT)
D61: Exhibit 2: Q3 Results and Quarterly Comparison [2]
D62: Fiscal Period | F62: 45992 | G62: 45901 | I62: QoQ Comp | J62: 45627 | K62: YoY Comp
D63: Revenue | F63: 21506 | G63: 19371 | I63: =F63/G63-1 -> 0.1102163 | J63: 17555 | K63: =F63/J63-1 -> 0.22506408
D64: Operating Income | F64: 2644.11 | G64: 1047.51 | I64: =F64/G64-1 -> 1.5241859 | J64: 1901.95 | K64: =F64/J64-1 -> 0.39021005
D65: PAT | F65: 1725.4 | G65: 702.82 | I65: =F65/G65-1 -> 1.4549671 | J65: 1359.43 | K65: =F65/J65-1 -> 0.26920842
D66: Diluted EPS | F66: 60.92 | G66: 23.89 | I66: =F66/G66-1 -> 1.5500209 | J66: 46.17 | K66: =F66/J66-1 -> 0.31947152
M67: MMT - Million Metric Tonnes
D68: Key Operational Highlights (Q3 FY26)
D76: Industry Outlook
D77: India Cement Demand Drivers
D85: Industry-Level Demand and Pricing | N85: Figure 3: Net Revenue (₹ in Cr.)
D90: Financial Analysis
D93: Exhibit 3: Financial Summary [4]
D94: Fiscal Period | F94: FY23 A | G94: FY24 A | I94: FY25 A | J94: FY26 E | K94: FY27 E | L94: FY28 E
D95: Revenue | F95: 63239.98 | G95: 70908.14 | I95: 75955.13 | J95: 88297.839 | K95: 98937.728 | L95: 110038.54
D96: % Growth | F96: 0.20230773 | G96: 0.12125494 | I96: 0.071176454 | J96: 0.1625 | K96: 0.1205 | L96: 0.1122 | N96: Figure 4:PAT (₹ in Cr.) - Earnings per Share (₹)
D97: EBITDA | F97: 10619.85 | G97: 12978.56 | I97: 12796.88 | J97: 15992.979 | K97: 17920.133 | L97: 19930.772
D98: % Margin | F98: 0.16792937 | G98: 0.18303343 | I98: 0.16847947 | J98: 0.18112537 | K98: 0.18112537 | L98: 0.18112537
D99: EBITDA/Tonne | F99: =F97/104.09*10 -> 1020.2565 | G99: =G97/117.2*10 -> 1107.3857 | I99: =I97/133.14*10 -> 961.15968 | J99: =J97/151.24*10 -> 1057.4569 | K99: =K97/171.81*10 -> 1043.0204 | L99: =L97/195.18*10 -> 1021.1483
D100: % Margin | F100: =F99/F95 -> 0.016133093 | G100: =G99/G95 -> 0.015617187 | I100: =I99/I95 -> 0.012654309 | J100: =J99/J95 -> 0.011976023 | K100: =K99/K95 -> 0.01054219 | L100: =L99/L95 -> 0.0092799145
D101: EBIT | F101: 7731.86 | G101: 9833.26 | I101: 8781.93 | J101: 11325.599 | K101: 12690.334 | L101: 14114.19
D102: % Margin | F102: 0.12226221 | G102: 0.13867604 | I102: 0.11561997 | J102: 0.12826587 | K102: 0.12826587 | L102: 0.12826587
D103: PAT | F103: 4566.29 | G103: 6447 | I103: 5642.9 | J103: 7443.415 | K103: 8340.3465 | L103: 9276.1333
D104: % Margin | F104: 0.072205747 | G104: 0.09092045 | I104: 0.074292546 | J104: 0.084298949 | K104: 0.084298949 | L104: 0.084298949
D105: EPS | F105: =DCF!G28/Inc_Stat!$O$36 -> 154.94706 | G105: =DCF!H28/Inc_Stat!$O$36 -> 218.76485 | I105: =DCF!I28/Inc_Stat!$O$36 -> 191.47947 | J105: =DCF!K28/Inc_Stat!$O$36 -> 252.57601 | K105: =DCF!L28/Inc_Stat!$O$36 -> 283.01142 | L105: =DCF!M28/Inc_Stat!$O$36 -> 314.7653
D106: % Growth | F106: =Inc_Stat!M39 -> -0.31486775 | G106: =G105/F105-1 -> 0.41186828 | I106: =I105/G105-1 -> -0.12472468 | J106: =J105/I105-1 -> 0.31907618 | K106: =K105/J105-1 -> 0.1205 | L106: =L105/K105-1 -> 0.1122
D114: Exhibit 4: Key Ratios [4] | K114: Figure 5: Return on Equity (%) | O114: Figure 6: Return on Equity (%)
D115: Fiscal Period | F115: FY23 A | G115: FY24 A | I115: FY25 A
D116: ROE | F116: =Ratio!L13 -> 0.13214621 | G116: =Ratio!M13 -> 0.084055751 | I116: =Ratio!O13 -> 0.079807068
D117: ROA | F117: =Ratio!L14 -> 0.079521722 | G117: =Ratio!M14 -> 0.049970125 | I117: =Ratio!O14 -> 0.042227142
D118: ROCE | F118: =Ratio!L15 -> 0.099994449 | G118: =Ratio!M15 -> 0.064737932 | I118: =Ratio!O15 -> 0.053017335
D119: Debt-to-Equity | F119: =Ratio!M35 -> 0.20353428 | G119: =Ratio!N35 -> 0.18934715 | I119: =Ratio!O35 -> 0.34087148
D120: Interest Coverage | F120: =Ratio!M39 -> 8.397924 | G120: =Ratio!N39 -> 9.1583264 | I120: =Ratio!O39 -> 4.3206405
D121: Current Ratio | F121: =Ratio!M20 -> 1.6524685 | G121: =Ratio!N20 -> 1.6173013 | I121: =Ratio!O20 -> 1.3366727
D122: Asset Turnover | F122: =Ratio!M27 -> 0.69205191 | G122: =Ratio!N27 -> 0.70347394 | I122: =Ratio!O27 -> 0.56839003
D125: Valuation
D126: DCF Analysis
D130: Exhibit 5: DCF Model Analysis
D165: Sensitivity Analysis
D170: Exhibit 6: Sensitivity Analysis
D188: Public Comparables (Trading Comps)
D192: Exhibit 7: Public Comparables
D217: Exhibit 8: Weighted Average Cost of Capital
D243: Recommendation & Conclusion
D244: Rating: HOLD | Target Price: ₹13,500 | Upside: ~12%
D256: Bibliography
D257: (1) UltraTech Cement Limited — Annual General Meeting Highlights, Financial Express, August 20, 2025.
... D266: -------------------- End of paper ---------------------

Sheet Data Sheet->

Sheet Historical FS
B1: Company Name | C1: ='Data Sheet'!B1 -> ULTRATECH CEMENT LTD
B2: Ticker | C2: ULTRACEMCO | F2: PLEASE DO NOT MAKE ANY CHANGES TO THIS SHEET
B4: Figures in Cr.
B5: Number of shares | C5: ='Data Sheet'!B6 -> 29.482018
B6: Face Value | C6: ='Data Sheet'!B7 -> 10
B7: Current Price | C7: ='Data Sheet'!B8 -> 12039
B8: Market Capitalization | C8: ='Data Sheet'!B9 -> 354934.02
B10: ="Historical Financial Statement - "&C1 -> Historical Financial Statement - ULTRATECH CEMENT LTD
B11: Years | C11: ='Data Sheet'!B16 -> 42460 | D11: ='Data Sheet'!C16 -> 42825 | E11: ='Data Sheet'!D16 -> 43190 | F11: ='Data Sheet'!E16 -> 43555 | G11: ='Data Sheet'!F16 -> 43921 | H11: ='Data Sheet'!G16 -> 44286 | I11: ='Data Sheet'!H16 -> 44651 | J11: ='Data Sheet'!I16 -> 45016 | ... L11: ='Data Sheet'!K16 -> 45747 | M11: LTM
B12: Figures in Cr.
A13: # | B13: Income Statement
B14: Revenue | C14: =IFERROR('Data Sheet'!B17,0) -> 25153.24 | D14: =IFERROR('Data Sheet'!C17,0) -> 25374.94 | E14: =IFERROR('Data Sheet'!D17,0) -> 30978.62 | F14: =IFERROR('Data Sheet'!E17,0) -> 41462.26 | G14: =IFERROR('Data Sheet'!F17,0) -> 42429.89 | H14: =IFERROR('Data Sheet'!G17,0) -> 44725.8 | I14: =IFERROR('Data Sheet'!H17,0) -> 52598.83 | J14: =IFERROR('Data Sheet'!I17,0) -> 63239.98 | ... L14: =IFERROR('Data Sheet'!K17,0) -> 75955.13 | M14: =IFERROR(SUM('Data Sheet'!I42:K42),0) -> 62712.06
B15: Expenses | C15: =IFERROR(SUM('Data Sheet'!B18,'Data Sheet'!B20:B22)-1*'Data Sheet'!B19,0) -> 12397.13 | D15: =IFERROR(SUM('Data Sheet'!C18,'Data Sheet'!C20:C22)-1*'Data Sheet'!C19,0) -> 12303.62 | E15: =IFERROR(SUM('Data Sheet'!D18,'Data Sheet'!D20:D22)-1*'Data Sheet'!D19,0) -> 15744.19 | F15: =IFERROR(SUM('Data Sheet'!E18,'Data Sheet'!E20:E22)-1*'Data Sheet'!E19,0) -> 21729.72 | G15: =IFERROR(SUM('Data Sheet'!F18,'Data Sheet'!F20:F22)-1*'Data Sheet'!F19,0) -> 20600.87 | H15: =IFERROR(SUM('Data Sheet'!G18,'Data Sheet'!G20:G22)-1*'Data Sheet'!G19,0) -> 20847.7 | I15: =IFERROR(SUM('Data Sheet'!H18,'Data Sheet'!H20:H22)-1*'Data Sheet'!H19,0) -> 26536.92 | J15: =IFERROR(SUM('Data Sheet'!I18,'Data Sheet'!I20:I22)-1*'Data Sheet'!I19,0) -> 35301.93 | ... L15: =IFERROR(SUM('Data Sheet'!K18,'Data Sheet'!K20:K22)-1*'Data Sheet'!K19,0) -> 41216.74 | M15: =IFERROR(SUM('Data Sheet'!I43:K43),0) -> 51306.6
B16: Gross Profit | C16: =C14-C15 -> 12756.11 | D16: =D14-D15 -> 13071.32 | E16: =E14-E15 -> 15234.43 | F16: =F14-F15 -> 19732.54 | G16: =G14-G15 -> 21829.02 | H16: =H14-H15 -> 23878.1 | I16: =I14-I15 -> 26061.91 | J16: =J14-J15 -> 27938.05 | ... M16: =M14-M15 -> 11405.46
B17: SG&A | C17: =IFERROR(SUM('Data Sheet'!B23:B24),0) -> 7855.14 | D17: =IFERROR(SUM('Data Sheet'!C23:C24),0) -> 7858.88 | E17: =IFERROR(SUM('Data Sheet'!D23:D24),0) -> 9089.4 | F17: =IFERROR(SUM('Data Sheet'!E23:E24),0) -> 12385.6 | G17: =IFERROR(SUM('Data Sheet'!F23:F24),0) -> 12583.05 | H17: =IFERROR(SUM('Data Sheet'!G23:G24),0) -> 12310.19 | I17: =IFERROR(SUM('Data Sheet'!H23:H24),0) -> 14547.56 | J17: =IFERROR(SUM('Data Sheet'!I23:I24),0) -> 17318.2 | ... L17: =IFERROR(SUM('Data Sheet'!K23:K24),0) -> 21941.51
B18: EBITDA | C18: =C16-C17 -> 4900.97 | D18: =D16-D17 -> 5212.44 | E18: =E16-E17 -> 6145.03 | F18: =F16-F17 -> 7346.94 | G18: =G16-G17 -> 9245.97 | H18: =H16-H17 -> 11567.91 | I18: =I16-I17 -> 11514.35 | J18: =J16-J17 -> 10619.85 | ... L18: =L16-L17 -> 12796.88 | M18: =IFERROR(SUM('Data Sheet'!I50:K50),0) -> 11405.46
B19: Depreciation | C19: =IFERROR('Data Sheet'!B26,0) -> 1377.17 | D19: =IFERROR('Data Sheet'!C26,0) -> 1348.41 | E19: =IFERROR('Data Sheet'!D26,0) -> 1847.93 | F19: =IFERROR('Data Sheet'!E26,0) -> 2450.73 | G19: =IFERROR('Data Sheet'!F26,0) -> 2722.66 | H19: =IFERROR('Data Sheet'!G26,0) -> 2700.23 | I19: =IFERROR('Data Sheet'!H26,0) -> 2714.75 | J19: =IFERROR('Data Sheet'!I26,0) -> 2887.99 | ... L19: =IFERROR('Data Sheet'!K26,0) -> 4014.95 | M19: =IFERROR(SUM('Data Sheet'!I45:K45),0) -> 3436.36
B20: Interest | C20: =IFERROR('Data Sheet'!B27,0) -> 566.3 | D20: =IFERROR('Data Sheet'!C27,0) -> 640.1 | E20: =IFERROR('Data Sheet'!D27,0) -> 1237.6 | F20: =IFERROR('Data Sheet'!E27,0) -> 1777.86 | G20: =IFERROR('Data Sheet'!F27,0) -> 1991.65 | H20: =IFERROR('Data Sheet'!G27,0) -> 1485.65 | I20: =IFERROR('Data Sheet'!H27,0) -> 944.71 | J20: =IFERROR('Data Sheet'!I27,0) -> 822.72 | ... L20: =IFERROR('Data Sheet'!K27,0) -> 1650.54 | M20: =IFERROR(SUM('Data Sheet'!I46:K46),0) -> 1384.79
B21: Profit Before Tax | C21: =C18-SUM(C19:C20) -> 2957.5 | D21: =D18-SUM(D19:D20) -> 3223.93 | E21: =E18-SUM(E19:E20) -> 3059.5 | F21: =F18-SUM(F19:F20) -> 3118.35 | G21: =G18-SUM(G19:G20) -> 4531.66 | H21: =H18-SUM(H19:H20) -> 7382.03 | I21: =I18-SUM(I19:I20) -> 7854.89 | J21: =J18-SUM(J19:J20) -> 6909.14 | ... M21: =M18-SUM(M19:M20) -> 6584.31
B22: Taxes | C22: =IFERROR('Data Sheet'!B29,0) -> 941.69 | D22: =IFERROR('Data Sheet'!C29,0) -> 1158.54 | E22: =IFERROR('Data Sheet'!D29,0) -> 1077.01 | F22: =IFERROR('Data Sheet'!E29,0) -> 1068.07 | G22: =IFERROR('Data Sheet'!F29,0) -> -568.16 | H22: =IFERROR('Data Sheet'!G29,0) -> 2538.7 | I22: =IFERROR('Data Sheet'!H29,0) -> 1190.06 | J22: =IFERROR('Data Sheet'!I29,0) -> 2342.85 | ... L22: =IFERROR('Data Sheet'!K29,0) -> 1488.49 | M22: =IFERROR(SUM('Data Sheet'!I48:K48),0) -> 1758.32
B23: Effective Tax Rate | C23: =C22/C21 -> 0.31840744 | D23: =D22/D21 -> 0.35935644 | E23: =E22/E21 -> 0.35202157 | F23: =F22/F21 -> 0.34251126 | G23: =G22/G21 -> -0.12537569 | H23: =H22/H21 -> 0.34390269 | I23: =I22/I21 -> 0.15150562 | J23: =J22/J21 -> 0.3390943 | ... M23: =M22/M21 -> 0.26704696
B24: Net Profit | C24: =C21-C22 -> 2015.81 | D24: =D21-D22 -> 2065.39 | E24: =E21-E22 -> 1982.49 | F24: =F21-F22 -> 2050.28 | G24: =G21-G22 -> 5099.82 | H24: =H21-H22 -> 4843.33 | I24: =I21-I22 -> 6664.83 | J24: =J21-J22 -> 4566.29 | ... M24: =M21-M22 -> 4825.99
B26: No of Equity Shares | C26: =IFERROR('Data Sheet'!B93,0) -> 27.44 | D26: =IFERROR('Data Sheet'!C93,0) -> 27.45 | E26: =IFERROR('Data Sheet'!D93,0) -> 27.46 | F26: =IFERROR('Data Sheet'!E93,0) -> 27.46 | G26: =IFERROR('Data Sheet'!F93,0) -> 28.86 | H26: =IFERROR('Data Sheet'!G93,0) -> 28.87 | I26: =IFERROR('Data Sheet'!H93,0) -> 28.87 | J26: =IFERROR('Data Sheet'!I93,0) -> 28.87 | ... L26: =IFERROR('Data Sheet'!K93,0) -> 29.47
B28: Earnings Per Share | C28: =C24/C26 -> 73.462464 | D28: =D24/D26 -> 75.241894 | E28: =E24/E26 -> 72.195557 | F28: =F24/F26 -> 74.664239 | G28: =G24/G26 -> 176.70894 | H28: =H24/H26 -> 167.76342 | I28: =I24/I26 -> 230.8566 | J28: =J24/J26 -> 158.1673 | ... L28: =L24/L26 -> 191.47947
B29: EPS Growth % | D29: =D28/C28-1 -> 0.024222313 | E29: =E28/D28-1 -> -0.040487247 | F29: =F28/E28-1 -> 0.034194372 | G29: =G28/F28-1 -> 1.3667145 | H29: =H28/G28-1 -> -0.050622891 | I29: =I28/H28-1 -> 0.37608422 | J29: =J28/I28-1 -> -0.31486775 | K29: =K28/J28-1 -> 0.41186828 | L29: =L28/K28-1 -> -0.14254501
B31: Dividend Per Share | C31: =IFERROR('Data Sheet'!B31/'Historical FS'!C26,0) -> 9.5010933 | D31: =IFERROR('Data Sheet'!C31/'Historical FS'!D26,0) -> 10.000364 | E31: =IFERROR('Data Sheet'!D31/'Historical FS'!E26,0) -> 10.500364 | F31: =IFERROR('Data Sheet'!E31/'Historical FS'!F26,0) -> 11.501821 | G31: =IFERROR('Data Sheet'!F31/'Historical FS'!G26,0) -> 13.001386 | H31: =IFERROR('Data Sheet'!G31/'Historical FS'!H26,0) -> 36.993419 | I31: =IFERROR('Data Sheet'!H31/'Historical FS'!I26,0) -> 37.99619 | J31: =IFERROR('Data Sheet'!I31/'Historical FS'!J26,0) -> 37.998614 | ... L31: =IFERROR('Data Sheet'!K31/'Historical FS'!L26,0) -> 77.49474
B32: Dividend Payout Ratio | C32: =IFERROR(C31/C28,0) -> 0.12933263 | D32: =IFERROR(D31/D28,0) -> 0.13290952 | E32: =IFERROR(E31/E28,0) -> 0.14544336 | F32: =IFERROR(F31/F28,0) -> 0.15404725 | G32: =IFERROR(G31/G28,0) -> 0.073575146 | H32: =IFERROR(H31/H28,0) -> 0.22050944 | I32: =IFERROR(I31/I28,0) -> 0.16458784 | J32: =IFERROR(J31/J28,0) -> 0.24024317 | ... L32: =IFERROR(L31/L28,0) -> 0.40471566
B34: Retained Earnings | C34: =IFERROR(1-C32,0) -> 0.87066737 | D34: =IFERROR(1-D32,0) -> 0.86709048 | E34: =IFERROR(1-E32,0) -> 0.85455664 | F34: =IFERROR(1-F32,0) -> 0.84595275 | G34: =IFERROR(1-G32,0) -> 0.92642485 | H34: =IFERROR(1-H32,0) -> 0.77949056 | I34: =IFERROR(1-I32,0) -> 0.83541216 | J34: =IFERROR(1-J32,0) -> 0.75975683 | ... L34: =IFERROR(1-L32,0) -> 0.59528434
A36: # | B36: Balance Sheet
B37: Equity Share Capital | C37: ='Data Sheet'!B57 -> 274.43 | D37: ='Data Sheet'!C57 -> 274.51 | E37: ='Data Sheet'!D57 -> 274.61 | F37: ='Data Sheet'!E57 -> 274.64 | G37: ='Data Sheet'!F57 -> 288.63 | H37: ='Data Sheet'!G57 -> 288.65 | I37: ='Data Sheet'!H57 -> 288.67 | J37: ='Data Sheet'!I57 -> 288.69 | ... L37: ='Data Sheet'!K57 -> 294.68
B38: Reserves | C38: ='Data Sheet'!B58 -> 21671.2 | D38: ='Data Sheet'!C58 -> 24117.38 | E38: ='Data Sheet'!D58 -> 26106.55 | F38: ='Data Sheet'!E58 -> 33476.01 | G38: ='Data Sheet'!F58 -> 38755.13 | H38: ='Data Sheet'!G58 -> 43886.03 | I38: ='Data Sheet'!H58 -> 50146.6 | J38: ='Data Sheet'!I58 -> 54035.85 | ... L38: ='Data Sheet'!K58 -> 70412.09
B39: Borrowings | C39: ='Data Sheet'!B59 -> 10615.99 | D39: ='Data Sheet'!C59 -> 8474.49 | E39: ='Data Sheet'!D59 -> 19480.22 | F39: ='Data Sheet'!E59 -> 25337 | G39: ='Data Sheet'!F59 -> 23018.96 | H39: ='Data Sheet'!G59 -> 21719.39 | I39: ='Data Sheet'!H59 -> 11298.8 | J39: ='Data Sheet'!I59 -> 11057.74 | ... L39: ='Data Sheet'!K59 -> 24102.18
B40: Other Liabilities | C40: ='Data Sheet'!B60 -> 8631.49 | D40: ='Data Sheet'!C60 -> 9342.73 | E40: ='Data Sheet'!D60 -> 11279.71 | F40: ='Data Sheet'!E60 -> 17437.72 | G40: ='Data Sheet'!F60 -> 17151.09 | H40: ='Data Sheet'!G60 -> 20282.28 | I40: ='Data Sheet'!H60 -> 22077.37 | J40: ='Data Sheet'!I60 -> 25998.12 | ... L40: ='Data Sheet'!K60 -> 38823.11
B41: Total Liabilities & Equity | C41: =SUM(C37:C40) -> 41193.11 | D41: =SUM(D37:D40) -> 42209.11 | E41: =SUM(E37:E40) -> 57141.09 | F41: =SUM(F37:F40) -> 76525.37 | G41: =SUM(G37:G40) -> 79213.81 | H41: =SUM(H37:H40) -> 86176.35 | I41: =SUM(I37:I40) -> 83811.44 | J41: =SUM(J37:J40) -> 91380.4 | ... L41: =SUM(L37:L40) -> 133632.06
B43: Fixed Assets Net Block | C43: ='Data Sheet'!B62 -> 25309.42 | D43: ='Data Sheet'!C62 -> 25903.75 | E43: ='Data Sheet'!D62 -> 39715.3 | F43: ='Data Sheet'!E62 -> 56644.62 | G43: ='Data Sheet'!F62 -> 57150.96 | H43: ='Data Sheet'!G62 -> 55411.61 | I43: ='Data Sheet'!H62 -> 55487.57 | J43: ='Data Sheet'!I62 -> 59579 | ... L43: ='Data Sheet'!K62 -> 94564.22
B44: Capital Work in Progress | C44: ='Data Sheet'!B63 -> 1469.09 | D44: ='Data Sheet'!C63 -> 921.48 | E44: ='Data Sheet'!D63 -> 1511.21 | F44: ='Data Sheet'!E63 -> 1153.32 | G44: ='Data Sheet'!F63 -> 919.59 | H44: ='Data Sheet'!G63 -> 1686.68 | I44: ='Data Sheet'!H63 -> 4784.67 | J44: ='Data Sheet'!I63 -> 4040.39 | ... L44: ='Data Sheet'!K63 -> 6234.19
B45: Investments | C45: ='Data Sheet'!B64 -> 5095.18 | D45: ='Data Sheet'!C64 -> 6690.51 | E45: ='Data Sheet'!D64 -> 5446.9 | F45: ='Data Sheet'!E64 -> 2921.33 | G45: ='Data Sheet'!F64 -> 5928.69 | H45: ='Data Sheet'!G64 -> 12178.11 | I45: ='Data Sheet'!H64 -> 6335.77 | J45: ='Data Sheet'!I64 -> 7296.95 | ... L45: ='Data Sheet'!K64 -> 5156.47
B46: Other Assets | C46: ='Data Sheet'!B65-SUM('Data Sheet'!B67:B69) -> 2669.67 | D46: ='Data Sheet'!C65-SUM('Data Sheet'!C67:C69) -> 2286.86 | E46: ='Data Sheet'!D65-SUM('Data Sheet'!D67:D69) -> 4760.39 | F46: ='Data Sheet'!E65-SUM('Data Sheet'!E67:E69) -> 8180.43 | G46: ='Data Sheet'!F65-SUM('Data Sheet'!F67:F69) -> 8108.09 | H46: ='Data Sheet'!G65-SUM('Data Sheet'!G67:G69) -> 8302.7 | I46: ='Data Sheet'!H65-SUM('Data Sheet'!H67:H69) -> 8177.06 | J46: ='Data Sheet'!I65-SUM('Data Sheet'!I67:I69) -> 8835.62 | ... L46: ='Data Sheet'!K65-SUM('Data Sheet'!K67:K69) -> 10550.63
B47: Total Non Current Assets | C47: =SUM(C43:C46) -> 34543.36 | D47: =SUM(D43:D46) -> 35802.6 | E47: =SUM(E43:E46) -> 51433.8 | F47: =SUM(F43:F46) -> 68899.7 | G47: =SUM(G43:G46) -> 72107.33 | H47: =SUM(H43:H46) -> 77579.1 | I47: =SUM(I43:I46) -> 74785.07 | J47: =SUM(J43:J46) -> 79751.96 | ... L47: =SUM(L43:L46) -> 116505.51
B49: Receivables | C49: ='Data Sheet'!B67 -> 1928.21 | D49: ='Data Sheet'!C67 -> 1757.09 | E49: ='Data Sheet'!D67 -> 2220.63 | F49: ='Data Sheet'!E67 -> 2787.03 | G49: ='Data Sheet'!F67 -> 2383.22 | H49: ='Data Sheet'!G67 -> 2571.73 | I49: ='Data Sheet'!H67 -> 3071.61 | J49: ='Data Sheet'!I67 -> 3867.02 | ... L49: ='Data Sheet'!K67 -> 5890.25
B50: Inventory | C50: ='Data Sheet'!B68 -> 2454.58 | D50: ='Data Sheet'!C68 -> 2400.64 | E50: ='Data Sheet'!D68 -> 3267.59 | F50: ='Data Sheet'!E68 -> 4098.96 | G50: ='Data Sheet'!F68 -> 4183.35 | H50: ='Data Sheet'!G68 -> 4017.97 | I50: ='Data Sheet'!H68 -> 5595.58 | J50: ='Data Sheet'!I68 -> 6611.83 | ... L50: ='Data Sheet'!K68 -> 9562.98
B51: Cash & Bank | C51: ='Data Sheet'!B69 -> 2266.96 | D51: ='Data Sheet'!C69 -> 2248.78 | E51: ='Data Sheet'!D69 -> 219.07 | F51: ='Data Sheet'!E69 -> 739.68 | G51: ='Data Sheet'!F69 -> 539.91 | H51: ='Data Sheet'!G69 -> 2007.55 | I51: ='Data Sheet'!H69 -> 359.18 | J51: ='Data Sheet'!I69 -> 1149.59 | ... L51: ='Data Sheet'!K69 -> 1673.32
B52: Total Current Assets | C52: =SUM(C49:C51) -> 6649.75 | D52: =SUM(D49:D51) -> 6406.51 | E52: =SUM(E49:E51) -> 5707.29 | F52: =SUM(F49:F51) -> 7625.67 | G52: =SUM(G49:G51) -> 7106.48 | H52: =SUM(H49:H51) -> 8597.25 | I52: =SUM(I49:I51) -> 9026.37 | J52: =SUM(J49:J51) -> 11628.44 | ... L52: =SUM(L49:L51) -> 17126.55
B53: Total Assets | C53: =C47+C52 -> 41193.11 | D53: =D47+D52 -> 42209.11 | E53: =E47+E52 -> 57141.09 | F53: =F47+F52 -> 76525.37 | G53: =G47+G52 -> 79213.81 | H53: =H47+H52 -> 86176.35 | I53: =I47+I52 -> 83811.44 | J53: =J47+J52 -> 91380.4 | ... L53: =L47+L52 -> 133632.06
B55: B.S Check | C55: =C53=C41 -> TRUE | D55: =D53=D41 -> TRUE | E55: =E53=E41 -> TRUE | F55: =F53=F41 -> TRUE | G55: =G53=G41 -> TRUE | H55: =H53=H41 -> TRUE | I55: =I53=I41 -> TRUE | J55: =J53=J41 -> TRUE | ... L55: =L53=L41 -> TRUE
A57: # | B57: Cash Flow Statement
B58: Operating Activities
B59: Profit from operations | C59: =IFERROR('CF Data'!C4,0) -> 4948 | D59: =IFERROR('CF Data'!D4,0) -> 5220 | E59: =IFERROR('CF Data'!E4,0) -> 5986 | F59: =IFERROR('CF Data'!F4,0) -> 7362 | G59: =IFERROR('CF Data'!G4,0) -> 9348 | H59: =IFERROR('CF Data'!H4,0) -> 11465 | I59: =IFERROR('CF Data'!I4,0) -> 11311 | J59: =IFERROR('CF Data'!J4,0) -> 10530 | ... L59: =IFERROR('CF Data'!L4,0) -> 12645
B60: Receivables | C60: =IFERROR('CF Data'!C5,0) -> -287 | D60: =IFERROR('CF Data'!D5,0) -> 156 | E60: =IFERROR('CF Data'!E5,0) -> -454 | F60: =IFERROR('CF Data'!F5,0) -> -279 | G60: =IFERROR('CF Data'!G5,0) -> 473 | H60: =IFERROR('CF Data'!H5,0) -> -201 | I60: =IFERROR('CF Data'!I5,0) -> -495 | J60: =IFERROR('CF Data'!J5,0) -> -752 | ... L60: =IFERROR('CF Data'!L5,0) -> -608
B61: Inventory | C61: =IFERROR('CF Data'!C6,0) -> 374 | D61: =IFERROR('CF Data'!D6,0) -> 54 | E61: =IFERROR('CF Data'!E6,0) -> -623 | F61: =IFERROR('CF Data'!F6,0) -> -15 | G61: =IFERROR('CF Data'!G6,0) -> -64 | H61: =IFERROR('CF Data'!H6,0) -> 165 | I61: =IFERROR('CF Data'!I6,0) -> -1579 | J61: =IFERROR('CF Data'!J6,0) -> -992 | ... L61: =IFERROR('CF Data'!L6,0) -> -317
B62: Payables | C62: =IFERROR('CF Data'!C7,0) -> 310 | D62: =IFERROR('CF Data'!D7,0) -> 482 | E62: =IFERROR('CF Data'!E7,0) -> 346 | F62: =IFERROR('CF Data'!F7,0) -> 766 | G62: =IFERROR('CF Data'!G7,0) -> 279 | H62: =IFERROR('CF Data'!H7,0) -> 2868 | I62: =IFERROR('CF Data'!I7,0) -> 2077 | J62: =IFERROR('CF Data'!J7,0) -> 1869 | ... L62: =IFERROR('CF Data'!L7,0) -> -476
B63: Loans Advances | C63: =IFERROR('CF Data'!C8,0) -> 0 | D63: =IFERROR('CF Data'!D8,0) -> 0 | E63: =IFERROR('CF Data'!E8,0) -> 0 | F63: =IFERROR('CF Data'!F8,0) -> 0 | G63: =IFERROR('CF Data'!G8,0) -> 0 | H63: =IFERROR('CF Data'!H8,0) -> 0 | I63: =IFERROR('CF Data'!I8,0) -> 0 | J63: =IFERROR('CF Data'!J8,0) -> 0 | ... L63: =IFERROR('CF Data'!L8,0) -> 0
B64: Other WC items | C64: =IFERROR('CF Data'!C9,0) -> 32 | D64: =IFERROR('CF Data'!D9,0) -> -162 | E64: =IFERROR('CF Data'!E9,0) -> -525 | F64: =IFERROR('CF Data'!F9,0) -> -1167 | G64: =IFERROR('CF Data'!G9,0) -> -172 | H64: =IFERROR('CF Data'!H9,0) -> -505 | I64: =IFERROR('CF Data'!I9,0) -> -476 | J64: =IFERROR('CF Data'!J9,0) -> -461 | ... L64: =IFERROR('CF Data'!L9,0) -> 729
B65: Working capital changes | C65: =IFERROR('CF Data'!C10,0) -> 429 | D65: =IFERROR('CF Data'!D10,0) -> 529 | E65: =IFERROR('CF Data'!E10,0) -> -1255 | F65: =IFERROR('CF Data'!F10,0) -> -696 | G65: =IFERROR('CF Data'!G10,0) -> 516 | H65: =IFERROR('CF Data'!H10,0) -> 2326 | I65: =IFERROR('CF Data'!I10,0) -> -473 | J65: =IFERROR('CF Data'!J10,0) -> -337 | ... L65: =IFERROR('CF Data'!L10,0) -> -671
B66: Direct taxes | C66: =IFERROR('CF Data'!C11,0) -> -852 | D66: =IFERROR('CF Data'!D11,0) -> -744 | E66: =IFERROR('CF Data'!E11,0) -> -843 | F66: =IFERROR('CF Data'!F11,0) -> -710 | G66: =IFERROR('CF Data'!G11,0) -> -891 | H66: =IFERROR('CF Data'!H11,0) -> -1291 | I66: =IFERROR('CF Data'!I11,0) -> -1555 | J66: =IFERROR('CF Data'!J11,0) -> -1124 | ... L66: =IFERROR('CF Data'!L11,0) -> -1301
B67: Other operating items | C67: =IFERROR('CF Data'!C12,0) -> 0 | D67: =IFERROR('CF Data'!D12,0) -> 0 | E67: =IFERROR('CF Data'!E12,0) -> 0 | F67: =IFERROR('CF Data'!F12,0) -> 0 | G67: =IFERROR('CF Data'!G12,0) -> 0 | H67: =IFERROR('CF Data'!H12,0) -> 0 | I67: =IFERROR('CF Data'!I12,0) -> 0 | J67: =IFERROR('CF Data'!J12,0) -> 0 | ... L67: =IFERROR('CF Data'!L12,0) -> 0
B68: Cash Flow from Operating Activities | C68: =SUM(C59:C67) -> 4954 | D68: =SUM(D59:D67) -> 5535 | E68: =SUM(E59:E67) -> 2632 | F68: =SUM(F59:F67) -> 5261 | G68: =SUM(G59:G67) -> 9489 | H68: =SUM(H59:H67) -> 14827 | I68: =SUM(I59:I67) -> 8810 | J68: =SUM(J59:J67) -> 8733 | ... L68: =SUM(L59:L67) -> 10001
B69: Investing Activities
B70: Fixed assets purchased | C70: =IFERROR('CF Data'!C14,0) -> -2150 | D70: =IFERROR('CF Data'!D14,0) -> -1402 | E70: =IFERROR('CF Data'!E14,0) -> -2103 | F70: =IFERROR('CF Data'!F14,0) -> -1808 | G70: =IFERROR('CF Data'!G14,0) -> -1766 | H70: =IFERROR('CF Data'!H14,0) -> -1925 | I70: =IFERROR('CF Data'!I14,0) -> -5613 | J70: =IFERROR('CF Data'!J14,0) -> -6200 | ... L70: =IFERROR('CF Data'!L14,0) -> -9129
B71: Fixed assets sold | C71: =IFERROR('CF Data'!C15,0) -> 18 | D71: =IFERROR('CF Data'!D15,0) -> 35 | E71: =IFERROR('CF Data'!E15,0) -> 220 | F71: =IFERROR('CF Data'!F15,0) -> 160 | G71: =IFERROR('CF Data'!G15,0) -> 79 | H71: =IFERROR('CF Data'!H15,0) -> 86 | I71: =IFERROR('CF Data'!I15,0) -> 73 | J71: =IFERROR('CF Data'!J15,0) -> 95 | ... L71: =IFERROR('CF Data'!L15,0) -> 179
B72: Investments purchased | C72: =IFERROR('CF Data'!C16,0) -> -2698 | D72: =IFERROR('CF Data'!D16,0) -> -3377 | E72: =IFERROR('CF Data'!E16,0) -> -3960 | F72: =IFERROR('CF Data'!F16,0) -> -1700 | G72: =IFERROR('CF Data'!G16,0) -> -6086 | H72: =IFERROR('CF Data'!H16,0) -> -12689 | I72: =IFERROR('CF Data'!I16,0) -> -7795 | J72: =IFERROR('CF Data'!J16,0) -> -7260 | ... L72: =IFERROR('CF Data'!L16,0) -> -15885
B73: Investments sold | C73: =IFERROR('CF Data'!C17,0) -> 2948 | D73: =IFERROR('CF Data'!D17,0) -> 2228 | E73: =IFERROR('CF Data'!E17,0) -> 5588 | F73: =IFERROR('CF Data'!F17,0) -> 4478 | G73: =IFERROR('CF Data'!G17,0) -> 3443 | H73: =IFERROR('CF Data'!H17,0) -> 7101 | I73: =IFERROR('CF Data'!I17,0) -> 13965 | J73: =IFERROR('CF Data'!J17,0) -> 7156 | ... L73: =IFERROR('CF Data'!L17,0) -> 19115
B74: Interest received | C74: =IFERROR('CF Data'!C18,0) -> 59 | D74: =IFERROR('CF Data'!D18,0) -> 47 | E74: =IFERROR('CF Data'!E18,0) -> 67 | F74: =IFERROR('CF Data'!F18,0) -> 78 | G74: =IFERROR('CF Data'!G18,0) -> 89 | H74: =IFERROR('CF Data'!H18,0) -> 77 | I74: =IFERROR('CF Data'!I18,0) -> 174 | J74: =IFERROR('CF Data'!J18,0) -> 283 | ... L74: =IFERROR('CF Data'!L18,0) -> 342
B75: Dividends received | C75: =IFERROR('CF Data'!C19,0) -> 0 | D75: =IFERROR('CF Data'!D19,0) -> 0 | E75: =IFERROR('CF Data'!E19,0) -> 0 | F75: =IFERROR('CF Data'!F19,0) -> 22 | G75: =IFERROR('CF Data'!G19,0) -> 32 | H75: =IFERROR('CF Data'!H19,0) -> 0 | I75: =IFERROR('CF Data'!I19,0) -> 0 | J75: =IFERROR('CF Data'!J19,0) -> 0 | ... L75: =IFERROR('CF Data'!L19,0) -> 1
B76: Invest in subsidiaries | C76: =IFERROR('CF Data'!C20,0) -> -13 | D76: =IFERROR('CF Data'!D20,0) -> 0 | E76: =IFERROR('CF Data'!E20,0) -> 0 | F76: =IFERROR('CF Data'!F20,0) -> 0 | G76: =IFERROR('CF Data'!G20,0) -> 0 | H76: =IFERROR('CF Data'!H20,0) -> 0 | I76: =IFERROR('CF Data'!I20,0) -> 0 | J76: =IFERROR('CF Data'!J20,0) -> 0 | ... L76: =IFERROR('CF Data'!L20,0) -> 0
B77: Investment in group cos | C77: =IFERROR('CF Data'!C21,0) -> 0 | D77: =IFERROR('CF Data'!D21,0) -> 0 | E77: =IFERROR('CF Data'!E21,0) -> -1 | F77: =IFERROR('CF Data'!F21,0) -> -8 | G77: =IFERROR('CF Data'!G21,0) -> -6 | H77: =IFERROR('CF Data'!H21,0) -> -3 | I77: =IFERROR('CF Data'!I21,0) -> 0 | J77: =IFERROR('CF Data'!J21,0) -> 0 | ... L77: =IFERROR('CF Data'!L21,0) -> 0
B78: Redemp n Canc of Shares | C78: =IFERROR('CF Data'!C22,0) -> 0 | D78: =IFERROR('CF Data'!D22,0) -> 0 | E78: =IFERROR('CF Data'!E22,0) -> 0 | F78: =IFERROR('CF Data'!F22,0) -> 0 | G78: =IFERROR('CF Data'!G22,0) -> 0 | H78: =IFERROR('CF Data'!H22,0) -> 0 | I78: =IFERROR('CF Data'!I22,0) -> 0 | J78: =IFERROR('CF Data'!J22,0) -> 3 | ... L78: =IFERROR('CF Data'!L22,0) -> 36
B79: Acquisition of companies | C79: =IFERROR('CF Data'!C23,0) -> 0 | D79: =IFERROR('CF Data'!D23,0) -> 0 | E79: =IFERROR('CF Data'!E23,0) -> 0 | F79: =IFERROR('CF Data'!F23,0) -> 0 | G79: =IFERROR('CF Data'!G23,0) -> 0 | H79: =IFERROR('CF Data'!H23,0) -> 0 | I79: =IFERROR('CF Data'!I23,0) -> 0 | J79: =IFERROR('CF Data'!J23,0) -> -847 | ... L79: =IFERROR('CF Data'!L23,0) -> -10262
B80: Other investing items | C80: =IFERROR('CF Data'!C24,0) -> -1839 | D80: =IFERROR('CF Data'!D24,0) -> -32 | E80: =IFERROR('CF Data'!E24,0) -> 2055 | F80: =IFERROR('CF Data'!F24,0) -> -58 | G80: =IFERROR('CF Data'!G24,0) -> 22 | H80: =IFERROR('CF Data'!H24,0) -> -1503 | I80: =IFERROR('CF Data'!I24,0) -> 1518 | J80: =IFERROR('CF Data'!J24,0) -> -417 | ... L80: =IFERROR('CF Data'!L24,0) -> -232
B81: Cash Flow from Investing Activities | C81: =SUM(C70:C80) -> -3675 | D81: =SUM(D70:D80) -> -2501 | E81: =SUM(E70:E80) -> 1866 | F81: =SUM(F70:F80) -> 1164 | G81: =SUM(G70:G80) -> -4193 | H81: =SUM(H70:H80) -> -8856 | I81: =SUM(I70:I80) -> 2322 | J81: =SUM(J70:J80) -> -7187 | ... L81: =SUM(L70:L80) -> -15835
B82: Financing Activities
B83: Proceeds from shares | C83: =IFERROR('CF Data'!C26,0) -> 3 | D83: =IFERROR('CF Data'!D26,0) -> 7 | E83: =IFERROR('CF Data'!E26,0) -> 16 | F83: =IFERROR('CF Data'!F26,0) -> 5 | G83: =IFERROR('CF Data'!G26,0) -> 3 | H83: =IFERROR('CF Data'!H26,0) -> 14 | I83: =IFERROR('CF Data'!I26,0) -> 13 | J83: =IFERROR('CF Data'!J26,0) -> 13 | ... L83: =IFERROR('CF Data'!L26,0) -> 33
B84: Proceeds from borrowings | C84: =IFERROR('CF Data'!C27,0) -> 2821 | D84: =IFERROR('CF Data'!D27,0) -> 3656 | E84: =IFERROR('CF Data'!E27,0) -> 15775 | F84: =IFERROR('CF Data'!F27,0) -> 9772 | G84: =IFERROR('CF Data'!G27,0) -> 1510 | H84: =IFERROR('CF Data'!H27,0) -> 4103 | I84: =IFERROR('CF Data'!I27,0) -> 175 | J84: =IFERROR('CF Data'!J27,0) -> 1032 | ... L84: =IFERROR('CF Data'!L27,0) -> 9410
B85: Repayment of borrowings | C85: =IFERROR('CF Data'!C28,0) -> -2775 | D85: =IFERROR('CF Data'!D28,0) -> -5272 | E85: =IFERROR('CF Data'!E28,0) -> -19982 | F85: =IFERROR('CF Data'!F28,0) -> -14420 | G85: =IFERROR('CF Data'!G28,0) -> -4154 | H85: =IFERROR('CF Data'!H28,0) -> -6499 | I85: =IFERROR('CF Data'!I28,0) -> -10346 | J85: =IFERROR('CF Data'!J28,0) -> -579 | ... L85: =IFERROR('CF Data'!L28,0) -> -550
B86: Interest paid fin | C86: =IFERROR('CF Data'!C29,0) -> -596 | D86: =IFERROR('CF Data'!D29,0) -> -614 | E86: =IFERROR('CF Data'!E29,0) -> -1210 | F86: =IFERROR('CF Data'!F29,0) -> -1685 | G86: =IFERROR('CF Data'!G29,0) -> -1950 | H86: =IFERROR('CF Data'!H29,0) -> -1481 | I86: =IFERROR('CF Data'!I29,0) -> -1026 | J86: =IFERROR('CF Data'!J29,0) -> -765 | ... L86: =IFERROR('CF Data'!L29,0) -> -1540
B87: Dividends paid | C87: =IFERROR('CF Data'!C30,0) -> -297 | D87: =IFERROR('CF Data'!D30,0) -> -312 | E87: =IFERROR('CF Data'!E30,0) -> -334 | F87: =IFERROR('CF Data'!F30,0) -> -346 | G87: =IFERROR('CF Data'!G30,0) -> -380 | H87: =IFERROR('CF Data'!H30,0) -> -375 | I87: =IFERROR('CF Data'!I30,0) -> -1065 | J87: =IFERROR('CF Data'!J30,0) -> -1091 | ... L87: =IFERROR('CF Data'!L30,0) -> -2012
B88: Financial liabilities | C88: =IFERROR('CF Data'!C31,0) -> 0 | D88: =IFERROR('CF Data'!D31,0) -> 0 | E88: =IFERROR('CF Data'!E31,0) -> 0 | F88: =IFERROR('CF Data'!F31,0) -> 0 | G88: =IFERROR('CF Data'!G31,0) -> -101 | H88: =IFERROR('CF Data'!H31,0) -> -118 | I88: =IFERROR('CF Data'!I31,0) -> -157 | J88: =IFERROR('CF Data'!J31,0) -> -126 | ... L88: =IFERROR('CF Data'!L31,0) -> -165
B89: Other financing items | C89: =IFERROR('CF Data'!C32,0) -> 1 | D89: =IFERROR('CF Data'!D32,0) -> 0 | E89: =IFERROR('CF Data'!E32,0) -> 0 | F89: =IFERROR('CF Data'!F32,0) -> -83 | G89: =IFERROR('CF Data'!G32,0) -> -4 | H89: =IFERROR('CF Data'!H32,0) -> 0 | I89: =IFERROR('CF Data'!I32,0) -> -91 | J89: =IFERROR('CF Data'!J32,0) -> -115 | ... L89: =IFERROR('CF Data'!L32,0) -> -100
B90: Cash Flow from Financing Activities | C90: =SUM(C83:C89) -> -843 | D90: =SUM(D83:D89) -> -2535 | E90: =SUM(E83:E89) -> -5735 | F90: =SUM(F83:F89) -> -6757 | G90: =SUM(G83:G89) -> -5076 | H90: =SUM(H83:H89) -> -4356 | I90: =SUM(I83:I89) -> -12497 | J90: =SUM(J83:J89) -> -1631 | ... L90: =SUM(L83:L89) -> 5076
B92: Net Cash Flow | C92: =SUM(C68,C81,C90) -> 436 | D92: =SUM(D68,D81,D90) -> 499 | E92: =SUM(E68,E81,E90) -> -1237 | F92: =SUM(F68,F81,F90) -> -332 | G92: =SUM(G68,G81,G90) -> 220 | H92: =SUM(H68,H81,H90) -> 1615 | I92: =SUM(I68,I81,I90) -> -1365 | J92: =SUM(J68,J81,J90) -> -85 | ... L92: =SUM(L68,L81,L90) -> -758

Sheet Data Sheet
A1: COMPANY NAME | B1: ULTRATECH CEMENT LTD | E1: =IF(B2<>B3, "A NEW VERSION OF THE WORKSHEET IS AVAILABLE", "")
A2: LATEST VERSION | B2: 2.1 | E2: PLEASE DO NOT MAKE ANY CHANGES TO THIS SHEET
A3: CURRENT VERSION | B3: 2.1
A5: META
A6: Number of shares | B6: =IF(B9>0, B9/B8, 0) -> 29.482018
A7: Face Value | B7: 10
A8: Current Price | B8: 12039
A9: Market Capitalization | B9: 354934.02
A15: PROFIT & LOSS
A16: Report Date | B16: 42460 | C16: 42825 | D16: 43190 | E16: 43555 | F16: 43921 | G16: 44286 | H16: 44651 | I16: 45016 | J16: 45382 | K16: 45747
A17: Sales | B17: 25153.24 | C17: 25374.94 | D17: 30978.62 | E17: 41462.26 | F17: 42429.89 | G17: 44725.8 | H17: 52598.83 | I17: 63239.98 | J17: 70908.14 | K17: 75955.13
A18: Raw Material Cost | B18: 4436.12 | C18: 4416.9 | D18: 5399.98 | E18: 6936.74 | F18: 6875.89 | G18: 6635.66 | H18: 8348.15 | I18: 10233.17 | J18: 11986.27 | K18: 13691.46
A19: Change in Inventory | B19: 18.61 | C19: -75.69 | D19: 111.2 | E19: -46.35 | F19: 357.83 | G19: -450.15 | H19: 383.16 | I19: 518.21 | J19: 83.35 | K19: -12.27
A20: Power and Fuel | B20: 4579.25 | C20: 4271.98 | D20: 6334.07 | E20: 9436.14 | F20: 8516.87 | G20: 8331.18 | H20: 12137.26 | I20: 18491.32 | J20: 18283.32 | K20: 18419.15
A21: Other Mfr. Exp | B21: 1933.88 | C21: 1991.28 | D21: 2289.53 | E21: 3001.06 | F21: 3043.3 | G21: 3067.38 | H21: 3889.67 | I21: 4344.34 | J21: 4898.17 | K21: 5474.61
A22: Employee Cost | B22: 1466.49 | C22: 1547.77 | D22: 1831.81 | E22: 2309.43 | F22: 2522.64 | G22: 2363.33 | H22: 2545 | I22: 2751.31 | J22: 3051.99 | K22: 3619.25
A23: Selling and admin | B23: 7200.47 | C23: 7149.12 | D23: 8320.28 | E23: 11563.8 | F23: 11237.32 | G23: 11266.02 | H23: 13282.22 | I23: 15859.6 | J23: 18066.95 | K23: 19571.95
A24: Other Expenses | B24: 654.67 | C24: 709.76 | D24: 769.12 | E24: 821.8 | F24: 1345.73 | G24: 1044.17 | H24: 1265.34 | I24: 1458.6 | J24: 1726.23 | K24: 2369.56
A25: Other Income | B25: 463.81 | C25: 648.12 | D25: 241.97 | E25: 350.1 | F25: 651.06 | G25: 618.52 | H25: 669.43 | I25: 507.11 | J25: 556.96 | K25: 396.74
A26: Depreciation | B26: 1377.17 | C26: 1348.41 | D26: 1847.93 | E26: 2450.73 | F26: 2722.66 | G26: 2700.23 | H26: 2714.75 | I26: 2887.99 | J26: 3145.3 | K26: 4014.95
A27: Interest | B27: 566.3 | C27: 640.1 | D27: 1237.6 | E27: 1777.86 | F27: 1991.65 | G27: 1485.65 | H27: 944.71 | I27: 822.72 | J27: 968 | K27: 1650.54
... A31: Dividend Amount | B31: 260.71 | C31: 274.51 | D31: 288.34 | E31: 315.84 | F31: 375.22 | G31: 1068 | H31: 1096.95 | I31: 1097.02 | J31: 2020.83 | K31: 2283.77
A40: Quarters
A41: Report Date | B41: 45199 | C41: 45291 | D41: 45382 | E41: 45473 | F41: 45565 | G41: 45657 | H41: 45747 | I41: 45838 | J41: 45930 | K41: 46022
A42: Sales | B42: 16012.13 | C42: 16739.97 | D42: 20418.94 | E42: 18818.56 | F42: 16294.42 | G42: 17778.83 | H42: 23063.32 | I42: 21275.45 | J42: 19606.93 | K42: 21829.68
A43: Expenses | B43: 13461.24 | C43: 13485.4 | D43: 16305.02 | E43: 15801.46 | F43: 14268.68 | G43: 14885.35 | H43: 18455.65 | I43: 16869.42 | J43: 16518.27 | K43: 17918.91
A44: Other Income | B44: 170.62 | C44: 146.24 | D44: 72.67 | E44: 83.31 | F44: 226.22 | G44: 247.32 | H44: 92.78 | I44: 141.85 | J44: 174.14 | K44: 46.35
A45: Depreciation | B45: 797.83 | C45: 783.48 | D45: 814.92 | E45: 917.93 | F45: 979.67 | G45: 992.78 | H45: 1124.57 | I45: 1106.78 | J45: 1147.68 | K45: 1181.9
A46: Interest | B46: 233.94 | C46: 262.16 | D46: 261.15 | E46: 325.76 | F46: 392.99 | G46: 456.75 | H46: 475.04 | I46: 433.3 | J46: 459.29 | K46: 492.2
A47: Profit before tax | B47: 1689.74 | C47: 2355.17 | D47: 3110.52 | E47: 1856.72 | F47: 879.3 | G47: 1691.27 | H47: 3100.84 | I47: 3007.8 | J47: 1655.83 | K47: 2283.02
A48: Tax | B48: 409.36 | C48: 580.39 | D48: 851.94 | E48: 363.27 | F48: 171.34 | G48: 327.83 | H48: 626.05 | I48: 786.89 | J48: 417.85 | K48: 553.58
A49: Net profit | B49: 1281.45 | C49: 1776.98 | D49: 2258.12 | E49: 1494.82 | F49: 702.82 | G49: 1359.43 | H49: 2482.04 | I49: 2225.9 | J49: 1231.58 | K49: 1725.4
A50: Operating Profit | B50: 2550.89 | C50: 3254.57 | D50: 4113.92 | E50: 3017.1 | F50: 2025.74 | G50: 2893.48 | H50: 4607.67 | I50: 4406.03 | J50: 3088.66 | K50: 3910.77
A55: BALANCE SHEET
A56: Report Date | B56: 42460 | C56: 42825 | D56: 43190 | E56: 43555 | F56: 43921 | G56: 44286 | H56: 44651 | I56: 45016 | J56: 45382 | K56: 45747
A57: Equity Share Capital | B57: 274.43 | C57: 274.51 | D57: 274.61 | E57: 274.64 | F57: 288.63 | G57: 288.65 | H57: 288.67 | I57: 288.69 | J57: 288.69 | K57: 294.68
A58: Reserves | B58: 21671.2 | C58: 24117.38 | D58: 26106.55 | E58: 33476.01 | F58: 38755.13 | G58: 43886.03 | H58: 50146.6 | I58: 54035.85 | J58: 59938.79 | K58: 70412.09
A59: Borrowings | B59: 10615.99 | C59: 8474.49 | D59: 19480.22 | E59: 25337 | F59: 23018.96 | G59: 21719.39 | H59: 11298.8 | I59: 11057.74 | J59: 11402.95 | K59: 24102.18
A60: Other Liabilities | B60: 8631.49 | C60: 9342.73 | D60: 11279.71 | E60: 17437.72 | F60: 17151.09 | G60: 20282.28 | H60: 22077.37 | I60: 25998.12 | J60: 29166.68 | K60: 38823.11
A61: Total | B61: 41193.11 | C61: 42209.11 | D61: 57141.09 | E61: 76525.37 | F61: 79213.81 | G61: 86176.35 | H61: 83811.44 | I61: 91380.4 | J61: 100797.11 | K61: 133632.06
A62: Net Block | B62: 25309.42 | C62: 25903.75 | D62: 39715.3 | E62: 56644.62 | F62: 57150.96 | G62: 55411.61 | H62: 55487.57 | I62: 59579 | J62: 62877.61 | K62: 94564.22
A63: Capital Work in Progress | B63: 1469.09 | C63: 921.48 | D63: 1511.21 | E63: 1153.32 | F63: 919.59 | G63: 1686.68 | H63: 4784.67 | I63: 4040.39 | J63: 6811.18 | K63: 6234.19
A64: Investments | B64: 5095.18 | C64: 6690.51 | D64: 5446.9 | E64: 2921.33 | F64: 5928.69 | G64: 12178.11 | H64: 6335.77 | I64: 7296.95 | J64: 8248.95 | K64: 5156.47
A65: Other Assets | B65: 9319.42 | C65: 8693.37 | D65: 10467.68 | E65: 15806.1 | F65: 15214.57 | G65: 16899.95 | H65: 17203.43 | I65: 20464.06 | J65: 22859.37 | K65: 27677.18
A66: Total | B66: 41193.11 | C66: 42209.11 | D66: 57141.09 | E66: 76525.37 | F66: 79213.81 | G66: 86176.35 | H66: 83811.44 | I66: 91380.4 | J66: 100797.11 | K66: 133632.06
A67: Receivables | B67: 1928.21 | C67: 1757.09 | D67: 2220.63 | E67: 2787.03 | F67: 2383.22 | G67: 2571.73 | H67: 3071.61 | I67: 3867.02 | J67: 4278.16 | K67: 5890.25
... A70: No. of Equity Shares | B70: 274431377 | C70: 274507906 | D70: 274613985 | E70: 274642720 | F70: 288625105 | G70: 288653398 | H70: 288670847 | I70: 288686345 | J70: 288686345 | K70: 294677410
A71: New Bonus Shares
A72: Face value | B72: 10 | C72: 10 | D72: 10 | E72: 10 | F72: 10 | G72: 10 | H72: 10 | I72: 10 | J72: 10 | K72: 10
A80: CASH FLOW:
A81: Report Date | B81: 42460 | C81: 42825 | D81: 43190 | E81: 43555 | F81: 43921 | G81: 44286 | H81: 44651 | I81: 45016 | J81: 45382 | K81: 45747
A82: Cash from Operating Activity | B82: 4525.51 | C82: 5005.02 | D82: 3887.72 | E82: 5956.11 | F82: 8972.43 | G82: 12500.43 | H82: 9283.24 | I82: 9068.51 | J82: 10897.54 | K82: 10673.43
A83: Cash from Investing Activity | B83: -3673.35 | C83: -2501.44 | D83: 1865.72 | E83: 1165.18 | F83: -4191.95 | G83: -8856.15 | H83: 2256.54 | I83: -7187.68 | J83: -8788.68 | K83: -15835.56
A84: Cash from Financing Activity | B84: -844.02 | C84: -2534.98 | D84: -5735.05 | E84: -6757.24 | F84: -5075.88 | G84: -4356.47 | H84: -12497.93 | I84: -1631 | J84: -1925.65 | K84: 5075.76
A85: Net Cash Flow | B85: 8.14 | C85: -31.4 | D85: 18.39 | E85: 364.05 | F85: -295.4 | G85: -712.19 | H85: -958.15 | I85: 249.83 | J85: 183.21 | K85: -86.37
A90: PRICE: | B90: 3228.75 | C90: 3984.75 | D90: 3950 | E90: 3998.35 | F90: 3244.85 | G90: 6737.95 | H90: 6602.3 | I90: 7622.15 | J90: 9749.15 | K90: 11509.55
A92: DERIVED:
A93: Adjusted Equity Shares in Cr | B93: 27.44 | C93: 27.45 | D93: 27.46 | E93: 27.46 | F93: 28.86 | G93: 28.87 | H93: 28.87 | I93: 28.87 | J93: 28.87 | K93: 29.47
B95: 41699 | C95: 42064 | D95: 42430 | E95: 42795 | F95: 43160 | G95: 43525 | H95: 43891 | I95: 44256 | J95: 44621 | K95: 44986 | L95: 45352 | M95: 45717 | N95: 45901
A96: Equity Capital | B96: 274 | C96: 274 | D96: 274 | E96: 275 | F96: 275 | G96: 275 | H96: 289 | I96: 289 | J96: 289 | K96: 289 | L96: 289 | M96: 295 | N96: 295
A97: Reserves | B97: 16908 | C97: 18767 | D97: 21671 | E97: 24117 | F97: 26107 | G97: 33476 | H97: 38755 | I97: 43886 | J97: 50147 | K97: 54036 | L97: 59939 | M97: 70412 | N97: 71738
A98: Borrowings - | B98: 7332 | C98: 9829 | D98: 10616 | E98: 8474 | F98: 19480 | G98: 25337 | H98: 23019 | I98: 21719 | J98: 11299 | K98: 11058 | L98: 11403 | M98: 24102 | N98: 25215
A99: Long term Borrowings | B99: 6021 | C99: 4993 | D99: 4897 | E99: 6371 | F99: 15863 | G99: 20650 | H99: 17368 | I99: 13548 | J99: 5303 | K99: 5356 | L99: 5308 | M99: 15781 | N99: 14790
A100: Short term Borrowings | B100: 985 | C100: 2564 | D100: 2476 | E100: 1079 | F100: 2763 | G100: 3668 | H100: 4106 | I100: 6939 | J100: 4900 | K100: 4544 | L100: 4991 | M100: 7250 | N100: 9455
A101: Lease Liabilities | B101: 0 | C101: 0 | D101: 0 | E101: 0 | F101: 0 | G101: 0 | H101: 0 | I101: 1232 | J101: 1096 | K101: 1157 | L101: 1105 | M101: 1071 | N101: 969
A102: Other Borrowings | B102: 327 | C102: 2273 | D102: 3244 | E102: 1024 | F102: 853 | G102: 1018 | H102: 1545 | I102: 0 | J102: 0 | K102: 0 | L102: 0 | M102: 0
A103: Other Liabilities - | B103: 7671 | C103: 9183 | D103: 8631 | E103: 9343 | F103: 11280 | G103: 17438 | H103: 17151 | I103: 20282 | J103: 22077 | K103: 25998 | L103: 29167 | M103: 38823 | N103: 40058
A104: Non controlling int | B104: 17 | C104: 18 | D104: 15 | E104: 10 | F104: 16 | G104: 12 | H104: 8 | I104: 6 | J104: -3 | K104: 56 | L104: 56 | M104: 3187 | N104: 3934
A105: Trade Payables | B105: 2591 | C105: 1711 | D105: 1717 | E105: 1849 | F105: 2385 | G105: 3160 | H105: 3363 | I105: 4548 | J105: 5863 | K105: 7209 | L105: 8478 | M105: 9327 | N105: 9711
A106: Advance from Customers | B106: 0 | C106: 0 | D106: 166 | E106: 196 | F106: 305 | G106: 357 | H106: 464 | I106: 415 | J106: 465 | K106: 384 | L106: 527 | M106: 541
A107: Other liability items | B107: 5063 | C107: 7454 | D107: 6733 | E107: 7288 | F107: 8574 | G107: 13909 | H107: 13316 | I107: 15313 | J107: 15753 | K107: 18349 | L107: 20106 | M107: 25768 | N107: 26412
A108: Total Liabilities | B108: 32185 | C108: 38053 | D108: 41193 | E108: 42209 | F108: 57141 | G108: 76525 | H108: 79214 | I108: 86176 | J108: 83811 | K108: 91380 | L108: 100797 | M108: 133632 | N108: 137305
A109: Fixed Assets - | B109: 18100 | C109: 23343 | D109: 25309 | E109: 25904 | F109: 39715 | G109: 56645 | H109: 57151 | I109: 55412 | J109: 55488 | K109: 59579 | L109: 62878 | M109: 94564 | N109: 95930
A110: Land | B110: 2154 | C110: 3311 | D110: 3627 | E110: 3785 | F110: 6361 | G110: 7492 | H110: 7943 | I110: 8085 | J110: 8454 | K110: 8709 | L110: 9259 | M110: 19872
A111: Building | B111: 2059 | C111: 2792 | D111: 2469 | E111: 2766 | F111: 4346 | G111: 5130 | H111: 5511 | I111: 5606 | J111: 5831 | K111: 6287 | L111: 6772 | M111: 9361
A112: Plant Machinery | B112: 21482 | C112: 26327 | D112: 18452 | E112: 19713 | F112: 28048 | G112: 36920 | H112: 38369 | I112: 38655 | J112: 40604 | K112: 46270 | L112: 51343 | M112: 67010
A113: Ships Vessels | B113: 0 | C113: 0 | D113: 0 | E113: 0 | F113: 0 | G113: 0 | H113: 717 | I113: 830 | J113: 719 | K113: 793 | L113: 801 | M113: 792
A114: Equipments | B114: 214 | C114: 236 | D114: 99 | E114: 115 | F114: 150 | G114: 208 | H114: 265 | I114: 289 | J114: 336 | K114: 387 | L114: 466 | M114: 555
A115: Furniture n fittings | B115: 146 | C115: 163 | D115: 57 | E115: 71 | F115: 80 | G115: 106 | H115: 112 | I115: 111 | J115: 114 | K115: 122 | L115: 154 | M115: 219
A116: Railway sidings | B116: 492 | C116: 536 | D116: 399 | E116: 444 | F116: 653 | G116: 890 | H116: 906 | I116: 959 | J116: 989 | K116: 1008 | L116: 1088 | M116: 1305
A117: Vehicles | B117: 65 | C117: 78 | D117: 46 | E117: 63 | F117: 91 | G117: 110 | H117: 122 | I117: 133 | J117: 163 | K117: 200 | L117: 260 | M117: 354
A118: Intangible Assets | B118: 967 | C118: 1053 | D118: 1287 | E118: 1329 | F118: 1280 | G118: 6626 | H118: 6680 | I118: 6375 | J118: 6405 | K118: 6484 | L118: 6501 | M118: 8108 | N118: 17730
A119: Other fixed assets | B119: 275 | C119: 414 | D119: 176 | E119: 213 | F119: 3073 | G119: 5899 | H119: 5927 | I119: 6289 | J119: 6387 | K119: 6695 | L119: 6637 | M119: 11055
A120: Gross Block | B120: 27854 | C120: 34910 | D120: 26611 | E120: 28498 | F120: 44082 | G120: 63382 | H120: 66550 | I120: 67332 | J120: 70002 | K120: 76957 | L120: 83280 | M120: 118631
A121: Accumulated Depreciation | B121: 9754 | C121: 11567 | D121: 1302 | E121: 2594 | F121: 4366 | G121: 6737 | H121: 9399 | I121: 11921 | J121: 14514 | K121: 17378 | L121: 20403 | M121: 24067
A122: CWIP | B122: 2186 | C122: 2250 | D122: 1469 | E122: 921 | F122: 1511 | G122: 1153 | H122: 920 | I122: 1687 | J122: 4785 | K122: 4040 | L122: 6811 | M122: 6234 | N122: 7206
A123: Investments | B123: 4862 | C123: 4500 | D123: 5095 | E123: 6691 | F123: 5447 | G123: 2921 | H123: 5929 | I123: 12178 | J123: 6336 | K123: 7297 | L123: 8249 | M123: 5156 | N123: 5098
A124: Other Assets - | B124: 7037 | C124: 7961 | D124: 9319 | E124: 8693 | F124: 10468 | G124: 15806 | H124: 15215 | I124: 16900 | J124: 17203 | K124: 20464 | L124: 22859 | M124: 27677 | N124: 29072
A125: Inventories | B125: 2580 | C125: 2949 | D125: 2455 | E125: 2401 | F125: 3268 | G125: 4099 | H125: 4183 | I125: 4018 | J125: 5596 | K125: 6612 | L125: 8330 | M125: 9563 | N125: 10471
A126: Trade receivables + | B126: 1632 | C126: 1659 | D126: 1928 | E126: 1757 | F126: 2221 | G126: 2787 | H126: 2383 | I126: 2572 | J126: 3072 | K126: 3867 | L126: 4278 | M126: 5890 | N126: 5818
A127: Cash Equivalents | B127: 348 | C127: 371 | D127: 2267 | E127: 2249 | F127: 219 | G127: 740 | H127: 540 | I127: 2008 | J127: 359 | K127: 1150 | L127: 783 | M127: 1673 | N127: 1288
A128: Loans n Advances | B128: 145 | C128: 2 | D128: 377 | E128: 519 | F128: 544 | G128: 750 | H128: 796 | I128: 660 | J128: 873 | K128: 951 | L128: 985 | M128: 1259 | N128: 3060
A129: Other asset items | B129: 2331 | C129: 2980 | D129: 2292 | E129: 1768 | F129: 4216 | G129: 7430 | H129: 7312 | I129: 7642 | J129: 7304 | K129: 7885 | L129: 8483 | M129: 9292 | N129: 8435
A130: Total Assets | B130: 32185 | C130: 38053 | D130: 41193 | E130: 42209 | F130: 57141 | G130: 76525 | H130: 79214 | I130: 86176 | J130: 83811 | K130: 91380 | L130: 100797 | M130: 133632 | N130: 137305
B133: 44286 | C133: 44651 | D133: 45016 | E133: 45382 | F133: 45747
A134: Production (MMT)
A135: Cement | B135: 82.72 | C135: 90.36 | D135: 103.13 | E135: 115.84 | F135: 131.64
A136: Clinker | B136: 61.08 | C136: 67.85 | D136: 74.14 | E136: 80.92 | F136: 92.48
A138: Sales Volume - Grey Cement (MMT) | B138: 85.1 | C138: 92.53 | D138: 104.09 | E138: 117.2 | F138: 133.14
A140: Capital Employed | B140: 70702 | C140: 66652 | D140: 70535 | E140: 77025 | F140: 106435

Sheet CF Data
C2: 42430 | D2: 42795 | E2: 43160 | F2: 43525 | G2: 43891 | H2: 44256 | I2: 44621 | J2: 44986 | K2: 45352 | L2: 45717
B3: Cash from Operating Activity - | C3: 4526 | D3: 5005 | E3: 3888 | F3: 5956 | G3: 8972 | H3: 12500 | I3: 9283 | J3: 9069 | K3: 10898 | L3: 10673
B4: Profit from operations | C4: 4948 | D4: 5220 | E4: 5986 | F4: 7362 | G4: 9348 | H4: 11465 | I4: 11311 | J4: 10530 | K4: 13029 | L4: 12645
B5: Receivables | C5: -287 | D5: 156 | E5: -454 | F5: -279 | G5: 473 | H5: -201 | I5: -495 | J5: -752 | K5: -421 | L5: -608
B6: Inventory | C6: 374 | D6: 54 | E6: -623 | F6: -15 | G6: -64 | H6: 165 | I6: -1579 | J6: -992 | K6: -1712 | L6: -317
B7: Payables | C7: 310 | D7: 482 | E7: 346 | F7: 766 | G7: 279 | H7: 2868 | I7: 2077 | J7: 1869 | K7: 1959 | L7: -476
B8: Loans Advances | C8: 0 | D8: 0 | E8: 0 | F8: 0 | G8: 0 | H8: 0 | I8: 0 | J8: 0 | K8: 0 | L8: 0
B9: Other WC items | C9: 32 | D9: -162 | E9: -525 | F9: -1167 | G9: -172 | H9: -505 | I9: -476 | J9: -461 | K9: -308 | L9: 729
B10: Working capital changes | C10: 429 | D10: 529 | E10: -1255 | F10: -696 | G10: 516 | H10: 2326 | I10: -473 | J10: -337 | K10: -481 | L10: -671
B11: Direct taxes | C11: -852 | D11: -744 | E11: -843 | F11: -710 | G11: -891 | H11: -1291 | I11: -1555 | J11: -1124 | K11: -1651 | L11: -1301
B12: Other operating items | C12: 0 | D12: 0 | E12: 0 | F12: 0 | G12: 0 | H12: 0 | I12: 0 | J12: 0 | K12: 0 | L12: 0
B13: Cash from Investing Activity - | C13: -3673 | D13: -2501 | E13: 1866 | F13: 1165 | G13: -4192 | H13: -8856 | I13: 2257 | J13: -7188 | K13: -8789 | L13: -15836
B14: Fixed assets purchased | C14: -2150 | D14: -1402 | E14: -2103 | F14: -1808 | G14: -1766 | H14: -1925 | I14: -5613 | J14: -6200 | K14: -9006 | L14: -9129
... B33: Net Cash Flow | C33: 8 | D33: -31 | E33: 18 | F33: 364 | G33: -295 | H33: -712 | I33: -958 | J33: 250 | K33: 183 | L33: -86

Sheet StockData
B2: Date | C2: UltraTech Cement | D2: Nifty 50 | J2: Price | K2: Open | L2: High | M2: Low | N2: Vol. | O2: Change % | P2: Date | Q2: Price | R2: Open | S2: High | T2: Low | U2: Vol. | V2: Change %
B3: 46134 | C3: 12193 | D3: 24378.1 | K3: 12013 | L3: 12222 | M3: 12001 | N3: 312.31K | O3: 0.0128 | P3: 46134 | R3: 24470.85 | S3: 24515.75 | T3: 24353.85 | U3: 440.52M | V3: -0.0081
B4: 46133 | C4: 12039 | D4: 24576.6 | E4: =C3/C4-1 -> 0.01279176 | F4: =D3/D4-1 -> -0.0080767885 | K4: 11800 | L4: 12065 | M4: 11800 | N4: 320.11K | O4: 0.0102 | P4: 46133 | R4: 24374.55 | S4: 24601.7 | T4: 24354.9 | U4: 425.83M | V4: 0.0087
B5: 46132 | C5: 11917 | D5: 24364.85 | E5: =C4/C5-1 -> 0.010237476 | F5: =D4/D5-1 -> 0.0086907984 | K5: 11970 | L5: 12062 | M5: 11816 | N5: 335.62K | O5: 0.0026 | P5: 46132 | R5: 24391.5 | S5: 24480.65 | T5: 24241.25 | U5: 415.94M | V5: 0.0005
B6: 46129 | C6: 11886 | D6: 24353.55 | E6: =C5/C6-1 -> 0.0026081104 | F6: =D5/D6-1 -> 0.00046399806 | K6: 11820 | L6: 11930 | M6: 11737 | N6: 165.11K | O6: 0.0051 | P6: 46129 | R6: 24165.9 | S6: 24371.9 | T6: 24096.05 | U6: 498.63M | V6: 0.0065
B7: 46128 | C7: 11826 | D7: 24196.75 | E7: =C6/C7-1 -> 0.0050735667 | F7: =D6/D7-1 -> 0.0064802091 | K7: 11840 | L7: 11859 | M7: 11710 | N7: 308.55K | O7: 0.0035 | P7: 46128 | R7: 24385.2 | S7: 24400.95 | T7: 24102.8 | U7: 508.02M | V7: -0.0014
B8: 46127 | C8: 11785 | D8: 24231.3 | E8: =C7/C8-1 -> 0.0034789987 | F8: =D7/D8-1 -> -0.0014258418 | K8: 11840 | L8: 11950 | M8: 11711 | N8: 274.81K | O8: 0.0246 | P8: 46127 | R8: 24163.8 | S8: 24280.9 | T8: 24145.8 | U8: 460.33M | V8: 0.0163
B9: 46125 | C9: 11502 | D9: 23842.65 | E9: =C8/C9-1 -> 0.024604417 | F9: =D8/D9-1 -> 0.016300621 | K9: 11366 | L9: 11522 | M9: 11282 | N9: 220.44K | O9: -0.0075 | P9: 46125 | R9: 23589.6 | S9: 23907.4 | T9: 23555.6 | U9: 488.84M | V9: -0.0086
B10: 46122 | C10: 11589 | D10: 24050.6 | E10: =C9/C10-1 -> -0.0075071188 | F10: =D9/D10-1 -> -0.0086463539 | K10: 11500 | L10: 11643 | M10: 11476 | N10: 420.34K | O10: 0.0123 | P10: 46122 | R10: 23880.55 | S10: 24074.05 | T10: 23856.35 | U10: 481.30M | V10: 0.0116
B11: 46121 | C11: 11448 | D11: 23775.1 | E11: =C10/C11-1 -> 0.012316562 | F11: =D10/D11-1 -> 0.011587754 | K11: 11425 | L11: 11562 | M11: 11390 | N11: 330.55K | O11: -0.0134 | P11: 46121 | R11: 23909.05 | S11: 23990.75 | T11: 23682.8 | U11: 466.59M | V11: -0.0093
B12: 46120 | C12: 11603 | D12: 23997.35 | E12: =C11/C12-1 -> -0.013358614 | F12: =D11/D12-1 -> -0.0092614393 | K12: 11400 | L12: 11776 | M12: 11349 | N12: 612.76K | O12: 0.061 | P12: 46120 | R12: 23855.15 | S12: 24025.15 | T12: 23828.5 | U12: 639.26M | V12: 0.0378
B13: 46119 | C13: 10936 | D13: 23123.65 | E13: =C12/C13-1 -> 0.060991222 | F13: =D12/D13-1 -> 0.037783827 | K13: 10922 | L13: 10954 | M13: 10765 | N13: 263.66K | O13: -0.0017 | P13: 46119 | R13: 22838.7 | S13: 23153.85 | T13: 22719.3 | U13: 476.98M | V13: 0.0068
B14: 46118 | C14: 10955 | D14: 22968.25 | E14: =C13/C14-1 -> -0.0017343679 | F14: =D13/D14-1 -> 0.0067658616 | K14: 10611 | L14: 10976 | M14: 10540 | N14: 374.42K | O14: 0.0315 | P14: 46118 | R14: 22780.3 | S14: 22998.35 | T14: 22542.95 | U14: 426.42M | V14: 0.0112
B15: 46114 | C15: 10620 | D15: 22713.1 | E15: =C14/C15-1 -> 0.031544256 | F15: =D14/D15-1 -> 0.011233605 | K15: 10639 | L15: 10663 | M15: 10365 | N15: 333.52K | O15: -0.0088 | P15: 46114 | R15: 22383.4 | S15: 22782.3 | T15: 22182.55 | U15: 495.12M | V15: 0.0015
... B268: 45740 | C268: 11051.2 | D268: 23658.35 | E268: =C267/C268-1 -> 0.033480527 | F268: =D267/D268-1 -> 0.00043536426 | K268: 11018.95 | L268: 11077.95 | M268: 10853.85 | N268: 294.69K | O268: 0.0068 | P268: 45740 | R268: 23515.4 | S268: 23708.75 | T268: 23433.5 | U268: 311.90M | V268: 0.0132

Sheet Historical->

Sheet Inc_Stat
D2: UltraTech Cement Ltd (NSE: ULTRACEMCO)
D3: Income Statement
D4: (Figures are in ₹ Cr, except price per share)
D6: Reported Income Statement
F7: Fiscal Year Ending March 31, | P7: ='Historical FS'!M11 -> LTM
D8: Particulars | F8: ='Historical FS'!C11 -> 42460 | G8: ='Historical FS'!D11 -> 42825 | H8: ='Historical FS'!E11 -> 43190 | I8: ='Historical FS'!F11 -> 43555 | J8: ='Historical FS'!G11 -> 43921 | K8: ='Historical FS'!H11 -> 44286 | L8: ='Historical FS'!I11 -> 44651 | M8: ='Historical FS'!J11 -> 45016 | ... O8: ='Historical FS'!L11 -> 45747 | P8: 03/31/2026
D9: Revenue | F9: ='Historical FS'!C14 -> 25153.24 | G9: ='Historical FS'!D14 -> 25374.94 | H9: ='Historical FS'!E14 -> 30978.62 | I9: ='Historical FS'!F14 -> 41462.26 | J9: ='Historical FS'!G14 -> 42429.89 | K9: ='Historical FS'!H14 -> 44725.8 | L9: ='Historical FS'!I14 -> 52598.83 | M9: ='Historical FS'!J14 -> 63239.98 | ... P9: ='Historical FS'!M14 -> 62712.06
D10: % Growth | F10: NA | G10: =G9/F9-1 -> 0.0088139739 | H10: =H9/G9-1 -> 0.2208352 | I10: =I9/H9-1 -> 0.33841533 | J10: =J9/I9-1 -> 0.023337609 | K10: =K9/J9-1 -> 0.054110675 | L10: =L9/K9-1 -> 0.17602882 | M10: =M9/L9-1 -> 0.20230773 | N10: =N9/M9-1 -> 0.12125494 | ... P10: =P9/O9-1 -> -0.17435386
D11: Cost of Goods Sold | F11: ='Historical FS'!C15 -> 12397.13 | G11: ='Historical FS'!D15 -> 12303.62 | H11: ='Historical FS'!E15 -> 15744.19 | I11: ='Historical FS'!F15 -> 21729.72 | J11: ='Historical FS'!G15 -> 20600.87 | K11: ='Historical FS'!H15 -> 20847.7 | L11: ='Historical FS'!I15 -> 26536.92 | M11: ='Historical FS'!J15 -> 35301.93 | ... P11: ='Historical FS'!M15 -> 51306.6
D12: % Margin | F12: =ABS(F11/F$9) -> 0.49286414 | G12: =ABS(G11/G$9) -> 0.48487287 | H12: =ABS(H11/H$9) -> 0.50822761 | I12: =ABS(I11/I$9) -> 0.52408431 | J12: =ABS(J11/J$9) -> 0.4855273 | K12: =ABS(K11/K$9) -> 0.46612246 | L12: =ABS(L11/L$9) -> 0.5045154 | M12: =ABS(M11/M$9) -> 0.55822171 | ... P12: =ABS(P11/P$9) -> 0.81812972
D13: Gross Margin | F13: =F9-F11 -> 12756.11 | G13: =G9-G11 -> 13071.32 | H13: =H9-H11 -> 15234.43 | I13: =I9-I11 -> 19732.54 | J13: =J9-J11 -> 21829.02 | K13: =K9-K11 -> 23878.1 | L13: =L9-L11 -> 26061.91 | M13: =M9-M11 -> 27938.05 | ... P13: =P9-P11 -> 11405.46
D14: % Margin | F14: =ABS(F13/F$9) -> 0.50713586 | G14: =ABS(G13/G$9) -> 0.51512713 | H14: =ABS(H13/H$9) -> 0.49177239 | I14: =ABS(I13/I$9) -> 0.47591569 | J14: =ABS(J13/J$9) -> 0.5144727 | K14: =ABS(K13/K$9) -> 0.53387754 | L14: =ABS(L13/L$9) -> 0.4954846 | M14: =ABS(M13/M$9) -> 0.44177829 | ... P14: =ABS(P13/P$9) -> 0.18187028
D16: Selling, General & Administration | F16: =-'Historical FS'!C17 -> -7855.14 | G16: =-'Historical FS'!D17 -> -7858.88 | H16: =-'Historical FS'!E17 -> -9089.4 | I16: =-'Historical FS'!F17 -> -12385.6 | J16: =-'Historical FS'!G17 -> -12583.05 | K16: =-'Historical FS'!H17 -> -12310.19 | L16: =-'Historical FS'!I17 -> -14547.56 | M16: =-'Historical FS'!J17 -> -17318.2 | ... P16: =-'Historical FS'!M17 -> 0
D17: % Margin | F17: =ABS(F16/F$9) -> 0.31229138 | G17: =ABS(G16/G$9) -> 0.30971029 | H17: =ABS(H16/H$9) -> 0.29340881 | I17: =ABS(I16/I$9) -> 0.29871985 | J17: =ABS(J16/J$9) -> 0.29656099 | K17: =ABS(K16/K$9) -> 0.27523689 | L17: =ABS(L16/L$9) -> 0.27657573 | M17: =ABS(M16/M$9) -> 0.27384892 | ... P17: =ABS(P16/P$9) -> 0
D18: EBITDA | F18: =F13+F16 -> 4900.97 | G18: =G13+G16 -> 5212.44 | H18: =H13+H16 -> 6145.03 | I18: =I13+I16 -> 7346.94 | J18: =J13+J16 -> 9245.97 | K18: =K13+K16 -> 11567.91 | L18: =L13+L16 -> 11514.35 | M18: =M13+M16 -> 10619.85 | ... P18: =P13+P16 -> 11405.46
D19: % Margin | F19: =ABS(F18/F$9) -> 0.19484448 | G19: =ABS(G18/G$9) -> 0.20541684 | H19: =ABS(H18/H$9) -> 0.19836358 | I19: =ABS(I18/I$9) -> 0.17719584 | J19: =ABS(J18/J$9) -> 0.21791171 | K19: =ABS(K18/K$9) -> 0.25864065 | L19: =ABS(L18/L$9) -> 0.21890886 | M19: =ABS(M18/M$9) -> 0.16792937 | ... P19: =ABS(P18/P$9) -> 0.18187028
D21: Depreciation | F21: =-'Historical FS'!C19 -> -1377.17 | G21: =-'Historical FS'!D19 -> -1348.41 | H21: =-'Historical FS'!E19 -> -1847.93 | I21: =-'Historical FS'!F19 -> -2450.73 | J21: =-'Historical FS'!G19 -> -2722.66 | K21: =-'Historical FS'!H19 -> -2700.23 | L21: =-'Historical FS'!I19 -> -2714.75 | M21: =-'Historical FS'!J19 -> -2887.99 | ... P21: =-'Historical FS'!M19 -> -3436.36
D22: % Margin | F22: =ABS(F21/F$9) -> 0.054751197 | G22: =ABS(G21/G$9) -> 0.053139436 | H22: =ABS(H21/H$9) -> 0.059651786 | I22: =ABS(I21/I$9) -> 0.059107487 | J22: =ABS(J21/J$9) -> 0.064168444 | K22: =ABS(K21/K$9) -> 0.060372984 | L22: =ABS(L21/L$9) -> 0.051612365 | M22: =ABS(M21/M$9) -> 0.045667155 | ... P22: =ABS(P21/P$9) -> 0.05479584
D23: EBIT | F23: =F18+F21 -> 3523.8 | G23: =G18+G21 -> 3864.03 | H23: =H18+H21 -> 4297.1 | I23: =I18+I21 -> 4896.21 | J23: =J18+J21 -> 6523.31 | K23: =K18+K21 -> 8867.68 | L23: =L18+L21 -> 8799.6 | M23: =M18+M21 -> 7731.86 | ... P23: =P18+P21 -> 7969.1
D24: % Margin | F24: =ABS(F23/F$9) -> 0.14009328 | G24: =ABS(G23/G$9) -> 0.1522774 | H24: =ABS(H23/H$9) -> 0.1387118 | I24: =ABS(I23/I$9) -> 0.11808835 | J24: =ABS(J23/J$9) -> 0.15374327 | K24: =ABS(K23/K$9) -> 0.19826767 | L24: =ABS(L23/L$9) -> 0.1672965 | M24: =ABS(M23/M$9) -> 0.12226221 | ... P24: =ABS(P23/P$9) -> 0.12707444
D26: Interest Expense | F26: =-'Historical FS'!C20 -> -566.3 | G26: =-'Historical FS'!D20 -> -640.1 | H26: =-'Historical FS'!E20 -> -1237.6 | I26: =-'Historical FS'!F20 -> -1777.86 | J26: =-'Historical FS'!G20 -> -1991.65 | K26: =-'Historical FS'!H20 -> -1485.65 | L26: =-'Historical FS'!I20 -> -944.71 | M26: =-'Historical FS'!J20 -> -822.72 | ... P26: =-'Historical FS'!M20 -> -1384.79
D27: % Margin | F27: =ABS(F26/F$9) -> 0.022513998 | G27: =ABS(G26/G$9) -> 0.025225675 | H27: =ABS(H26/H$9) -> 0.039950133 | I27: =ABS(I26/I$9) -> 0.042878994 | J27: =ABS(J26/J$9) -> 0.046939787 | K27: =ABS(K26/K$9) -> 0.033216846 | L27: =ABS(L26/L$9) -> 0.017960666 | M27: =ABS(M26/M$9) -> 0.013009492 | ... P27: =ABS(P26/P$9) -> 0.022081718
D28: Profit Before Taxes | F28: =F23+F26 -> 2957.5 | G28: =G23+G26 -> 3223.93 | H28: =H23+H26 -> 3059.5 | I28: =I23+I26 -> 3118.35 | J28: =J23+J26 -> 4531.66 | K28: =K23+K26 -> 7382.03 | L28: =L23+L26 -> 7854.89 | M28: =M23+M26 -> 6909.14 | ... P28: =P23+P26 -> 6584.31
D29: % Margin | F29: =ABS(F28/F$9) -> 0.11757929 | G29: =ABS(G28/G$9) -> 0.12705173 | H29: =ABS(H28/H$9) -> 0.098761662 | I29: =ABS(I28/I$9) -> 0.075209359 | J29: =ABS(J28/J$9) -> 0.10680348 | K29: =ABS(K28/K$9) -> 0.16505082 | L29: =ABS(L28/L$9) -> 0.14933583 | M29: =ABS(M28/M$9) -> 0.10925272 | ... P29: =ABS(P28/P$9) -> 0.10499272
D31: Taxes | F31: =-'Historical FS'!C22 -> -941.69 | G31: =-'Historical FS'!D22 -> -1158.54 | H31: =-'Historical FS'!E22 -> -1077.01 | I31: =-'Historical FS'!F22 -> -1068.07 | J31: =-'Historical FS'!G22 -> 568.16 | K31: =-'Historical FS'!H22 -> -2538.7 | L31: =-'Historical FS'!I22 -> -1190.06 | M31: =-'Historical FS'!J22 -> -2342.85 | ... P31: =-'Historical FS'!M22 -> -1758.32
D32: % Tax Rate | F32: =ABS(F31/F$28) -> 0.31840744 | G32: =ABS(G31/G$28) -> 0.35935644 | H32: =ABS(H31/H$28) -> 0.35202157 | I32: =ABS(I31/I$28) -> 0.34251126 | J32: =ABS(J31/J$28) -> 0.12537569 | K32: =ABS(K31/K$28) -> 0.34390269 | L32: =ABS(L31/L$28) -> 0.15150562 | M32: =ABS(M31/M$28) -> 0.3390943 | ... O32: =ABS(O31/O$28) -> 0.20872369 | P32: =ABS(P31/P$9) -> 0.028037988
D33: Net Profit | F33: =F28+F31 -> 2015.81 | G33: =G28+G31 -> 2065.39 | H33: =H28+H31 -> 1982.49 | I33: =I28+I31 -> 2050.28 | J33: =J28+J31 -> 5099.82 | K33: =K28+K31 -> 4843.33 | L33: =L28+L31 -> 6664.83 | M33: =M28+M31 -> 4566.29 | ... P33: =P28+P31 -> 4825.99
D34: % Margin | F34: =ABS(F33/F$9) -> 0.080141167 | G34: =ABS(G33/G$9) -> 0.081394872 | H34: =ABS(H33/H$9) -> 0.063995427 | I34: =ABS(I33/I$9) -> 0.049449306 | J34: =ABS(J33/J$9) -> 0.12019404 | K34: =ABS(K33/K$9) -> 0.1082894 | L34: =ABS(L33/L$9) -> 0.12671061 | M34: =ABS(M33/M$9) -> 0.072205747 | ... P34: =ABS(P33/P$9) -> 0.076954736
D36: Fully Diluted Shares | F36: ='Historical FS'!C26 -> 27.44 | G36: ='Historical FS'!D26 -> 27.45 | H36: ='Historical FS'!E26 -> 27.46 | I36: ='Historical FS'!F26 -> 27.46 | J36: ='Historical FS'!G26 -> 28.86 | K36: ='Historical FS'!H26 -> 28.87 | L36: ='Historical FS'!I26 -> 28.87 | M36: ='Historical FS'!J26 -> 28.87 | ... O36: ='Historical FS'!L26 -> 29.47 | P36: =O36 -> 29.47
D38: Earnings per Share (₹) | F38: =F33/F36 -> 73.462464 | G38: =G33/G36 -> 75.241894 | H38: =H33/H36 -> 72.195557 | I38: =I33/I36 -> 74.664239 | J38: =J33/J36 -> 176.70894 | K38: =K33/K36 -> 167.76342 | L38: =L33/L36 -> 230.8566 | M38: =M33/M36 -> 158.1673 | ... P38: =P33/P36 -> 163.75942
D39: % EPS Growth | F39: NA | G39: =G38/F38-1 -> 0.024222313 | H39: =H38/G38-1 -> -0.040487247 | I39: =I38/H38-1 -> 0.034194372 | J39: =J38/I38-1 -> 1.3667145 | K39: =K38/J38-1 -> -0.050622891 | L39: =L38/K38-1 -> 0.37608422 | M39: =M38/L38-1 -> -0.31486775 | N39: =N38/M38-1 -> 0.41186828 | ... P39: =P38/O38-1 -> -0.14476776
D41: Dividend per Share (₹) | F41: ='Data Sheet'!B31/Inc_Stat!F36 -> 9.5010933 | G41: ='Data Sheet'!C31/Inc_Stat!G36 -> 10.000364 | H41: ='Data Sheet'!D31/Inc_Stat!H36 -> 10.500364 | I41: ='Data Sheet'!E31/Inc_Stat!I36 -> 11.501821 | J41: ='Data Sheet'!F31/Inc_Stat!J36 -> 13.001386 | K41: ='Data Sheet'!G31/Inc_Stat!K36 -> 36.993419 | L41: ='Data Sheet'!H31/Inc_Stat!L36 -> 37.99619 | M41: ='Data Sheet'!I31/Inc_Stat!M36 -> 37.998614 | ... O41: ='Data Sheet'!K31/Inc_Stat!O36 -> 77.49474
D42: Dividend Payout Ratio | F42: =F41/F38 -> 0.12933263 | G42: =G41/G38 -> 0.13290952 | H42: =H41/H38 -> 0.14544336 | I42: =I41/I38 -> 0.15404725 | J42: =J41/J38 -> 0.073575146 | K42: =K41/K38 -> 0.22050944 | L42: =L41/L38 -> 0.16458784 | M42: =M41/M38 -> 0.24024317 | ... O42: =O41/O38 -> 0.40471566
D44: Retained Earnings (%) | F44: =(1-F42) -> 0.87066737 | G44: =(1-G42) -> 0.86709048 | H44: =(1-H42) -> 0.85455664 | I44: =(1-I42) -> 0.84595275 | J44: =(1-J42) -> 0.92642485 | K44: =(1-K42) -> 0.77949056 | L44: =(1-L42) -> 0.83541216 | M44: =(1-M42) -> 0.75975683 | ... O44: =(1-O42) -> 0.59528434

Sheet Bal_Sht
D2: UltraTech Cement Ltd (NSE: ULTRACEMCO)
D3: Balance Sheet
D4: (Figures are in ₹ Cr, except price per share)
D6: Reported Balance Sheet
F7: Fiscal Year Ending March 31,
D8: Particulars | F8: ='Historical FS'!C11 -> 42460 | G8: ='Historical FS'!D11 -> 42825 | H8: ='Historical FS'!E11 -> 43190 | I8: ='Historical FS'!F11 -> 43555 | J8: ='Historical FS'!G11 -> 43921 | K8: ='Historical FS'!H11 -> 44286 | L8: ='Historical FS'!I11 -> 44651 | M8: ='Historical FS'!J11 -> 45016 | ... O8: ='Historical FS'!L11 -> 45747
D9: Equity Share Capital | F9: ='Historical FS'!C37 -> 274.43 | G9: ='Historical FS'!D37 -> 274.51 | H9: ='Historical FS'!E37 -> 274.61 | I9: ='Historical FS'!F37 -> 274.64 | J9: ='Historical FS'!G37 -> 288.63 | K9: ='Historical FS'!H37 -> 288.65 | L9: ='Historical FS'!I37 -> 288.67 | M9: ='Historical FS'!J37 -> 288.69 | ... O9: ='Historical FS'!L37 -> 294.68
D10: Reserves | F10: ='Historical FS'!C38 -> 21671.2 | G10: ='Historical FS'!D38 -> 24117.38 | H10: ='Historical FS'!E38 -> 26106.55 | I10: ='Historical FS'!F38 -> 33476.01 | J10: ='Historical FS'!G38 -> 38755.13 | K10: ='Historical FS'!H38 -> 43886.03 | L10: ='Historical FS'!I38 -> 50146.6 | M10: ='Historical FS'!J38 -> 54035.85 | ... O10: ='Historical FS'!L38 -> 70412.09
D11: Borrowings | F11: ='Historical FS'!C39 -> 10615.99 | G11: ='Historical FS'!D39 -> 8474.49 | H11: ='Historical FS'!E39 -> 19480.22 | I11: ='Historical FS'!F39 -> 25337 | J11: ='Historical FS'!G39 -> 23018.96 | K11: ='Historical FS'!H39 -> 21719.39 | L11: ='Historical FS'!I39 -> 11298.8 | M11: ='Historical FS'!J39 -> 11057.74 | ... O11: ='Historical FS'!L39 -> 24102.18
D12: Other Liabilities | F12: ='Historical FS'!C40 -> 8631.49 | G12: ='Historical FS'!D40 -> 9342.73 | H12: ='Historical FS'!E40 -> 11279.71 | I12: ='Historical FS'!F40 -> 17437.72 | J12: ='Historical FS'!G40 -> 17151.09 | K12: ='Historical FS'!H40 -> 20282.28 | L12: ='Historical FS'!I40 -> 22077.37 | M12: ='Historical FS'!J40 -> 25998.12 | ... O12: ='Historical FS'!L40 -> 38823.11
D13: Total Liabilities & Equity | F13: =SUM(F9:F12) -> 41193.11 | G13: =SUM(G9:G12) -> 42209.11 | H13: =SUM(H9:H12) -> 57141.09 | I13: =SUM(I9:I12) -> 76525.37 | J13: =SUM(J9:J12) -> 79213.81 | K13: =SUM(K9:K12) -> 86176.35 | L13: =SUM(L9:L12) -> 83811.44 | M13: =SUM(M9:M12) -> 91380.4 | ... O13: =SUM(O9:O12) -> 133632.06
D15: Fixed Assets Net Block | F15: ='Historical FS'!C43 -> 25309.42 | G15: ='Historical FS'!D43 -> 25903.75 | H15: ='Historical FS'!E43 -> 39715.3 | I15: ='Historical FS'!F43 -> 56644.62 | J15: ='Historical FS'!G43 -> 57150.96 | K15: ='Historical FS'!H43 -> 55411.61 | L15: ='Historical FS'!I43 -> 55487.57 | M15: ='Historical FS'!J43 -> 59579 | ... O15: ='Historical FS'!L43 -> 94564.22
D16: Capital Work in Progress | F16: ='Historical FS'!C44 -> 1469.09 | G16: ='Historical FS'!D44 -> 921.48 | H16: ='Historical FS'!E44 -> 1511.21 | I16: ='Historical FS'!F44 -> 1153.32 | J16: ='Historical FS'!G44 -> 919.59 | K16: ='Historical FS'!H44 -> 1686.68 | L16: ='Historical FS'!I44 -> 4784.67 | M16: ='Historical FS'!J44 -> 4040.39 | ... O16: ='Historical FS'!L44 -> 6234.19
D17: Investments | F17: ='Historical FS'!C45 -> 5095.18 | G17: ='Historical FS'!D45 -> 6690.51 | H17: ='Historical FS'!E45 -> 5446.9 | I17: ='Historical FS'!F45 -> 2921.33 | J17: ='Historical FS'!G45 -> 5928.69 | K17: ='Historical FS'!H45 -> 12178.11 | L17: ='Historical FS'!I45 -> 6335.77 | M17: ='Historical FS'!J45 -> 7296.95 | ... O17: ='Historical FS'!L45 -> 5156.47
D18: Other Assets | F18: ='Historical FS'!C46 -> 2669.67 | G18: ='Historical FS'!D46 -> 2286.86 | H18: ='Historical FS'!E46 -> 4760.39 | I18: ='Historical FS'!F46 -> 8180.43 | J18: ='Historical FS'!G46 -> 8108.09 | K18: ='Historical FS'!H46 -> 8302.7 | L18: ='Historical FS'!I46 -> 8177.06 | M18: ='Historical FS'!J46 -> 8835.62 | ... O18: ='Historical FS'!L46 -> 10550.63
D19: Total Non Current Assets | F19: =SUM(F15:F18) -> 34543.36 | G19: =SUM(G15:G18) -> 35802.6 | H19: =SUM(H15:H18) -> 51433.8 | I19: =SUM(I15:I18) -> 68899.7 | J19: =SUM(J15:J18) -> 72107.33 | K19: =SUM(K15:K18) -> 77579.1 | L19: =SUM(L15:L18) -> 74785.07 | M19: =SUM(M15:M18) -> 79751.96 | ... O19: =SUM(O15:O18) -> 116505.51
D21: Receivables | F21: ='Historical FS'!C49 -> 1928.21 | G21: ='Historical FS'!D49 -> 1757.09 | H21: ='Historical FS'!E49 -> 2220.63 | I21: ='Historical FS'!F49 -> 2787.03 | J21: ='Historical FS'!G49 -> 2383.22 | K21: ='Historical FS'!H49 -> 2571.73 | L21: ='Historical FS'!I49 -> 3071.61 | M21: ='Historical FS'!J49 -> 3867.02 | ... O21: ='Historical FS'!L49 -> 5890.25
D22: Inventory | F22: ='Historical FS'!C50 -> 2454.58 | G22: ='Historical FS'!D50 -> 2400.64 | H22: ='Historical FS'!E50 -> 3267.59 | I22: ='Historical FS'!F50 -> 4098.96 | J22: ='Historical FS'!G50 -> 4183.35 | K22: ='Historical FS'!H50 -> 4017.97 | L22: ='Historical FS'!I50 -> 5595.58 | M22: ='Historical FS'!J50 -> 6611.83 | ... O22: ='Historical FS'!L50 -> 9562.98
D23: Cash & Bank | F23: ='Historical FS'!C51 -> 2266.96 | G23: ='Historical FS'!D51 -> 2248.78 | H23: ='Historical FS'!E51 -> 219.07 | I23: ='Historical FS'!F51 -> 739.68 | J23: ='Historical FS'!G51 -> 539.91 | K23: ='Historical FS'!H51 -> 2007.55 | L23: ='Historical FS'!I51 -> 359.18 | M23: ='Historical FS'!J51 -> 1149.59 | ... O23: ='Historical FS'!L51 -> 1673.32
D24: Total Current Assets | F24: =SUM(F21:F23) -> 6649.75 | G24: =SUM(G21:G23) -> 6406.51 | H24: =SUM(H21:H23) -> 5707.29 | I24: =SUM(I21:I23) -> 7625.67 | J24: =SUM(J21:J23) -> 7106.48 | K24: =SUM(K21:K23) -> 8597.25 | L24: =SUM(L21:L23) -> 9026.37 | M24: =SUM(M21:M23) -> 11628.44 | ... O24: =SUM(O21:O23) -> 17126.55
D25: Total Assets | F25: =F24+F19 -> 41193.11 | G25: =G24+G19 -> 42209.11 | H25: =H24+H19 -> 57141.09 | I25: =I24+I19 -> 76525.37 | J25: =J24+J19 -> 79213.81 | K25: =K24+K19 -> 86176.35 | L25: =L24+L19 -> 83811.44 | M25: =M24+M19 -> 91380.4 | ... O25: =O24+O19 -> 133632.06
D27: Balance Check | F27: =F13=F25 -> TRUE | G27: =G13=G25 -> TRUE | H27: =H13=H25 -> TRUE | I27: =I13=I25 -> TRUE | J27: =J13=J25 -> TRUE | K27: =K13=K25 -> TRUE | L27: =L13=L25 -> TRUE | M27: =M13=M25 -> TRUE | ... O27: =O13=O25 -> TRUE

Sheet Cash_Flow
D2: UltraTech Cement Ltd (NSE: ULTRACEMCO)
D3: Cash Flow Statement
D4: (Figures are in ₹ Cr, except price per share)
D6: Reported Cash Flow Statement
F7: Fiscal Year Ending March 31,
D8: Particulars | F8: ='Historical FS'!C11 -> 42460 | G8: ='Historical FS'!D11 -> 42825 | H8: ='Historical FS'!E11 -> 43190 | I8: ='Historical FS'!F11 -> 43555 | J8: ='Historical FS'!G11 -> 43921 | K8: ='Historical FS'!H11 -> 44286 | L8: ='Historical FS'!I11 -> 44651 | M8: ='Historical FS'!J11 -> 45016 | ... O8: ='Historical FS'!L11 -> 45747
D9: Operating Activities
D10: Profit from operations | F10: ='Historical FS'!C59 -> 4948 | G10: ='Historical FS'!D59 -> 5220 | H10: ='Historical FS'!E59 -> 5986 | I10: ='Historical FS'!F59 -> 7362 | J10: ='Historical FS'!G59 -> 9348 | K10: ='Historical FS'!H59 -> 11465 | L10: ='Historical FS'!I59 -> 11311 | M10: ='Historical FS'!J59 -> 10530 | ... O10: ='Historical FS'!L59 -> 12645
D11: Receivables | F11: ='Historical FS'!C60 -> -287 | G11: ='Historical FS'!D60 -> 156 | H11: ='Historical FS'!E60 -> -454 | I11: ='Historical FS'!F60 -> -279 | J11: ='Historical FS'!G60 -> 473 | K11: ='Historical FS'!H60 -> -201 | L11: ='Historical FS'!I60 -> -495 | M11: ='Historical FS'!J60 -> -752 | ... O11: ='Historical FS'!L60 -> -608
D12: Inventory | F12: ='Historical FS'!C61 -> 374 | G12: ='Historical FS'!D61 -> 54 | H12: ='Historical FS'!E61 -> -623 | I12: ='Historical FS'!F61 -> -15 | J12: ='Historical FS'!G61 -> -64 | K12: ='Historical FS'!H61 -> 165 | L12: ='Historical FS'!I61 -> -1579 | M12: ='Historical FS'!J61 -> -992 | ... O12: ='Historical FS'!L61 -> -317
D13: Payables | F13: ='Historical FS'!C62 -> 310 | G13: ='Historical FS'!D62 -> 482 | H13: ='Historical FS'!E62 -> 346 | I13: ='Historical FS'!F62 -> 766 | J13: ='Historical FS'!G62 -> 279 | K13: ='Historical FS'!H62 -> 2868 | L13: ='Historical FS'!I62 -> 2077 | M13: ='Historical FS'!J62 -> 1869 | ... O13: ='Historical FS'!L62 -> -476
D14: Loans Advances | F14: ='Historical FS'!C63 -> 0 | G14: ='Historical FS'!D63 -> 0 | H14: ='Historical FS'!E63 -> 0 | I14: ='Historical FS'!F63 -> 0 | J14: ='Historical FS'!G63 -> 0 | K14: ='Historical FS'!H63 -> 0 | L14: ='Historical FS'!I63 -> 0 | M14: ='Historical FS'!J63 -> 0 | ... O14: ='Historical FS'!L63 -> 0
D15: Other WC items | F15: ='Historical FS'!C64 -> 32 | G15: ='Historical FS'!D64 -> -162 | H15: ='Historical FS'!E64 -> -525 | I15: ='Historical FS'!F64 -> -1167 | J15: ='Historical FS'!G64 -> -172 | K15: ='Historical FS'!H64 -> -505 | L15: ='Historical FS'!I64 -> -476 | M15: ='Historical FS'!J64 -> -461 | ... O15: ='Historical FS'!L64 -> 729
D16: Working capital changes | F16: =SUM(F11:F15) -> 429 | G16: =SUM(G11:G15) -> 530 | H16: =SUM(H11:H15) -> -1256 | I16: =SUM(I11:I15) -> -695 | J16: =SUM(J11:J15) -> 516 | K16: =SUM(K11:K15) -> 2327 | L16: =SUM(L11:L15) -> -473 | M16: =SUM(M11:M15) -> -336 | ... O16: =SUM(O11:O15) -> -672
D17: Direct taxes | F17: ='Historical FS'!C66 -> -852 | G17: ='Historical FS'!D66 -> -744 | H17: ='Historical FS'!E66 -> -843 | I17: ='Historical FS'!F66 -> -710 | J17: ='Historical FS'!G66 -> -891 | K17: ='Historical FS'!H66 -> -1291 | L17: ='Historical FS'!I66 -> -1555 | M17: ='Historical FS'!J66 -> -1124 | ... O17: ='Historical FS'!L66 -> -1301
D18: Other operating items | F18: ='Historical FS'!C67 -> 0 | G18: ='Historical FS'!D67 -> 0 | H18: ='Historical FS'!E67 -> 0 | I18: ='Historical FS'!F67 -> 0 | J18: ='Historical FS'!G67 -> 0 | K18: ='Historical FS'!H67 -> 0 | L18: ='Historical FS'!I67 -> 0 | M18: ='Historical FS'!J67 -> 0 | ... O18: ='Historical FS'!L67 -> 0
D19: Cash Flow from Operating Activities | F19: =F10+F16+F17+F18 -> 4525 | G19: =G10+G16+G17+G18 -> 5006 | H19: =H10+H16+H17+H18 -> 3887 | I19: =I10+I16+I17+I18 -> 5957 | J19: =J10+J16+J17+J18 -> 8973 | K19: =K10+K16+K17+K18 -> 12501 | L19: =L10+L16+L17+L18 -> 9283 | M19: =M10+M16+M17+M18 -> 9070 | ... O19: =O10+O16+O17+O18 -> 10672
D21: Investing Activities
D22: Fixed assets purchased | F22: ='Historical FS'!C70 -> -2150 | G22: ='Historical FS'!D70 -> -1402 | H22: ='Historical FS'!E70 -> -2103 | I22: ='Historical FS'!F70 -> -1808 | J22: ='Historical FS'!G70 -> -1766 | K22: ='Historical FS'!H70 -> -1925 | L22: ='Historical FS'!I70 -> -5613 | M22: ='Historical FS'!J70 -> -6200 | ... O22: ='Historical FS'!L70 -> -9129
D23: Fixed assets sold | F23: ='Historical FS'!C71 -> 18 | G23: ='Historical FS'!D71 -> 35 | H23: ='Historical FS'!E71 -> 220 | I23: ='Historical FS'!F71 -> 160 | J23: ='Historical FS'!G71 -> 79 | K23: ='Historical FS'!H71 -> 86 | L23: ='Historical FS'!I71 -> 73 | M23: ='Historical FS'!J71 -> 95 | ... O23: ='Historical FS'!L71 -> 179
D24: Investments purchased | F24: ='Historical FS'!C72 -> -2698 | G24: ='Historical FS'!D72 -> -3377 | H24: ='Historical FS'!E72 -> -3960 | I24: ='Historical FS'!F72 -> -1700 | J24: ='Historical FS'!G72 -> -6086 | K24: ='Historical FS'!H72 -> -12689 | L24: ='Historical FS'!I72 -> -7795 | M24: ='Historical FS'!J72 -> -7260 | ... O24: ='Historical FS'!L72 -> -15885
D25: Investments sold | F25: ='Historical FS'!C73 -> 2948 | G25: ='Historical FS'!D73 -> 2228 | H25: ='Historical FS'!E73 -> 5588 | I25: ='Historical FS'!F73 -> 4478 | J25: ='Historical FS'!G73 -> 3443 | K25: ='Historical FS'!H73 -> 7101 | L25: ='Historical FS'!I73 -> 13965 | M25: ='Historical FS'!J73 -> 7156 | ... O25: ='Historical FS'!L73 -> 19115
D26: Interest received | F26: ='Historical FS'!C74 -> 59 | G26: ='Historical FS'!D74 -> 47 | H26: ='Historical FS'!E74 -> 67 | I26: ='Historical FS'!F74 -> 78 | J26: ='Historical FS'!G74 -> 89 | K26: ='Historical FS'!H74 -> 77 | L26: ='Historical FS'!I74 -> 174 | M26: ='Historical FS'!J74 -> 283 | ... O26: ='Historical FS'!L74 -> 342
D27: Dividends received | F27: ='Historical FS'!C75 -> 0 | G27: ='Historical FS'!D75 -> 0 | H27: ='Historical FS'!E75 -> 0 | I27: ='Historical FS'!F75 -> 22 | J27: ='Historical FS'!G75 -> 32 | K27: ='Historical FS'!H75 -> 0 | L27: ='Historical FS'!I75 -> 0 | M27: ='Historical FS'!J75 -> 0 | ... O27: ='Historical FS'!L75 -> 1
D28: Invest in subsidiaries | F28: ='Historical FS'!C76 -> -13 | G28: ='Historical FS'!D76 -> 0 | H28: ='Historical FS'!E76 -> 0 | I28: ='Historical FS'!F76 -> 0 | J28: ='Historical FS'!G76 -> 0 | K28: ='Historical FS'!H76 -> 0 | L28: ='Historical FS'!I76 -> 0 | M28: ='Historical FS'!J76 -> 0 | ... O28: ='Historical FS'!L76 -> 0
D29: Investment in group cos | F29: ='Historical FS'!C77 -> 0 | G29: ='Historical FS'!D77 -> 0 | H29: ='Historical FS'!E77 -> -1 | I29: ='Historical FS'!F77 -> -8 | J29: ='Historical FS'!G77 -> -6 | K29: ='Historical FS'!H77 -> -3 | L29: ='Historical FS'!I77 -> 0 | M29: ='Historical FS'!J77 -> 0 | ... O29: ='Historical FS'!L77 -> 0
D30: Redemp n Canc of Shares | F30: ='Historical FS'!C78 -> 0 | G30: ='Historical FS'!D78 -> 0 | H30: ='Historical FS'!E78 -> 0 | I30: ='Historical FS'!F78 -> 0 | J30: ='Historical FS'!G78 -> 0 | K30: ='Historical FS'!H78 -> 0 | L30: ='Historical FS'!I78 -> 0 | M30: ='Historical FS'!J78 -> 3 | ... O30: ='Historical FS'!L78 -> 36
D31: Acquisition of companies | F31: ='Historical FS'!C79 -> 0 | G31: ='Historical FS'!D79 -> 0 | H31: ='Historical FS'!E79 -> 0 | I31: ='Historical FS'!F79 -> 0 | J31: ='Historical FS'!G79 -> 0 | K31: ='Historical FS'!H79 -> 0 | L31: ='Historical FS'!I79 -> 0 | M31: ='Historical FS'!J79 -> -847 | ... O31: ='Historical FS'!L79 -> -10262
D32: Other investing items | F32: ='Historical FS'!C80 -> -1839 | G32: ='Historical FS'!D80 -> -32 | H32: ='Historical FS'!E80 -> 2055 | I32: ='Historical FS'!F80 -> -58 | J32: ='Historical FS'!G80 -> 22 | K32: ='Historical FS'!H80 -> -1503 | L32: ='Historical FS'!I80 -> 1518 | M32: ='Historical FS'!J80 -> -417 | ... O32: ='Historical FS'!L80 -> -232
D33: Cash Flow from Investing Activities | F33: =SUM(F22:F32) -> -3675 | G33: =SUM(G22:G32) -> -2501 | H33: =SUM(H22:H32) -> 1866 | I33: =SUM(I22:I32) -> 1164 | J33: =SUM(J22:J32) -> -4193 | K33: =SUM(K22:K32) -> -8856 | L33: =SUM(L22:L32) -> 2322 | M33: =SUM(M22:M32) -> -7187 | ... O33: =SUM(O22:O32) -> -15835
D35: Financing Activities
D36: Proceeds from shares | F36: ='Historical FS'!C83 -> 3 | G36: ='Historical FS'!D83 -> 7 | H36: ='Historical FS'!E83 -> 16 | I36: ='Historical FS'!F83 -> 5 | J36: ='Historical FS'!G83 -> 3 | K36: ='Historical FS'!H83 -> 14 | L36: ='Historical FS'!I83 -> 13 | M36: ='Historical FS'!J83 -> 13 | ... O36: ='Historical FS'!L83 -> 33
D37: Proceeds from borrowings | F37: ='Historical FS'!C84 -> 2821 | G37: ='Historical FS'!D84 -> 3656 | H37: ='Historical FS'!E84 -> 15775 | I37: ='Historical FS'!F84 -> 9772 | J37: ='Historical FS'!G84 -> 1510 | K37: ='Historical FS'!H84 -> 4103 | L37: ='Historical FS'!I84 -> 175 | M37: ='Historical FS'!J84 -> 1032 | ... O37: ='Historical FS'!L84 -> 9410
D38: Repayment of borrowings | F38: ='Historical FS'!C85 -> -2775 | G38: ='Historical FS'!D85 -> -5272 | H38: ='Historical FS'!E85 -> -19982 | I38: ='Historical FS'!F85 -> -14420 | J38: ='Historical FS'!G85 -> -4154 | K38: ='Historical FS'!H85 -> -6499 | L38: ='Historical FS'!I85 -> -10346 | M38: ='Historical FS'!J85 -> -579 | ... O38: ='Historical FS'!L85 -> -550
D39: Interest paid fin | F39: ='Historical FS'!C86 -> -596 | G39: ='Historical FS'!D86 -> -614 | H39: ='Historical FS'!E86 -> -1210 | I39: ='Historical FS'!F86 -> -1685 | J39: ='Historical FS'!G86 -> -1950 | K39: ='Historical FS'!H86 -> -1481 | L39: ='Historical FS'!I86 -> -1026 | M39: ='Historical FS'!J86 -> -765 | ... O39: ='Historical FS'!L86 -> -1540
D40: Dividends paid | F40: ='Historical FS'!C87 -> -297 | G40: ='Historical FS'!D87 -> -312 | H40: ='Historical FS'!E87 -> -334 | I40: ='Historical FS'!F87 -> -346 | J40: ='Historical FS'!G87 -> -380 | K40: ='Historical FS'!H87 -> -375 | L40: ='Historical FS'!I87 -> -1065 | M40: ='Historical FS'!J87 -> -1091 | ... O40: ='Historical FS'!L87 -> -2012
D41: Financial liabilities | F41: ='Historical FS'!C88 -> 0 | G41: ='Historical FS'!D88 -> 0 | H41: ='Historical FS'!E88 -> 0 | I41: ='Historical FS'!F88 -> 0 | J41: ='Historical FS'!G88 -> -101 | K41: ='Historical FS'!H88 -> -118 | L41: ='Historical FS'!I88 -> -157 | M41: ='Historical FS'!J88 -> -126 | ... O41: ='Historical FS'!L88 -> -165
D42: Other financing items | F42: ='Historical FS'!C89 -> 1 | G42: ='Historical FS'!D89 -> 0 | H42: ='Historical FS'!E89 -> 0 | I42: ='Historical FS'!F89 -> -83 | J42: ='Historical FS'!G89 -> -4 | K42: ='Historical FS'!H89 -> 0 | L42: ='Historical FS'!I89 -> -91 | M42: ='Historical FS'!J89 -> -115 | ... O42: ='Historical FS'!L89 -> -100
D43: Cash Flow from Financing Activities | F43: =SUM(F36:F42) -> -843 | G43: =SUM(G36:G42) -> -2535 | H43: =SUM(H36:H42) -> -5735 | I43: =SUM(I36:I42) -> -6757 | J43: =SUM(J36:J42) -> -5076 | K43: =SUM(K36:K42) -> -4356 | L43: =SUM(L36:L42) -> -12497 | M43: =SUM(M36:M42) -> -1631 | ... O43: =SUM(O36:O42) -> 5076
D45: Net Cash Flow | F45: =F19+F33+F43 -> 7 | G45: =G19+G33+G43 -> -30 | H45: =H19+H33+H43 -> 18 | I45: =I19+I33+I43 -> 364 | J45: =J19+J33+J43 -> -296 | K45: =K19+K33+K43 -> -711 | L45: =L19+L33+L43 -> -892 | M45: =M19+M33+M43 -> 252 | ... O45: =O19+O33+O43 -> -87

Sheet Com_Size
D2: UltraTech Cement Ltd (NSE: ULTRACEMCO)
D3: Common Size Statement
D4: (Figures are in ₹ Cr, except price per share)
D6: Common Size Income Statement
F7: Fiscal Year Ending March 31,
D8: Particulars | F8: ='Historical FS'!C11 -> 42460 | G8: ='Historical FS'!D11 -> 42825 | H8: ='Historical FS'!E11 -> 43190 | I8: ='Historical FS'!F11 -> 43555 | J8: ='Historical FS'!G11 -> 43921 | K8: ='Historical FS'!H11 -> 44286 | L8: ='Historical FS'!I11 -> 44651 | M8: ='Historical FS'!J11 -> 45016 | ... O8: ='Historical FS'!L11 -> 45747
D9: Revenue | F9: ='Data Sheet'!B17/'Data Sheet'!B$17 -> 1 | G9: ='Data Sheet'!C17/'Data Sheet'!C$17 -> 1 | H9: ='Data Sheet'!D17/'Data Sheet'!D$17 -> 1 | I9: ='Data Sheet'!E17/'Data Sheet'!E$17 -> 1 | J9: ='Data Sheet'!F17/'Data Sheet'!F$17 -> 1 | K9: ='Data Sheet'!G17/'Data Sheet'!G$17 -> 1 | L9: ='Data Sheet'!H17/'Data Sheet'!H$17 -> 1 | M9: ='Data Sheet'!I17/'Data Sheet'!I$17 -> 1 | ... O9: ='Data Sheet'!K17/'Data Sheet'!K$17 -> 1
D10: ='Data Sheet'!A18 -> Raw Material Cost | F10: ='Data Sheet'!B18/'Data Sheet'!B$17 -> 0.17636376 | G10: ='Data Sheet'!C18/'Data Sheet'!C$17 -> 0.17406544 | H10: ='Data Sheet'!D18/'Data Sheet'!D$17 -> 0.17431312 | I10: ='Data Sheet'!E18/'Data Sheet'!E$17 -> 0.16730251 | J10: ='Data Sheet'!F18/'Data Sheet'!F$17 -> 0.16205298 | K10: ='Data Sheet'!G18/'Data Sheet'!G$17 -> 0.14836314 | L10: ='Data Sheet'!H18/'Data Sheet'!H$17 -> 0.15871361 | M10: ='Data Sheet'!I18/'Data Sheet'!I$17 -> 0.16181488 | ... O10: ='Data Sheet'!K18/'Data Sheet'!K$17 -> 0.18025721
D11: ='Data Sheet'!A19 -> Change in Inventory | F11: ='Data Sheet'!B19/'Data Sheet'!B$17 -> 0.00073986492 | G11: ='Data Sheet'!C19/'Data Sheet'!C$17 -> -0.0029828642 | H11: ='Data Sheet'!D19/'Data Sheet'!D$17 -> 0.0035895724 | I11: ='Data Sheet'!E19/'Data Sheet'!E$17 -> -0.0011178841 | J11: ='Data Sheet'!F19/'Data Sheet'!F$17 -> 0.0084334416 | K11: ='Data Sheet'!G19/'Data Sheet'!G$17 -> -0.010064661 | L11: ='Data Sheet'!H19/'Data Sheet'!H$17 -> 0.0072845727 | M11: ='Data Sheet'!I19/'Data Sheet'!I$17 -> 0.0081943416 | ... O11: ='Data Sheet'!K19/'Data Sheet'!K$17 -> -0.00016154274
D12: ='Data Sheet'!A20 -> Power and Fuel | F12: ='Data Sheet'!B20/'Data Sheet'!B$17 -> 0.18205408 | G12: ='Data Sheet'!C20/'Data Sheet'!C$17 -> 0.16835429 | H12: ='Data Sheet'!D20/'Data Sheet'!D$17 -> 0.20446585 | I12: ='Data Sheet'!E20/'Data Sheet'!E$17 -> 0.22758383 | J12: ='Data Sheet'!F20/'Data Sheet'!F$17 -> 0.20072807 | K12: ='Data Sheet'!G20/'Data Sheet'!G$17 -> 0.18627235 | L12: ='Data Sheet'!H20/'Data Sheet'!H$17 -> 0.23075152 | M12: ='Data Sheet'!I20/'Data Sheet'!I$17 -> 0.29239921 | ... O12: ='Data Sheet'!K20/'Data Sheet'!K$17 -> 0.24250041
D13: ='Data Sheet'!A21 -> Other Mfr. Exp | F13: ='Data Sheet'!B21/'Data Sheet'!B$17 -> 0.076883932 | G13: ='Data Sheet'!C21/'Data Sheet'!C$17 -> 0.078474274 | H13: ='Data Sheet'!D21/'Data Sheet'!D$17 -> 0.073906778 | I13: ='Data Sheet'!E21/'Data Sheet'!E$17 -> 0.072380521 | J13: ='Data Sheet'!F21/'Data Sheet'!F$17 -> 0.07172538 | K13: ='Data Sheet'!G21/'Data Sheet'!G$17 -> 0.068581892 | L13: ='Data Sheet'!H21/'Data Sheet'!H$17 -> 0.073949744 | M13: ='Data Sheet'!I21/'Data Sheet'!I$17 -> 0.0686961 | ... O13: ='Data Sheet'!K21/'Data Sheet'!K$17 -> 0.072076896
D14: ='Data Sheet'!A22 -> Employee Cost | F14: ='Data Sheet'!B22/'Data Sheet'!B$17 -> 0.058302231 | G14: ='Data Sheet'!C22/'Data Sheet'!C$17 -> 0.060996006 | H14: ='Data Sheet'!D22/'Data Sheet'!D$17 -> 0.059131427 | I14: ='Data Sheet'!E22/'Data Sheet'!E$17 -> 0.055699569 | J14: ='Data Sheet'!F22/'Data Sheet'!F$17 -> 0.059454314 | K14: ='Data Sheet'!G22/'Data Sheet'!G$17 -> 0.052840419 | L14: ='Data Sheet'!H22/'Data Sheet'!H$17 -> 0.048385107 | M14: ='Data Sheet'!I22/'Data Sheet'!I$17 -> 0.043505864 | ... O14: ='Data Sheet'!K22/'Data Sheet'!K$17 -> 0.047649843
D15: ='Data Sheet'!A23 -> Selling and admin | F15: ='Data Sheet'!B23/'Data Sheet'!B$17 -> 0.28626412 | G15: ='Data Sheet'!C23/'Data Sheet'!C$17 -> 0.28173939 | H15: ='Data Sheet'!D23/'Data Sheet'!D$17 -> 0.26858136 | I15: ='Data Sheet'!E23/'Data Sheet'!E$17 -> 0.27889941 | J15: ='Data Sheet'!F23/'Data Sheet'!F$17 -> 0.26484443 | K15: ='Data Sheet'!G23/'Data Sheet'!G$17 -> 0.25189085 | L15: ='Data Sheet'!H23/'Data Sheet'!H$17 -> 0.25251931 | M15: ='Data Sheet'!I23/'Data Sheet'!I$17 -> 0.25078439 | ... O15: ='Data Sheet'!K23/'Data Sheet'!K$17 -> 0.25767779
D16: ='Data Sheet'!A24 -> Other Expenses | F16: ='Data Sheet'!B24/'Data Sheet'!B$17 -> 0.026027263 | G16: ='Data Sheet'!C24/'Data Sheet'!C$17 -> 0.027970904 | H16: ='Data Sheet'!D24/'Data Sheet'!D$17 -> 0.024827446 | I16: ='Data Sheet'!E24/'Data Sheet'!E$17 -> 0.019820434 | J16: ='Data Sheet'!F24/'Data Sheet'!F$17 -> 0.031716556 | K16: ='Data Sheet'!G24/'Data Sheet'!G$17 -> 0.023346033 | L16: ='Data Sheet'!H24/'Data Sheet'!H$17 -> 0.024056429 | M16: ='Data Sheet'!I24/'Data Sheet'!I$17 -> 0.023064523 | ... O16: ='Data Sheet'!K24/'Data Sheet'!K$17 -> 0.03119684
D17: ='Data Sheet'!A25 -> Other Income | F17: ='Data Sheet'!B25/'Data Sheet'!B$17 -> 0.018439374 | G17: ='Data Sheet'!C25/'Data Sheet'!C$17 -> 0.025541735 | H17: ='Data Sheet'!D25/'Data Sheet'!D$17 -> 0.0078108709 | I17: ='Data Sheet'!E25/'Data Sheet'!E$17 -> 0.0084438234 | J17: ='Data Sheet'!F25/'Data Sheet'!F$17 -> 0.015344372 | K17: ='Data Sheet'!G25/'Data Sheet'!G$17 -> 0.013829155 | L17: ='Data Sheet'!H25/'Data Sheet'!H$17 -> 0.012727089 | M17: ='Data Sheet'!I25/'Data Sheet'!I$17 -> 0.0080188197 | ... O17: ='Data Sheet'!K25/'Data Sheet'!K$17 -> 0.005223347
D18: ='Data Sheet'!A26 -> Depreciation | F18: ='Data Sheet'!B26/'Data Sheet'!B$17 -> 0.054751197 | G18: ='Data Sheet'!C26/'Data Sheet'!C$17 -> 0.053139436 | H18: ='Data Sheet'!D26/'Data Sheet'!D$17 -> 0.059651786 | I18: ='Data Sheet'!E26/'Data Sheet'!E$17 -> 0.059107487 | J18: ='Data Sheet'!F26/'Data Sheet'!F$17 -> 0.064168444 | K18: ='Data Sheet'!G26/'Data Sheet'!G$17 -> 0.060372984 | L18: ='Data Sheet'!H26/'Data Sheet'!H$17 -> 0.051612365 | M18: ='Data Sheet'!I26/'Data Sheet'!I$17 -> 0.045667155 | ... O18: ='Data Sheet'!K26/'Data Sheet'!K$17 -> 0.052859497
D19: ='Data Sheet'!A27 -> Interest | F19: ='Data Sheet'!B27/'Data Sheet'!B$17 -> 0.022513998 | G19: ='Data Sheet'!C27/'Data Sheet'!C$17 -> 0.025225675 | H19: ='Data Sheet'!D27/'Data Sheet'!D$17 -> 0.039950133 | I19: ='Data Sheet'!E27/'Data Sheet'!E$17 -> 0.042878994 | J19: ='Data Sheet'!F27/'Data Sheet'!F$17 -> 0.046939787 | K19: ='Data Sheet'!G27/'Data Sheet'!G$17 -> 0.033216846 | L19: ='Data Sheet'!H27/'Data Sheet'!H$17 -> 0.017960666 | M19: ='Data Sheet'!I27/'Data Sheet'!I$17 -> 0.013009492 | ... O19: ='Data Sheet'!K27/'Data Sheet'!K$17 -> 0.021730461
D20: ='Data Sheet'!A28 -> Profit before tax | F20: ='Data Sheet'!B28/'Data Sheet'!B$17 -> 0.13601866 | G20: ='Data Sheet'!C28/'Data Sheet'!C$17 -> 0.15259346 | H20: ='Data Sheet'!D28/'Data Sheet'!D$17 -> 0.10657253 | I20: ='Data Sheet'!E28/'Data Sheet'!E$17 -> 0.083653182 | J20: ='Data Sheet'!F28/'Data Sheet'!F$17 -> 0.12214785 | K20: ='Data Sheet'!G28/'Data Sheet'!G$17 -> 0.17887998 | L20: ='Data Sheet'!H28/'Data Sheet'!H$17 -> 0.16206292 | M20: ='Data Sheet'!I28/'Data Sheet'!I$17 -> 0.11727154 | ... O20: ='Data Sheet'!K28/'Data Sheet'!K$17 -> 0.099112858
D21: ='Data Sheet'!A29 -> Tax | F21: ='Data Sheet'!B29/'Data Sheet'!B$17 -> 0.037438119 | G21: ='Data Sheet'!C29/'Data Sheet'!C$17 -> 0.045656857 | H21: ='Data Sheet'!D29/'Data Sheet'!D$17 -> 0.034766236 | I21: ='Data Sheet'!E29/'Data Sheet'!E$17 -> 0.025760053 | J21: ='Data Sheet'!F29/'Data Sheet'!F$17 -> -0.01339056 | K21: ='Data Sheet'!G29/'Data Sheet'!G$17 -> 0.056761422 | L21: ='Data Sheet'!H29/'Data Sheet'!H$17 -> 0.022625218 | M21: ='Data Sheet'!I29/'Data Sheet'!I$17 -> 0.037046976 | ... O21: ='Data Sheet'!K29/'Data Sheet'!K$17 -> 0.019596965
D22: ='Data Sheet'!A30 -> Net profit | F22: ='Data Sheet'!B30/'Data Sheet'!B$17 -> 0.098517726 | G22: ='Data Sheet'!C30/'Data Sheet'!C$17 -> 0.10699217 | H22: ='Data Sheet'!D30/'Data Sheet'!D$17 -> 0.071732375 | I22: ='Data Sheet'!E30/'Data Sheet'!E$17 -> 0.05796862 | J22: ='Data Sheet'!F30/'Data Sheet'!F$17 -> 0.13564164 | K22: ='Data Sheet'!G30/'Data Sheet'!G$17 -> 0.1221465 | L22: ='Data Sheet'!H30/'Data Sheet'!H$17 -> 0.13962877 | M22: ='Data Sheet'!I30/'Data Sheet'!I$17 -> 0.080075294 | ... O22: ='Data Sheet'!K30/'Data Sheet'!K$17 -> 0.079508915
D24: ='Data Sheet'!A31 -> Dividend Amount | F24: ='Data Sheet'!B31/'Data Sheet'!B$17 -> 0.010364868 | G24: ='Data Sheet'!C31/'Data Sheet'!C$17 -> 0.010818154 | H24: ='Data Sheet'!D31/'Data Sheet'!D$17 -> 0.0093077096 | I24: ='Data Sheet'!E31/'Data Sheet'!E$17 -> 0.0076175298 | J24: ='Data Sheet'!F31/'Data Sheet'!F$17 -> 0.0088432942 | K24: ='Data Sheet'!G31/'Data Sheet'!G$17 -> 0.023878835 | L24: ='Data Sheet'!H31/'Data Sheet'!H$17 -> 0.020855027 | M24: ='Data Sheet'!I31/'Data Sheet'!I$17 -> 0.017346938 | ... O24: ='Data Sheet'!K31/'Data Sheet'!K$17 -> 0.030067357
D25: EBITDA | F25: =Inc_Stat!F18/'Data Sheet'!B17 -> 0.19484448 | G25: =Inc_Stat!G18/'Data Sheet'!C17 -> 0.20541684 | H25: =Inc_Stat!H18/'Data Sheet'!D17 -> 0.19836358 | I25: =Inc_Stat!I18/'Data Sheet'!E17 -> 0.17719584 | J25: =Inc_Stat!J18/'Data Sheet'!F17 -> 0.21791171 | K25: =Inc_Stat!K18/'Data Sheet'!G17 -> 0.25864065 | L25: =Inc_Stat!L18/'Data Sheet'!H17 -> 0.21890886 | M25: =Inc_Stat!M18/'Data Sheet'!I17 -> 0.16792937 | ... O25: =Inc_Stat!O18/'Data Sheet'!K17 -> 0.16847947
D27: Common Size Balance Sheet
F28: Fiscal Year Ending March 31,
D29: Particulars | F29: =F8 -> 42460 | G29: =G8 -> 42825 | H29: =H8 -> 43190 | I29: =I8 -> 43555 | J29: =J8 -> 43921 | K29: =K8 -> 44286 | L29: =L8 -> 44651 | M29: =M8 -> 45016 | ... O29: =O8 -> 45747
D30: Total Liabilities & Equity: | F30: ='Data Sheet'!B61/'Data Sheet'!B61 -> 1 | G30: ='Data Sheet'!C61/'Data Sheet'!C61 -> 1 | H30: ='Data Sheet'!D61/'Data Sheet'!D61 -> 1 | I30: ='Data Sheet'!E61/'Data Sheet'!E61 -> 1 | J30: ='Data Sheet'!F61/'Data Sheet'!F61 -> 1 | K30: ='Data Sheet'!G61/'Data Sheet'!G61 -> 1 | L30: ='Data Sheet'!H61/'Data Sheet'!H61 -> 1 | M30: ='Data Sheet'!I61/'Data Sheet'!I61 -> 1 | ... O30: ='Data Sheet'!K61/'Data Sheet'!K61 -> 1
D31: ='Data Sheet'!A57 -> Equity Share Capital | F31: ='Data Sheet'!B57/'Data Sheet'!B$61 -> 0.0066620364 | G31: ='Data Sheet'!C57/'Data Sheet'!C$61 -> 0.0065035723 | H31: ='Data Sheet'!D57/'Data Sheet'!D$61 -> 0.0048058236 | I31: ='Data Sheet'!E57/'Data Sheet'!E$61 -> 0.0035888752 | J31: ='Data Sheet'!F57/'Data Sheet'!F$61 -> 0.0036436828 | K31: ='Data Sheet'!G57/'Data Sheet'!G$61 -> 0.0033495269 | L31: ='Data Sheet'!H57/'Data Sheet'!H$61 -> 0.0034442792 | M31: ='Data Sheet'!I57/'Data Sheet'!I$61 -> 0.0031592114 | ... O31: ='Data Sheet'!K57/'Data Sheet'!K$61 -> 0.0022051595
D32: ='Data Sheet'!A58 -> Reserves | F32: ='Data Sheet'!B58/'Data Sheet'!B$61 -> 0.52608798 | G32: ='Data Sheet'!C58/'Data Sheet'!C$61 -> 0.57137855 | H32: ='Data Sheet'!D58/'Data Sheet'!D$61 -> 0.45687875 | I32: ='Data Sheet'!E58/'Data Sheet'!E$61 -> 0.43744983 | J32: ='Data Sheet'!F58/'Data Sheet'!F$61 -> 0.48924714 | K32: ='Data Sheet'!G58/'Data Sheet'!G$61 -> 0.5092584 | L32: ='Data Sheet'!H58/'Data Sheet'!H$61 -> 0.59832643 | M32: ='Data Sheet'!I58/'Data Sheet'!I$61 -> 0.59132867 | ... O32: ='Data Sheet'!K58/'Data Sheet'!K$61 -> 0.52691016
D33: ='Data Sheet'!A59 -> Borrowings | F33: ='Data Sheet'!B59/'Data Sheet'!B$61 -> 0.25771276 | G33: ='Data Sheet'!C59/'Data Sheet'!C$61 -> 0.20077396 | H33: ='Data Sheet'!D59/'Data Sheet'!D$61 -> 0.34091439 | I33: ='Data Sheet'!E59/'Data Sheet'!E$61 -> 0.33109281 | J33: ='Data Sheet'!F59/'Data Sheet'!F$61 -> 0.29059276 | K33: ='Data Sheet'!G59/'Data Sheet'!G$61 -> 0.25203423 | L33: ='Data Sheet'!H59/'Data Sheet'!H$61 -> 0.13481214 | M33: ='Data Sheet'!I59/'Data Sheet'!I$61 -> 0.12100779 | ... O33: ='Data Sheet'!K59/'Data Sheet'!K$61 -> 0.18036226
D34: ='Data Sheet'!A60 -> Other Liabilities | F34: ='Data Sheet'!B60/'Data Sheet'!B$61 -> 0.20953723 | G34: ='Data Sheet'!C60/'Data Sheet'!C$61 -> 0.22134392 | H34: ='Data Sheet'!D60/'Data Sheet'!D$61 -> 0.19740103 | I34: ='Data Sheet'!E60/'Data Sheet'!E$61 -> 0.22786848 | J34: ='Data Sheet'!F60/'Data Sheet'!F$61 -> 0.21651641 | K34: ='Data Sheet'!G60/'Data Sheet'!G$61 -> 0.23535784 | L34: ='Data Sheet'!H60/'Data Sheet'!H$61 -> 0.26341714 | M34: ='Data Sheet'!I60/'Data Sheet'!I$61 -> 0.28450434 | ... O34: ='Data Sheet'!K60/'Data Sheet'!K$61 -> 0.29052242
D36: Total Assets: | F36: ='Data Sheet'!B66/'Data Sheet'!B66 -> 1 | G36: ='Data Sheet'!C66/'Data Sheet'!C66 -> 1 | H36: ='Data Sheet'!D66/'Data Sheet'!D66 -> 1 | I36: ='Data Sheet'!E66/'Data Sheet'!E66 -> 1 | J36: ='Data Sheet'!F66/'Data Sheet'!F66 -> 1 | K36: ='Data Sheet'!G66/'Data Sheet'!G66 -> 1 | L36: ='Data Sheet'!H66/'Data Sheet'!H66 -> 1 | M36: ='Data Sheet'!I66/'Data Sheet'!I66 -> 1 | ... O36: ='Data Sheet'!K66/'Data Sheet'!K66 -> 1
D37: ='Data Sheet'!A62 -> Net Block | F37: ='Data Sheet'!B62/'Data Sheet'!B$66 -> 0.61440906 | G37: ='Data Sheet'!C62/'Data Sheet'!C$66 -> 0.61370045 | H37: ='Data Sheet'!D62/'Data Sheet'!D$66 -> 0.69503924 | I37: ='Data Sheet'!E62/'Data Sheet'!E$66 -> 0.74020707 | J37: ='Data Sheet'!F62/'Data Sheet'!F$66 -> 0.72147723 | K37: ='Data Sheet'!G62/'Data Sheet'!G$66 -> 0.64300252 | L37: ='Data Sheet'!H62/'Data Sheet'!H$66 -> 0.66205246 | M37: ='Data Sheet'!I62/'Data Sheet'!I$66 -> 0.65198883 | ... O37: ='Data Sheet'!K62/'Data Sheet'!K$66 -> 0.7076462
D38: ='Data Sheet'!A63 -> Capital Work in Progress | F38: ='Data Sheet'!B63/'Data Sheet'!B$66 -> 0.035663488 | G38: ='Data Sheet'!C63/'Data Sheet'!C$66 -> 0.021831306 | H38: ='Data Sheet'!D63/'Data Sheet'!D$66 -> 0.026446993 | I38: ='Data Sheet'!E63/'Data Sheet'!E$66 -> 0.01507108 | J38: ='Data Sheet'!F63/'Data Sheet'!F$66 -> 0.011608961 | K38: ='Data Sheet'!G63/'Data Sheet'!G$66 -> 0.019572423 | L38: ='Data Sheet'!H63/'Data Sheet'!H$66 -> 0.057088507 | M38: ='Data Sheet'!I63/'Data Sheet'!I$66 -> 0.044215061 | ... O38: ='Data Sheet'!K63/'Data Sheet'!K$66 -> 0.046651904
D39: ='Data Sheet'!A64 -> Investments | F39: ='Data Sheet'!B64/'Data Sheet'!B$66 -> 0.1236901 | G39: ='Data Sheet'!C64/'Data Sheet'!C$66 -> 0.15850867 | H39: ='Data Sheet'!D64/'Data Sheet'!D$66 -> 0.095323698 | I39: ='Data Sheet'!E64/'Data Sheet'!E$66 -> 0.03817466 | J39: ='Data Sheet'!F64/'Data Sheet'!F$66 -> 0.074844146 | K39: ='Data Sheet'!G64/'Data Sheet'!G$66 -> 0.14131615 | L39: ='Data Sheet'!H64/'Data Sheet'!H$66 -> 0.075595527 | M39: ='Data Sheet'!I64/'Data Sheet'!I$66 -> 0.079852463 | ... O39: ='Data Sheet'!K64/'Data Sheet'!K$66 -> 0.038587073
D40: ='Data Sheet'!A65 -> Other Assets | F40: ='Data Sheet'!B65/'Data Sheet'!B$66 -> 0.22623735 | G40: ='Data Sheet'!C65/'Data Sheet'!C$66 -> 0.20595957 | H40: ='Data Sheet'!D65/'Data Sheet'!D$66 -> 0.18319007 | I40: ='Data Sheet'!E65/'Data Sheet'!E$66 -> 0.20654719 | J40: ='Data Sheet'!F65/'Data Sheet'!F$66 -> 0.19206967 | K40: ='Data Sheet'!G65/'Data Sheet'!G$66 -> 0.19610891 | L40: ='Data Sheet'!H65/'Data Sheet'!H$66 -> 0.20526351 | M40: ='Data Sheet'!I65/'Data Sheet'!I$66 -> 0.22394365 | ... O40: ='Data Sheet'!K65/'Data Sheet'!K$66 -> 0.20711482
D41: ='Data Sheet'!A67 -> Receivables | F41: ='Data Sheet'!B67/'Data Sheet'!B$66 -> 0.046809042 | G41: ='Data Sheet'!C67/'Data Sheet'!C$66 -> 0.041628217 | H41: ='Data Sheet'!D67/'Data Sheet'!D$66 -> 0.038862227 | I41: ='Data Sheet'!E67/'Data Sheet'!E$66 -> 0.036419687 | J41: ='Data Sheet'!F67/'Data Sheet'!F$66 -> 0.030085916 | K41: ='Data Sheet'!G67/'Data Sheet'!G$66 -> 0.029842642 | L41: ='Data Sheet'!H67/'Data Sheet'!H$66 -> 0.036649054 | M41: ='Data Sheet'!I67/'Data Sheet'!I$66 -> 0.042317827 | ... O41: ='Data Sheet'!K67/'Data Sheet'!K$66 -> 0.04407812
D42: ='Data Sheet'!A68 -> Inventory | F42: ='Data Sheet'!B68/'Data Sheet'!B$66 -> 0.059587149 | G42: ='Data Sheet'!C68/'Data Sheet'!C$66 -> 0.056874926 | H42: ='Data Sheet'!D68/'Data Sheet'!D$66 -> 0.057184593 | I42: ='Data Sheet'!E68/'Data Sheet'!E$66 -> 0.053563413 | J42: ='Data Sheet'!F68/'Data Sheet'!F$66 -> 0.052810867 | K42: ='Data Sheet'!G68/'Data Sheet'!G$66 -> 0.046624973 | L42: ='Data Sheet'!H68/'Data Sheet'!H$66 -> 0.066763917 | M42: ='Data Sheet'!I68/'Data Sheet'!I$66 -> 0.072355013 | ... O42: ='Data Sheet'!K68/'Data Sheet'!K$66 -> 0.071562019
D43: ='Data Sheet'!A69 -> Cash & Bank | F43: ='Data Sheet'!B69/'Data Sheet'!B$66 -> 0.055032504 | G43: ='Data Sheet'!C69/'Data Sheet'!C$66 -> 0.053277124 | H43: ='Data Sheet'!D69/'Data Sheet'!D$66 -> 0.0038338436 | I43: ='Data Sheet'!E69/'Data Sheet'!E$66 -> 0.0096658141 | J43: ='Data Sheet'!F69/'Data Sheet'!F$66 -> 0.006815857 | K43: ='Data Sheet'!G69/'Data Sheet'!G$66 -> 0.023295835 | L43: ='Data Sheet'!H69/'Data Sheet'!H$66 -> 0.0042855725 | M43: ='Data Sheet'!I69/'Data Sheet'!I$66 -> 0.012580269 | ... O43: ='Data Sheet'!K69/'Data Sheet'!K$66 -> 0.012521845

Sheet Ratio
D2: UltraTech Cement Ltd (NSE: ULTRACEMCO)
D3: Ratio Analysis
D4: (Figures are in ₹ Cr, except price per share)
D6: Profitability Ratios
F7: 42460 | G7: =EDATE(F7,12) -> 42825 | H7: =EDATE(G7,12) -> 43190 | I7: =EDATE(H7,12) -> 43555 | J7: =EDATE(I7,12) -> 43921 | K7: =EDATE(J7,12) -> 44286 | L7: =EDATE(K7,12) -> 44651 | M7: =EDATE(L7,12) -> 45016 | N7: =EDATE(M7,12) -> 45382 | O7: =EDATE(N7,12) -> 45747 | P7: Trend
D8: Gross Profit Margin | F8: =Inc_Stat!F13/Inc_Stat!F9 -> 0.50713586 | G8: =Inc_Stat!G13/Inc_Stat!G9 -> 0.51512713 | H8: =Inc_Stat!H13/Inc_Stat!H9 -> 0.49177239 | I8: =Inc_Stat!I13/Inc_Stat!I9 -> 0.47591569 | J8: =Inc_Stat!J13/Inc_Stat!J9 -> 0.5144727 | K8: =Inc_Stat!K13/Inc_Stat!K9 -> 0.53387754 | L8: =Inc_Stat!L13/Inc_Stat!L9 -> 0.4954846 | M8: =Inc_Stat!M13/Inc_Stat!M9 -> 0.44177829 | ... O8: =Inc_Stat!O13/Inc_Stat!O9 -> 0.4573541
D9: EBITDA Margin | F9: =Inc_Stat!F18/Inc_Stat!F9 -> 0.19484448 | G9: =Inc_Stat!G18/Inc_Stat!G9 -> 0.20541684 | H9: =Inc_Stat!H18/Inc_Stat!H9 -> 0.19836358 | I9: =Inc_Stat!I18/Inc_Stat!I9 -> 0.17719584 | J9: =Inc_Stat!J18/Inc_Stat!J9 -> 0.21791171 | K9: =Inc_Stat!K18/Inc_Stat!K9 -> 0.25864065 | L9: =Inc_Stat!L18/Inc_Stat!L9 -> 0.21890886 | M9: =Inc_Stat!M18/Inc_Stat!M9 -> 0.16792937 | ... O9: =Inc_Stat!O18/Inc_Stat!O9 -> 0.16847947
D10: EBIT Margin | F10: =Inc_Stat!F23/Inc_Stat!F9 -> 0.14009328 | G10: =Inc_Stat!G23/Inc_Stat!G9 -> 0.1522774 | H10: =Inc_Stat!H23/Inc_Stat!H9 -> 0.1387118 | I10: =Inc_Stat!I23/Inc_Stat!I9 -> 0.11808835 | J10: =Inc_Stat!J23/Inc_Stat!J9 -> 0.15374327 | K10: =Inc_Stat!K23/Inc_Stat!K9 -> 0.19826767 | L10: =Inc_Stat!L23/Inc_Stat!L9 -> 0.1672965 | M10: =Inc_Stat!M23/Inc_Stat!M9 -> 0.12226221 | ... O10: =Inc_Stat!O23/Inc_Stat!O9 -> 0.11561997
D11: Pre-Tax Margin | F11: =Inc_Stat!F28/Inc_Stat!F9 -> 0.11757929 | G11: =Inc_Stat!G28/Inc_Stat!G9 -> 0.12705173 | H11: =Inc_Stat!H28/Inc_Stat!H9 -> 0.098761662 | I11: =Inc_Stat!I28/Inc_Stat!I9 -> 0.075209359 | J11: =Inc_Stat!J28/Inc_Stat!J9 -> 0.10680348 | K11: =Inc_Stat!K28/Inc_Stat!K9 -> 0.16505082 | L11: =Inc_Stat!L28/Inc_Stat!L9 -> 0.14933583 | M11: =Inc_Stat!M28/Inc_Stat!M9 -> 0.10925272 | ... O11: =Inc_Stat!O28/Inc_Stat!O9 -> 0.093889511
D12: Net Profit Margin | F12: =Inc_Stat!F33/Inc_Stat!F9 -> 0.080141167 | G12: =Inc_Stat!G33/Inc_Stat!G9 -> 0.081394872 | H12: =Inc_Stat!H33/Inc_Stat!H9 -> 0.063995427 | I12: =Inc_Stat!I33/Inc_Stat!I9 -> 0.049449306 | J12: =Inc_Stat!J33/Inc_Stat!J9 -> 0.12019404 | K12: =Inc_Stat!K33/Inc_Stat!K9 -> 0.1082894 | L12: =Inc_Stat!L33/Inc_Stat!L9 -> 0.12671061 | M12: =Inc_Stat!M33/Inc_Stat!M9 -> 0.072205747 | ... O12: =Inc_Stat!O33/Inc_Stat!O9 -> 0.074292546
D13: Return on Equity (ROE) | F13: =Inc_Stat!F33/(Bal_Sht!F9+Bal_Sht!F10) -> 0.091854734 | G13: =Inc_Stat!G33/(Bal_Sht!G9+Bal_Sht!G10) -> 0.084675275 | H13: =Inc_Stat!H33/(Bal_Sht!H9+Bal_Sht!H10) -> 0.075147946 | I13: =Inc_Stat!I33/(Bal_Sht!I9+Bal_Sht!I10) -> 0.060747867 | J13: =Inc_Stat!J33/(Bal_Sht!J9+Bal_Sht!J10) -> 0.13061806 | K13: =Inc_Stat!K33/(Bal_Sht!K9+Bal_Sht!K10) -> 0.10964041 | L13: =Inc_Stat!L33/(Bal_Sht!L9+Bal_Sht!L10) -> 0.13214621 | M13: =Inc_Stat!M33/(Bal_Sht!M9+Bal_Sht!M10) -> 0.084055751 | ... O13: =Inc_Stat!O33/(Bal_Sht!O9+Bal_Sht!O10) -> 0.079807068
D14: Return on Assets (ROA) | F14: =Inc_Stat!F33/Bal_Sht!F25 -> 0.048935611 | G14: =Inc_Stat!G33/Bal_Sht!G25 -> 0.048932328 | H14: =Inc_Stat!H33/Bal_Sht!H25 -> 0.034694648 | I14: =Inc_Stat!I33/Bal_Sht!I25 -> 0.026792161 | J14: =Inc_Stat!J33/Bal_Sht!J25 -> 0.064380441 | K14: =Inc_Stat!K33/Bal_Sht!K25 -> 0.056202543 | L14: =Inc_Stat!L33/Bal_Sht!L25 -> 0.079521722 | M14: =Inc_Stat!M33/Bal_Sht!M25 -> 0.049970125 | ... O14: =Inc_Stat!O33/Bal_Sht!O25 -> 0.042227142
D15: Return on Capital Employed | F15: =Inc_Stat!F33/(Bal_Sht!F25-Bal_Sht!F12) -> 0.061907546 | G15: =Inc_Stat!G33/(Bal_Sht!G25-Bal_Sht!G12) -> 0.062842029 | H15: =Inc_Stat!H33/(Bal_Sht!H25-Bal_Sht!H12) -> 0.043227875 | I15: =Inc_Stat!I33/(Bal_Sht!I25-Bal_Sht!I12) -> 0.03469896 | J15: =Inc_Stat!J33/(Bal_Sht!J25-Bal_Sht!J12) -> 0.082172035 | K15: =Inc_Stat!K33/'Data Sheet'!B140 -> 0.068503437 | L15: =Inc_Stat!L33/'Data Sheet'!C140 -> 0.099994449 | M15: =Inc_Stat!M33/'Data Sheet'!D140 -> 0.064737932 | N15: =Inc_Stat!N33/'Data Sheet'!E140 -> 0.083700097 | O15: =Inc_Stat!O33/'Data Sheet'!F140 -> 0.053017335
D16: Return on Invested Capital | F16: =Inc_Stat!F33/(Bal_Sht!F9+Bal_Sht!F10+Bal_Sht!F11) -> 0.061907546 | G16: =Inc_Stat!G33/(Bal_Sht!G9+Bal_Sht!G10+Bal_Sht!G11) -> 0.062842029 | H16: =Inc_Stat!H33/(Bal_Sht!H9+Bal_Sht!H10+Bal_Sht!H11) -> 0.043227875 | I16: =Inc_Stat!I33/(Bal_Sht!I9+Bal_Sht!I10+Bal_Sht!I11) -> 0.03469896 | J16: =Inc_Stat!J33/(Bal_Sht!J9+Bal_Sht!J10+Bal_Sht!J11) -> 0.082172035 | K16: =Inc_Stat!K33/(Bal_Sht!K9+Bal_Sht!K10+Bal_Sht!K11) -> 0.073501758 | L16: =Inc_Stat!L33/(Bal_Sht!L9+Bal_Sht!L10+Bal_Sht!L11) -> 0.10796032 | M16: =Inc_Stat!M33/(Bal_Sht!M9+Bal_Sht!M10+Bal_Sht!M11) -> 0.069839871 | ... O16: =Inc_Stat!O33/(Bal_Sht!O9+Bal_Sht!O10+Bal_Sht!O11) -> 0.059518642
D18: Liquidity Ratios
F19: 42460 | G19: =EDATE(F19,12) -> 42825 | H19: =EDATE(G19,12) -> 43190 | I19: =EDATE(H19,12) -> 43555 | J19: =EDATE(I19,12) -> 43921 | K19: =EDATE(J19,12) -> 44286 | L19: =EDATE(K19,12) -> 44651 | M19: =EDATE(L19,12) -> 45016 | N19: =EDATE(M19,12) -> 45382 | O19: =EDATE(N19,12) -> 45747 | P19: Trend
D20: Current Ratio | F20: =('Data Sheet'!D125+'Data Sheet'!D126+'Data Sheet'!D127+'Data Sheet'!D129)/('Data Sheet'!D105+'Data Sheet'!D104+'Data Sheet'!D100+'Data Sheet'!D102) -> 1.1999463 | G20: =('Data Sheet'!E125+'Data Sheet'!E126+'Data Sheet'!E127+'Data Sheet'!E129)/('Data Sheet'!E105+'Data Sheet'!E104+'Data Sheet'!E100+'Data Sheet'!E102) -> 2.0633518 | H20: =('Data Sheet'!F125+'Data Sheet'!F126+'Data Sheet'!F127+'Data Sheet'!F129)/('Data Sheet'!F105+'Data Sheet'!F104+'Data Sheet'!F100+'Data Sheet'!F102) -> 1.6493269 | I20: =('Data Sheet'!G125+'Data Sheet'!G126+'Data Sheet'!G127+'Data Sheet'!G129)/('Data Sheet'!G105+'Data Sheet'!G104+'Data Sheet'!G100+'Data Sheet'!G102) -> 1.9160092 | J20: =('Data Sheet'!H125+'Data Sheet'!H126+'Data Sheet'!H127+'Data Sheet'!H129)/('Data Sheet'!H105+'Data Sheet'!H104+'Data Sheet'!H100+'Data Sheet'!H102) -> 1.5980935 | K20: =('Data Sheet'!I125+'Data Sheet'!I126+'Data Sheet'!I127+'Data Sheet'!I129)/('Data Sheet'!I105+'Data Sheet'!I104+'Data Sheet'!I100+'Data Sheet'!I102) -> 1.413034 | L20: =('Data Sheet'!J125+'Data Sheet'!J126+'Data Sheet'!J127+'Data Sheet'!J129)/('Data Sheet'!J105+'Data Sheet'!J104+'Data Sheet'!J100+'Data Sheet'!J102) -> 1.5177509 | M20: =('Data Sheet'!K125+'Data Sheet'!K126+'Data Sheet'!K127+'Data Sheet'!K129)/('Data Sheet'!K105+'Data Sheet'!K104+'Data Sheet'!K100+'Data Sheet'!K102) -> 1.6524685 | ... O20: =('Data Sheet'!M125+'Data Sheet'!M126+'Data Sheet'!M127+'Data Sheet'!M129)/('Data Sheet'!M105+'Data Sheet'!M104+'Data Sheet'!M100+'Data Sheet'!M102) -> 1.3366727
D21: Quick Ratio | F21: =('Data Sheet'!D126+'Data Sheet'!D127+'Data Sheet'!D128)/('Data Sheet'!D106+'Data Sheet'!D105+'Data Sheet'!D104+'Data Sheet'!D107) -> 0.52971846 | G21: =('Data Sheet'!E126+'Data Sheet'!E127+'Data Sheet'!E128)/('Data Sheet'!E106+'Data Sheet'!E105+'Data Sheet'!E104+'Data Sheet'!E107) -> 0.48431981 | H21: =('Data Sheet'!F126+'Data Sheet'!F127+'Data Sheet'!F128)/('Data Sheet'!F106+'Data Sheet'!F105+'Data Sheet'!F104+'Data Sheet'!F107) -> 0.26453901 | I21: =('Data Sheet'!G126+'Data Sheet'!G127+'Data Sheet'!G128)/('Data Sheet'!G106+'Data Sheet'!G105+'Data Sheet'!G104+'Data Sheet'!G107) -> 0.24526895 | J21: =('Data Sheet'!H126+'Data Sheet'!H127+'Data Sheet'!H128)/('Data Sheet'!H106+'Data Sheet'!H105+'Data Sheet'!H104+'Data Sheet'!H107) -> 0.21683867 | K21: =('Data Sheet'!I126+'Data Sheet'!I127+'Data Sheet'!I128)/('Data Sheet'!I106+'Data Sheet'!I105+'Data Sheet'!I104+'Data Sheet'!I107) -> 0.25835716 | L21: =('Data Sheet'!J126+'Data Sheet'!J127+'Data Sheet'!J128)/('Data Sheet'!J106+'Data Sheet'!J105+'Data Sheet'!J104+'Data Sheet'!J107) -> 0.19494519 | M21: =('Data Sheet'!K126+'Data Sheet'!K127+'Data Sheet'!K128)/('Data Sheet'!K106+'Data Sheet'!K105+'Data Sheet'!K104+'Data Sheet'!K107) -> 0.22955612 | ... O21: =('Data Sheet'!M126+'Data Sheet'!M127+'Data Sheet'!M128)/('Data Sheet'!M106+'Data Sheet'!M105+'Data Sheet'!M104+'Data Sheet'!M107) -> 0.22723643
D22: Cash Ratio | F22: =('Data Sheet'!D127)/('Data Sheet'!D105+'Data Sheet'!D106+'Data Sheet'!D107) -> 0.26311513 | G22: =('Data Sheet'!E127)/('Data Sheet'!E105+'Data Sheet'!E106+'Data Sheet'!E107) -> 0.24097289 | H22: =('Data Sheet'!F127)/('Data Sheet'!F105+'Data Sheet'!F106+'Data Sheet'!F107) -> 0.019442472 | I22: =('Data Sheet'!G127)/('Data Sheet'!G105+'Data Sheet'!G106+'Data Sheet'!G107) -> 0.042465282 | J22: =('Data Sheet'!H127)/('Data Sheet'!H105+'Data Sheet'!H106+'Data Sheet'!H107) -> 0.031499738 | K22: =('Data Sheet'!I127)/('Data Sheet'!I105+'Data Sheet'!I106+'Data Sheet'!I107) -> 0.09903334 | L22: =('Data Sheet'!J127)/('Data Sheet'!J105+'Data Sheet'!J106+'Data Sheet'!J107) -> 0.016258322 | M22: =('Data Sheet'!K127)/('Data Sheet'!K105+'Data Sheet'!K106+'Data Sheet'!K107) -> 0.044329658 | ... O22: =('Data Sheet'!M127)/('Data Sheet'!M105+'Data Sheet'!M106+'Data Sheet'!M107) -> 0.046946908
D23: Operating Cash Flow Ratio | F23: ='Data Sheet'!B82/('Data Sheet'!D105+'Data Sheet'!D106+'Data Sheet'!D107) -> 0.52524489 | G23: ='Data Sheet'!C82/('Data Sheet'!E105+'Data Sheet'!E106+'Data Sheet'!E107) -> 0.5362713 | H23: ='Data Sheet'!D82/('Data Sheet'!F105+'Data Sheet'!F106+'Data Sheet'!F107) -> 0.3451456 | I23: ='Data Sheet'!E82/('Data Sheet'!G105+'Data Sheet'!G106+'Data Sheet'!G107) -> 0.34179445 | J23: ='Data Sheet'!F82/('Data Sheet'!H105+'Data Sheet'!H106+'Data Sheet'!H107) -> 0.52338739 | K23: ='Data Sheet'!G82/('Data Sheet'!I105+'Data Sheet'!I106+'Data Sheet'!I107) -> 0.61651361 | L23: ='Data Sheet'!H82/('Data Sheet'!J105+'Data Sheet'!J106+'Data Sheet'!J107) -> 0.42041755 | M23: ='Data Sheet'!I82/('Data Sheet'!K105+'Data Sheet'!K106+'Data Sheet'!K107) -> 0.34956865 | ... O23: ='Data Sheet'!K82/('Data Sheet'!M105+'Data Sheet'!M106+'Data Sheet'!M107) -> 0.29951257
D25: Efficiency Ratios
F26: 42460 | G26: =EDATE(F26,12) -> 42825 | H26: =EDATE(G26,12) -> 43190 | I26: =EDATE(H26,12) -> 43555 | J26: =EDATE(I26,12) -> 43921 | K26: =EDATE(J26,12) -> 44286 | L26: =EDATE(K26,12) -> 44651 | M26: =EDATE(L26,12) -> 45016 | N26: =EDATE(M26,12) -> 45382 | O26: =EDATE(N26,12) -> 45747 | P26: Trend
D27: Asset Turnover | F27: ='Data Sheet'!B17/'Data Sheet'!B66 -> 0.61061765 | G27: ='Data Sheet'!C17/'Data Sheet'!C66 -> 0.60117212 | H27: ='Data Sheet'!D17/'Data Sheet'!D66 -> 0.54214262 | I27: ='Data Sheet'!E17/'Data Sheet'!E66 -> 0.54181064 | J27: ='Data Sheet'!F17/'Data Sheet'!F66 -> 0.53563754 | K27: ='Data Sheet'!G17/'Data Sheet'!G66 -> 0.51900318 | L27: ='Data Sheet'!H17/'Data Sheet'!H66 -> 0.62758533 | M27: ='Data Sheet'!I17/'Data Sheet'!I66 -> 0.69205191 | ... O27: ='Data Sheet'!K17/'Data Sheet'!K66 -> 0.56839003
D28: Fixed Asset Turnover | F28: ='Data Sheet'!B17/('Data Sheet'!B62+'Data Sheet'!B63) -> 0.93930693 | G28: ='Data Sheet'!C17/('Data Sheet'!C62+'Data Sheet'!C63) -> 0.9459356 | H28: ='Data Sheet'!D17/('Data Sheet'!D62+'Data Sheet'!D63) -> 0.75142475 | I28: ='Data Sheet'!E17/('Data Sheet'!E62+'Data Sheet'!E63) -> 0.71736571 | J28: ='Data Sheet'!F17/('Data Sheet'!F62+'Data Sheet'!F63) -> 0.73066107 | K28: ='Data Sheet'!G17/('Data Sheet'!G62+'Data Sheet'!G63) -> 0.78331242 | L28: ='Data Sheet'!H17/('Data Sheet'!H62+'Data Sheet'!H63) -> 0.87268749 | M28: ='Data Sheet'!I17/('Data Sheet'!I62+'Data Sheet'!I63) -> 0.99403625 | ... O28: ='Data Sheet'!K17/('Data Sheet'!K62+'Data Sheet'!K63) -> 0.753535
D29: Days Sales Outstanding (DSO) | F29: ='Data Sheet'!D126/'Data Sheet'!B17*365 -> 27.97731 | G29: ='Data Sheet'!E126/'Data Sheet'!C17*365 -> 25.273163 | H29: ='Data Sheet'!F126/'Data Sheet'!D17*365 -> 26.168532 | I29: ='Data Sheet'!G126/'Data Sheet'!E17*365 -> 24.53448 | J29: ='Data Sheet'!H126/'Data Sheet'!F17*365 -> 20.499582 | K29: ='Data Sheet'!I126/'Data Sheet'!G17*365 -> 20.989675 | L29: ='Data Sheet'!J126/'Data Sheet'!H17*365 -> 21.317584 | M29: ='Data Sheet'!K126/'Data Sheet'!I17*365 -> 22.31903 | ... O29: ='Data Sheet'!M126/'Data Sheet'!K17*365 -> 28.304211
D30: Days Inventory Outstanding (DIO) | F30: ='Data Sheet'!D125/'Data Sheet'!B17*365 -> 35.624635 | G30: ='Data Sheet'!E125/'Data Sheet'!C17*365 -> 34.536633 | H30: ='Data Sheet'!F125/'Data Sheet'!D17*365 -> 38.50462 | I30: ='Data Sheet'!G125/'Data Sheet'!E17*365 -> 36.084261 | J30: ='Data Sheet'!H125/'Data Sheet'!F17*365 -> 35.983949 | K30: ='Data Sheet'!I125/'Data Sheet'!G17*365 -> 32.790246 | L30: ='Data Sheet'!J125/'Data Sheet'!H17*365 -> 38.832423 | M30: ='Data Sheet'!K125/'Data Sheet'!I17*365 -> 38.162251 | ... O30: ='Data Sheet'!M125/'Data Sheet'!K17*365 -> 45.954697
D31: Days Payable Outstanding (DPO) | F31: ='Data Sheet'!D105/('Data Sheet'!B18+'Data Sheet'!B19+'Data Sheet'!B20+'Data Sheet'!B21+'Data Sheet'!B22)*365 -> 50.401107 | G31: ='Data Sheet'!E105/('Data Sheet'!C18+'Data Sheet'!C19+'Data Sheet'!C20+'Data Sheet'!C21+'Data Sheet'!C22)*365 -> 55.535852 | H31: ='Data Sheet'!F105/('Data Sheet'!D18+'Data Sheet'!D19+'Data Sheet'!D20+'Data Sheet'!D21+'Data Sheet'!D22)*365 -> 54.521661 | I31: ='Data Sheet'!G105/('Data Sheet'!E18+'Data Sheet'!E19+'Data Sheet'!E20+'Data Sheet'!E21+'Data Sheet'!E22)*365 -> 53.306786 | J31: ='Data Sheet'!H105/('Data Sheet'!F18+'Data Sheet'!F19+'Data Sheet'!F20+'Data Sheet'!F21+'Data Sheet'!F22)*365 -> 57.584185 | K31: ='Data Sheet'!I105/('Data Sheet'!G18+'Data Sheet'!G19+'Data Sheet'!G20+'Data Sheet'!G21+'Data Sheet'!G22)*365 -> 83.219868 | L31: ='Data Sheet'!J105/('Data Sheet'!H18+'Data Sheet'!H19+'Data Sheet'!H20+'Data Sheet'!H21+'Data Sheet'!H22)*365 -> 78.378793 | M31: ='Data Sheet'!K105/('Data Sheet'!I18+'Data Sheet'!I19+'Data Sheet'!I20+'Data Sheet'!I21+'Data Sheet'!I22)*365 -> 72.41069 | ... O31: ='Data Sheet'!M105/('Data Sheet'!K18+'Data Sheet'!K19+'Data Sheet'!K20+'Data Sheet'!K21+'Data Sheet'!K22)*365 -> 82.645622
D33: Leverage Ratios
F34: 42460 | G34: =EDATE(F34,12) -> 42825 | H34: =EDATE(G34,12) -> 43190 | I34: =EDATE(H34,12) -> 43555 | J34: =EDATE(I34,12) -> 43921 | K34: =EDATE(J34,12) -> 44286 | L34: =EDATE(K34,12) -> 44651 | M34: =EDATE(L34,12) -> 45016 | N34: =EDATE(M34,12) -> 45382 | O34: =EDATE(N34,12) -> 45747 | P34: Trend
D35: Debt-to-Equity | F35: =('Data Sheet'!D102+'Data Sheet'!D99+'Data Sheet'!D100+'Data Sheet'!D101)/('Data Sheet'!D96+'Data Sheet'!D97) -> 0.48380041 | G35: =('Data Sheet'!E102+'Data Sheet'!E99+'Data Sheet'!E100+'Data Sheet'!E101)/('Data Sheet'!E96+'Data Sheet'!E97) -> 0.34740899 | H35: =('Data Sheet'!F102+'Data Sheet'!F99+'Data Sheet'!F100+'Data Sheet'!F101)/('Data Sheet'!F96+'Data Sheet'!F97) -> 0.73834433 | I35: =('Data Sheet'!G102+'Data Sheet'!G99+'Data Sheet'!G100+'Data Sheet'!G101)/('Data Sheet'!G96+'Data Sheet'!G97) -> 0.75067405 | J35: =('Data Sheet'!H102+'Data Sheet'!H99+'Data Sheet'!H100+'Data Sheet'!H101)/('Data Sheet'!H96+'Data Sheet'!H97) -> 0.58956562 | K35: =('Data Sheet'!I102+'Data Sheet'!I99+'Data Sheet'!I100+'Data Sheet'!I101)/('Data Sheet'!I96+'Data Sheet'!I97) -> 0.49165818 | L35: =('Data Sheet'!J102+'Data Sheet'!J99+'Data Sheet'!J100+'Data Sheet'!J101)/('Data Sheet'!J96+'Data Sheet'!J97) -> 0.22402649 | M35: =('Data Sheet'!K102+'Data Sheet'!K99+'Data Sheet'!K100+'Data Sheet'!K101)/('Data Sheet'!K96+'Data Sheet'!K97) -> 0.20353428 | ... O35: =('Data Sheet'!M102+'Data Sheet'!M99+'Data Sheet'!M100+'Data Sheet'!M101)/('Data Sheet'!M96+'Data Sheet'!M97) -> 0.34087148
D36: Debt-to-Assets | F36: =('Data Sheet'!D99+'Data Sheet'!D100+'Data Sheet'!D101+'Data Sheet'!D102)/'Data Sheet'!D130 -> 0.25773797 | G36: =('Data Sheet'!E99+'Data Sheet'!E100+'Data Sheet'!E101+'Data Sheet'!E102)/'Data Sheet'!E130 -> 0.20076287 | H36: =('Data Sheet'!F99+'Data Sheet'!F100+'Data Sheet'!F101+'Data Sheet'!F102)/'Data Sheet'!F130 -> 0.34089358 | I36: =('Data Sheet'!G99+'Data Sheet'!G100+'Data Sheet'!G101+'Data Sheet'!G102)/'Data Sheet'!G130 -> 0.33108135 | J36: =('Data Sheet'!H99+'Data Sheet'!H100+'Data Sheet'!H101+'Data Sheet'!H102)/'Data Sheet'!H130 -> 0.29059257 | K36: =('Data Sheet'!I99+'Data Sheet'!I100+'Data Sheet'!I101+'Data Sheet'!I102)/'Data Sheet'!I130 -> 0.25203073 | L36: =('Data Sheet'!J99+'Data Sheet'!J100+'Data Sheet'!J101+'Data Sheet'!J102)/'Data Sheet'!J130 -> 0.13481524 | M36: =('Data Sheet'!K99+'Data Sheet'!K100+'Data Sheet'!K101+'Data Sheet'!K102)/'Data Sheet'!K130 -> 0.12100022 | ... O36: =('Data Sheet'!M99+'Data Sheet'!M100+'Data Sheet'!M101+'Data Sheet'!M102)/'Data Sheet'!M130 -> 0.18036099
D37: Debt-to-EBITDA | F37: =('Data Sheet'!D99+'Data Sheet'!D100+'Data Sheet'!D101+'Data Sheet'!D102)/'Historical FS'!C18 -> 2.1663059 | G37: =('Data Sheet'!E99+'Data Sheet'!E100+'Data Sheet'!E101+'Data Sheet'!E102)/'Historical FS'!D18 -> 1.6257261 | H37: =('Data Sheet'!F99+'Data Sheet'!F100+'Data Sheet'!F101+'Data Sheet'!F102)/'Historical FS'!E18 -> 3.1698787 | I37: =('Data Sheet'!G99+'Data Sheet'!G100+'Data Sheet'!G101+'Data Sheet'!G102)/'Historical FS'!F18 -> 3.4485105 | J37: =('Data Sheet'!H99+'Data Sheet'!H100+'Data Sheet'!H101+'Data Sheet'!H102)/'Historical FS'!G18 -> 2.4896252 | K37: =('Data Sheet'!I99+'Data Sheet'!I100+'Data Sheet'!I101+'Data Sheet'!I102)/'Historical FS'!H18 -> 1.8775215 | L37: =('Data Sheet'!J99+'Data Sheet'!J100+'Data Sheet'!J101+'Data Sheet'!J102)/'Historical FS'!I18 -> 0.98129725 | M37: =('Data Sheet'!K99+'Data Sheet'!K100+'Data Sheet'!K101+'Data Sheet'!K102)/'Historical FS'!J18 -> 1.0411635 | ... O37: =('Data Sheet'!M99+'Data Sheet'!M100+'Data Sheet'!M101+'Data Sheet'!M102)/'Historical FS'!L18 -> 1.8834278
D38: Equity Multiplier | F38: ='Data Sheet'!D130/('Data Sheet'!D96+'Data Sheet'!D97) -> 1.8771018 | G38: ='Data Sheet'!E130/('Data Sheet'!E96+'Data Sheet'!E97) -> 1.7304444 | H38: ='Data Sheet'!F130/('Data Sheet'!F96+'Data Sheet'!F97) -> 2.1659086 | I38: ='Data Sheet'!G130/('Data Sheet'!G96+'Data Sheet'!G97) -> 2.2673402 | J38: ='Data Sheet'!H130/('Data Sheet'!H96+'Data Sheet'!H97) -> 2.0288393 | K38: ='Data Sheet'!I130/('Data Sheet'!I96+'Data Sheet'!I97) -> 1.9507866 | L38: ='Data Sheet'!J130/('Data Sheet'!J96+'Data Sheet'!J97) -> 1.6617297 | M38: ='Data Sheet'!K130/('Data Sheet'!K96+'Data Sheet'!K97) -> 1.6820985 | ... O38: ='Data Sheet'!M130/('Data Sheet'!M96+'Data Sheet'!M97) -> 1.8899402
D39: Interest Coverage (ICR) | F39: ='Historical FS'!C21/'Historical FS'!C20 -> 5.2224969 | G39: ='Historical FS'!D21/'Historical FS'!D20 -> 5.0366037 | H39: ='Historical FS'!E21/'Historical FS'!E20 -> 2.4721235 | I39: ='Historical FS'!F21/'Historical FS'!F20 -> 1.7539908 | J39: ='Historical FS'!G21/'Historical FS'!G20 -> 2.2753295 | K39: ='Historical FS'!H21/'Historical FS'!H20 -> 4.968889 | L39: ='Historical FS'!I21/'Historical FS'!I20 -> 8.3146045 | M39: ='Historical FS'!J21/'Historical FS'!J20 -> 8.397924 | ... O39: ='Historical FS'!L21/'Historical FS'!L20 -> 4.3206405
D40: Debt Service Coverage (DSCR) | F40: ='Historical FS'!C18/'Historical FS'!C20 -> 8.6543705 | G40: ='Historical FS'!D18/'Historical FS'!D20 -> 8.1431651 | H40: ='Historical FS'!E18/'Historical FS'!E20 -> 4.9652796 | I40: ='Historical FS'!F18/'Historical FS'!F20 -> 4.1324626 | J40: ='Historical FS'!G18/'Historical FS'!G20 -> 4.6423669 | K40: ='Historical FS'!H18/'Historical FS'!H20 -> 7.7864302 | L40: ='Historical FS'!I18/'Historical FS'!I20 -> 12.188238 | M40: ='Historical FS'!J18/'Historical FS'!J20 -> 12.908219 | ... O40: ='Historical FS'!L18/'Historical FS'!L20 -> 7.7531475
D42: DuPont Ratios
F43: 42460 | G43: =EDATE(F43,12) -> 42825 | H43: =EDATE(G43,12) -> 43190 | I43: =EDATE(H43,12) -> 43555 | J43: =EDATE(I43,12) -> 43921 | K43: =EDATE(J43,12) -> 44286 | L43: =EDATE(K43,12) -> 44651 | M43: =EDATE(L43,12) -> 45016 | N43: =EDATE(M43,12) -> 45382 | O43: =EDATE(N43,12) -> 45747 | P43: Trend
D44: Net Profit Margin | F44: =F12 -> 0.080141167 | G44: =G12 -> 0.081394872 | H44: =H12 -> 0.063995427 | I44: =I12 -> 0.049449306 | J44: =J12 -> 0.12019404 | K44: =K12 -> 0.1082894 | L44: =L12 -> 0.12671061 | M44: =M12 -> 0.072205747 | ... O44: =O12 -> 0.074292546
D45: Asset Turnover | F45: =F27 -> 0.61061765 | G45: =G27 -> 0.60117212 | H45: =H27 -> 0.54214262 | I45: =I27 -> 0.54181064 | J45: =J27 -> 0.53563754 | K45: =K27 -> 0.51900318 | L45: =L27 -> 0.62758533 | M45: =M27 -> 0.69205191 | ... O45: =O27 -> 0.56839003
D46: Equity Multiplier | F46: =F38 -> 1.8771018 | G46: =G38 -> 1.7304444 | H46: =H38 -> 2.1659086 | I46: =I38 -> 2.2673402 | J46: =J38 -> 2.0288393 | K46: =K38 -> 1.9507866 | L46: =L38 -> 1.6617297 | M46: =M38 -> 1.6820985 | ... O46: =O38 -> 1.8899402
D47: DuPont ROE | F47: =F44*F45*F46 -> 0.091857125 | G47: =G44*G45*G46 -> 0.084674673 | H47: =H44*H45*H46 -> 0.075145435 | I47: =I44*I45*I46 -> 0.060746943 | J47: =J44*J45*J46 -> 0.13061757 | K47: =K44*K45*K46 -> 0.10963917 | L47: =L44*L45*L46 -> 0.13214361 | M47: =M44*M45*M46 -> 0.084054671 | ... O47: =O44*O45*O46 -> 0.079806773

Sheet Valuation->

Sheet NWC
D2: UltraTech Cement Ltd (NSE: ULTRACEMCO)
D3: Working Capital Projections
D4: (Figures are in ₹ Cr, except price per share)
F5: Historical Period | I5: Projection Period
F6: 2023A | G6: 2024A | H6: 2025A | I6: 2026E | J6: 2027E | K6: 2028E | L6: 2029E | M6: 2030E
D8: Revenue | F8: =DCF!G8 -> 63239.98 | G8: =DCF!H8 -> 70908.14 | H8: =DCF!I8 -> 75955.13 | I8: =DCF!K8 -> 88297.839 | J8: =DCF!L8 -> 98937.728 | K8: =DCF!M8 -> 110038.54 | L8: =DCF!N8 -> 119094.71 | M8: =DCF!O8 -> 125895.02
D9: Cost of Goods Sold | F9: =DCF!G10 -> 35301.93 | G9: =DCF!H10 -> 38136.4 | H9: =DCF!I10 -> 41216.74 | I9: =DCF!K10 -> 46797.854 | J9: =DCF!L10 -> 52436.996 | K9: =DCF!M10 -> 58320.427 | L9: =DCF!N10 -> 63120.198 | M9: =DCF!O10 -> 66724.361
D11: Current Assets
D12: Trade Receivables | F12: 3867 | G12: 4278 | H12: 5890 | I12: =I29*I$8/365 -> 6847.125 | J12: =J29*J$8/365 -> 7672.2036 | K12: =K29*K$8/365 -> 8533.0248 | L12: =L29*L$8/365 -> 9235.2927 | M12: =M29*M$8/365 -> 9762.628
D13: Inventories | F13: 6612 | G13: 8330 | H13: 9563 | I13: =I30*I$8/365 -> 11116.988 | J13: =J30*J$8/365 -> 12456.584 | K13: =K30*K$8/365 -> 13854.213 | L13: =L30*L$8/365 -> 14994.415 | M13: =M30*M$8/365 -> 15850.596
D14: Loans and Advances | F14: 951 | G14: 985 | H14: 1259 | I14: =I8*I31 -> 1463.5875 | J14: =J8*J31 -> 1639.9498 | K14: =K8*K31 -> 1823.9522 | L14: =L8*L31 -> 1974.0634 | M14: =M8*M31 -> 2086.7824
D15: Total Current Assets | F15: =SUM(F12:F14) -> 11430 | G15: =SUM(G12:G14) -> 13593 | H15: =SUM(H12:H14) -> 16712 | I15: =SUM(I12:I14) -> 19427.7 | J15: =SUM(J12:J14) -> 21768.738 | K15: =SUM(K12:K14) -> 24211.19 | L15: =SUM(L12:L14) -> 26203.771 | M15: =SUM(M12:M14) -> 27700.007
D17: Current Liabilities
D18: Trade Payables | F18: 7209 | G18: 8478 | H18: 9327 | I18: =I34*I9/365 -> 10589.959 | J18: =J34*J9/365 -> 11866.049 | K18: =K34*K9/365 -> 13197.42 | L18: =L34*L9/365 -> 14283.567 | M18: =M34*M9/365 -> 15099.159
D19: Advance from Customers | F19: 384 | G19: 527 | H19: 541 | I19: =I8*I35 -> 628.9125 | J19: =J8*J35 -> 704.69646 | K19: =K8*K35 -> 783.7634 | L19: =L8*L35 -> 848.26713 | M19: =M8*M35 -> 896.70318
D20: Total Current Liabilties | F20: =SUM(F18:F19) -> 7593 | G20: =SUM(G18:G19) -> 9005 | H20: =SUM(H18:H19) -> 9868 | I20: =SUM(I18:I19) -> 11218.872 | J20: =SUM(J18:J19) -> 12570.746 | K20: =SUM(K18:K19) -> 13981.183 | L20: =SUM(L18:L19) -> 15131.835 | M20: =SUM(M18:M19) -> 15995.862
D22: Net Working Capital | F22: =F15-F20 -> 3837 | G22: =G15-G20 -> 4588 | H22: =H15-H20 -> 6844 | I22: =I15-I20 -> 8208.8285 | J22: =J15-J20 -> 9197.9923 | K22: =K15-K20 -> 10230.007 | L22: =L15-L20 -> 11071.937 | M22: =M15-M20 -> 11704.144
D23: % Revenue | F23: =F22/F8 -> 0.060673643 | G23: =G22/G8 -> 0.064703432 | H23: =H22/H8 -> 0.09010583 | I23: =I22/I8 -> 0.09296749 | J23: =J22/J8 -> 0.09296749 | K23: =K22/K8 -> 0.09296749 | L23: =L22/L8 -> 0.09296749 | M23: =M22/M8 -> 0.09296749
D25: Increase/Decrease in NWC | F25: 0 | G25: =F22-G22 -> -751 | H25: =G22-H22 -> -2256 | I25: =H22-I22 -> -1364.8285 | J25: =I22-J22 -> -989.16383 | K25: =J22-K22 -> -1032.0147 | L25: =K22-L22 -> -841.92958 | M25: =L22-M22 -> -632.20758
D27: Assumptions
D28: Current Assets
D29: Trade Receivables | F29: =F12/F$8*365 -> 22.31903 | G29: =G12/G$8*365 -> 22.021026 | H29: =H12/H$8*365 -> 28.304211 | I29: =H29 -> 28.304211 | J29: =I29 -> 28.304211 | K29: =J29 -> 28.304211 | L29: =K29 -> 28.304211 | M29: =L29 -> 28.304211
D30: Inventories | F30: =F13/F$8*365 -> 38.162251 | G30: =G13/G$8*365 -> 42.878716 | H30: =H13/H$8*365 -> 45.954697 | I30: =H30 -> 45.954697 | J30: =I30 -> 45.954697 | K30: =J30 -> 45.954697 | L30: =K30 -> 45.954697 | M30: =L30 -> 45.954697
D31: Loans and Advances (% of Rev.) | F31: =F14/F8 -> 0.015037955 | G31: =G14/G8 -> 0.013891212 | H31: =H14/H8 -> 0.016575576 | I31: =H31 -> 0.016575576 | J31: =I31 -> 0.016575576 | K31: =J31 -> 0.016575576 | L31: =K31 -> 0.016575576 | M31: =L31 -> 0.016575576
D33: Current Liabilities
D34: Trade Payables | F34: =F18/F9*365 -> 74.536576 | G34: =G18/G9*365 -> 81.142163 | H34: =H18/H9*365 -> 82.596416 | I34: =H34 -> 82.596416 | J34: =I34 -> 82.596416 | K34: =J34 -> 82.596416 | L34: =K34 -> 82.596416 | M34: =L34 -> 82.596416
D35: Advance from Customers (% of Rev.) | F35: =F19/F8 -> 0.0060721082 | G35: =G19/G8 -> 0.0074321509 | H35: =H19/H8 -> 0.0071226262 | I35: =H35 -> 0.0071226262 | J35: =I35 -> 0.0071226262 | K35: =J35 -> 0.0071226262 | L35: =K35 -> 0.0071226262 | M35: =L35 -> 0.0071226262

Sheet Comps
D2: UltraTech Cement Ltd (NSE: ULTRACEMCO)
D3: Comparable Company Analysis
D4: (Figures are in ₹ Cr, except price per share)
D6: Comparable Company Analysis - UltraTech Cement Ltd.
E7: Market Data | K7: Financials | O7: Valuation
E8: Current | F8: Shares | G8: Equity | H8: Net | I8: Enterprise | O8: Enterprise Value/ | Q8: Price/
D9: Company (1) | E9: Price | F9: Outstanding | G9: Value | H9: Debt | I9: Value | K9: Revenue | L9: EBITDA | M9: Net Profit | O9: Revenue | P9: EBITDA | Q9: EPS
D10: UltraTech Cement Ltd. | E10: 12039 | F10: 29.47 | G10: 354934.02 | H10: 24102.18 | I10: =G10+H10 -> 379036.2 | K10: 75955.13 | L10: 12796.88 | M10: 5642.9 | O10: =I10/K10 -> 4.9902646 | P10: =I10/L10 -> 29.619423 | Q10: =E10/(M10/F10) -> 62.873581
D12: Ambuja Cements | E12: 456.25 | F12: 248.48 | G12: 113469.56 | H12: 1270.72 | I12: =G12+H12 -> 114740.28 | K12: 39720.76 | L12: =4705.74+3428.89 -> 8134.63 | M12: 3842.1 | O12: =I12/K12 -> 2.8886728 | P12: =I12/L12 -> 14.105163 | Q12: =E12/(M12/F12) -> 29.50704
D13: Shree Cement | E13: 25540 | F13: 3.61 | G13: 92253.2 | H13: 2141.96 | I13: =G13+H13 -> 94395.16 | K13: 20374.49 | L13: 5400.04 | M13: 1792.19 | O13: =I13/K13 -> 4.6330073 | P13: =I13/L13 -> 17.480456 | Q13: =E13/(M13/F13) -> 51.445103
D14: J K Cements | E14: 5920.5 | F14: 7.73 | G14: 45817.02 | H14: 6509.83 | I14: =G14+H14 -> 52326.85 | K14: 13415.98 | L14: 2655.8 | M14: 1050.87 | O14: =I14/K14 -> 3.9003375 | P14: =I14/L14 -> 19.702858 | Q14: =E14/(M14/F14) -> 43.550073
D15: Dalmia Bharat Ltd | E15: 1990 | F15: 18.76 | G15: 37369.94 | H15: 7082 | I15: =G15+H15 -> 44451.94 | K15: 14650 | L15: 3244 | M15: 1196.3 | O15: =I15/K15 -> 3.0342621 | P15: =I15/L15 -> 13.702818 | Q15: =E15/(M15/F15) -> 31.206554
D16: ACC | E16: 1438 | F16: 18.78 | G16: 26989.64 | H16: 485.44 | I16: =G16+H16 -> 27475.08 | K16: 24689.33 | L16: 3703.66 | M16: 2516.29 | O16: =I16/K16 -> 1.1128321 | P16: =I16/L16 -> 7.4183591 | Q16: =E16/(M16/F16) -> 10.732324
D17: The Ramco Cement | E17: 1003.6 | F17: 23.63 | G17: 23669.79 | H17: 4699.15 | I17: =G17+H17 -> 28368.94 | K17: 8815.71 | L17: 1426.7 | M17: 187.73 | O17: =I17/K17 -> 3.2179983 | P17: =I17/L17 -> 19.884306 | Q17: =E17/(M17/F17) -> 126.3254
D18: Nuvoco Vistas | E18: 304.8 | F18: 1.78159 | G18: 10889.65 | H18: 4916.1 | I18: =G18+H18 -> 15805.75 | K18: 11338.29 | L18: =883.98+996.94 -> 1880.92 | M18: 389.84 | O18: =I18/K18 -> 1.3940153 | P18: =I18/L18 -> 8.4032016 | Q18: =E18/(M18/F18) -> 1.3929526
D20: Mean | O20: =AVERAGE(O12:O18) -> 2.8830179 | P20: =AVERAGE(P12:P18) -> 14.385309 | Q20: =AVERAGE(Q12:Q18) -> 42.022779
D21: Median | O21: =MEDIAN(O12:O18) -> 3.0342621 | P21: =MEDIAN(P12:P18) -> 14.105163 | Q21: =MEDIAN(Q12:Q18) -> 31.206554
D23: Maximum | O23: =MAX(O12:O18) -> 4.6330073 | P23: =MAX(P12:P18) -> 19.884306 | Q23: =MAX(Q12:Q18) -> 126.3254
D24: Minimum | O24: =MIN(O12:O18) -> 1.1128321 | P24: =MIN(P12:P18) -> 7.4183591 | Q24: =MIN(Q12:Q18) -> 1.3929526
D26: UltraTech Cement Ltd. Comparable Valuation | O26: EV/Revenue | P26: EV/EBITDA | Q26: P/E
D27: Implied Enterprise Value | O27: =O20*K$10 -> 218980 | P27: =P20*L$10 -> 184087.07 | Q27: =Q20*M$10 -> 237130.34
D28: Net Debt | O28: =$H$10 -> 24102.18 | P28: =$H$10 -> 24102.18 | Q28: =$H$10 -> 24102.18
D29: Implied Equity Value | O29: =O27-O28 -> 194877.82 | P29: =P27-P28 -> 159984.89 | Q29: =Q27-Q28 -> 213028.16
D30: Diluted Shares Outstanding | O30: =$F$10 -> 29.47 | P30: =$F$10 -> 29.47 | Q30: =$F$10 -> 29.47
D32: Implied Share Price | O32: =O29/O30 -> 6612.7527 | P32: =P29/P30 -> 5428.7373 | Q32: =Q29/Q30 -> 7228.6446
D33: Discount/Premium | O33: =IF(O32<$E$10,"Overvalued","Undervalued") -> Overvalued | P33: =IF(P32<$E$10,"Overvalued","Undervalued") -> Overvalued | Q33: =IF(Q32<$E$10,"Overvalued","Undervalued") -> Overvalued
D36: (1) Sourced from Screener.com

Sheet WACC
D2: UltraTech Cement Ltd (NSE: ULTRACEMCO)
D3: Weighted Average Cost of Capital
D4: (Figures are in ₹ Cr, except price per share)
D7: WACC Calculation | H7: Comparable Companies Unlevered Beta
D8: Target Capital Structure | I8: Predicted | J8: Market | K8: Market | L8: Debt/ | M8: Marginal | N8: Unlevered
D9: Debt-to-Total Capitalization | F9: 0.2 | H9: Company | I9: Levered Beta (1) | J9: Value of Debt | K9: Value of Equity | L9: Equity | M9: Tax Rate | N9: Beta
D10: Equity-to-Total Capitalization | F10: =1-F9 -> 0.8 | H10: Ambuja Cements | I10: 1.16 | J10: 1270.72 | K10: 113469.56 | L10: =J10/K10 -> 0.011198774 | M10: 0.3 | N10: =I10/(1+L10*(1-M10)) -> 1.1509773
H11: Shree Cement | I11: 0.67 | J11: 2141.96 | K11: 92253.2 | L11: =J11/K11 -> 0.023218273 | M11: 0.3 | N11: =I11/(1+L11*(1-M11)) -> 0.65928478
H12: J K Cements | I12: 1.04 | J12: 6509.83 | K12: 45817.02 | L12: =J12/K12 -> 0.14208323 | M12: 0.3 | N12: =I12/(1+L12*(1-M12)) -> 0.9459204
D13: Cost of Debt | H13: Dalmia Bharat Ltd | I13: 0.9 | J13: 7082 | K13: 37369.94 | L13: =J13/K13 -> 0.18951061 | M13: 0.3 | N13: =I13/(1+L13*(1-M13)) -> 0.79459153
D14: Cost of Debt (2) | F14: ='Historical FS'!L20/('Historical FS'!L39) -> 0.068480942 | H14: ACC | I14: 1.12 | J14: 485.44 | K14: 26989.64 | L14: =J14/K14 -> 0.017986161 | M14: 0.3 | N14: =I14/(1+L14*(1-M14)) -> 1.1060742
D15: Tax Rate | F15: 0.3 | H15: The Ramco Cement | I15: 0.76 | J15: 4699.15 | K15: 23669.79 | L15: =J15/K15 -> 0.19852943 | M15: 0.3 | N15: =I15/(1+L15*(1-M15)) -> 0.6672692
D16: After-Tax Cost of Debt | F16: =F14*(1-F15) -> 0.04793666 | H16: Nuvoco Vistas | I16: 0.78 | J16: 4916.1 | K16: 10889.65 | L16: =J16/K16 -> 0.45144702 | M16: 0.3 | N16: =I16/(1+L16*(1-M16)) -> 0.59269935
H18: Mean | I18: =AVERAGE(I10:I16) -> 0.91857143 | L18: =AVERAGE(L10:L16) -> 0.1477105 | N18: =AVERAGE(N10:N16) -> 0.84525954
D19: Cost of Equity | H19: Median | I19: =MEDIAN(I10:I16) -> 0.9 | L19: =MEDIAN(L10:L16) -> 0.14208323 | N19: =MEDIAN(N10:N16) -> 0.79459153
D20: Risk Free Rate (3) | F20: 0.06891
D21: Market Risk Premium (4) | F21: =7%-2.85% -> 0.0415 | H21: UltraTech Cement Relevered Beta
D22: Levered Beta | F22: =N25 -> 0.99317996 | K22: Mean | L22: Target | M22: Target
D23: Country Risk Premium (5) | F23: 0.0285 | K23: UnLevered | L23: Debt/ | M23: Marginal | N23: Relevered
D24: Cost of Equity | F24: =F20+(F21*F22)+F23 -> 0.13862697 | K24: Beta | L24: Equity | M24: Tax Rate | N24: Beta
H25: Relevered Beta | K25: =N18 -> 0.84525954 | L25: =F9/F10 -> 0.25 | M25: 0.3 | N25: =K25*(1+L25*(1-M25)) -> 0.99317996
D26: WACC | F26: =(F16*F9)+(F24*F10) -> 0.12048891
H27: WACC Sensitivity Analysis
J28: Pre-Tax Cost of Debt
H29: Debt to Total Capitalization | I29: =F26 -> 0.12048891 | J29: 0.06 | K29: 0.065 | L29: 0.07 | M29: 0.075 | N29: 0.08
I30: 0.1 | J30: 0.12589492 | K30: 0.12624492 | L30: 0.12659492 | M30: 0.12694492 | N30: 0.12729492
I31: 0.15 | J31: 0.12259825 | K31: 0.12312325 | L31: 0.12364825 | M31: 0.12417325 | N31: 0.12469825
I32: 0.2 | J32: 0.11930157 | K32: 0.12000157 | L32: 0.12070157 | M32: 0.12140157 | N32: 0.12210157
I33: 0.25 | J33: 0.1160049 | K33: 0.1168799 | L33: 0.1177549 | M33: 0.1186299 | N33: 0.1195049
I34: 0.3 | J34: 0.11270823 | K34: 0.11375823 | L34: 0.11480823 | M34: 0.11585823 | N34: 0.11690823
D35: (1) Sourced from MorningStar.com
D36: (2) Average cost of debt across UltraTech Cement's capital structure
D37: (3) Interpolated yield on 10-year India Govt Yield, sourced from tradingeconomics.com
D38: (4), (5) Sourced from Aswath Damodaran

Sheet DCF
D2: UltraTech Cement Ltd (NSE: ULTRACEMCO)
D3: Discounted Cash Flow Analysis (DCF) | N3: Valuation Method | P3: =IF(F7="Y", "EBITDA Multiple", "Terminal Rate") -> Terminal Rate
D4: (Figures are in ₹ Cr, fiscal year ending March 31) | N4: Operating Scenario | P4: {=_xlfn.IFS(F5=1,"Base",F5=2,"Upside",F5=3,"Downside")} -> Base
D5: Opearting Scenario | F5: 1
D6: Mid-Year Convention | F6: Y | G6: Historical Period | J6: CAGR | K6: Projection Period | P6: CAGR
D7: Multiple Method | F7: N | G7: 2023A | H7: 2024A | I7: 2025A | J7: ('23-'25) | K7: 2026E | L7: 2027E | M7: 2028E | N7: 2029E | O7: 2030E | P7: ('26-'30)
D8: Revenue | G8: =Inc_Stat!M9 -> 63239.98 | H8: =Inc_Stat!N9 -> 70908.14 | I8: =Inc_Stat!O9 -> 75955.13 | J8: =_xlfn.RRI(2,G8,I8) -> 0.095929693 | K8: =I8*(1+K9) -> 88297.839 | L8: =K8*(1+L9) -> 98937.728 | M8: =L8*(1+M9) -> 110038.54 | N8: =M8*(1+N9) -> 119094.71 | O8: =N8*(1+O9) -> 125895.02 | P8: =_xlfn.RRI(4,K8,O8) -> 0.092734414
D9: % Growth | G9: =G8/Inc_Stat!L9-1 -> 0.20230773 | H9: =H8/G8-1 -> 0.12125494 | I9: =I8/H8-1 -> 0.071176454 | K9: {=_xlfn.IFS(F5=1,16.25%,F5=2,17.5%,F5=3,15%)} -> 0.1625 | L9: {=_xlfn.IFS(F5=1,12.05%,F5=2,13%,F5=3,11%)} -> 0.1205 | M9: {=_xlfn.IFS(F5=1,11.22%,F5=2,12.2%,F5=3,10.2%)} -> 0.1122 | N9: {=_xlfn.IFS(F5=1,8.23%,F5=2,9.2%,F5=3,7.2%)} -> 0.0823 | O9: {=_xlfn.IFS(F5=1,5.71%,F5=2,6.7%,F5=3,4.7%)} -> 0.0571
D10: Cost of Goods Sold | G10: =Inc_Stat!M11 -> 35301.93 | H10: =Inc_Stat!N11 -> 38136.4 | I10: =Inc_Stat!O11 -> 41216.74 | K10: =K8*K11 -> 46797.854 | L10: =L8*L11 -> 52436.996 | M10: =M8*M11 -> 58320.427 | N10: =N8*N11 -> 63120.198 | O10: =O8*O11 -> 66724.361
D11: % Margin | G11: =G10/G8 -> 0.55822171 | H11: =H10/H8 -> 0.53782824 | I11: =I10/I8 -> 0.5426459 | K11: 0.53 | L11: 0.53 | M11: 0.53 | N11: 0.53 | O11: 0.53
D12: Gross Margin | G12: =G8-G10 -> 27938.05 | H12: =H8-H10 -> 32771.74 | I12: =I8-I10 -> 34738.39 | J12: =_xlfn.RRI(2,G12,I12) -> 0.11508198 | K12: =K8-K10 -> 41499.984 | L12: =L8-L10 -> 46500.732 | M12: =M8-M10 -> 51718.114 | N12: =N8-N10 -> 55974.515 | O12: =O8-O10 -> 59170.66 | P12: =_xlfn.RRI(4,K12,O12) -> 0.092734414
D13: % Margin | G13: =G12/G10 -> 0.79140291 | H13: =H12/H10 -> 0.85932967 | I13: =I12/I10 -> 0.84282236 | K13: =I13 -> 0.84282236 | L13: =K13 -> 0.84282236 | M13: =L13 -> 0.84282236 | N13: =M13 -> 0.84282236 | O13: =N13 -> 0.84282236
D14: Selling, General & Administration | G14: =-Inc_Stat!M16 -> 17318.2 | H14: =-Inc_Stat!N16 -> 19793.18 | I14: =-Inc_Stat!O16 -> 21941.51 | K14: =K15*K8 -> 25507.005 | L14: =L15*L8 -> 28580.6 | M14: =M15*M8 -> 31787.343 | N14: =N15*N8 -> 34403.441 | O14: =O15*O8 -> 36367.878
D15: % Margin | G15: =G14/G8 -> 0.27384892 | H15: =H14/H8 -> 0.27913833 | I15: =I14/I8 -> 0.28887463 | K15: =I15 -> 0.28887463 | L15: =K15 -> 0.28887463 | M15: =L15 -> 0.28887463 | N15: =M15 -> 0.28887463 | O15: =N15 -> 0.28887463
D16: EBITDA | G16: =G12-G14 -> 10619.85 | H16: =H12-H14 -> 12978.56 | I16: =I12-I14 -> 12796.88 | J16: =_xlfn.RRI(2,G16,I16) -> 0.097723237 | K16: =K12-K14 -> 15992.979 | L16: =L12-L14 -> 17920.133 | M16: =M12-M14 -> 19930.772 | N16: =N12-N14 -> 21571.074 | O16: =O12-O14 -> 22802.782 | P16: =_xlfn.RRI(4,K16,O16) -> 0.092734414
D17: % Margin | G17: =G16/G8 -> 0.16792937 | H17: =H16/H8 -> 0.18303343 | I17: =I16/I8 -> 0.16847947 | K17: =K16/K8 -> 0.18112537 | L17: =L16/L8 -> 0.18112537 | M17: =M16/M8 -> 0.18112537 | N17: =N16/N8 -> 0.18112537 | O17: =O16/O8 -> 0.18112537
D18: Depreciation & Amortisation | G18: =-Inc_Stat!M21 -> 2887.99 | H18: =-Inc_Stat!N21 -> 3145.3 | I18: =-Inc_Stat!O21 -> 4014.95 | K18: =K19*K8 -> 4667.3794 | L18: =L19*L8 -> 5229.7986 | M18: =M19*M8 -> 5816.582 | N18: =N19*N8 -> 6295.2867 | O18: =O19*O8 -> 6654.7476
D19: % Margin | G19: =G18/G8 -> 0.045667155 | H19: =H18/H8 -> 0.04435739 | I19: =I18/I8 -> 0.052859497 | K19: =I19 -> 0.052859497 | L19: =K19 -> 0.052859497 | M19: =L19 -> 0.052859497 | N19: =M19 -> 0.052859497 | O19: =N19 -> 0.052859497
D20: EBIT | G20: =G16-G18 -> 7731.86 | H20: =H16-H18 -> 9833.26 | I20: =I16-I18 -> 8781.93 | J20: =_xlfn.RRI(2,G20,I20) -> 0.065744241 | K20: =K16-K18 -> 11325.599 | L20: =L16-L18 -> 12690.334 | M20: =M16-M18 -> 14114.19 | N20: =N16-N18 -> 15275.787 | O20: =O16-O18 -> 16148.035 | P20: =_xlfn.RRI(4,K20,O20) -> 0.092734414
D21: % Margin | G21: =G20/G8 -> 0.12226221 | H21: =H20/H8 -> 0.13867604 | I21: =I20/I8 -> 0.11561997 | K21: =K20/K8 -> 0.12826587 | L21: =L20/L8 -> 0.12826587 | M21: =M20/M8 -> 0.12826587 | N21: =N20/N8 -> 0.12826587 | O21: =O20/O8 -> 0.12826587
D22: Interest Expense | G22: =-Inc_Stat!M26 -> 822.72 | H22: =-Inc_Stat!N26 -> 968 | I22: =-Inc_Stat!O26 -> 1650.54 | K22: =K23*K8 -> 1918.7528 | L22: =L23*L8 -> 2149.9625 | M22: =M23*M8 -> 2391.1882 | N22: =N23*N8 -> 2587.983 | O22: =O23*O8 -> 2735.7569
D23: % Margin | G23: =G22/G8 -> 0.013009492 | H23: =H22/H8 -> 0.013651465 | I23: =I22/I8 -> 0.021730461 | K23: =I23 -> 0.021730461 | L23: =K23 -> 0.021730461 | M23: =L23 -> 0.021730461 | N23: =M23 -> 0.021730461 | O23: =N23 -> 0.021730461
D24: Profit Before Taxes | G24: =G20-G22 -> 6909.14 | H24: =H20-H22 -> 8865.26 | I24: =I20-I22 -> 7131.39 | J24: =_xlfn.RRI(2,G24,I24) -> 0.015956463 | K24: =K20-K22 -> 9406.8467 | L24: =L20-L22 -> 10540.372 | M24: =M20-M22 -> 11723.001 | N24: =N20-N22 -> 12687.804 | O24: =O20-O22 -> 13412.278 | P24: =_xlfn.RRI(4,K24,O24) -> 0.092734414
D25: % Margin | G25: =G24/G8 -> 0.10925272 | H25: =H24/H8 -> 0.12502457 | I25: =I24/I8 -> 0.093889511 | K25: =K24/K8 -> 0.10653541 | L25: =L24/L8 -> 0.10653541 | M25: =M24/M8 -> 0.10653541 | N25: =N24/N8 -> 0.10653541 | O25: =O24/O8 -> 0.10653541
D26: Taxes | G26: =-Inc_Stat!M31 -> 2342.85 | H26: =-Inc_Stat!N31 -> 2418.26 | I26: =-Inc_Stat!O31 -> 1488.49 | K26: =K27*K24 -> 1963.4317 | L26: =L27*L24 -> 2200.0252 | M26: =M27*M24 -> 2446.868 | N26: =N27*N24 -> 2648.2453 | O26: =O27*O24 -> 2799.4601
D27: % Effective Tax Rate | G27: =G26/G24 -> 0.3390943 | H27: =H26/H24 -> 0.27277937 | I27: =I26/I24 -> 0.20872369 | K27: =I27 -> 0.20872369 | L27: =K27 -> 0.20872369 | M27: =L27 -> 0.20872369 | N27: =M27 -> 0.20872369 | O27: =N27 -> 0.20872369
D28: Net Profit | G28: =G24-G26 -> 4566.29 | H28: =H24-H26 -> 6447 | I28: =I24-I26 -> 5642.9 | J28: =_xlfn.RRI(2,G28,I28) -> 0.11165348 | K28: =K24-K26 -> 7443.415 | L28: =L24-L26 -> 8340.3465 | M28: =M24-M26 -> 9276.1333 | N28: =N24-N26 -> 10039.559 | O28: =O24-O26 -> 10612.818 | P28: =_xlfn.RRI(4,K28,O28) -> 0.092734414
D30: Add: Depreciation & Amortisation | G30: =G18 -> 2887.99 | H30: =H18 -> 3145.3 | I30: =I18 -> 4014.95 | K30: =K18 -> 4667.3794 | L30: =L18 -> 5229.7986 | M30: =M18 -> 5816.582 | N30: =N18 -> 6295.2867 | O30: =O18 -> 6654.7476
D31: Less: Capital Expenditure | G31: =Cash_Flow!M22 -> -6200 | H31: =Cash_Flow!N22 -> -9006 | I31: =Cash_Flow!O22 -> -9129 | K31: =I31*(1-0.125) -> -7987.875 | L31: =K31*(1-0.1) -> -7189.0875 | M31: =L31*(1-0.1) -> -6470.1788 | N31: =M31*(1-0.1) -> -5823.1609 | O31: =N31*(1+0.1) -> -6405.477
D32: Inc/Dec in Net Working Capital | G32: =NWC!F25 -> 0 | H32: =NWC!G25 -> -751 | I32: =NWC!H25 -> -2256 | K32: =NWC!I25 -> -1364.8285 | L32: =NWC!J25 -> -989.16383 | M32: =NWC!K25 -> -1032.0147 | N32: =NWC!L25 -> -841.92958 | O32: =NWC!M25 -> -632.20758
D34: Unlevered Free Cash Flow | K34: =SUM(K28:K32) -> 2758.0909 | L34: =SUM(L28:L32) -> 5391.8937 | M34: =SUM(M28:M32) -> 7590.5218 | N34: =SUM(N28:N32) -> 9669.7553 | O34: =SUM(O28:O32) -> 10229.881
D35: WACC | F35: =WACC!F26 -> 0.12048891
D36: Discount Period | K36: =IF(F6="Y",0.5,1) -> 0.5 | L36: =K36+1 -> 1.5 | M36: =L36+1 -> 2.5 | N36: =M36+1 -> 3.5 | O36: =N36+1 -> 4.5
D37: Discount Factor | K37: =1/(1+$F$35)^K36 -> 0.94470501 | L37: =1/(1+$F$35)^L36 -> 0.84311858 | M37: =1/(1+$F$35)^M36 -> 0.75245598 | N37: =1/(1+$F$35)^N36 -> 0.67154255 | O37: =1/(1+$F$35)^O36 -> 0.59932994
D38: Present Value of Free Cash Flow | K38: =K34*K37 -> 2605.5823 | L38: =L34*L37 -> 4546.0058 | M38: =M34*M37 -> 5711.5335 | N38: =N34*N37 -> 6493.6522 | O38: =O34*O37 -> 6131.0739
D41: Enterprise Value | I41: Implied Equity Value and Share Price | N41: Implied Perpetuity Growth Rate
D42: Cumulative Present Value of FCF | G42: =SUM(K38:O38) -> 25487.848 | I42: Enterprise Value | L42: =G52 -> 118218.6 | N42: Treminal Year Free Cash Flow (2030E) | Q42: =O34 -> 10229.881
I43: Less: Total Debt | L43: =-'Historical FS'!L39 -> -24102.18 | N43: WACC | Q43: =F35 -> 0.12048891
D44: Terminal Value | I44: Less: Preferred Stock | L44: 0 | N44: Terminal Value | Q44: =G47 -> 154724.05
D45: Terminal Value EBITDA (2030E) | G45: =O16 -> 22802.782 | I45: Less: Noncontrolling Interest | L45: -3187
D46: Exit Multiple | G46: 10 | I46: Plus: Cash & Cash Equivalents | L46: =Bal_Sht!O23 -> 1673.32 | N46: Implied Perpetuity Growth Rate | Q46: 0.051
D47: Terminal Value | G47: =IF(F7="Y",G45*G46,Q42*(1+Q46)/(F35-Q46)) -> 154724.05
D48: Discount Factor | G48: =O37 -> 0.59932994 | I48: Implied Equity Value | L48: =SUM(L42:L46) -> 92602.742 | N48: Implied EV/EBITDA
D49: Present Value of Terminal Value | G49: =G47*G48 -> 92730.754 | N49: Enterprise Value | Q49: =G52 -> 118218.6
D50: % of Enterprise Value | G50: =G49/G52 -> 0.7844007 | I50: Fully Diluted Shares Outstanding | L50: =Inc_Stat!O36 -> 29.47 | N50: 03/31/2025 EBITDA | Q50: =I16 -> 12796.88
D52: Enterprise Value | G52: =G42+G49 -> 118218.6 | I52: Implied Share Price | L52: =L48/L50 -> 3142.2715 | N52: Implied EV/EBITDA | Q52: =Q49/Q50 -> 9.2380801
D55: Sensitivity Analysis
D57: Enterprise Value (Perpetuity Growth Rate - Discount Factor) | L57: Enterprise Value (EBITDA Multiple - Discount Factor)
F58: Discount Fator | N58: Discount Factor
E59: =G52 -> 118218.6 | F59: 0.115 | G59: 0.12 | H59: 0.125 | I59: 0.13 | J59: 0.135 | M59: =L48 -> 92602.742 | N59: 0.115 | O59: 0.12 | P59: 0.125 | Q59: 0.13 | R59: 0.135
D60: Terminal Growth Rate | E60: 0.03 | F60: 101802.21 | G60: 95824.281 | H60: 90480.342 | I60: 85675.214 | J60: 81331.845 | L60: EBITDA Multiple | M60: 8 | N60: 103165.55 | O60: 93475.143 | P60: 85099.366 | Q60: 77788.517 | R60: 71352.349
E61: 0.04 | F61: 112765.19 | G61: 105380.26 | H61: 98869.034 | I61: 93085.817 | J61: 87915.577 | M61: 9 | N61: 103165.55 | O61: 93475.143 | P61: 85099.366 | Q61: 77788.517 | R61: 71352.349
E62: 0.05 | F62: 127101.38 | G62: 117666.51 | H62: 109494.71 | I62: 102349.07 | J62: 96048.423 | M62: 10 | N62: 103165.55 | O62: 93475.143 | P62: 85099.366 | Q62: 77788.517 | R62: 71352.349
E63: 0.06 | F63: 146650.74 | G63: 134048.18 | H63: 123389.82 | I63: 114258.97 | J63: 106350.03 | M63: 11 | N63: 103165.55 | O63: 93475.143 | P63: 85099.366 | Q63: 77788.517 | R63: 71352.349
E64: 0.07 | F64: 174888.7 | G64: 156982.52 | H64: 142337.71 | I64: 130138.83 | J64: 119821.36 | M64: 12 | N64: 103165.55 | O64: 93475.143 | P64: 85099.366 | Q64: 77788.517 | R64: 71352.349
D66: Equity Value (Perpetuity Growth Rate - Discount Factor) | L66: Equity Value (EBITDA Multiple - Discount Factor)
F67: Discount Fator | N67: Discount Factor
E68: =L48 -> 92602.742 | F68: 0.115 | G68: 0.12 | H68: 0.125 | I68: 0.13 | J68: 0.135 | M68: =L48 -> 92602.742 | N68: 0.115 | O68: 0.12 | P68: 0.125 | Q68: 0.13 | R68: 0.135
D69: Terminal Growth Rate | E69: 0.03 | F69: 76186.354 | G69: 70208.421 | H69: 64864.482 | I69: 60059.354 | J69: 55715.985 | L69: EBITDA Multiple | M69: 8 | N69: 103165.55 | O69: 93475.143 | P69: 85099.366 | Q69: 77788.517 | R69: 71352.349
E70: 0.04 | F70: 87149.327 | G70: 79764.396 | H70: 73253.174 | I70: 67469.957 | J70: 62299.717 | M70: 9 | N70: 103165.55 | O70: 93475.143 | P70: 85099.366 | Q70: 77788.517 | R70: 71352.349
E71: 0.05 | F71: 101485.52 | G71: 92050.649 | H71: 83878.85 | I71: 76733.21 | J71: 70432.563 | M71: 10 | N71: 103165.55 | O71: 93475.143 | P71: 85099.366 | Q71: 77788.517 | R71: 71352.349
E72: 0.06 | F72: 121034.88 | G72: 108432.32 | H72: 97773.964 | I72: 88643.107 | J72: 80734.168 | M72: 11 | N72: 103165.55 | O72: 93475.143 | P72: 85099.366 | Q72: 77788.517 | R72: 71352.349
E73: 0.07 | F73: 149272.84 | G73: 131366.66 | H73: 116721.85 | I73: 104522.97 | J73: 94205.497 | M73: 12 | N73: 103165.55 | O73: 93475.143 | P73: 85099.366 | Q73: 77788.517 | R73: 71352.349
D76: Implied Share Price (Perpetuity Growth Rate - Discount Factor) | L76: Implied Share Price (EBITDA Multiple - Discount Factor)
F77: Discount Fator | N77: Discount Factor
E78: =L52 -> 3142.2715 | F78: 0.115 | G78: 0.12 | H78: 0.125 | I78: 0.13 | J78: 0.135 | M78: =L52 -> 3142.2715 | N78: 0.115 | O78: 0.12 | P78: 0.125 | Q78: 0.13 | R78: 0.135
D79: Terminal Growth Rate | E79: 0.03 | F79: 2585.2173 | G79: 2382.3692 | H79: 2201.0344 | I79: 2037.9828 | J79: 1890.6001 | L79: EBITDA Multiple | M79: 8 | N79: 3500.6972 | O79: 3171.8745 | P79: 2887.6609 | Q79: 2639.5832 | R79: 2421.1859
E80: 0.04 | F80: 2957.2218 | G80: 2706.6303 | H80: 2485.6863 | I80: 2289.4454 | J80: 2114.0047 | M80: 9 | N80: 3500.6972 | O80: 3171.8745 | P80: 2887.6609 | Q80: 2639.5832 | R80: 2421.1859
E81: 0.05 | F81: 3443.6893 | G81: 3123.5375 | H81: 2846.2453 | I81: 2603.7737 | J81: 2389.975 | M81: 10 | N81: 3500.6972 | O81: 3171.8745 | P81: 2887.6609 | Q81: 2639.5832 | R81: 2421.1859
E82: 0.06 | F82: 4107.054 | G82: 3679.4137 | H82: 3317.7456 | I82: 3007.91 | J82: 2739.5374 | M82: 11 | N82: 3500.6972 | O82: 3171.8745 | P82: 2887.6609 | Q82: 2639.5832 | R82: 2421.1859
E83: 0.07 | F83: 5065.2474 | G83: 4457.6403 | H83: 3960.7006 | I83: 3546.7584 | J83: 3196.6575 | M83: 12 | N83: 3500.6972 | O83: 3171.8745 | P83: 2887.6609 | Q83: 2639.5832 | R83: 2421.1859

Sheet ValGraph
D2: UltraTech Cement Ltd (NSE: ULTRACEMCO)
D3: Valuation Graph
D4: (Figures are in ₹ Cr, except price per share)
D25: Valuation Statistics - UltraTech Cement Ltd. (Implied Share Price)
K26: Range of Multiples | N26: Implied Share Price Range
K27: Min | L27: Mean | M27: Max | N27: Min | O27: Mean | P27: Max
D28: Discounted Cash Flow Analysis
D29: 11.5% - 13.5% Discount Factor, 3.0% - 7.0% Perpetuity Growth Rate | N29: 2289.4454 | O29: 2846.2453 | P29: 3679.4137
D30: 11.5% - 13.5% Discount Factor, 8.0x - 12.0x EBITDA Multiple | N30: 3992.9819 | O30: 4540.1071 | P30: 5107.8917
D32: Public Company Comparables
D33: EV/Revenue | K33: 1.1128321 | L33: 2.8830179 | M33: 4.6330073 | N33: 2050.3268 | O33: 6612.7527 | P33: 11123.125
D34: EV/EBITDA | K34: 7.4183591 | L34: 14.385309 | M34: 19.884306 | N34: 2403.45 | O34: 5428.7373 | P34: 7816.5899
D35: P/E | K35: 1.3929526 | L35: 42.022779 | M35: 126.3254 | N35: -551.13295 | O35: 7228.6446 | P35: 23370.867
D37: 52-week high/low | N37: 10325 | O37: =AVERAGE(N37,P37) -> 11717.5 | P37: 13110
