Workbook
Name scenario: DCF!$E$17
Name tgr: DCF!$E$22
Name wacc: DCF!$E$21

Sheet Summary
B2: Walmart Inc.
B3: Summary
B4: ($ in 'Billions, except per share data and number of employees in '000)
A6: * | B6: Valuation
B8: Metrics | C8: DCF | D8: EV / Revenue | E8: EV / EBITDA | F8: P / Sales | G8: P / E | H8: 52 - wk range
B9: 75th Percentile | C9: =DCF!L191 -> 72.034035 | D9: =Comps!R30 -> 12.517437 | E9: =Comps!S30 -> 9.6120511 | F9: =Comps!T30 -> 40.537366 | G9: =Comps!U30 -> 35.648384 | H9: =Comps!D39 -> 113.56
B10: Average | C10: =DCF!L192 -> 59.842471 | D10: =Comps!R31 -> 10.633325 | E10: =Comps!S31 -> 8.1557751 | F10: =Comps!T31 -> 55.137229 | G10: =Comps!U31 -> 53.334523 | H10: =Comps!D40 -> 104.44327
B11: Median | C11: =DCF!L193 -> 53.335455 | D11: =Comps!R32 -> 6.0804137 | E11: =Comps!S32 -> 6.752042 | F11: =Comps!T32 -> 14.978242 | G11: =Comps!U32 -> 16.334053 | H11: =Comps!D41 -> 101.84
B12: 25th Percentile | C12: =DCF!L194 -> 35.884431 | D12: =Comps!R33 -> 5.6471299 | E12: =Comps!S33 -> 5.8434136 | F12: =Comps!T33 -> 6.8224205 | G12: =Comps!U33 -> 10.021673 | H12: =Comps!D42 -> 96.775
A15: * | B15: Football Chart
B17: Method | C17: Min | D17: Median | E17: Max
B18: DCF | C18: {=TRANSPOSE(C12:H12)} -> 35.884431 | D18: {=TRANSPOSE(C11:H11)} -> 53.335455 | E18: {=TRANSPOSE(C9:H9)} -> 72.034035
B19: EV / Revenue | C19: 5.6471299 | D19: 6.0804137 | E19: 12.517437
B20: EV / EBITDA | C20: 5.8434136 | D20: 6.752042 | E20: 9.6120511
B21: P / Sales | C21: 6.8224205 | D21: 14.978242 | E21: 40.537366
B22: P / E | C22: 10.021673 | D22: 16.334053 | E22: 35.648384
B23: 52 - wk range | C23: 96.775 | D23: 101.84 | E23: 113.56
A25: * | B25: End

Sheet Comps
B2: Walmart Inc.
B3: Companies Comparable
B4: ($ in 'Billions, except per share data and number of employees in '000)
A6: * | B6: Overview
B8: Name | D8: Employees | E8: Revenue | F8: EBITDA | G8: EBITDA % | H8: Net Income | I8: NI % | J8: Price / Share ($) | K8: Market Cap | L8: EV | M8: EV / Revenue | N8: EV / EBITDA | O8: P / Sales | P8: P / E
B9: Walmart | D9: 2100 | E9: 713.16 | F9: 44.03 | G9: =F9/E9 -> 0.061739301 | H9: 21.89 | I9: =H9/E9 -> 0.030694374 | J9: 119.02 | K9: 949.57 | L9: 1010
B10: Costco Wholesale Corp | D10: 341 | E10: 286.27 | F10: 13.46 | G10: =F10/E10 -> 0.047018549 | H10: 8.55 | I10: =H10/E10 -> 0.029866909 | J10: 972.33 | K10: 448.48 | L10: 439.4 | M10: =L10/E10 -> 1.5349146 | N10: =L10/F10 -> 32.644874 | O10: =J10/E10 -> 3.3965487 | P10: =J10/H10 -> 113.72281
B11: Target Corp | D11: 440 | E11: 104.78 | F11: 8.07 | G11: =F11/E11 -> 0.077018515 | H11: 3.7 | I11: =H11/E11 -> 0.035312082 | J11: 113.26 | K11: 47.76 | L11: 63.98 | M11: =L11/E11 -> 0.61061271 | N11: =L11/F11 -> 7.9281289 | O11: =J11/E11 -> 1.0809315 | P11: =J11/H11 -> 30.610811
B12: CVS Health Corp | D12: 300 | E12: 399.83 | F12: 14.63 | G12: =F12/E12 -> 0.036590551 | H12: 1.77 | I12: =H12/E12 -> 0.0044268814 | J12: 71.5 | K12: 100.87 | L12: 171.39 | M12: =L12/E12 -> 0.42865718 | N12: =L12/F12 -> 11.714969 | O12: =J12/E12 -> 0.178826 | P12: =J12/H12 -> 40.39548
B13: Loblaw Companies Limited | D13: 220 | E13: 63.9 | F13: 5.63 | G13: =F13/E13 -> 0.088106416 | H13: 2.53 | I13: =H13/E13 -> 0.039593114 | J13: 44.02 | K13: 45.56 | L13: 56.55 | M13: =L13/E13 -> 0.88497653 | N13: =L13/F13 -> 10.044405 | O13: =J13/E13 -> 0.68888889 | P13: =J13/H13 -> 17.399209
B14: Kroger Co. | D14: 409 | E14: 147.64 | F14: 7.96 | G14: =F14/E14 -> 0.053914928 | H14: 1.02 | I14: =H14/E14 -> 0.0069086968 | J14: 73.2 | K14: 39.77 | L14: 59.91 | M14: =L14/E14 -> 0.40578434 | N14: =L14/F14 -> 7.5263819 | O14: =J14/E14 -> 0.4958006 | P14: =J14/H14 -> 71.764706
B15: Tesco Plc | D15: 341 | E15: 71.18 | F15: 4.26 | G15: =F15/E15 -> 0.059848272 | H15: 1.53 | I15: =H15/E15 -> 0.021494802 | J15: 625.47 | K15: 29.8 | L15: 40.2 | M15: =L15/E15 -> 0.56476538 | N15: =L15/F15 -> 9.4366197 | O15: =J15/E15 -> 8.7871593 | P15: =J15/H15 -> 408.80392
B16: Us Foods Holding Corp | D16: 30 | E16: 39.42 | F16: 1.71 | G16: =F16/E16 -> 0.043378995 | H16: 0.676 | I16: =H16/E16 -> 0.017148656 | J16: 89.4 | K16: 16.61 | L16: 21.67 | M16: =L16/E16 -> 0.54972095 | N16: =L16/F16 -> 12.672515 | O16: =J16/E16 -> 2.2678843 | P16: =J16/H16 -> 132.24852
B17: Sysco Corporation | D17: 75 | E17: 82.65 | F17: 4.52 | G17: =F17/E17 -> 0.054688445 | H17: 1.8 | I17: =H17/E17 -> 0.021778584 | J17: 81.33 | K17: 35.29 | L17: 49.03 | M17: =L17/E17 -> 0.59322444 | N17: =L17/F17 -> 10.847345 | O17: =J17/E17 -> 0.98402904 | P17: =J17/H17 -> 45.183333
B18: O`Reilly Automotive, Inc. | D18: 95 | E18: 17.78 | F18: 3.97 | G18: =F18/E18 -> 0.22328459 | H18: 2.54 | I18: =H18/E18 -> 0.14285714 | J18: 87.3 | K18: 65.37 | L18: 72.35 | M18: =L18/E18 -> 4.0691789 | N18: =L18/F18 -> 18.224181 | O18: =J18/E18 -> 4.9100112 | P18: =J18/H18 -> 34.370079
B19: Casey`s General Stores, Inc. | D19: 23.4 | E19: 16.98 | F19: 1.39 | G19: =F19/E19 -> 0.081861013 | H19: 0.65 | I19: =H19/E19 -> 0.03828033 | J19: 659.63 | K19: 22.48 | L19: 24.91 | M19: =L19/E19 -> 1.46702 | N19: =L19/F19 -> 17.920863 | O19: =J19/E19 -> 38.847468 | P19: =J19/H19 -> 1014.8154
B21: 75th Percentile | M21: =QUARTILE(M10:M19,3) -> 1.3215091 | N21: =QUARTILE(N10:N19,3) -> 16.608776 | O21: =QUARTILE(O10:O19,3) -> 4.5316456 | P21: =QUARTILE(P10:P19,3) -> 127.61709
B22: Average | M22: =AVERAGE(M10:M19) -> 1.1108855 | N22: =AVERAGE(N10:N19) -> 13.896028 | O22: =AVERAGE(O10:O19) -> 6.1637547 | P22: =AVERAGE(P10:P19) -> 190.93143
B23: Median | M23: =MEDIAN(M10:M19) -> 0.60191858 | N23: =MEDIAN(N10:N19) -> 11.281157 | O23: =MEDIAN(O10:O19) -> 1.6744079 | P23: =MEDIAN(P10:P19) -> 58.47402
B24: 25th Percentile | M24: =QUARTILE(M10:M19,1) -> 0.55348206 | N24: =QUARTILE(N10:N19,1) -> 9.588566 | O24: =QUARTILE(O10:O19,1) -> 0.76267393 | P24: =QUARTILE(P10:P19,1) -> 35.876429
A27: * | B27: Valuation
N28: Equity Value | R28: Price Per Share
B29: Walmart Inc. | D29: Revenue | E29: EBITDA | F29: Net Income | G29: # Shares | H29: Cash | I29: Debt | J29: EV / Revenue | K29: EV / EBITDA | L29: P / Sales | M29: P / E | N29: EV / Revenue | O29: EV / EBITDA | P29: P / Sales | Q29: P / E | R29: EV / Revenue | S29: EV / EBITDA | T29: P / Sales | U29: P / E
B30: 75th Percentile | D30: 713.163 | E30: 42.798 | F30: 22.27 | G30: 7972.4025 | H30: 10.727 | I30: 44.762 | J30: =M21 -> 1.3215091 | K30: =N21 -> 16.608776 | L30: =O21 -> 4.5316456 | M30: =P21 -> 127.61709 | N30: =J30*D30+H30+I30 -> 997.94043 | O30: =K30*E30+H30+I30 -> 766.3114 | P30: =L30*D30 -> 3231.802 | Q30: =M30*F30 -> 2842.0326 | R30: =N30*100/$G30 -> 12.517437 | S30: =O30*100/$G30 -> 9.6120511 | T30: =P30*100/$G30 -> 40.537366 | U30: =Q30*100/$G30 -> 35.648384
B31: Average | D31: 713.163 | E31: 42.798 | F31: 22.27 | G31: 7972.4025 | H31: 10.727 | I31: 44.762 | J31: =M22 -> 1.1108855 | K31: =N22 -> 13.896028 | L31: =O22 -> 6.1637547 | M31: =P22 -> 190.93143 | N31: =J31*D31+H31+I31 -> 847.73144 | O31: =K31*E31+H31+I31 -> 650.21122 | P31: =L31*D31 -> 4395.7618 | Q31: =M31*F31 -> 4252.0428 | R31: =N31*100/$G31 -> 10.633325 | S31: =O31*100/$G31 -> 8.1557751 | T31: =P31*100/$G31 -> 55.137229 | U31: =Q31*100/$G31 -> 53.334523
B32: Median | D32: 713.163 | E32: 42.798 | F32: 22.27 | G32: 7972.4025 | H32: 10.727 | I32: 44.762 | J32: =M23 -> 0.60191858 | K32: =N23 -> 11.281157 | L32: =O23 -> 1.6744079 | M32: =P23 -> 58.47402 | N32: =J32*D32+H32+I32 -> 484.75506 | O32: =K32*E32+H32+I32 -> 538.29997 | P32: =L32*D32 -> 1194.1258 | Q32: =M32*F32 -> 1302.2164 | R32: =N32*100/$G32 -> 6.0804137 | S32: =O32*100/$G32 -> 6.752042 | T32: =P32*100/$G32 -> 14.978242 | U32: =Q32*100/$G32 -> 16.334053
B33: 25th Percentile | D33: 713.163 | E33: 42.798 | F33: 22.27 | G33: 7972.4025 | H33: 10.727 | I33: 44.762 | J33: =M24 -> 0.55348206 | K33: =N24 -> 9.588566 | L33: =O24 -> 0.76267393 | M33: =P24 -> 35.876429 | N33: =J33*D33+H33+I33 -> 450.21193 | O33: =K33*E33+H33+I33 -> 465.86045 | P33: =L33*D33 -> 543.91083 | Q33: =M33*F33 -> 798.96808 | R33: =N33*100/$G33 -> 5.6471299 | S33: =O33*100/$G33 -> 5.8434136 | T33: =P33*100/$G33 -> 6.8224205 | U33: =Q33*100/$G33 -> 10.021673
A36: * | B36: 52 Week Share Price
B38: Valuation
B39: 75th Percentile | D39: =QUARTILE(Input!S4:S58,3) -> 113.56
B40: Average | D40: =AVERAGE(Input!S4:S58) -> 104.44327
B41: Median | D41: =MEDIAN(Input!S4:S58) -> 101.84
B42: 25th Percentile | D42: =QUARTILE(Input!S4:S58,1) -> 96.775
A44: * | B44: End

Sheet DCF
B2: Walmart Inc.
B3: DCF Model
B4: ($ in 'Millions, except per share data)
A6: * | B6: Overview
B8: Company Name: | E8: Walmart Inc. | G8: Implied Share Price: | J8: =O185 -> 39.729146
B9: Ticker: | E9: WMT US | G9: % Delta vs Current: | J9: =J8/E11-1 -> -0.66614163
B10: Date: | E10: =TODAY() -> 46106
B11: Price Per Share: | E11: 119
A13: * | B13: Assumptions (31/12 CYE)
B15: Triggers | G15: Conservative | H15: Year | I15: Average | K15: Base/Street | L15: Year | M15: Average | O15: Optimistic | P15: Year | Q15: Average
B17: Scenario: | E17: 1 | G17: Revenue | H17: 27'-31' | I17: -0.00014529609 | K17: Revenue | L17: 27'-31' | M17: 0.045044039 | O17: Revenue | P17: 27'-31' | Q17: 0.059521416
G18: Cost of Sales | H18: 27'-31' | I18: 0.063106601 | K18: Cost of Sales | L18: 27'-31' | M18: 0.048084527 | O18: Cost of Sales | P18: 27'-31' | Q18: 0.037067888
G19: OSG&A | H19: 27'-31' | I19: 0.0088729277 | K19: OSG&A | L19: 27'-31' | M19: 0.032653214 | O19: OSG&A | P19: 27'-31' | Q19: 0.042192472
B21: WACC | E21: =CHOOSE(scenario,M21,I21,Q21) -> 0.075210832 | G21: WACC | I21: 0.082 | K21: WACC | M21: =WACC!L11 -> 0.075210832 | O21: WACC | Q21: 0.068
B22: TGR | E22: =CHOOSE(scenario,M22,I22,Q22) -> 0.02 | G22: TGR | I22: 0.015 | K22: TGR | M22: =WACC!L12 -> 0.02 | O22: TGR | Q22: 0.025
A24: * | B24: Income Statement (31/12 CYE)
J25: Historicals | O25: Projections
B26: $ 'Millions | J26: 44592 | K26: =EOMONTH(J26,12) -> 44957 | L26: =EOMONTH(K26,12) -> 45322 | M26: =EOMONTH(L26,12) -> 45688 | N26: =EOMONTH(M26,12) -> 46053 | O26: =EOMONTH(N26,12) -> 46418 | P26: =EOMONTH(O26,12) -> 46783 | Q26: =EOMONTH(P26,12) -> 47149 | R26: =EOMONTH(Q26,12) -> 47514 | S26: =EOMONTH(R26,12) -> 47879
B28: Walmart U.S. Segment
B29: Sales | J29: =Input!H38 -> 393247 | K29: =Input!I38 -> 420553 | L29: =Input!J38 -> 441817 | M29: =Input!K38 -> 462415 | N29: =Input!L38 -> 482975 | O29: =N29*(1+O30) -> 504708.87 | P29: =O29*(1+P30) -> 525906.65 | Q29: =P29*(1+Q30) -> 548520.63 | R29: =Q29*(1+R30) -> 571009.98 | S29: =R29*(1+S30) -> 595563.41
B30: % Growth | K30: =K29/J29-1 -> 0.069437275 | L30: =L29/K29-1 -> 0.050561998 | M30: =M29/L29-1 -> 0.046621112 | N30: =N29/M29-1 -> 0.044462225 | O30: =OFFSET(O30,scenario,0) -> 0.045 | P30: =OFFSET(P30,scenario,0) -> 0.042 | Q30: =OFFSET(Q30,scenario,0) -> 0.043 | R30: =OFFSET(R30,scenario,0) -> 0.041 | S30: =OFFSET(S30,scenario,0) -> 0.043
B31: 1. Base | O31: 0.045 | P31: 0.042 | Q31: 0.043 | R31: 0.041 | S31: 0.043
B32: 2. Conservative | O32: =O31-1% -> 0.035 | P32: =P31-1% -> 0.032 | Q32: =Q31-1% -> 0.033 | R32: =R31-1% -> 0.031 | S32: =S31-1% -> 0.033
B33: 3. Optimistic | O33: =O31+1% -> 0.055 | P33: =P31+1% -> 0.052 | Q33: =Q31+1% -> 0.053 | R33: =R31+1% -> 0.051 | S33: =S31+1% -> 0.053
B34: Membership | J34: =Input!H39 -> 1924.398 | K34: =Input!I39 -> 2084.7645 | L34: =Input!J39 -> 1985 | M34: =Input!K39 -> 2594 | N34: =Input!L39 -> 2624 | O34: =N34*(1+O35) -> 2676.48 | P34: =O34*(1+P35) -> 2727.3331 | Q34: =P34*(1+Q35) -> 2787.3344 | R34: =Q34*(1+R35) -> 2854.2305 | S34: =R34*(1+S35) -> 2928.4405
B35: % Growth | K35: =K34/J34-1 -> 0.083333333 | L35: =L34/K34-1 -> -0.047854069 | M35: =M34/L34-1 -> 0.30680101 | N35: =N34/M34-1 -> 0.01156515 | O35: =OFFSET(O35,scenario,0) -> 0.02 | P35: =OFFSET(P35,scenario,0) -> 0.019 | Q35: =OFFSET(Q35,scenario,0) -> 0.022 | R35: =OFFSET(R35,scenario,0) -> 0.024 | S35: =OFFSET(S35,scenario,0) -> 0.026
B36: 1. Base | O36: 0.02 | P36: 0.019 | Q36: 0.022 | R36: 0.024 | S36: 0.026
B37: 2. Conservative | O37: =O36-1% -> 0.01 | P37: =P36-1% -> 0.009 | Q37: =Q36-1% -> 0.012 | R37: =R36-1% -> 0.014 | S37: =S36-1% -> 0.016
B38: 3. Optimistic | O38: =O36+1% -> 0.03 | P38: =P36+1% -> 0.029 | Q38: =Q36+1% -> 0.032 | R38: =R36+1% -> 0.034 | S38: =S36+1% -> 0.036
B39: Total Revenue | J39: =Input!H40 -> 395171.4 | K39: =Input!I40 -> 422637.76 | L39: =Input!J40 -> 443802 | M39: =Input!K40 -> 465009 | N39: =Input!L40 -> 485599 | O39: =O29+O34 -> 507385.35 | P39: =P29+P34 -> 528633.98 | Q39: =Q29+Q34 -> 551307.97 | R39: =R29+R34 -> 573864.21 | S39: =S29+S34 -> 598491.85
B41: Cost of Sales | J41: =Input!H42 -> 281957.5 | K41: =Input!I42 -> 304777.66 | L41: =Input!J42 -> 323563 | M41: =Input!K42 -> 336451 | N41: =Input!L42 -> 350360 | O41: =N41*(1+O42) -> 365425.48 | P41: =O41*(1+P42) -> 380407.92 | Q41: =P41*(1+Q42) -> 396385.06 | R41: =Q41*(1+R42) -> 413826 | S41: =R41*(1+S42) -> 431620.52
B42: % Growth | K42: =K41/J41-1 -> 0.080934732 | L42: =L41/K41-1 -> 0.061636227 | M42: =M41/L41-1 -> 0.039831501 | N42: =N41/M41-1 -> 0.041340344 | O42: =OFFSET(O42,scenario,0) -> 0.043 | P42: =OFFSET(P42,scenario,0) -> 0.041 | Q42: =OFFSET(Q42,scenario,0) -> 0.042 | R42: =OFFSET(R42,scenario,0) -> 0.044 | S42: =OFFSET(S42,scenario,0) -> 0.043
B43: 1. Base | O43: 0.043 | P43: 0.041 | Q43: 0.042 | R43: 0.044 | S43: 0.043
B44: 2. Conservative | O44: =O43-1% -> 0.033 | P44: =P43-1% -> 0.031 | Q44: =Q43-1% -> 0.032 | R44: =R43-1% -> 0.034 | S44: =S43-1% -> 0.033
B45: 3. Optimistic | O45: =O43+1% -> 0.053 | P45: =P43+1% -> 0.051 | Q45: =Q43+1% -> 0.052 | R45: =R43+1% -> 0.054 | S45: =S43+1% -> 0.053
B46: Operating, selling, general and administrative expenses | J46: =Input!H43 -> 88005.534 | K46: =Input!I43 -> 94973.548 | L46: =Input!J43 -> 98085 | M46: =Input!K43 -> 104676 | N46: =Input!L43 -> 110081 | O46: =N46*(1+O47) -> 112282.62 | P46: =O46*(1+P47) -> 114303.71 | Q46: =P46*(1+Q47) -> 116132.57 | R46: =Q46*(1+R47) -> 117758.42 | S46: =R46*(1+S47) -> 119171.52
B47: % Growth | K47: =K46/J46-1 -> 0.079176994 | L47: =L46/K46-1 -> 0.03276125 | M47: =M46/L46-1 -> 0.067196819 | N47: =N46/M46-1 -> 0.051635523 | O47: =OFFSET(O47,scenario,0) -> 0.02 | P47: =OFFSET(P47,scenario,0) -> 0.018 | Q47: =OFFSET(Q47,scenario,0) -> 0.016 | R47: =OFFSET(R47,scenario,0) -> 0.014 | S47: =OFFSET(S47,scenario,0) -> 0.012
B48: 1. Base | O48: 0.02 | P48: 0.018 | Q48: 0.016 | R48: 0.014 | S48: 0.012
B49: 2. Conservative | O49: =O48-1% -> 0.01 | P49: =P48-1% -> 0.008 | Q49: =Q48-1% -> 0.006 | R49: =R48-1% -> 0.004 | S49: =S48-1% -> 0.002
B50: 3. Optimistic | O50: =O48+1% -> 0.03 | P50: =P48+1% -> 0.028 | Q50: =Q48+1% -> 0.026 | R50: =R48+1% -> 0.024 | S50: =S48+1% -> 0.022
B51: Operating Income | J51: =Input!H44 -> 25208.363 | K51: =Input!I44 -> 22886.561 | L51: =Input!J44 -> 22154 | M51: =Input!K44 -> 23882 | N51: =Input!L44 -> 25158 | O51: =O39-O41-O46 -> 29677.255 | P51: =P39-P41-P46 -> 33922.349 | Q51: =Q39-Q41-Q46 -> 38790.344 | R51: =R39-R41-R46 -> 42279.788 | S51: =S39-S41-S46 -> 47699.808
B53: Walmart International
B54: Sales | J54: =Input!H47 -> 100959 | K54: =Input!I47 -> 100983 | L54: =Input!J47 -> 114641 | M54: =Input!K47 -> 121885 | N54: =Input!L47 -> 130423 | O54: =N54*(1+O55) -> 140074.3 | P54: =O54*(1+P55) -> 150579.87 | Q54: =P54*(1+Q55) -> 161572.21 | R54: =Q54*(1+R55) -> 173528.55 | S54: =R54*(1+S55) -> 185849.08
B55: % Growth | K55: =K54/J54-1 -> 0.00023772026 | L55: =L54/K54-1 -> 0.13525049 | M55: =M54/L54-1 -> 0.063188563 | N55: =N54/M54-1 -> 0.070049637 | O55: =OFFSET(O55,scenario,0) -> 0.074 | P55: =OFFSET(P55,scenario,0) -> 0.075 | Q55: =OFFSET(Q55,scenario,0) -> 0.073 | R55: =OFFSET(R55,scenario,0) -> 0.074 | S55: =OFFSET(S55,scenario,0) -> 0.071
B56: 1. Base | O56: 0.074 | P56: 0.075 | Q56: 0.073 | R56: 0.074 | S56: 0.071
B57: 2. Conservative | O57: =O56-1% -> 0.064 | P57: =P56-1% -> 0.065 | Q57: =Q56-1% -> 0.063 | R57: =R56-1% -> 0.064 | S57: =S56-1% -> 0.061
B58: 3. Optimistic | O58: =O56+1% -> 0.084 | P58: =P56+1% -> 0.085 | Q58: =Q56+1% -> 0.083 | R58: =R56+1% -> 0.084 | S58: =S56+1% -> 0.081
B59: Membership | J59: =Input!H48 -> 1189.1566 | K59: =Input!I48 -> 1288.253 | L59: =Input!J48 -> 1408 | M59: =Input!K48 -> 1478 | N59: =Input!L48 -> 1565 | O59: =N59*(1+O60) -> 1662.03 | P59: =O59*(1+P60) -> 1763.4138 | Q59: =P59*(1+Q60) -> 1876.2723 | R59: =Q59*(1+R60) -> 2000.1063 | S59: =R59*(1+S60) -> 2126.113
B60: % Growth | K60: =K59/J59-1 -> 0.083333333 | L60: =L59/K59-1 -> 0.092952983 | M60: =M59/L59-1 -> 0.049715909 | N60: =N59/M59-1 -> 0.058863329 | O60: =OFFSET(O60,scenario,0) -> 0.062 | P60: =OFFSET(P60,scenario,0) -> 0.061 | Q60: =OFFSET(Q60,scenario,0) -> 0.064 | R60: =OFFSET(R60,scenario,0) -> 0.066 | S60: =OFFSET(S60,scenario,0) -> 0.063
B61: 1. Base | O61: 0.062 | P61: 0.061 | Q61: 0.064 | R61: 0.066 | S61: 0.063
B62: 2. Conservative | O62: =O61-1% -> 0.052 | P62: =P61-1% -> 0.051 | Q62: =Q61-1% -> 0.054 | R62: =R61-1% -> 0.056 | S62: =S61-1% -> 0.053
B63: 3. Optimistic | O63: =O61+1% -> 0.072 | P63: =P61+1% -> 0.071 | Q63: =Q61+1% -> 0.074 | R63: =R61+1% -> 0.076 | S63: =S61+1% -> 0.073
B64: Total Revenue | J64: =Input!H49 -> 102148.16 | K64: =Input!I49 -> 102271.25 | L64: =Input!J49 -> 116049 | M64: =Input!K49 -> 123363 | N64: =Input!L49 -> 131988 | O64: =O54+O59 -> 141736.33 | P64: =P54+P59 -> 152343.29 | Q64: =Q54+Q59 -> 163448.48 | R64: =R54+R59 -> 175528.65 | S64: =S54+S59 -> 187975.19
B66: Cost of Sales | J66: =Input!H51 -> 80279.027 | K66: =Input!I51 -> 86776.389 | L66: =Input!J51 -> 89831 | M66: =Input!K51 -> 95267 | N66: =Input!L51 -> 102576 | O66: =N66*(1+O67) -> 110679.5 | P66: =O66*(1+P67) -> 119201.83 | Q66: =P66*(1+Q67) -> 128857.17 | R66: =Q66*(1+R67) -> 138650.32 | S66: =R66*(1+S67) -> 148771.79
B67: % Growth | K67: =K66/J66-1 -> 0.080934732 | L67: =L66/K66-1 -> 0.035200947 | M67: =M66/L66-1 -> 0.060513631 | N67: =N66/M66-1 -> 0.076721215 | O67: =OFFSET(O67,scenario,0) -> 0.079 | P67: =OFFSET(P67,scenario,0) -> 0.077 | Q67: =OFFSET(Q67,scenario,0) -> 0.081 | R67: =OFFSET(R67,scenario,0) -> 0.076 | S67: =OFFSET(S67,scenario,0) -> 0.073
B68: 1. Base | O68: 0.079 | P68: 0.077 | Q68: 0.081 | R68: 0.076 | S68: 0.073
B69: 2. Conservative | O69: =O68-1% -> 0.069 | P69: =P68-1% -> 0.067 | Q69: =Q68-1% -> 0.071 | R69: =R68-1% -> 0.066 | S69: =S68-1% -> 0.063
B70: 3. Optimistic | O70: =O68+1% -> 0.089 | P70: =P68+1% -> 0.087 | Q70: =Q68+1% -> 0.091 | R70: =R68+1% -> 0.086 | S70: =S68+1% -> 0.083
B71: Operating, selling, general and administrative expenses | J71: =Input!H52 -> 19188.988 | K71: =Input!I52 -> 20708.315 | L71: =Input!J52 -> 21309 | M71: =Input!K52 -> 22595 | N71: =Input!L52 -> 24309 | O71: =N71*(1+O72) -> 26205.102 | P71: =O71*(1+P72) -> 28275.305 | Q71: =P71*(1+Q72) -> 30452.504 | R71: =Q71*(1+R72) -> 32736.441 | S71: =R71*(1+S72) -> 35093.465
B72: % Growth | K72: =K71/J71-1 -> 0.079176994 | L72: =L71/K71-1 -> 0.029006957 | M72: =M71/L71-1 -> 0.060350087 | N72: =N71/M71-1 -> 0.075857491 | O72: =OFFSET(O72,scenario,0) -> 0.078 | P72: =OFFSET(P72,scenario,0) -> 0.079 | Q72: =OFFSET(Q72,scenario,0) -> 0.077 | R72: =OFFSET(R72,scenario,0) -> 0.075 | S72: =OFFSET(S72,scenario,0) -> 0.072
B73: 1. Base | O73: 0.078 | P73: 0.079 | Q73: 0.077 | R73: 0.075 | S73: 0.072
B74: 2. Conservative | O74: =O73-1% -> 0.068 | P74: =P73-1% -> 0.069 | Q74: =Q73-1% -> 0.067 | R74: =R73-1% -> 0.065 | S74: =S73-1% -> 0.062
B75: 3. Optimistic | O75: =O73+1% -> 0.088 | P75: =P73+1% -> 0.089 | Q75: =Q73+1% -> 0.087 | R75: =R73+1% -> 0.085 | S75: =S73+1% -> 0.082
B76: Operating Income | J76: =Input!H53 -> 2680.1409 | K76: =Input!I53 -> -5213.4507 | L76: =Input!J53 -> 4909 | M76: =Input!K53 -> 5501 | N76: =Input!L53 -> 5103 | O76: =O64-O66-O71 -> 4851.726 | P76: =P64-P66-P71 -> 4866.1576 | Q76: =Q64-Q66-Q71 -> 4138.8006 | R76: =R64-R66-R71 -> 4141.8948 | S76: =S64-S66-S71 -> 4109.9314
B78: Sam's Club U.S. Segment
B79: Sales | J79: =Input!H56 -> 73556 | K79: =Input!I56 -> 84345 | L79: =Input!J56 -> 86179 | M79: =Input!K56 -> 90238 | N79: =Input!L56 -> 93015 | O79: =N79*(1+O80) -> 96270.525 | P79: =O79*(1+P80) -> 99543.723 | Q79: =P79*(1+Q80) -> 102629.58 | R79: =Q79*(1+R80) -> 106324.24 | S79: =R79*(1+S80) -> 110364.56
B80: % Growth | K80: =K79/J79-1 -> 0.14667736 | L80: =L79/K79-1 -> 0.021744028 | M80: =M79/L79-1 -> 0.047099641 | N80: =N79/M79-1 -> 0.030774175 | O80: =OFFSET(O80,scenario,0) -> 0.035 | P80: =OFFSET(P80,scenario,0) -> 0.034 | Q80: =OFFSET(Q80,scenario,0) -> 0.031 | R80: =OFFSET(R80,scenario,0) -> 0.036 | S80: =OFFSET(S80,scenario,0) -> 0.038
B81: 1. Base | O81: 0.035 | P81: 0.034 | Q81: 0.031 | R81: 0.036 | S81: 0.038
B82: 2. Conservative | O82: 0.025 | P82: 0.024 | Q82: 0.021 | R82: 0.026 | S82: 0.028
B83: 3. Optimistic | O83: 0.045 | P83: 0.044 | Q83: 0.041 | R83: 0.046 | S83: 0.048
B84: Membership | J84: =Input!H57 -> 1843.1794 | K84: =Input!I57 -> 1996.7777 | L84: =Input!J57 -> 2051 | M84: =Input!K57 -> 2323 | N84: =Input!L57 -> 2525 | O84: =N84*(1+O85) -> 2737.1 | P84: =O84*(1+P85) -> 2958.8051 | Q84: =P84*(1+Q85) -> 3198.4683 | R84: =Q84*(1+R85) -> 3463.9412 | S84: =R84*(1+S85) -> 3761.8401
B85: % Growth | K85: =K84/J84-1 -> 0.083333333 | L85: =L84/K84-1 -> 0.027154882 | M85: =M84/L84-1 -> 0.13261824 | N85: =N84/M84-1 -> 0.086956522 | O85: =OFFSET(O85,scenario,0) -> 0.084 | P85: =OFFSET(P85,scenario,0) -> 0.081 | Q85: =OFFSET(Q85,scenario,0) -> 0.081 | R85: =OFFSET(R85,scenario,0) -> 0.083 | S85: =OFFSET(S85,scenario,0) -> 0.086
B86: 1. Base | O86: 0.084 | P86: 0.081 | Q86: 0.081 | R86: 0.083 | S86: 0.086
B87: 2. Conservative | O87: 0.074 | P87: 0.071 | Q87: 0.071 | R87: 0.073 | S87: 0.076
B88: 3. Optimistic | O88: 0.094 | P88: 0.091 | Q88: 0.091 | R88: 0.093 | S88: 0.096
B89: Total Revenue | J89: =Input!H58 -> 75399.179 | K89: =Input!I58 -> 86341.778 | L89: =Input!J58 -> 88230 | M89: =Input!K58 -> 92561 | N89: =Input!L58 -> 95540 | O89: =O79+O84 -> 99007.625 | P89: =P79+P84 -> 102502.53 | Q89: =Q79+Q84 -> 105828.05 | R89: =R79+R84 -> 109788.18 | S89: =S79+S84 -> 114126.4
B91: Cost of Sales | J91: =Input!H60 -> 66763.472 | K91: =Input!I60 -> 72166.956 | L91: =Input!J60 -> 76748 | M91: =Input!K60 -> 80035 | N91: =Input!L60 -> 82459 | O91: =N91*(1+O92) -> 85097.688 | P91: =O91*(1+P92) -> 87735.716 | Q91: =P91*(1+Q92) -> 90630.995 | R91: =Q91*(1+R92) -> 93712.449 | S91: =R91*(1+S92) -> 96711.247
B92: % Growth | K92: =K91/J91-1 -> 0.080934732 | L92: =L91/K91-1 -> 0.063478418 | M92: =M91/L91-1 -> 0.042828478 | N92: =N91/M91-1 -> 0.03028675 | O92: =OFFSET(O92,scenario,0) -> 0.032 | P92: =OFFSET(P92,scenario,0) -> 0.031 | Q92: =OFFSET(Q92,scenario,0) -> 0.033 | R92: =OFFSET(R92,scenario,0) -> 0.034 | S92: =OFFSET(S92,scenario,0) -> 0.032
B93: 1. Base | O93: 0.032 | P93: 0.031 | Q93: 0.033 | R93: 0.034 | S93: 0.032
B94: 2. Conservative | O94: 0.042 | P94: 0.041 | Q94: 0.043 | R94: 0.044 | S94: 0.042
B95: 3. Optimistic | O95: 0.022 | P95: 0.021 | Q95: 0.023 | R95: 0.024 | S95: 0.022
B96: Operating, selling, general and administrative expenses | J96: =Input!H61 -> 8453.6421 | K96: =Input!I61 -> 9122.9761 | L96: =Input!J61 -> 9290 | M96: =Input!K61 -> 10122 | N96: =Input!L61 -> 10639 | O96: =N96*(1+O97) -> 11202.867 | P96: =O96*(1+P97) -> 11785.416 | Q96: =P96*(1+Q97) -> 12421.829 | R96: =Q96*(1+R97) -> 13105.029 | S96: =R96*(1+S97) -> 13786.491
B97: % Growth | K97: =K96/J96-1 -> 0.079176994 | L97: =L96/K96-1 -> 0.018308051 | M97: =M96/L96-1 -> 0.089558665 | N97: =N96/M96-1 -> 0.051076862 | O97: =OFFSET(O97,scenario,0) -> 0.053 | P97: =OFFSET(P97,scenario,0) -> 0.052 | Q97: =OFFSET(Q97,scenario,0) -> 0.054 | R97: =OFFSET(R97,scenario,0) -> 0.055 | S97: =OFFSET(S97,scenario,0) -> 0.052
B98: 1. Base | O98: 0.053 | P98: 0.052 | Q98: 0.054 | R98: 0.055 | S98: 0.052
B99: 2. Conservative | O99: 0.063 | P99: 0.062 | Q99: 0.064 | R99: 0.065 | S99: 0.062
B100: 3. Optimistic | O100: 0.043 | P100: 0.042 | Q100: 0.044 | R100: 0.045 | S100: 0.042
B101: Operating Income | J101: =Input!H62 -> 182.06525 | K101: =Input!I62 -> 5051.8458 | L101: =Input!J62 -> 2192 | M101: =Input!K62 -> 2404 | N101: =Input!L62 -> 2442 | O101: =O89-O91-O96 -> 2707.07 | P101: =P89-P91-P96 -> 2981.3955 | Q101: =Q89-Q91-Q96 -> 2775.2231 | R101: =R89-R91-R96 -> 2970.7063 | S101: =S89-S91-S96 -> 3628.6666
B103: Corporate and support
B104: Membership and Other Income | J104: =Input!H65 -> 0 | K104: =Input!I65 -> 0 | L104: =Input!J65 -> 44 | M104: =Input!K65 -> 52 | N104: =Input!L65 -> 36 | O104: =N104*(1+O105) -> 39.6 | P104: =O104*(1+P105) -> 43.2432 | Q104: =P104*(1+Q105) -> 46.918872 | R104: =Q104*(1+R105) -> 50.76622 | S104: =R104*(1+S105) -> 55.284413
B105: % Growth | M105: =M104/L104-1 -> 0.18181818 | N105: =N104/M104-1 -> -0.30769231 | O105: =OFFSET(O105,scenario,0) -> 0.1 | P105: =OFFSET(P105,scenario,0) -> 0.092 | Q105: =OFFSET(Q105,scenario,0) -> 0.085 | R105: =OFFSET(R105,scenario,0) -> 0.082 | S105: =OFFSET(S105,scenario,0) -> 0.089
B106: 1. Base | O106: 0.1 | P106: 0.092 | Q106: 0.085 | R106: 0.082 | S106: 0.089
B107: 2. Conservative | O107: 0.11 | P107: 0.102 | Q107: 0.095 | R107: 0.092 | S107: 0.099
B108: 3. Optimistic | O108: 0.09 | P108: 0.082 | Q108: 0.075 | R108: 0.072 | S108: 0.079
B109: Operating, selling, general and administrative expenses | J109: =Input!H66 -> -1662 | K109: =Input!I66 -> -5121 | L109: =Input!J66 -> 2287 | M109: =Input!K66 -> 2491 | N109: =Input!L66 -> 2914 | O109: =N109*(1+O110) -> 3354.014 | P109: =O109*(1+P110) -> 3850.4081 | Q109: =P109*(1+Q110) -> 4397.166 | R109: =Q109*(1+R110) -> 5003.9749 | S109: =R109*(1+S110) -> 5674.5076
B110: % Growth | K110: =K109/J109-1 -> 2.0812274 | L110: =L109/K109-1 -> -1.4465925 | M110: =M109/L109-1 -> 0.089199825 | N110: =N109/M109-1 -> 0.16981132 | O110: =OFFSET(O110,scenario,0) -> 0.151 | P110: =OFFSET(P110,scenario,0) -> 0.148 | Q110: =OFFSET(Q110,scenario,0) -> 0.142 | R110: =OFFSET(R110,scenario,0) -> 0.138 | S110: =OFFSET(S110,scenario,0) -> 0.134
B111: 1. Base | O111: 0.151 | P111: 0.148 | Q111: 0.142 | R111: 0.138 | S111: 0.134
B112: 2. Conservative | O112: 0.161 | P112: 0.158 | Q112: 0.152 | R112: 0.148 | S112: 0.144
B113: 3. Optimistic | O113: 0.141 | P113: 0.138 | Q113: 0.132 | R113: 0.128 | S113: 0.124
B114: Operating Income | J114: =Input!H67 -> 1662 | K114: =Input!I67 -> 5121 | L114: =Input!J67 -> -2243 | M114: =Input!K67 -> -2439 | N114: =Input!L67 -> -2878 | O114: =O104-O109 -> -3314.414 | P114: =P104-P109 -> -3807.1649 | Q114: =Q104-Q109 -> -4350.2471 | R114: =R104-R109 -> -4953.2087 | S114: =S104-S109 -> -5619.2232
B116: Consolidated
...

Sheet WACC
A3: * | B3: Weighted Average Cost of Capital
B5: Cost of Equity | I5: Capital Structure
I6: Market Cap | L6: 949566
B7: Risk Free Rate | E7: 0.04392 | F7: US 10-Year Treasury Yield | I7: Total Debt | L7: 44762
B8: Equity Risk Premium | E8: 0.0446 | F8: Aswath Damodharan | I8: Total | L8: =SUM(L6:L7) -> 994328
B9: Country Risk Premium | E9: 0.0023 | F9: Aswath Damodharan
B10: Beta | E10: =Input!AB22 -> 0.6905058 | F10: Regression
B11: Cost of Equity | E11: =E7+(E8*E10)+E9 -> 0.077016559 | I11: WACC | L11: =(E25*(L7/L8))+(E11*(L6/L8)) -> 0.075210832
I12: Terminal Growth Rate | L12: 0.02 | M12: (1%-3%) Google
B14: Cost of Debt
B15: Using YTM Approach
B17: CMP | E17: 111.431 | F17: Investing.com
B18: Face Value | E18: 100
B19: Maturity Year | E19: 50510
B20: Total Years | E20: =YEARFRAC(TODAY(),E19,1) -> 12.05813
B21: Coupon Rate | E21: 0.062 | F21: Investing.com
B22: YTM | E22: =RATE(E20,(E18*E21),-E17,E18) -> 0.049206348
B24: Tax Rate | E24: 0.25
B25: Post Tax Cost of Debt | E25: =E22*(1-E24) -> 0.036904761
A27: * | B27: End

Sheet Data->

Sheet Input
B2: Income Statement
B3: (Amounts in millions, except per share data) | H3: 2022 | I3: 2023 | J3: 2024 | K3: 2025 | L3: 2026 | R3: Date | S3: Price | V3: Date | W3: Price | AA3: SUMMARY OUTPUT
B4: Revenues: | R4: 46096 | S4: 119.02 | V4: 46096 | W4: 21616.7
B5: Net sales | H5: 567762 | I5: 605881 | J5: 642637 | K5: 674538 | L5: 706413 | R5: 46089 | S5: 126.52 | T5: =S4/S5-1 -> -0.059279165 | V5: 46089 | W5: 22050.9 | X5: =W4/W5-1 -> -0.019690806 | AA5: Regression Statistics
B6: Membership and other income | H6: 4992 | I6: 5408 | J6: 5488 | K6: 6447 | L6: 6750 | R6: 46082 | S6: 123.8 | T6: =S5/S6-1 -> 0.021970921 | V6: 46082 | W6: 22518.1 | X6: =W5/W6-1 -> -0.020747754 | AA6: Multiple R | AB6: 0.45516506
B7: Total revenues | H7: 572754 | I7: 611289 | J7: 648125 | K7: 680985 | L7: 713163 | R7: 46075 | S7: 127.95 | T7: =S6/S7-1 -> -0.032434545 | V7: 46075 | W7: 23494.4 | X7: =W6/W7-1 -> -0.041554583 | AA7: R Square | AB7: 0.20717523
B8: Costs and expenses: | R8: 46068 | S8: 122.99 | T8: =S7/S8-1 -> 0.040328482 | V8: 46068 | W8: 23452.6 | X8: =W7/W8-1 -> 0.0017823184 | AA8: Adjusted R Square | AB8: 0.20422793
B9: Cost of sales | H9: 429000 | I9: 463721 | J9: 490142 | K9: 511753 | L9: 535395 | R9: 46061 | S9: 133.89 | T9: =S8/S9-1 -> -0.081410113 | V9: 46061 | W9: 23326.1 | X9: =W8/W9-1 -> 0.0054231097 | AA9: Standard Error | AB9: 0.02743684
B10: Operating, selling, general and administrative expenses | H10: 117812 | I10: 127140 | J10: 130971 | K10: 139884 | L10: 147943 | R10: 46054 | S10: 131.18 | T10: =S9/S10-1 -> 0.020658637 | V10: 46054 | W10: 23252.8 | X10: =W9/W10-1 -> 0.0031523085 | AA10: Observations | AB10: 271
B11: Operating income | H11: 25942 | I11: 20428 | J11: 27012 | K11: 29348 | L11: 29825 | R11: 46047 | S11: 119.14 | T11: =S10/S11-1 -> 0.10105758 | V11: 46047 | W11: 22719.3 | X11: =W10/W11-1 -> 0.023482238
B12: Interest: | R12: 46040 | S12: 117.73 | T12: =S11/S12-1 -> 0.011976557 | V12: 46040 | W12: 22757.2 | X12: =W11/W12-1 -> -0.001665407 | AA12: ANOVA
B13: Debt | H13: 1674 | I13: 1787 | J13: 2259 | K13: 2249 | L13: 2318 | R13: 46033 | S13: 119.7 | T13: =S12/S13-1 -> -0.016457811 | V13: 46033 | W13: 22807.1 | X13: =W12/W13-1 -> -0.0021879152 | AB13: df | AC13: SS | AD13: MS | AE13: F | AF13: Significance F
B14: Finance lease | H14: 320 | I14: 341 | J14: 424 | K14: 479 | L14: 481 | R14: 46026 | S14: 114.53 | T14: =S13/S14-1 -> 0.045141011 | V14: 46026 | W14: 22591.7 | X14: =W13/W14-1 -> 0.0095344751 | AA14: Regression | AB14: 1 | AC14: 0.05291528 | AD14: 0.05291528 | AE14: 70.293133 | AF14: 2.8966402e-15
B15: Interest income | H15: -158 | I15: -254 | J15: -546 | K15: -483 | L15: -368 | R15: 46019 | S15: 112.76 | T15: =S14/S15-1 -> 0.015697056 | V15: 46019 | W15: 22233.8 | X15: =W14/W15-1 -> 0.016097113 | AA15: Residual | AB15: 269 | AC15: 0.20249788 | AD15: 0.00075278021
B16: Interest, net | H16: 1836 | I16: 1874 | J16: 2137 | K16: 2245 | L16: 2431 | R16: 46012 | S16: 111.74 | T16: =S15/S16-1 -> 0.0091283336 | V16: 46012 | W16: 22246.6 | X16: =W15/W16-1 -> -0.00057536882 | AA16: Total | AB16: 270 | AC16: 0.25541316
B17: Loss on extinguishment of debt | H17: 2410 | I17: — | J17: — | K17: — | L17: — | R17: 46005 | S17: 114.36 | T17: =S16/S17-1 -> -0.022910108 | V17: 46005 | W17: 21923.9 | X17: =W16/W17-1 -> 0.014719097
B18: Other (gains) and losses | H18: 3000 | I18: 1538 | J18: 3027 | K18: 794 | L18: -2075 | R18: 45998 | S18: 116.7 | T18: =S17/S18-1 -> -0.020051414 | V18: 45998 | W18: 22004.3 | X18: =W17/W18-1 -> -0.0036538313 | AB18: Coefficients | AC18: Standard Error | AD18: t Stat | AE18: P-value | AF18: Lower 95% | AG18: Upper 95% | AH18: Lower 95.0% | AI18: Upper 95.0%
B19: Income before income taxes | H19: 18696 | I19: 17016 | J19: 21848 | K19: 26309 | L19: 29469 | R19: 45991 | S19: 115.11 | T19: =S18/S19-1 -> 0.013812875 | V19: 45991 | W19: 21810.1 | X19: =W18/W19-1 -> 0.0089041316 | AA19: Intercept | AB19: 0.0026901003 | AC19: 0.0016716337 | AD19: 1.6092643 | AE19: 0.10873147 | AF19: -0.00060104879 | AG19: 0.0059812495 | AH19: -0.00060104879 | AI19: 0.0059812495
B20: Provision for income taxes | H20: 4756 | I20: 5724 | J20: 5578 | K20: 6152 | L20: 7199 | R20: 45984 | S20: 110.51 | T20: =S19/S20-1 -> 0.041625192 | V20: 45984 | W20: 21824.7 | X20: =W19/W20-1 -> -0.00066896681 | AA20: X Variable 1 | AB20: 0.6905058 | AC20: 0.082358965 | AD20: 8.3841 | AE20: 2.8966402e-15 | AF20: 0.52835566 | AG20: 0.85265594 | AH20: 0.52835566 | AI20: 0.85265594
B21: Consolidated net income | H21: 13940 | I21: 11292 | J21: 16270 | K21: 20157 | L21: 22270 | R21: 45977 | S21: 105.32 | T21: =S20/S21-1 -> 0.04927839 | V21: 45977 | W21: 21177 | X21: =W20/W21-1 -> 0.030585069
B22: Consolidated net income attributable to noncontrolling interest | H22: -267 | I22: 388 | J22: -759 | K22: -721 | L22: -377 | R22: 45970 | S22: 102.48 | T22: =S21/S22-1 -> 0.027712724 | V22: 45970 | W22: 21470.3 | X22: =W21/W22-1 -> -0.013660731 | AA22: Beta | AB22: 0.6905058
B23: Consolidated net income attributable to Walmart | H23: 13673 | I23: 11680 | J23: 15511 | K23: 19436 | L23: 21893 | R23: 45963 | S23: 102.59 | T23: =S22/S23-1 -> -0.0010722293 | V23: 45963 | W23: 21408.6 | X23: =W22/W23-1 -> 0.0028820194
R24: 45956 | S24: 101.18 | T24: =S23/S24-1 -> 0.01393556 | V24: 45956 | W24: 21459.6 | X24: =W23/W24-1 -> -0.0023765587
B25: Net income per common share: | R25: 45949 | S25: 106.17 | T25: =S24/S25-1 -> -0.047000094 | V25: 45949 | W25: 21698.1 | X25: =W24/W25-1 -> -0.010991746
B26: Basic net income per common share attributable to Walmart | H26: 4.9 | I26: 4.29 | J26: 1.92 | K26: 2.42 | L26: 2.74 | R26: 45942 | S26: 107.73 | T26: =S25/S26-1 -> -0.014480646 | V26: 45942 | W26: 21411.4 | X26: =W25/W26-1 -> 0.013390063
B27: Diluted net income per common share attributable to Walmart | H27: 4.87 | I27: 4.27 | J27: 1.91 | K27: 2.41 | L27: 2.73 | R27: 45935 | S27: 101.84 | T27: =S26/S27-1 -> 0.057835821 | V27: 45935 | W27: 21096.9 | X27: =W26/W27-1 -> 0.014907403
R28: 45928 | S28: 102.07 | T28: =S27/S28-1 -> -0.0022533555 | V28: 45928 | W28: 21725.4 | X28: =W27/W28-1 -> -0.028929272
B29: Weighted-average common shares outstanding: | R29: 45921 | S29: 103.16 | T29: =S28/S29-1 -> -0.010566111 | V29: 45921 | W29: 21477.5 | X29: =W28/W29-1 -> 0.011542312
B30: Basic | H30: 2792 | I30: 2724 | J30: 8077 | K30: 8041 | L30: 7983 | R30: 45914 | S30: 102.33 | T30: =S29/S30-1 -> 0.0081110134 | V30: 45914 | W30: 21494 | X30: =W29/W30-1 -> -0.00076765609
B31: Diluted | H31: 2805 | I31: 2734 | J31: 8108 | K31: 8081 | L31: 8022 | R31: 45907 | S31: 103.49 | T31: =S30/S31-1 -> -0.011208812 | V31: 45907 | W31: 21374.3 | X31: =W30/W31-1 -> 0.0056001834
R32: 45900 | S32: 100.51 | T32: =S31/S32-1 -> 0.029648791 | V32: 45900 | W32: 21136 | X32: =W31/W32-1 -> 0.011274603
B33: Dividends declared per common share | H33: 2.2 | I33: 2.24 | J33: 0.76 | K33: 0.83 | L33: 0.94 | R33: 45893 | S33: 96.98 | T33: =S32/S33-1 -> 0.036399258 | V33: 45893 | W33: 21151.5 | X33: =W32/W33-1 -> -0.00073280855
R34: 45886 | S34: 96.83 | T34: =S33/S34-1 -> 0.0015491067 | V34: 45886 | W34: 21150.1 | X34: =W33/W34-1 -> 6.619354e-05
B35: Revenue Break Down | H35: 2022 | I35: 2023 | J35: 2024 | K35: 2025 | L35: 2026 | R35: 45879 | S35: 100 | T35: =S34/S35-1 -> -0.0317 | V35: 45879 | W35: 20802.7 | X35: =W34/W35-1 -> 0.016699755
R36: 45872 | S36: 103.73 | T36: =S35/S36-1 -> -0.035958739 | V36: 45872 | W36: 20524.2 | X36: =W35/W36-1 -> 0.013569347
B37: Walmart U.S. Segment | R37: 45865 | S37: 98.49 | T37: =S36/S37-1 -> 0.053203371 | V37: 45865 | W37: 20267.7 | X37: =W36/W37-1 -> 0.012655605
B38: Sales | H38: 393247 | I38: 420553 | J38: 441817 | K38: 462415 | L38: 482975 | R38: 45858 | S38: 97.47 | T38: =S37/S38-1 -> 0.010464758 | V38: 45858 | W38: 20950.4 | X38: =W37/W38-1 -> -0.03258649
B39: Membership | H39: 1924.398 | I39: 2084.7645 | J39: 1985 | K39: 2594 | L39: 2624 | N39: Membership | P39: =AVERAGE(J39:L39)/AVERAGE(J$71:L$71) -> 0.38549639 | R39: 45851 | S39: 95.05 | T39: =S38/S39-1 -> 0.025460284 | V39: 45851 | W39: 20541.6 | X39: =W38/W39-1 -> 0.019901079
B40: Total Revenue | H40: 395171.4 | I40: 422637.76 | J40: 443802 | K40: 465009 | L40: 485599 | R40: 45844 | S40: 94.4 | T40: =S39/S40-1 -> 0.0068855932 | V40: 45844 | W40: 20547.7 | X40: =W39/W40-1 -> -0.00029687021
R41: 45837 | S41: 98.36 | T41: =S40/S41-1 -> -0.040260268 | V41: 45837 | W41: 20725.8 | X41: =W40/W41-1 -> -0.0085931544
B42: Cost of Sales | H42: 281957.5 | I42: 304777.66 | J42: 323563 | K42: 336451 | L42: 350360 | N42: Cost of Sales | P42: =AVERAGE(J42:L42)/AVERAGE(J$74:L$74) -> 0.65724359 | R42: 45830 | S42: 97.27 | T42: =S41/S42-1 -> 0.011205922 | V42: 45830 | W42: 20338.4 | X42: =W41/W42-1 -> 0.019047713
B43: Operating, selling, general and administrative expenses | H43: 88005.534 | I43: 94973.548 | J43: 98085 | K43: 104676 | L43: 110081 | N43: OSGA | P43: =AVERAGE(J43:L43)/AVERAGE(J$75:L$75) -> 0.74699975 | R43: 45823 | S43: 96.12 | T43: =S42/S43-1 -> 0.011964211 | V43: 45823 | W43: 19868.4 | X43: =W42/W43-1 -> 0.023655654
B44: Operating Income | H44: 25208.363 | I44: 22886.561 | J44: 22154 | K44: 23882 | L44: 25158 | R44: 45816 | S44: 94.44 | T44: =S43/S44-1 -> 0.017789072 | V44: 45816 | W44: 19981.1 | X44: =W43/W44-1 -> -0.0056403301
R45: 45809 | S45: 97.47 | T45: =S44/S45-1 -> -0.031086488 | V45: 45809 | W45: 20045.4 | X45: =W44/W45-1 -> -0.0032077185
B46: Walmart International | R46: 45802 | S46: 98.72 | T46: =S45/S46-1 -> -0.012662075 | V46: 45802 | W46: 19783.8 | X46: =W45/W46-1 -> 0.01322294
B47: Sales | H47: 100959 | I47: 100983 | J47: 114641 | K47: 121885 | L47: 130423 | R47: 45795 | S47: 96.34 | T47: =S46/S47-1 -> 0.024704173 | V47: 45795 | W47: 19534.8 | X47: =W46/W47-1 -> 0.012746483
B48: Membership | H48: 1189.1566 | I48: 1288.253 | J48: 1408 | K48: 1478 | L48: 1565 | N48: Membership | P48: =AVERAGE(J48:L48)/AVERAGE(J$71:L$71) -> 0.23821247 | R48: 45788 | S48: 98.24 | T48: =S47/S48-1 -> -0.019340391 | V48: 45788 | W48: 19934.1 | X48: =W47/W48-1 -> -0.020031002
B49: Total Revenue | H49: 102148.16 | I49: 102271.25 | J49: 116049 | K49: 123363 | L49: 131988 | R49: 45781 | S49: 96.72 | T49: =S48/S49-1 -> 0.015715467 | V49: 45781 | W49: 19319.2 | X49: =W48/W49-1 -> 0.03182844
R50: 45774 | S50: 98.75 | T50: =S49/S50-1 -> -0.020556962 | V50: 45774 | W50: 19386.7 | X50: =W49/W50-1 -> -0.0034817684
B51: Cost of Sales | H51: 80279.027 | I51: 86776.389 | J51: 89831 | K51: 95267 | L51: 102576 | N51: Cost of Sales | P51: =AVERAGE(J51:L51)/AVERAGE(J$74:L$74) -> 0.1871306 | R51: 45767 | S51: 95.09 | T51: =S50/S51-1 -> 0.038489852 | V51: 45767 | W51: 18899.8 | X51: =W50/W51-1 -> 0.025762177
B52: Operating, selling, general and administrative expenses | H52: 19188.988 | I52: 20708.315 | J52: 21309 | K52: 22595 | L52: 24309 | N52: OSGA | P52: =AVERAGE(J52:L52)/AVERAGE(J$75:L$75) -> 0.16287805 | R52: 45760 | S52: 93.22 | T52: =S51/S52-1 -> 0.020060073 | V52: 45760 | W52: 18367.1 | X52: =W51/W52-1 -> 0.029002945
B53: Operating Income | H53: 2680.1409 | I53: -5213.4507 | J53: 4909 | K53: 5501 | L53: 5103 | R53: 45753 | S53: 92.8 | T53: =S52/S53-1 -> 0.0045258621 | V53: 45753 | W53: 18219.7 | X53: =W52/W53-1 -> 0.0080901442
R54: 45746 | S54: 83.19 | T54: =S53/S54-1 -> 0.11551869 | V54: 45746 | W54: 17618.6 | X54: =W53/W54-1 -> 0.034117353
B55: Sam's Club U.S. Segment | R55: 45739 | S55: 85.15 | T55: =S54/S55-1 -> -0.023018203 | V55: 45739 | W55: 19270.3 | X55: =W54/W55-1 -> -0.08571221
B56: Sales | H56: 73556 | I56: 84345 | J56: 86179 | K56: 90238 | L56: 93015 | R56: 45732 | S56: 85.98 | T56: =S55/S56-1 -> -0.0096534078 | V56: 45732 | W56: 19454.3 | X56: =W55/W56-1 -> -0.0094580633
B57: Membership | H57: 1843.1794 | I57: 1996.7777 | J57: 2051 | K57: 2323 | L57: 2525 | N57: Membership | P57: =AVERAGE(J57:L57)/AVERAGE(J$71:L$71) -> 0.36922665 | R57: 45725 | S57: 85.35 | T57: =S56/S57-1 -> 0.0073813708 | V57: 45725 | W57: 19231.3 | X57: =W56/W57-1 -> 0.01159568
B58: Total Revenue | H58: 75399.179 | I58: 86341.778 | J58: 88230 | K58: 92561 | L58: 95540 | R58: 45718 | S58: 91.72 | T58: =S57/S58-1 -> -0.069450502 | V58: 45718 | W58: 19573.1 | X58: =W57/W58-1 -> -0.017462742
R59: 45711 | S59: 98.61 | T59: =S58/S59-1 -> -0.06987121 | V59: 45711 | W59: 20028.2 | X59: =W58/W59-1 -> -0.022722961
B60: Cost of Sales | H60: 66763.472 | I60: 72166.956 | J60: 76748 | K60: 80035 | L60: 82459 | N60: Cost of Sales | P60: =AVERAGE(J60:L60)/AVERAGE(J$74:L$74) -> 0.15562581 | R60: 45704 | S60: 94.78 | T60: =S59/S60-1 -> 0.040409369 | V60: 45704 | W60: 19881.5 | X60: =W59/W60-1 -> 0.0073787189
B61: Operating, selling, general and administrative expenses | H61: 8453.6421 | I61: 9122.9761 | J61: 9290 | K61: 10122 | L61: 10639 | N61: OSGA | P61: =AVERAGE(J61:L61)/AVERAGE(J$75:L$75) -> 0.071755357 | R61: 45697 | S61: 104.04 | T61: =S60/S61-1 -> -0.089004229 | V61: 45697 | W61: 20130.5 | X61: =W60/W61-1 -> -0.01236929
B62: Operating Income | H62: 182.06525 | I62: 5051.8458 | J62: 2192 | K62: 2404 | L62: 2442 | R62: 45690 | S62: 101.15 | T62: =S61/S62-1 -> 0.028571429 | V62: 45690 | W62: 20039.5 | X62: =W61/W62-1 -> 0.0045410315
R63: 45683 | S63: 98.16 | T63: =S62/S63-1 -> 0.030460473 | V63: 45683 | W63: 19998.8 | X63: =W62/W63-1 -> 0.0020351221
B64: Corporate and support | R64: 45676 | S64: 94.76 | T64: =S63/S64-1 -> 0.035880118 | V64: 45676 | W64: 19997.5 | X64: =W63/W64-1 -> 6.5008126e-05
B65: Membership and Other Income | H65: 0 | I65: 0 | J65: 44 | K65: 52 | L65: 36 | R65: 45669 | S65: 91.94 | T65: =S64/S65-1 -> 0.030672178 | V65: 45669 | W65: 19607.4 | X65: =W64/W65-1 -> 0.01989555
B66: Operating, selling, general and administrative expenses | H66: -1662 | I66: -5121 | J66: 2287 | K66: 2491 | L66: 2914 | R66: 45662 | S66: 93 | T66: =S65/S66-1 -> -0.011397849 | V66: 45662 | W66: 18963 | X66: =W65/W66-1 -> 0.033981965
B67: Operating Income | H67: 1662 | I67: 5121 | J67: -2243 | K67: -2439 | L67: -2878 | R67: 45655 | S67: 90.78 | T67: =S66/S67-1 -> 0.024454726 | V67: 45655 | W67: 19254.3 | X67: =W66/W67-1 -> -0.015129088
R68: 45648 | S68: 91.66 | T68: =S67/S68-1 -> -0.0096006982 | V68: 45648 | W68: 19238.5 | X68: =W67/W68-1 -> 0.00082126985
B69: Consolidated | R69: 45641 | S69: 92.24 | T69: =S68/S69-1 -> -0.0062879445 | V69: 45641 | W69: 19119.4 | X69: =W68/W69-1 -> 0.006229275
B70: Sales | H70: 567762 | I70: 605881 | J70: 642637 | K70: 674538 | L70: 706413 | R70: 45634 | S70: 94.25 | T70: =S69/S70-1 -> -0.02132626 | V70: 45634 | W70: 19729.4 | X70: =W69/W70-1 -> -0.030918325
B71: Membership | H71: 4992 | I71: 5408 | J71: 5488 | K71: 6447 | L71: 6750 | R71: 45627 | S71: 95.7 | T71: =S70/S71-1 -> -0.015151515 | V71: 45627 | W71: 20107.8 | X71: =W70/W71-1 -> -0.018818568
B72: Total Revenue | H72: 572754 | I72: 611289 | J72: 648125 | K72: 680985 | L72: 713163 | R72: 45620 | S72: 92.5 | T72: =S71/S72-1 -> 0.034594595 | V72: 45620 | W72: 20272 | X72: =W71/W72-1 -> -0.0080998421
R73: 45613 | S73: 90.44 | T73: =S72/S73-1 -> 0.022777532 | V73: 45613 | W73: 20123.5 | X73: =W72/W73-1 -> 0.007379432
B74: Cost of Sales | H74: 429000 | I74: 463721 | J74: 490142 | K74: 511753 | L74: 535395 | R74: 45606 | S74: 84.25 | T74: =S73/S74-1 -> 0.07347181 | V74: 45606 | W74: 19645.8 | X74: =W73/W74-1 -> 0.02431563
B75: Operating, selling, general and administrative expenses | H75: 117812 | I75: 127140 | J75: 130971 | K75: 139884 | L75: 147943 | R75: 45599 | S75: 84.83 | T75: =S74/S75-1 -> -0.0068372038 | V75: 45599 | W75: 19937.1 | X75: =W74/W75-1 -> -0.014610951
B76: Operating Income | H76: 25942 | I76: 20428 | J76: 27012 | K76: 29348 | L76: 29825 | R76: 45592 | S76: 82.19 | T76: =S75/S76-1 -> 0.032120696 | V76: 45592 | W76: 19253.5 | X76: =W75/W76-1 -> 0.035505233
R77: 45585 | S77: 82.51 | T77: =S76/S77-1 -> -0.0038783178 | V77: 45585 | W77: 19456.3 | X77: =W76/W77-1 -> -0.010423359
R78: 45578 | S78: 81.31 | T78: =S77/S78-1 -> 0.014758332 | V78: 45578 | W78: 19884.8 | X78: =W77/W78-1 -> -0.021549123
B79: Personal consumption expenditures | G79: Reference | I79: Table 1.1.5. Gross Domestic Product | R79: 45571 | S79: 80.1 | T79: =S78/S79-1 -> 0.015106117 | V79: 45571 | W79: 19711.2 | X79: =W78/W79-1 -> 0.0088071756
B80: [Billions of dollars] Seasonally adjusted at annual rates | G80: Bureau of Economic analysis | J80: U.S Department of Commerce | R80: 45564 | S80: 80.94 | T80: =S79/S80-1 -> -0.010378058 | V80: 45564 | W80: 19538.7 | X80: =W79/W80-1 -> 0.0088286324
B81: 2023 | F81: 2024 | J81: 2025 | R81: 45557 | S81: 79.78 | T81: =S80/S81-1 -> 0.014539985 | V81: 45557 | W81: 19501.2 | X81: =W80/W81-1 -> 0.0019229586
B82: Q1 | C82: Q2 | D82: Q3 | E82: Q4 | F82: Q1 | G82: Q2 | H82: Q3 | I82: Q4 | J82: Q1 | K82: Q2 | L82: Q3 | M82: Q4 | R82: 45550 | S82: 79.06 | T82: =S81/S82-1 -> 0.0091070073 | V82: 45550 | W82: 19373.7 | X82: =W81/W82-1 -> 0.0065810867
B83: 18487 | C83: 18693.1 | D83: 18961.8 | E83: 19190.6 | F83: 19443.8 | G83: 19756.1 | H83: 20032.8 | I83: 20351.3 | J83: 20555 | K83: 20789.9 | L83: 21111.2 | M83: 21368.1 | R83: 45543 | S83: 80.6 | T83: =S82/S83-1 -> -0.0191067 | V83: 45543 | W83: 19121.5 | X83: =W82/W83-1 -> 0.013189342
R84: 45536 | S84: 76.64 | T84: =S83/S84-1 -> 0.051670146 | V84: 45536 | W84: 18663.1 | X84: =W83/W84-1 -> 0.024561836
B85: Forecast | R85: 45529 | S85: 77.23 | T85: =S84/S85-1 -> -0.0076395183 | V85: 45529 | W85: 19292.2 | X85: =W84/W85-1 -> -0.032609034
B86: 23 | C86: 24 | D86: 25 | E86: 26 | F86: 27 | G86: 28 | H86: 29 | I86: 30 | R86: 45522 | S86: 75.7 | T86: =S85/S86-1 -> 0.020211361 | V86: 45522 | W86: 19093.5 | X86: =W85/W86-1 -> 0.010406683
B87: =AVERAGE(B83:E83) -> 18833.125 | C87: =AVERAGE(F83:I83) -> 19896 | D87: =AVERAGE(J83:M83) -> 20956.05 | E87: =_xlfn.FORECAST.LINEAR(E86,$B$87:$D$87,$B$86:$D$86) -> 22017.983 | F87: =_xlfn.FORECAST.LINEAR(F86,$B$87:$D$87,$B$86:$D$86) -> 23079.446 | G87: =_xlfn.FORECAST.LINEAR(G86,$B$87:$D$87,$B$86:$D$86) -> 24140.908 | H87: =_xlfn.FORECAST.LINEAR(H86,$B$87:$D$87,$B$86:$D$86) -> 25202.371 | I87: =_xlfn.FORECAST.LINEAR(I86,$B$87:$D$87,$B$86:$D$86) -> 26263.833 | R87: 45515 | S87: 73.45 | T87: =S86/S87-1 -> 0.030633084 | V87: 45515 | W87: 18753.8 | X87: =W86/W87-1 -> 0.018113662
R88: 45508 | S88: 67.95 | T88: =S87/S88-1 -> 0.080941869 | V88: 45508 | W88: 18267.2 | X88: =W87/W88-1 -> 0.026637908
B89: United States Inflation Rate | G89: https://tradingeconomics.com/united-states/inflation-cpi | R89: 45501 | S89: 68.46 | T89: =S88/S89-1 -> -0.0074496056 | V89: 45501 | W89: 18162.3 | X89: =W88/W89-1 -> 0.0057757002
B90: Forecast | R90: 45494 | S90: 69.78 | T90: =S89/S90-1 -> -0.018916595 | V90: 45494 | W90: 18564.5 | X90: =W89/W90-1 -> -0.021665006
B91: 22 | C91: 23 | D91: 24 | E91: 25 | F91: 26 | G91: 27 | H91: 28 | I91: 29 | J91: 30 | R91: 45487 | S91: 70.75 | T91: =S90/S91-1 -> -0.013710247 | V91: 45487 | W91: 18406.1 | X91: =W90/W91-1 -> 0.0086058426
B92: 8 | C92: 4.1 | D92: 3 | E92: 2.7 | F92: 2.4 | G92: 2.2 | H92: 2.2 | I92: 2.2 | J92: 2.2 | R92: 45480 | S92: 69.24 | T92: =S91/S92-1 -> 0.021808203 | V92: 45480 | W92: 18505.9 | X92: =W91/W92-1 -> -0.0053928747
R93: 45473 | S93: 70.04 | T93: =S92/S93-1 -> -0.011422045 | V93: 45473 | W93: 18098.9 | X93: =W92/W93-1 -> 0.022487554
E94: 23 | F94: 24 | G94: 25 | H94: 26 | R94: 45466 | S94: 67.71 | T94: =S93/S94-1 -> 0.034411461 | V94: 45466 | W94: 18026.5 | X94: =W93/W94-1 -> 0.0040163093
B95: Accounts Receivables | E95: 7933 | F95: 8796 | G95: 9975 | H95: 11172 | R95: 45459 | S95: 67.91 | T95: =S94/S95-1 -> -0.0029450744 | V95: 45459 | W95: 17995.7 | X95: =W94/W95-1 -> 0.00171152
B96: Inventories | E96: 56576 | F96: 54892 | G96: 56435 | H96: 58851 | R96: 45452 | S96: 67.02 | T96: =S95/S96-1 -> 0.013279618 | V96: 45452 | W96: 17817.3 | X96: =W95/W96-1 -> 0.01001274
B97: Account Payable | E97: 53742 | F97: 56812 | G97: 58666 | H97: 63061 | R97: 45445 | S97: 65.88 | T97: =S96/S97-1 -> 0.017304189 | V97: 45445 | W97: 17985.6 | X97: =W96/W97-1 -> -0.009357486
R98: 45438 | S98: 65.76 | T98: =S97/S98-1 -> 0.0018248175 | V98: 45438 | W98: 18083.7 | X98: =W97/W98-1 -> -0.0054247748
R99: 45431 | S99: 65.38 | T99: =S98/S99-1 -> 0.005812175 | V99: 45431 | W99: 18110.6 | X99: =W98/W99-1 -> -0.001485318
R100: 45424 | S100: 64.65 | T100: =S99/S100-1 -> 0.01129157 | V100: 45424 | W100: 18388.3 | X100: =W99/W100-1 -> -0.015101994
R101: 45417 | S101: 60.48 | T101: =S100/S101-1 -> 0.068948413 | V101: 45417 | W101: 18162.1 | X101: =W100/W101-1 -> 0.012454507
...
